Workbook

Sheet BOM new
A1: No. | C1: 母件料号 Parent Item Code | D1: 母件料名 Parent Item Name | E1: 子件项次 Child Item Code | F1: 子项 Child Item Name | G1: 工序号( công đoạn sẽ trừ NVL) | H1: 用量 Dosage | I1: 母件底数 Parent Item Quantity | J1: 用量单位 UOM | K1: 损耗类型 | L1: 固定损耗 | M1: 变动损耗 | N1: BOM子项_从数量 | O1: BOM子项_到数量
C2: Parent code | D2: parent name | E2: Child | F2: Chind name | G2: Công đoan | H2: tiêu hao
A3: 1 (Hosiden) | C3: 120394 | D3: PK Hosiden HEG Cover HGU0810-27PW(3) | E3: 301612 | F3: CNC Hosiden HEG Stand Cover HGU0810-27PW(3) | G3: Polishing | H3: 1 | I3: 1 | J3: PCS | P3: =VLOOKUP(C3,COSTING!C270:D319,2,0) -> #N/A
C4: 120394 | D4: PK Hosiden HEG Cover HGU0810-27PW(3) | E4: 800832 | F4: PE bag 177*58*27 | G4: Packing | H4: 1 | I4: 1 | J4: EA | P4: =VLOOKUP(C4,COSTING!C271:D536,2,0) -> #N/A
C5: 301612 | D5: CNC Hosiden HEG Stand Cover HGU0810-27PW(3) | E5: 210351 | F5: CA Hosiden HGU0810-270120 Stand Cover | G5: CNC 1 | H5: 1 | I5: 1 | J5: PCS | P5: =VLOOKUP(C5,COSTING!C272:D536,2,0) -> #N/A
C6: 210351 | D6: CA Hosiden HGU0810-270120 Stand Cover | E6: 760010 | F6: Hợp kim maggie 2190W AZ91D để chế tạo khung xương điện thoại di động, kt 60x10x5cm | G6: Casting | H6: 0.13853 | I6: 1 | J6: KG | P6: =VLOOKUP(C6,COSTING!C273:D536,2,0) -> #N/A
A7: 2 (Hyoseong) | C7: 120424 | D7: PK HYOSEONG MQ4 T33 Coupling Base Cover H0345034C00 | E7: 301646 | F7: CNC HYOSEONG MQ4 T33 Coupling Base Cover H0345034C00 | G7: Cleaning | H7: 1 | I7: 1 | J7: PCS | P7: =VLOOKUP(C7,COSTING!C274:D536,2,0) -> #N/A
C8: 120424 | D8: PK HYOSEONG MQ4 T33 Coupling Base Cover H0345034C00 | E8: 762259 | F8: Carton tray IN/YLR 44 3 plates 2 surface yellow/Khay carton ba lớp hai mặt vàng IN/YLR44 525*350*85 | G8: Packing | H8: 0.02381 | I8: 1 | J8: EA | P8: =VLOOKUP(C8,COSTING!C275:D536,2,0) -> #N/A
C9: 120424 | D9: PK HYOSEONG MQ4 T33 Coupling Base Cover H0345034C00 | E9: 800837 | F9: Devide pad BR80-5R/Vách dài MQ4 (5 khía) 501x75mm | G9: Packing | H9: 0.08658 | I9: 1 | J9: EA | P9: =VLOOKUP(C9,COSTING!C276:D536,2,0) -> #N/A
C10: 120424 | D10: PK HYOSEONG MQ4 T33 Coupling Base Cover H0345034C00 | E10: 800838 | F10: Devide pad BR81-6R/Vách ngắn MQ4 (6 khía) 340x75mm | G10: Packing | H10: 0.103896 | I10: 1 | J10: EA | P10: =VLOOKUP(C10,COSTING!C277:D536,2,0) -> #N/A
C11: 301646 | D11: CNC HYOSEONG MQ4 T33 Coupling Base Cover H0345034C00 | E11: 210381 | F11: CA HYOSEONG MQ4 T33 Coupling Base Cover H0345034C00 | G11: CNC 1 | H11: 1 | I11: 1 | J11: PCS | P11: =VLOOKUP(C11,COSTING!C277:D536,2,0) -> #N/A
C12: 210381 | D12: CA HYOSEONG MQ4 T33 Coupling Base Cover H0345034C00 | E12: 762802 | F12: Aluminium ALDCS 12 Fe 0.9%-Nhôm thỏi ALDC12 thành phần Fe 0.9% | G12: Casting | H12: 0.27061 | I12: 1 | J12: KG | P12: =VLOOKUP(C12,COSTING!C278:D536,2,0) -> #N/A
A13: 3 (Hyoseong) | C13: 120423 | D13: PK HYOSEONG GEN5 STATOR BLOCK SOLO H1000004C01 | E13: 301645 | F13: CNC HYOSEONG GEN5 STATOR BLOCK SOLO H1000004C01 | G13: Cleaning | H13: 1 | I13: 1 | J13: PCS | P13: =VLOOKUP(C13,COSTING!C279:D536,2,0) -> PK HYOSEONG GEN5 STATOR BLOCK SOLO H1000004C01
C14: 120423 | D14: PK HYOSEONG GEN5 STATOR BLOCK SOLO H1000004C01 | E14: 762599 | F14: Carton box 3 plates YLR63/Thùng carton 3 lớp 1V5 Cover 528*352*104mm | G14: Packing | H14: 0.03571 | I14: 1 | J14: EA | P14: =VLOOKUP(C14,COSTING!C280:D536,2,0) -> PK HYOSEONG GEN5 STATOR BLOCK SOLO H1000004C01
C15: 120423 | D15: PK HYOSEONG GEN5 STATOR BLOCK SOLO H1000004C01 | E15: 800839 | F15: Devide pad BR82-3R/vách dài gen 5 (3 khía) sz 504x101mm | G15: Packing | H15: 0.21428 | I15: 1 | J15: EA | P15: =VLOOKUP(C15,COSTING!C515:D536,2,0) -> #N/A
C16: 120423 | D16: PK HYOSEONG GEN5 STATOR BLOCK SOLO H1000004C01 | E16: 800840 | F16: Devide pad BR83-6R/Vách ngắn gen 5 (6 khía) kt 342x101mm | G16: Packing | H16: 0.10714 | I16: 1 | J16: EA | P16: =VLOOKUP(C16,COSTING!C280:D536,2,0) -> PK HYOSEONG GEN5 STATOR BLOCK SOLO H1000004C01
C17: 301645 | D17: CNC HYOSEONG GEN5 STATOR BLOCK SOLO H1000004C01 | E17: 210380 | F17: CA HYOSEONG GEN5 STATOR BLOCK SOLO H1000004C01 | G17: CNC 1 | H17: 1 | I17: 1 | J17: PCS | P17: =VLOOKUP(C17,COSTING!C280:D536,2,0) -> #N/A
C18: 210380 | D18: CA HYOSEONG GEN5 STATOR BLOCK SOLO H1000004C01 | E18: 762802 | F18: Aluminium ALDCS 12 Fe 0.9%-Nhôm thỏi ALDC12 thành phần Fe 0.9% | G18: Casting | H18: 0.22936 | I18: 1 | J18: KG | P18: =VLOOKUP(C18,COSTING!C280:D536,2,0) -> #N/A
A19: 4 LG | C19: 120168 | D19: PK OMS ENTRY LENS HOLDER 3CAC00203A | E19: 301189 | F19: CNC OMS ENTRY LENS 3CAC00203A | G19: N-Chromate | H19: 1 | I19: 1 | J19: PCS | P19: =VLOOKUP(C19,COSTING!C280:D536,2,0) -> PK OMS ENTRY LENS HOLDER 3CAC00203A
C20: 120168 | D20: PK OMS ENTRY LENS HOLDER 3CAC00203A | E20: 760018 | F20: Carton box. 5 Plate: 1 surface Yellow, 1 surface raw. Thùng carton 5 lớp,mặt ngoài vàng, mặt trong thô MC-YLR01 | G20: Packing | H20: 0.00025 | I20: 1 | J20: EA | P20: =VLOOKUP(C20,COSTING!C280:D536,2,0) -> PK OMS ENTRY LENS HOLDER 3CAC00203A
C21: 301189 | D21: CNC OMS ENTRY LENS 3CAC00203A | E21: 210159 | F21: CA OMS ENTRY LENS 3CAC00203A | G21: CNC 1 | H21: 1 | I21: 1 | J21: PCS | P21: =VLOOKUP(C21,COSTING!C280:D536,2,0) -> #N/A
C22: 210159 | D22: CA OMS ENTRY LENS 3CAC00203A | E22: 762802 | F22: Aluminium ALDCS 12 Fe 0.9%-Nhôm thỏi ALDC12 thành phần Fe 0.9% | G22: Casting | H22: 0.04335 | I22: 1 | J22: KG | P22: =VLOOKUP(C22,COSTING!C280:D536,2,0) -> #N/A
A23: 5 LG | C23: 120178 | D23: PK 570W 3MAM00541A | E23: 301314 | F23: CNC 570W 3MAM00541A | G23: Cleaning | H23: 1 | I23: 1 | J23: PCS | P23: =VLOOKUP(C23,COSTING!C282:D536,2,0) -> PK 570W 3MAM00541A
C24: 120178 | D24: PK 570W 3MAM00541A | E24: 762207 | F24: Bearing 608A21T1XZZ1#MC-02 K NS7ST-3BBB00019A | G24: Caulking | H24: 1 | I24: 1 | J24: EA | P24: =VLOOKUP(C24,COSTING!C283:D536,2,0) -> PK 570W 3MAM00541A
C25: 120178 | D25: PK 570W 3MAM00541A | E25: 762262 | F25: Carton tray IN/YLR 45 3 plates 2 surface yellow/Khay carton 3 lớp 2 mặt vàng IN/YLR45 525*350*122 | G25: Packing | H25: 0.025 | I25: 1 | J25: EA | P25: =VLOOKUP(C25,COSTING!C284:D536,2,0) -> PK 570W 3MAM00541A
C26: 120178 | D26: PK 570W 3MAM00541A | E26: 762263 | F26: Devide pad 3 plates 2 surface yellow (9R) BR36-9R/Vách carton 3 lớp 2 mặt vàng BR36-9R 338*119 | G26: Packing | H26: 0.075 | I26: 1 | J26: EA | P26: =VLOOKUP(C26,COSTING!C285:D536,2,0) -> PK 570W 3MAM00541A
C27: 120178 | D27: PK 570W 3MAM00541A | E27: 762264 | F27: Devide pad 3 plates 2 surface yellow (3R) BR37-3R/Vách carton 3 lớp 2 mặt vàng BR37-3R 501*119 | G27: Packing | H27: 0.225 | I27: 1 | J27: EA | P27: =VLOOKUP(C27,COSTING!C286:D536,2,0) -> PK 570W 3MAM00541A
C28: 301314 | D28: CNC 570W 3MAM00541A | E28: 210166 | F28: CA LGIT 570W 3MAM00541A | G28: CNC 1 | H28: 1 | I28: 1 | J28: PCS | P28: =VLOOKUP(C28,COSTING!C287:D536,2,0) -> #N/A
C29: 210166 | D29: CA LGIT 570W 3MAM00541A | E29: 762802 | F29: Aluminium ALDCS 12 Fe 0.9%-Nhôm thỏi ALDC12 thành phần Fe 0.9% | G29: Casting | H29: 0.439 | I29: 1 | J29: KG | P29: =VLOOKUP(C29,COSTING!C288:D536,2,0) -> #N/A
A30: 6 LG | C30: 120165 | D30: PK PSA BMS Bottom Cover 3CAC00182A | E30: 301186 | F30: CNC PSA BMS Bottom Cover 3CAC00182A | G30: N-Chromate | H30: 1 | I30: 1 | J30: PCS | P30: =VLOOKUP(C30,COSTING!C289:D536,2,0) -> PK PSA BMS Bottom Cover 3CAC00182A
C31: 120165 | D31: PK PSA BMS Bottom Cover 3CAC00182A | E31: 762265 | F31: Carton tray IN/YLR 46 3 plates 2 surface yellow/Khay carton 3 lớp 2 mặt vàng IN/YLR46 525*350*109 | G31: Packing | H31: 0.04 | I31: 1 | J31: EA | P31: =VLOOKUP(C31,COSTING!C290:D536,2,0) -> PK PSA BMS Bottom Cover 3CAC00182A
C32: 120165 | D32: PK PSA BMS Bottom Cover 3CAC00182A | E32: 762266 | F32: Devide pad 3 plates 2 surface yellow (2R) BR38-2R/Vách carton 3 lớp 2 mặt vàng BR38-2R 338*106 | G32: Packing | H32: 0.96 | I32: 1 | J32: EA | P32: =VLOOKUP(C32,COSTING!C291:D536,2,0) -> PK PSA BMS Bottom Cover 3CAC00182A
C33: 120165 | D33: PK PSA BMS Bottom Cover 3CAC00182A | E33: 762267 | F33: Devide pad 3 plates 2 surface yellow (24R) BR39-24R/Vách carton 3 lớp 2 mặt vàng BR39-24R 501*106 | G33: Packing | H33: 0.08 | I33: 1 | J33: EA | P33: =VLOOKUP(C33,COSTING!C292:D536,2,0) -> PK PSA BMS Bottom Cover 3CAC00182A
C34: 301186 | D34: CNC PSA BMS Bottom Cover 3CAC00182A | E34: 210156 | F34: CA PSA BMS Bottom Cover 3CAC00182A | G34: CNC 1 | H34: 1 | I34: 1 | J34: PCS | P34: =VLOOKUP(C34,COSTING!C293:D536,2,0) -> #N/A
C35: 210156 | D35: CA PSA BMS Bottom Cover 3CAC00182A | E35: 762802 | F35: Aluminium ALDCS 12 Fe 0.9%-Nhôm thỏi ALDC12 thành phần Fe 0.9% | G35: Casting | H35: 0.79582 | I35: 1 | J35: KG | P35: =VLOOKUP(C35,COSTING!C294:D536,2,0) -> #N/A
A36: 7 LG | C36: 120166 | D36: PK PSA BMS Top Cover 3CAC00181A | E36: 301187 | F36: CNC PSA BMS Top Cover 3CAC00181A | G36: N-Chromate | H36: 1 | I36: 1 | J36: PCS | P36: =VLOOKUP(C36,COSTING!C294:D536,2,0) -> PK PSA BMS Top Cover 3CAC00181A
C37: 120166 | D37: PK PSA BMS Top Cover 3CAC00181A | E37: 762266 | F37: Devide pad 3 plates 2 surface yellow (2R) BR38-2R/Vách carton 3 lớp 2 mặt vàng BR38-2R 338*106 | G37: Packing | H37: 0.9 | I37: 1 | J37: EA | P37: =VLOOKUP(C37,COSTING!C295:D536,2,0) -> PK PSA BMS Top Cover 3CAC00181A
C38: 120166 | D38: PK PSA BMS Top Cover 3CAC00181A | E38: 762268 | F38: Devide pad 3 plates 2 surface yellow (9R) BR40-9R/Vách carton 3 lớp 2 mặt vàng BR40-9R 501*106 | G38: Packing | H38: 0.2 | I38: 1 | J38: EA | P38: =VLOOKUP(C38,COSTING!C296:D536,2,0) -> PK PSA BMS Top Cover 3CAC00181A
C39: 120166 | D39: PK PSA BMS Top Cover 3CAC00181A | E39: 762265 | F39: Carton tray IN/YLR 46 3 plates 2 surface yellow/Khay carton 3 lớp 2 mặt vàng IN/YLR46 525*350*109 | G39: Packing | H39: 0.1 | I39: 1 | J39: EA | P39: =VLOOKUP(C39,COSTING!C297:D536,2,0) -> PK PSA BMS Top Cover 3CAC00181A
C40: 301187 | D40: CNC PSA BMS Top Cover 3CAC00181A | E40: 210157 | F40: CA PSA BMS Top Cover 3CAC00181A | G40: CNC 1 | H40: 1 | I40: 1 | J40: PCS | P40: =VLOOKUP(C40,COSTING!C298:D536,2,0) -> #N/A
C41: 210157 | D41: CA PSA BMS Top Cover 3CAC00181A | E41: 762802 | F41: Aluminium ALDCS 12 Fe 0.9%-Nhôm thỏi ALDC12 thành phần Fe 0.9% | G41: Casting | H41: 1.027 | I41: 1 | J41: KG | P41: =VLOOKUP(C41,COSTING!C299:D536,2,0) -> #N/A
A42: 8 LG | C42: 120421 | D42: PK LGIT BYD HX Housing 3HU000001A | E42: 301629 | F42: CNC LGIT BYD HX Housing 3HU000001A | G42: Cleaning | H42: 1 | I42: 1 | J42: PCS | P42: =VLOOKUP(C42,COSTING!C300:D536,2,0) -> #N/A
C43: 120421 | D43: PK LGIT BYD HX Housing 3HU000001A | E43: 762584 | F43: Carton tray 3 plates printing YLR 61/Khay carton YLR61 có in R12L Cover :525x350x94 | G43: Packing | H43: 0.1111 | I43: 1 | J43: EA | P43: =VLOOKUP(C43,COSTING!C301:D536,2,0) -> #N/A
C44: 120421 | D44: PK LGIT BYD HX Housing 3HU000001A | E44: 800818 | F44: Devide pad BR76-2R/Vách thùng DL3A Housing (2 khía), kt: 338*88mm | G44: Packing | H44: 0.44444 | I44: 1 | J44: EA | P44: =VLOOKUP(C44,COSTING!C302:D536,2,0) -> #N/A
C45: 120421 | D45: PK LGIT BYD HX Housing 3HU000001A | E45: 800819 | F45: Devide pad BR77-4R/Vách thùng DL3A Housing (4 khía), kt: 501*88mm | G45: Packing | H45: 0.222222 | I45: 1 | J45: EA | P45: =VLOOKUP(C45,COSTING!C303:D536,2,0) -> #N/A
C46: 301629 | D46: CNC LGIT BYD HX Housing 3HU000001A | E46: 210377 | F46: CA LGIT BYD HX Housing 3HU000001A | G46: CNC 1 | H46: 1 | I46: 1 | J46: PCS | P46: =VLOOKUP(C46,COSTING!C304:D536,2,0) -> #N/A
C47: 210377 | D47: CA LGIT BYD HX Housing 3HU000001A | E47: 762802 | F47: Aluminium ALDCS 12 Fe 0.9%-Nhôm thỏi ALDC12 thành phần Fe 0.9% | G47: Casting | H47: 1.08159 | I47: 1 | J47: KG | P47: =VLOOKUP(C47,COSTING!C305:D536,2,0) -> #N/A
A48: 9 LG | C48: 120416 | D48: PK LGIT 3CAZ00042A CL4 Cover | E48: 301570 | F48: CNC LGIT 3CAZ00042A CL4 Cover | G48: Cleaning | H48: 1 | I48: 1 | J48: PCS | P48: =VLOOKUP(C48,COSTING!C306:D536,2,0) -> PK LGIT 3CAZ00042A CL4 Cover
C49: 120416 | D49: PK LGIT 3CAZ00042A CL4 Cover | E49: 762599 | F49: Carton box 3 plates YLR63/Thùng carton 3 lớp 1V5 Cover 528*352*104mm | G49: Packing | H49: 0.025 | I49: 1 | J49: EA | P49: =VLOOKUP(C49,COSTING!C307:D536,2,0) -> PK LGIT 3CAZ00042A CL4 Cover
C50: 120416 | D50: PK LGIT 3CAZ00042A CL4 Cover | E50: 762600 | F50: Devide pad BR47-3R/Vách thùng 1V5 cover ( 3 khía) 504*101mm | G50: Packing | H50: 0.225 | I50: 1 | J50: EA | P50: =VLOOKUP(C50,COSTING!C308:D536,2,0) -> PK LGIT 3CAZ00042A CL4 Cover
C51: 120416 | D51: PK LGIT 3CAZ00042A CL4 Cover | E51: 762601 | F51: Devide pad BR48-9R/Vách thùng 1V5 cover ( 9 khía) 342*101mm | G51: Packing | H51: 0.075 | I51: 1 | J51: EA | P51: =VLOOKUP(C51,COSTING!C309:D536,2,0) -> PK LGIT 3CAZ00042A CL4 Cover
C52: 301570 | D52: CNC LGIT 3CAZ00042A CL4 Cover | E52: 210365 | F52: CA LGIT 3CAZ00042A CL4 Cover | G52: CNC 1 | H52: 1 | I52: 1 | J52: PCS | P52: =VLOOKUP(C52,COSTING!C319:D536,2,0) -> #N/A
C53: 210365 | D53: CA LGIT 3CAZ00042A CL4 Cover | E53: 762802 | F53: Aluminium ALDCS 12 Fe 0.9%-Nhôm thỏi ALDC12 thành phần Fe 0.9% | G53: Casting | H53: 0.34623 | I53: 1 | J53: KG | P53: =VLOOKUP(C53,COSTING!C536:D536,2,0) -> #N/A
A54: 10 LG | C54: 120415 | D54: PK LGIT 3CAZ00041A CL4 Housing | E54: 301569 | F54: CNC LGIT 3CAZ00041A CL4 Housing | G54: Cleaning | H54: 1 | I54: 1 | J54: PCS | P54: =VLOOKUP(C54,COSTING!#REF!,2,0) -> #REF!
C55: 120415 | D55: PK LGIT 3CAZ00041A CL4 Housing | E55: 762259 | F55: Carton tray IN/YLR 44 3 plates 2 surface yellow/Khay carton ba lớp hai mặt vàng IN/YLR44 525*350*85 | G55: Packing | H55: 0.111111 | I55: 1 | J55: EA | P55: =VLOOKUP(C55,COSTING!#REF!,2,0) -> #REF!
C56: 120415 | D56: PK LGIT 3CAZ00041A CL4 Housing | E56: 762260 | F56: Devide pad 3 plates 2 surface yellow (2R) BR34-2R/Vách carton 3 lớp 2 mặt vàng BR34-2R 338*82 | G56: Packing | H56: 0.444444 | I56: 1 | J56: EA | P56: =VLOOKUP(C56,COSTING!#REF!,2,0) -> #REF!
C57: 120415 | D57: PK LGIT 3CAZ00041A CL4 Housing | E57: 800878 | F57: Devide pad BR87-4R/Vách carton 3 lớp CN7a Housing (4 khía), kt 501*82mm | G57: Packing | H57: 0.222222 | I57: 1 | J57: EA | P57: =VLOOKUP(C57,COSTING!#REF!,2,0) -> #REF!
C58: 301569 | D58: CNC LGIT 3CAZ00041A CL4 Housing | E58: 210364 | F58: CA LGIT 3CAZ00041A CL4 Housing | G58: CNC 1 | H58: 1 | I58: 1 | J58: PCS | P58: =VLOOKUP(C58,COSTING!#REF!,2,0) -> #REF!
C59: 210364 | D59: CA LGIT 3CAZ00041A CL4 Housing | E59: 762802 | F59: Aluminium ALDCS 12 Fe 0.9%-Nhôm thỏi ALDC12 thành phần Fe 0.9% | G59: Casting | H59: 1.0222 | I59: 1 | J59: KG | P59: =VLOOKUP(C59,COSTING!#REF!,2,0) -> #REF!
A60: 11 LG | C60: 120160 | D60: PK LGIT Gen 2 | E60: 301178 | F60: CNC LGIT Gen 2 | G60: Cleaning | H60: 1 | I60: 1 | J60: PCS | P60: =VLOOKUP(C60,COSTING!#REF!,2,0) -> #REF!
C61: 120160 | D61: PK LGIT Gen 2 | E61: 762208 | F61: Bearing 6000ZZ3CMR K NS7ST-3BBB00035A | G61: Caulking | H61: 1 | I61: 1 | J61: EA | P61: =VLOOKUP(C61,COSTING!#REF!,2,0) -> #REF!
C62: 120160 | D62: PK LGIT Gen 2 | E62: 762236 | F62: Carton tray IN/YLR42 3 plates, 2 yellow surface IN/YLR 42/Khay carton Gen 2 không nắp đục lỗ tay cầm 2 mặt vàng 525*350*140 | G62: Packing | H62: 0.025 | I62: 1 | J62: EA | P62: =VLOOKUP(C62,COSTING!#REF!,2,0) -> #REF!
C63: 120160 | D63: PK LGIT Gen 2 | E63: 762237 | F63: Devide pad BR30(3 plates) 2 yellow surface/Vách ngăn (chia 3) 487*136*3T | G63: Packing | H63: 0.225 | I63: 1 | J63: EA | P63: =VLOOKUP(C63,COSTING!#REF!,2,0) -> #REF!
C64: 120160 | D64: PK LGIT Gen 2 | E64: 762238 | F64: Devide pad BR31(3 plates) 2 yellow surface/Vách ngăn (chia 9) 339*136*3T | G64: Packing | H64: 0.075 | I64: 1 | J64: EA | P64: =VLOOKUP(C64,COSTING!#REF!,2,0) -> #REF!
C65: 301178 | D65: CNC LGIT Gen 2 | E65: 210148 | F65: CA LGIT Gen 2 | G65: CNC 1 | H65: 1 | I65: 1 | J65: PCS | P65: =VLOOKUP(C65,COSTING!#REF!,2,0) -> #REF!
C66: 210148 | D66: CA LGIT Gen 2 | E66: 762802 | F66: Aluminium ALDCS 12 Fe 0.9%-Nhôm thỏi ALDC12 thành phần Fe 0.9% | G66: Casting | H66: 0.3087 | I66: 1 | J66: KG | P66: =VLOOKUP(C66,COSTING!#REF!,2,0) -> #REF!
A67: 12 LG | C67: 120157 | D67: PK LGIT Gen3 AL5 | E67: 301161 | F67: CNC LGIT Gen3 AL5 | G67: Cleaning | H67: 1 | I67: 1 | J67: PCS | P67: =VLOOKUP(C67,COSTING!#REF!,2,0) -> #REF!
C68: 120157 | D68: PK LGIT Gen3 AL5 | E68: 762259 | F68: Carton tray IN/YLR 44 3 plates 2 surface yellow/Khay carton ba lớp hai mặt vàng IN/YLR44 525*350*85 | G68: Packing | H68: 0.083333 | I68: 1 | J68: EA | P68: =VLOOKUP(C68,COSTING!#REF!,2,0) -> #REF!
C69: 120157 | D69: PK LGIT Gen3 AL5 | E69: 762260 | F69: Devide pad 3 plates 2 surface yellow (2R) BR34-2R/Vách carton 3 lớp 2 mặt vàng BR34-2R 338*82 | G69: Packing | H69: 0.25 | I69: 1 | J69: EA | P69: =VLOOKUP(C69,COSTING!#REF!,2,0) -> #REF!
C70: 120157 | D70: PK LGIT Gen3 AL5 | E70: 762261 | F70: Devide pad 3 plates 2 surface yellow (3R) BR35-3R/Vách carton 3 lớp 2 mặt vàng BR35-3R 501*82 | G70: Packing | H70: 0.166667 | I70: 1 | J70: EA | P70: =VLOOKUP(C70,COSTING!#REF!,2,0) -> #REF!
C71: 301161 | D71: CNC LGIT Gen3 AL5 | E71: 210145 | F71: CA LGIT Gen3 AL5 | G71: CNC 1 | H71: 1 | I71: 1 | J71: PCS | P71: =VLOOKUP(C71,COSTING!#REF!,2,0) -> #REF!
C72: 210145 | D72: CA LGIT Gen3 AL5 | E72: 762802 | F72: Aluminium ALDCS 12 Fe 0.9%-Nhôm thỏi ALDC12 thành phần Fe 0.9% | G72: Casting | H72: 0.6665 | I72: 1 | J72: KG | P72: =VLOOKUP(C72,COSTING!#REF!,2,0) -> #REF!
A73: 13 LG | C73: 120158 | D73: PK LGIT Gen3 AL6 | E73: 301162 | F73: CNC LGIT Gen3 AL6 | G73: Cleaning | H73: 1 | I73: 1 | J73: PCS | P73: =VLOOKUP(C73,COSTING!#REF!,2,0) -> #REF!
C74: 120158 | D74: PK LGIT Gen3 AL6 | E74: 762259 | F74: Carton tray IN/YLR 44 3 plates 2 surface yellow/Khay carton ba lớp hai mặt vàng IN/YLR44 525*350*85 | G74: Packing | H74: 0.083 | I74: 1 | J74: EA | P74: =VLOOKUP(C74,COSTING!#REF!,2,0) -> #REF!
C75: 120158 | D75: PK LGIT Gen3 AL6 | E75: 762260 | F75: Devide pad 3 plates 2 surface yellow (2R) BR34-2R/Vách carton 3 lớp 2 mặt vàng BR34-2R 338*82 | G75: Packing | H75: 0.25 | I75: 1 | J75: EA | P75: =VLOOKUP(C75,COSTING!#REF!,2,0) -> #REF!
C76: 120158 | D76: PK LGIT Gen3 AL6 | E76: 762261 | F76: Devide pad 3 plates 2 surface yellow (3R) BR35-3R/Vách carton 3 lớp 2 mặt vàng BR35-3R 501*82 | G76: Packing | H76: 0.1666 | I76: 1 | J76: EA | P76: =VLOOKUP(C76,COSTING!#REF!,2,0) -> #REF!
C77: 301162 | D77: CNC LGIT Gen3 AL6 | E77: 210146 | F77: CA LGIT Gen3 AL6 | G77: CNC 1 | H77: 1 | I77: 1 | J77: PCS | P77: =VLOOKUP(C77,COSTING!#REF!,2,0) -> #REF!
C78: 210146 | D78: CA LGIT Gen3 AL6 | E78: 762802 | F78: Aluminium ALDCS 12 Fe 0.9%-Nhôm thỏi ALDC12 thành phần Fe 0.9% | G78: Casting | H78: 0.6775 | I78: 1 | J78: KG | P78: =VLOOKUP(C78,COSTING!#REF!,2,0) -> #REF!
A79: 14 LG | C79: 120341 | D79: PK LGIT T6M6 Housing 3HUC00006A | E79: 301450 | F79: CNC LGIT T6M6 Housing 3HUC00006A | G79: Cleaning | H79: 1 | I79: 1 | J79: PCS | P79: =VLOOKUP(C79,COSTING!#REF!,2,0) -> #REF!
C80: 120341 | D80: PK LGIT T6M6 Housing 3HUC00006A | E80: 762660 | F80: Carton box 3 plates printing YLR68/Thùng nắp gập 3 lớp có in kích thước : 520*350*135 (dùng cho KA4) | G80: Packing | H80: 0.083333 | I80: 1 | J80: EA | P80: =VLOOKUP(C80,COSTING!#REF!,2,0) -> #REF!
C81: 120341 | D81: PK LGIT T6M6 Housing 3HUC00006A | E81: 762796 | F81: Devide pad BR73-3R/Vách ngăn T6 housing (3 khía) 5 lớp, kt: 507*132mm | G81: Packing | H81: 0.166666 | I81: 1 | J81: EA | P81: =VLOOKUP(C81,COSTING!#REF!,2,0) -> #REF!
C82: 120341 | D82: PK LGIT T6M6 Housing 3HUC00006A | E82: 762797 | F82: Devide pad BR74-2R/Vách ngăn T6 housing (2 khía) 5 lớp, kt: 344*132mm | G82: Packing | H82: 0.25 | I82: 1 | J82: EA | P82: =VLOOKUP(C82,COSTING!#REF!,2,0) -> #REF!
C83: 301450 | D83: CNC LGIT T6M6 Housing 3HUC00006A | E83: 210333 | F83: CA LGIT T6M6 Housing 3HUC00006A | G83: CNC 1 | H83: 1 | I83: 1 | J83: PCS | P83: =VLOOKUP(C83,COSTING!#REF!,2,0) -> #REF!
C84: 210333 | D84: CA LGIT T6M6 Housing 3HUC00006A | E84: 762802 | F84: Aluminium ALDCS 12 Fe 0.9%-Nhôm thỏi ALDC12 thành phần Fe 0.9% | G84: Casting | H84: 1.63691 | I84: 1 | J84: KG | P84: =VLOOKUP(C84,COSTING!#REF!,2,0) -> #REF!
A85: 15 LG | C85: 120431 | D85: PK LGIT T6M8 Housing 3HUC00007A | E85: 301671 | F85: CNC LGIT T6 Housing 3HUC00006A | G85: Cleaning | H85: 1 | I85: 1 | J85: PCS | P85: =VLOOKUP(C85,COSTING!#REF!,2,0) -> #REF!
C86: 120431 | D86: PK LGIT T6M8 Housing 3HUC00007A | E86: 762660 | F86: Carton box 3 plates printing YLR68/Thùng nắp gập 3 lớp có in kích thước : 520*350*135 (dùng cho KA4) | G86: Packing | H86: 0.083333 | I86: 1 | J86: EA | P86: =VLOOKUP(C86,COSTING!#REF!,2,0) -> #REF!
C87: 120431 | D87: PK LGIT T6M8 Housing 3HUC00007A | E87: 762796 | F87: Devide pad BR73-3R/Vách ngăn T6 housing (3 khía) 5 lớp, kt: 507*132mm | G87: Packing | H87: 0.166666 | I87: 1 | J87: EA | P87: =VLOOKUP(C87,COSTING!#REF!,2,0) -> #REF!
C88: 120431 | D88: PK LGIT T6M8 Housing 3HUC00007A | E88: 762797 | F88: Devide pad BR74-2R/Vách ngăn T6 housing (2 khía) 5 lớp, kt: 344*132mm | G88: Packing | H88: 0.25 | I88: 1 | J88: EA | P88: =VLOOKUP(C88,COSTING!#REF!,2,0) -> #REF!
C89: 301671 | D89: CNC LGIT T6 Housing 3HUC00006A | E89: 210388 | F89: CA LGIT T6M8 Housing 3HUC00007A | G89: CNC 1 | H89: 1 | I89: 1 | J89: PCS | P89: =VLOOKUP(C89,COSTING!#REF!,2,0) -> #REF!
C90: 210388 | D90: CA LGIT T6M8 Housing 3HUC00007A | E90: 762802 | F90: Aluminium ALDCS 12 Fe 0.9%-Nhôm thỏi ALDC12 thành phần Fe 0.9% | G90: Casting | H90: 1.63691 | I90: 1 | J90: KG | P90: =VLOOKUP(C90,COSTING!#REF!,2,0) -> #REF!
A91: 16 LG | C91: 120362 | D91: PK LGIT MPC5.5 Cover lens 3HDC00003A | E91: 301520 | F91: CNC LIGT MPC5.5 Cover Lens 3HDC00003A | G91: Laser | H91: 1 | I91: 1 | J91: PCS | P91: =VLOOKUP(C91,COSTING!#REF!,2,0) -> #REF!
C92: 120362 | D92: PK LGIT MPC5.5 Cover lens 3HDC00003A | E92: 762279 | F92: Tray MPC5.5 - PET Black 520*360*1.4T | G92: Laser | H92: 0.0333 | I92: 1 | J92: EA | P92: =VLOOKUP(C92,COSTING!#REF!,2,0) -> #REF!
C93: 120362 | D93: PK LGIT MPC5.5 Cover lens 3HDC00003A | E93: 762327 | F93: Carton box 5 plates 2 surface yellow 480*350*380mm/Thùng carton 5 lớp 2 mặt vàng IN/YLR49 480*350*380mm | G93: Packing | H93: 0.001111 | I93: 1 | J93: EA | P93: =VLOOKUP(C93,COSTING!#REF!,2,0) -> #REF!
C94: 301520 | D94: CNC LIGT MPC5.5 Cover Lens 3HDC00003A | E94: 210178 | F94: CA LGIT MPC5.5 Cover lens 3HDC00003A | G94: CNC 1 | H94: 1 | I94: 1 | J94: PCS | P94: =VLOOKUP(C94,COSTING!#REF!,2,0) -> #REF!
C95: 210178 | D95: CA LGIT MPC5.5 Cover lens 3HDC00003A | E95: 762802 | F95: Aluminium ALDCS 12 Fe 0.9%-Nhôm thỏi ALDC12 thành phần Fe 0.9% | G95: Casting | H95: 0.062 | I95: 1 | J95: KG | P95: =VLOOKUP(C95,COSTING!#REF!,2,0) -> #REF!
A96: 17 LG | C96: 120411 | D96: PK PK LGIT MQ4a PE Cover | E96: 301469 | F96: CNC LGIT MQ4a PE Cover | G96: Cleaning | H96: 1 | I96: 1 | J96: PCS | P96: =VLOOKUP(C96,COSTING!#REF!,2,0) -> #REF!
C97: 120411 | D97: PK PK LGIT MQ4a PE Cover | E97: 762599 | F97: Carton box 3 plates YLR63/Thùng carton 3 lớp 1V5 Cover 528*352*104mm | G97: Packing | H97: 0.025 | I97: 1 | J97: EA | P97: =VLOOKUP(C97,COSTING!#REF!,2,0) -> #REF!
C98: 120411 | D98: PK PK LGIT MQ4a PE Cover | E98: 762600 | F98: Devide pad BR47-3R/Vách thùng 1V5 cover ( 3 khía) 504*101mm | G98: Packing | H98: 0.225 | I98: 1 | J98: EA | P98: =VLOOKUP(C98,COSTING!#REF!,2,0) -> #REF!
C99: 120411 | D99: PK PK LGIT MQ4a PE Cover | E99: 762601 | F99: Devide pad BR48-9R/Vách thùng 1V5 cover ( 9 khía) 342*101mm | G99: Packing | H99: 0.075 | I99: 1 | J99: EA | P99: =VLOOKUP(C99,COSTING!#REF!,2,0) -> #REF!
C100: 301469 | D100: CNC LGIT MQ4a PE Cover | E100: 210340 | F100: CA LGIT MQ4a PE Cover | G100: CNC 1 | H100: 1 | I100: 1 | J100: PCS | P100: =VLOOKUP(C100,COSTING!#REF!,2,0) -> #REF!
...

Sheet COSTING
U2: =+U4='Manufacturing Cost.'!M7 -> TRUE
D3: COSTING TABLE Apr.2026 | U3: 622 | V3: 627 | W3: =Y4=Outsoucing!J2 -> TRUE | X3: 627 | Y3: 627
Q4: =Q113+R113+R269+R536 -> 2.3186101e+10 | S4: =SUM(S7:S535) -> 275658.5 | U4: =+U113+U269+U536 -> 7.8122116e+09 | V4: =+V113+V269+V536 -> 2.5809805e+10 | W4: =ROUND((U4+V4+X4),0)=ROUND((('Manufacturing Cost.'!M7+'Manufacturing Cost.'!N7+'Manufacturing Cost.'!O7)+'Re-allowcate'!J27),0) -> TRUE | X4: =+X113+X269+X536 -> 1.1305394e+10 | Y4: =+Y113+Y269+Y536 -> 1339026728 | Z4: =+Z113+Z269+Z536 -> 1.5831593e+11 | AB4: =+AB113+AB269+AB536 -> 0
A5: Type | B5: Key Parent and chid | C5: Item code | D5: Item Parent Name | E5: In Qty | F5: NG Qty | G5: TOT Pro | H5: Item Child Code | I5: Item Child Name | J5: Process | K5: Usage | L5: 母件底数 Parent Item Quantity | M5: 用量单位 UOM | N5: Material Using BOM | O5: Qty Actual Material Issue | P5: Ave price | Q5: Actual Material Amt | R5: Raw-other-Amt | S5: Working hour | T5: Working hour(%) | U5: Direct Labour Cost | V5: Manufactuing Cost | W5: Working hour Allocation Indirect(%) | X5: Indirect cost | Y5: Outsourcing Fee | Z5: Total Cost(Include NG) | AA5: Unit cost Input | AB5: Remark
A7: WIP 1 | B7: =C7&H7 -> 210145762802 | C7: 210145 | D7: CA LGIT Gen3 AL5 | E7: 78082 | F7: 1971 | G7: =+E7+F7 -> 80053 | H7: 762802 | I7: Aluminium ALDCS 12 Fe 0.9%-Nhôm thỏi ALDC12 thành phần Fe 0.9% | J7: Casting | K7: 0.6665 | L7: 1 | M7: KG | N7: =K7*(E7+F7) -> 53355.324 | O7: 53669.333 | P7: 25493.055 | Q7: =O7*P7 -> 1.3681953e+09 | R7: 0 | S7: =VLOOKUP(C7,'Working Hours'!A:I,9,0)*G7 -> 2065.3674 | T7: =S7/SUM($S$7:$S$112) -> 0.05088998 | U7: =SUMIFS('Manufacturing Cost.'!N:N,'Manufacturing Cost.'!G:G,"622",'Manufacturing Cost.'!H:H,"0501")*T7 -> 1.0121078e+08 | V7: =SUMIFS('Manufacturing Cost.'!N:N,'Manufacturing Cost.'!G:G,"627",'Manufacturing Cost.'!H:H,"0501")*T7 -> 5.6881394e+08 | W7: =S7/SUM($S$7:$S$507) -> 0.0075240417 | X7: =SUMIFS('Manufacturing Cost.'!N:N,'Manufacturing Cost.'!H:H,"indirect",'Manufacturing Cost.'!G:G,"627")*W7 -> 85062259 | Y7: =SUMIF(Outsoucing!D:D,C7,Outsoucing!J:J) -> 0 | Z7: =Q7+R7+U7+V7+X7+Y7 -> 2.1232823e+09 | AA7: =IF(Z7<>0,(Z7/(E7+F7)),0) -> 26523.457 | AC7: 2.1232823e+09 | AD7: =+Z7-AC7 -> 0
A8: WIP 1 | B8: =C8&H8 -> 210148762802 | C8: 210148 | D8: CA LGIT Gen 2 | E8: 0 | F8: 0 | G8: =+E8+F8 -> 0 | H8: 762802 | I8: Aluminium ALDCS 12 Fe 0.9%-Nhôm thỏi ALDC12 thành phần Fe 0.9% | J8: Casting | K8: 0.3087 | L8: 1 | M8: KG | N8: =K8*(E8+F8) -> 0 | O8: 0 | P8: 25493.055 | Q8: =O8*P8 -> 0 | R8: 0 | S8: =VLOOKUP(C8,'Working Hours'!A:I,9,0)*G8 -> 0 | T8: =S8/SUM($S$7:$S$112) -> 0 | U8: =SUMIFS('Manufacturing Cost.'!N:N,'Manufacturing Cost.'!G:G,"622",'Manufacturing Cost.'!H:H,"0501")*T8 -> 0 | V8: =SUMIFS('Manufacturing Cost.'!N:N,'Manufacturing Cost.'!G:G,"627",'Manufacturing Cost.'!H:H,"0501")*T8 -> 0 | W8: =S8/SUM($S$7:$S$507) -> 0 | X8: =SUMIFS('Manufacturing Cost.'!N:N,'Manufacturing Cost.'!H:H,"indirect",'Manufacturing Cost.'!G:G,"627")*W8 -> 0 | Y8: =SUMIF(Outsoucing!D:D,C8,Outsoucing!J:J) -> 0 | Z8: =Q8+R8+U8+V8+X8+Y8 -> 0 | AA8: =IF(Z8<>0,(Z8/(E8+F8)),0) -> 0 | AC8: 0 | AD8: =+Z8-AC8 -> 0
A9: WIP 1 | B9: =C9&H9 -> 210152760309 | C9: 210152 | D9: CA Qualcomm Bittra 55-PM920 Front housing | E9: 0 | F9: 0 | G9: =+E9+F9 -> 0 | H9: 760309 | I9: Aluminum Ingots ADC3 , Hợp kim nhôm ADC3 | J9: Casting | K9: 0.19633 | L9: 1 | M9: KG | N9: =K9*(E9+F9) -> 0 | O9: 0 | P9: 88365.489 | Q9: =O9*P9 -> 0 | R9: 0 | S9: =VLOOKUP(C9,'Working Hours'!A:I,9,0)*G9 -> 0 | T9: =S9/SUM($S$7:$S$112) -> 0 | U9: =SUMIFS('Manufacturing Cost.'!N:N,'Manufacturing Cost.'!G:G,"622",'Manufacturing Cost.'!H:H,"0501")*T9 -> 0 | V9: =SUMIFS('Manufacturing Cost.'!N:N,'Manufacturing Cost.'!G:G,"627",'Manufacturing Cost.'!H:H,"0501")*T9 -> 0 | W9: =S9/SUM($S$7:$S$507) -> 0 | X9: =SUMIFS('Manufacturing Cost.'!N:N,'Manufacturing Cost.'!H:H,"indirect",'Manufacturing Cost.'!G:G,"627")*W9 -> 0 | Y9: =SUMIF(Outsoucing!D:D,C9,Outsoucing!J:J) -> 0 | Z9: =Q9+R9+U9+V9+X9+Y9 -> 0 | AA9: =IF(Z9<>0,(Z9/(E9+F9)),0) -> 0 | AC9: 0 | AD9: =+Z9-AC9 -> 0
A10: WIP 1 | B10: =C10&H10 -> 210158762802 | C10: 210158 | D10: CA OMS ENTRY_3CAC00250A VCSEL COVER | E10: 0 | F10: 0 | G10: =+E10+F10 -> 0 | H10: 762802 | I10: Aluminium ALDCS 12 Fe 0.9%-Nhôm thỏi ALDC12 thành phần Fe 0.9% | J10: Casting | K10: 0.06433 | L10: 1 | M10: KG | N10: =K10*(E10+F10) -> 0 | O10: 0 | P10: 25493.055 | Q10: =O10*P10 -> 0 | R10: 0 | S10: =VLOOKUP(C10,'Working Hours'!A:I,9,0)*G10 -> 0 | T10: =S10/SUM($S$7:$S$112) -> 0 | U10: =SUMIFS('Manufacturing Cost.'!N:N,'Manufacturing Cost.'!G:G,"622",'Manufacturing Cost.'!H:H,"0501")*T10 -> 0 | V10: =SUMIFS('Manufacturing Cost.'!N:N,'Manufacturing Cost.'!G:G,"627",'Manufacturing Cost.'!H:H,"0501")*T10 -> 0 | W10: =S10/SUM($S$7:$S$507) -> 0 | X10: =SUMIFS('Manufacturing Cost.'!N:N,'Manufacturing Cost.'!H:H,"indirect",'Manufacturing Cost.'!G:G,"627")*W10 -> 0 | Y10: =SUMIF(Outsoucing!D:D,C10,Outsoucing!J:J) -> 0 | Z10: =Q10+R10+U10+V10+X10+Y10 -> 0 | AA10: =IF(Z10<>0,(Z10/(E10+F10)),0) -> 0 | AC10: 0 | AD10: =+Z10-AC10 -> 0
A11: WIP 1 | B11: =C11&H11 -> 210159762802 | C11: 210159 | D11: CA OMS ENTRY LENS 3CAC00203A | E11: 0 | F11: 0 | G11: =+E11+F11 -> 0 | H11: 762802 | I11: Aluminium ALDCS 12 Fe 0.9%-Nhôm thỏi ALDC12 thành phần Fe 0.9% | J11: Casting | K11: 0.04335 | L11: 1 | M11: KG | N11: =K11*(E11+F11) -> 0 | O11: 0 | P11: 25493.055 | Q11: =O11*P11 -> 0 | R11: 0 | S11: =VLOOKUP(C11,'Working Hours'!A:I,9,0)*G11 -> 0 | T11: =S11/SUM($S$7:$S$112) -> 0 | U11: =SUMIFS('Manufacturing Cost.'!N:N,'Manufacturing Cost.'!G:G,"622",'Manufacturing Cost.'!H:H,"0501")*T11 -> 0 | V11: =SUMIFS('Manufacturing Cost.'!N:N,'Manufacturing Cost.'!G:G,"627",'Manufacturing Cost.'!H:H,"0501")*T11 -> 0 | W11: =S11/SUM($S$7:$S$507) -> 0 | X11: =SUMIFS('Manufacturing Cost.'!N:N,'Manufacturing Cost.'!H:H,"indirect",'Manufacturing Cost.'!G:G,"627")*W11 -> 0 | Y11: =SUMIF(Outsoucing!D:D,C11,Outsoucing!J:J) -> 0 | Z11: =Q11+R11+U11+V11+X11+Y11 -> 0 | AA11: =IF(Z11<>0,(Z11/(E11+F11)),0) -> 0 | AC11: 0 | AD11: =+Z11-AC11 -> 0
A12: WIP 1 | B12: =C12&H12 -> 210171762249 | C12: 210171 | D12: CA ZF TRW - GM EU2L Housing A021D074 | E12: 49850 | F12: 2430 | G12: =+E12+F12 -> 52280 | H12: 762249 | I12: Aluminum S3Y/Nhôm hợp kim dạng thanh S3Y | J12: Casting | K12: 0.22739 | L12: 1 | M12: KG | N12: =K12*(E12+F12) -> 11887.949 | O12: 12860.194 | P12: 33082.841 | Q12: =O12*P12 -> 4.2545176e+08 | R12: 0 | S12: =VLOOKUP(C12,'Working Hours'!A:I,9,0)*G12 -> 711.008 | T12: =S12/SUM($S$7:$S$112) -> 0.017519005 | U12: =SUMIFS('Manufacturing Cost.'!N:N,'Manufacturing Cost.'!G:G,"622",'Manufacturing Cost.'!H:H,"0501")*T12 -> 34842069 | V12: =SUMIFS('Manufacturing Cost.'!N:N,'Manufacturing Cost.'!G:G,"627",'Manufacturing Cost.'!H:H,"0501")*T12 -> 1.9581565e+08 | W12: =S12/SUM($S$7:$S$507) -> 0.0025901706 | X12: =SUMIFS('Manufacturing Cost.'!N:N,'Manufacturing Cost.'!H:H,"indirect",'Manufacturing Cost.'!G:G,"627")*W12 -> 29282900 | Y12: =SUMIF(Outsoucing!D:D,C12,Outsoucing!J:J) -> 0 | Z12: =Q12+R12+U12+V12+X12+Y12 -> 6.8539238e+08 | AA12: =IF(Z12<>0,(Z12/(E12+F12)),0) -> 13110.03 | AC12: 6.8539238e+08 | AD12: =+Z12-AC12 -> 0
A13: WIP 1 | B13: =C13&H13 -> 210172762249 | C13: 210172 | D13: CA ZF TRW-Nissan/FCA/GMT 4.8 Lenmount | E13: 290546 | F13: 21627 | G13: =+E13+F13 -> 312173 | H13: 762249 | I13: Aluminum S3Y/Nhôm hợp kim dạng thanh S3Y | J13: Casting | K13: 0.05228 | L13: 1 | M13: KG | N13: =K13*(E13+F13) -> 16320.404 | O13: 15092.158 | P13: 33082.841 | Q13: =O13*P13 -> 4.9929145e+08 | R13: 0 | S13: =VLOOKUP(C13,'Working Hours'!A:I,9,0)*G13 -> 2247.6456 | T13: =S13/SUM($S$7:$S$112) -> 0.055381255 | U13: =SUMIFS('Manufacturing Cost.'!N:N,'Manufacturing Cost.'!G:G,"622",'Manufacturing Cost.'!H:H,"0501")*T13 -> 1.101431e+08 | V13: =SUMIFS('Manufacturing Cost.'!N:N,'Manufacturing Cost.'!G:G,"627",'Manufacturing Cost.'!H:H,"0501")*T13 -> 6.190144e+08 | W13: =S13/SUM($S$7:$S$507) -> 0.0081880731 | X13: =SUMIFS('Manufacturing Cost.'!N:N,'Manufacturing Cost.'!H:H,"indirect",'Manufacturing Cost.'!G:G,"627")*W13 -> 92569396 | Y13: =SUMIF(Outsoucing!D:D,C13,Outsoucing!J:J) -> 0 | Z13: =Q13+R13+U13+V13+X13+Y13 -> 1.3210183e+09 | AA13: =IF(Z13<>0,(Z13/(E13+F13)),0) -> 4231.6867 | AC13: 1.3210183e+09 | AD13: =+Z13-AC13 -> 0
A14: WIP 1 | B14: =C14&H14 -> 210178762802 | C14: 210178 | D14: CA LGIT MPC5.5 Cover lens 3HDC00003A | E14: 144040 | F14: 5038 | G14: =+E14+F14 -> 149078 | H14: 762802 | I14: Aluminium ALDCS 12 Fe 0.9%-Nhôm thỏi ALDC12 thành phần Fe 0.9% | J14: Casting | K14: 0.062 | L14: 1 | M14: KG | N14: =K14*(E14+F14) -> 9242.836 | O14: 11492.143 | P14: 25493.055 | Q14: =O14*P14 -> 2.9296984e+08 | R14: 0 | S14: =VLOOKUP(C14,'Working Hours'!A:I,9,0)*G14 -> 1162.8084 | T14: =S14/SUM($S$7:$S$112) -> 0.02865122 | U14: =SUMIFS('Manufacturing Cost.'!N:N,'Manufacturing Cost.'!G:G,"622",'Manufacturing Cost.'!H:H,"0501")*T14 -> 56981990 | V14: =SUMIFS('Manufacturing Cost.'!N:N,'Manufacturing Cost.'!G:G,"627",'Manufacturing Cost.'!H:H,"0501")*T14 -> 3.2024406e+08 | W14: =S14/SUM($S$7:$S$507) -> 0.0042360594 | X14: =SUMIFS('Manufacturing Cost.'!N:N,'Manufacturing Cost.'!H:H,"indirect",'Manufacturing Cost.'!G:G,"627")*W14 -> 47890322 | Y14: =SUMIF(Outsoucing!D:D,C14,Outsoucing!J:J) -> 0 | Z14: =Q14+R14+U14+V14+X14+Y14 -> 7.1808621e+08 | AA14: =IF(Z14<>0,(Z14/(E14+F14)),0) -> 4816.849 | AC14: 7.1808621e+08 | AD14: =+Z14-AC14 -> 0
A15: WIP 1 | B15: =C15&H15 -> 210179762249 | C15: 210179 | D15: CA TRW-FCA 4.8 Housing | E15: 108420 | F15: 4966 | G15: =+E15+F15 -> 113386 | H15: 762249 | I15: Aluminum S3Y/Nhôm hợp kim dạng thanh S3Y | J15: Casting | K15: 0.258199 | L15: 1 | M15: KG | N15: =K15*(E15+F15) -> 29276.152 | O15: 25512.578 | P15: 33082.841 | Q15: =O15*P15 -> 8.4402858e+08 | R15: 0 | S15: =VLOOKUP(C15,'Working Hours'!A:I,9,0)*G15 -> 1542.0496 | T15: =S15/SUM($S$7:$S$112) -> 0.0379956 | U15: =SUMIFS('Manufacturing Cost.'!N:N,'Manufacturing Cost.'!G:G,"622",'Manufacturing Cost.'!H:H,"0501")*T15 -> 75566237 | V15: =SUMIFS('Manufacturing Cost.'!N:N,'Manufacturing Cost.'!G:G,"627",'Manufacturing Cost.'!H:H,"0501")*T15 -> 4.2468924e+08 | W15: =S15/SUM($S$7:$S$507) -> 0.0056176182 | X15: =SUMIFS('Manufacturing Cost.'!N:N,'Manufacturing Cost.'!H:H,"indirect",'Manufacturing Cost.'!G:G,"627")*W15 -> 63509390 | Y15: =SUMIF(Outsoucing!D:D,C15,Outsoucing!J:J) -> 0 | Z15: =Q15+R15+U15+V15+X15+Y15 -> 1.4077934e+09 | AA15: =IF(Z15<>0,(Z15/(E15+F15)),0) -> 12415.937 | AC15: 1.4077934e+09 | AD15: =+Z15-AC15 -> 0
A16: WIP 1 | B16: =C16&H16 -> 210180762249 | C16: 210180 | D16: CA TRW-FCA 4.8 Cover | E16: 83422 | F16: 3700 | G16: =+E16+F16 -> 87122 | H16: 762249 | I16: Aluminum S3Y/Nhôm hợp kim dạng thanh S3Y | J16: Casting | K16: 0.15738 | L16: 1 | M16: KG | N16: =K16*(E16+F16) -> 13711.26 | O16: 15267.21 | P16: 33082.841 | Q16: =O16*P16 -> 5.0508268e+08 | R16: 0 | S16: =VLOOKUP(C16,'Working Hours'!A:I,9,0)*G16 -> 409.4734 | T16: =S16/SUM($S$7:$S$112) -> 0.010089291 | U16: =SUMIFS('Manufacturing Cost.'!N:N,'Manufacturing Cost.'!G:G,"622",'Manufacturing Cost.'!H:H,"0501")*T16 -> 20065739 | V16: =SUMIFS('Manufacturing Cost.'!N:N,'Manufacturing Cost.'!G:G,"627",'Manufacturing Cost.'!H:H,"0501")*T16 -> 1.1277131e+08 | W16: =S16/SUM($S$7:$S$507) -> 0.0014916934 | X16: =SUMIFS('Manufacturing Cost.'!N:N,'Manufacturing Cost.'!H:H,"indirect",'Manufacturing Cost.'!G:G,"627")*W16 -> 16864182 | Y16: =SUMIF(Outsoucing!D:D,C16,Outsoucing!J:J) -> 0 | Z16: =Q16+R16+U16+V16+X16+Y16 -> 6.5478391e+08 | AA16: =IF(Z16<>0,(Z16/(E16+F16)),0) -> 7515.7125 | AC16: 6.5478391e+08 | AD16: =+Z16-AC16 -> 0
A17: WIP 1 | B17: =C17&H17 -> 210191762802 | C17: 210191 | D17: CA LGIT OMS Front 3CAC00207A | E17: 0 | F17: 0 | G17: =+E17+F17 -> 0 | H17: 762802 | I17: Aluminium ALDCS 12 Fe 0.9%-Nhôm thỏi ALDC12 thành phần Fe 0.9% | J17: Casting | K17: 0.04163 | L17: 1 | M17: KG | N17: =K17*(E17+F17) -> 0 | O17: 0 | P17: 25493.055 | Q17: =O17*P17 -> 0 | R17: 0 | S17: =VLOOKUP(C17,'Working Hours'!A:I,9,0)*G17 -> 0 | T17: =S17/SUM($S$7:$S$112) -> 0 | U17: =SUMIFS('Manufacturing Cost.'!N:N,'Manufacturing Cost.'!G:G,"622",'Manufacturing Cost.'!H:H,"0501")*T17 -> 0 | V17: =SUMIFS('Manufacturing Cost.'!N:N,'Manufacturing Cost.'!G:G,"627",'Manufacturing Cost.'!H:H,"0501")*T17 -> 0 | W17: =S17/SUM($S$7:$S$507) -> 0 | X17: =SUMIFS('Manufacturing Cost.'!N:N,'Manufacturing Cost.'!H:H,"indirect",'Manufacturing Cost.'!G:G,"627")*W17 -> 0 | Y17: =SUMIF(Outsoucing!D:D,C17,Outsoucing!J:J) -> 0 | Z17: =Q17+R17+U17+V17+X17+Y17 -> 0 | AA17: =IF(Z17<>0,(Z17/(E17+F17)),0) -> 0 | AC17: 0 | AD17: =+Z17-AC17 -> 0
A18: WIP 1 | B18: =C18&H18 -> 210192762249 | C18: 210192 | D18: CA ZF TRW - GM EU2L Cover A021D075 | E18: 34422 | F18: 2100 | G18: =+E18+F18 -> 36522 | H18: 762249 | I18: Aluminum S3Y/Nhôm hợp kim dạng thanh S3Y | J18: Casting | K18: 0.14131 | L18: 1 | M18: KG | N18: =K18*(E18+F18) -> 5160.9238 | O18: 3264.261 | P18: 33082.841 | Q18: =O18*P18 -> 1.0799103e+08 | R18: 0 | S18: =VLOOKUP(C18,'Working Hours'!A:I,9,0)*G18 -> 171.6534 | T18: =S18/SUM($S$7:$S$112) -> 0.0042294838 | U18: =SUMIFS('Manufacturing Cost.'!N:N,'Manufacturing Cost.'!G:G,"622",'Manufacturing Cost.'!H:H,"0501")*T18 -> 8411663 | V18: =SUMIFS('Manufacturing Cost.'!N:N,'Manufacturing Cost.'!G:G,"627",'Manufacturing Cost.'!H:H,"0501")*T18 -> 47274324 | W18: =S18/SUM($S$7:$S$507) -> 0.00062532571 | X18: =SUMIFS('Manufacturing Cost.'!N:N,'Manufacturing Cost.'!H:H,"indirect",'Manufacturing Cost.'!G:G,"627")*W18 -> 7069553.8 | Y18: =SUMIF(Outsoucing!D:D,C18,Outsoucing!J:J) -> 0 | Z18: =Q18+R18+U18+V18+X18+Y18 -> 1.7074657e+08 | AA18: =IF(Z18<>0,(Z18/(E18+F18)),0) -> 4675.1703 | AC18: 1.7074657e+08 | AD18: =+Z18-AC18 -> 0
... A73: WIP 1 | B73: =C73&H73 -> 210402762802 | C73: 210402 | D73: CA Mando Brose JG REPS ME210JGRW0 Housing cover | E73: 3731 | F73: 263 | G73: =+E73+F73 -> 3994 | H73: 762802 | I73: Aluminium ALDCS 12 Fe 0.9%, Nhôm thỏi ALDC12 thành phần Fe 0.9% | J73: Casting | K73: 0.52821 | L73: 1 | M73: KG | N73: =K73*(E73+F73) -> 2109.6707 | O73: 607.4415 | P73: 25493.055 | Q73: =O73*P73 -> 15485540 | R73: 0 | S73: =VLOOKUP(C73,'Working Hours'!A:I,9,0)*G73 -> 39.5406 | T73: =S73/SUM($S$7:$S$112) -> 0.0009742675 | U73: =SUMIFS('Manufacturing Cost.'!N:N,'Manufacturing Cost.'!G:G,"622",'Manufacturing Cost.'!H:H,"0501")*T73 -> 1937638.3 | V73: =SUMIFS('Manufacturing Cost.'!N:N,'Manufacturing Cost.'!G:G,"627",'Manufacturing Cost.'!H:H,"0501")*T73 -> 10889706 | W73: =S73/SUM($S$7:$S$507) -> 0.00014404465 | X73: =SUMIFS('Manufacturing Cost.'!N:N,'Manufacturing Cost.'!H:H,"indirect",'Manufacturing Cost.'!G:G,"627")*W73 -> 1628481.6 | Y73: =SUMIF(Outsoucing!D:D,C73,Outsoucing!J:J) -> 0 | Z73: =Q73+R73+U73+V73+X73+Y73 -> 29941366 | AA73: =IF(Z73<>0,(Z73/(E73+F73)),0) -> 7496.5864 | AC73: 29941366 | AD73: =+Z73-AC73 -> 0
A74: WIP 1 | B74: =C74&H74 -> 551243800786 | C74: 551243 | D74: IN Qualcomm MTP MTP PAKALA CA90-58183-5 FRAME, WLAN AREA, MULTIPURPOSE | E74: 0 | F74: 0 | G74: =+E74+F74 -> 0 | H74: 800786 | I74: Resin Lucky Enpla PC- LPC1001F 9306(BK), Hạt nhựa nguyên sinh Lucky Enpla PC- LPC1001F 9306(BK) | J74: Casting | K74: 0.00624 | M74: KG | N74: =K74*(E74+F74) -> 0 | O74: 0 | P74: 152445.57 | Q74: =O74*P74 -> 0 | R74: 0 | S74: =VLOOKUP(C74,'Working Hours'!A:I,9,0)*G74 -> 0 | T74: =S74/SUM($S$7:$S$112) -> 0 | U74: =SUMIFS('Manufacturing Cost.'!N:N,'Manufacturing Cost.'!G:G,"622",'Manufacturing Cost.'!H:H,"0501")*T74 -> 0 | V74: =SUMIFS('Manufacturing Cost.'!N:N,'Manufacturing Cost.'!G:G,"627",'Manufacturing Cost.'!H:H,"0501")*T74 -> 0 | W74: =S74/SUM($S$7:$S$507) -> 0 | X74: =SUMIFS('Manufacturing Cost.'!N:N,'Manufacturing Cost.'!H:H,"indirect",'Manufacturing Cost.'!G:G,"627")*W74 -> 0 | Y74: =SUMIF(Outsoucing!D:D,C74,Outsoucing!J:J) -> 0 | Z74: =Q74+R74+U74+V74+X74+Y74 -> 0 | AA74: =IF(Z74<>0,(Z74/(E74+F74)),0) -> 0 | AC74: 0 | AD74: =+Z74-AC74 -> 0
A75: WIP 1 | B75: =C75&H75 -> 210151762802 | C75: 210151 | D75: CA Qualcomm Lahaina 55-PP323-1 Module 0 | E75: 0 | F75: 0 | G75: =+E75+F75 -> 0 | H75: 762802 | I75: Aluminium ALDCS 12 Fe 0.9%, Nhôm thỏi ALDC12 thành phần Fe 0.9% | J75: Casting | K75: 0.04422 | L75: 1 | M75: KG | N75: =K75*(E75+F75) -> 0 | O75: 0 | P75: 25493.055 | Q75: =O75*P75 -> 0 | R75: 0 | S75: =VLOOKUP(C75,'Working Hours'!A:I,9,0)*G75 -> 0 | T75: =S75/SUM($S$7:$S$112) -> 0 | U75: =SUMIFS('Manufacturing Cost.'!N:N,'Manufacturing Cost.'!G:G,"622",'Manufacturing Cost.'!H:H,"0501")*T75 -> 0 | V75: =SUMIFS('Manufacturing Cost.'!N:N,'Manufacturing Cost.'!G:G,"627",'Manufacturing Cost.'!H:H,"0501")*T75 -> 0 | W75: =S75/SUM($S$7:$S$507) -> 0 | X75: =SUMIFS('Manufacturing Cost.'!N:N,'Manufacturing Cost.'!H:H,"indirect",'Manufacturing Cost.'!G:G,"627")*W75 -> 0 | Y75: =SUMIF(Outsoucing!D:D,C75,Outsoucing!J:J) -> 0 | Z75: =Q75+R75+U75+V75+X75+Y75 -> 0 | AA75: =IF(Z75<>0,(Z75/(E75+F75)),0) -> 0 | AC75: 0 | AD75: =+Z75-AC75 -> 0
A76: WIP 1 | B76: =C76&H76 -> 210403762802 | C76: 210403 | D76: CA Mando Brose US4 GE844EM003 cover | E76: 0 | F76: 0 | G76: =+E76+F76 -> 0 | H76: 762802 | I76: Aluminium ALDCS 12 Fe 0.9%, Nhôm thỏi ALDC12 thành phần Fe 0.9% | J76: Casting | K76: 0.5282 | L76: 1 | M76: KG | N76: =K76*(E76+F76) -> 0 | O76: 0 | P76: 25493.055 | Q76: =O76*P76 -> 0 | R76: 0 | S76: =VLOOKUP(C76,'Working Hours'!A:I,9,0)*G76 -> 0 | T76: =S76/SUM($S$7:$S$112) -> 0 | U76: =SUMIFS('Manufacturing Cost.'!N:N,'Manufacturing Cost.'!G:G,"622",'Manufacturing Cost.'!H:H,"0501")*T76 -> 0 | V76: =SUMIFS('Manufacturing Cost.'!N:N,'Manufacturing Cost.'!G:G,"627",'Manufacturing Cost.'!H:H,"0501")*T76 -> 0 | W76: =S76/SUM($S$7:$S$507) -> 0 | X76: =SUMIFS('Manufacturing Cost.'!N:N,'Manufacturing Cost.'!H:H,"indirect",'Manufacturing Cost.'!G:G,"627")*W76 -> 0 | Y76: =SUMIF(Outsoucing!D:D,C76,Outsoucing!J:J) -> 0 | Z76: =Q76+R76+U76+V76+X76+Y76 -> 0 | AA76: =IF(Z76<>0,(Z76/(E76+F76)),0) -> 0 | AC76: 0 | AD76: =+Z76-AC76 -> 0
A77: WIP 1 | B77: =C77&H77 -> 210404762802 | C77: 210404 | D77: CA Mando Brose LT2 ME200LT200 DIECAST HOUSING | E77: 370 | F77: 0 | G77: =+E77+F77 -> 370 | H77: 762802 | I77: Aluminium ALDCS 12 Fe 0.9%, Nhôm thỏi ALDC12 thành phần Fe 0.9% | J77: Casting | K77: 1.61047 | L77: 1 | M77: KG | N77: =K77*(E77+F77) -> 595.8739 | O77: 128.8376 | P77: 25493.055 | Q77: =O77*P77 -> 3284464.1 | R77: 0 | S77: =VLOOKUP(C77,'Working Hours'!A:I,9,0)*G77 -> 13.912 | T77: =S77/SUM($S$7:$S$112) -> 0.00034278715 | U77: =SUMIFS('Manufacturing Cost.'!N:N,'Manufacturing Cost.'!G:G,"622",'Manufacturing Cost.'!H:H,"0501")*T77 -> 681740.39 | V77: =SUMIFS('Manufacturing Cost.'!N:N,'Manufacturing Cost.'!G:G,"627",'Manufacturing Cost.'!H:H,"0501")*T77 -> 3831444 | W77: =S77/SUM($S$7:$S$507) -> 5.0680798e-05 | X77: =SUMIFS('Manufacturing Cost.'!N:N,'Manufacturing Cost.'!H:H,"indirect",'Manufacturing Cost.'!G:G,"627")*W77 -> 572966.41 | Y77: =SUMIF(Outsoucing!D:D,C77,Outsoucing!J:J) -> 0 | Z77: =Q77+R77+U77+V77+X77+Y77 -> 8370614.9 | AA77: =IF(Z77<>0,(Z77/(E77+F77)),0) -> 22623.284 | AC77: 8370614.9 | AD77: =+Z77-AC77 -> 0
A78: WIP 1 | B78: =C78&H78 -> 210405760011 | C78: 210405 | D78: CA SM-A176B | E78: 997013 | F78: 40157 | G78: =+E78+F78 -> 1037170 | H78: 760011 | I78: Aluminum alloy bar S36, Nhôm hợp kim dạng thanh S36 | J78: Casting | K78: 0.1786 | L78: 1 | M78: KG | N78: =K78*(E78+F78) -> 185238.56 | O78: 148672.71 | P78: 15519.439 | Q78: =O78*P78 -> 2.3073171e+09 | R78: 0 | S78: =VLOOKUP(C78,'Working Hours'!A:I,9,0)*G78 -> 18046.758 | T78: =S78/SUM($S$7:$S$112) -> 0.44466624 | U78: =SUMIFS('Manufacturing Cost.'!N:N,'Manufacturing Cost.'!G:G,"622",'Manufacturing Cost.'!H:H,"0501")*T78 -> 8.843591e+08 | V78: =SUMIFS('Manufacturing Cost.'!N:N,'Manufacturing Cost.'!G:G,"627",'Manufacturing Cost.'!H:H,"0501")*T78 -> 4.9701799e+09 | W78: =S78/SUM($S$7:$S$507) -> 0.065743538 | X78: =SUMIFS('Manufacturing Cost.'!N:N,'Manufacturing Cost.'!H:H,"indirect",'Manufacturing Cost.'!G:G,"627")*W78 -> 7.4325663e+08 | Y78: =SUMIF(Outsoucing!D:D,C78,Outsoucing!J:J) -> 207068994 | Z78: =Q78+R78+U78+V78+X78+Y78 -> 9.1121818e+09 | AA78: =IF(Z78<>0,(Z78/(E78+F78)),0) -> 8785.6202 | AC78: 9.1121818e+09 | AD78: =+Z78-AC78 -> 0
A79: WIP 1 | B79: =C79&H79 -> 210406760309 | C79: 210406 | D79: CA Qualcomm AMBOSELI 55-84713-1 HIELD, HEATSINK, RF CARD, PICTOR/ALIOTH" | E79: 347 | F79: 0 | G79: =+E79+F79 -> 347 | H79: 760309 | I79: Aluminum Ingots ADC3 , Hợp kim nhôm ADC3 | J79: Casting | K79: 0.144 | L79: 1 | M79: KG | N79: =K79*(E79+F79) -> 49.968 | O79: 49.968 | P79: 88365.489 | Q79: =O79*P79 -> 4415446.7 | R79: 0 | S79: =VLOOKUP(C79,'Working Hours'!A:I,9,0)*G79 -> 6.8359 | T79: =S79/SUM($S$7:$S$112) -> 0.00016843435 | U79: =SUMIFS('Manufacturing Cost.'!N:N,'Manufacturing Cost.'!G:G,"622",'Manufacturing Cost.'!H:H,"0501")*T79 -> 334984.84 | V79: =SUMIFS('Manufacturing Cost.'!N:N,'Manufacturing Cost.'!G:G,"627",'Manufacturing Cost.'!H:H,"0501")*T79 -> 1882645.8 | W79: =S79/SUM($S$7:$S$507) -> 2.490288e-05 | X79: =SUMIFS('Manufacturing Cost.'!N:N,'Manufacturing Cost.'!H:H,"indirect",'Manufacturing Cost.'!G:G,"627")*W79 -> 281536.88 | Y79: =SUMIF(Outsoucing!D:D,C79,Outsoucing!J:J) -> 0 | Z79: =Q79+R79+U79+V79+X79+Y79 -> 6914614.3 | AA79: =IF(Z79<>0,(Z79/(E79+F79)),0) -> 19926.842 | AC79: 6914614.3 | AD79: =+Z79-AC79 -> 0
A80: WIP 1 | B80: =C80&H80 -> 210407762802 | C80: 210407 | D80: CA Mando Brose JG RWS Cover GE844EM111 | E80: 285 | F80: 0 | G80: =+E80+F80 -> 285 | H80: 762802 | I80: Aluminium ALDCS 12 Fe 0.9%, Nhôm thỏi ALDC12 thành phần Fe 0.9% | J80: Casting | K80: 0.5364 | L80: 1 | M80: KG | N80: =K80*(E80+F80) -> 152.874 | O80: 536.4 | P80: 25493.055 | Q80: =O80*P80 -> 13674475 | R80: 0 | S80: =VLOOKUP(C80,'Working Hours'!A:I,9,0)*G80 -> 2.8215 | T80: =S80/SUM($S$7:$S$112) -> 6.952084e-05 | U80: =SUMIFS('Manufacturing Cost.'!N:N,'Manufacturing Cost.'!G:G,"622",'Manufacturing Cost.'!H:H,"0501")*T80 -> 138264.12 | V80: =SUMIFS('Manufacturing Cost.'!N:N,'Manufacturing Cost.'!G:G,"627",'Manufacturing Cost.'!H:H,"0501")*T80 -> 777057.17 | W80: =S80/SUM($S$7:$S$507) -> 1.0278599e-05 | X80: =SUMIFS('Manufacturing Cost.'!N:N,'Manufacturing Cost.'!H:H,"indirect",'Manufacturing Cost.'!G:G,"627")*W80 -> 116203.62 | Y80: =SUMIF(Outsoucing!D:D,C80,Outsoucing!J:J) -> 0 | Z80: =Q80+R80+U80+V80+X80+Y80 -> 14706000 | AA80: =IF(Z80<>0,(Z80/(E80+F80)),0) -> 51599.999 | AC80: 14706000 | AD80: =+Z80-AC80 -> 0
A81: WIP 1 | B81: =C81&H81 -> 210183762802 | C81: 210183 | D81: CA LG IKC Camera Base 3CAC00180A | E81: 2251 | F81: 127 | G81: =+E81+F81 -> 2378 | H81: 762802 | I81: Aluminium ALDCS 12 Fe 0.9%, Nhôm thỏi ALDC12 thành phần Fe 0.9% | J81: Casting | K81: 0.0292 | L81: 1 | M81: KG | N81: =K81*(E81+F81) -> 69.4376 | O81: 0 | P81: 25493.055 | Q81: =O81*P81 -> 0 | R81: 0 | S81: =VLOOKUP(C81,'Working Hours'!A:I,9,0)*G81 -> 33.292 | T81: =S81/SUM($S$7:$S$112) -> 0.00082030403 | U81: =SUMIFS('Manufacturing Cost.'!N:N,'Manufacturing Cost.'!G:G,"622",'Manufacturing Cost.'!H:H,"0501")*T81 -> 1631433.4 | V81: =SUMIFS('Manufacturing Cost.'!N:N,'Manufacturing Cost.'!G:G,"627",'Manufacturing Cost.'!H:H,"0501")*T81 -> 9168806.4 | W81: =S81/SUM($S$7:$S$507) -> 0.00012128128 | X81: =SUMIFS('Manufacturing Cost.'!N:N,'Manufacturing Cost.'!H:H,"indirect",'Manufacturing Cost.'!G:G,"627")*W81 -> 1371132.7 | Y81: =SUMIF(Outsoucing!D:D,C81,Outsoucing!J:J) -> 0 | Z81: =Q81+R81+U81+V81+X81+Y81 -> 12171372 | AA81: =IF(Z81<>0,(Z81/(E81+F81)),0) -> 5118.3231 | AC81: 12171372 | AD81: =+Z81-AC81 -> 0
A82: WIP 1 | B82: =C82&H82 -> 210408762802 | C82: 210408 | D82: CA Mando Brose JK1-LHD Housing ME200V1200 | E82: 60 | F82: 0 | G82: =+E82+F82 -> 60 | H82: 762802 | I82: Aluminium ALDCS 12 Fe 0.9%, Nhôm thỏi ALDC12 thành phần Fe 0.9% | J82: Casting | K82: 1.01964 | L82: 1 | M82: KG | N82: =K82*(E82+F82) -> 61.1784 | O82: 61.1784 | P82: 25493.055 | Q82: =O82*P82 -> 1559624.3 | R82: 0 | S82: =VLOOKUP(C82,'Working Hours'!A:I,9,0)*G82 -> 1.602 | T82: =S82/SUM($S$7:$S$112) -> 3.9472758e-05 | U82: =SUMIFS('Manufacturing Cost.'!N:N,'Manufacturing Cost.'!G:G,"622",'Manufacturing Cost.'!H:H,"0501")*T82 -> 78504.033 | V82: =SUMIFS('Manufacturing Cost.'!N:N,'Manufacturing Cost.'!G:G,"627",'Manufacturing Cost.'!H:H,"0501")*T82 -> 441199.92 | W82: =S82/SUM($S$7:$S$507) -> 5.8360149e-06 | X82: =SUMIFS('Manufacturing Cost.'!N:N,'Manufacturing Cost.'!H:H,"indirect",'Manufacturing Cost.'!G:G,"627")*W82 -> 65978.45 | Y82: =SUMIF(Outsoucing!D:D,C82,Outsoucing!J:J) -> 3666166 | Z82: =Q82+R82+U82+V82+X82+Y82 -> 5811472.7 | AA82: =IF(Z82<>0,(Z82/(E82+F82)),0) -> 96857.879 | AC82: 5811472.7 | AD82: =+Z82-AC82 -> 0
A83: WIP 1 | B83: =C83&H83 -> 210409762802 | C83: 210409 | D83: CA ZF Wabco OGM2.0 IPM2.0 Housing_Base new A032N890/A032N891 | E83: 0 | F83: 0 | G83: =+E83+F83 -> 0 | H83: 762802 | I83: Aluminium ALDCS 12 Fe 0.9%, Nhôm thỏi ALDC12 thành phần Fe 0.9% | J83: Casting | K83: 0.6243 | L83: 1 | M83: KG | N83: =K83*(E83+F83) -> 0 | O83: 0 | P83: 25493.055 | Q83: =O83*P83 -> 0 | R83: 0 | S83: =VLOOKUP(C83,'Working Hours'!A:I,9,0)*G83 -> 0 | T83: =S83/SUM($S$7:$S$112) -> 0 | U83: =SUMIFS('Manufacturing Cost.'!N:N,'Manufacturing Cost.'!G:G,"622",'Manufacturing Cost.'!H:H,"0501")*T83 -> 0 | V83: =SUMIFS('Manufacturing Cost.'!N:N,'Manufacturing Cost.'!G:G,"627",'Manufacturing Cost.'!H:H,"0501")*T83 -> 0 | W83: =S83/SUM($S$7:$S$507) -> 0 | X83: =SUMIFS('Manufacturing Cost.'!N:N,'Manufacturing Cost.'!H:H,"indirect",'Manufacturing Cost.'!G:G,"627")*W83 -> 0 | Y83: =SUMIF(Outsoucing!D:D,C83,Outsoucing!J:J) -> 0 | Z83: =Q83+R83+U83+V83+X83+Y83 -> 0 | AA83: =IF(Z83<>0,(Z83/(E83+F83)),0) -> 0 | AC83: 0 | AD83: =+Z83-AC83 -> 0
A84: WIP 1 | B84: =C84&H84 -> 551244762762 | C84: 551244 | D84: IN Qualcomm MTP SM7750 CA90-28768-3 FRAME, WLAN AREA, MULTIPURPOSE | E84: 0 | F84: 0 | G84: =+E84+F84 -> 0 | H84: 762762 | I84: PC LGF 1308M 98309(BK) - PC +GF20% (LDS resin), resin) PC LGF 1308M(update:30%) | J84: Casting | K84: 0.0172 | L84: 1 | M84: KG | N84: =K84*(E84+F84) -> 0 | O84: 0 | P84: 127233.07 | Q84: =O84*P84 -> 0 | R84: 0 | S84: =VLOOKUP(C84,'Working Hours'!A:I,9,0)*G84 -> 0 | T84: =S84/SUM($S$7:$S$112) -> 0 | U84: =SUMIFS('Manufacturing Cost.'!N:N,'Manufacturing Cost.'!G:G,"622",'Manufacturing Cost.'!H:H,"0501")*T84 -> 0 | V84: =SUMIFS('Manufacturing Cost.'!N:N,'Manufacturing Cost.'!G:G,"627",'Manufacturing Cost.'!H:H,"0501")*T84 -> 0 | W84: =S84/SUM($S$7:$S$507) -> 0 | X84: =SUMIFS('Manufacturing Cost.'!N:N,'Manufacturing Cost.'!H:H,"indirect",'Manufacturing Cost.'!G:G,"627")*W84 -> 0 | Y84: =SUMIF(Outsoucing!D:D,C84,Outsoucing!J:J) -> 0 | Z84: =Q84+R84+U84+V84+X84+Y84 -> 0 | AA84: =IF(Z84<>0,(Z84/(E84+F84)),0) -> 0 | AC84: 0 | AD84: =+Z84-AC84 -> 0
A85: WIP 1 | B85: =C85&H85 -> 551245762762 | C85: 551245 | D85: IN Qualcomm KAANAPALI CA90-58184-2 CARRIER FRAME, ASSY | E85: 0 | F85: 0 | G85: =+E85+F85 -> 0 | H85: 762762 | I85: PC LGF 1308M 98309(BK) - PC +GF20% (LDS resin), resin) PC LGF 1308M(update:30%) | J85: Casting | K85: 0.07776 | L85: 1 | M85: KG | N85: =K85*(E85+F85) -> 0 | O85: 0 | P85: 127233.07 | Q85: =O85*P85 -> 0 | R85: 0 | S85: =VLOOKUP(C85,'Working Hours'!A:I,9,0)*G85 -> 0 | T85: =S85/SUM($S$7:$S$112) -> 0 | U85: =SUMIFS('Manufacturing Cost.'!N:N,'Manufacturing Cost.'!G:G,"622",'Manufacturing Cost.'!H:H,"0501")*T85 -> 0 | V85: =SUMIFS('Manufacturing Cost.'!N:N,'Manufacturing Cost.'!G:G,"627",'Manufacturing Cost.'!H:H,"0501")*T85 -> 0 | W85: =S85/SUM($S$7:$S$507) -> 0 | X85: =SUMIFS('Manufacturing Cost.'!N:N,'Manufacturing Cost.'!H:H,"indirect",'Manufacturing Cost.'!G:G,"627")*W85 -> 0 | Y85: =SUMIF(Outsoucing!D:D,C85,Outsoucing!J:J) -> 0 | Z85: =Q85+R85+U85+V85+X85+Y85 -> 0 | AA85: =IF(Z85<>0,(Z85/(E85+F85)),0) -> 0 | AC85: 0 | AD85: =+Z85-AC85 -> 0
A86: WIP 1 | B86: =C86&H86 -> 210411760011 | C86: 210411 | D86: CA SM-A376B | E86: 1096 | F86: 0 | G86: =+E86+F86 -> 1096 | H86: 760011 | I86: Aluminum alloy bar S36, Nhôm hợp kim dạng thanh S36 | J86: Casting | K86: 0.1871 | L86: 1 | M86: KG | N86: =K86*(E86+F86) -> 205.0616 | O86: 304.4848 | P86: 15519.439 | Q86: =O86*P86 -> 4725433.3 | R86: 0 | S86: =VLOOKUP(C86,'Working Hours'!A:I,9,0)*G86 -> 33.2088 | T86: =S86/SUM($S$7:$S$112) -> 0.00081825401 | U86: =SUMIFS('Manufacturing Cost.'!N:N,'Manufacturing Cost.'!G:G,"622",'Manufacturing Cost.'!H:H,"0501")*T86 -> 1627356.3 | V86: =SUMIFS('Manufacturing Cost.'!N:N,'Manufacturing Cost.'!G:G,"627",'Manufacturing Cost.'!H:H,"0501")*T86 -> 9145892.7 | W86: =S86/SUM($S$7:$S$507) -> 0.00012097818 | X86: =SUMIFS('Manufacturing Cost.'!N:N,'Manufacturing Cost.'!H:H,"indirect",'Manufacturing Cost.'!G:G,"627")*W86 -> 1367706.1 | Y86: =SUMIF(Outsoucing!D:D,C86,Outsoucing!J:J) -> 0 | Z86: =Q86+R86+U86+V86+X86+Y86 -> 16866388 | AA86: =IF(Z86<>0,(Z86/(E86+F86)),0) -> 15389.04 | AC86: 16866388 | AD86: =+Z86-AC86 -> 0
... A105: WIP 1 | B105: =C105&H105 -> 551255800786 | C105: 551255 | D105: IN Qualcomm MAILI 55-97051-1 ALTERED FRAME, CAMERA CARD COVER ASSY_PROCESS | E105: 1200 | F105: 0 | G105: =+E105+F105 -> 1200 | H105: 800786 | I105: Resin Lucky Enpla PC- LPC1001F 9306(BK), Hạt nhựa nguyên sinh Lucky Enpla PC- LPC1001F 9306(BK) | J105: Injection | K105: 0.0065 | L105: 1 | M105: KG | N105: =K105*(E105+F105) -> 7.8 | O105: 30.09903 | P105: 152445.57 | Q105: =O105*P105 -> 4588463.9 | R105: 1600328 | S105: =VLOOKUP(C105,'Working Hours'!A:I,9,0)*G105 -> 10.8 | T105: =S105/SUM($S$7:$S$112) -> 0.00026610848 | U105: =SUMIFS('Manufacturing Cost.'!N:N,'Manufacturing Cost.'!G:G,"622",'Manufacturing Cost.'!H:H,"0501")*T105 -> 529240.67 | V105: =SUMIFS('Manufacturing Cost.'!N:N,'Manufacturing Cost.'!G:G,"627",'Manufacturing Cost.'!H:H,"0501")*T105 -> 2974381.5 | W105: =S105/SUM($S$7:$S$507) -> 3.934392e-05 | X105: =SUMIFS('Manufacturing Cost.'!N:N,'Manufacturing Cost.'!H:H,"indirect",'Manufacturing Cost.'!G:G,"627")*W105 -> 444798.54 | Y105: =SUMIF(Outsoucing!D:D,C105,Outsoucing!J:J) -> 0 | Z105: =Q105+R105+U105+V105+X105+Y105 -> 10137213 | AA105: =IF(Z105<>0,(Z105/(E105+F105)),0) -> 8447.6772 | AC105: 10137213 | AD105: =+Z105-AC105 -> 0
A106: WIP 1 | B106: =C106&H106 -> 551222800450 | C106: 551222 | D106: IN Qualcomm ADP Ride Arnage(4.0) 50-36927-3 Inlet Bafle SOC 2 | E106: 100 | F106: 0 | G106: =+E106+F106 -> 100 | H106: 800450 | I106: Resin PC/ABS/HR5007A/BLACK, Hạt nhựa nguyên sinh màu đen PC/ABS/HR5007A | J106: Injection | K106: 0.0074 | L106: 1 | M106: KG | N106: =K106*(E106+F106) -> 0.74 | O106: 0.74 | P106: 34448.491 | Q106: =O106*P106 -> 25491.883 | R106: 92023.741 | S106: =VLOOKUP(C106,'Working Hours'!A:I,9,0)*G106 -> 1.11 | T106: =S106/SUM($S$7:$S$112) -> 2.7350038e-05 | U106: =SUMIFS('Manufacturing Cost.'!N:N,'Manufacturing Cost.'!G:G,"622",'Manufacturing Cost.'!H:H,"0501")*T106 -> 54394.18 | V106: =SUMIFS('Manufacturing Cost.'!N:N,'Manufacturing Cost.'!G:G,"627",'Manufacturing Cost.'!H:H,"0501")*T106 -> 305700.32 | W106: =S106/SUM($S$7:$S$507) -> 4.0436807e-06 | X106: =SUMIFS('Manufacturing Cost.'!N:N,'Manufacturing Cost.'!H:H,"indirect",'Manufacturing Cost.'!G:G,"627")*W106 -> 45715.405 | Y106: =SUMIF(Outsoucing!D:D,C106,Outsoucing!J:J) -> 0 | Z106: =Q106+R106+U106+V106+X106+Y106 -> 523325.53 | AA106: =IF(Z106<>0,(Z106/(E106+F106)),0) -> 5233.2553 | AC106: 523325.53
A107: WIP 1 | B107: =C107&H107 -> 551254800450 | C107: 551254 | D107: IN QualcommIDP CEDROS_55-PR954-80_ASSY, SUB-ASSY, REAR HOUSING | E107: 350 | F107: 0 | G107: =+E107+F107 -> 350 | H107: 800450 | I107: Resin PC/ABS/HR5007A/BLACK, Hạt nhựa nguyên sinh màu đen PC/ABS/HR5007A | J107: Injection | K107: 0.0507 | L107: 1 | M107: KG | N107: =K107*(E107+F107) -> 17.745 | O107: 17.745 | P107: 34448.491 | Q107: =O107*P107 -> 611288.46 | R107: 1465410.9 | S107: =VLOOKUP(C107,'Working Hours'!A:I,9,0)*G107 -> 6.79 | T107: =S107/SUM($S$7:$S$112) -> 0.00016730339 | U107: =SUMIFS('Manufacturing Cost.'!N:N,'Manufacturing Cost.'!G:G,"622",'Manufacturing Cost.'!H:H,"0501")*T107 -> 332735.57 | V107: =SUMIFS('Manufacturing Cost.'!N:N,'Manufacturing Cost.'!G:G,"627",'Manufacturing Cost.'!H:H,"0501")*T107 -> 1870004.7 | W107: =S107/SUM($S$7:$S$507) -> 2.4735669e-05 | X107: =SUMIFS('Manufacturing Cost.'!N:N,'Manufacturing Cost.'!H:H,"indirect",'Manufacturing Cost.'!G:G,"627")*W107 -> 279646.49 | Y107: =SUMIF(Outsoucing!D:D,C107,Outsoucing!J:J) -> 0 | Z107: =Q107+R107+U107+V107+X107+Y107 -> 4559086.1 | AA107: =IF(Z107<>0,(Z107/(E107+F107)),0) -> 13025.96 | AC107: 4559086.1
A108: WIP 1 | B108: =C108&H108 -> 551256763008 | C108: 551256 | D108: IN A 147-9222-001 SIDE SHIELD, LEFT,BUCK HMD | E108: 100 | F108: 0 | G108: =+E108+F108 -> 100 | H108: 763008 | I108: Resin Markrolon LQ3187/ Hạt nhựa Markrolon LQ3187 (NAT) | J108: Injection | K108: 0.0035 | L108: 1 | M108: KG | N108: =K108*(E108+F108) -> 0.35 | O108: 0.49 | P108: 439096.27 | Q108: =O108*P108 -> 215157.17 | R108: 326220.93 | S108: =VLOOKUP(C108,'Working Hours'!A:I,9,0)*G108 -> 1.94 | T108: =S108/SUM($S$7:$S$112) -> 4.7800968e-05 | U108: =SUMIFS('Manufacturing Cost.'!N:N,'Manufacturing Cost.'!G:G,"622",'Manufacturing Cost.'!H:H,"0501")*T108 -> 95067.305 | V108: =SUMIFS('Manufacturing Cost.'!N:N,'Manufacturing Cost.'!G:G,"627",'Manufacturing Cost.'!H:H,"0501")*T108 -> 534287.05 | W108: =S108/SUM($S$7:$S$507) -> 7.0673339e-06 | X108: =SUMIFS('Manufacturing Cost.'!N:N,'Manufacturing Cost.'!H:H,"indirect",'Manufacturing Cost.'!G:G,"627")*W108 -> 79898.997 | Y108: =SUMIF(Outsoucing!D:D,C108,Outsoucing!J:J) -> 0 | Z108: =Q108+R108+U108+V108+X108+Y108 -> 1250631.4 | AA108: =IF(Z108<>0,(Z108/(E108+F108)),0) -> 12506.314 | AC108: 1250631.4
A109: WIP 1 | B109: =C109&H109 -> 551257763008 | C109: 551257 | D109: IN A 147-9223-001 SIDE SHIELD, RIGHT,BUCK HMD | E109: 140 | F109: 0 | G109: =+E109+F109 -> 140 | H109: 763008 | I109: Resin Markrolon LQ3187/ Hạt nhựa Markrolon LQ3187 (NAT) | J109: Injection | K109: 0.0035 | L109: 1 | M109: KG | N109: =K109*(E109+F109) -> 0.49 | O109: 0.49 | P109: 439096.27 | Q109: =O109*P109 -> 215157.17 | R109: 694500.93 | S109: =VLOOKUP(C109,'Working Hours'!A:I,9,0)*G109 -> 2.716 | T109: =S109/SUM($S$7:$S$112) -> 6.6921355e-05 | U109: =SUMIFS('Manufacturing Cost.'!N:N,'Manufacturing Cost.'!G:G,"622",'Manufacturing Cost.'!H:H,"0501")*T109 -> 133094.23 | V109: =SUMIFS('Manufacturing Cost.'!N:N,'Manufacturing Cost.'!G:G,"627",'Manufacturing Cost.'!H:H,"0501")*T109 -> 748001.87 | W109: =S109/SUM($S$7:$S$507) -> 9.8942674e-06 | X109: =SUMIFS('Manufacturing Cost.'!N:N,'Manufacturing Cost.'!H:H,"indirect",'Manufacturing Cost.'!G:G,"627")*W109 -> 111858.6 | Y109: =SUMIF(Outsoucing!D:D,C109,Outsoucing!J:J) -> 0 | Z109: =Q109+R109+U109+V109+X109+Y109 -> 1902612.8 | AA109: =IF(Z109<>0,(Z109/(E109+F109)),0) -> 13590.091 | AC109: 1902612.8
A110: WIP 1 | B110: =C110&H110 -> 551258763995 | C110: 551258 | D110: IN A 150-6547-002 TEMPLE ARM, LEFT ,BUCK HMD | E110: 90 | F110: 0 | G110: =+E110+F110 -> 90 | H110: 763995 | I110: EMS-GRIVORY GRILAMID TR 90 NZ, 10% GLASS FILL, Tan499/Hạt nhựa Grilamid TR90, 10% Glass Fill, màu Tan499 | J110: Injection | K110: 0.00601 | L110: 1 | M110: KG | N110: =K110*(E110+F110) -> 0.5409 | O110: 3.8581 | P110: 0 | Q110: =O110*P110 -> 0 | R110: 60000 | S110: =VLOOKUP(C110,'Working Hours'!A:I,9,0)*G110 -> 1.125 | T110: =S110/SUM($S$7:$S$112) -> 2.7719633e-05 | U110: =SUMIFS('Manufacturing Cost.'!N:N,'Manufacturing Cost.'!G:G,"622",'Manufacturing Cost.'!H:H,"0501")*T110 -> 55129.236 | V110: =SUMIFS('Manufacturing Cost.'!N:N,'Manufacturing Cost.'!G:G,"627",'Manufacturing Cost.'!H:H,"0501")*T110 -> 309831.41 | W110: =S110/SUM($S$7:$S$507) -> 4.0983251e-06 | X110: =SUMIFS('Manufacturing Cost.'!N:N,'Manufacturing Cost.'!H:H,"indirect",'Manufacturing Cost.'!G:G,"627")*W110 -> 46333.181 | Y110: =SUMIF(Outsoucing!D:D,C110,Outsoucing!J:J) -> 0 | Z110: =Q110+R110+U110+V110+X110+Y110 -> 471293.82 | AA110: =IF(Z110<>0,(Z110/(E110+F110)),0) -> 5236.598 | AC110: 471293.82
A111: WIP 1 | B111: =C111&H111 -> 551259763995 | C111: 551259 | D111: IN A 150-6548-002 TEMPLE ARM, RIGHT ,BUCK HMD | E111: 90 | F111: 0 | G111: =+E111+F111 -> 90 | H111: 763995 | I111: EMS-GRIVORY GRILAMID TR 90 NZ, 10% GLASS FILL, Tan499/Hạt nhựa Grilamid TR90, 10% Glass Fill, màu Tan499 | J111: Injection | K111: 0.00601 | L111: 1 | M111: KG | N111: =K111*(E111+F111) -> 0.5409 | O111: 1.1419 | P111: 0 | Q111: =O111*P111 -> 0 | R111: 114000 | S111: =VLOOKUP(C111,'Working Hours'!A:I,9,0)*G111 -> 1.125 | T111: =S111/SUM($S$7:$S$112) -> 2.7719633e-05 | U111: =SUMIFS('Manufacturing Cost.'!N:N,'Manufacturing Cost.'!G:G,"622",'Manufacturing Cost.'!H:H,"0501")*T111 -> 55129.236 | V111: =SUMIFS('Manufacturing Cost.'!N:N,'Manufacturing Cost.'!G:G,"627",'Manufacturing Cost.'!H:H,"0501")*T111 -> 309831.41 | W111: =S111/SUM($S$7:$S$507) -> 4.0983251e-06 | X111: =SUMIFS('Manufacturing Cost.'!N:N,'Manufacturing Cost.'!H:H,"indirect",'Manufacturing Cost.'!G:G,"627")*W111 -> 46333.181 | Y111: =SUMIF(Outsoucing!D:D,C111,Outsoucing!J:J) -> 0 | Z111: =Q111+R111+U111+V111+X111+Y111 -> 525293.82 | AA111: =IF(Z111<>0,(Z111/(E111+F111)),0) -> 5836.598 | AC111: 525293.82
A113: TOTAL WIP1 | B113: =C113&H113 | E113: =SUM(E7:E112) -> 2701239 | F113: =SUM(F7:F112) -> 101071 | G113: =SUM(G7:G112) -> 2802310 | N113: =SUM(N7:N112) -> 812617.8 | O113: =SUM(O7:O112) -> 738825.74 | Q113: =SUM(Q7:Q112) -> 1.7818048e+10 | R113: =SUM(R7:R112) -> 6512668.5 | U113: =SUM(U7:U112) -> 1.9888155e+09 | V113: =SUM(V7:V112) -> 1.1177327e+10 | X113: =SUM(X7:X112) -> 1.6714933e+09 | Y113: =SUM(Y7:Y112) -> 212278388 | Z113: =SUM(Z7:Z112) -> 3.2874475e+10 | AB113: =SUM(AB7:AB98) -> 0 | AC113: 0
A114: WIP 2 | B114: =C114&H114 -> 301161210145 | C114: 301161 | D114: CNC LGIT Gen3 AL5 | E114: 68139 | F114: 8040 | G114: =+E114+F114 -> 76179 | H114: 210145 | I114: CA LGIT Gen3 AL5 | J114: CNC 1 | K114: 1 | L114: 1 | M114: PCS | N114: =K114*(E114+F114) -> 76179 | P114: =IF(AND(Z114<>0,G114<>0),Z114/G114,"") -> 37968.87 | Q114: 2.0717543e+09 | R114: 0 | S114: =VLOOKUP(C114,'Working Hours'!A:I,9,0)*G114 -> 3092.8674 | T114: =S114/SUM($S$114:$S$245) -> 0.061508563 | U114: =SUMIF('Re-allowcate'!C:C,C114,'Re-allowcate'!N:N) -> 1.467667e+08 | V114: =SUMIFS('Manufacturing Cost.'!N:N,'Manufacturing Cost.'!G:G,"627",'Manufacturing Cost.'!H:H,"CNC1")*T114+SUMIF('Re-allowcate'!C:C,C114,'Re-allowcate'!J:J) -> 5.465297e+08 | W114: =S114/SUM($S$7:$S$507) -> 0.011267179 | X114: =SUMIFS('Manufacturing Cost.'!N:N,'Manufacturing Cost.'!H:H,"indirect",'Manufacturing Cost.'!G:G,"627")*W114 -> 1.273799e+08 | Y114: =SUMIF(Outsoucing!D:D,C114,Outsoucing!J:J) -> 0 | Z114: =Q114+R114+U114+V114+X114+Y114 -> 2.8924306e+09 | AA114: =IF(Z114<>0,(Z114/(E114+F114)),0) -> 37968.87 | AB114: LG | AC114: 2.8924306e+09 | AD114: =+Z114-AC114 -> 0
A115: WIP 2 | B115: =C115&H115 -> 301178210148 | C115: 301178 | D115: CNC LGIT Gen 2 | E115: 0 | F115: 0 | G115: =+E115+F115 -> 0 | H115: 210148 | I115: CA LGIT Gen 2 | J115: CNC 1 | K115: 1 | L115: 1 | M115: PCS | N115: =K115*(E115+F115) -> 0 | P115: =IF(AND(Z115<>0,G115<>0),Z115/G115,"") | Q115: 0 | R115: 0 | S115: =VLOOKUP(C115,'Working Hours'!A:I,9,0)*G115 -> 0 | T115: =S115/SUM($S$114:$S$236) -> 0 | U115: =SUMIF('Re-allowcate'!C:C,C115,'Re-allowcate'!N:N) -> 0 | V115: =SUMIFS('Manufacturing Cost.'!N:N,'Manufacturing Cost.'!G:G,"627",'Manufacturing Cost.'!H:H,"CNC1")*T115+SUMIF('Re-allowcate'!C:C,C115,'Re-allowcate'!J:J) -> 0 | W115: =S115/SUM($S$7:$S$507) -> 0 | X115: =SUMIFS('Manufacturing Cost.'!N:N,'Manufacturing Cost.'!H:H,"indirect",'Manufacturing Cost.'!G:G,"627")*W115 -> 0 | Y115: =SUMIF(Outsoucing!D:D,C115,Outsoucing!J:J) -> 0 | Z115: =Q115+R115+U115+V115+X115+Y115 -> 0 | AA115: =IF(Z115<>0,(Z115/(E115+F115)),0) -> 0 | AB115: LG | AC115: 0 | AD115: =+Z115-AC115 -> 0
A116: WIP 2 | B116: =C116&H116 -> 301188210158 | C116: 301188 | D116: CNC OMS ENTRY_3CAC00250A VCSEL COVER | E116: 0 | F116: 0 | G116: =+E116+F116 -> 0 | H116: 210158 | I116: CA OMS ENTRY_3CAC00250A VCSEL COVER | J116: CNC 1 | K116: 1 | L116: 1 | M116: PCS | N116: =K116*(E116+F116) -> 0 | P116: =IF(AND(Z116<>0,G116<>0),Z116/G116,"") | Q116: 0 | R116: 0 | S116: =VLOOKUP(C116,'Working Hours'!A:I,9,0)*G116 -> 0 | T116: =S116/SUM($S$114:$S$236) -> 0 | U116: =SUMIF('Re-allowcate'!C:C,C116,'Re-allowcate'!N:N) -> 0 | V116: =SUMIFS('Manufacturing Cost.'!N:N,'Manufacturing Cost.'!G:G,"627",'Manufacturing Cost.'!H:H,"CNC1")*T116+SUMIF('Re-allowcate'!C:C,C116,'Re-allowcate'!J:J) -> 0 | W116: =S116/SUM($S$7:$S$507) -> 0 | X116: =SUMIFS('Manufacturing Cost.'!N:N,'Manufacturing Cost.'!H:H,"indirect",'Manufacturing Cost.'!G:G,"627")*W116 -> 0 | Y116: =SUMIF(Outsoucing!D:D,C116,Outsoucing!J:J) -> 0 | Z116: =Q116+R116+U116+V116+X116+Y116 -> 0 | AA116: =IF(Z116<>0,(Z116/(E116+F116)),0) -> 0 | AB116: 0 | AC116: 0 | AD116: =+Z116-AC116 -> 0
A117: WIP 2 | B117: =C117&H117 -> 301189210159 | C117: 301189 | D117: CNC OMS ENTRY LENS 3CAC00203A | E117: 0 | F117: 0 | G117: =+E117+F117 -> 0 | H117: 210159 | I117: CA OMS ENTRY LENS 3CAC00203A | J117: CNC 1 | K117: 1 | L117: 1 | M117: PCS | N117: =K117*(E117+F117) -> 0 | P117: =IF(AND(Z117<>0,G117<>0),Z117/G117,"") | Q117: 0 | R117: 0 | S117: =VLOOKUP(C117,'Working Hours'!A:I,9,0)*G117 -> 0 | T117: =S117/SUM($S$114:$S$236) -> 0 | U117: =SUMIF('Re-allowcate'!C:C,C117,'Re-allowcate'!N:N) -> 0 | V117: =SUMIFS('Manufacturing Cost.'!N:N,'Manufacturing Cost.'!G:G,"627",'Manufacturing Cost.'!H:H,"CNC1")*T117+SUMIF('Re-allowcate'!C:C,C117,'Re-allowcate'!J:J) -> 0 | W117: =S117/SUM($S$7:$S$507) -> 0 | X117: =SUMIFS('Manufacturing Cost.'!N:N,'Manufacturing Cost.'!H:H,"indirect",'Manufacturing Cost.'!G:G,"627")*W117 -> 0 | Y117: =SUMIF(Outsoucing!D:D,C117,Outsoucing!J:J) -> 0 | Z117: =Q117+R117+U117+V117+X117+Y117 -> 0 | AA117: =IF(Z117<>0,(Z117/(E117+F117)),0) -> 0 | AB117: 0 | AC117: 0 | AD117: =+Z117-AC117 -> 0
A118: WIP 2 | B118: =C118&H118 -> 301341210171 | C118: 301341 | D118: CNC ZF TRW - GM EU2L Housing A021D074 | E118: 49694 | F118: 851 | G118: =+E118+F118 -> 50545 | H118: 210171 | I118: CA LGIT TRW-GMT1XX Housing | J118: CNC 1 | K118: 1 | L118: 1 | M118: PCS | N118: =K118*(E118+F118) -> 50545 | P118: =IF(AND(Z118<>0,G118<>0),Z118/G118,"") -> 16152.401 | Q118: 6.9084515e+08 | R118: 0 | S118: =VLOOKUP(C118,'Working Hours'!A:I,9,0)*G118 -> 561.0495 | T118: =S118/SUM($S$114:$S$245) -> 0.01115772 | U118: =SUMIF('Re-allowcate'!C:C,C118,'Re-allowcate'!N:N) -> 36140888 | V118: =SUMIFS('Manufacturing Cost.'!N:N,'Manufacturing Cost.'!G:G,"627",'Manufacturing Cost.'!H:H,"CNC1")*T118+SUMIF('Re-allowcate'!C:C,C118,'Re-allowcate'!J:J) -> 66330193 | W118: =S118/SUM($S$7:$S$507) -> 0.0020438784 | X118: =SUMIFS('Manufacturing Cost.'!N:N,'Manufacturing Cost.'!H:H,"indirect",'Manufacturing Cost.'!G:G,"627")*W118 -> 23106852 | Y118: =SUMIF(Outsoucing!D:D,C118,Outsoucing!J:J) -> 0 | Z118: =Q118+R118+U118+V118+X118+Y118 -> 8.1642309e+08 | AA118: =IF(Z118<>0,(Z118/(E118+F118)),0) -> 16152.401 | AB118: ZF | AC118: 8.1642309e+08 | AD118: =+Z118-AC118 -> 0
A119: WIP 2 | B119: =C119&H119 -> 301343210172 | C119: 301343 | D119: CNC TRW-Nissan/FCA/GMT 4.8 Lenmount | E119: 269857 | F119: 2795 | G119: =+E119+F119 -> 272652 | H119: 210172 | I119: CA ZF TRW-Nissan/FCA/GMT 4.8 Lenmount | J119: CNC 1 | K119: 1 | L119: 1 | M119: PCS | N119: =K119*(E119+F119) -> 272652 | P119: =IF(AND(Z119<>0,G119<>0),Z119/G119,"") -> 6658.1235 | Q119: 1.2429058e+09 | R119: 0 | S119: =VLOOKUP(C119,'Working Hours'!A:I,9,0)*G119 -> 2263.0116 | T119: =S119/SUM($S$114:$S$245) -> 0.045005031 | U119: =SUMIF('Re-allowcate'!C:C,C119,'Re-allowcate'!N:N) -> 1.9495272e+08 | V119: =SUMIFS('Manufacturing Cost.'!N:N,'Manufacturing Cost.'!G:G,"627",'Manufacturing Cost.'!H:H,"CNC1")*T119+SUMIF('Re-allowcate'!C:C,C119,'Re-allowcate'!J:J) -> 2.8428989e+08 | W119: =S119/SUM($S$7:$S$507) -> 0.0082440508 | X119: =SUMIFS('Manufacturing Cost.'!N:N,'Manufacturing Cost.'!H:H,"indirect",'Manufacturing Cost.'!G:G,"627")*W119 -> 93202245 | Y119: =SUMIF(Outsoucing!D:D,C119,Outsoucing!J:J) -> 0 | Z119: =Q119+R119+U119+V119+X119+Y119 -> 1.8153507e+09 | AA119: =IF(Z119<>0,(Z119/(E119+F119)),0) -> 6658.1235 | AB119: ZF | AC119: 1.8153507e+09 | AD119: =+Z119-AC119 -> 0
A120: WIP 2 | B120: =C120&H120 -> 301397210191 | C120: 301397 | D120: CNC LGIT OMS Front 3CAC00207A | E120: 0 | F120: 0 | G120: =+E120+F120 -> 0 | H120: 210191 | I120: CA LGIT OMS Front 3CAC00207A | J120: CNC 1 | K120: 1 | L120: 1 | M120: PCS | N120: =K120*(E120+F120) -> 0 | P120: =IF(AND(Z120<>0,G120<>0),Z120/G120,"") | Q120: 0 | R120: 0 | S120: =VLOOKUP(C120,'Working Hours'!A:I,9,0)*G120 -> 0 | T120: =S120/SUM($S$114:$S$236) -> 0 | U120: =SUMIF('Re-allowcate'!C:C,C120,'Re-allowcate'!N:N) -> 0 | V120: =SUMIFS('Manufacturing Cost.'!N:N,'Manufacturing Cost.'!G:G,"627",'Manufacturing Cost.'!H:H,"CNC1")*T120+SUMIF('Re-allowcate'!C:C,C120,'Re-allowcate'!J:J) -> 0 | W120: =S120/SUM($S$7:$S$507) -> 0 | X120: =SUMIFS('Manufacturing Cost.'!N:N,'Manufacturing Cost.'!H:H,"indirect",'Manufacturing Cost.'!G:G,"627")*W120 -> 0 | Y120: =SUMIF(Outsoucing!D:D,C120,Outsoucing!J:J) -> 0 | Z120: =Q120+R120+U120+V120+X120+Y120 -> 0 | AA120: =IF(Z120<>0,(Z120/(E120+F120)),0) -> 0 | AC120: 0 | AD120: =+Z120-AC120 -> 0
A121: WIP 2 | B121: =C121&H121 -> 301409210302 | C121: 301409 | D121: CNC Mando NX4 Motor Housing | E121: 48000 | F121: 2462 | G121: =+E121+F121 -> 50462 | H121: 210302 | I121: CA Mando NX4 Motor housing | J121: CNC 1 | K121: 1 | L121: 1 | M121: PCS | N121: =K121*(E121+F121) -> 50462 | P121: =IF(AND(Z121<>0,G121<>0),Z121/G121,"") -> 50451.901 | Q121: 1.7430247e+09 | R121: 0 | S121: =VLOOKUP(C121,'Working Hours'!A:I,9,0)*G121 -> 5227.8632 | T121: =S121/SUM($S$114:$S$245) -> 0.10396771 | U121: =SUMIF('Re-allowcate'!C:C,C121,'Re-allowcate'!N:N) -> 56714197 | V121: =SUMIFS('Manufacturing Cost.'!N:N,'Manufacturing Cost.'!G:G,"627",'Manufacturing Cost.'!H:H,"CNC1")*T121+SUMIF('Re-allowcate'!C:C,C121,'Re-allowcate'!J:J) -> 5.3085505e+08 | W121: =S121/SUM($S$7:$S$507) -> 0.019044874 | X121: =SUMIFS('Manufacturing Cost.'!N:N,'Manufacturing Cost.'!H:H,"indirect",'Manufacturing Cost.'!G:G,"627")*W121 -> 2.1530981e+08 | Y121: =SUMIF(Outsoucing!D:D,C121,Outsoucing!J:J) -> 0 | Z121: =Q121+R121+U121+V121+X121+Y121 -> 2.5459038e+09 | AA121: =IF(Z121<>0,(Z121/(E121+F121)),0) -> 50451.901 | AB121: MANDO | AC121: 2.5459038e+09 | AD121: =+Z121-AC121 -> 0
A122: WIP 2 | B122: =C122&H122 -> 301415210311 | C122: 301415 | D122: CNC ZF IPM Housing A010R190 (2) | E122: 19757 | F122: 895 | G122: =+E122+F122 -> 20652 | H122: 210311 | I122: CA ZF IPM Housing A010R190 (2) | J122: CNC 1 | K122: 1 | L122: 1 | M122: PCS | N122: =K122*(E122+F122) -> 20652 | P122: =IF(AND(Z122<>0,G122<>0),Z122/G122,"") -> 17666.308 | Q122: 2.6924422e+08 | R122: 0 | S122: =VLOOKUP(C122,'Working Hours'!A:I,9,0)*G122 -> 551.4084 | T122: =S122/SUM($S$114:$S$245) -> 0.010965985 | U122: =SUMIF('Re-allowcate'!C:C,C122,'Re-allowcate'!N:N) -> 14766676 | V122: =SUMIFS('Manufacturing Cost.'!N:N,'Manufacturing Cost.'!G:G,"627",'Manufacturing Cost.'!H:H,"CNC1")*T122+SUMIF('Re-allowcate'!C:C,C122,'Re-allowcate'!J:J) -> 58123913 | W122: =S122/SUM($S$7:$S$507) -> 0.0020087563 | X122: =SUMIFS('Manufacturing Cost.'!N:N,'Manufacturing Cost.'!H:H,"indirect",'Manufacturing Cost.'!G:G,"627")*W122 -> 22709782 | Y122: =SUMIF(Outsoucing!D:D,C122,Outsoucing!J:J) -> 0 | Z122: =Q122+R122+U122+V122+X122+Y122 -> 3.6484459e+08 | AA122: =IF(Z122<>0,(Z122/(E122+F122)),0) -> 17666.308 | AB122: ZF | AC122: 3.6484459e+08 | AD122: =+Z122-AC122 -> 0
A123: WIP 2 | B123: =C123&H123 -> 301443210327 | C123: 301443 | D123: CNC Mando NX4 Cover | E123: 61153 | F123: 3734 | G123: =+E123+F123 -> 64887 | H123: 210327 | I123: CA Mando N3 Motor & Heatsink Cover | J123: CNC 1 | K123: 1 | L123: 1 | M123: PCS | N123: =K123*(E123+F123) -> 64887 | P123: =IF(AND(Z123<>0,G123<>0),Z123/G123,"") -> 21108.638 | Q123: 9.4922875e+08 | R123: 0 | S123: =VLOOKUP(C123,'Working Hours'!A:I,9,0)*G123 -> 2271.045 | T123: =S123/SUM($S$114:$S$245) -> 0.045164793 | U123: =SUMIF('Re-allowcate'!C:C,C123,'Re-allowcate'!N:N) -> 72926442 | V123: =SUMIFS('Manufacturing Cost.'!N:N,'Manufacturing Cost.'!G:G,"627",'Manufacturing Cost.'!H:H,"CNC1")*T123+SUMIF('Re-allowcate'!C:C,C123,'Re-allowcate'!J:J) -> 2.5398791e+08 | W123: =S123/SUM($S$7:$S$507) -> 0.0082733161 | X123: =SUMIFS('Manufacturing Cost.'!N:N,'Manufacturing Cost.'!H:H,"indirect",'Manufacturing Cost.'!G:G,"627")*W123 -> 93533101 | Y123: =SUMIF(Outsoucing!D:D,C123,Outsoucing!J:J) -> 0 | Z123: =Q123+R123+U123+V123+X123+Y123 -> 1.3696762e+09 | AA123: =IF(Z123<>0,(Z123/(E123+F123)),0) -> 21108.638 | AB123: MANDO | AC123: 1.3696762e+09 | AD123: =+Z123-AC123 -> 0
A124: WIP 2 | B124: =C124&H124 -> 301449210332 | C124: 301449 | D124: CNC LGIT T6 Bearing Plate 3CVC00004A | E124: 24226 | F124: 595 | G124: =+E124+F124 -> 24821 | H124: 210332 | I124: CA LGIT T6 Bearing Plate 3CVC00004A | J124: CNC 1 | K124: 1 | L124: 1 | M124: PCS | N124: =K124*(E124+F124) -> 24821 | P124: =IF(AND(Z124<>0,G124<>0),Z124/G124,"") -> 20645.546 | Q124: 2.8019319e+08 | R124: 0 | S124: =VLOOKUP(C124,'Working Hours'!A:I,9,0)*G124 -> 752.0763 | T124: =S124/SUM($S$114:$S$245) -> 0.014956714 | U124: =SUMIF('Re-allowcate'!C:C,C124,'Re-allowcate'!N:N) -> 47820216 | V124: =SUMIFS('Manufacturing Cost.'!N:N,'Manufacturing Cost.'!G:G,"627",'Manufacturing Cost.'!H:H,"CNC1")*T124+SUMIF('Re-allowcate'!C:C,C124,'Re-allowcate'!J:J) -> 1.5345539e+08 | W124: =S124/SUM($S$7:$S$507) -> 0.0027397806 | X124: =SUMIFS('Manufacturing Cost.'!N:N,'Manufacturing Cost.'!H:H,"indirect",'Manufacturing Cost.'!G:G,"627")*W124 -> 30974300 | Y124: =SUMIF(Outsoucing!D:D,C124,Outsoucing!J:J) -> 0 | Z124: =Q124+R124+U124+V124+X124+Y124 -> 5.1244309e+08 | AA124: =IF(Z124<>0,(Z124/(E124+F124)),0) -> 20645.546 | AB124: LG | AC124: 5.1244309e+08 | AD124: =+Z124-AC124 -> 0
A125: WIP 2 | B125: =C125&H125 -> 301450210333 | C125: 301450 | D125: CNC LGIT T6M6 Housing 3HUC00006A | E125: 3442 | F125: 165 | G125: =+E125+F125 -> 3607 | H125: 210333 | I125: CA LGIT T6M6 Housing 3HUC00006A | J125: CNC 1 | K125: 1 | L125: 1 | M125: PCS | N125: =K125*(E125+F125) -> 3607 | P125: =IF(AND(Z125<>0,G125<>0),Z125/G125,"") -> 89281.776 | Q125: 2.4608953e+08 | R125: 0 | S125: =VLOOKUP(C125,'Working Hours'!A:I,9,0)*G125 -> 416.2478 | T125: =S125/SUM($S$114:$S$245) -> 0.0082780154 | U125: =SUMIF('Re-allowcate'!C:C,C125,'Re-allowcate'!N:N) -> 6949257.5 | V125: =SUMIFS('Manufacturing Cost.'!N:N,'Manufacturing Cost.'!G:G,"627",'Manufacturing Cost.'!H:H,"CNC1")*T125+SUMIF('Re-allowcate'!C:C,C125,'Re-allowcate'!J:J) -> 51857389 | W125: =S125/SUM($S$7:$S$507) -> 0.0015163723 | X125: =SUMIFS('Manufacturing Cost.'!N:N,'Manufacturing Cost.'!H:H,"indirect",'Manufacturing Cost.'!G:G,"627")*W125 -> 17143186 | Y125: =SUMIF(Outsoucing!D:D,C125,Outsoucing!J:J) -> 0 | Z125: =Q125+R125+U125+V125+X125+Y125 -> 3.2203937e+08 | AA125: =IF(Z125<>0,(Z125/(E125+F125)),0) -> 89281.776 | AB125: LG | AC125: 3.2203937e+08 | AD125: =+Z125-AC125 -> 0
A126: WIP 2 | B126: =C126&H126 -> 301469210340 | C126: 301469 | D126: CNC LGIT MQ4a PE Cover | E126: 25618 | F126: 969 | G126: =+E126+F126 -> 26587 | H126: 210340 | I126: CA LGIT MQ4a PE Cover | J126: CNC 1 | K126: 1 | L126: 1 | M126: PCS | N126: =K126*(E126+F126) -> 26587 | P126: =IF(AND(Z126<>0,G126<>0),Z126/G126,"") -> 18454.537 | Q126: 2.1044269e+08 | R126: 0 | S126: =VLOOKUP(C126,'Working Hours'!A:I,9,0)*G126 -> 1034.2343 | T126: =S126/SUM($S$114:$S$245) -> 0.020568055 | U126: =SUMIF('Re-allowcate'!C:C,C126,'Re-allowcate'!N:N) -> 51222597 | V126: =SUMIFS('Manufacturing Cost.'!N:N,'Manufacturing Cost.'!G:G,"627",'Manufacturing Cost.'!H:H,"CNC1")*T126+SUMIF('Re-allowcate'!C:C,C126,'Re-allowcate'!J:J) -> 1.8639049e+08 | W126: =S126/SUM($S$7:$S$507) -> 0.0037676696 | X126: =SUMIFS('Manufacturing Cost.'!N:N,'Manufacturing Cost.'!H:H,"indirect",'Manufacturing Cost.'!G:G,"627")*W126 -> 42594991 | Y126: =SUMIF(Outsoucing!D:D,C126,Outsoucing!J:J) -> 0 | Z126: =Q126+R126+U126+V126+X126+Y126 -> 4.9065077e+08 | AA126: =IF(Z126<>0,(Z126/(E126+F126)),0) -> 18454.537 | AB126: LG | AC126: 4.9065077e+08 | AD126: =+Z126-AC126 -> 0
A127: WIP 2 | B127: =C127&H127 -> 301489551183 | C127: 301489 | D127: CNC Qualcomm IDP Fillmore 50-PR727-3 Battery Door | E127: 300 | F127: 0 | G127: =+E127+F127 -> 300 | H127: 551183 | I127: IN Qualcomm IDP Fillmore 50-PR727-3 Batt | J127: CNC 1 | K127: 1 | L127: 1 | M127: PCS | N127: =K127*(E127+F127) -> 300 | P127: =IF(AND(Z127<>0,G127<>0),Z127/G127,"") -> 11300.847 | Q127: 2356210.3 | R127: 0 | S127: =VLOOKUP(C127,'Working Hours'!A:I,9,0)*G127 -> 5.43 | T127: =S127/SUM($S$114:$S$245) -> 0.00010798765 | U127: =SUMIF('Re-allowcate'!C:C,C127,'Re-allowcate'!N:N) -> 214507.2 | V127: =SUMIFS('Manufacturing Cost.'!N:N,'Manufacturing Cost.'!G:G,"627",'Manufacturing Cost.'!H:H,"CNC1")*T127+SUMIF('Re-allowcate'!C:C,C127,'Re-allowcate'!J:J) -> 595901.76 | W127: =S127/SUM($S$7:$S$507) -> 1.9781249e-05 | X127: =SUMIFS('Manufacturing Cost.'!N:N,'Manufacturing Cost.'!H:H,"indirect",'Manufacturing Cost.'!G:G,"627")*W127 -> 223634.82 | Y127: =SUMIF(Outsoucing!D:D,C127,Outsoucing!J:J) -> 0 | Z127: =Q127+R127+U127+V127+X127+Y127 -> 3390254.1 | AA127: =IF(Z127<>0,(Z127/(E127+F127)),0) -> 11300.847 | AB127: ZF | AC127: 3390254.1 | AD127: =+Z127-AC127 -> 0
A128: WIP 2 | B128: =C128&H128 -> 301498210343 | C128: 301498 | D128: CNC ZF GM ACP2 Housing A020R331 (A0038A6898)/A020R330(A0038A6008) | E128: 32460 | F128: 1792 | G128: =+E128+F128 -> 34252 | H128: 210343 | I128: CA ZF-GM ACP2 Housing A020R331 (A0038A6898)/A020R330 (A0038A6008) | J128: CNC 1 | K128: 1 | L128: 1 | M128: PCS | N128: =K128*(E128+F128) -> 34252 | P128: =IF(AND(Z128<>0,G128<>0),Z128/G128,"") -> 14319.747 | Q128: 3.3992873e+08 | R128: 0 | S128: =VLOOKUP(C128,'Working Hours'!A:I,9,0)*G128 -> 856.3 | T128: =S128/SUM($S$114:$S$245) -> 0.017029434 | U128: =SUMIF('Re-allowcate'!C:C,C128,'Re-allowcate'!N:N) -> 24491002 | V128: =SUMIFS('Manufacturing Cost.'!N:N,'Manufacturing Cost.'!G:G,"627",'Manufacturing Cost.'!H:H,"CNC1")*T128+SUMIF('Re-allowcate'!C:C,C128,'Re-allowcate'!J:J) -> 90793470 | W128: =S128/SUM($S$7:$S$507) -> 0.0031194629 | X128: =SUMIFS('Manufacturing Cost.'!N:N,'Manufacturing Cost.'!H:H,"indirect",'Manufacturing Cost.'!G:G,"627")*W128 -> 35266758 | Y128: =SUMIF(Outsoucing!D:D,C128,Outsoucing!J:J) -> 0 | Z128: =Q128+R128+U128+V128+X128+Y128 -> 4.9047996e+08 | AA128: =IF(Z128<>0,(Z128/(E128+F128)),0) -> 14319.747 | AB128: ZF | AC128: 4.9047996e+08 | AD128: =+Z128-AC128 -> 0
A129: WIP 2 | B129: =C129&H129 -> 301500210346 | C129: 301500 | D129: CNC ZF Handle Bar 606-60012 | E129: 0 | F129: 0 | G129: =+E129+F129 -> 0 | H129: 210346 | I129: CA ZF Handle Bar 606-60012 | J129: CNC 1 | K129: 1 | L129: 1 | M129: PCS | N129: =K129*(E129+F129) -> 0 | P129: =IF(AND(Z129<>0,G129<>0),Z129/G129,"") | Q129: 0 | R129: 0 | S129: =VLOOKUP(C129,'Working Hours'!A:I,9,0)*G129 -> 0 | T129: =S129/SUM($S$114:$S$236) -> 0 | U129: =SUMIF('Re-allowcate'!C:C,C129,'Re-allowcate'!N:N) -> 0 | V129: =SUMIFS('Manufacturing Cost.'!N:N,'Manufacturing Cost.'!G:G,"627",'Manufacturing Cost.'!H:H,"CNC1")*T129+SUMIF('Re-allowcate'!C:C,C129,'Re-allowcate'!J:J) -> 0 | W129: =S129/SUM($S$7:$S$507) -> 0 | X129: =SUMIFS('Manufacturing Cost.'!N:N,'Manufacturing Cost.'!H:H,"indirect",'Manufacturing Cost.'!G:G,"627")*W129 -> 0 | Y129: =SUMIF(Outsoucing!D:D,C129,Outsoucing!J:J) -> 0 | Z129: =Q129+R129+U129+V129+X129+Y129 -> 0 | AA129: =IF(Z129<>0,(Z129/(E129+F129)),0) -> 0 | AB129: 0 | AC129: 0 | AD129: =+Z129-AC129 -> 0
A130: WIP 2 | B130: =C130&H130 -> 301511210350 | C130: 301511 | D130: CNC LGIT MQ4a PE Housing 3CAZ00039A | E130: 36684 | F130: 1819 | G130: =+E130+F130 -> 38503 | H130: 210350 | I130: CA LGIT MQ4a PE Housing 3CAZ00039A | J130: CNC 1 | K130: 1 | L130: 1 | M130: PCS | N130: =K130*(E130+F130) -> 38503 | P130: =IF(AND(Z130<>0,G130<>0),Z130/G130,"") -> 74703.781 | Q130: 2.2969067e+09 | R130: 0 | S130: =VLOOKUP(C130,'Working Hours'!A:I,9,0)*G130 -> 2760.6651 | T130: =S130/SUM($S$114:$S$245) -> 0.05490198 | U130: =SUMIF('Re-allowcate'!C:C,C130,'Re-allowcate'!N:N) -> 74180000 | V130: =SUMIFS('Manufacturing Cost.'!N:N,'Manufacturing Cost.'!G:G,"627",'Manufacturing Cost.'!H:H,"CNC1")*T130+SUMIF('Re-allowcate'!C:C,C130,'Re-allowcate'!J:J) -> 3.9153484e+08 | W130: =S130/SUM($S$7:$S$507) -> 0.01005698 | X130: =SUMIFS('Manufacturing Cost.'!N:N,'Manufacturing Cost.'!H:H,"indirect",'Manufacturing Cost.'!G:G,"627")*W130 -> 1.1369813e+08 | Y130: =SUMIF(Outsoucing!D:D,C130,Outsoucing!J:J) -> 0 | Z130: =Q130+R130+U130+V130+X130+Y130 -> 2.8763197e+09 | AA130: =IF(Z130<>0,(Z130/(E130+F130)),0) -> 74703.781 | AB130: LG | AC130: 2.8763197e+09 | AD130: =+Z130-AC130 -> 0
A131: WIP 2 | B131: =C131&H131 -> 301520210178 | C131: 301520 | D131: CNC LIGT MPC5.5 Cover Lens 3HDC00003A | E131: 138504 | F131: 5648 | G131: =+E131+F131 -> 144152 | H131: 210178 | I131: CA LGIT MPC5.5 Cover lens 3HDC00003A | J131: CNC 1 | K131: 1 | L131: 1 | M131: PCS | N131: =K131*(E131+F131) -> 144152 | P131: =IF(AND(Z131<>0,G131<>0),Z131/G131,"") -> 11620.299 | Q131: 7.0081089e+08 | R131: 0 | S131: =VLOOKUP(C131,'Working Hours'!A:I,9,0)*G131 -> 1643.3328 | T131: =S131/SUM($S$114:$S$245) -> 0.032681336 | U131: =SUMIF('Re-allowcate'!C:C,C131,'Re-allowcate'!N:N) -> 2.7772369e+08 | V131: =SUMIFS('Manufacturing Cost.'!N:N,'Manufacturing Cost.'!G:G,"627",'Manufacturing Cost.'!H:H,"CNC1")*T131+SUMIF('Re-allowcate'!C:C,C131,'Re-allowcate'!J:J) -> 6.2887401e+08 | W131: =S131/SUM($S$7:$S$507) -> 0.0059865884 | X131: =SUMIFS('Manufacturing Cost.'!N:N,'Manufacturing Cost.'!H:H,"indirect",'Manufacturing Cost.'!G:G,"627")*W131 -> 67680743 | Y131: =SUMIF(Outsoucing!D:D,C131,Outsoucing!J:J) -> 0 | Z131: =Q131+R131+U131+V131+X131+Y131 -> 1.6750893e+09 | AA131: =IF(Z131<>0,(Z131/(E131+F131)),0) -> 11620.299 | AB131: LG | AC131: 1.6750893e+09 | AD131: =+Z131-AC131 -> 0
A132: WIP 2 | B132: =C132&H132 -> 301537210323 | C132: 301537 | D132: CNC Mando MAS65C 4.5 Heat Sink(2) | E132: 104769 | F132: 0 | G132: =+E132+F132 -> 104769 | H132: 210323 | I132: CA Mando MAS65C 4.5 Heat Sink | J132: CNC 1 | K132: 1 | L132: 1 | M132: PCS | N132: =K132*(E132+F132) -> 104769 | P132: =IF(AND(Z132<>0,G132<>0),Z132/G132,"") -> 18874.153 | Q132: 1.4060498e+09 | R132: 0 | S132: =VLOOKUP(C132,'Working Hours'!A:I,9,0)*G132 -> 1382.9508 | T132: =S132/SUM($S$114:$S$245) -> 0.02750306 | U132: =SUMIF('Re-allowcate'!C:C,C132,'Re-allowcate'!N:N) -> 1.1774979e+08 | V132: =SUMIFS('Manufacturing Cost.'!N:N,'Manufacturing Cost.'!G:G,"627",'Manufacturing Cost.'!H:H,"CNC1")*T132+SUMIF('Re-allowcate'!C:C,C132,'Re-allowcate'!J:J) -> 1.9017248e+08 | W132: =S132/SUM($S$7:$S$507) -> 0.0050380284 | X132: =SUMIFS('Manufacturing Cost.'!N:N,'Manufacturing Cost.'!H:H,"indirect",'Manufacturing Cost.'!G:G,"627")*W132 -> 56956898 | Y132: =SUMIF(Outsoucing!D:D,C132,Outsoucing!J:J) -> 206497200 | Z132: =Q132+R132+U132+V132+X132+Y132 -> 1.9774262e+09 | AA132: =IF(Z132<>0,(Z132/(E132+F132)),0) -> 18874.153 | AB132: MANDO | AC132: 1.9774262e+09 | AD132: =+Z132-AC132 -> 0
A133: WIP 2 | B133: =C133&H133 -> 301538210334 | C133: 301538 | D133: CNC Mando Brose IMEB2 Housing(2) | E133: 47575 | F133: 3552 | G133: =+E133+F133 -> 51127 | H133: 210334 | I133: CA Mando Brose IMEB2 Housing | J133: CNC 1 | K133: 1 | L133: 1 | M133: PCS | N133: =K133*(E133+F133) -> 51127 | P133: =IF(AND(Z133<>0,G133<>0),Z133/G133,"") -> 43423.814 | Q133: 1.6329957e+09 | R133: 0 | S133: =VLOOKUP(C133,'Working Hours'!A:I,9,0)*G133 -> 3650.4678 | T133: =S133/SUM($S$114:$S$245) -> 0.07259769 | U133: =SUMIF('Re-allowcate'!C:C,C133,'Re-allowcate'!N:N) -> 57461590 | V133: =SUMIFS('Manufacturing Cost.'!N:N,'Manufacturing Cost.'!G:G,"627",'Manufacturing Cost.'!H:H,"CNC1")*T133+SUMIF('Re-allowcate'!C:C,C133,'Re-allowcate'!J:J) -> 3.7932737e+08 | W133: =S133/SUM($S$7:$S$507) -> 0.013298492 | X133: =SUMIFS('Manufacturing Cost.'!N:N,'Manufacturing Cost.'!H:H,"indirect",'Manufacturing Cost.'!G:G,"627")*W133 -> 1.503447e+08 | Y133: =SUMIF(Outsoucing!D:D,C133,Outsoucing!J:J) -> 0 | Z133: =Q133+R133+U133+V133+X133+Y133 -> 2.2201293e+09 | AA133: =IF(Z133<>0,(Z133/(E133+F133)),0) -> 43423.814 | AB133: MANDO | AC133: 2.2201293e+09 | AD133: =+Z133-AC133 -> 0
A134: WIP 2 | B134: =C134&H134 -> 301569210364 | C134: 301569 | D134: CNC LGIT 3CAZ00041A CL4 Housing | E134: 74113 | F134: 1708 | G134: =+E134+F134 -> 75821 | H134: 210364 | I134: CA LGIT 3CAZ00041A CL4 Housing | J134: CNC 1 | K134: 1 | L134: 1 | M134: PCS | N134: =K134*(E134+F134) -> 75821 | P134: =IF(AND(Z134<>0,G134<>0),Z134/G134,"") -> 50226.485 | Q134: 2.6953726e+09 | R134: 0 | S134: =VLOOKUP(C134,'Working Hours'!A:I,9,0)*G134 -> 5231.649 | T134: =S134/SUM($S$114:$S$245) -> 0.104043 | U134: =SUMIF('Re-allowcate'!C:C,C134,'Re-allowcate'!N:N) -> 1.4607698e+08 | V134: =SUMIFS('Manufacturing Cost.'!N:N,'Manufacturing Cost.'!G:G,"627",'Manufacturing Cost.'!H:H,"CNC1")*T134+SUMIF('Re-allowcate'!C:C,C134,'Re-allowcate'!J:J) -> 7.5130703e+08 | W134: =S134/SUM($S$7:$S$507) -> 0.019058665 | X134: =SUMIFS('Manufacturing Cost.'!N:N,'Manufacturing Cost.'!H:H,"indirect",'Manufacturing Cost.'!G:G,"627")*W134 -> 2.1546572e+08 | Y134: =SUMIF(Outsoucing!D:D,C134,Outsoucing!J:J) -> 0 | Z134: =Q134+R134+U134+V134+X134+Y134 -> 3.8082223e+09 | AA134: =IF(Z134<>0,(Z134/(E134+F134)),0) -> 50226.485 | AB134: LG | AC134: 3.8082223e+09 | AD134: =+Z134-AC134 -> 0
A135: WIP 2 | B135: =C135&H135 -> 301570210365 | C135: 301570 | D135: CNC LGIT 3CAZ00042A CL4 Cover | E135: 17451 | F135: 1757 | G135: =+E135+F135 -> 19208 | H135: 210365 | I135: CA LGIT 3CAZ00042A CL4 Cover | J135: CNC 1 | K135: 1 | L135: 1 | M135: PCS | N135: =K135*(E135+F135) -> 19208 | P135: =IF(AND(Z135<>0,G135<>0),Z135/G135,"") -> 24416.367 | Q135: 2.5546019e+08 | R135: 0 | S135: =VLOOKUP(C135,'Working Hours'!A:I,9,0)*G135 -> 827.8648 | T135: =S135/SUM($S$114:$S$245) -> 0.016463937 | U135: =SUMIF('Re-allowcate'!C:C,C135,'Re-allowcate'!N:N) -> 37006193 | V135: =SUMIFS('Manufacturing Cost.'!N:N,'Manufacturing Cost.'!G:G,"627",'Manufacturing Cost.'!H:H,"CNC1")*T135+SUMIF('Re-allowcate'!C:C,C135,'Re-allowcate'!J:J) -> 1.4242754e+08 | W135: =S135/SUM($S$7:$S$507) -> 0.0030158747 | X135: =SUMIFS('Manufacturing Cost.'!N:N,'Manufacturing Cost.'!H:H,"indirect",'Manufacturing Cost.'!G:G,"627")*W135 -> 34095653 | Y135: =SUMIF(Outsoucing!D:D,C135,Outsoucing!J:J) -> 0 | Z135: =Q135+R135+U135+V135+X135+Y135 -> 4.6898957e+08 | AA135: =IF(Z135<>0,(Z135/(E135+F135)),0) -> 24416.367 | AB135: LG | AC135: 4.6898957e+08 | AD135: =+Z135-AC135 -> 0
A136: WIP 2 | B136: =C136&H136 -> 301603210179 | C136: 301603 | D136: CNC TRW-FCA4.8 Housing(2) | E136: 101763 | F136: 248 | G136: =+E136+F136 -> 102011 | H136: 210179 | I136: CA TRW-FCA 4.8 Housing | J136: CNC 1 | K136: 1 | L136: 1 | M136: PCS | N136: =K136*(E136+F136) -> 102011 | P136: =IF(AND(Z136<>0,G136<>0),Z136/G136,"") -> 16284.003 | Q136: 1.3291683e+09 | R136: 0 | S136: =VLOOKUP(C136,'Working Hours'!A:I,9,0)*G136 -> 1703.5837 | T136: =S136/SUM($S$114:$S$245) -> 0.03387956 | U136: =SUMIF('Re-allowcate'!C:C,C136,'Re-allowcate'!N:N) -> 72940313 | V136: =SUMIFS('Manufacturing Cost.'!N:N,'Manufacturing Cost.'!G:G,"627",'Manufacturing Cost.'!H:H,"CNC1")*T136+SUMIF('Re-allowcate'!C:C,C136,'Re-allowcate'!J:J) -> 1.8887656e+08 | W136: =S136/SUM($S$7:$S$507) -> 0.0062060798 | X136: =SUMIFS('Manufacturing Cost.'!N:N,'Manufacturing Cost.'!H:H,"indirect",'Manufacturing Cost.'!G:G,"627")*W136 -> 70162179 | Y136: =SUMIF(Outsoucing!D:D,C136,Outsoucing!J:J) -> 0 | Z136: =Q136+R136+U136+V136+X136+Y136 -> 1.6611474e+09 | AA136: =IF(Z136<>0,(Z136/(E136+F136)),0) -> 16284.003 | AB136: ZF | AC136: 1.6611474e+09 | AD136: =+Z136-AC136 -> 0
A137: WIP 2 | B137: =C137&H137 -> 301618210375 | C137: 301618 | D137: CNC TTI 642427003 Milwwaukee Electic Tool Co Guidance | E137: 0 | F137: 0 | G137: =+E137+F137 -> 0 | H137: 210375 | I137: CA TTI 642427003 Milwwaukee Electic Tool Co Guidance | J137: CNC 1 | K137: 1 | L137: 1 | M137: PCS | N137: =K137*(E137+F137) -> 0 | P137: =IF(AND(Z137<>0,G137<>0),Z137/G137,"") | Q137: 0 | R137: 0 | S137: =VLOOKUP(C137,'Working Hours'!A:I,9,0)*G137 -> 0 | T137: =S137/SUM($S$114:$S$236) -> 0 | U137: =SUMIF('Re-allowcate'!C:C,C137,'Re-allowcate'!N:N) -> 0 | V137: =SUMIFS('Manufacturing Cost.'!N:N,'Manufacturing Cost.'!G:G,"627",'Manufacturing Cost.'!H:H,"CNC1")*T137+SUMIF('Re-allowcate'!C:C,C137,'Re-allowcate'!J:J) -> 0 | W137: =S137/SUM($S$7:$S$507) -> 0 | X137: =SUMIFS('Manufacturing Cost.'!N:N,'Manufacturing Cost.'!H:H,"indirect",'Manufacturing Cost.'!G:G,"627")*W137 -> 0 | Y137: =SUMIF(Outsoucing!D:D,C137,Outsoucing!J:J) -> 0 | Z137: =Q137+R137+U137+V137+X137+Y137 -> 0 | AA137: =IF(Z137<>0,(Z137/(E137+F137)),0) -> 0 | AB137: 0 | AC137: 0 | AD137: =+Z137-AC137 -> 0
A138: WIP 2 | B138: =C138&H138 -> 301644210361 | C138: 301644 | D138: CNC Qualcomm MTP PAKALA 55-29708-20 MIDFRAME, HEATSINK ASSY_PROCESS | E138: 0 | F138: 0 | G138: =+E138+F138 -> 0 | H138: 210361 | I138: CA Qualcom MTP Pinnacles 55-29708 5G Midframe, Heatsink Assy | J138: CNC 1 | K138: 1 | L138: 1 | M138: PCS | N138: =K138*(E138+F138) -> 0 | R138: 0 | S138: =VLOOKUP(C138,'Working Hours'!A:I,9,0)*G138 -> 0 | T138: =S138/SUM($S$114:$S$236) -> 0 | U138: =SUMIF('Re-allowcate'!C:C,C138,'Re-allowcate'!N:N) -> 0 | V138: =SUMIFS('Manufacturing Cost.'!N:N,'Manufacturing Cost.'!G:G,"627",'Manufacturing Cost.'!H:H,"CNC1")*T138+SUMIF('Re-allowcate'!C:C,C138,'Re-allowcate'!J:J) -> 0 | W138: =S138/SUM($S$7:$S$507) -> 0 | X138: =SUMIFS('Manufacturing Cost.'!N:N,'Manufacturing Cost.'!H:H,"indirect",'Manufacturing Cost.'!G:G,"627")*W138 -> 0 | Y138: =SUMIF(Outsoucing!D:D,C138,Outsoucing!J:J) -> 0 | Z138: =Q138+R138+U138+V138+X138+Y138 -> 0 | AA138: =IF(Z138<>0,(Z138/(E138+F138)),0) -> 0 | AB138: 0 | AC138: 0 | AD138: =+Z138-AC138 -> 0
A139: WIP 2 | B139: =C139&H139 -> 301673210361 | C139: 301673 | D139: CNC Qualcomm MTP KAANAPALI 55-29708-40 MIDFRAME, HEATSINK ASSY_PROCESS | E139: 0 | F139: 0 | G139: =+E139+F139 -> 0 | H139: 210361 | I139: CA Qualcom MTP Pinnacles 55-29708 5G Midframe, Heatsink Assy | J139: CNC 1 | K139: 1 | L139: 1 | M139: PCS | N139: =K139*(E139+F139) -> 0 | P139: =IF(AND(Z139<>0,G139<>0),Z139/G139,"") | R139: 0 | S139: =VLOOKUP(C139,'Working Hours'!A:I,9,0)*G139 -> 0 | T139: =S139/SUM($S$114:$S$236) -> 0 | U139: =SUMIF('Re-allowcate'!C:C,C139,'Re-allowcate'!N:N) -> 0 | V139: =SUMIFS('Manufacturing Cost.'!N:N,'Manufacturing Cost.'!G:G,"627",'Manufacturing Cost.'!H:H,"CNC1")*T139+SUMIF('Re-allowcate'!C:C,C139,'Re-allowcate'!J:J) -> 0 | W139: =S139/SUM($S$7:$S$507) -> 0 | X139: =SUMIFS('Manufacturing Cost.'!N:N,'Manufacturing Cost.'!H:H,"indirect",'Manufacturing Cost.'!G:G,"627")*W139 -> 0 | Y139: =SUMIF(Outsoucing!D:D,C139,Outsoucing!J:J) -> 0 | Z139: =Q139+R139+U139+V139+X139+Y139 -> 0 | AA139: =IF(Z139<>0,(Z139/(E139+F139)),0) -> 0 | AB139: 0 | AC139: 0 | AD139: =+Z139-AC139 -> 0
A140: WIP 2 | B140: =C140&H140 -> 301567210361 | C140: 301567 | D140: CNC Qualcomm MTP Pinnacles 55-29708-10 5G Midframe, Heatsink Assy | E140: 0 | F140: 0 | G140: =+E140+F140 -> 0 | H140: 210361 | I140: CA Qualcom MTP Pinnacles 55-29708 5G Midframe, Heatsink Assy | J140: CNC 1 | K140: 1 | L140: 1 | M140: PCS | N140: =K140*(E140+F140) -> 0 | P140: =IF(AND(Z140<>0,G140<>0),Z140/G140,"") | Q140: 0 | R140: 0 | S140: =VLOOKUP(C140,'Working Hours'!A:I,9,0)*G140 -> 0 | T140: =S140/SUM($S$114:$S$236) -> 0 | U140: =SUMIF('Re-allowcate'!C:C,C140,'Re-allowcate'!N:N) -> 0 | V140: =SUMIFS('Manufacturing Cost.'!N:N,'Manufacturing Cost.'!G:G,"627",'Manufacturing Cost.'!H:H,"CNC1")*T140+SUMIF('Re-allowcate'!C:C,C140,'Re-allowcate'!J:J) -> 0 | W140: =S140/SUM($S$7:$S$507) -> 0 | X140: =SUMIFS('Manufacturing Cost.'!N:N,'Manufacturing Cost.'!H:H,"indirect",'Manufacturing Cost.'!G:G,"627")*W140 -> 0 | Y140: =SUMIF(Outsoucing!D:D,C140,Outsoucing!J:J) -> 0 | Z140: =Q140+R140+U140+V140+X140+Y140 -> 0 | AA140: =IF(Z140<>0,(Z140/(E140+F140)),0) -> 0 | AB140: 0 | AC140: 0 | AD140: =+Z140-AC140 -> 0
A141: WIP 2 | B141: =C141&H141 -> 301648210382 | C141: 301648 | D141: CNC SM-A156E | E141: 46252 | F141: 494 | G141: =+E141+F141 -> 46746 | H141: 210382 | I141: CA SM-A156E | J141: CNC 1 | K141: 1 | L141: 1 | M141: PCS | N141: =K141*(E141+F141) -> 46746 | O141: 0 | P141: =IF(AND(Z141<>0,G141<>0),Z141/G141,"") -> 8504.0211 | Q141: 3.2078512e+08 | R141: 0 | S141: =VLOOKUP(C141,'Working Hours'!A:I,9,0)*G141 -> 453.4362 | T141: =S141/SUM($S$114:$S$245) -> 0.0090175897 | U141: =SUMIF('Re-allowcate'!C:C,C141,'Re-allowcate'!N:N) -> 7723855.5 | V141: =SUMIFS('Manufacturing Cost.'!N:N,'Manufacturing Cost.'!G:G,"627",'Manufacturing Cost.'!H:H,"CNC1")*T141+SUMIF('Re-allowcate'!C:C,C141,'Re-allowcate'!J:J) -> 50345204 | W141: =S141/SUM($S$7:$S$507) -> 0.0016518479 | X141: =SUMIFS('Manufacturing Cost.'!N:N,'Manufacturing Cost.'!H:H,"indirect",'Manufacturing Cost.'!G:G,"627")*W141 -> 18674792 | Y141: =SUMIF(Outsoucing!D:D,C141,Outsoucing!J:J) -> 0 | Z141: =Q141+R141+U141+V141+X141+Y141 -> 3.9752897e+08 | AA141: =IF(Z141<>0,(Z141/(E141+F141)),0) -> 8504.0211 | AB141: Braket | AC141: 3.9752897e+08 | AD141: =+Z141-AC141 -> 0
A142: WIP 2 | B142: =C142&H142 -> 301651210385 | C142: 301651 | D142: CNC Qualcomm AIR GEN 5 50-36917-2 SOC CARD, BOTTOM TRAY (2) | E142: 438 | F142: 5 | G142: =+E142+F142 -> 443 | H142: 210385 | I142: CA Qualcomm AIR GEN 5 50-36917 | J142: CNC 1 | K142: 1 | L142: 1 | M142: PCS | N142: =K142*(E142+F142) -> 443 | P142: =IF(AND(Z142<>0,G142<>0),Z142/G142,"") -> 37359.908 | Q142: 9333907.2 | R142: 0 | S142: =VLOOKUP(C142,'Working Hours'!A:I,9,0)*G142 -> 15.3721 | T142: =S142/SUM($S$114:$S$245) -> 0.00030570848 | U142: =SUMIF('Re-allowcate'!C:C,C142,'Re-allowcate'!N:N) -> 3727402.6 | V142: =SUMIFS('Manufacturing Cost.'!N:N,'Manufacturing Cost.'!G:G,"627",'Manufacturing Cost.'!H:H,"CNC1")*T142+SUMIF('Re-allowcate'!C:C,C142,'Re-allowcate'!J:J) -> 2856029 | W142: =S142/SUM($S$7:$S$507) -> 5.5999878e-05 | X142: =SUMIFS('Manufacturing Cost.'!N:N,'Manufacturing Cost.'!H:H,"indirect",'Manufacturing Cost.'!G:G,"627")*W142 -> 633100.7 | Y142: =SUMIF(Outsoucing!D:D,C142,Outsoucing!J:J) -> 0 | Z142: =Q142+R142+U142+V142+X142+Y142 -> 16550439 | AA142: =IF(Z142<>0,(Z142/(E142+F142)),0) -> 37359.908 | AB142: QUALCOM | AC142: 16550439 | AD142: =+Z142-AC142 -> 0
A143: WIP 2 | B143: =C143&H143 -> 301654210385 | C143: 301654 | D143: CNC Qualcomm AIR GEN 5 50-36917-5 ETHERNET CARD, BOTTOM TRAY (2) | E143: 0 | F143: 0 | G143: =+E143+F143 -> 0 | H143: 210385 | I143: CA Qualcomm AIR GEN 5 50-36917 | J143: CNC 1 | K143: 1 | L143: 1 | M143: PCS | N143: =K143*(E143+F143) -> 0 | P143: =IF(AND(Z143<>0,G143<>0),Z143/G143,"") | Q143: 0 | R143: 0 | S143: =VLOOKUP(C143,'Working Hours'!A:I,9,0)*G143 -> 0 | T143: =S143/SUM($S$114:$S$236) -> 0 | U143: =SUMIF('Re-allowcate'!C:C,C143,'Re-allowcate'!N:N) -> 0 | V143: =SUMIFS('Manufacturing Cost.'!N:N,'Manufacturing Cost.'!G:G,"627",'Manufacturing Cost.'!H:H,"CNC1")*T143+SUMIF('Re-allowcate'!C:C,C143,'Re-allowcate'!J:J) -> 0 | W143: =S143/SUM($S$7:$S$507) -> 0 | X143: =SUMIFS('Manufacturing Cost.'!N:N,'Manufacturing Cost.'!H:H,"indirect",'Manufacturing Cost.'!G:G,"627")*W143 -> 0 | Y143: =SUMIF(Outsoucing!D:D,C143,Outsoucing!J:J) -> 0 | Z143: =Q143+R143+U143+V143+X143+Y143 -> 0 | AA143: =IF(Z143<>0,(Z143/(E143+F143)),0) -> 0 | AB143: 0 | AC143: 0 | AD143: =+Z143-AC143 -> 0
A144: WIP 2 | B144: =C144&H144 -> 301653210385 | C144: 301653 | D144: CNC Qualcomm AIR GEN 5 50-36917-4 PCIE CARD, BOTTOM TRAY (2) | E144: 0 | F144: 0 | G144: =+E144+F144 -> 0 | H144: 210385 | I144: CA Qualcomm AIR GEN 5 50-36917 | J144: CNC 1 | K144: 1 | L144: 1 | M144: PCS | N144: =K144*(E144+F144) -> 0 | P144: =IF(AND(Z144<>0,G144<>0),Z144/G144,"") | Q144: 0 | R144: 0 | S144: =VLOOKUP(C144,'Working Hours'!A:I,9,0)*G144 -> 0 | T144: =S144/SUM($S$114:$S$236) -> 0 | U144: =SUMIF('Re-allowcate'!C:C,C144,'Re-allowcate'!N:N) -> 0 | V144: =SUMIFS('Manufacturing Cost.'!N:N,'Manufacturing Cost.'!G:G,"627",'Manufacturing Cost.'!H:H,"CNC1")*T144+SUMIF('Re-allowcate'!C:C,C144,'Re-allowcate'!J:J) -> 0 | W144: =S144/SUM($S$7:$S$507) -> 0 | X144: =SUMIFS('Manufacturing Cost.'!N:N,'Manufacturing Cost.'!H:H,"indirect",'Manufacturing Cost.'!G:G,"627")*W144 -> 0 | Y144: =SUMIF(Outsoucing!D:D,C144,Outsoucing!J:J) -> 0 | Z144: =Q144+R144+U144+V144+X144+Y144 -> 0 | AA144: =IF(Z144<>0,(Z144/(E144+F144)),0) -> 0 | AB144: QUALCOM | AC144: 0 | AD144: =+Z144-AC144 -> 0
A145: WIP 2 | B145: =C145&H145 -> 301652210385 | C145: 301652 | D145: CNC Qualcomm AIR GEN 5 50-36917-3 CAMERA CARD, BOTTOM TRAY (2) | E145: 0 | F145: 0 | G145: =+E145+F145 -> 0 | H145: 210385 | I145: CA Qualcomm AIR GEN 5 50-36917 | J145: CNC 1 | K145: 1 | L145: 1 | M145: PCS | N145: =K145*(E145+F145) -> 0 | P145: =IF(AND(Z145<>0,G145<>0),Z145/G145,"") | Q145: 0 | R145: 0 | S145: =VLOOKUP(C145,'Working Hours'!A:I,9,0)*G145 -> 0 | T145: =S145/SUM($S$114:$S$236) -> 0 | U145: =SUMIF('Re-allowcate'!C:C,C145,'Re-allowcate'!N:N) -> 0 | V145: =SUMIFS('Manufacturing Cost.'!N:N,'Manufacturing Cost.'!G:G,"627",'Manufacturing Cost.'!H:H,"CNC1")*T145+SUMIF('Re-allowcate'!C:C,C145,'Re-allowcate'!J:J) -> 0 | W145: =S145/SUM($S$7:$S$507) -> 0 | X145: =SUMIFS('Manufacturing Cost.'!N:N,'Manufacturing Cost.'!H:H,"indirect",'Manufacturing Cost.'!G:G,"627")*W145 -> 0 | Y145: =SUMIF(Outsoucing!D:D,C145,Outsoucing!J:J) -> 0 | Z145: =Q145+R145+U145+V145+X145+Y145 -> 0 | AA145: =IF(Z145<>0,(Z145/(E145+F145)),0) -> 0 | AB145: QUALCOM | AC145: 0 | AD145: =+Z145-AC145 -> 0
A146: WIP 2 | B146: =C146&H146 -> 301656210386 | C146: 301656 | D146: CNC SM-A356B | E146: 0 | F146: 0 | G146: =+E146+F146 -> 0 | H146: 210386 | I146: CA SM-A356B | J146: CNC 1 | K146: 1 | L146: 1 | M146: PCS | N146: =K146*(E146+F146) -> 0 | O146: 0 | P146: =IF(AND(Z146<>0,G146<>0),Z146/G146,"") | Q146: 0 | R146: 0 | S146: =VLOOKUP(C146,'Working Hours'!A:I,9,0)*G146 -> 0 | T146: =S146/SUM($S$114:$S$236) -> 0 | U146: =SUMIF('Re-allowcate'!C:C,C146,'Re-allowcate'!N:N) -> 0 | V146: =SUMIFS('Manufacturing Cost.'!N:N,'Manufacturing Cost.'!G:G,"627",'Manufacturing Cost.'!H:H,"CNC1")*T146+SUMIF('Re-allowcate'!C:C,C146,'Re-allowcate'!J:J) -> 0 | W146: =S146/SUM($S$7:$S$507) -> 0 | X146: =SUMIFS('Manufacturing Cost.'!N:N,'Manufacturing Cost.'!H:H,"indirect",'Manufacturing Cost.'!G:G,"627")*W146 -> 0 | Y146: =SUMIF(Outsoucing!D:D,C146,Outsoucing!J:J) -> 0 | Z146: =Q146+R146+U146+V146+X146+Y146 -> 0 | AA146: =IF(Z146<>0,(Z146/(E146+F146)),0) -> 0 | AC146: 0 | AD146: =+Z146-AC146 -> 0
A147: WIP 2 | B147: =C147&H147 -> 301663210329 | C147: 301663 | D147: CNC Mando Tey Gen4 Heatsink Cover (2) | E147: 78377 | F147: 4000 | G147: =+E147+F147 -> 82377 | H147: 210329 | I147: CA Mando Tey Gen4 Heatsink Cover | J147: CNC 1 | K147: 1 | L147: 1 | M147: PCS | N147: =K147*(E147+F147) -> 82377 | P147: =IF(AND(Z147<>0,G147<>0),Z147/G147,"") -> 31004.995 | Q147: 1.6805745e+09 | R147: 0 | S147: =VLOOKUP(C147,'Working Hours'!A:I,9,0)*G147 -> 5354.505 | T147: =S147/SUM($S$114:$S$245) -> 0.10648627 | U147: =SUMIF('Re-allowcate'!C:C,C147,'Re-allowcate'!N:N) -> 92583437 | V147: =SUMIFS('Manufacturing Cost.'!N:N,'Manufacturing Cost.'!G:G,"627",'Manufacturing Cost.'!H:H,"CNC1")*T147+SUMIF('Re-allowcate'!C:C,C147,'Re-allowcate'!J:J) -> 5.6041496e+08 | W147: =S147/SUM($S$7:$S$507) -> 0.019506224 | X147: =SUMIFS('Manufacturing Cost.'!N:N,'Manufacturing Cost.'!H:H,"indirect",'Manufacturing Cost.'!G:G,"627")*W147 -> 2.2052556e+08 | Y147: =SUMIF(Outsoucing!D:D,C147,Outsoucing!J:J) -> 0 | Z147: =Q147+R147+U147+V147+X147+Y147 -> 2.5540985e+09 | AA147: =IF(Z147<>0,(Z147/(E147+F147)),0) -> 31004.995 | AB147: MANDO | AC147: 2.5540985e+09 | AD147: =+Z147-AC147 -> 0
A148: WIP 2 | B148: =C148&H148 -> 301664210152 | C148: 301664 | D148: CNC Qualcomm MTP IDPS MILOS 55-PM920-100 FRONT HOUSING | E148: 0 | F148: 0 | G148: =+E148+F148 -> 0 | H148: 210152 | I148: CA Qualcomm Bittra 55-PM920 Front housing | J148: CNC 1 | K148: 1 | L148: 1 | M148: PCS | N148: =K148*(E148+F148) -> 0 | R148: 0 | S148: =VLOOKUP(C148,'Working Hours'!A:I,9,0)*G148 -> 0 | T148: =S148/SUM($S$114:$S$236) -> 0 | U148: =SUMIF('Re-allowcate'!C:C,C148,'Re-allowcate'!N:N) -> 0 | V148: =SUMIFS('Manufacturing Cost.'!N:N,'Manufacturing Cost.'!G:G,"627",'Manufacturing Cost.'!H:H,"CNC1")*T148+SUMIF('Re-allowcate'!C:C,C148,'Re-allowcate'!J:J) -> 0 | W148: =S148/SUM($S$7:$S$507) -> 0 | X148: =SUMIFS('Manufacturing Cost.'!N:N,'Manufacturing Cost.'!H:H,"indirect",'Manufacturing Cost.'!G:G,"627")*W148 -> 0 | Y148: =SUMIF(Outsoucing!D:D,C148,Outsoucing!J:J) -> 0 | Z148: =Q148+R148+U148+V148+X148+Y148 -> 0 | AA148: =IF(Z148<>0,(Z148/(E148+F148)),0) -> 0 | AB148: 0 | AC148: 0 | AD148: =+Z148-AC148 -> 0
A149: WIP 2 | B149: =C149&H149 -> 301630210152 | C149: 301630 | D149: CNC Qualcomm MTP Camano 55-PR725-20 Assy Font Housing | E149: 0 | F149: 0 | G149: =+E149+F149 -> 0 | H149: 210152 | I149: CA Qualcomm Bittra 55-PM920 Front housing | J149: CNC 1 | K149: 1 | L149: 1 | M149: PCS | N149: =K149*(E149+F149) -> 0 | R149: 0 | S149: =VLOOKUP(C149,'Working Hours'!A:I,9,0)*G149 -> 0 | T149: =S149/SUM($S$114:$S$236) -> 0 | U149: =SUMIF('Re-allowcate'!C:C,C149,'Re-allowcate'!N:N) -> 0 | V149: =SUMIFS('Manufacturing Cost.'!N:N,'Manufacturing Cost.'!G:G,"627",'Manufacturing Cost.'!H:H,"CNC1")*T149+SUMIF('Re-allowcate'!C:C,C149,'Re-allowcate'!J:J) -> 0 | W149: =S149/SUM($S$7:$S$507) -> 0 | X149: =SUMIFS('Manufacturing Cost.'!N:N,'Manufacturing Cost.'!H:H,"indirect",'Manufacturing Cost.'!G:G,"627")*W149 -> 0 | Y149: =SUMIF(Outsoucing!D:D,C149,Outsoucing!J:J) -> 0 | Z149: =Q149+R149+U149+V149+X149+Y149 -> 0 | AA149: =IF(Z149<>0,(Z149/(E149+F149)),0) -> 0 | AB149: 0 | AC149: 0 | AD149: =+Z149-AC149 -> 0
A150: WIP 2 | B150: =C150&H150 -> 301748210152 | C150: 301748 | D150: CNC Qualcomm MTP IDP FILLMORE 55-PM920-80 FRONT HOUSING | E150: 0 | F150: 0 | G150: =+E150+F150 -> 0 | H150: 210152 | I150: CA Qualcomm Bittra 55-PM920 Front housing | J150: CNC 1 | K150: 1 | L150: 1 | M150: PCS | N150: =K150*(E150+F150) -> 0 | R150: 0 | S150: =VLOOKUP(C150,'Working Hours'!A:I,9,0)*G150 -> 0 | T150: =S150/SUM($S$114:$S$236) -> 0 | U150: =SUMIF('Re-allowcate'!C:C,C150,'Re-allowcate'!N:N) -> 0 | V150: =SUMIFS('Manufacturing Cost.'!N:N,'Manufacturing Cost.'!G:G,"627",'Manufacturing Cost.'!H:H,"CNC1")*T150+SUMIF('Re-allowcate'!C:C,C150,'Re-allowcate'!J:J) -> 0 | W150: =S150/SUM($S$7:$S$507) -> 0 | X150: =SUMIFS('Manufacturing Cost.'!N:N,'Manufacturing Cost.'!H:H,"indirect",'Manufacturing Cost.'!G:G,"627")*W150 -> 0 | Y150: =SUMIF(Outsoucing!D:D,C150,Outsoucing!J:J) -> 0 | Z150: =Q150+R150+U150+V150+X150+Y150 -> 0 | AA150: =IF(Z150<>0,(Z150/(E150+F150)),0) -> 0 | AB150: 0 | AC150: 0 | AD150: =+Z150-AC150 -> 0
A151: WIP 2 | B151: =C151&H151 -> 301666551236 | C151: 301666 | D151: CNC Qualcomm MTP IDPS MILOS 55-PR954-100 FRONT HOUSING | E151: 0 | F151: 0 | G151: =+E151+F151 -> 0 | H151: 551236 | I151: IN Qualcomm MTP IDPS MILOS 55-PR954-100 FRONT HOUSING | J151: CNC 1 | K151: 1 | L151: 1 | M151: PCS | N151: =K151*(E151+F151) -> 0 | P151: =IF(AND(Z151<>0,G151<>0),Z151/G151,"") | Q151: 0 | R151: 0 | S151: =VLOOKUP(C151,'Working Hours'!A:I,9,0)*G151 -> 0 | T151: =S151/SUM($S$114:$S$236) -> 0 | U151: =SUMIF('Re-allowcate'!C:C,C151,'Re-allowcate'!N:N) -> 0 | V151: =SUMIFS('Manufacturing Cost.'!N:N,'Manufacturing Cost.'!G:G,"627",'Manufacturing Cost.'!H:H,"CNC1")*T151+SUMIF('Re-allowcate'!C:C,C151,'Re-allowcate'!J:J) -> 0 | W151: =S151/SUM($S$7:$S$507) -> 0 | X151: =SUMIFS('Manufacturing Cost.'!N:N,'Manufacturing Cost.'!H:H,"indirect",'Manufacturing Cost.'!G:G,"627")*W151 -> 0 | Y151: =SUMIF(Outsoucing!D:D,C151,Outsoucing!J:J) -> 0 | Z151: =Q151+R151+U151+V151+X151+Y151 -> 0 | AA151: =IF(Z151<>0,(Z151/(E151+F151)),0) -> 0 | AB151: 0 | AC151: 0 | AD151: =+Z151-AC151 -> 0
A152: WIP 2 | B152: =C152&H152 -> 301668551230 | C152: 301668 | D152: CNC Qualcomm MTP IDPS MILOS CA90-58183-1 FRAME, WLAN AREA, MULTIPURPOSE (2) | E152: 0 | F152: 0 | G152: =+E152+F152 -> 0 | H152: 551230 | I152: IN Qualcomm MTP PAKALA 50-58183-1 FRAME, WLAN AREA, MULTIPURPOSE | J152: CNC 1 | K152: 1 | L152: 1 | M152: PCS | N152: =K152*(E152+F152) -> 0 | P152: =IF(AND(Z152<>0,G152<>0),Z152/G152,"") | Q152: 0 | R152: 0 | S152: =VLOOKUP(C152,'Working Hours'!A:I,9,0)*G152 -> 0 | T152: =S152/SUM($S$114:$S$236) -> 0 | U152: =SUMIF('Re-allowcate'!C:C,C152,'Re-allowcate'!N:N) -> 0 | V152: =SUMIFS('Manufacturing Cost.'!N:N,'Manufacturing Cost.'!G:G,"627",'Manufacturing Cost.'!H:H,"CNC1")*T152+SUMIF('Re-allowcate'!C:C,C152,'Re-allowcate'!J:J) -> 0 | W152: =S152/SUM($S$7:$S$507) -> 0 | X152: =SUMIFS('Manufacturing Cost.'!N:N,'Manufacturing Cost.'!H:H,"indirect",'Manufacturing Cost.'!G:G,"627")*W152 -> 0 | Y152: =SUMIF(Outsoucing!D:D,C152,Outsoucing!J:J) -> 0 | Z152: =Q152+R152+U152+V152+X152+Y152 -> 0 | AA152: =IF(Z152<>0,(Z152/(E152+F152)),0) -> 0 | AC152: 0 | AD152: =+Z152-AC152 -> 0
A153: WIP 2 | B153: =C153&H153 -> 301671210388 | C153: 301671 | D153: CNC LGIT T6M8 Housing 3HUC00007A | E153: 14463 | F153: 2128 | G153: =+E153+F153 -> 16591 | H153: 210388 | I153: CA LGIT T6M8 Housing 3HUC00007A | J153: CNC 1 | K153: 1 | L153: 1 | M153: PCS | N153: =K153*(E153+F153) -> 16591 | P153: =IF(AND(Z153<>0,G153<>0),Z153/G153,"") -> 68746.819 | Q153: 8.943771e+08 | R153: 0 | S153: =VLOOKUP(C153,'Working Hours'!A:I,9,0)*G153 -> 1753.6687 | T153: =S153/SUM($S$114:$S$245) -> 0.034875611 | U153: =SUMIF('Re-allowcate'!C:C,C153,'Re-allowcate'!N:N) -> 2741335.9 | V153: =SUMIFS('Manufacturing Cost.'!N:N,'Manufacturing Cost.'!G:G,"627",'Manufacturing Cost.'!H:H,"CNC1")*T153+SUMIF('Re-allowcate'!C:C,C153,'Re-allowcate'!J:J) -> 1.7123511e+08 | W153: =S153/SUM($S$7:$S$507) -> 0.0063885372 | X153: =SUMIFS('Manufacturing Cost.'!N:N,'Manufacturing Cost.'!H:H,"indirect",'Manufacturing Cost.'!G:G,"627")*W153 -> 72224933 | Y153: =SUMIF(Outsoucing!D:D,C153,Outsoucing!J:J) -> 0 | Z153: =Q153+R153+U153+V153+X153+Y153 -> 1.1405785e+09 | AA153: =IF(Z153<>0,(Z153/(E153+F153)),0) -> 68746.819 | AB153: Braket | AC153: 1.1405785e+09 | AD153: =+Z153-AC153 -> 0
A154: WIP 2 | B154: =C154&H154 -> 301672210389 | C154: 301672 | D154: CNC Qualcomm MTP KAANAPALI 55-71907-1 ASSY, BRACKET, 5G, MODULE, REAR | E154: 0 | F154: 0 | G154: =+E154+F154 -> 0 | H154: 210389 | I154: CA Qualcomm MTP KAANAPALI 55-71907-1 ASSY, BRACKET, 5G, MODULE, REAR | J154: CNC 1 | K154: 1 | L154: 1 | M154: PCS | N154: =K154*(E154+F154) -> 0 | P154: =IF(AND(Z154<>0,G154<>0),Z154/G154,"") | Q154: 0 | R154: 0 | S154: =VLOOKUP(C154,'Working Hours'!A:I,9,0)*G154 -> 0 | T154: =S154/SUM($S$114:$S$236) -> 0 | U154: =SUMIF('Re-allowcate'!C:C,C154,'Re-allowcate'!N:N) -> 0 | V154: =SUMIFS('Manufacturing Cost.'!N:N,'Manufacturing Cost.'!G:G,"627",'Manufacturing Cost.'!H:H,"CNC1")*T154+SUMIF('Re-allowcate'!C:C,C154,'Re-allowcate'!J:J) -> 0 | W154: =S154/SUM($S$7:$S$507) -> 0 | X154: =SUMIFS('Manufacturing Cost.'!N:N,'Manufacturing Cost.'!H:H,"indirect",'Manufacturing Cost.'!G:G,"627")*W154 -> 0 | Y154: =SUMIF(Outsoucing!D:D,C154,Outsoucing!J:J) -> 0 | Z154: =Q154+R154+U154+V154+X154+Y154 -> 0 | AA154: =IF(Z154<>0,(Z154/(E154+F154)),0) -> 0 | AB154: 0 | AC154: 0 | AD154: =+Z154-AC154 -> 0
A155: WIP 2 | B155: =C155&H155 -> 301674551237 | C155: 301674 | D155: CNC Qualcomm MTP KAANAPALI 55-58484-3 Sub Assy, Front housing | E155: 0 | F155: 0 | G155: =+E155+F155 -> 0 | H155: 551237 | I155: IN Qualcomm MTP KAANAPALI 55-58484-3 Sub Assy, Front housing | J155: CNC 1 | K155: 1 | L155: 1 | M155: PCS | N155: =K155*(E155+F155) -> 0 | P155: =IF(AND(Z155<>0,G155<>0),Z155/G155,"") | Q155: 0 | R155: 0 | S155: =VLOOKUP(C155,'Working Hours'!A:I,9,0)*G155 -> 0 | T155: =S155/SUM($S$114:$S$236) -> 0 | U155: =SUMIF('Re-allowcate'!C:C,C155,'Re-allowcate'!N:N) -> 0 | V155: =SUMIFS('Manufacturing Cost.'!N:N,'Manufacturing Cost.'!G:G,"627",'Manufacturing Cost.'!H:H,"CNC1")*T155+SUMIF('Re-allowcate'!C:C,C155,'Re-allowcate'!J:J) -> 0 | W155: =S155/SUM($S$7:$S$507) -> 0 | X155: =SUMIFS('Manufacturing Cost.'!N:N,'Manufacturing Cost.'!H:H,"indirect",'Manufacturing Cost.'!G:G,"627")*W155 -> 0 | Y155: =SUMIF(Outsoucing!D:D,C155,Outsoucing!J:J) -> 0 | Z155: =Q155+R155+U155+V155+X155+Y155 -> 0 | AA155: =IF(Z155<>0,(Z155/(E155+F155)),0) -> 0 | AB155: 0 | AC155: 0 | AD155: =+Z155-AC155 -> 0
A156: WIP 2 | B156: =C156&H156 -> 301675551238 | C156: 301675 | D156: CNC Qualcomm MTP KAANAPALI CA90-34464-30 REAR HOUSING | E156: 0 | F156: 0 | G156: =+E156+F156 -> 0 | H156: 551238 | I156: IN Qualcomm MTP KAANAPALI CA90-34464 REAR HOUSING | J156: CNC 1 | K156: 1 | L156: 1 | M156: PCS | N156: =K156*(E156+F156) -> 0 | P156: =IF(AND(Z156<>0,G156<>0),Z156/G156,"") | Q156: 0 | R156: 0 | S156: =VLOOKUP(C156,'Working Hours'!A:I,9,0)*G156 -> 0 | T156: =S156/SUM($S$114:$S$236) -> 0 | U156: =SUMIF('Re-allowcate'!C:C,C156,'Re-allowcate'!N:N) -> 0 | V156: =SUMIFS('Manufacturing Cost.'!N:N,'Manufacturing Cost.'!G:G,"627",'Manufacturing Cost.'!H:H,"CNC1")*T156+SUMIF('Re-allowcate'!C:C,C156,'Re-allowcate'!J:J) -> 0 | W156: =S156/SUM($S$7:$S$507) -> 0 | X156: =SUMIFS('Manufacturing Cost.'!N:N,'Manufacturing Cost.'!H:H,"indirect",'Manufacturing Cost.'!G:G,"627")*W156 -> 0 | Y156: =SUMIF(Outsoucing!D:D,C156,Outsoucing!J:J) -> 0 | Z156: =Q156+R156+U156+V156+X156+Y156 -> 0 | AA156: =IF(Z156<>0,(Z156/(E156+F156)),0) -> 0 | AB156: 0 | AC156: 0 | AD156: =+Z156-AC156 -> 0
A157: WIP 2 | B157: =C157&H157 -> 301676551238 | C157: 301676 | D157: CNC Qualcomm MTP KAANAPALI CA90-34464-40 REAR HOUSING | E157: 0 | F157: 0 | G157: =+E157+F157 -> 0 | H157: 551238 | I157: IN Qualcomm MTP KAANAPALI CA90-34464 REAR HOUSING | J157: CNC 1 | K157: 1 | L157: 1 | M157: PCS | N157: =K157*(E157+F157) -> 0 | P157: =IF(AND(Z157<>0,G157<>0),Z157/G157,"") | Q157: 0 | R157: 0 | S157: =VLOOKUP(C157,'Working Hours'!A:I,9,0)*G157 -> 0 | T157: =S157/SUM($S$114:$S$236) -> 0 | U157: =SUMIF('Re-allowcate'!C:C,C157,'Re-allowcate'!N:N) -> 0 | V157: =SUMIFS('Manufacturing Cost.'!N:N,'Manufacturing Cost.'!G:G,"627",'Manufacturing Cost.'!H:H,"CNC1")*T157+SUMIF('Re-allowcate'!C:C,C157,'Re-allowcate'!J:J) -> 0 | W157: =S157/SUM($S$7:$S$507) -> 0 | X157: =SUMIFS('Manufacturing Cost.'!N:N,'Manufacturing Cost.'!H:H,"indirect",'Manufacturing Cost.'!G:G,"627")*W157 -> 0 | Y157: =SUMIF(Outsoucing!D:D,C157,Outsoucing!J:J) -> 0 | Z157: =Q157+R157+U157+V157+X157+Y157 -> 0 | AA157: =IF(Z157<>0,(Z157/(E157+F157)),0) -> 0 | AC157: 0 | AD157: =+Z157-AC157 -> 0
A158: WIP 2 | B158: =C158&H158 -> 301677551238 | C158: 301677 | D158: CNC Qualcomm MTP KAANAPALI CA90-34464- 50 REAR HOUSING | E158: 0 | F158: 0 | G158: =+E158+F158 -> 0 | H158: 551238 | I158: IN Qualcomm MTP KAANAPALI CA90-34464 REAR HOUSING | J158: CNC 1 | K158: 1 | L158: 1 | M158: PCS | N158: =K158*(E158+F158) -> 0 | P158: =IF(AND(Z158<>0,G158<>0),Z158/G158,"") | Q158: 0 | R158: 0 | S158: =VLOOKUP(C158,'Working Hours'!A:I,9,0)*G158 -> 0 | T158: =S158/SUM($S$114:$S$236) -> 0 | U158: =SUMIF('Re-allowcate'!C:C,C158,'Re-allowcate'!N:N) -> 0 | V158: =SUMIFS('Manufacturing Cost.'!N:N,'Manufacturing Cost.'!G:G,"627",'Manufacturing Cost.'!H:H,"CNC1")*T158+SUMIF('Re-allowcate'!C:C,C158,'Re-allowcate'!J:J) -> 0 | W158: =S158/SUM($S$7:$S$507) -> 0 | X158: =SUMIFS('Manufacturing Cost.'!N:N,'Manufacturing Cost.'!H:H,"indirect",'Manufacturing Cost.'!G:G,"627")*W158 -> 0 | Y158: =SUMIF(Outsoucing!D:D,C158,Outsoucing!J:J) -> 0 | Z158: =Q158+R158+U158+V158+X158+Y158 -> 0 | AA158: =IF(Z158<>0,(Z158/(E158+F158)),0) -> 0 | AC158: 0 | AD158: =+Z158-AC158 -> 0
A159: WIP 2 | B159: =C159&H159 -> 301678210390 | C159: 301678 | D159: CNC ZF Remote Camera 2.1 A014V743 Housing, Camera RH Lane-Detection | E159: 0 | F159: 0 | G159: =+E159+F159 -> 0 | H159: 210390 | I159: CA ZF Remote Camera 2.1 A014V743 Housing, Camera RH Lane-Detection | J159: CNC 1 | K159: 1 | L159: 1 | M159: PCS | N159: =K159*(E159+F159) -> 0 | P159: =IF(AND(Z159<>0,G159<>0),Z159/G159,"") | Q159: 0 | R159: 0 | S159: =VLOOKUP(C159,'Working Hours'!A:I,9,0)*G159 -> 0 | T159: =S159/SUM($S$114:$S$236) -> 0 | U159: =SUMIF('Re-allowcate'!C:C,C159,'Re-allowcate'!N:N) -> 0 | V159: =SUMIFS('Manufacturing Cost.'!N:N,'Manufacturing Cost.'!G:G,"627",'Manufacturing Cost.'!H:H,"CNC1")*T159+SUMIF('Re-allowcate'!C:C,C159,'Re-allowcate'!J:J) -> 0 | W159: =S159/SUM($S$7:$S$507) -> 0 | X159: =SUMIFS('Manufacturing Cost.'!N:N,'Manufacturing Cost.'!H:H,"indirect",'Manufacturing Cost.'!G:G,"627")*W159 -> 0 | Y159: =SUMIF(Outsoucing!D:D,C159,Outsoucing!J:J) -> 0 | Z159: =Q159+R159+U159+V159+X159+Y159 -> 0 | AA159: =IF(Z159<>0,(Z159/(E159+F159)),0) -> 0 | AC159: 0 | AD159: =+Z159-AC159 -> 0
A160: WIP 2 | B160: =C160&H160 -> 301539210359 | C160: 301539 | D160: CNC ZF IPM 2.0 Housing Base A014A906/A014A871 | E160: 6824 | F160: 38 | G160: =+E160+F160 -> 6862 | H160: 210359 | I160: CA ZF IPM 2.0 Housing Base A014A906/A014A871 | J160: CNC 1 | K160: 1 | L160: 1 | M160: PCS | N160: =K160*(E160+F160) -> 6862 | P160: =IF(AND(Z160<>0,G160<>0),Z160/G160,"") -> 17930.899 | Q160: 86088380 | R160: 0 | S160: =VLOOKUP(C160,'Working Hours'!A:I,9,0)*G160 -> 220.9564 | T160: =S160/SUM($S$114:$S$245) -> 0.0043942106 | U160: =SUMIF('Re-allowcate'!C:C,C160,'Re-allowcate'!N:N) -> 4906494.7 | V160: =SUMIFS('Manufacturing Cost.'!N:N,'Manufacturing Cost.'!G:G,"627",'Manufacturing Cost.'!H:H,"CNC1")*T160+SUMIF('Re-allowcate'!C:C,C160,'Re-allowcate'!J:J) -> 22946851 | W160: =S160/SUM($S$7:$S$507) -> 0.00080493435 | X160: =SUMIFS('Manufacturing Cost.'!N:N,'Manufacturing Cost.'!H:H,"indirect",'Manufacturing Cost.'!G:G,"627")*W160 -> 9100100.3 | Y160: =SUMIF(Outsoucing!D:D,C160,Outsoucing!J:J) -> 0 | Z160: =Q160+R160+U160+V160+X160+Y160 -> 1.2304183e+08 | AA160: =IF(Z160<>0,(Z160/(E160+F160)),0) -> 17930.899 | AB160: ZF | AC160: 1.2304183e+08 | AD160: =+Z160-AC160 -> 0
A161: WIP 2 | B161: =C161&H161 -> 301162210146 | C161: 301162 | D161: CNC LGIT Gen3 AL6 | E161: 0 | F161: 0 | G161: =+E161+F161 -> 0 | H161: 210146 | I161: CA LGIT Gen3 AL6 | J161: CNC 1 | K161: 1 | L161: 1 | M161: PCS | N161: =K161*(E161+F161) -> 0 | P161: =IF(AND(Z161<>0,G161<>0),Z161/G161,"") | Q161: 0 | R161: 0 | S161: =VLOOKUP(C161,'Working Hours'!A:I,9,0)*G161 -> 0 | T161: =S161/SUM($S$114:$S$236) -> 0 | U161: =SUMIF('Re-allowcate'!C:C,C161,'Re-allowcate'!N:N) -> 0 | V161: =SUMIFS('Manufacturing Cost.'!N:N,'Manufacturing Cost.'!G:G,"627",'Manufacturing Cost.'!H:H,"CNC1")*T161+SUMIF('Re-allowcate'!C:C,C161,'Re-allowcate'!J:J) -> 0 | W161: =S161/SUM($S$7:$S$507) -> 0 | X161: =SUMIFS('Manufacturing Cost.'!N:N,'Manufacturing Cost.'!H:H,"indirect",'Manufacturing Cost.'!G:G,"627")*W161 -> 0 | Y161: =SUMIF(Outsoucing!D:D,C161,Outsoucing!J:J) -> 0 | Z161: =Q161+R161+U161+V161+X161+Y161 -> 0 | AA161: =IF(Z161<>0,(Z161/(E161+F161)),0) -> 0 | AB161: 0 | AC161: 0 | AD161: =+Z161-AC161 -> 0
A162: WIP 2 | B162: =C162&H162 -> 301448210331 | C162: 301448 | D162: CNC Mando Brose GE821-J10-00-J100 Housing | E162: 6439 | F162: 507 | G162: =+E162+F162 -> 6946 | H162: 210331 | I162: CA Mando Brose GE821-J10-00-J100 Housing | J162: CNC 1 | K162: 1 | L162: 1 | M162: PCS | N162: =K162*(E162+F162) -> 6946 | P162: =IF(AND(Z162<>0,G162<>0),Z162/G162,"") -> 50594.286 | Q162: 2.4091311e+08 | R162: 0 | S162: =VLOOKUP(C162,'Working Hours'!A:I,9,0)*G162 -> 719.6056 | T162: =S162/SUM($S$114:$S$245) -> 0.014310962 | U162: =SUMIF('Re-allowcate'!C:C,C162,'Re-allowcate'!N:N) -> 7806603.3 | V162: =SUMIFS('Manufacturing Cost.'!N:N,'Manufacturing Cost.'!G:G,"627",'Manufacturing Cost.'!H:H,"CNC1")*T162+SUMIF('Re-allowcate'!C:C,C162,'Re-allowcate'!J:J) -> 73071206 | W162: =S162/SUM($S$7:$S$507) -> 0.0026214913 | X162: =SUMIFS('Manufacturing Cost.'!N:N,'Manufacturing Cost.'!H:H,"indirect",'Manufacturing Cost.'!G:G,"627")*W162 -> 29636992 | Y162: =SUMIF(Outsoucing!D:D,C162,Outsoucing!J:J) -> 0 | Z162: =Q162+R162+U162+V162+X162+Y162 -> 3.5142791e+08 | AA162: =IF(Z162<>0,(Z162/(E162+F162)),0) -> 50594.286 | AB162: MANDO | AC162: 3.5142791e+08 | AD162: =+Z162-AC162 -> 0
A163: WIP 2 | B163: =C163&H163 -> 301614210370 | C163: 301614 | D163: CNC Qualcomm CPE Pinnacles 55-36814-2 Grounding Frame | E163: 0 | F163: 0 | G163: =+E163+F163 -> 0 | H163: 210370 | I163: CA Qualcomm CPE Pinnacles 55-36814-1 Grounding Frame | J163: CNC 1 | K163: 1 | L163: 1 | M163: PCS | N163: =K163*(E163+F163) -> 0 | P163: =IF(AND(Z163<>0,G163<>0),Z163/G163,"") | Q163: 0 | R163: 0 | S163: =VLOOKUP(C163,'Working Hours'!A:I,9,0)*G163 -> 0 | T163: =S163/SUM($S$114:$S$236) -> 0 | U163: =SUMIF('Re-allowcate'!C:C,C163,'Re-allowcate'!N:N) -> 0 | V163: =SUMIFS('Manufacturing Cost.'!N:N,'Manufacturing Cost.'!G:G,"627",'Manufacturing Cost.'!H:H,"CNC1")*T163+SUMIF('Re-allowcate'!C:C,C163,'Re-allowcate'!J:J) -> 0 | W163: =S163/SUM($S$7:$S$507) -> 0 | X163: =SUMIFS('Manufacturing Cost.'!N:N,'Manufacturing Cost.'!H:H,"indirect",'Manufacturing Cost.'!G:G,"627")*W163 -> 0 | Y163: =SUMIF(Outsoucing!D:D,C163,Outsoucing!J:J) -> 0 | Z163: =Q163+R163+U163+V163+X163+Y163 -> 0 | AA163: =IF(Z163<>0,(Z163/(E163+F163)),0) -> 0 | AB163: 0 | AC163: 0 | AD163: =+Z163-AC163 -> 0
A164: WIP 2 | B164: =C164&H164 -> 301687210391 | C164: 301687 | D164: CNC LGIT eK- LQ2 3BKO00001A Cover | E164: 12754 | F164: 579 | G164: =+E164+F164 -> 13333 | H164: 210391 | I164: CA LGIT eK- LQ2 3BKO00001A Cover | J164: CNC 1 | K164: 1 | L164: 1 | M164: PCS | N164: =K164*(E164+F164) -> 13333 | P164: =IF(AND(Z164<>0,G164<>0),Z164/G164,"") -> 24422.61 | Q164: 1.9023865e+08 | R164: 0 | S164: =VLOOKUP(C164,'Working Hours'!A:I,9,0)*G164 -> 481.3213 | T164: =S164/SUM($S$114:$S$245) -> 0.009572147 | U164: =SUMIF('Re-allowcate'!C:C,C164,'Re-allowcate'!N:N) -> 25687399 | V164: =SUMIFS('Manufacturing Cost.'!N:N,'Manufacturing Cost.'!G:G,"627",'Manufacturing Cost.'!H:H,"CNC1")*T164+SUMIF('Re-allowcate'!C:C,C164,'Re-allowcate'!J:J) -> 89877378 | W164: =S164/SUM($S$7:$S$507) -> 0.0017534321 | X164: =SUMIFS('Manufacturing Cost.'!N:N,'Manufacturing Cost.'!H:H,"indirect",'Manufacturing Cost.'!G:G,"627")*W164 -> 19823242 | Y164: =SUMIF(Outsoucing!D:D,C164,Outsoucing!J:J) -> 0 | Z164: =Q164+R164+U164+V164+X164+Y164 -> 3.2562666e+08 | AA164: =IF(Z164<>0,(Z164/(E164+F164)),0) -> 24422.61 | AB164: LG | AC164: 3.2562666e+08 | AD164: =+Z164-AC164 -> 0
A165: WIP 2 | B165: =C165&H165 -> 301683551239 | C165: 301683 | D165: CNC Qualcomm MTP PAKALA CA90-58184-1 CARRIER FRAME, ASSY | E165: 0 | F165: 0 | G165: =+E165+F165 -> 0 | H165: 551239 | I165: IN Qualcomm MTP PAKALA CA90-58184-1 CARRIER FRAME, ASSY | J165: CNC 1 | K165: 1 | L165: 1 | M165: PCS | N165: =K165*(E165+F165) -> 0 | P165: =IF(AND(Z165<>0,G165<>0),Z165/G165,"") | Q165: 0 | R165: 0 | S165: =VLOOKUP(C165,'Working Hours'!A:I,9,0)*G165 -> 0 | T165: =S165/SUM($S$114:$S$236) -> 0 | U165: =SUMIF('Re-allowcate'!C:C,C165,'Re-allowcate'!N:N) -> 0 | V165: =SUMIFS('Manufacturing Cost.'!N:N,'Manufacturing Cost.'!G:G,"627",'Manufacturing Cost.'!H:H,"CNC1")*T165+SUMIF('Re-allowcate'!C:C,C165,'Re-allowcate'!J:J) -> 0 | W165: =S165/SUM($S$7:$S$507) -> 0 | X165: =SUMIFS('Manufacturing Cost.'!N:N,'Manufacturing Cost.'!H:H,"indirect",'Manufacturing Cost.'!G:G,"627")*W165 -> 0 | Y165: =SUMIF(Outsoucing!D:D,C165,Outsoucing!J:J) -> 0 | Z165: =Q165+R165+U165+V165+X165+Y165 -> 0 | AA165: =IF(Z165<>0,(Z165/(E165+F165)),0) -> 0 | AC165: 0 | AD165: =+Z165-AC165 -> 0
A166: WIP 2 | B166: =C166&H166 -> 301713210392 | C166: 301713 | D166: CNC Qualcomm QCB Glymur 50-74874-1 HEATSINK, SIDE B, QCB SIP, PROJECT GLYMUR | E166: 0 | F166: 0 | G166: =+E166+F166 -> 0 | H166: 210392 | I166: CA Qualcomm QCB Glymur 50-74874-1 HEATSINK, SIDE B, QCB SIP, PROJECT GLYMUR | J166: CNC 1 | K166: 1 | L166: 1 | M166: PCS | N166: =K166*(E166+F166) -> 0 | P166: =IF(AND(Z166<>0,G166<>0),Z166/G166,"") | Q166: 0 | R166: 0 | S166: =VLOOKUP(C166,'Working Hours'!A:I,9,0)*G166 -> 0 | T166: =S166/SUM($S$114:$S$236) -> 0 | U166: =SUMIF('Re-allowcate'!C:C,C166,'Re-allowcate'!N:N) -> 0 | V166: =SUMIFS('Manufacturing Cost.'!N:N,'Manufacturing Cost.'!G:G,"627",'Manufacturing Cost.'!H:H,"CNC1")*T166+SUMIF('Re-allowcate'!C:C,C166,'Re-allowcate'!J:J) -> 0 | W166: =S166/SUM($S$7:$S$507) -> 0 | X166: =SUMIFS('Manufacturing Cost.'!N:N,'Manufacturing Cost.'!H:H,"indirect",'Manufacturing Cost.'!G:G,"627")*W166 -> 0 | Y166: =SUMIF(Outsoucing!D:D,C166,Outsoucing!J:J) -> 0 | Z166: =Q166+R166+U166+V166+X166+Y166 -> 0 | AA166: =IF(Z166<>0,(Z166/(E166+F166)),0) -> 0 | AC166: 0 | AD166: =+Z166-AC166 -> 0
A167: WIP 2 | B167: =C167&H167 -> 301715210394 | C167: 301715 | D167: CNC Qualcomm RIDE 5 50-74187-1 MIDFRAME ASSEMBLY, RIDE 5 | E167: 774 | F167: 42 | G167: =+E167+F167 -> 816 | H167: 210394 | I167: CA Qualcomm RIDE 5 50-74187-1 MIDFRAME ASSEMBLY, RIDE 5 | J167: CNC 1 | K167: 1 | L167: 1 | M167: PCS | N167: =K167*(E167+F167) -> 816 | P167: =IF(AND(Z167<>0,G167<>0),Z167/G167,"") -> 64862.46 | Q167: 30436192 | R167: 0 | S167: =VLOOKUP(C167,'Working Hours'!A:I,9,0)*G167 -> 95.2272 | T167: =S167/SUM($S$114:$S$245) -> 0.0018938052 | U167: =SUMIF('Re-allowcate'!C:C,C167,'Re-allowcate'!N:N) -> 6865825.1 | V167: =SUMIFS('Manufacturing Cost.'!N:N,'Manufacturing Cost.'!G:G,"627",'Manufacturing Cost.'!H:H,"CNC1")*T167+SUMIF('Re-allowcate'!C:C,C167,'Re-allowcate'!J:J) -> 11703813 | W167: =S167/SUM($S$7:$S$507) -> 0.00034690846 | X167: =SUMIFS('Manufacturing Cost.'!N:N,'Manufacturing Cost.'!H:H,"indirect",'Manufacturing Cost.'!G:G,"627")*W167 -> 3921937 | Y167: =SUMIF(Outsoucing!D:D,C167,Outsoucing!J:J) -> 0 | Z167: =Q167+R167+U167+V167+X167+Y167 -> 52927767 | AA167: =IF(Z167<>0,(Z167/(E167+F167)),0) -> 64862.46 | AB167: QUALCOM | AC167: 52927767 | AD167: =+Z167-AC167 -> 0
A168: WIP 2 | B168: =C168&H168 -> 301716210395 | C168: 301716 | D168: CNC Qualcomm RIDE 5 50-74188-1 LOWER FRAME, RIDE 5 | E168: 0 | F168: 0 | G168: =+E168+F168 -> 0 | H168: 210395 | I168: CA Qualcomm RIDE 5 50-74188-1 LOWER FRAME, RIDE 5 | J168: CNC 1 | K168: 1 | L168: 1 | M168: PCS | N168: =K168*(E168+F168) -> 0 | Q168: 0 | R168: 0 | S168: =VLOOKUP(C168,'Working Hours'!A:I,9,0)*G168 -> 0 | T168: =S168/SUM($S$114:$S$236) -> 0 | U168: =SUMIF('Re-allowcate'!C:C,C168,'Re-allowcate'!N:N) -> 0 | V168: =SUMIFS('Manufacturing Cost.'!N:N,'Manufacturing Cost.'!G:G,"627",'Manufacturing Cost.'!H:H,"CNC1")*T168+SUMIF('Re-allowcate'!C:C,C168,'Re-allowcate'!J:J) -> 0 | W168: =S168/SUM($S$7:$S$507) -> 0 | X168: =SUMIFS('Manufacturing Cost.'!N:N,'Manufacturing Cost.'!H:H,"indirect",'Manufacturing Cost.'!G:G,"627")*W168 -> 0 | Y168: =SUMIF(Outsoucing!D:D,C168,Outsoucing!J:J) -> 0 | Z168: =Q168+R168+U168+V168+X168+Y168 -> 0 | AA168: =IF(Z168<>0,(Z168/(E168+F168)),0) -> 0 | AB168: 0 | AC168: 0 | AD168: =+Z168-AC168 -> 0
A169: WIP 2 | B169: =C169&H169 -> 301717210396 | C169: 301717 | D169: CNC Qualcomm RIDE 5 50-74190-1 TOP HOUSING, PAINTED, RIDE 5 | E169: 451 | F169: 88 | G169: =+E169+F169 -> 539 | H169: 210396 | I169: CA Qualcomm RIDE 5 50-74190-1 TOP HOUSING, PAINTED, RIDE 5 | J169: CNC 1 | K169: 1 | L169: 1 | M169: PCS | N169: =K169*(E169+F169) -> 539 | P169: =IF(AND(Z169<>0,G169<>0),Z169/G169,"") -> 55928.176 | Q169: 13065726 | R169: 0 | S169: =VLOOKUP(C169,'Working Hours'!A:I,9,0)*G169 -> 79.0713 | T169: =S169/SUM($S$114:$S$245) -> 0.0015725091 | U169: =SUMIF('Re-allowcate'!C:C,C169,'Re-allowcate'!N:N) -> 4535146.7 | V169: =SUMIFS('Manufacturing Cost.'!N:N,'Manufacturing Cost.'!G:G,"627",'Manufacturing Cost.'!H:H,"CNC1")*T169+SUMIF('Re-allowcate'!C:C,C169,'Re-allowcate'!J:J) -> 9287858.4 | W169: =S169/SUM($S$7:$S$507) -> 0.00028805324 | X169: =SUMIFS('Manufacturing Cost.'!N:N,'Manufacturing Cost.'!H:H,"indirect",'Manufacturing Cost.'!G:G,"627")*W169 -> 3256555.4 | Y169: =SUMIF(Outsoucing!D:D,C169,Outsoucing!J:J) -> 0 | Z169: =Q169+R169+U169+V169+X169+Y169 -> 30145287 | AA169: =IF(Z169<>0,(Z169/(E169+F169)),0) -> 55928.176 | AB169: QUALCOM | AC169: 30145287 | AD169: =+Z169-AC169 -> 0
A170: WIP 2 | B170: =C170&H170 -> 301719551241 | C170: 301719 | D170: CNC Qualcomm RIDE 5 50-74192-1 PCIe Cover | E170: 0 | F170: 0 | G170: =+E170+F170 -> 0 | H170: 551241 | I170: IN Qualcomm RIDE 5 50-74192-1 PCIe Cover | J170: CNC 1 | K170: 1 | L170: 1 | M170: PCS | N170: =K170*(E170+F170) -> 0 | P170: =IF(AND(Z170<>0,G170<>0),Z170/G170,"") | Q170: 0 | R170: 0 | S170: =VLOOKUP(C170,'Working Hours'!A:I,9,0)*G170 -> 0 | T170: =S170/SUM($S$114:$S$236) -> 0 | U170: =SUMIF('Re-allowcate'!C:C,C170,'Re-allowcate'!N:N) -> 0 | V170: =SUMIFS('Manufacturing Cost.'!N:N,'Manufacturing Cost.'!G:G,"627",'Manufacturing Cost.'!H:H,"CNC1")*T170+SUMIF('Re-allowcate'!C:C,C170,'Re-allowcate'!J:J) -> 0 | W170: =S170/SUM($S$7:$S$507) -> 0 | X170: =SUMIFS('Manufacturing Cost.'!N:N,'Manufacturing Cost.'!H:H,"indirect",'Manufacturing Cost.'!G:G,"627")*W170 -> 0 | Y170: =SUMIF(Outsoucing!D:D,C170,Outsoucing!J:J) -> 0 | Z170: =Q170+R170+U170+V170+X170+Y170 -> 0 | AA170: =IF(Z170<>0,(Z170/(E170+F170)),0) -> 0 | AB170: QUALCOM | AC170: 0 | AD170: =+Z170-AC170 -> 0
A171: WIP 2 | B171: =C171&H171 -> 301720210397 | C171: 301720 | D171: CNC Qualcomm RIDE 5 50-74194-1 BOTTOM HOUSING, PAINTED, BASE UNIT, RIDE 5 | E171: 0 | F171: 0 | G171: =+E171+F171 -> 0 | H171: 210397 | I171: CA Qualcomm RIDE 5 50-74194-1 BOTTOM HOUSING, PAINTED, BASE UNIT, RIDE 5 | J171: CNC 1 | K171: 1 | L171: 1 | M171: PCS | N171: =K171*(E171+F171) -> 0 | Q171: 0 | R171: 0 | S171: =VLOOKUP(C171,'Working Hours'!A:I,9,0)*G171 -> 0 | T171: =S171/SUM($S$114:$S$236) -> 0 | U171: =SUMIF('Re-allowcate'!C:C,C171,'Re-allowcate'!N:N) -> 0 | V171: =SUMIFS('Manufacturing Cost.'!N:N,'Manufacturing Cost.'!G:G,"627",'Manufacturing Cost.'!H:H,"CNC1")*T171+SUMIF('Re-allowcate'!C:C,C171,'Re-allowcate'!J:J) -> 0 | W171: =S171/SUM($S$7:$S$507) -> 0 | X171: =SUMIFS('Manufacturing Cost.'!N:N,'Manufacturing Cost.'!H:H,"indirect",'Manufacturing Cost.'!G:G,"627")*W171 -> 0 | Y171: =SUMIF(Outsoucing!D:D,C171,Outsoucing!J:J) -> 0 | Z171: =Q171+R171+U171+V171+X171+Y171 -> 0 | AA171: =IF(Z171<>0,(Z171/(E171+F171)),0) -> 0 | AB171: 0 | AC171: 0 | AD171: =+Z171-AC171 -> 0
A172: WIP 2 | B172: =C172&H172 -> 301721763952 | C172: 301721 | D172: CNC Qualcomm RIDE 5 50-74195-1 FRONT COVER, PAINTED, BASE UNIT, RIDE 5 | E172: 0 | F172: 0 | G172: =+E172+F172 -> 0 | H172: 763952 | I172: Ride 5 Materials AL 6063 Block 1/Phôi nhôm AL 6063 kích thước 230*95*6T | J172: CNC 1 | K172: 1 | L172: 1 | M172: PCS | N172: =K172*(E172+F172) -> 0 | P172: =IF(AND(Z172<>0,G172<>0),Z172/G172,"") | Q172: 0 | R172: 0 | S172: =VLOOKUP(C172,'Working Hours'!A:I,9,0)*G172 -> 0 | T172: =S172/SUM($S$114:$S$236) -> 0 | U172: =SUMIF('Re-allowcate'!C:C,C172,'Re-allowcate'!N:N) -> 0 | V172: =SUMIFS('Manufacturing Cost.'!N:N,'Manufacturing Cost.'!G:G,"627",'Manufacturing Cost.'!H:H,"CNC1")*T172+SUMIF('Re-allowcate'!C:C,C172,'Re-allowcate'!J:J) -> 0 | W172: =S172/SUM($S$7:$S$507) -> 0 | X172: =SUMIFS('Manufacturing Cost.'!N:N,'Manufacturing Cost.'!H:H,"indirect",'Manufacturing Cost.'!G:G,"627")*W172 -> 0 | Y172: =SUMIF(Outsoucing!D:D,C172,Outsoucing!J:J) -> 0 | Z172: =Q172+R172+U172+V172+X172+Y172 -> 0 | AA172: =IF(Z172<>0,(Z172/(E172+F172)),0) -> 0 | AB172: 0 | AC172: 0 | AD172: =+Z172-AC172 -> 0
A173: WIP 2 | B173: =C173&H173 -> 301722763952 | C173: 301722 | D173: CNC Qualcomm RIDE 5 50-74196-1 REAR COVER, PAINTED, BASE UNIT, RIDE 5 | E173: 293 | F173: 1 | G173: =+E173+F173 -> 294 | H173: 763952 | I173: Ride 5 Materials AL 6063 Block 1/Phôi nhôm AL 6063 kích thước 230*95*6T | J173: CNC 1 | K173: 1 | L173: 1 | M173: PCS | N173: =K173*(E173+F173) -> 294 | P173: =IF(AND(Z173<>0,G173<>0),Z173/G173,"") -> 168641.66 | Q173: 0 | R173: 25524057 | S173: =VLOOKUP(C173,'Working Hours'!A:I,9,0)*G173 -> 150.3516 | T173: =S173/SUM($S$114:$S$245) -> 0.0029900767 | U173: =SUMIF('Re-allowcate'!C:C,C173,'Re-allowcate'!N:N) -> 2473716.4 | V173: =SUMIFS('Manufacturing Cost.'!N:N,'Manufacturing Cost.'!G:G,"627",'Manufacturing Cost.'!H:H,"CNC1")*T173+SUMIF('Re-allowcate'!C:C,C173,'Re-allowcate'!J:J) -> 15390636 | W173: =S173/SUM($S$7:$S$507) -> 0.0005477242 | X173: =SUMIFS('Manufacturing Cost.'!N:N,'Manufacturing Cost.'!H:H,"indirect",'Manufacturing Cost.'!G:G,"627")*W173 -> 6192238.1 | Y173: =SUMIF(Outsoucing!D:D,C173,Outsoucing!J:J) -> 0 | Z173: =Q173+R173+U173+V173+X173+Y173 -> 49580647 | AA173: =IF(Z173<>0,(Z173/(E173+F173)),0) -> 168641.66 | AB173: QUALCOM | AC173: 49580647 | AD173: =+Z173-AC173 -> 0
A174: WIP 2 | B174: =C174&H174 -> 301679713130 | C174: 301679 | D174: CNC Qualcomm Front Jig CA90-58484-1 REV AA CNC Machining Jig | E174: 0 | F174: 0 | G174: =+E174+F174 -> 0 | H174: 713130 | I174: Aluminium alloy/Tấm nhôm kích thước 450*200*30 | J174: CNC 1 | K174: 1 | L174: 1 | M174: PCS | N174: =K174*(E174+F174) -> 0 | P174: =IF(AND(Z174<>0,G174<>0),Z174/G174,"") | Q174: 0 | R174: 0 | S174: =VLOOKUP(C174,'Working Hours'!A:I,9,0)*G174 -> 0 | T174: =S174/SUM($S$114:$S$236) -> 0 | U174: =SUMIF('Re-allowcate'!C:C,C174,'Re-allowcate'!N:N) -> 0 | V174: =SUMIFS('Manufacturing Cost.'!N:N,'Manufacturing Cost.'!G:G,"627",'Manufacturing Cost.'!H:H,"CNC1")*T174+SUMIF('Re-allowcate'!C:C,C174,'Re-allowcate'!J:J) -> 0 | W174: =S174/SUM($S$7:$S$507) -> 0 | X174: =SUMIFS('Manufacturing Cost.'!N:N,'Manufacturing Cost.'!H:H,"indirect",'Manufacturing Cost.'!G:G,"627")*W174 -> 0 | Y174: =SUMIF(Outsoucing!D:D,C174,Outsoucing!J:J) -> 0 | Z174: =Q174+R174+U174+V174+X174+Y174 -> 0 | AA174: =IF(Z174<>0,(Z174/(E174+F174)),0) -> 0 | AC174: 0 | AD174: =+Z174-AC174 -> 0
A175: WIP 2 | B175: =C175&H175 -> 301680713130 | C175: 301680 | D175: CNC Qualcomm Jig 55-71907-1 REV AA CNC Machining Jig | E175: 0 | F175: 0 | G175: =+E175+F175 -> 0 | H175: 713130 | I175: Aluminium alloy/Tấm nhôm kích thước 450*200*30 | J175: CNC 1 | K175: 1 | L175: 1 | M175: PCS | N175: =K175*(E175+F175) -> 0 | P175: =IF(AND(Z175<>0,G175<>0),Z175/G175,"") | Q175: 0 | R175: 0 | S175: =VLOOKUP(C175,'Working Hours'!A:I,9,0)*G175 -> 0 | T175: =S175/SUM($S$114:$S$236) -> 0 | U175: =SUMIF('Re-allowcate'!C:C,C175,'Re-allowcate'!N:N) -> 0 | V175: =SUMIFS('Manufacturing Cost.'!N:N,'Manufacturing Cost.'!G:G,"627",'Manufacturing Cost.'!H:H,"CNC1")*T175+SUMIF('Re-allowcate'!C:C,C175,'Re-allowcate'!J:J) -> 0 | W175: =S175/SUM($S$7:$S$507) -> 0 | X175: =SUMIFS('Manufacturing Cost.'!N:N,'Manufacturing Cost.'!H:H,"indirect",'Manufacturing Cost.'!G:G,"627")*W175 -> 0 | Y175: =SUMIF(Outsoucing!D:D,C175,Outsoucing!J:J) -> 0 | Z175: =Q175+R175+U175+V175+X175+Y175 -> 0 | AA175: =IF(Z175<>0,(Z175/(E175+F175)),0) -> 0 | AC175: 0 | AD175: =+Z175-AC175 -> 0
...

Sheet Piv
B1: TB | C1: 622
A3: =C3&D3 | B3: Sum of Pro cost
B4: Expense Allocation Group.Code | C4: Expense Allocation Group | D4: Department | E4: Total
B5: 41070100 | C5: Direct labour costs | D5: Production 1 | E5: 874420444
B6: 41070100 | C6: Direct labour costs | D6: Production 2 | E6: 1507469792
B7: 41070100 | C7: Direct labour costs | D7: Production 3 | E7: 1225735086
B8: 41070101 | C8: Direct labour costs-Overtime | D8: Production 1 | E8: 816675102
B9: 41070101 | C9: Direct labour costs-Overtime | D9: Production 2 | E9: 1161826090
B10: 41070101 | C10: Direct labour costs-Overtime | D10: Production 3 | E10: 1021161665
B11: 41070102 | C11: Direct labour cost-Trade union | D11: Production 1 | E11: 14993000
B12: 41070102 | C12: Direct labour cost-Trade union | D12: Production 2 | E12: 24378000
B13: 41070102 | C13: Direct labour cost-Trade union | D13: Production 3 | E13: 21494900
B14: 41070104 | C14: Direct labour costs - Labor- SHUI | D14: Production 1 | E14: 163158750
B15: 41070104 | C15: Direct labour costs - Labor- SHUI | D15: Production 2 | E15: 261853500
B16: 41070104 | C16: Direct labour costs - Labor- SHUI | D16: Production 3 | E16: 231664188
... B22: 41070105 | C22: Direct labour costs- Labor - Outsourcing | D22: Production 3 | E22: 52884300
B23: Grand Total | E23: 7812211598
J213: 3.3839429e+10
J214: =+J213-G214 -> 3.3839429e+10

Sheet Book GL
A1: Loại | B1: Description | C1: ERP | D1: Acc name | E1: VAS | F1: Nợ | G1: Có | H1: Department | I1: Dept. Code
A2: 1- Kết chuyển chi nhân công trực tiếp | B2: Kết chuyển chi phí nhân công TT/ Transfer Derect cost labour | C2: 41070100 | D2: Direct labour costs | E2: 622 | G2: 874420444 | H2: Production 1
B3: Kết chuyển chi phí nhân công TT/ Transfer Derect cost labour | C3: 41070100 | D3: Direct labour costs | E3: 622 | G3: 1507469792 | H3: Production 2
B4: Kết chuyển chi phí nhân công TT/ Transfer Derect cost labour | C4: 41070100 | D4: Direct labour costs | E4: 622 | G4: 1225735086 | H4: Production 3
B5: Kết chuyển chi phí nhân công TT/ Transfer Derect cost labour | C5: 41070101 | D5: Direct labour costs-Overtime | E5: 622 | G5: 816675102 | H5: Production 1
B6: Kết chuyển chi phí nhân công TT/ Transfer Derect cost labour | C6: 41070101 | D6: Direct labour costs-Overtime | E6: 622 | G6: 1161826090 | H6: Production 2
B7: Kết chuyển chi phí nhân công TT/ Transfer Derect cost labour W | C7: 41070101 | D7: Direct labour costs-Overtime | E7: 622 | G7: 1021161665 | H7: Production 3
B8: Kết chuyển chi phí nhân công TT/ Transfer Derect cost labour | C8: 41070102 | D8: Direct labour cost-Trade union | E8: 622 | G8: 14993000 | H8: Production 1
B9: Kết chuyển chi phí nhân công TT/ Transfer Derect cost labour | C9: 41070102 | D9: Direct labour cost-Trade union | E9: 622 | G9: 24378000 | H9: Production 2
B10: Kết chuyển chi phí nhân công TT/ Transfer Derect cost labour | C10: 41070102 | D10: Direct labour cost-Trade union | E10: 622 | G10: 21494900 | H10: Production 3
B11: Kết chuyển chi phí nhân công TT/ Transfer Derect cost labour | C11: 41070104 | D11: Direct labour costs - Labor- SHUI | E11: 622 | G11: 163158750 | H11: Production 1
B12: Kết chuyển chi phí nhân công TT/ Transfer Derect cost labour | C12: 41070104 | D12: Direct labour costs - Labor- SHUI | E12: 622 | G12: 261853500 | H12: Production 2
B13: Kết chuyển chi phí nhân công TT/ Transfer Derect cost labour | C13: 41070104 | D13: Direct labour costs - Labor- SHUI | E13: 622 | G13: 231664188 | H13: Production 3
B14: Kết chuyển chi phí nhân công TT/ Transfer Derect cost labour | C14: 41070103 | D14: Direct labour costs- bonus | E14: 622 | G14: 48495799 | H14: Production 1
... B19: Kết chuyển chi phí nhân công TT/ Transfer Derect cost labour | C19: 41070105 | D19: Direct labour costs- Labor - Outsourcing | E19: 622 | G19: 52884300 | H19: Production 3
B20: Kết chuyển chi phí nhân công TT/ Transfer Derect cost labour | C20: 41010201 | D20: Production costs - labor - basic wage | E20: 631 | F20: =SUMIF($H$2:$H$19,H20,$G$2:$G$19) -> 1988815495 | H20: Production 1
B21: Kết chuyển chi phí nhân công TT/ Transfer Derect cost labour | C21: 41010201 | D21: Production costs - labor - basic wage | E21: 631 | F21: =SUMIF($H$2:$H$19,H21,$G$2:$G$19) -> 3192297686 | H21: Production 2
B22: Kết chuyển chi phí nhân công TT/ Transfer Derect cost labour | C22: 41010201 | D22: Production costs - labor - basic wage | E22: 631 | F22: =SUMIF($H$2:$H$19,H22,$G$2:$G$19) -> 2631098417 | H22: Production 3
F23: =SUM(F20:F22) -> 7812211598 | G23: =SUM(G2:G19) -> 7812211598
A24: 1- Kết chuyển chí gia công ngoài
B25: Kết chuyển chi phí gia công ngoài /trsf OS fee for Anodizing | C25: 12220100 | D25: Material purchasing | E25: trsf | G25: =+F31 -> 212278388 | H25: Production 1
B26: Kết chuyển chi phí gia công ngoài /trsf OS fee for lasering | C26: 12220100 | D26: Material purchasing | E26: trsf | H26: Production 2
B27: Kết chuyển chi phí gia công ngoài /trsf OS fee for Painting (UV) | C27: 12220100 | D27: Material purchasing | E27: trsf | G27: =Outsoucing!J2-G30-G25 -> 1065490056 | H27: Production 3
B28: Kết chuyển chi phí gia công ngoài /trsf OS fee for CNC model Stand cover | C28: 12220100 | D28: Material purchasing | E28: trsf
B29: Kết chuyển chi phí gia công ngoài /trsf OS fee for CNC model J100, NX4, ACP housing | C29: 12220100 | D29: Material purchasing | E29: trsf
B30: Kết chuyển chi phí gia công ngoài /trsf OS fee for sand blasting model BYD housing/Phí gia công phun cát tháng 07.2024 | C30: 41059802 | D30: Manufacturing costs - Outsourcing fee | E30: 627 | G30: 61258284 | H30: Production 3
B31: Kết chuyển chi phí gia công ngoài W2 | C31: 41010400 | D31: Production costs - Outsoucing | E31: 631 | F31: =+COSTING!Y113 -> 212278388 | H31: Production 1
B32: Kết chuyển chi phí gia công ngoài W2 | C32: 41010400 | D32: Production costs - Outsoucing | E32: 631 | F32: =+COSTING!Y269 -> 206497200 | H32: Production 2
B33: Kết chuyển chi phí gia công ngoài W3 | C33: 41010400 | D33: Production costs - Outsoucing | E33: 631 | F33: =+COSTING!Y536 -> 920251140 | H33: Production 3
F34: =SUM(F25:F33) -> 1339026728 | G34: =SUM(G25:G32) -> 1339026728
A35: 3- Kết chuyển chi phí NVL xuất cho SX
B36: kết chuyển chi phí NVL trực tiếp / Trsf RM to calculate costing | C36: 41080100 | D36: Direct raw material costs | E36: 621 | G36: =COSTING!Q113+COSTING!R113 -> 1.782456e+10 | H36: Production 1 | I36: 0501
B37: kết chuyển chi phí NVL trực tiếp / Trsf RM to calculate costing | C37: 41080100 | D37: Direct raw material costs | E37: 621 | G37: =COSTING!R269 -> 3.3842751e+08 | H37: Production 2 | I37: 0502
B38: kết chuyển chi phí NVL trực tiếp / Trsf RM to calculate costing | C38: 41080100 | D38: Direct raw material costs | E38: 621 | G38: =COSTING!R536-G39 -> 4.8534825e+09 | H38: Production 3 | I38: 0503
B39: kết chuyển chi phí NVL trực tiếp / Trsf RM to calculate costing Mold | C39: 41080100 | D39: Direct raw material costs | E39: 621 | G39: 1.6963051e+08 | H39: Production 3 | I39: 0503 | J39: FG-mold
B40: kết chuyển chi phí NVL trực tiếp / Trsf RM to calculate costing | C40: 41010100 | D40: Production costs - materials | E40: 631 | F40: =+G36 -> 1.782456e+10 | H40: Production 1 | I40: 0501
B41: kết chuyển chi phí NVL trực tiếp / Trsf RM to calculate costing | C41: 41010100 | D41: Production costs - materials | E41: 631 | F41: =+G37 -> 3.3842751e+08 | G41: =+F37 -> 0 | H41: Production 2 | I41: 0502
B42: kết chuyển chi phí NVL trực tiếp / Trsf RM to calculate costing | C42: 41010100 | D42: Production costs - materials | E42: 631 | F42: =+G38+G39 -> 5.023113e+09 | G42: =+F38+F39 -> 0 | H42: Production 3 | I42: 0503
F43: =SUM(F36:F42) -> 2.3186101e+10 | G43: =SUM(G36:G42) -> 2.3186101e+10
A44: 4- Kết chuyển chi phí CCDC xuất cho SX
B45: Kết chuyển chi phí CCDC cho SX/ Trsf Tool to calculate costing | C45: 41051505 | D45: Manufacturing costs - production Supplies - labor supplies | E45: 627 | N45: 41051505 | O45: Manufacturing costs - production Supplies - labor supplies | P45: Production | R45: 14699000
B46: Kết chuyển chi phí CCDC cho SX/ Trsf Tool to calculate costing | C46: 41051505 | D46: Manufacturing costs - production Supplies - labor supplies | E46: 627 | N46: 41051505 | O46: Manufacturing costs - production Supplies - labor supplies | P46: Utility | R46: 260000
B47: Kết chuyển chi phí CCDC cho SX/ Trsf Tool to calculate costing | C47: 41051401 | D47: Manufacturing costs - supplies - office supplies | E47: 627 | N47: 41051401 | O47: Manufacturing costs - supplies - office supplies | P47: Mold | R47: 45600.003
B48: Kết chuyển chi phí CCDC cho SX/ Trsf Tool to calculate costing | C48: 41051404 | D48: Manufacturing costs - supplies - other | E48: 627 | N48: 41051404 | O48: Manufacturing costs - supplies - other | P48: Mold | R48: 4.4274217e+08
B49: Kết chuyển chi phí CCDC cho SX/ Trsf Tool to calculate costing | C49: 41051404 | D49: Manufacturing costs - supplies - other | E49: 627 | N49: 41051404 | O49: Manufacturing costs - supplies - other | P49: Production 1 | R49: 2.430817e+09
B50: Kết chuyển chi phí CCDC cho SX/ Trsf Tool to calculate costing | C50: 41051404 | D50: Manufacturing costs - supplies - other | E50: 627 | N50: 41051404 | O50: Manufacturing costs - supplies - other | P50: Production 2 | R50: 1.4278756e+09
B51: Kết chuyển chi phí CCDC cho SX/ Trsf Tool to calculate costing | C51: 41051404 | D51: Manufacturing costs - supplies - other | E51: 627 | N51: 41051404 | O51: Manufacturing costs - supplies - other | P51: Production 3 | R51: 1.1073561e+08
B52: Kết chuyển chi phí CCDC cho SX/ Trsf Tool to calculate costing | C52: 41051404 | D52: Manufacturing costs - supplies - other | E52: 627 | N52: 41051404 | O52: Manufacturing costs - supplies - other | P52: QC | R52: 6294412.3
B53: Kết chuyển chi phí CCDC cho SX/ Trsf Tool to calculate costing | C53: 41051404 | D53: Manufacturing costs - supplies - other | E53: 627 | N53: 41051404 | O53: Manufacturing costs - supplies - other | P53: Utility | R53: 3630189.7
B54: Kết chuyển chi phí CCDC cho SX/ Trsf Tool to calculate costing | C54: 41051404 | D54: Manufacturing costs - supplies - other | E54: 627 | N54: 41051404 | O54: Manufacturing costs - supplies - other | P54: Warehouse | R54: 3.2965726e+08
B55: Kết chuyển chi phí CCDC cho SX/ Trsf Tool to calculate costing | C55: 41051505 | D55: Manufacturing costs - production Supplies - labor | E55: 627 | N55: 41051505 | O55: Manufacturing costs - production Supplies - labor | P55: Mold | R55: 18881900
B56: Kết chuyển chi phí CCDC cho SX/ Trsf Tool to calculate costing | C56: 41051505 | D56: Manufacturing costs - production Supplies - labor | E56: 627 | N56: 41051505 | O56: Manufacturing costs - production Supplies - labor | P56: Production 1 | R56: 1.1603093e+08
B57: Kết chuyển chi phí CCDC cho SX/ Trsf Tool to calculate costing | C57: 41051505 | D57: Manufacturing costs - production Supplies - labor | E57: 627 | N57: 41051505 | O57: Manufacturing costs - production Supplies - labor | P57: Production 2 | R57: 86804197
B58: Kết chuyển chi phí CCDC cho SX/ Trsf Tool to calculate costing | C58: 41051505 | D58: Manufacturing costs - production Supplies - labor | E58: 627 | N58: 41051505 | O58: Manufacturing costs - production Supplies - labor | P58: Production 3 | R58: 15675954
... B66: Kết chuyển chi phí CCDC cho SX/ Trsf Tool to calculate costing | C66: 41059801 | D66: Manufacturing costs - other | E66: 627 | N66: 41059801 | O66: Manufacturing costs - other | P66: Production 3 | R66: 11132292
B67: Kết chuyển chi phí CCDC cho SX/ Trsf Tool to calculate costing | C67: 41010300 | D67: Production costs - manufacturing costs | E67: 631
B68: Kết chuyển chi phí CCDC cho SX/ Trsf Tool to calculate costing | C68: 41010300 | D68: Production costs - manufacturing costs | E68: 631
B69: Kết chuyển chi phí CCDC cho SX/ Trsf Tool to calculate costing | C69: 41010300 | D69: Production costs - manufacturing costs | E69: 631
B70: Kết chuyển chi phí CCDC cho SX/ Trsf Tool to calculate costing | C70: 41010300 | D70: Production costs - manufacturing costs | E70: 631
B71: Kết chuyển chi phí CCDC cho SX/ Trsf Tool to calculate costing | C71: 41010300 | D71: Production costs - manufacturing costs | E71: 631
B72: Kết chuyển chi phí CCDC cho SX/ Trsf Tool to calculate costing | C72: 41010300 | D72: Production costs - manufacturing costs | E72: 631
B73: Kết chuyển chi phí CCDC cho SX/ Trsf Tool to calculate costing | C73: 41010300 | D73: Production costs - manufacturing costs | E73: 631
B74: Kết chuyển chi phí CCDC cho SX/ Trsf Tool to calculate costing | C74: 41010300 | D74: Production costs - manufacturing costs | E74: 631
F75: =SUM(F45:F74) -> 0 | G75: =SUM(G45:G74) -> 0
A76: 5- Kết chuyển chi phí SXC
B77: Kết chuyển chi phí sản xuất chung tính giá thành sx/Trsf overhead cost to calculate costing | C77: 41051505 | D77: Manufacturing costs - Local staff salary - basic wage | H77: Production
B78: Kết chuyển chi phí sản xuất chung tính giá thành sx/Trsf overhead cost to calculate costing | C78: 41051505 | D78: Manufacturing costs - Local staff salary - basic wage | H78: Production 1
B79: Kết chuyển chi phí sản xuất chung tính giá thành sx/Trsf overhead cost to calculate costing | C79: 41051505 | D79: Manufacturing costs - Local staff salary - basic wage | H79: Production 2
B80: Kết chuyển chi phí sản xuất chung tính giá thành sx/Trsf overhead cost to calculate costing | C80: 41051505 | D80: Manufacturing costs - Local staff salary - basic wage | H80: Production 3
B81: Kết chuyển chi phí sản xuất chung tính giá thành sx/Trsf overhead cost to calculate costing | C81: 41051505 | D81: Manufacturing costs - Local staff salary - basic wage | H81: Production Plan
B82: Kết chuyển chi phí sản xuất chung tính giá thành sx/Trsf overhead cost to calculate costing | C82: 41051505 | D82: Manufacturing costs - Local staff salary - basic wage | H82: QC
B83: Kết chuyển chi phí sản xuất chung tính giá thành sx/Trsf overhead cost to calculate costing | C83: 41052208 | D83: Manufacturing costs - Local staff salary - basic wage | H83: Utility
B84: Kết chuyển chi phí sản xuất chung tính giá thành sx/Trsf overhead cost to calculate costing | C84: 41052208 | D84: Manufacturing costs - Local staff salary - basic wage | H84: Warehouse
B85: Kết chuyển chi phí sản xuất chung tính giá thành sx/Trsf overhead cost to calculate costing | C85: 41050101 | D85: Manufacturing costs - Local staff salary - Overtime | E85: 627 | H85: Production
B86: Kết chuyển chi phí sản xuất chung tính giá thành sx/Trsf overhead cost to calculate costing | C86: 41050101 | D86: Manufacturing costs - Local staff salary - Overtime | E86: 627 | H86: Production 1
B87: Kết chuyển chi phí sản xuất chung tính giá thành sx/Trsf overhead cost to calculate costing | C87: 41050101 | D87: Manufacturing costs - Local staff salary - Overtime | E87: 627 | H87: Production 2
B88: Kết chuyển chi phí sản xuất chung tính giá thành sx/Trsf overhead cost to calculate costing | C88: 41050101 | D88: Manufacturing costs - Local staff salary - Overtime | E88: 627 | H88: Production 3
B89: Kết chuyển chi phí sản xuất chung tính giá thành sx/Trsf overhead cost to calculate costing | C89: 41050101 | D89: Manufacturing costs - Local staff salary - Overtime | E89: 627 | H89: Production Plan
B90: Kết chuyển chi phí sản xuất chung tính giá thành sx/Trsf overhead cost to calculate costing | C90: 41050101 | D90: Manufacturing costs - Local staff salary - Overtime | E90: 627 | H90: QC
B91: Kết chuyển chi phí sản xuất chung tính giá thành sx/Trsf overhead cost to calculate costing | C91: 41050101 | D91: Manufacturing costs - Local staff salary - Overtime | E91: 627 | H91: Utility
B92: Kết chuyển chi phí sản xuất chung tính giá thành sx/Trsf overhead cost to calculate costing | C92: 41050101 | D92: Manufacturing costs - Local staff salary - Overtime | H92: Warehouse
B93: Kết chuyển chi phí sản xuất chung tính giá thành sx/Trsf overhead cost to calculate costing | C93: 41050102 | D93: Manufacturing costs - Local staff salary - bonuses | H93: Production
B94: Kết chuyển chi phí sản xuất chung tính giá thành sx/Trsf overhead cost to calculate costing | C94: 41050102 | D94: Manufacturing costs - Local staff salary - bonuses | H94: Production 1
B95: Kết chuyển chi phí sản xuất chung tính giá thành sx/Trsf overhead cost to calculate costing | C95: 41050102 | D95: Manufacturing costs - Local staff salary - bonuses | H95: Production 2
B96: Kết chuyển chi phí sản xuất chung tính giá thành sx/Trsf overhead cost to calculate costing | C96: 41050102 | D96: Manufacturing costs - Local staff salary - bonuses | H96: Production 3
B97: Kết chuyển chi phí sản xuất chung tính giá thành sx/Trsf overhead cost to calculate costing | C97: 41050102 | D97: Manufacturing costs - Local staff salary - bonuses | H97: Production Plan
B98: Kết chuyển chi phí sản xuất chung tính giá thành sx/Trsf overhead cost to calculate costing | C98: 41050102 | D98: Manufacturing costs - Local staff salary - bonuses | H98: QC
B99: Kết chuyển chi phí sản xuất chung tính giá thành sx/Trsf overhead cost to calculate costing | C99: 41050102 | D99: Manufacturing costs - Local staff salary - bonuses | H99: Utility
B100: Kết chuyển chi phí sản xuất chung tính giá thành sx/Trsf overhead cost to calculate costing | C100: 41050102 | D100: Manufacturing costs - Local staff salary - bonuses | H100: Warehouse
B101: Kết chuyển chi phí sản xuất chung tính giá thành sx/Trsf overhead cost to calculate costing | C101: 41050105 | D101: Manufacturing costs - Expatriates- basic wage | H101: Production 1
B102: Kết chuyển chi phí sản xuất chung tính giá thành sx/Trsf overhead cost to calculate costing | C102: 41050105 | D102: Manufacturing costs - Expatriates- basic wage | H102: Production 3
B103: Kết chuyển chi phí sản xuất chung tính giá thành sx/Trsf overhead cost to calculate costing | C103: 41050105 | D103: Manufacturing costs - Expatriates- basic wage | H103: QC
... B217: Kết chuyển chi phí sản xuất chung tính giá thành sx/Trsf overhead cost to calculate costing | C217: 41052101 | D217: Manufacturing costs - security | H217: Production
B218: Kết chuyển chi phí sản xuất chung tính giá thành sx/Trsf overhead cost to calculate costing | C218: 41052101 | D218: Manufacturing costs - sewage charges | E218: 627 | H218: Mold
B219: Kết chuyển chi phí sản xuất chung tính giá thành sx/Trsf overhead cost to calculate costing | C219: 41052101 | D219: Manufacturing costs - sewage charges | E219: 627 | H219: Production
B220: Kết chuyển chi phí sản xuất chung tính giá thành sx/Trsf overhead cost to calculate costing | C220: 41052101 | D220: Manufacturing costs - sewage charges | E220: 627 | H220: Production 1
B221: Kết chuyển chi phí sản xuất chung tính giá thành sx/Trsf overhead cost to calculate costing | C221: 41052101 | D221: Manufacturing costs - sewage charges | H221: Production 2
B222: Kết chuyển chi phí sản xuất chung tính giá thành sx/Trsf overhead cost to calculate costing | C222: 41052202 | D222: Manufacturing costs - sewage charges | H222: Production 3
B223: Kết chuyển chi phí sản xuất chung tính giá thành sx/Trsf overhead cost to calculate costing | C223: 41052202 | D223: Manufacturing costs - sewage charges | H223: QC
B224: Kết chuyển chi phí sản xuất chung tính giá thành sx/Trsf overhead cost to calculate costing | C224: 41052202 | D224: Manufacturing costs - sewage charges | H224: Warehouse
...

Sheet Manufacturing Cost.
M1: 622 | N1: 627 | O1: Inventory Management
K2: =COSTING!U113-M2 -> 0 | L2: 0501 | M2: =+SUMIFS($N$10:$N$380,$G$10:$G$380,$M$1,$H$10:$H$380,$L2) -> 1988815495 | N2: =+SUMIFS($N$10:$N$380,$G$10:$G$380,$N$1,$H$10:$H$380,$L2) -> 9.2859369e+09 | O2: =SUMIFS($N$9:$N$421,$O$9:$O$421,$O$1,$H$9:$H$421,L2) -> 1.8913901e+09 | P2: =SUBTOTAL(9,N2:O2) -> 1.1177327e+10
K3: =M3-COSTING!U536 -> 0 | L3: 0503 | M3: =+SUMIFS($N$10:$N$380,$G$10:$G$380,$M$1,$H$10:$H$380,$L3) -> 2631098417 | N3: =+SUMIFS($N$10:$N$380,$G$10:$G$380,$N$1,$H$10:$H$380,$L3) -> 2.7615923e+09 | O3: =SUMIFS($N$9:$N$421,$O$9:$O$421,$O$1,$H$9:$H$421,L3) -> 3.0780027e+08 | P3: =SUBTOTAL(9,N3:O3) -> 3.0693926e+09
J4: =+J6-J5 -> 61258279 | K4: =M4+M5-COSTING!U269 -> 0 | L4: CNC1 | M4: =+SUMIFS($M$10:$M$380,$G$10:$G$380,$M$1,$H$10:$H$380,$L4) -> 1838795093 | N4: =+SUMIFS($N$10:$N$380,$G$10:$G$380,$N$1,$H$10:$H$380,$L4) -> 3791911443 | O4: =SUMIFS($N$9:$N$421,$O$9:$O$421,$O$1,$H$9:$H$421,L4) -> 1.0499567e+09 | P4: =SUBTOTAL(9,N4:O4) -> 4.8418682e+09
J5: 2.2929396e+09 | L5: CNC2 | M5: =+SUMIFS($N$10:$N$380,$G$10:$G$380,$M$1,$H$10:$H$380,$L5) -> 1353502593 | N5: =+SUMIFS($N$10:$N$380,$G$10:$G$380,$N$1,$H$10:$H$380,$L5) -> 3279187011 | O5: =SUMIFS($N$9:$N$421,$O$9:$O$421,$O$1,$H$9:$H$421,L5) -> 1.1490907e+09 | P5: =SUBTOTAL(9,N5:O5) -> 4.4282777e+09
J6: =+J8-J7 -> 2.3541978e+09 | K6: =COSTING!X4-'Manufacturing Cost.'!N6-O6 -> -5.4836273e-06 | L6: Indirect | M6: =+SUMIFS($N$10:$N$380,$G$10:$G$380,$M$1,$H$10:$H$380,$L6) -> 0 | N6: =+SUMIFS($N$10:$N$380,$G$10:$G$380,$N$1,$H$10:$H$380,$L6) -> 1.0207615e+10 | O6: =SUMIFS($N$9:$N$421,$O$9:$O$421,$O$1,$H$9:$H$421,L6) -> 1.0977797e+09 | P6: =SUBTOTAL(9,M6:O6) -> 1.1305394e+10
J7: 1277768444 | M7: =SUM(M2:M6) -> 7812211598 | N7: =SUM(N2:N6) -> 2.9326242e+10 | O7: =SUM(O2:O6) -> 5.4960174e+09 | P7: =SUBTOTAL(9,N7:O7) -> 3.482226e+10 | Q7: =SUM(M7:O7)-COSTING!U4-COSTING!V4-COSTING!X4+'Re-allowcate'!J18 -> -0.23185635
I8: 3.2958209e+10 | J8: =+I8-N7 -> 3.6319663e+09 | M8: =SUM(M10:M421)-'Re-allowcate'!J27-'Re-allowcate'!N27 -> -5.0407 | N8: =SUM(N10:N475)+SUMIF(G9:G379,"622",M9:M379)=(M7+N7+O7) -> TRUE
A9: Booking Period | B9: Cost Field | C9: Cost Type | D9: Expense Allocation Group.Code | E9: Expense Allocation Group | F9: Department | G9: TB | H9: Dept | I9: Work Center | J9: Name CC | K9: PL Daily Schedule | L9: Current Level Cost | M9: Re-alowcate | N9: Total Cost | O9: Source Application.Name | P9: Pro cost | Q9: Item.Finance Classes.Class Code | R9: Labor
C10: GL | D10: 41050101 | E10: Manufacturing costs - Local staff salary - basic wage | F10: Warehouse | G10: 627 | H10: Indirect | I10: C-6400 | J10: Warehouse | N10: 112381706 | O10: General Ledger | P10: =+M10+N10 -> 112381706
C11: GL | D11: 41050101 | E11: Manufacturing costs - Local staff salary - basic wage | F11: Utility | G11: 627 | H11: Indirect | I11: C-6000 | J11: Prod support | N11: 445206179 | O11: General Ledger | P11: =+M11+N11 -> 445206179
C12: GL | D12: 41050101 | E12: Manufacturing costs - Local staff salary - basic wage | F12: QC | G12: 627 | H12: Indirect | I12: C-6000 | J12: Prod support | N12: 694735314 | O12: General Ledger | P12: =+M12+N12 -> 694735314
C13: GL | D13: 41050101 | E13: Manufacturing costs - Local staff salary - basic wage | F13: Production Plan | G13: 627 | H13: Indirect | I13: C-6100 | J13: Prod Plan | N13: 94708065 | O13: General Ledger | P13: =+M13+N13 -> 94708065
C14: GL | D14: 41050101 | E14: Manufacturing costs - Local staff salary - basic wage | F14: Production 3 | G14: 627 | H14: 0503 | I14: C-2200 | J14: Polishing | N14: 118114436 | O14: General Ledger | P14: =+M14+N14 -> 118114436
C15: GL | D15: 41050101 | E15: Manufacturing costs - Local staff salary - basic wage | F15: Production 3 | G15: 627 | H15: 0503 | I15: C-2220 | J15: Hot press | N15: 22235962 | O15: General Ledger | P15: =+M15+N15 -> 22235962
C16: GL | D16: 41050101 | E16: Manufacturing costs - Local staff salary - basic wage | F16: Production 3 | G16: 627 | H16: 0503 | I16: C-2400 | J16: N-Chromate | N16: 37878672 | O16: General Ledger | P16: =+M16+N16 -> 37878672
C17: GL | D17: 41050101 | E17: Manufacturing costs - Local staff salary - basic wage | F17: Production 3 | G17: 627 | H17: 0503 | I17: C-2600 | J17: Injection | N17: 45233627 | O17: General Ledger | P17: =+M17+N17 -> 45233627
C18: GL | D18: 41050101 | E18: Manufacturing costs - Local staff salary - basic wage | F18: Production 3 | G18: 627 | H18: 0503 | I18: C-3200 | J18: Assembly | N18: 121371845 | O18: General Ledger | P18: =+M18+N18 -> 121371845
C19: GL | D19: 41050101 | E19: Manufacturing costs - Local staff salary - basic wage | F19: Production 2 | G19: 627 | H19: CNC1 | I19: C-2110 | J19: CNC1 | N19: 90115468 | O19: General Ledger | P19: =+M19+N19 -> 90115468
C20: GL | D20: 41050101 | E20: Manufacturing costs - Local staff salary - basic wage | F20: Production 2 | G20: 627 | H20: CNC2 | I20: C-2120 | J20: CNC2 | N20: 123913872 | O20: General Ledger | P20: =+M20+N20 -> 123913872
C21: GL | D21: 41050101 | E21: Manufacturing costs - Local staff salary - basic wage | F21: Production 2 | G21: 627 | H21: CNC1 | I21: C-2110-6 | J21: CNC1 Auto LG | N21: 63425302 | O21: General Ledger | P21: =+M21+N21 -> 63425302
... C157: GL | D157: 41051806 | E157: Manufacturing costs - rental - car rental for staff | F157: Mold | G157: 627 | H157: Indirect | I157: C-6300 | J157: Mold Dev | N157: 41352613 | O157: General Ledger | P157: =+M157+N157 -> 41352613
C158: GL | D158: 41051807 | E158: Manufacturing costs - rental - crane | F158: Production 2 | G158: 627 | H158: CNC2 | I158: C-2120 | J158: CNC2 | M158: 170332500 | O158: General Ledger | P158: =+M158+N158 -> 170332500
C159: GL | D159: 41051807 | E159: Manufacturing costs - rental - crane | F159: Production 2 | G159: 627 | H159: CNC1 | I159: C-2110-6 | J159: CNC1 Auto LG | M159: 459897750 | O159: General Ledger | P159: =+M159+N159 -> 459897750
C160: GL | D160: 41051807 | E160: Manufacturing costs - rental - crane | F160: Production 2 | G160: 627 | H160: CNC1 | I160: C-2110-5 | J160: CNC1 Auto Mando | M160: 51099750 | O160: General Ledger | P160: =+M160+N160 -> 51099750
C161: GL | D161: 41051807 | E161: Manufacturing costs - rental - crane | F161: Production 1 | G161: 627 | H161: 0501 | I161: C-1100 | J161: Casting | N161: 65512500 | O161: General Ledger | P161: =+M161+N161 -> 65512500
C162: GL | D162: 41051809 | E162: Manufacturing costs - rental - equipment | F162: QC | G162: 627 | H162: Indirect | I162: C-6000 | J162: Prod support | N162: 2941300 | O162: General Ledger | P162: =+M162+N162 -> 2941300
C163: GL | D163: 41051809 | E163: Manufacturing costs - rental - equipment | F163: Production 2 | G163: 627 | H163: CNC1 | I163: C-2110 | J163: CNC1 | N163: 3775600 | O163: General Ledger | P163: =+M163+N163 -> 3775600
C164: GL | D164: 41051809 | E164: Manufacturing costs - rental - equipment | F164: Production 1 | G164: 627 | H164: 0501 | I164: C-1100 | J164: Casting | N164: 1250000 | O164: General Ledger | P164: =+M164+N164 -> 1250000
C165: GL | D165: 41051901 | E165: Manufacturing costs - trade union - trade union | F165: Warehouse | G165: 627 | H165: Indirect | I165: C-6400 | J165: Warehouse | N165: 1954327 | O165: General Ledger | P165: =+M165+N165 -> 1954327
C166: GL | D166: 41051901 | E166: Manufacturing costs - trade union - trade union | F166: Utility | G166: 627 | H166: Indirect | I166: C-6000 | J166: Prod support | N166: 7491667 | O166: General Ledger | P166: =+M166+N166 -> 7491667
C167: GL | D167: 41051901 | E167: Manufacturing costs - trade union - trade union | F167: QC | G167: 627 | H167: Indirect | I167: C-6000 | J167: Prod support | N167: 14666912 | O167: General Ledger | P167: =+M167+N167 -> 14666912
C168: GL | D168: 41051901 | E168: Manufacturing costs - trade union - trade union | F168: Production Plan | G168: 627 | H168: Indirect | I168: C-6100 | J168: Prod Plan | N168: 1834376 | O168: General Ledger | P168: =+M168+N168 -> 1834376
C169: GL | D169: 41051901 | E169: Manufacturing costs - trade union - trade union | F169: Production 3 | G169: 627 | H169: 0503 | I169: C-2200 | J169: Polishing | N169: 3034159 | O169: General Ledger | P169: =+M169+N169 -> 3034159
C170: GL | D170: 41051901 | E170: Manufacturing costs - trade union - trade union | F170: Production 3 | G170: 627 | H170: 0503 | I170: C-2220 | J170: Hot press | N170: 370000 | O170: General Ledger | P170: =+M170+N170 -> 370000
C171: GL | D171: 41051901 | E171: Manufacturing costs - trade union - trade union | F171: Production 3 | G171: 627 | H171: 0503 | I171: C-2400 | J171: N-Chromate | N171: 641040 | O171: General Ledger | P171: =+M171+N171 -> 641040
C172: GL | D172: 41051901 | E172: Manufacturing costs - trade union - trade union | F172: Production 3 | G172: 627 | H172: 0503 | I172: C-2600 | J172: Injection | N172: 874556 | O172: General Ledger | P172: =+M172+N172 -> 874556
... C177: GL | D177: 41051901 | E177: Manufacturing costs - trade union - trade union | F177: Production 2 | G177: 627 | H177: CNC1 | I177: C-2110-5 | J177: CNC1 Auto Mando | N177: 1714216 | O177: General Ledger | P177: =+M177+N177 -> 1714216
C178: GL | D178: 41051901 | E178: Manufacturing costs - trade union - trade union | F178: Production 2 | G178: 627 | H178: CNC1 | I178: C-2110-4 | J178: CNC1 Auto ZF | N178: 361645 | P178: =+M178+N178 -> 361645
C179: GL | D179: 41051901 | E179: Manufacturing costs - trade union - trade union | F179: Production 2 | G179: 627 | H179: CNC1 | I179: C-2110-1 | J179: CNC1 Mobile Braket | N179: 594743 | P179: =+M179+N179 -> 594743
C180: GL | D180: 41051901 | E180: Manufacturing costs - trade union - trade union | F180: Production 1 | G180: 627 | H180: 0501 | I180: C-1100 | J180: Casting | N180: 11262475 | P180: =+M180+N180 -> 11262475
C181: GL | D181: 41051901 | E181: Manufacturing costs - trade union - trade union | F181: Production 1 | G181: 627 | H181: 0501 | I181: C-1110 | J181: Trimming | N181: 2161130 | P181: =+M181+N181 -> 2161130
C182: GL | D182: 41051901 | E182: Manufacturing costs - trade union - trade union | F182: Production 1 | G182: 627 | H182: 0501 | I182: C-1140 | J182: Internal Magie_EHS | N182: 767500 | P182: =+M182+N182 -> 767500
C183: GL | D183: 41051901 | E183: Manufacturing costs - trade union - trade union | F183: Production | G183: 627 | H183: Indirect | I183: C-6000 | J183: Prod support | N183: 2574393 | P183: =+M183+N183 -> 2574393
C184: GL | D184: 41051901 | E184: Manufacturing costs - trade union - trade union | F184: Mold | G184: 627 | H184: Indirect | I184: C-6300 | J184: Mold Dev | N184: 6496640 | P184: =+M184+N184 -> 6496640
C185: GL | D185: 41052101 | E185: Manufacturing costs - depreciation | F185: Warehouse | G185: 627 | H185: Indirect | I185: 0 | J185: (blank) | N185: 10879630 | O185: General Ledger | P185: =+M185+N185 -> 10879630
C186: GL | D186: 41052101 | E186: Manufacturing costs - depreciation | F186: Utility | G186: 627 | H186: Indirect | I186: 0 | J186: (blank) | N186: 45687048 | O186: General Ledger | P186: =+M186+N186 -> 45687048
C187: GL | D187: 41052101 | E187: Manufacturing costs - depreciation | F187: QC | G187: 627 | H187: Indirect | I187: 0 | J187: (blank) | N187: 2.5111214e+08 | O187: General Ledger | P187: =+M187+N187 -> 2.5111214e+08
C188: GL | D188: 41052101 | E188: Manufacturing costs - depreciation | F188: QC | G188: 627 | H188: Indirect | I188: C-6000 | J188: Prod support | N188: 19699544 | O188: General Ledger | P188: =+M188+N188 -> 19699544
C189: GL | D189: 41052101 | E189: Manufacturing costs - depreciation | F189: Production 3 | G189: 627 | H189: 0503 | I189: 0 | J189: (blank) | N189: 3.8641484e+08 | O189: General Ledger | P189: =+M189+N189 -> 3.8641484e+08
C190: GL | D190: 41052101 | E190: Manufacturing costs - depreciation | F190: Production 2 | G190: 627 | H190: CNC1 | J190: ALL | M190: 9.8834365e+08 | O190: General Ledger | P190: =+M190+N190 -> 9.8834365e+08
C191: GL | D191: 41052101 | E191: Manufacturing costs - depreciation | F191: Production 2 | G191: 627 | H191: CNC1 | I191: C-2110 | J191: CNC1 | M191: 6.2326592e+08 | O191: General Ledger | P191: =+M191+N191 -> 6.2326592e+08
C192: GL | D192: 41052101 | E192: Manufacturing costs - depreciation | F192: Production 1 | G192: 627 | H192: 0501 | I192: 0 | J192: (blank) | N192: 1.433163e+09 | O192: General Ledger | P192: =+M192+N192 -> 1.433163e+09
C193: GL | D193: 41052101 | E193: Manufacturing costs - depreciation | F193: Production 1 | G193: 627 | H193: 0501 | I193: C-1100 | J193: Casting | N193: 254920727 | O193: General Ledger | P193: =+M193+N193 -> 254920727
C194: GL | D194: 41052101 | E194: Manufacturing costs - depreciation | F194: Production 1 | G194: 627 | H194: 0501 | I194: C-1110 | J194: Trimming | N194: 41584884 | O194: General Ledger | P194: =+M194+N194 -> 41584884
C195: GL | D195: 41052101 | E195: Manufacturing costs - depreciation | F195: Production | G195: 627 | H195: Indirect | I195: 0 | J195: (blank) | N195: 8.1469672e+08 | O195: General Ledger | P195: =+M195+N195 -> 8.1469672e+08
C196: GL | D196: 41052101 | E196: Manufacturing costs - depreciation | F196: Production | G196: 627 | H196: Indirect | I196: C-1000 | J196: Production | N196: 7500000 | O196: General Ledger | P196: =+M196+N196 -> 7500000
C197: GL | D197: 41052101 | E197: Manufacturing costs - depreciation | F197: Mold | G197: 627 | H197: Indirect | I197: 0 | J197: (blank) | N197: 26156117 | O197: General Ledger | P197: =+M197+N197 -> 26156117
C198: GL | D198: 41052101 | E198: Manufacturing costs - depreciation | F198: Mold | G198: 627 | H198: Indirect | I198: C-6300 | J198: Mold Dev | N198: 1.0502073e+08 | O198: General Ledger | P198: =+M198+N198 -> 1.0502073e+08
C199: GL | D199: 41052202 | E199: Manufacturing costs - Amortization - Supplies | F199: QC | G199: 627 | H199: Indirect | I199: C-6000 | J199: Prod support | N199: 14896424 | O199: General Ledger | P199: =+M199+N199 -> 14896424
C200: GL | D200: 41052202 | E200: Manufacturing costs - Amortization - Supplies | F200: Production 3 | G200: 627 | H200: 0503 | I200: C-2200 | J200: Polishing | N200: 104221645 | O200: General Ledger | P200: =+M200+N200 -> 104221645
C201: GL | D201: 41052202 | E201: Manufacturing costs - Amortization - Supplies | F201: Production 3 | G201: 627 | H201: 0503 | I201: C-2400 | J201: N-Chromate | N201: 13088889 | O201: General Ledger | P201: =+M201+N201 -> 13088889
C202: GL | D202: 41052202 | E202: Manufacturing costs - Amortization - Supplies | F202: Production 3 | G202: 627 | H202: 0503 | I202: C-2420 | J202: Cleaning | N202: 9291667 | O202: General Ledger | P202: =+M202+N202 -> 9291667
C203: GL | D203: 41052202 | E203: Manufacturing costs - Amortization - Supplies | F203: Production 3 | G203: 627 | H203: 0503 | I203: C-2500 | J203: Painting | N203: 10583333 | O203: General Ledger | P203: =+M203+N203 -> 10583333
... C281: GL | D281: 41070100 | E281: Direct labour costs | F281: Production 3 | G281: 622 | H281: 0503 | I281: C-3200 | J281: Assembly | N281: 301811272 | O281: General Ledger | P281: =+M281+N281 -> 301811272
C282: GL | D282: 41070100 | E282: Direct labour costs | F282: Production 2 | G282: 622 | H282: CNC1 | I282: C-2110 | J282: CNC1 | M282: 19990628 | O282: General Ledger | P282: =+M282+N282 -> 19990628
C283: GL | D283: 41070100 | E283: Direct labour costs | F283: Production 2 | G283: 622 | H283: CNC2 | I283: C-2120 | J283: CNC2 | N283: 665338717 | O283: General Ledger | P283: =+M283+N283 -> 665338717
C284: GL | D284: 41070100 | E284: Direct labour costs | F284: Production 2 | G284: 622 | H284: CNC1 | I284: C-2110-6 | J284: CNC1 Auto LG | M284: 397344005 | O284: General Ledger | P284: =+M284+N284 -> 397344005
C285: GL | D285: 41070100 | E285: Direct labour costs | F285: Production 2 | G285: 622 | H285: CNC1 | I285: C-2110-5 | J285: CNC1 Auto Mando | M285: 189444303 | O285: General Ledger | P285: =+M285+N285 -> 189444303
C286: GL | D286: 41070100 | E286: Direct labour costs | F286: Production 2 | G286: 622 | H286: CNC1 | I286: C-2110-4 | J286: CNC1 Auto ZF | M286: 151554538 | O286: General Ledger | P286: =+M286+N286 -> 151554538
C287: GL | D287: 41070100 | E287: Direct labour costs | F287: Production 2 | G287: 622 | H287: CNC1 | I287: C-2110-1 | J287: CNC1 Mobile Braket | M287: 54737380 | O287: General Ledger | P287: =+M287+N287 -> 54737380
C288: GL | D288: 41070100 | E288: Direct labour costs | F288: Production 2 | G288: 622 | H288: CNC1 | I288: C-2110-2 | J288: CNC1 Mobile Qualcom | M288: 29060221 | O288: General Ledger | P288: =+M288+N288 -> 29060221
C289: GL | D289: 41070100 | E289: Direct labour costs | F289: Production 1 | G289: 622 | H289: 0501 | I289: C-1100 | J289: Casting | N289: 463200554 | O289: General Ledger | P289: =+M289+N289 -> 463200554
C290: GL | D290: 41070100 | E290: Direct labour costs | F290: Production 1 | G290: 622 | H290: 0501 | I290: C-1110 | J290: Trimming | N290: 353872255 | O290: General Ledger | P290: =+M290+N290 -> 353872255
C291: GL | D291: 41070100 | E291: Direct labour costs | F291: Production 1 | G291: 622 | H291: 0501 | I291: C-1140 | J291: Internal Magie_EHS | N291: 57347635 | O291: General Ledger | P291: =+M291+N291 -> 57347635
C292: GL | D292: 41070101 | E292: Direct labour costs-Overtime | F292: Production 3 | G292: 622 | H292: 0503 | I292: C-2200 | J292: Polishing | N292: 650617837 | O292: General Ledger | P292: =+M292+N292 -> 650617837
C293: GL | D293: 41070101 | E293: Direct labour costs-Overtime | F293: Production 3 | G293: 622 | H293: 0503 | I293: C-2220 | J293: Hot press | N293: 32833534 | O293: General Ledger | P293: =+M293+N293 -> 32833534
C294: GL | D294: 41070101 | E294: Direct labour costs-Overtime | F294: Production 3 | G294: 622 | H294: 0503 | I294: C-2400 | J294: N-Chromate | N294: 77906895 | O294: General Ledger | P294: =+M294+N294 -> 77906895
C295: GL | D295: 41070101 | E295: Direct labour costs-Overtime | F295: Production 3 | G295: 622 | H295: 0503 | I295: C-2600 | J295: Injection | N295: 15121707 | O295: General Ledger | P295: =+M295+N295 -> 15121707
C296: GL | D296: 41070101 | E296: Direct labour costs-Overtime | F296: Production 3 | G296: 622 | H296: 0503 | I296: C-3200 | J296: Assembly | N296: 244681692 | O296: General Ledger | P296: =+M296+N296 -> 244681692
C297: GL | D297: 41070101 | E297: Direct labour costs-Overtime | F297: Production 2 | G297: 622 | H297: CNC1 | I297: C-2110 | J297: CNC1 | M297: 11557237 | O297: General Ledger | P297: =+M297+N297 -> 11557237
C298: GL | D298: 41070101 | E298: Direct labour costs-Overtime | F298: Production 2 | G298: 622 | H298: CNC2 | I298: C-2120 | J298: CNC2 | N298: 525234403 | O298: General Ledger | P298: =+M298+N298 -> 525234403
C299: GL | D299: 41070101 | E299: Direct labour costs-Overtime | F299: Production 2 | G299: 622 | H299: CNC1 | I299: C-2110-6 | J299: CNC1 Auto LG | M299: 304932474 | O299: General Ledger | P299: =+M299+N299 -> 304932474
C300: GL | D300: 41070101 | E300: Direct labour costs-Overtime | F300: Production 2 | G300: 622 | H300: CNC1 | I300: C-2110-5 | J300: CNC1 Auto Mando | M300: 146368006 | O300: General Ledger | P300: =+M300+N300 -> 146368006
C301: GL | D301: 41070101 | E301: Direct labour costs-Overtime | F301: Production 2 | G301: 622 | H301: CNC1 | I301: C-2110-4 | J301: CNC1 Auto ZF | M301: 123104329 | O301: General Ledger | P301: =+M301+N301 -> 123104329
C302: GL | D302: 41070101 | E302: Direct labour costs-Overtime | F302: Production 2 | G302: 622 | H302: CNC1 | I302: C-2110-1 | J302: CNC1 Mobile Braket | M302: 35514953 | O302: General Ledger | P302: =+M302+N302 -> 35514953
C303: GL | D303: 41070101 | E303: Direct labour costs-Overtime | F303: Production 2 | G303: 622 | H303: CNC1 | I303: C-2110-2 | J303: CNC1 Mobile Qualcom | M303: 15114688 | O303: General Ledger | P303: =+M303+N303 -> 15114688
C304: GL | D304: 41070101 | E304: Direct labour costs-Overtime | F304: Production 1 | G304: 622 | H304: 0501 | I304: C-1100 | J304: Casting | N304: 443167448 | O304: General Ledger | P304: =+M304+N304 -> 443167448
C305: GL | D305: 41070101 | E305: Direct labour costs-Overtime | F305: Production 1 | G305: 622 | H305: 0501 | I305: C-1110 | J305: Trimming | N305: 324322151 | O305: General Ledger | P305: =+M305+N305 -> 324322151
C306: GL | D306: 41070101 | E306: Direct labour costs-Overtime | F306: Production 1 | G306: 622 | H306: 0501 | I306: C-1140 | J306: Internal Magie_EHS | N306: 49185503 | O306: General Ledger | P306: =+M306+N306 -> 49185503
C307: GL | D307: 41070102 | E307: Direct labour cost-Trade union | F307: Production 3 | G307: 622 | H307: 0503 | I307: C-2200 | J307: Polishing | N307: 13152750 | O307: General Ledger | P307: =+M307+N307 -> 13152750
C308: GL | D308: 41070102 | E308: Direct labour cost-Trade union | F308: Production 3 | G308: 622 | H308: 0503 | I308: C-2220 | J308: Hot press | N308: 790000 | O308: General Ledger | P308: =+M308+N308 -> 790000
C309: GL | D309: 41070102 | E309: Direct labour cost-Trade union | F309: Production 3 | G309: 622 | H309: 0503 | I309: C-2400 | J309: N-Chromate | N309: 1924850 | O309: General Ledger | P309: =+M309+N309 -> 1924850
C310: GL | D310: 41070102 | E310: Direct labour cost-Trade union | F310: Production 3 | G310: 622 | H310: 0503 | I310: C-2600 | J310: Injection | N310: 402000 | O310: General Ledger | P310: =+M310+N310 -> 402000
C311: GL | D311: 41070102 | E311: Direct labour cost-Trade union | F311: Production 3 | G311: 622 | H311: 0503 | I311: C-3200 | J311: Assembly | N311: 5225300 | O311: General Ledger | P311: =+M311+N311 -> 5225300
C312: GL | D312: 41070102 | E312: Direct labour cost-Trade union | F312: Production 2 | G312: 622 | H312: CNC2 | I312: C-2120 | J312: CNC2 | N312: 10604000 | O312: General Ledger | P312: =+M312+N312 -> 10604000
C313: GL | D313: 41070102 | E313: Direct labour cost-Trade union | F313: Production 2 | G313: 622 | H313: CNC1 | I313: C-2110-6 | J313: CNC1 Auto LG | M313: 6712000 | O313: General Ledger | P313: =+M313+N313 -> 6712000
C314: GL | D314: 41070102 | E314: Direct labour cost-Trade union | F314: Production 2 | G314: 622 | H314: CNC1 | I314: C-2110-5 | J314: CNC1 Auto Mando | M314: 3150000 | O314: General Ledger | P314: =+M314+N314 -> 3150000
C315: GL | D315: 41070102 | E315: Direct labour cost-Trade union | F315: Production 2 | G315: 622 | H315: CNC1 | I315: C-2110-4 | J315: CNC1 Auto ZF | M315: 2470000 | O315: General Ledger | P315: =+M315+N315 -> 2470000
C316: GL | D316: 41070102 | E316: Direct labour cost-Trade union | F316: Production 2 | G316: 622 | H316: CNC1 | I316: C-2110-1 | J316: CNC1 Mobile Braket | M316: 912000 | O316: General Ledger | P316: =+M316+N316 -> 912000
...

Sheet Re-allowcate
E1: CNC machines | G1: Other machines | I1: TOT DPRECIATION | K1: Account code | L1: Name acc
A2: Kind | B2: KHÁCH HÀNG | C2: Cost center | D2: NameCC | E2: Qty machines | F2: Depre in Apr.26 | G2: Qty machines | H2: Depre in APr.26 | I2: Qty machines | J2: Depre amt
A3: TSCĐ Fix assets | B3: All Cus | C3: C-2110 | D3: CNC1 | G3: 33 | H3: 2.2855319e+08 | I3: =+E3+G3 -> 33 | J3: =+F3+H3 -> 2.2855319e+08 | K3: 41052101 | L3: Manufacturing costs - depreciation | M3: CNC1
B4: A-PROJECT | C4: C-2110-3 | D4: CNC1 Others A | E4: 6 | F4: 1.3452417e+08 | G4: 7 | H4: 34793535 | I4: =+E4+G4 -> 13 | J4: =+F4+H4 -> 1.6931771e+08 | K4: 41052101 | L4: Manufacturing costs - depreciation | M4: CNC1
B5: Braket | C5: C-2110-1 | D5: CNC1 Mobile Braket | G5: 8 | H5: 62030136 | I5: =+E5+G5 -> 8 | J5: =+F5+H5 -> 62030136 | K5: 41052101 | L5: Manufacturing costs - depreciation | M5: CNC1
B6: LG | C6: C-2110-6 | D6: CNC1 Auto LG | E6: 29 | F6: 2.5167446e+08 | G6: 55 | H6: 2.3461865e+08 | I6: =+E6+G6 -> 84 | J6: =+F6+H6 -> 4.8629311e+08 | K6: 41052101 | L6: Manufacturing costs - depreciation | M6: CNC1
B7: MANDO | C7: C-2110-5 | D7: CNC1 Auto Mando | E7: 4 | F7: 9660995.4 | G7: 4 | H7: 4859949.1 | I7: =+E7+G7 -> 8 | J7: =+F7+H7 -> 14520944 | K7: 41052101 | L7: Manufacturing costs - depreciation | M7: CNC1
B8: QUALCOM | C8: C-2110-2 | D8: CNC1 Mobile Qualcom | E8: 2 | F8: 3122651.4 | I8: =+E8+G8 -> 2 | J8: =+F8+H8 -> 3122651.4 | K8: 41052101 | L8: Manufacturing costs - depreciation | M8: CNC1
B9: ZF | C9: C-2110-4 | D9: CNC1 Auto ZF | E9: 8 | F9: 32539905 | I9: =+E9+G9 -> 8 | J9: =+F9+H9 -> 32539905 | K9: 41052101 | L9: Manufacturing costs - depreciation | M9: CNC1
A10: TSTTC Financial FA | B10: All Cus | C10: C-2110 | D10: CNC1 | G10: 1 | H10: 19434786 | I10: =+E10+G10 -> 1 | J10: =+F10+H10 -> 19434786 | K10: 41052101 | L10: Manufacturing costs - depreciation | M10: CNC1
B11: LG | C11: C-2110-6 | D11: CNC1 Auto LG | E11: 32 | F11: 2.1602645e+08 | G11: 10 | H11: 2.1994824e+08 | I11: =+E11+G11 -> 42 | J11: =+F11+H11 -> 4.3597468e+08 | K11: 41052101 | L11: Manufacturing costs - depreciation | M11: CNC1
B12: MANDO | C12: C-2110-5 | D12: CNC1 Auto Mando | E12: 16 | F12: 1.0102483e+08 | I12: =+E12+G12 -> 16 | J12: =+F12+H12 -> 1.0102483e+08 | K12: 41052101 | L12: Manufacturing costs - depreciation | M12: CNC1
B13: QUALCOM | C13: C-2110-2 | D13: CNC1 Mobile Qualcom | E13: 2 | F13: 15792370 | I13: =+E13+G13 -> 2 | J13: =+F13+H13 -> 15792370 | K13: 41052101 | L13: Manufacturing costs - depreciation | M13: CNC1
B14: ZF | C14: C-2110-4 | D14: CNC1 Auto ZF | E14: 6 | F14: 43005247 | I14: =+E14+G14 -> 6 | J14: =+F14+H14 -> 43005247 | K14: 41052101 | L14: Manufacturing costs - depreciation | M14: CNC1
A15: Thuê MFG Rental Machines | B15: LG | C15: C-2110-6 | D15: CNC1 Auto LG | E15: 27 | F15: 459897750 | I15: =+E15+G15 -> 27 | J15: =+F15+H15 -> 459897750 | K15: 41051807 | L15: Manufacturing costs - rental - Machines | M15: CNC1
B16: MANDO | C16: C-2110-5 | D16: CNC1 Auto Mando | E16: 3 | F16: 51099750 | I16: =+E16+G16 -> 3 | J16: =+F16+H16 -> 51099750 | K16: 41051807 | L16: Manufacturing costs - rental - Machines | M16: CNC1
B17: SEVT | C17: C-2120 | D17: CNC2 | E17: 10 | F17: 170332500 | I17: =+E17+G17 -> 10 | J17: =+F17+H17 -> 170332500 | K17: 41051807 | L17: Manufacturing costs - rental - Machines | M17: CNC1
A18: Grand Total | E18: =SUM(E3:E17) -> 145 | F18: 1.5310655e+09 | G18: 115 | H18: 7.8645054e+08 | I18: =SUM(I3:I17) -> 263 | J18: =SUM(J3:J17)+5 -> 2.2929396e+09
A20: Chi phí 242 Long term prepaid | B20: LG | C20: C-2110-6 | D20: CNC1 Auto LG | J20: 46559588 | K20: 41052202 | L20: Manufacturing costs - Amortization - Supplies | M20: CNC1
B21: MANDO | C21: C-2110-5 | D21: CNC1 Auto Mando | J21: 10085319 | K21: 41052202 | L21: Manufacturing costs - Amortization - Supplies | M21: CNC1
B22: MANDO | C22: C-6300-5 | D22: Mold Auto Mando | J22: 20333371 | K22: 41052203 | L22: Manufacturing costs - Amortization - Mold | M22: Mold
B23: ZF | C23: C-6300-4 | D23: Mold Auto ZF | J23: 52874559 | K23: 41052203 | L23: Manufacturing costs - Amortization - Mold | M23: Mold
B24: Braket | C24: C-6300-1 | D24: Mold Mobile Braket | J24: 48835371 | K24: 41052203 | L24: Manufacturing costs - Amortization - Mold | M24: Mold
G25: =ROUND(G27,0)=ROUND(SUM(G28:G89),0) -> TRUE | I25: =ROUND(I27,0)=ROUND(SUM(I28:I89),0) -> TRUE | J25: =J27=J18 -> TRUE | K25: =ROUND(K27,0)=ROUND(SUM(K28:K81),0) -> TRUE | M25: =ROUND(M27,0)=ROUND(SUM(M28:M81),0) -> TRUE
B26: KHÁCH HÀNG | C26: WIP code | D26: Name Code | E26: Qty Pro | F26: Rate detail | G26: Amt-Allowcate | H26: Rate common | I26: Amt-Allowcate (all model) | J26: ALLOWCATE-Depre | N26: ALLOWCATE-Salary
B27: All Cus | G27: =J18-I27 -> 2.0449516e+09 | I27: =SUMIF($B$3:$B$17,B27,$J$3:$J$17) -> 2.4798798e+08 | J27: =+G27+I27 -> 2.2929396e+09 | K27: =+'Realowcate Salary-CNC1'!F31-'Re-allowcate'!M27 -> 1659599528 | L27: Rate | M27: =SUM('Realowcate Salary-CNC1'!F2:F5) -> 179195565 | N27: =SUM(N28:N81) -> 1.8387951e+09 | O27: =N27='Manufacturing Cost.'!M4 -> TRUE | P27: =J27+N27-'Manufacturing Cost.'!M8 -> 4.1317347e+09
B28: A-PROJECT | C28: 301766 | D28: CNC A 149-0313-002 FRAME, WORLD SIDE, BUCK HMD | E28: =SUMIF(COSTING!C:C,C28,COSTING!G:G) -> 20 | F28: =E28/SUMIF($B$28:$B$89,B28,$E$28:$E$89) -> 0.035335689 | G28: =SUMIF($B$3:$B$17,B28,$J$3:$J$17)*F28+I27/(SUM($E$28:$E$81)*E28) -> 5982963 | H28: =+E28/SUM($E$28:$E$89) -> 7.1356145e-06 | I28: =+H28*$I$27 -> 1769.5466 | J28: =+G28+I28 -> 5984732.5 | K28: =SUMIF('Realowcate Salary-CNC1'!G:G,B28,'Realowcate Salary-CNC1'!F:F) -> 0 | L28: =+E28/SUM($E$28:$E$81) -> 8.2186692e-06 | M28: =+L28*$M$27 -> 1472.7491 | N28: =+K28+M28 -> 1472.7491
B29: A-PROJECT | C29: 301767 | D29: CNC A 149-0314-002 FRAME, EYE SIDE, BUCK HMD | E29: =SUMIF(COSTING!C:C,C29,COSTING!G:G) -> 73 | F29: =E29/SUMIF($B$28:$B$89,B29,$E$28:$E$89) -> 0.12897527 | G29: =SUMIF($B$3:$B$17,B29,$J$3:$J$17)*F29+I28/(SUM($E$28:$E$81)*E29) -> 21837796 | H29: =+E29/SUM($E$28:$E$89) -> 2.6044993e-05 | I29: =+H29*$I$27 -> 6458.845 | J29: =+G29+I29 -> 21844255 | K29: =SUMIF('Realowcate Salary-CNC1'!G:G,B29,'Realowcate Salary-CNC1'!F:F) -> 0 | L29: =+E29/SUM($E$28:$E$81) -> 2.9998143e-05 | M29: =+L29*$M$27 -> 5375.5341 | N29: =+K29+M29 -> 5375.5341
B30: A-PROJECT | C30: 301774 | D30: CNC A 149-0313-004 FRAME, WORLD SIDE, BUCK HMD | E30: =SUMIF(COSTING!C:C,C30,COSTING!G:G) -> 53 | F30: =E30/SUMIF($B$28:$B$89,B30,$E$28:$E$89) -> 0.093639576 | G30: =SUMIF($B$3:$B$17,B30,$J$3:$J$17)*F30+I29/(SUM($E$28:$E$81)*E30) -> 15854838 | H30: =+E30/SUM($E$28:$E$89) -> 1.8909378e-05 | I30: =+H30*$I$27 -> 4689.2985 | J30: =+G30+I30 -> 15859528 | K30: =SUMIF('Realowcate Salary-CNC1'!G:G,B30,'Realowcate Salary-CNC1'!F:F) -> 0 | L30: =+E30/SUM($E$28:$E$81) -> 2.1779473e-05 | M30: =+L30*$M$27 -> 3902.785 | N30: =+K30+M30 -> 3902.785
B31: A-PROJECT | C31: 301775 | D31: CNC A 147-9222-001 SIDE SHIELD, LEFT,BUCK HMD | E31: =SUMIF(COSTING!C:C,C31,COSTING!G:G) -> 100 | F31: =E31/SUMIF($B$28:$B$89,B31,$E$28:$E$89) -> 0.17667845 | G31: =SUMIF($B$3:$B$17,B31,$J$3:$J$17)*F31+I30/(SUM($E$28:$E$81)*E31) -> 29914789 | H31: =+E31/SUM($E$28:$E$89) -> 3.5678072e-05 | I31: =+H31*$I$27 -> 8847.7329 | J31: =+G31+I31 -> 29923637 | K31: =SUMIF('Realowcate Salary-CNC1'!G:G,B31,'Realowcate Salary-CNC1'!F:F) -> 0 | L31: =+E31/SUM($E$28:$E$81) -> 4.1093346e-05 | M31: =+L31*$M$27 -> 7363.7454 | N31: =+K31+M31 -> 7363.7454
B32: A-PROJECT | C32: 301776 | D32: CNC A 147-9223-001 SIDE SHIELD, RIGHT,BUCK HMD | E32: =SUMIF(COSTING!C:C,C32,COSTING!G:G) -> 140 | F32: =E32/SUMIF($B$28:$B$89,B32,$E$28:$E$89) -> 0.24734982 | G32: =SUMIF($B$3:$B$17,B32,$J$3:$J$17)*F32+I31/(SUM($E$28:$E$81)*E32) -> 41880705 | H32: =+E32/SUM($E$28:$E$89) -> 4.9949301e-05 | I32: =+H32*$I$27 -> 12386.826 | J32: =+G32+I32 -> 41893092 | K32: =SUMIF('Realowcate Salary-CNC1'!G:G,B32,'Realowcate Salary-CNC1'!F:F) -> 0 | L32: =+E32/SUM($E$28:$E$81) -> 5.7530684e-05 | M32: =+L32*$M$27 -> 10309.243 | N32: =+K32+M32 -> 10309.243
B33: A-PROJECT | C33: 301777 | D33: CNC A 150-6547-002 TEMPLE ARM, LEFT ,BUCK HMD | E33: =SUMIF(COSTING!C:C,C33,COSTING!G:G) -> 90 | F33: =E33/SUMIF($B$28:$B$89,B33,$E$28:$E$89) -> 0.1590106 | G33: =SUMIF($B$3:$B$17,B33,$J$3:$J$17)*F33+I32/(SUM($E$28:$E$81)*E33) -> 26923311 | H33: =+E33/SUM($E$28:$E$89) -> 3.2110265e-05 | I33: =+H33*$I$27 -> 7962.9597 | J33: =+G33+I33 -> 26931273 | K33: =SUMIF('Realowcate Salary-CNC1'!G:G,B33,'Realowcate Salary-CNC1'!F:F) -> 0 | L33: =+E33/SUM($E$28:$E$81) -> 3.6984011e-05 | M33: =+L33*$M$27 -> 6627.3708 | N33: =+K33+M33 -> 6627.3708
B34: A-PROJECT | C34: 301778 | D34: CNC A 150-6548-002 TEMPLE ARM, RIGHT ,BUCK HMD | E34: =SUMIF(COSTING!C:C,C34,COSTING!G:G) -> 90 | F34: =E34/SUMIF($B$28:$B$89,B34,$E$28:$E$89) -> 0.1590106 | G34: =SUMIF($B$3:$B$17,B34,$J$3:$J$17)*F34+I33/(SUM($E$28:$E$81)*E34) -> 26923311 | H34: =+E34/SUM($E$28:$E$89) -> 3.2110265e-05 | I34: =+H34*$I$27 -> 7962.9597 | J34: =+G34+I34 -> 26931273 | K34: =SUMIF('Realowcate Salary-CNC1'!G:G,B34,'Realowcate Salary-CNC1'!F:F) -> 0 | L34: =+E34/SUM($E$28:$E$81) -> 3.6984011e-05 | M34: =+L34*$M$27 -> 6627.3708 | N34: =+K34+M34 -> 6627.3708
B35: Braket | C35: 301648 | D35: CNC SM-A156E | E35: =SUMIF(COSTING!C:C,C35,COSTING!G:G) -> 46746 | F35: =E35/SUMIF($B$28:$B$89,B35,$E$28:$E$89) -> 0.041064915 | G35: =SUMIF($B$3:$B$17,B35,$J$3:$J$17)*F35+I34/(SUM($E$28:$E$81)*E35) -> 2547262.3 | H35: =+E35/SUM($E$28:$E$89) -> 0.016678072 | I35: =+H35*$I$27 -> 4135961.2 | J35: =+G35+I35 -> 6683223.5 | K35: =SUMIF('Realowcate Salary-CNC1'!G:G,B35,'Realowcate Salary-CNC1'!F:F)*F35 -> 4281599.1 | L35: =+E35/SUM($E$28:$E$81) -> 0.019209496 | M35: =+L35*$M$27 -> 3442256.4 | N35: =+K35+M35 -> 7723855.5
B36: Braket | C36: 301671 | D36: CNC LGIT T6M8 Housing 3HUC00007A | E36: =SUMIF(COSTING!C:C,C36,COSTING!G:G) -> 16591 | F36: =E36/SUMIF($B$28:$B$89,B36,$E$28:$E$89) -> 0.01457468 | G36: =SUMIF($B$3:$B$17,B36,$J$3:$J$17)*F36+I35/(SUM($E$28:$E$81)*E36) -> 904069.41 | H36: =+E36/SUM($E$28:$E$89) -> 0.005919349 | I36: =+H36*$I$27 -> 1467927.4 | J36: =+G36+I36 -> 2371996.8 | K36: =SUMIF('Realowcate Salary-CNC1'!G:G,B36,'Realowcate Salary-CNC1'!F:F)*F36 -> 1519616.9 | L36: =+E36/SUM($E$28:$E$81) -> 0.006817797 | M36: =+L36*$M$27 -> 1221719 | N36: =+K36+M36 -> 2741335.9
B37: Braket | C37: 301723 | D37: CNC SM-A366B | E37: =SUMIF(COSTING!C:C,C37,COSTING!G:G) -> 53891 | F37: =E37/SUMIF($B$28:$B$89,B37,$E$28:$E$89) -> 0.047341577 | G37: =SUMIF($B$3:$B$17,B37,$J$3:$J$17)*F37+I36/(SUM($E$28:$E$81)*E37) -> 2936604.5 | H37: =+E37/SUM($E$28:$E$89) -> 0.01922727 | I37: =+H37*$I$27 -> 4768131.8 | J37: =+G37+I37 -> 7704736.2 | K37: =SUMIF('Realowcate Salary-CNC1'!G:G,B37,'Realowcate Salary-CNC1'!F:F)*F37 -> 4936029.9 | L37: =+E37/SUM($E$28:$E$81) -> 0.022145615 | M37: =+L37*$M$27 -> 3968396 | N37: =+K37+M37 -> 8904425.9
B38: Braket | C38: 301724 | D38: CNC SM-A266B | E38: =SUMIF(COSTING!C:C,C38,COSTING!G:G) -> 24660 | F38: =E38/SUMIF($B$28:$B$89,B38,$E$28:$E$89) -> 0.021663047 | G38: =SUMIF($B$3:$B$17,B38,$J$3:$J$17)*F38+I37/(SUM($E$28:$E$81)*E38) -> 1343761.8 | H38: =+E38/SUM($E$28:$E$89) -> 0.0087982127 | I38: =+H38*$I$27 -> 2181850.9 | J38: =+G38+I38 -> 3525612.7 | K38: =SUMIF('Realowcate Salary-CNC1'!G:G,B38,'Realowcate Salary-CNC1'!F:F)*F38 -> 2258679.5 | L38: =+E38/SUM($E$28:$E$81) -> 0.010133619 | M38: =+L38*$M$27 -> 1815899.6 | N38: =+K38+M38 -> 4074579.1
B39: Braket | C39: 301736 | D39: CNC SM-A176B | E39: =SUMIF(COSTING!C:C,C39,COSTING!G:G) -> 995075 | F39: =E39/SUMIF($B$28:$B$89,B39,$E$28:$E$89) -> 0.87414261 | G39: =SUMIF($B$3:$B$17,B39,$J$3:$J$17)*F39+I38/(SUM($E$28:$E$81)*E39) -> 54223185 | H39: =+E39/SUM($E$28:$E$89) -> 0.35502358 | I39: =+H39*$I$27 -> 88041579 | J39: =+G39+I39 -> 1.4226476e+08 | K39: =SUMIF('Realowcate Salary-CNC1'!G:G,B39,'Realowcate Salary-CNC1'!F:F)*F39 -> 91141749 | L39: =+E39/SUM($E$28:$E$81) -> 0.40890961 | M39: =+L39*$M$27 -> 73274789 | N39: =+K39+M39 -> 1.6441654e+08
B40: Braket | C40: 301738 | D40: CNC Mando Brose JG RWS Cover GE844EM111 | E40: =SUMIF(COSTING!C:C,C40,COSTING!G:G) -> 285 | F40: =E40/SUMIF($B$28:$B$89,B40,$E$28:$E$89) -> 0.00025036369 | G40: =SUMIF($B$3:$B$17,B40,$J$3:$J$17)*F40+I39/(SUM($E$28:$E$81)*E40) -> 15530.22 | H40: =+E40/SUM($E$28:$E$89) -> 0.00010168251 | I40: =+H40*$I$27 -> 25216.039 | J40: =+G40+I40 -> 40746.259 | K40: =SUMIF('Realowcate Salary-CNC1'!G:G,B40,'Realowcate Salary-CNC1'!F:F)*F40 -> 26103.96 | L40: =+E40/SUM($E$28:$E$81) -> 0.00011711604 | M40: =+L40*$M$27 -> 20986.674 | N40: =+K40+M40 -> 47090.635
B41: Braket | C41: 301750 | D41: CNC SM-A376B | E41: =SUMIF(COSTING!C:C,C41,COSTING!G:G) -> 1096 | F41: =E41/SUMIF($B$28:$B$89,B41,$E$28:$E$89) -> 0.00096280211 | G41: =SUMIF($B$3:$B$17,B41,$J$3:$J$17)*F41+I40/(SUM($E$28:$E$81)*E41) -> 59722.746 | H41: =+E41/SUM($E$28:$E$89) -> 0.00039103167 | I41: =+H41*$I$27 -> 96971.153 | J41: =+G41+I41 -> 156693.9 | K41: =SUMIF('Realowcate Salary-CNC1'!G:G,B41,'Realowcate Salary-CNC1'!F:F)*F41 -> 100385.76 | L41: =+E41/SUM($E$28:$E$81) -> 0.00045038307 | M41: =+L41*$M$27 -> 80706.649 | N41: =+K41+M41 -> 181092.41
B42: LG | C42: 301161 | D42: CNC LGIT Gen3 AL5 | E42: =SUMIF(COSTING!C:C,C42,COSTING!G:G) -> 76179 | F42: =E42/SUMIF($B$28:$B$89,B42,$E$28:$E$89) -> 0.1750682 | G42: =SUMIF($B$3:$B$17,B42,$J$3:$J$17)*F42+I41/(SUM($E$28:$E$81)*E42) -> 2.4197323e+08 | H42: =+E42/SUM($E$28:$E$89) -> 0.027179199 | I42: =+H42*$I$27 -> 6740114.5 | J42: =+G42+I42 -> 2.4871334e+08 | K42: =SUMIF('Realowcate Salary-CNC1'!G:G,B42,'Realowcate Salary-CNC1'!F:F)*F42 -> 1.4115707e+08 | L42: =+E42/SUM($E$28:$E$81) -> 0.0313045 | M42: =+L42*$M$27 -> 5609627.6 | N42: =+K42+M42 -> 1.467667e+08
B43: LG | C43: 301449 | D43: CNC LGIT T6 Bearing Plate 3CVC00004A | E43: =SUMIF(COSTING!C:C,C43,COSTING!G:G) -> 24821 | F43: =E43/SUMIF($B$28:$B$89,B43,$E$28:$E$89) -> 0.057041543 | G43: =SUMIF($B$3:$B$17,B43,$J$3:$J$17)*F43+I42/(SUM($E$28:$E$81)*E43) -> 78840855 | H43: =+E43/SUM($E$28:$E$89) -> 0.0088556544 | I43: =+H43*$I$27 -> 2196095.8 | J43: =+G43+I43 -> 81036951 | K43: =SUMIF('Realowcate Salary-CNC1'!G:G,B43,'Realowcate Salary-CNC1'!F:F)*F43 -> 45992461 | L43: =+E43/SUM($E$28:$E$81) -> 0.010199779 | M43: =+L43*$M$27 -> 1827755.2 | N43: =+K43+M43 -> 47820216
B44: LG | C44: 301450 | D44: CNC LGIT T6M6 Housing 3HUC00006A | E44: =SUMIF(COSTING!C:C,C44,COSTING!G:G) -> 3607 | F44: =E44/SUMIF($B$28:$B$89,B44,$E$28:$E$89) -> 0.0082893053 | G44: =SUMIF($B$3:$B$17,B44,$J$3:$J$17)*F44+I43/(SUM($E$28:$E$81)*E44) -> 11457192 | H44: =+E44/SUM($E$28:$E$89) -> 0.0012869081 | I44: =+H44*$I$27 -> 319137.73 | J44: =+G44+I44 -> 11776330 | K44: =SUMIF('Realowcate Salary-CNC1'!G:G,B44,'Realowcate Salary-CNC1'!F:F)*F44 -> 6683647.2 | L44: =+E44/SUM($E$28:$E$81) -> 0.001482237 | M44: =+L44*$M$27 -> 265610.29 | N44: =+K44+M44 -> 6949257.5
B45: LG | C45: 301469 | D45: CNC LGIT MQ4a PE Cover | E45: =SUMIF(COSTING!C:C,C45,COSTING!G:G) -> 26587 | F45: =E45/SUMIF($B$28:$B$89,B45,$E$28:$E$89) -> 0.061100016 | G45: =SUMIF($B$3:$B$17,B45,$J$3:$J$17)*F45+I44/(SUM($E$28:$E$81)*E45) -> 84450337 | H45: =+E45/SUM($E$28:$E$89) -> 0.0094857291 | I45: =+H45*$I$27 -> 2352346.8 | J45: =+G45+I45 -> 86802684 | K45: =SUMIF('Realowcate Salary-CNC1'!G:G,B45,'Realowcate Salary-CNC1'!F:F)*F45 -> 49264798 | L45: =+E45/SUM($E$28:$E$81) -> 0.010925488 | M45: =+L45*$M$27 -> 1957799 | N45: =+K45+M45 -> 51222597
B46: LG | C46: 301511 | D46: CNC LGIT MQ4a PE Housing 3CAZ00039A | E46: =SUMIF(COSTING!C:C,C46,COSTING!G:G) -> 38503 | F46: =E46/SUMIF($B$28:$B$89,B46,$E$28:$E$89) -> 0.088484369 | G46: =SUMIF($B$3:$B$17,B46,$J$3:$J$17)*F46+I45/(SUM($E$28:$E$81)*E46) -> 1.2230005e+08 | H46: =+E46/SUM($E$28:$E$89) -> 0.013737128 | I46: =+H46*$I$27 -> 3406642.6 | J46: =+G46+I46 -> 1.2570669e+08 | K46: =SUMIF('Realowcate Salary-CNC1'!G:G,B46,'Realowcate Salary-CNC1'!F:F)*F46 -> 71344737 | L46: =+E46/SUM($E$28:$E$81) -> 0.015822171 | M46: =+L46*$M$27 -> 2835262.9 | N46: =+K46+M46 -> 74180000
... B73: QUALCOM | C73: 301768 | D73: CNC QualcommIDP CEDROS_55-PR954-80_ASSY, SUB-ASSY, REAR HOUSING | E73: =SUMIF(COSTING!C:C,C73,COSTING!G:G) -> 342 | F73: =E73/SUMIF($B$28:$B$89,B73,$E$28:$E$89) -> 0.054554155 | G73: =SUMIF($B$3:$B$17,B73,$J$3:$J$17)*F73+I72/(SUM($E$28:$E$81)*E73) -> 1031893 | H73: =+E73/SUM($E$28:$E$89) -> 0.00012201901 | I73: =+H73*$I$27 -> 30259.247 | J73: =+G73+I73 -> 1062152.3 | K73: =SUMIF('Realowcate Salary-CNC1'!G:G,B73,'Realowcate Salary-CNC1'!F:F)*F73 -> 2852404.4 | L73: =+E73/SUM($E$28:$E$81) -> 0.00014053924 | M73: =+L73*$M$27 -> 25184.009 | N73: =+K73+M73 -> 2877588.4
B74: ZF | C74: 301341 | D74: CNC ZF TRW - GM EU2L Housing A021D074 | E74: =SUMIF(COSTING!C:C,C74,COSTING!G:G) -> 50545 | F74: =E74/SUMIF($B$28:$B$89,B74,$E$28:$E$89) -> 0.10369822 | G74: =SUMIF($B$3:$B$17,B74,$J$3:$J$17)*F74+I89/(SUM($E$28:$E$81)*E74) -> 7833897.6 | H74: =+E74/SUM($E$28:$E$89) -> 0.018033482 | I74: =+H74*$I$27 -> 4472086.6 | J74: =+G74+I74 -> 12305984 | K74: =SUMIF('Realowcate Salary-CNC1'!G:G,B74,'Realowcate Salary-CNC1'!F:F)*F74 -> 32418883 | L74: =+E74/SUM($E$28:$E$81) -> 0.020770632 | M74: =+L74*$M$27 -> 3722005.1 | N74: =+K74+M74 -> 36140888
B75: ZF | C75: 301343 | D75: CNC TRW-Nissan/FCA/GMT 4.8 Lenmount | E75: =SUMIF(COSTING!C:C,C75,COSTING!G:G) -> 272652 | F75: =E75/SUMIF($B$28:$B$89,B75,$E$28:$E$89) -> 0.55937336 | G75: =SUMIF($B$3:$B$17,B75,$J$3:$J$17)*F75+I74/(SUM($E$28:$E$81)*E75) -> 42257945 | H75: =+E75/SUM($E$28:$E$89) -> 0.097276978 | I75: =+H75*$I$27 -> 24123521 | J75: =+G75+I75 -> 66381466 | K75: =SUMIF('Realowcate Salary-CNC1'!G:G,B75,'Realowcate Salary-CNC1'!F:F)*F75 -> 1.7487532e+08 | L75: =+E75/SUM($E$28:$E$81) -> 0.11204183 | M75: =+L75*$M$27 -> 20077399 | N75: =+K75+M75 -> 1.9495272e+08
B76: ZF | C76: 301415 | D76: CNC ZF IPM Housing A010R190 (2) | E76: =SUMIF(COSTING!C:C,C76,COSTING!G:G) -> 20652 | F76: =E76/SUMIF($B$28:$B$89,B76,$E$28:$E$89) -> 0.042369682 | G76: =SUMIF($B$3:$B$17,B76,$J$3:$J$17)*F76+I75/(SUM($E$28:$E$81)*E76) -> 3200824.1 | H76: =+E76/SUM($E$28:$E$89) -> 0.0073682355 | I76: =+H76*$I$27 -> 1827233.8 | J76: =+G76+I76 -> 5028057.9 | K76: =SUMIF('Realowcate Salary-CNC1'!G:G,B76,'Realowcate Salary-CNC1'!F:F)*F76 -> 13245915 | L76: =+E76/SUM($E$28:$E$81) -> 0.0084865978 | M76: =+L76*$M$27 -> 1520760.7 | N76: =+K76+M76 -> 14766676
B77: ZF | C77: 301489 | D77: CNC Qualcomm IDP Fillmore 50-PR727-3 Battery Door | E77: =SUMIF(COSTING!C:C,C77,COSTING!G:G) -> 300 | F77: =E77/SUMIF($B$28:$B$89,B77,$E$28:$E$89) -> 0.00061548057 | G77: =SUMIF($B$3:$B$17,B77,$J$3:$J$17)*F77+I76/(SUM($E$28:$E$81)*E77) -> 46496.575 | H77: =+E77/SUM($E$28:$E$89) -> 0.00010703422 | I77: =+H77*$I$27 -> 26543.199 | J77: =+G77+I77 -> 73039.774 | K77: =SUMIF('Realowcate Salary-CNC1'!G:G,B77,'Realowcate Salary-CNC1'!F:F)*F77 -> 192415.96 | L77: =+E77/SUM($E$28:$E$81) -> 0.00012328004 | M77: =+L77*$M$27 -> 22091.236 | N77: =+K77+M77 -> 214507.2
B78: ZF | C78: 301498 | D78: CNC ZF GM ACP2 Housing A020R331 (A0038A6898)/A020R330(A0038A6008) | E78: =SUMIF(COSTING!C:C,C78,COSTING!G:G) -> 34252 | F78: =E78/SUMIF($B$28:$B$89,B78,$E$28:$E$89) -> 0.070271468 | G78: =SUMIF($B$3:$B$17,B78,$J$3:$J$17)*F78+I77/(SUM($E$28:$E$81)*E78) -> 5308668.7 | H78: =+E78/SUM($E$28:$E$89) -> 0.012220453 | I78: =+H78*$I$27 -> 3030525.5 | J78: =+G78+I78 -> 8339194.2 | K78: =SUMIF('Realowcate Salary-CNC1'!G:G,B78,'Realowcate Salary-CNC1'!F:F)*F78 -> 21968772 | L78: =+E78/SUM($E$28:$E$81) -> 0.014075293 | M78: =+L78*$M$27 -> 2522230.1 | N78: =+K78+M78 -> 24491002
B79: ZF | C79: 301603 | D79: CNC TRW-FCA4.8 Housing(2) | E79: =SUMIF(COSTING!C:C,C79,COSTING!G:G) -> 102011 | F79: =E79/SUMIF($B$28:$B$89,B79,$E$28:$E$89) -> 0.20928596 | G79: =SUMIF($B$3:$B$17,B79,$J$3:$J$17)*F79+I78/(SUM($E$28:$E$81)*E79) -> 15810540 | H79: =+E79/SUM($E$28:$E$89) -> 0.036395559 | I79: =+H79*$I$27 -> 9025660.9 | J79: =+G79+I79 -> 24836200 | K79: =SUMIF('Realowcate Salary-CNC1'!G:G,B79,'Realowcate Salary-CNC1'!F:F)*F79 -> 65428483 | L79: =+E79/SUM($E$28:$E$81) -> 0.041919733 | M79: =+L79*$M$27 -> 7511830.3 | N79: =+K79+M79 -> 72940313
B80: ZF | C80: 301539 | D80: CNC ZF IPM 2.0 Housing Base A014A906/A014A871 | E80: =SUMIF(COSTING!C:C,C80,COSTING!G:G) -> 6862 | F80: =E80/SUMIF($B$28:$B$89,B80,$E$28:$E$89) -> 0.014078092 | G80: =SUMIF($B$3:$B$17,B80,$J$3:$J$17)*F80+I79/(SUM($E$28:$E$81)*E80) -> 1063531.6 | H80: =+E80/SUM($E$28:$E$89) -> 0.0024482293 | I80: =+H80*$I$27 -> 607131.43 | J80: =+G80+I80 -> 1670663 | K80: =SUMIF('Realowcate Salary-CNC1'!G:G,B80,'Realowcate Salary-CNC1'!F:F)*F80 -> 4401194.5 | L80: =+E80/SUM($E$28:$E$81) -> 0.0028198254 | M80: =+L80*$M$27 -> 505300.21 | N80: =+K80+M80 -> 4906494.7
B81: ZF | C81: 301749 | D81: CNC ZF Wabco OGM2.0 IPM2.0 Advance Lite A036A979/A036A983 | E81: =SUMIF(COSTING!C:C,C81,COSTING!G:G) -> 150 | F81: =E81/SUMIF($B$28:$B$89,B81,$E$28:$E$89) -> 0.00030774028 | G81: =SUMIF($B$3:$B$17,B81,$J$3:$J$17)*F81+I80/(SUM($E$28:$E$81)*E81) -> 23248.288 | H81: =+E81/SUM($E$28:$E$89) -> 5.3517109e-05 | I81: =+H81*$I$27 -> 13271.599 | J81: =+G81+I81 -> 36519.887 | K81: =SUMIF('Realowcate Salary-CNC1'!G:G,B81,'Realowcate Salary-CNC1'!F:F)*F81 -> 96207.981 | L81: =+E81/SUM($E$28:$E$81) -> 6.1640019e-05 | M81: =+L81*$M$27 -> 11045.618 | N81: =+K81+M81 -> 107253.6
B82: SEVT | C82: 310125 | D82: CNC2 Diamond3 (Samsung) | E82: =SUMIF(COSTING!C:C,C82,COSTING!G:G) -> 46000 | F82: =E82/SUMIF($B$28:$B$89,B82,$E$28:$E$89) -> 0.12454042 | G82: =SUMIF($B$3:$B$17,B82,$J$3:$J$17)*F82+I73/(SUM($E$28:$E$81)*E82) -> 21213281 | H82: =+E82/SUM($E$28:$E$89) -> 0.016411913 | I82: =+H82*$I$27 -> 4069957.2 | J82: =+G82+I82 -> 25283238 | K82: =SUMIF('Realowcate Salary-CNC1'!G:G,B82,'Realowcate Salary-CNC1'!F:F)*F82 -> 0 | N82: =+K82+M82 -> 0
B83: SEVT | C83: 310150 | D83: CNC PA1 - GH94-40718A (Samsung) | E83: =SUMIF(COSTING!C:C,C83,COSTING!G:G) -> 43540 | F83: =E83/SUMIF($B$28:$B$89,B83,$E$28:$E$89) -> 0.11788021 | G83: =SUMIF($B$3:$B$17,B83,$J$3:$J$17)*F83+I82/(SUM($E$28:$E$81)*E83) -> 20078832 | H83: =+E83/SUM($E$28:$E$89) -> 0.015534233 | I83: =+H83*$I$27 -> 3852302.9 | J83: =+G83+I83 -> 23931134 | K83: =SUMIF('Realowcate Salary-CNC1'!G:G,B83,'Realowcate Salary-CNC1'!F:F)*F83 -> 0 | N83: =+K83+M83 -> 0
B84: SEVT | C84: 310153 | D84: CNC B7R Main Sub6 - GH94-42274A( Samsung) | E84: =SUMIF(COSTING!C:C,C84,COSTING!G:G) -> 17896 | F84: =E84/SUMIF($B$28:$B$89,B84,$E$28:$E$89) -> 0.048451638 | G84: =SUMIF($B$3:$B$17,B84,$J$3:$J$17)*F84+I83/(SUM($E$28:$E$81)*E84) -> 8252888.6 | H84: =+E84/SUM($E$28:$E$89) -> 0.0063849478 | I84: =+H84*$I$27 -> 1583390.3 | J84: =+G84+I84 -> 9836278.9 | K84: =SUMIF('Realowcate Salary-CNC1'!G:G,B84,'Realowcate Salary-CNC1'!F:F)*F84 -> 0 | N84: =+K84+M84 -> 0
B85: SEVT | C85: 310154 | D85: CNC B7 Sub- GH94-42470A ( Samsung) | E85: =SUMIF(COSTING!C:C,C85,COSTING!G:G) -> 95756 | F85: =E85/SUMIF($B$28:$B$89,B85,$E$28:$E$89) -> 0.25924983 | G85: =SUMIF($B$3:$B$17,B85,$J$3:$J$17)*F85+I84/(SUM($E$28:$E$81)*E85) -> 44158672 | H85: =+E85/SUM($E$28:$E$89) -> 0.034163895 | I85: =+H85*$I$27 -> 8472235.2 | J85: =+G85+I85 -> 52630907 | K85: =SUMIF('Realowcate Salary-CNC1'!G:G,B85,'Realowcate Salary-CNC1'!F:F)*F85 -> 0 | N85: =+K85+M85 -> 0
B86: SEVT | C86: 310156 | D86: CNC B6 Main MMW - GH94-39265A ( Samsung) | E86: =SUMIF(COSTING!C:C,C86,COSTING!G:G) -> 27900 | F86: =E86/SUMIF($B$28:$B$89,B86,$E$28:$E$89) -> 0.075536471 | G86: =SUMIF($B$3:$B$17,B86,$J$3:$J$17)*F86+I85/(SUM($E$28:$E$81)*E86) -> 12866316 | H86: =+E86/SUM($E$28:$E$89) -> 0.0099541822 | I86: =+H86*$I$27 -> 2468517.5 | J86: =+G86+I86 -> 15334834 | K86: =SUMIF('Realowcate Salary-CNC1'!G:G,B86,'Realowcate Salary-CNC1'!F:F)*F86 -> 0 | N86: =+K86+M86 -> 0
B87: SEVT | C87: 310160 | D87: CNC M1 GH94-43770A ( Samsung) | E87: =SUMIF(COSTING!C:C,C87,COSTING!G:G) -> 112600 | F87: =E87/SUMIF($B$28:$B$89,B87,$E$28:$E$89) -> 0.30485329 | G87: =SUMIF($B$3:$B$17,B87,$J$3:$J$17)*F87+I86/(SUM($E$28:$E$81)*E87) -> 51926422 | H87: =+E87/SUM($E$28:$E$89) -> 0.04017351 | I87: =+H87*$I$27 -> 9962547.3 | J87: =+G87+I87 -> 61888970 | K87: =SUMIF('Realowcate Salary-CNC1'!G:G,B87,'Realowcate Salary-CNC1'!F:F)*F87 -> 0 | N87: =+K87+M87 -> 0
B88: SEVT | C88: 310139 | D88: CNC Q5MMW-GH94-36580A (Samsung) | E88: =SUMIF(COSTING!C:C,C88,COSTING!G:G) -> 7800 | F88: =E88/SUMIF($B$28:$B$89,B88,$E$28:$E$89) -> 0.021117723 | G88: =SUMIF($B$3:$B$17,B88,$J$3:$J$17)*F88+I87/(SUM($E$28:$E$81)*E88) -> 3597034.6 | H88: =+E88/SUM($E$28:$E$89) -> 0.0027828897 | I88: =+H88*$I$27 -> 690123.17 | J88: =+G88+I88 -> 4287157.8 | K88: =SUMIF('Realowcate Salary-CNC1'!G:G,B88,'Realowcate Salary-CNC1'!F:F)*F88 -> 0 | N88: =+K88+M88 -> 0
B89: SEVT | C89: 310159 | D89: CNC M3 GH94-43862A ( Samsung) | E89: =SUMIF(COSTING!C:C,C89,COSTING!G:G) -> 17866 | F89: =E89/SUMIF($B$28:$B$89,B89,$E$28:$E$89) -> 0.048370416 | G89: =SUMIF($B$3:$B$17,B89,$J$3:$J$17)*F89+I88/(SUM($E$28:$E$81)*E89) -> 8239053.8 | H89: =+E89/SUM($E$28:$E$89) -> 0.0063742444 | I89: =+H89*$I$27 -> 1580736 | J89: =+G89+I89 -> 9819789.8 | K89: =SUMIF('Realowcate Salary-CNC1'!G:G,B89,'Realowcate Salary-CNC1'!F:F)*F89 -> 0 | N89: =+K89+M89 -> 0

Sheet Realowcate Salary-CNC1
A1: Expense Allocation Group.Code | B1: Expense Allocation Group | C1: Dept | D1: Work Center | E1: Name CC | F1: Total Cost
A2: 41070105 | B2: Direct labour costs- Labor - Outsourcing | C2: CNC1 | D2: C-2110 | E2: CNC1 | F2: 148253700 | G2: ALL
A3: 41070104 | B3: Direct labour costs - Labor- SHUI | C3: CNC1 | D3: C-2110 | E3: CNC1 | F3: -606000 | G3: ALL
A4: 41070101 | B4: Direct labour costs-Overtime | C4: CNC1 | D4: C-2110 | E4: CNC1 | F4: 11557237 | G4: ALL
A5: 41070100 | B5: Direct labour costs | C5: CNC1 | D5: C-2110 | E5: CNC1 | F5: 19990628 | G5: ALL
A6: 41070104 | B6: Direct labour costs - Labor- SHUI | C6: CNC1 | D6: C-2110-6 | E6: CNC1 Auto LG | F6: 72355000 | G6: LG
A7: 41070103 | B7: Direct labour costs- bonus | C7: CNC1 | D7: C-2110-6 | E7: CNC1 Auto LG | F7: 24954149 | G7: LG
A8: 41070102 | B8: Direct labour cost-Trade union | C8: CNC1 | D8: C-2110-6 | E8: CNC1 Auto LG | F8: 6712000 | G8: LG
A9: 41070101 | B9: Direct labour costs-Overtime | C9: CNC1 | D9: C-2110-6 | E9: CNC1 Auto LG | F9: 304932474 | G9: LG
A10: 41070100 | B10: Direct labour costs | C10: CNC1 | D10: C-2110-6 | E10: CNC1 Auto LG | F10: 397344005 | G10: LG
A11: 41070104 | B11: Direct labour costs - Labor- SHUI | C11: CNC1 | D11: C-2110-5 | E11: CNC1 Auto Mando | F11: 33862500 | G11: MANDO
A12: 41070103 | B12: Direct labour costs- bonus | C12: CNC1 | D12: C-2110-5 | E12: CNC1 Auto Mando | F12: 11299992 | G12: MANDO
A13: 41070102 | B13: Direct labour cost-Trade union | C13: CNC1 | D13: C-2110-5 | E13: CNC1 Auto Mando | F13: 3150000 | G13: MANDO
... A30: 41070100 | B30: Direct labour costs | C30: CNC1 | D30: C-2110-2 | E30: CNC1 Mobile Qualcom | F30: 29060221 | G30: QUALCOM
F31: =SUM(F2:F30) -> 1838795093

Sheet Defect Warehouse
A1: Code | B1: Acc | C1: Kind | D1: Booking Period | E1: Doc Type. Code | F1: Doc Type. Name | G1: Doc No. | H1: Business Date | I1: Doc Status | J1: Misc Shipment Doc Line.Benefiting Dept..Code | K1: Dept | L1: Dept2 | M1: Item. Code | N1: Misc Shipment Doc Line.Item.Item.Item Name | O1: Item State Attribute | P1: Cost Qty | Q1: Unit | R1: Cost Amt | S1: Price Getting Source | T1: Warehouse. Code | U1: Warehouse. Name
A2: 01 | B2: F/G | C2: FG | D2: 2024-09 | E2: MiscShip003 | F2: Retirement | G2: ZF2024090122
A3: 01 | B3: F/G | C3: FG | D3: 2024-09 | E3: MiscShip003 | F3: Retirement | G3: ZF2024090121
A4: 01 | B4: F/G | C4: FG | D4: 2024-09 | E4: MiscShip003 | F4: Retirement | G4: ZF2024090094
A5: 08 | B5: WIP 2 | C5: WIP | D5: 2024-09 | E5: MiscShip003 | F5: Retirement | G5: ZF2024090094
A6: 01 | B6: F/G | C6: FG | D6: 2024-09 | E6: MiscShip003 | F6: Retirement | G6: ZF2024090094
A7: 01 | B7: F/G | C7: FG | D7: 2024-09 | E7: MiscShip003 | F7: Retirement | G7: ZF2024090094
A8: 07 | B8: WIP 1 | C8: WIP | D8: 2024-09 | E8: MiscShip003 | F8: Retirement | G8: ZF2024090094
A9: 07 | B9: WIP 1 | C9: WIP | D9: 2024-09 | E9: MiscShip003 | F9: Retirement | G9: ZF2024090094
A10: 07 | B10: WIP 1 | C10: WIP | D10: 2024-09 | E10: MiscShip003 | F10: Retirement | G10: ZF2024090094
A11: 07 | B11: WIP 1 | C11: WIP | D11: 2024-09 | E11: MiscShip003 | F11: Retirement | G11: ZF2024090094
A12: 07 | B12: WIP 1 | C12: WIP | D12: 2024-09 | E12: MiscShip003 | F12: Retirement | G12: ZF2024090094
A13: 07 | B13: WIP 1 | C13: WIP | D13: 2024-09 | E13: MiscShip003 | F13: Retirement | G13: ZF2024090094
... A391: 01 | B391: F/G | C391: FG | D391: 2024-09 | E391: MiscShip003 | F391: Retirement | G391: ZF2024090004

Sheet Working Hours
A1: Quota Hours
A2: Item.Item No. | B2: Item.Item Name | C2: From Date | D2: To Date | E2: Department.Name | F2: Production Line.Production Line Name | G2: Time UOM.Name | H2: Preparation Hours | I2: Processing Hours | J2: Preparation Machine Hours | K2: Processing Machine Hours | L2: Idle Time
A3: 100543 | B3: PK Qualcomm IDP Talos 55-PG284-1 Ant carrier | C3: 36526 | D3: 2958465 | G3: Hour | H3: 0 | I3: 0.0349 | L3: 0
A4: 100626 | B4: PK Qualcomm Saipan 55-PL927-1 Camera Assy | C4: 36526 | D4: 2958465 | G4: Hour | H4: 0 | I4: 0.0139 | L4: 0
A5: 100705 | B5: PK Qualcomm MTP Bittra 55-PP813-10 Assy Rear Lens | C5: 36526 | D5: 2958465 | G5: Hour | H5: 0 | I5: 0.0028 | L5: 0
