Workbook
Name __DemandLoad: TRUE
Name __IntlFixup: TRUE
Name _1: #N/A
Name _2: #N/A
Name _3: #N/A
Name _4: #N/A
Name _5: #N/A
Name _6: #N/A
Name _Order1: 255
Name _Order2: 255
Name _Regression_Int: 1
Name \a: #N/A
Name \b: #N/A
Name \e: #N/A
Name \m: #N/A
Name \q: #N/A
Name \r: #N/A
Name \s: #N/A
Name aa: #N/A
Name aaa: #N/A
Name aaaa: #N/A
Name aaaaa: #N/A
Name aaaaaa: #N/A
Name as: #N/A
Name AS2DocOpenMode: "AS2DocumentEdit"
Name AS2ReportLS: 1
Name AS2SyncStepLS: 0
Name AS2VersionLS: 300
Name asd: #N/A
Name asdf: #N/A
Name asdfg: #N/A
Name asxz: #N/A
Name bbb: #N/A
Name bbbbb: #N/A
Name BG_Del: 15
Name BG_Ins: 4
Name BG_Mod: 6
Name book: #N/A
Name book2: #N/A
Name book3: #N/A
Name ccc: #N/A
Name cccccccccccccccccccccc: #N/A
Name dd: #N/A
Name ddd: #N/A
Name DSFDSF: #N/A
Name erre: #N/A
Name fff: #N/A
Name fghgfjk: #N/A
Name gfgfgf: #N/A
Name ggg: #N/A
Name GHJ: #N/A
Name GO: #N/A
Name GoAssetChart: #N/A
Name GoBack: #N/A
Name GoBalanceSheet: #N/A
Name GoCashFlow: #N/A
Name GoData: #N/A
Name GoIncomeChart: #N/A
Name h: #N/A
Name han: #N/A

Sheet Sale detail by code
E1: Sale | H1: COGS (sale out) | K1: Cost of Producing in Feb
A2: Code | B2: Name | C2: Item No. | D2: Item Name | E2: Qty | F2: VND | G2: USD | H2: Unit cost (everage) VND | I2: VND | J2: USD | K2: Unit cost product | L2: VND | M2: USD
A3: FG | B3: ELENTEC | C3: 120425 | D3: PK SM-A156E | E3: 46400 | F3: 776457600 | G3: =+F3/26000 -> 29863.754 | H3: 19655.967 | I3: =+H3*E3 -> 9.1203685e+08 | J3: =+I3/26000 -> 35078.341 | K3: 17463.275 | L3: =+K3*E3 -> 8.1029595e+08 | M3: =+L3/26000 -> 31165.229
A4: FG | B4: ELENTEC | C4: 120434 | D4: PK SM-A266B | E4: 55533 | F4: 1014698976 | G4: =+F4/26000 -> 39026.884 | H4: 19471.798 | I4: =+H4*E4 -> 1.0813273e+09 | J4: =+I4/26000 -> 41589.513 | K4: 24299.323 | L4: =+K4*E4 -> 1.3494143e+09 | M4: =+L4/26000 -> 51900.551
A5: FG | B5: ELENTEC | C5: 120438 | D5: PK SM-A176B | E5: 589680 | F5: 9546919200 | G5: =+F5/26000 -> 367189.2 | H5: 18096.416 | I5: =+H5*E5 -> 1.0671095e+10 | J5: =+I5/26000 -> 410426.72 | K5: 19124.579 | L5: =+K5*E5 -> 1.1277382e+10 | M5: =+L5/26000 -> 433745.46
A6: FG | B6: ELENTEC | C6: 120443 | D6: PK SM-A376B | E6: 411900 | F6: 8331501300 | G6: =+F6/26000 -> 320442.36 | H6: 19943.711 | I6: =+H6*E6 -> 8.2148144e+09 | J6: =+I6/26000 -> 315954.4 | K6: 19792.519 | L6: =+K6*E6 -> 8.1525387e+09 | M6: =+L6/26000 -> 313559.18
A7: FG | B7: INTOPS | C7: 120438 | D7: PK SM-A176B | E7: 168480 | F7: 2773180800 | G7: =+F7/26000 -> 106660.8 | H7: 18096.416 | I7: =+H7*E7 -> 3.0488842e+09 | J7: =+I7/26000 -> 117264.78 | K7: 19124.579 | L7: =+K7*E7 -> 3.2221091e+09 | M7: =+L7/26000 -> 123927.27
A8: FG | B8: SEVT | C8: 101196 | D8: PK B6 Main Sub6 - GH94-39228A (Samsung) | E8: 21100 | F8: 370516000 | G8: =+F8/26000 -> 14250.615 | H8: 26471.907 | I8: =+H8*E8 -> 5.5855724e+08 | J8: =+I8/26000 -> 21482.971 | K8: 26471.907 | L8: =+K8*E8 -> 5.5855724e+08 | M8: =+L8/26000 -> 21482.971
A9: FG | B9: SEVT | C9: 101202 | D9: PK Q5MMW-GH94-36580A (Samsung) | E9: 21901 | F9: 558212688 | G9: =+F9/26000 -> 21469.719 | H9: 20211.909 | I9: =+H9*E9 -> 4.4266103e+08 | J9: =+I9/26000 -> 17025.424 | K9: 20211.909 | L9: =+K9*E9 -> 4.4266103e+08 | M9: =+L9/26000 -> 17025.424
A10: FG | B10: SEVT | C10: 101203 | D10: PK Q5 MAIN SUB6/GH94-36611A (Samsung) | E10: 200 | F10: 5754228 | G10: =+F10/26000 -> 221.31646 | H10: 21418.927 | I10: =+H10*E10 -> 4283785.4 | J10: =+I10/26000 -> 164.76098 | K10: 21418.927 | L10: =+K10*E10 -> 4283785.4 | M10: =+L10/26000 -> 164.76098
A11: FG | B11: SEVT | C11: 101284 | D11: PK B7R Sub- GH94-42329A ( Samsung) | E11: 13552 | F11: 245494480 | G11: =+F11/26000 -> 9442.0954 | H11: 56369.955 | I11: =+H11*E11 -> 7.6392563e+08 | J11: =+I11/26000 -> 29381.755 | K11: 56369.955 | L11: =+K11*E11 -> 7.6392563e+08 | M11: =+L11/26000 -> 29381.755
A12: FG | B12: SEVT | C12: 101285 | D12: PK B7R Main Sub6 - GH94-42274A( Samsung) | E12: 15060 | F12: 257706720 | G12: =+F12/26000 -> 9911.7969 | H12: 38227.208 | I12: =+H12*E12 -> 5.7570175e+08 | J12: =+I12/26000 -> 22142.375 | K12: 38227.208 | L12: =+K12*E12 -> 5.7570175e+08 | M12: =+L12/26000 -> 22142.375
A13: FG | B13: SEVT | C13: 101286 | D13: PK B7 Sub- GH94-42470A ( Samsung) | E13: 83366 | F13: 1676156796 | G13: =+F13/26000 -> 64467.569 | H13: 16320.965 | I13: =+H13*E13 -> 1.3606136e+09 | J13: =+I13/26000 -> 52331.291 | K13: 16320.965 | L13: =+K13*E13 -> 1.3606136e+09 | M13: =+L13/26000 -> 52331.291
A14: FG | B14: SEVT | C14: 101288 | D14: PK B7 Main Sub 6 GH94-42417A ( Samsung) | E14: 336 | F14: 6134016 | G14: =+F14/26000 -> 235.92369 | H14: 11657.829 | I14: =+H14*E14 -> 3917030.6 | J14: =+I14/26000 -> 150.65502 | K14: 11657.829 | L14: =+K14*E14 -> 3917030.6 | M14: =+L14/26000 -> 150.65502
... A45: FG | B45: MFG | C45: 101342 | D45: PK A 149-0314-001 FRAME, EYE SIDE, BUCK HMD | E45: 15 | F45: 40062120 | G45: =+F45/26000 -> 1540.8508 | H45: 6151859.3 | I45: =+H45*E45 -> 92277889 | J45: =+I45/26000 -> 3549.1496 | K45: 6151859.3 | L45: =+K45*E45 -> 92277889 | M45: =+L45/26000 -> 3549.1496
A46: Trading | B46: MFG | C46: 785015 | D46: Oring Mold for P/N: 143-8808-001-A03 & 143-6225-001-A04 | E46: 1 | F46: 89541936 | G46: =+F46/26000 -> 3443.9206 | H46: 44625000 | I46: =+H46*E46 -> 44625000 | J46: =+I46/26000 -> 1716.3462 | K46: =+H46 -> 44625000 | L46: =+K46*E46 -> 44625000 | M46: =+L46/26000 -> 1716.3462
A47: Trading | B47: MFG | C47: 901175 | D47: 50-60551-1 ADHESIVE, Adhesive display, Linh kiện Qualcomm 50-60551-1 | E47: 1000 | F47: 32828520 | G47: =+F47/26000 -> 1262.6354 | H47: 11474 | I47: =+H47*E47 -> 11474000 | J47: =+I47/26000 -> 441.30769 | K47: =+H47 -> 11474 | L47: =+K47*E47 -> 11474000 | M47: =+L47/26000 -> 441.30769
A48: Trading | B48: MFG | C48: 901430 | D48: 135-8837-003_ISW ANTENNA ENCLOSURE, FRONT SENSORS, C3 INJECTION MOLD (1ST INJECTION) | E48: 1 | F48: 2.0774458e+08 | G48: =+F48/26000 -> 7990.1763 | H48: 180000000 | I48: =+H48*E48 -> 180000000 | J48: =+I48/26000 -> 6923.0769 | K48: =+H48 -> 180000000 | L48: =+K48*E48 -> 180000000 | M48: =+L48/26000 -> 6923.0769
A49: Trading | B49: MFG | C49: 901431 | D49: 135-8837-003_ISW ANTENNA ENCLOSURE , FRONT SENSORS, C3 INJECTION MOLD (2nd INJECTION) | E49: 1 | F49: 2.0774458e+08 | G49: =+F49/26000 -> 7990.1763 | H49: 150000000 | I49: =+H49*E49 -> 150000000 | J49: =+I49/26000 -> 5769.2308 | K49: =+H49 -> 150000000 | L49: =+K49*E49 -> 150000000 | M49: =+L49/26000 -> 5769.2308
A50: Trading | B50: MFG | C50: 901432 | D50: 142-7607-002 LOW LIGHT SENSOR BAR INJECTION MOLD | E50: 1 | F50: 2.1335932e+08 | G50: =+F50/26000 -> 8206.1278 | H50: 170000000 | I50: =+H50*E50 -> 170000000 | J50: =+I50/26000 -> 6538.4615 | K50: =+H50 -> 170000000 | L50: =+K50*E50 -> 170000000 | M50: =+L50/26000 -> 6538.4615
A51: Trading | B51: MFG | C51: 901433 | D51: 132-8032-006 _VF Grip_Low Light_C6 INJECTION MOLD - Material : NAK80 | E51: 1 | F51: 1.3475297e+08 | G51: =+F51/26000 -> 5182.8065 | H51: 150000000 | I51: =+H51*E51 -> 150000000 | J51: =+I51/26000 -> 5769.2308 | K51: =+H51 -> 150000000 | L51: =+K51*E51 -> 150000000 | M51: =+L51/26000 -> 5769.2308
A52: Trading | B52: MFG | C52: 901434 | D52: 136-2429-002_ Button Membrane_ Front UI_ C2 INJECTION MOLD | E52: 1 | F52: 111171375 | G52: =+F52/26000 -> 4275.8221 | H52: 130000000 | I52: =+H52*E52 -> 130000000 | J52: =+I52/26000 -> 5000 | K52: =+H52 -> 130000000 | L52: =+K52*E52 -> 130000000 | M52: =+L52/26000 -> 5000
A53: Trading | B53: MFG | C53: 901435 | D53: 132-8032-006, VF Grip, Low Light, C6, RevA, 11-10-25 Silicone Mold | E53: 1 | F53: 1.3475297e+08 | G53: =+F53/26000 -> 5182.8065 | H53: 68000000 | I53: =+H53*E53 -> 68000000 | J53: =+I53/26000 -> 2615.3846 | K53: =+H53 -> 68000000 | L53: =+K53*E53 -> 68000000 | M53: =+L53/26000 -> 2615.3846
A54: Trading | B54: MFG | C54: 901436 | D54: 136-2429-002, Button Membrane, Front UI, C2, RevA Silicone Mold | E54: 1 | F54: 111171375 | G54: =+F54/26000 -> 4275.8221 | H54: 56000000 | I54: =+H54*E54 -> 56000000 | J54: =+I54/26000 -> 2153.8462 | K54: =+H54 -> 56000000 | L54: =+K54*E54 -> 56000000 | M54: =+L54/26000 -> 2153.8462
A55: Trading | B55: MFG | C55: 901437 | D55: 143-0466-001 _ BODY COMPUTE_ANTENNA_CAPS _ LEFT & RIGHT_INJECTION MOLD 2525 | E55: 1 | F55: 212661936 | G55: =+F55/26000 -> 8179.3052 | H55: 150000000 | I55: =+H55*E55 -> 150000000 | J55: =+I55/26000 -> 5769.2308 | K55: =+H55 -> 150000000 | L55: =+K55*E55 -> 150000000 | M55: =+L55/26000 -> 5769.2308
A56: Trading | B56: MFG | C56: 901458 | D56: O-ring for Battery Pack Rear-to-Front Cable (P/N: 143-8808-001-A03) | E56: 15 | F56: 181749 | G56: =+F56/26000 -> 6.9903462 | H56: 12495 | I56: =+H56*E56 -> 187425 | J56: =+I56/26000 -> 7.2086538 | K56: =+H56 -> 12495 | L56: =+K56*E56 -> 187425 | M56: =+L56/26000 -> 7.2086538
A57: Trading | B57: MFG | C57: 901459 | D57: Oring for BATTERY PACK, TOP LID (P/N: 143-6225-001-A04) | E57: 15 | F57: 471774 | G57: =+F57/26000 -> 18.145154 | H57: 12495 | I57: =+H57*E57 -> 187425 | J57: =+I57/26000 -> 7.2086538 | K57: =+H57 -> 12495 | L57: =+K57*E57 -> 187425 | M57: =+L57/26000 -> 7.2086538
A58: FG | B58: LG YANTAI | C58: 120157 | D58: PK LGIT Gen3 AL5 | E58: 38016 | F58: 2158263360 | G58: =+F58/26000 -> 83010.129 | H58: 48824.223 | I58: =+H58*E58 -> 1.8561017e+09 | J58: =+I58/26000 -> 71388.525 | K58: 50620.495 | L58: =+K58*E58 -> 1.9243888e+09 | M58: =+L58/26000 -> 74014.952
A59: FG | B59: LG YANTAI | C59: 120362 | D59: PK LGIT MPC5.5 Cover lens 3HDC00003A | E59: 83819 | F59: 1.9062715e+09 | G59: =+F59/26000 -> 73318.135 | H59: 13779.559 | I59: =+H59*E59 -> 1.1549889e+09 | J59: =+I59/26000 -> 44422.649 | K59: 14228.907 | L59: =+K59*E59 -> 1.1926527e+09 | M59: =+L59/26000 -> 45871.26
A60: FG | B60: LG YANTAI | C60: 120411 | D60: PK PK LGIT MQ4a PE Cover | E60: 16200 | F60: 593541540 | G60: =+F60/26000 -> 22828.521 | H60: 26655.358 | I60: =+H60*E60 -> 4.318168e+08 | J60: =+I60/26000 -> 16608.339 | K60: 27038.492 | L60: =+K60*E60 -> 4.3802357e+08 | M60: =+L60/26000 -> 16847.06
A61: FG | B61: LG YANTAI | C61: 120414 | D61: PK LGIT MQ4a PE Housing 3CAZ00039A | E61: 16200 | F61: 1383536970 | G61: =+F61/26000 -> 53212.96 | H61: =108739.09367+2355212817 -> 2.3553216e+09 | I61: =+H61*E61 -> 3.8156209e+13 | J61: =+I61/26000 -> 1.4675465e+09 | K61: =+H61 -> 2.3553216e+09 | L61: =+K61*E61 -> 3.8156209e+13 | M61: =+L61/26000 -> 1.4675465e+09
A62: FG | B62: LG YANTAI | C62: 120415 | D62: PK LGIT 3CAZ00041A CL4 Housing | E62: 31446 | F62: 2.7334606e+09 | G62: =+F62/26000 -> 105133.1 | H62: 63694.348 | I62: =+H62*E62 -> 2.0029325e+09 | J62: =+I62/26000 -> 77035.864 | K62: 78595.287 | L62: =+K62*E62 -> 2.4715074e+09 | M62: =+L62/26000 -> 95057.976
A63: FG | B63: LG YANTAI | C63: 120416 | D63: PK LGIT 3CAZ00042A CL4 Cover | E63: 19099 | F63: 6.6046721e+08 | G63: =+F63/26000 -> 25402.585 | H63: 25784.69 | I63: =+H63*E63 -> 4.9246179e+08 | J63: =+I63/26000 -> 18940.838 | K63: 27793.351 | L63: =+K63*E63 -> 5.3082521e+08 | M63: =+L63/26000 -> 20416.354
A64: Trading | B64: LG YANTAI | C64: 901371 | D64: Mold Die casting CL4 Housing 1 CAV (Full set) #17 | E64: 1 | F64: 6.1736723e+08 | G64: =+F64/26000 -> 23744.893 | H64: 450000000 | I64: =+H64*E64 -> 450000000 | J64: =+I64/26000 -> 17307.692 | K64: =+H64 -> 450000000 | L64: =+K64*E64 -> 450000000 | M64: =+L64/26000 -> 17307.692
A65: FG | B65: LG KOREA | C65: 120332 | D65: PK LGIT DCU15 3CAC00306A Housing | E65: 27000 | F65: 479512995 | G65: =+F65/26000 -> 18442.807 | H65: 9931.666 | I65: =+H65*E65 -> 2.6815498e+08 | J65: =+I65/26000 -> 10313.653 | K65: 9018.5208 | L65: =+K65*E65 -> 2.4350006e+08 | M65: =+L65/26000 -> 9365.387
A66: FG | B66: LG KOREA | C66: 120333 | D66: PK LGIT DCU15 3CAC00307A Cover | E66: 27000 | F66: 337538175 | G66: =+F66/26000 -> 12982.237 | H66: 5942.602 | I66: =+H66*E66 -> 1.6045025e+08 | J66: =+I66/26000 -> 6171.1636 | K66: 4345.8392 | L66: =+K66*E66 -> 1.1733766e+08 | M66: =+L66/26000 -> 4512.9869
A67: FG | B67: LG MEXICO | C67: 120411 | D67: PK PK LGIT MQ4a PE Cover | E67: 20000 | F67: 724920000 | G67: =+F67/26000 -> 27881.538 | H67: 26655.358 | I67: =+H67*E67 -> 5.3310716e+08 | J67: =+I67/26000 -> 20504.122 | K67: 27038.492 | L67: =+K67*E67 -> 5.4076984e+08 | M67: =+L67/26000 -> 20798.84
A68: FG | B68: LG MEXICO | C68: 120414 | D68: PK LGIT MQ4a PE Housing 3CAZ00039A | E68: 20000 | F68: 1662138000 | G68: =+F68/26000 -> 63928.385 | H68: 61253.781 | I68: =+H68*E68 -> 1.2250756e+09 | J68: =+I68/26000 -> 47118.293 | K68: =+H68 -> 61253.781 | L68: =+K68*E68 -> 1.2250756e+09 | M68: =+L68/26000 -> 47118.293
A69: FG | B69: LG MEXICO | C69: 120415 | D69: PK LGIT 3CAZ00041A CL4 Housing | E69: 20000 | F69: 1693206000 | G69: =+F69/26000 -> 65123.308 | H69: 63694.348 | I69: =+H69*E69 -> 1.273887e+09 | J69: =+I69/26000 -> 48995.652 | K69: 78595.287 | L69: =+K69*E69 -> 1.5719057e+09 | M69: =+L69/26000 -> 60457.913
A70: FG | B70: LG MEXICO | C70: 120416 | D70: PK LGIT 3CAZ00042A CL4 Cover | E70: 20000 | F70: 683496000 | G70: =+F70/26000 -> 26288.308 | H70: 25784.69 | I70: =+H70*E70 -> 5.1569379e+08 | J70: =+I70/26000 -> 19834.377 | K70: 27793.351 | L70: =+K70*E70 -> 5.5586702e+08 | M70: =+L70/26000 -> 21379.501
A71: FG | B71: LG MEXICO | C71: 120433 | D71: PK LGIT eK- LQ2 3BKO00001A Cover | E71: 15120 | F71: 6.3893915e+08 | G71: =+F71/26000 -> 24574.583 | H71: 28527.353 | I71: =+H71*E71 -> 4.3133358e+08 | J71: =+I71/26000 -> 16589.753 | K71: 30930.435 | L71: =+K71*E71 -> 4.6766818e+08 | M71: =+L71/26000 -> 17987.238
A72: Trading | B72: LG MEXICO | C72: 901421 | D72: Mold Die Casting eK LQ2 Cover #2 | E72: 1 | F72: 5.8909084e+08 | G72: =+F72/26000 -> 22657.34 | H72: 460000000 | I72: =+H72*E72 -> 460000000 | J72: =+I72/26000 -> 17692.308 | K72: =+H72 -> 460000000 | L72: =+K72*E72 -> 460000000 | M72: =+L72/26000 -> 17692.308
A73: FG | B73: ZF POLAND | C73: 120187 | D73: PK TRW-Nissan/FCA/GMT 4.8 Lenmount(336416-13/A011F352) | E73: 129024 | F73: 1.8944335e+09 | G73: =+F73/26000 -> 72862.828 | H73: 8055.3049 | I73: =+H73*E73 -> 1.0393277e+09 | J73: =+I73/26000 -> 39974.141 | K73: 7906.0383 | L73: =+K73*E73 -> 1.0200687e+09 | M73: =+L73/26000 -> 39233.411
A74: FG | B74: ZF POLAND | C74: 120192 | D74: PK TRW-FCA 4.8 Cover A012U602 | E74: 51840 | F74: 1.4988992e+09 | G74: =+F74/26000 -> 57649.97 | H74: 11429.908 | I74: =+H74*E74 -> 5.9252641e+08 | J74: =+I74/26000 -> 22789.477 | K74: 11411.038 | L74: =+K74*E74 -> 5.9154823e+08 | M74: =+L74/26000 -> 22751.855
A75: FG | B75: ZF POLAND | C75: 120386 | D75: PK TRW-FCA 4.8 Housing A010W096(2) | E75: 51840 | F75: 1.6748536e+09 | G75: =+F75/26000 -> 64417.447 | H75: 18943.239 | I75: =+H75*E75 -> 9.820175e+08 | J75: =+I75/26000 -> 37769.904 | K75: 18450.071 | L75: =+K75*E75 -> 9.5645167e+08 | M75: =+L75/26000 -> 36786.603
A76: FG | B76: ZF UK | C76: 120187 | D76: PK TRW-Nissan/FCA/GMT 4.8 Lenmount(336416-13/A011F352) | E76: 43008 | F76: 6.3975427e+08 | G76: =+F76/26000 -> 24605.934 | H76: 8055.3049 | I76: =+H76*E76 -> 3.4644255e+08 | J76: =+I76/26000 -> 13324.714 | K76: 7906.0383 | L76: =+K76*E76 -> 3.4002289e+08 | M76: =+L76/26000 -> 13077.804
A77: FG | B77: ZF UK | C77: 120318 | D77: PK ZF IPM Housing A010R190 (2) | E77: 9792 | F77: 9.3523651e+08 | G77: =+F77/26000 -> 35970.635 | H77: 72580.337 | I77: =+H77*E77 -> 7.1070666e+08 | J77: =+I77/26000 -> 27334.872 | K77: 72933.344 | L77: =+K77*E77 -> 7.1416331e+08 | M77: =+L77/26000 -> 27467.82
A78: FG | B78: ZF UK | C78: 120370 | D78: PK ZF IPM 2.0 Housing Base A014A906/A014A871 | E78: 1344 | F78: 1.9121526e+08 | G78: =+F78/26000 -> 7354.4329 | H78: 71046.239 | I78: =+H78*E78 -> 95486145 | J78: =+I78/26000 -> 3672.544 | K78: 36890.044 | L78: =+K78*E78 -> 49580219 | M78: =+L78/26000 -> 1906.9315
A79: FG | B79: ZF MEXICO | C79: 120402 | D79: PK ZF TRW - GM EU2L Housing A021D074 (2) | E79: 44160 | F79: 1.5298079e+09 | G79: =+F79/26000 -> 58838.764 | H79: 15777.27 | I79: =+H79*E79 -> 6.9672424e+08 | J79: =+I79/26000 -> 26797.086 | K79: 14081.75 | L79: =+K79*E79 -> 6.218501e+08 | M79: =+L79/26000 -> 23917.311
A80: FG | B80: ZF MEXICO | C80: 120403 | D80: PK ZF TRW - GM EU2L Cover A021D075 | E80: 44160 | F80: 1.3235917e+09 | G80: =+F80/26000 -> 50907.372 | H80: 11542.492 | I80: =+H80*E80 -> 5.0971647e+08 | J80: =+I80/26000 -> 19604.48 | K80: 11186.258 | L80: =+K80*E80 -> 4.9398516e+08 | M80: =+L80/26000 -> 18999.429
A81: FG | B81: MANDO (ZHANGJIAGANG) | C81: 120309 | D81: PK Mando NX4 Motor Housing | E81: 50710 | F81: 5459305720 | G81: =+F81/26000 -> 209973.3 | H81: 73089.758 | I81: =+H81*E81 -> 3.7063816e+09 | J81: =+I81/26000 -> 142553.14 | K81: 84117.538 | L81: =+K81*E81 -> 4.2656003e+09 | M81: =+L81/26000 -> 164061.55
A82: FG | B82: MANDO (ZHANGJIAGANG) | C82: 120336 | D82: PK Mando Brose GE821-J10-00-J100 Housing | E82: 5287 | F82: 5.1640878e+08 | G82: =+F82/26000 -> 19861.876 | H82: 76804.399 | I82: =+H82*E82 -> 4.0606486e+08 | J82: =+I82/26000 -> 15617.879 | K82: 82307.601 | L82: =+K82*E82 -> 4.3516029e+08 | M82: =+L82/26000 -> 16736.934
A83: FG | B83: MANDO (ZHANGJIAGANG) | C83: 120338 | D83: PK Mando NX4 Cover | E83: 58320 | F83: 4046391612 | G83: =+F83/26000 -> 155630.45 | H83: 26106.582 | I83: =+H83*E83 -> 1.5225359e+09 | J83: =+I83/26000 -> 58559.073 | K83: 28421.545 | L83: =+K83*E83 -> 1.6575445e+09 | M83: =+L83/26000 -> 63751.712
A84: FG | B84: MANDO (ZHANGJIAGANG) | C84: 120368 | D84: PK Mando Brose IMEB2 Housing(2) | E84: 27648 | F84: 1.935247e+09 | G84: =+F84/26000 -> 74432.576 | H84: 70186.84 | I84: =+H84*E84 -> 1.9405258e+09 | J84: =+I84/26000 -> 74635.606 | K84: 77295.27 | L84: =+K84*E84 -> 2.1370596e+09 | M84: =+L84/26000 -> 82194.601
... A86: FG | B86: HL KLEMOVE INDIA | C86: 120367 | D86: PK Mando MAS65C 4.5 Heat Sink(2) | E86: 67200 | F86: 1913457623 | G86: =+F86/26000 -> 73594.524 | H86: 17797.398 | I86: =+H86*E86 -> 1.1959851e+09 | J86: =+I86/26000 -> 45999.429 | K86: 17317.656 | L86: =+K86*E86 -> 1.1637465e+09 | M86: =+L86/26000 -> 44759.48
A87: FG | B87: MANDO CORPORATION | C87: 120440 | D87: PK Mando Brose JK1-LHD Housing ME200V1200 | E87: 300 | F87: 29644200 | G87: =+F87/26000 -> 1140.1615 | H87: 69860.788 | I87: =+H87*E87 -> 20958236 | J87: =+I87/26000 -> 806.08601 | K87: =+H87 -> 69860.788 | L87: =+K87*E87 -> 20958236 | M87: =+L87/26000 -> 806.08601
D88: Scrapt | F88: 2423970950 | G88: =+F88/26000 -> 93229.652
A89: Grand Total | E89: =SUM(E3:E87) -> 2627719 | F89: =SUM(F3:F88) -> 8.1739615e+10 | G89: =SUM(G3:G88) -> 3143831.3 | I89: =SUM(I3:I88) -> 3.8220514e+13 | J89: =SUM(J3:J88) -> 1.4700198e+09 | L89: =SUM(L3:L88) -> 3.8223179e+13 | M89: =SUM(M3:M88) -> 1.4701223e+09
G90: =G89='PL USD'!F5 -> TRUE
H91: Trading | I91: =SUMIF(A2:A88,H91,I2:I88) -> 2020473850 | J91: =+I91/26000 -> 77710.533 | L91: =G86-K86 -> 56276.868
H92: FG | I92: =SUMIF(A2:A88,H92,I2:I88) -> 3.8218493e+13 | J92: =+I92/26000 -> 1.469942e+09 | K92: =SUM(J91:J92)=J89 -> TRUE
H93: WIP NG | I93: 61382802 | J93: =+I93/26000 -> 2360.877
H94: RMA | I94: 2.0588769e+08 | J94: =+I94/26000 -> 7918.7573
H95: Distroy | I95: 1.4809718e+09 | J95: =+I95/26000 -> 56960.455
H96: Others | I96: 81941567 | J96: =+I96/26000 -> 3151.5987
I97: TOT COGS | J97: =SUBTOTAL(9,J91:J96) -> 1.4700902e+09
J98: =J97='02.Income Statement '!D8 -> FALSE
G99: =SUBTOTAL(9,G2:G45) -> 1303768 | J99: =SUBTOTAL(9,J2:J45) -> 1349615.2
J100: +
E102: Code | F102: Name | G102: Sale | J102: COGS (sale out) | L102: Cost of Producing in Mar
A103: Code | B103: Name | C103: Item No. | D103: Item Name | G103: Qty | H103: Unit | I103: Sales Revenue | J103: USD | K103: VND | L103: VND | M103: USD
A104: FG | B104: SEVT | C104: 101271 | D104: PK PA1 - GH94-40718A (Samsung) | E104: CD-0001 | F104: CÔNG TY TNHH SAMSUNG ELECTRONICS VIỆT NAM THÁI NGUYÊN | G104: 138000 | H104: 31525 | I104: 4350450000 | J104: 34053.986 | K104: =+G104*J104 -> 4.6994501e+09 | L104: =+I104-K104 -> -3.4900013e+08 | M104: =+I104/26000 -> 167325
A105: FG | B105: SEVT | C105: 101285 | D105: PK B7R Main Sub6 - GH94-42274A( Samsung) | E105: CD-0001 | F105: CÔNG TY TNHH SAMSUNG ELECTRONICS VIỆT NAM THÁI NGUYÊN | G105: 2400 | H105: 17090 | I105: 41016000 | J105: 27414.601 | K105: =+G105*J105 -> 65795043 | L105: =+I105-K105 -> -24779043 | M105: =+I105/26000 -> 1577.5385
A106: FG | B106: SEVT | C106: 101286 | D106: PK B7 Sub- GH94-42470A ( Samsung) | E106: CD-0001 | F106: CÔNG TY TNHH SAMSUNG ELECTRONICS VIỆT NAM THÁI NGUYÊN | G106: 151400 | H106: 21754.81 | I106: 3293678392 | J106: 12162.806 | K106: =+G106*J106 -> 1.8414488e+09 | L106: =+I106-K106 -> 1.4522296e+09 | M106: =+I106/26000 -> 126679.94
A107: FG | B107: SEVT | C107: 101318 | D107: PK M3 GH94-43862A ( Samsung) | E107: CD-0001 | F107: CÔNG TY TNHH SAMSUNG ELECTRONICS VIỆT NAM THÁI NGUYÊN | G107: 115495 | H107: 45590 | I107: 5265417050 | J107: 28004.421 | K107: =+G107*J107 -> 3.2343706e+09 | L107: =+I107-K107 -> 2.0310465e+09 | M107: =+I107/26000 -> 202516.04
A108: FG | B108: SEVT | C108: 101328 | D108: PK M1 GH94-43770A ( Samsung) | E108: CD-0001 | F108: CÔNG TY TNHH SAMSUNG ELECTRONICS VIỆT NAM THÁI NGUYÊN | G108: 115454 | H108: 31672 | I108: 3656659088 | J108: 19282.398 | K108: =+G108*J108 -> 2.22623e+09 | L108: =+I108-K108 -> 1.4304291e+09 | M108: =+I108/26000 -> 140640.73
A109: FG | B109: INTOPS | C109: 120438 | D109: PK SM-A176B | E109: CD-0003 | F109: CÔNG TY TNHH INTOPS VIỆT NAM | G109: 182530 | H109: 16213 | I109: 2959358890 | J109: 15261.134 | K109: =+G109*J109 -> 2.7856148e+09 | L109: =+I109-K109 -> 1.7374411e+08 | M109: =+I109/26000 -> 113821.5
A110: FG | B110: ELENTEC | C110: 101319 | D110: PK Bracket Front A37 fixxing jig | E110: CD-0004 | F110: CÔNG TY TNHH ELENTEC VIỆT NAM | G110: 3 | H110: 5290740 | I110: 15872220 | J110: 3353749.1 | K110: =+G110*J110 -> 10061247 | L110: =+I110-K110 -> 5810972.7 | M110: =+I110/26000 -> 610.47
A111: FG | B111: ELENTEC | C111: 101320 | D111: PK Bracket Front A37 Jig check location hole | E111: CD-0004 | F111: CÔNG TY TNHH ELENTEC VIỆT NAM | G111: 2 | H111: 13050492 | I111: 26100984 | J111: 3058749.1 | K111: =+G111*J111 -> 6117498.2 | L111: =+I111-K111 -> 19983486 | M111: =+I111/26000 -> 1003.884
A112: FG | B112: ELENTEC | C112: 101321 | D112: PK Bracket Front A37 Bending Jig | E112: CD-0004 | F112: CÔNG TY TNHH ELENTEC VIỆT NAM | G112: 2 | H112: 14108640 | I112: 28217280 | J112: 3058749.1 | K112: =+G112*J112 -> 6117498.2 | L112: =+I112-K112 -> 22099782 | M112: =+I112/26000 -> 1085.28
A113: FG | B113: ELENTEC | C113: 101322 | D113: PK Bracket Front A37 Jig check length | E113: CD-0004 | F113: CÔNG TY TNHH ELENTEC VIỆT NAM | G113: 2 | H113: 8465184 | I113: 16930368 | J113: 3193749.1 | K113: =+G113*J113 -> 6387498.2 | L113: =+I113-K113 -> 10542870 | M113: =+I113/26000 -> 651.168
A114: FG | B114: ELENTEC | C114: 101323 | D114: PK Bracket Front A37 Jig check width | E114: CD-0004 | F114: CÔNG TY TNHH ELENTEC VIỆT NAM | G114: 2 | H114: 8465184 | I114: 16930368 | J114: 3193749.1 | K114: =+G114*J114 -> 6387498.2 | L114: =+I114-K114 -> 10542870 | M114: =+I114/26000 -> 651.168
A115: FG | B115: ELENTEC | C115: 101346 | D115: PK Front A376B Jig fixing product for check dimension (Back ) | E115: CD-0004 | F115: CÔNG TY TNHH ELENTEC VIỆT NAM | G115: 3 | H115: 5290740 | I115: 15872220 | J115: 1749428.3 | K115: =+G115*J115 -> 5248284.9 | L115: =+I115-K115 -> 10623935 | M115: =+I115/26000 -> 610.47
... A127: FG | B127: ELENTEC | C127: 140417 | D127: PK JIG - Test Resistance Jig ( 22point Ω) Đồ gá bằng thép kiểm tra điện trở cho sản phẩm A376B | E127: CD-0004 | F127: CÔNG TY TNHH ELENTEC VIỆT NAM | G127: 1 | H127: 20020000 | I127: 20020000 | J127: 18528895 | K127: =+G127*J127 -> 18528895 | L127: =+I127-K127 -> 1491104.8 | M127: =+I127/26000 -> 770
A128: Trading | B128: ELENTEC | C128: 784985 | D128: SM- A376B SIMTRAY, USB CHECK JIG | E128: CD-0004 | F128: CÔNG TY TNHH ELENTEC VIỆT NAM | G128: 1 | H128: 13050492 | I128: 13050492 | J128: #N/A | M128: =+I128/26000 -> 501.942
A129: Trading | B129: ELENTEC | C129: 785058 | D129: Jig Hotpress A37 | E129: CD-0004 | F129: CÔNG TY TNHH ELENTEC VIỆT NAM | G129: 2 | H129: 12345060 | I129: 24690120 | J129: #N/A | M129: =+I129/26000 -> 949.62
A130: Trading | B130: ELENTEC | C130: 785059 | D130: Flatness Sensor Jig ( 25 point LVDT)/ Đồ gá kiểm tra độ phẳng sản phẩm A376B | E130: CD-0004 | F130: CÔNG TY TNHH ELENTEC VIỆT NAM | G130: 1 | H130: 55146000 | I130: 55146000 | J130: #N/A | M130: =+I130/26000 -> 2121
A131: FG | B131: MOBASE VN | C131: 120634 | D131: PK SM-A366B | E131: CD-0005 | F131: CÔNG TY TNHH MOBASE VIỆT NAM | G131: 60960 | H131: 17553 | I131: 1070030880 | J131: 29225.558 | K131: =+G131*J131 -> 1.78159e+09 | L131: =+I131-K131 -> -7.1155916e+08 | M131: =+I131/26000 -> 41155.034
A132: Scrapt | B132: TONKIN | C132: 8900030 | D132: Sỉ Nhôm từ Casting Loại 1 | E132: CD-0010 | F132: Công ty TNHH Tonkin | G132: 1542 | H132: 34545.45 | I132: 53269091 | J132: #N/A | L132: =+I132/26000 -> 2048.8112
A133: Scrapt | B133: TONKIN | C133: 8900043 | D133: Phế liệu Nhôm - S36 | E133: CD-0010 | F133: Công ty TNHH Tonkin | G133: 4715 | H133: 41818.18 | I133: 197172727 | J133: #N/A | L133: =+I133/26000 -> 7583.5664
A134: Scrapt | B134: TONKIN | C134: 8900051 | D134: Sỉ nhôm từ tái chế Loại 2 | E134: CD-0010 | F134: Công ty TNHH Tonkin | G134: 18023 | H134: 21363.64 | I134: 385036818 | J134: #N/A | L134: =+I134/26000 -> 14809.108
A135: Scrapt | B135: THUAN THANH | C135: 8900023 | D135: Phoi Nhôm CNC ép | E135: CD-0012 | F135: CÔNG TY CỔ PHẦN MÔI TRƯỜNG THUẬN THÀNH | G135: 23943 | H135: 31818.18 | I135: 761822727 | J135: #N/A | L135: =+I135/26000 -> 29300.874
A136: Scrapt | B136: THUAN THANH | C136: 8900037 | D136: Magie dính dầu | E136: CD-0012 | F136: CÔNG TY CỔ PHẦN MÔI TRƯỜNG THUẬN THÀNH | G136: 373 | H136: 909.09 | I136: 339091 | J136: #N/A | L136: =+I136/26000 -> 13.041962
A137: Scrapt | B137: BÌNH NGUYÊN | C137: 8900000 | D137: Nhựa can/ White plastic can | E137: CD-0013 | F137: CÔNG TY CỔ PHẦN CÔNG NGHỆ CAO MÔI TRƯỜNG BÌNH NGUYÊN | G137: 289 | H137: 7273.15 | I137: 2101940 | J137: #N/A | L137: =+I137/26000 -> 80.843846
A138: Scrapt | B138: BÌNH NGUYÊN | C138: 8900001 | D138: Giấy bìa/Paper cover | E138: CD-0013 | F138: CÔNG TY CỔ PHẦN CÔNG NGHỆ CAO MÔI TRƯỜNG BÌNH NGUYÊN | G138: 1506 | H138: 3181.48 | I138: 4791311 | J138: #N/A | L138: =+I138/26000 -> 184.28119
A139: Scrapt | B139: BÌNH NGUYÊN | C139: 8900002 | D139: Nylon | E139: CD-0013 | F139: CÔNG TY CỔ PHẦN CÔNG NGHỆ CAO MÔI TRƯỜNG BÌNH NGUYÊN | G139: 632 | H139: 10000 | I139: 6320000 | J139: #N/A | L139: =+I139/26000 -> 243.07692
A140: Scrapt | B140: BÌNH NGUYÊN | C140: 8900003 | D140: Gỗ phế/ Wasted wood | E140: CD-0013 | F140: CÔNG TY CỔ PHẦN CÔNG NGHỆ CAO MÔI TRƯỜNG BÌNH NGUYÊN | G140: 5754 | H140: 363.89 | I140: 2093817 | J140: #N/A | L140: =+I140/26000 -> 80.531423
A141: Scrapt | B141: BÌNH NGUYÊN | C141: 8900004 | D141: Sắt phế liệu/ Scrap iron | E141: CD-0013 | F141: CÔNG TY CỔ PHẦN CÔNG NGHỆ CAO MÔI TRƯỜNG BÌNH NGUYÊN | G141: 12453 | H141: 4090.91 | I141: 50944091 | J141: #N/A | L141: =+I141/26000 -> 1959.3881
A142: Scrapt | B142: BÌNH NGUYÊN | C142: 8900005 | D142: Vỏ thùng sơn/ Paint bucket | E142: CD-0013 | F142: CÔNG TY CỔ PHẦN CÔNG NGHỆ CAO MÔI TRƯỜNG BÌNH NGUYÊN | G142: 140 | H142: 3181.82 | I142: 445455 | J142: #N/A | L142: =+I142/26000 -> 17.132885
A143: Scrapt | B143: BÌNH NGUYÊN | C143: 8900007 | D143: Phi sắt /Iron barrel 200lit | E143: CD-0013 | F143: CÔNG TY CỔ PHẦN CÔNG NGHỆ CAO MÔI TRƯỜNG BÌNH NGUYÊN | G143: 106 | H143: 59090.91 | I143: 6263636 | J143: #N/A | L143: =+I143/26000 -> 240.90908
...

Sheet Sch 1 - Sales
C1: Sales summary 2026
D2: 25000 | E2: 25000 | F2: 25000 | G2: 25500 | H2: 25500 | I2: 25500 | J2: 25500 | K2: 25500 | L2: 26000 | M2: 26000 | N2: 26000 | O2: 26000 | P2: Ex.rate: | Q2: 26000
B3: STT | C3: By Customer | D3: Jan | E3: Feb | F3: Mar | G3: Apr | H3: May | I3: Jun | J3: July | K3: Aug | L3: Sep | M3: Oct | N3: Nov | O3: Dec | P3: Total | Q3: % | R3: Cos
A4: CD-0004 | B4: =SUBTOTAL(3,$C$3:C3) -> 1 | C4: ELENTEC | D4: 604744.27 | E4: 756522.2 | F4: 608328.86 | G4: 415561.43 | P4: =+SUM(D4:O4) -> 2385156.8 | Q4: =+P4/$P$32 -> 0.1681923 | R4: Samsung Others
A5: CD-0003 | B5: =SUBTOTAL(3,$C$3:C4) -> 2 | C5: INTOPS | D5: 335328.18 | E5: 106660.8 | F5: 113821.5 | G5: 188120.69 | P5: =+SUM(D5:O5) -> 743931.17 | Q5: =+P5/$P$32 -> 0.052459234 | R5: Samsung Others
A6: CD-0005 | B6: =SUBTOTAL(3,$C$3:C5) -> 3 | C6: MOBASE | D6: 32440.034 | E6: 0 | F6: 41155.034 | G6: 55359.36 | P6: =+SUM(D6:O6) -> 128954.43 | Q6: =+P6/$P$32 -> 0.0090933823 | R6: Samsung Others
A7: CD-0001 | B7: =SUBTOTAL(3,$C$3:C6) -> 4 | C7: SEVT | D7: 593607.82 | E7: 397029.05 | F7: 638739.25 | G7: 395524.35 | P7: =+SUM(D7:O7) -> 2024900.5 | Q7: =+P7/$P$32 -> 0.14278838 | R7: Samsung CNC: Sale
A8: CF-0023-1 | B8: 5 | C8: MFG-Qualcomm | D8: 69610.571 | E8: 41511.335 | F8: 50108.973 | G8: 60343.375 | P8: =+SUM(D8:O8) -> 221574.25 | Q8: =+P8/$P$32 -> 0.015624585 | R8: Qualcomm ( Mobile)
A9: CF-0023-2 | B9: 6 | C9: MFG-ASG | D9: 0 | E9: 58059.391 | F9: 20296.514 | G9: 82073.518 | P9: =+SUM(D9:O9) -> 160429.42 | Q9: =+P9/$P$32 -> 0.011312881 | R9: Qualcomm ( Mobile)
A10: CF-0005 | B10: =SUBTOTAL(3,$C$3:C9) -> 7 | C10: LG YANTAI | D10: 439497.67 | E10: 386650.32 | F10: 730071.83 | G10: 592426.44 | P10: =+SUM(D10:O10) -> 2148646.3 | Q10: =+P10/$P$32 -> 0.15151447 | R10: LGIT
A11: CF-0012 | B11: =SUBTOTAL(3,$C$3:C10) -> 8 | C11: LG KOREA | D11: 27064.312 | E11: 31425.045 | F11: 76617.498 | G11: 76718.642 | P11: =+SUM(D11:O11) -> 211825.5 | Q11: =+P11/$P$32 -> 0.014937139 | R11: LGIT
A12: CF-0006 | B12: =SUBTOTAL(3,$C$3:C11) -> 9 | C12: LG MEXICO | D12: 34795.633 | E12: 230453.46 | F12: 27226.136 | G12: 264238.78 | P12: =+SUM(D12:O12) -> 556714.01 | Q12: =+P12/$P$32 -> 0.039257383 | R12: LGIT
A13: CF-0007 | B13: =SUBTOTAL(3,$C$3:C12) -> 10 | C13: ZF POLAND | D13: 196323.69 | E13: 194930.25 | F13: 186807.09 | G13: 175585.87 | P13: =+SUM(D13:O13) -> 753646.89 | Q13: =+P13/$P$32 -> 0.05314435 | R13: ZF
A14: CF-0010 | B14: =SUBTOTAL(3,$C$3:C13) -> 11 | C14: ZF SHANGHAI | D14: 82267.015 | E14: 0 | F14: 102419.41 | G14: 89314.257 | P14: =+SUM(D14:O14) -> 274000.69 | Q14: =+P14/$P$32 -> 0.0193215 | R14: ZF
A15: CF-0009 | B15: =SUBTOTAL(3,$C$3:C14) -> 12 | C15: ZF US | D15: 292701.27 | E15: 0 | F15: 399697.3 | G15: 4829.9798 | P15: =+SUM(D15:O15) -> 697228.55 | Q15: =+P15/$P$32 -> 0.049165941 | R15: ZF
A16: CF-0011 | B16: =SUBTOTAL(3,$C$3:C15) -> 13 | C16: ZF UK | D16: 58523.918 | E16: 67931.002 | F16: 87723.904 | G16: 95266.498 | P16: =+SUM(D16:O16) -> 309445.32 | Q16: =+P16/$P$32 -> 0.021820923 | R16: ZF
A17: CF-0017 | B17: =SUBTOTAL(3,$C$3:C16) -> 14 | C17: ZF MEXICO | D17: 110834.5 | E17: 109746.14 | F17: 111174.61 | G17: 0 | P17: =+SUM(D17:O17) -> 331755.25 | Q17: =+P17/$P$32 -> 0.023394135 | R17: ZF
A18: CF-0029 | B18: 16 | C18: ZF BRASIL | G18: 19419.771 | P18: =+SUM(D18:O18) -> 19419.771 | Q18: =+P18/$P$32 -> 0.0013694093 | R18: ZF
A19: CF-0013 | B19: =SUBTOTAL(3,$C$3:C17) -> 15 | C19: MANDO (ZHANGJIAGANG) | D19: 513233.63 | E19: 594948.02 | F19: 658588.51 | G19: 524204.8 | P19: =+SUM(D19:O19) -> 2290975 | Q19: =+P19/$P$32 -> 0.16155096 | R19: Mando
A20: CF-0015 | B20: =SUBTOTAL(3,$C$3:C19) -> 17 | C20: HL KLEMOVE INDIA | D20: 109952.43 | E20: 73594.524 | F20: 74493.236 | G20: 111853.98 | P20: =+SUM(D20:O20) -> 369894.17 | Q20: =+P20/$P$32 -> 0.026083549 | R20: Mando
A21: CF-0027 | B21: =SUBTOTAL(3,$C$3:C20) -> 18 | C21: MANDO CORPORATION | D21: 429.243 | E21: 1140.1615 | G21: 18270.47 | P21: =+SUM(D21:O21) -> 19839.875 | Q21: =+P21/$P$32 -> 0.0013990335 | R21: Mando
A22: CF-0014 | B22: =SUBTOTAL(3,$C$3:C21) -> 19 | C22: MANDO KOREA | D22: 0 | E22: 0 | G22: 0 | P22: =+SUM(D22:O22) -> 0 | Q22: =+P22/$P$32 -> 0 | R22: Mando
A23: CD-0008 | B23: =SUBTOTAL(3,$C$3:C22) -> 20 | C23: TTI | D23: 0 | E23: 0 | G23: 0 | P23: =+SUM(D23:O23) -> 0 | Q23: =+P23/$P$32 -> 0 | R23: TTI
A24: CF-0019 | B24: =SUBTOTAL(3,$C$3:C23) -> 21 | C24: HYOSEONG | D24: 0 | E24: 0 | G24: 0 | P24: =+SUM(D24:O24) -> 0 | Q24: =+P24/$P$32 -> 0 | R24: Hyoseong
A25: CF-0022 | B25: =SUBTOTAL(3,$C$3:C24) -> 22 | C25: DORIGO | D25: 0 | E25: 0 | G25: 0 | P25: =+SUM(D25:O25) -> 0 | Q25: =+P25/$P$32 -> 0 | R25: Dorigo
A26: CF-0028 | B26: =SUBTOTAL(3,$C$3:C25) -> 23 | C26: TAILYN | D26: 23541.21 | E26: 0 | F26: 23505.09 | G26: 0 | P26: =+SUM(D26:O26) -> 47046.3 | Q26: =+P26/$P$32 -> 0.0033175285 | R26: TAILYN
A27: CD-0027 | B27: =SUBTOTAL(3,$C$3:C26) -> 24 | C27: LONG BÌNH | D27: 0 | E27: 0 | F27: 704 | G27: 4296 | P27: =+SUM(D27:O27) -> 5000 | Q27: =+P27/$P$32 -> 0.00035258123 | R27: LONG BINH
A28: CD-0012 | B28: =SUBTOTAL(3,$C$3:C27) -> 25 | C28: THUAN THANH | D28: 22187.783 | E28: 10306.643 | F28: 29313.916 | G28: 29493.846 | P28: =+SUM(D28:O28) -> 91302.189 | Q28: =+P28/$P$32 -> 0.0064382877 | R28: Waste
A29: CD-0013 | B29: =SUBTOTAL(3,$C$3:C28) -> 26 | C29: BÌNH NGUYÊN | D29: 30274.907 | E29: 15704.634 | F29: 32224.831 | G29: 19322.124 | P29: =+SUM(D29:O29) -> 97526.497 | Q29: =+P29/$P$32 -> 0.0068772025 | R29: Waste
A30: CD-0010 | B30: =SUBTOTAL(3,$C$3:C29) -> 27 | C30: TONKIN | D30: 15630.07 | E30: 22544.773 | F30: 24441.486 | G30: 22867.343 | P30: =+SUM(D30:O30) -> 85483.671 | Q30: =+P30/$P$32 -> 0.0060279877 | R30: Waste
A31: CD-0015 | B31: =SUBTOTAL(3,$C$3:C30) -> 28 | C31: MINH PHÚC | D31: 53192.902 | E31: 44673.601 | F31: 59051.469 | G31: 49514.685 | P31: =+SUM(D31:O31) -> 206432.66 | Q31: =+P31/$P$32 -> 0.014556856 | R31: Waste
B32: Total Sales | D32: =SUM(D4:D31) -> 3646181.1 | E32: =SUM(E4:E31) -> 3143831.3 | F32: =SUM(F4:F31) -> 4096510.4 | G32: =SUM(G4:G31) -> 3294606.2 | H32: =SUM(H4:H31) -> 0 | I32: =SUM(I4:I31) -> 0 | J32: =SUM(J4:J31) -> 0 | K32: =SUM(K4:K31) -> 0 | ... Q32: =SUM(Q4:Q31) -> 1 | R32: =+(D32+E32+F32)*25000+(G32+H32+I32+J32)*25500+K32*25500+L32*26000+M32*26000+N32*26000+O32*26000 -> 3.5617553e+11
C33: TB | D33: 3646181.1 | E33: 3143831.3 | F33: =3457771.19413846+F7 -> 4096510.4 | G33: 3294606.2

Sheet 02.Income Statement 
B1: 01. 2020Y Monthly Income Statement
B2: Income Statement | P2: [unit: USD]
B3: Description | C3: Jan.26 | D3: Feb.26 | E3: Mar.26 | F3: Apr.26 | G3: May.26 | H3: Jun.26 | I3: Jul.26 | J3: Aug.26 | K3: Sep.26 | L3: Oct.26 | M3: Nov.26 | N3: Dec.26 | O3: TotalY26 | P3: 4월 수정 | Q3: 조정내용
B4: Total Sale | C4: =SUM(C5:C7) -> 3646181.1 | D4: =SUM(D5:D7) -> 3143831.3 | E4: =SUM(E5:E7) -> 4096510.4 | F4: =SUM(F5:F7) -> 3294606.2 | G4: =SUM(G5:G7) -> 0 | H4: =SUM(H5:H7) -> 0 | I4: =SUM(I5:I7) -> 0 | J4: =SUM(J5:J7) -> 0 | ... N4: =SUM(N5:N7) -> 0 | O4: =SUM(C4:N4) -> 14181129 | P4: =SUM(P5:P7) -> 3375582.2
B5: Sales | C5: 3468446.9 | D5: 2951628.6 | E5: 3887018.2 | F5: 3055323.5 | O5: =SUM(C5:N5) -> 13362417 | P5: =3055323.54918077+'비용 증가 사유'!E12 -> 3136299.5 | Q5: A276 금형 정상 매출 반영시 (+8만불)
B6: Sales-trading | C6: 56448.55 | D6: 98973.047 | E6: 64460.585 | F6: 118084.66 | O6: =SUM(C6:N6) -> 337966.84 | P6: 118084.66
B7: Sales -scrap | C7: 121285.66 | D7: 93229.652 | E7: 145031.7 | F7: 121198 | O7: =SUM(C7:N7) -> 480745.01 | P7: 121198
B8: Cost of Goods Sold | C8: =C9+C10-C11+C12 -> 2633553.7 | D8: =D9+D10-D11+D12 -> 2581808.6 | E8: =E9+E10-E11+E12-E13+265 -> 3130898.4 | F8: =F9+F10-F11+F12 -> 2825043.4 | G8: =G9+G10-G11+G12+G13 -> 0 | H8: =H9+H10-H11+H12+H13 -> 0 | I8: =I9+I10-I11+I12+I13 -> 0 | J8: =J9+J10-J11+J12+J13 -> 0 | K8: =K9+K10-K11+K12+K13 -> 0 | L8: =L9+L10-L11+L12+L13 -> 0 | M8: =M9+M10-M11+M12+M13 -> 0 | N8: =N9+N10-N11+N12+N13 -> 0 | O8: =SUM(C8:N8) -> 11171304 | P8: =P9+P10-P11+P12 -> 2814781.4
B9: Beginning Goods | C9: 1552094.3 | D9: 1685226.7 | E9: 1326384.5 | F9: 846959.1 | O9: =SUM(C9:N9) -> 5410664.5 | P9: 846959.1
B10: Manufacturing cost | C10: 2662039.5 | D10: 2210773.2 | E10: 2856536.5 | F10: 2717168.7 | O10: =SUM(C10:N10) -> 10446518 | P10: =2717168.6991031-50000-15000+'비용 증가 사유'!F12 -> 2706906.7 | Q10: OT관리 (-5만불) + 금형원가반영 (+5.4만불)
B11: Ending Goods | C11: 1629668 | D11: 1326384.5 | E11: 846959.1 | F11: 808791.43 | O11: =SUM(C11:N11) -> 4611803 | P11: 808791.43
B12: Cost of Trading & Others | C12: 49088 | D12: 12193.199 | E12: -92960 | F12: 69707 | O12: =SUM(C12:N12) -> 38028.199 | P12: 69707
B13: Clear stock | C13: 204746.19 | D13: =+'PL USD'!F17 -> 95089.477 | E13: 112368.48 | O13: =SUM(C13:N13) -> 412204.15
B14: Gross margin | C14: =C4-C8-C13 -> 807881.19 | D14: =D4-D8-D13 -> 466933.26 | E14: =E4-E8-E13 -> 853243.6 | F14: =F4-F8-F13 -> 469562.84 | G14: =G4-G8 -> 0 | H14: =H4-H8 -> 0 | I14: =I4-I8 -> 0 | J14: =J4-J8 -> 0 | K14: =K4-K8 -> 0 | L14: =L4-L8 -> 0 | M14: =M4-M8 -> 0 | N14: =N4-N8 -> 0 | O14: =O4-O8 -> 3009825 | P14: =P4-P8-P13 -> 560800.84
B15: SA&GA | C15: 348666.18 | D15: =+'PL USD'!F46 -> 334109.77 | E15: =+'PL USD'!G46 -> 351521.91 | F15: =+'PL USD'!H46 -> 366191.26 | O15: =SUM(C15:N15) -> 1400489.1 | P15: =F15-12000 -> 354191.26 | Q15: Air 물류비 관리 (-1.2만불)
B16: R&D | C16: 70161.86 | D16: =+'PL USD'!F62 -> 59271.189 | E16: =+'PL USD'!G62 -> 65128.591 | F16: =+'PL USD'!H62 -> 64351.366 | O16: =SUM(C16:N16) -> 258913.01 | P16: =F16 -> 64351.366
B17: Operating profit | C17: =+C14-C15-C16 -> 389053.15 | D17: =+D14-D15-D16 -> 73552.302 | E17: =+E14-E15-E16 -> 436593.1 | F17: =+F14-F15-F16 -> 39020.217 | G17: =G14-G15-G16 -> 0 | H17: =H14-H15-H16 -> 0 | I17: =I14-I15-I16 -> 0 | J17: =J14-J15-J16 -> 0 | K17: =K14-K15-K16 -> 0 | L17: =L14-L15-L16 -> 0 | M17: =M14-M15-M16 -> 0 | N17: =N14-N15-N16 -> 0 | O17: =O14-O15-O16 -> 1350422.9 | P17: =+P14-P15-P16 -> 142258.22
B18: Other Profit & Loss | C18: -96154.297 | D18: -73552.302 | E18: =-395029.837433846 -> -395029.84 | F18: -29210.882 | O18: =SUM(C18:N18) -> -593947.32 | P18: -29210.882
B19: investment income | O19: =SUM(C19:N19) -> 0
B20: Ordinary profit | C20: =C17+C18 -> 292898.86 | D20: =D17+D18 -> 0 | E20: =E17+E18 -> 41563.259 | F20: =F17+F18 -> 9809.3356 | G20: =G17+G18 -> 0 | H20: =H17+H18 -> 0 | I20: =I17+I18 -> 0 | J20: =J17+J18 -> 0 | ... P20: =P17+P18 -> 113047.34
B21: Non - deductable expense | C21: 14107 | D21: 9892.8426 | E21: 8792 | F21: 13566 | O21: =SUM(C21:N21) -> 46357.843 | P21: 13566
B22: Chargable income accumulated | C22: =+C20+C21 -> 307005.86 | D22: =+D20+D21 -> 9892.8426 | E22: =+E20+E21 -> 50355.259 | F22: =+F20+F21 -> 23375.336 | G22: =+G20+G21 -> 0 | H22: =+H20+H21 -> 0 | I22: =+I20+I21 -> 0 | J22: =+J20+J21 -> 0 | ... N22: =+N20+N21 -> 0 | O22: =SUM(C22:N22) -> 390629.29 | P22: =+P20+P21 -> 126613.34 | S22: Carried forward Losses | T22: Remaining
B23: CIT 20% | O23: =SUM(C23:N23) -> 0
B24: Net Income Before clear stock | C24: =+C20+C13+C23 -> 497645.05 | D24: =+D20+D13-D23 -> 95089.477 | E24: =+E20+E13-E23+Q18 -> 153931.74 | F24: =+F20+F13-F23 -> 9809.3356 | G24: =+G20+G13-G23 -> 0 | H24: =+H20+H13-H23 -> 0 | I24: =+I20+I13-I23 -> 0 | J24: =+J20+J13-J23 -> 0 | K24: =+K20+K13-K23 -> 0 | L24: =+L20+L13-L23 -> 0 | M24: =+M20+M13-M23 -> 0 | N24: =+N20-N23+N13 -> 0 | O24: =+O20+O13-O23+S24 -> 1168679.7 | P24: =+P20+P13-P23 -> 113047.34
B25: Net Income After clear stock | C25: =+C20-C23 -> 292898.86 | D25: =+D20-D23 -> 0 | E25: =+E20-E23 -> 41563.259 | F25: =+F20-F23 -> 9809.3356 | G25: =+G20-G23 -> 0 | H25: =+H20-H23 -> 0 | I25: =+I20-I23 -> 0 | J25: =+J20-J23 -> 0 | ... N25: =+N20-N23 -> 0 | O25: =SUM(C25:N25) -> 344271.45 | P25: =+P20-P23 -> 113047.34 | S25: 941645.19 | T25: =+S25-O22 -> 551015.9
B26: Gross profit Margin | C26: =IF(C14/C4<>0,C14/C4,"") -> 0.22156914 | D26: =IF(D14/D4<>0,D14/D4,"") -> 0.14852363 | E26: =IF(E14/E4<>0,E14/E4,"") -> 0.20828547 | F26: =IF(F14/F4<>0,F14/F4,"") -> 0.14252473 | G26: =IF(G14/G4<>0,G14/G4,"") -> #DIV/0! | H26: =IF(H14/H4<>0,H14/H4,"") -> #DIV/0! | I26: =IF(I14/I4<>0,I14/I4,"") -> #DIV/0! | J26: =IF(J14/J4<>0,J14/J4,"") -> #DIV/0! | ... N26: =IF(N14/N4<>0,N14/N4,"") -> #DIV/0! | O26: =O14/O4 -> 0.21224157 | P26: =IF(P14/P4<>0,P14/P4,"") -> 0.16613455
B27: COGSTS | C27: =C8/C4 -> 0.72227726 | D27: =D8/D4 -> 0.82123 | E27: =E8/E4 -> 0.76428424 | F27: =F8/F4 -> 0.85747527 | G27: =G8/G4 -> #DIV/0! | H27: =H8/H4 -> #DIV/0! | I27: =I8/I4 -> #DIV/0! | J27: =J8/J4 -> #DIV/0! | ... P27: =P8/P4 -> 0.83386545
B28: Business management fee rate | C28: =(C15+C16)/C4 -> 0.11486759 | D28: =(D15+D16)/D4 -> 0.12512788 | E28: =(E15+E16)/E4 -> 0.10170864 | F28: =(F15+F16)/F4 -> 0.13068106 | G28: =(G15+G16)/G4 -> #DIV/0! | H28: =(H15+H16)/H4 -> #DIV/0! | I28: =(I15+I16)/I4 -> #DIV/0! | J28: =(J15+J16)/J4 -> #DIV/0! | ... P28: =(P15+P16)/P4 -> 0.12399124
B29: Net Profit Margin ( before) | C29: =C24/C4 -> 0.13648391 | D29: =D24/D4 -> 0.030246367 | E29: =E24/E4 -> 0.037576307 | F29: =F24/F4 -> 0.0029773924 | G29: =G24/G4 -> #DIV/0! | H29: =H24/H4 -> #DIV/0! | I29: =I24/I4 -> #DIV/0! | J29: =J24/J4 -> #DIV/0! | ... P29: =P24/P4 -> 0.03348973 | Q29: 약 +3% 개선
B30: Net Profit Margin ( after) | C30: =C25/C4 -> 0.08033031 | D30: =D25/D4 -> 0 | E30: =E25/E4 -> 0.010146016 | F30: =F25/F4 -> 0.0029773924 | G30: =G25/G4 -> #DIV/0! | H30: =H25/H4 -> #DIV/0! | I30: =I25/I4 -> #DIV/0! | J30: =J25/J4 -> #DIV/0! | ... P30: =P25/P4 -> 0.03348973
B31: EBITDA | C31: =+C25+C33+C34+C35+C36 -> 703640.85 | D31: =+D25+D33+D34+D35+D36 -> 400745.32 | E31: =+E25+E33+E34+E35+E36 -> 432934.01 | F31: =+F25+F33+F34+F35+F36 -> 407234.1 | G31: =+G25+G33+G34+G35+G36 -> 0 | H31: =+H25+H33+H34+H35+H36 -> 0 | I31: =+I25+I33+I34+I35+I36 -> 0 | J31: =+J24+J33+J34+J35+J36 -> 0 | K31: =+K24+K33+K34+K35+K36 -> 0 | L31: =+L24+L33+L34+L35+L36 -> 0 | M31: =+M24+M33+M34+M35+M36 -> 0 | N31: =+N24+N33+N34+N35+N36 -> 0 | O31: =+O25+O33+O34+O35+O36 -> 1944554.3 | P31: =+P25+P33+P34+P35+P36 -> 510472.1
B33: Interest Expenses | C33: 77451.044 | D33: 63055.526 | E33: 52889.094 | F33: =+'PL USD'!H90 -> 58686.246 | O33: =SUM(C33:N33) -> 252081.91 | P33: =F33 -> 58686.246
B34: Taxes | C34: 0 | D34: 0 | E34: 0 | O34: =SUM(C34:N34) -> 0
B35: Depreciation | C35: 205800.61 | D35: 209386.77 | E35: 209759.11 | F35: =+'PL USD'!H92 -> 205689.61 | O35: =SUM(C35:N35) -> 830636.09 | P35: =F35 -> 205689.61
B36: Amortization | C36: 127490.34 | D36: 128303.03 | E36: 128722.55 | F36: =+'PL USD'!H93 -> 133048.9 | O36: =SUM(C36:N36) -> 517564.82 | P36: =F36 -> 133048.9

Sheet PL USD
A1: Statement of Comprehensive Income | C1: Statement of Comprehensive Income
A2: January 2024 through Dec 2024 | C2: January 2026 through Dec 2026 | D2: 25000 | E2: 25000 | F2: 25000 | G2: 25000 | H2: 25000 | I2: 25000 | J2: 25000 | K2: 25000 | L2: 25000 | M2: 25000 | N2: 25000 | O2: 25000 | P2: 25000
D3: 12 | E3: 01 | F3: 02 | G3: 03 | H3: 04 | I3: 05 | J3: 06 | K3: 07 | L3: 08 | M3: 09 | N3: 10 | O3: 11 | P3: 12 | Q3: 4 | S3: Monthly
D4: 45992 | E4: Jan.26 | F4: February | G4: March | H4: April | I4: May | J4: June | K4: Jul | L4: Aug | M4: Sep | N4: Oct | O4: Nov | P4: Dec | Q4: Total | R4: % | S4: Average
A5: 4-0000 | C5: Income | D5: =+D6+D7+D8 -> 4017516.6 | E5: =+E6+E7+E8 -> 3646181.1 | F5: =+F6+F7+F8 -> 3143831.3 | G5: =+G9 -> 4096510.4 | H5: =+H6+H7+H8 -> 3294606.2 | Q5: =SUM(E5:OFFSET(E5,0,$Q$3-1)) -> 14181129
A6: 4-1000 | C6: Sales | D6: 3823390 | E6: 3468446.9 | F6: 2951628.6 | G6: 3887018.2 | H6: 3055323.5 | Q6: =SUM(E6:OFFSET(E6,0,$Q$3-1)) -> 13362417 | S6: =AVERAGE(E6:OFFSET(E6,0,$Q$3-1)) -> 3340604.3
A7: 4-1001 | C7: Sales-trading | D7: 54436.813 | E7: 56448.55 | F7: 98973.047 | G7: 64460.585 | H7: 118084.66 | Q7: =SUM(E7:OFFSET(E7,0,$Q$3-1)) -> 337966.84 | S7: =AVERAGE(E7:OFFSET(E7,0,$Q$3-1)) -> 84491.711
A8: 4-1002 | C8: Sales -scrapt | D8: 139689.74 | E8: 121285.66 | F8: 93229.652 | G8: 145031.7 | H8: 121198 | Q8: =SUM(E8:OFFSET(E8,0,$Q$3-1)) -> 480745.01 | S8: =AVERAGE(E8:OFFSET(E8,0,$Q$3-1)) -> 120186.25
C9: Total Income | D9: =SUM(D6:D8) -> 4017516.6 | E9: =SUM(E6:E8) -> 3646181.1 | F9: =SUM(F6:F8) -> 3143831.3 | G9: =SUM(G6:G8) -> 4096510.4 | H9: 3294606.2 | Q9: =SUM(Q6:Q8) -> 14181129 | S9: =AVERAGE(E9:OFFSET(E9,0,$Q$3-1)) -> 3545282.3
A10: 5-0000 | C10: Cost of Goods Sold | D10: 3299928.3 | E10: 2633553.7 | F10: 2581808.6 | G10: 3130898.3 | H10: 2825043.3 | Q10: =SUM(E10:OFFSET(E10,0,$Q$3-1)) -> 11171304 | S10: =AVERAGE(E10:OFFSET(E10,0,$Q$3-1)) -> 2792826
A11: 5-1001 | C11: Beginning Goods | D11: 1454995 | E11: 1552094.3 | F11: 1685226.7 | G11: 1326384.5 | H11: 846959.1 | Q11: =SUM(E11:OFFSET(E11,0,$Q$3-1)) -> 5410664.5 | S11: =AVERAGE(E11:OFFSET(E11,0,$Q$3-1)) -> 1352666.1
A12: 5-1002 | C12: Manufacturing cost | D12: 3264245.8 | E12: 2816146.9 | F12: 2210773.2 | G12: 2856536.5 | H12: 2717168.7 | Q12: =SUM(E12:OFFSET(E12,0,$Q$3-1)) -> 10600625 | S12: =AVERAGE(E12:OFFSET(E12,0,$Q$3-1)) -> 2650156.3
A13: 5-1003 | C13: Ending Goods | D13: 1532520.9 | E13: 1665118 | F13: 1326384.5 | G13: 846959.1 | H13: 808791.43 | Q13: =SUM(E13:OFFSET(E13,0,$Q$3-1)) -> 4647253 | S13: =AVERAGE(E13:OFFSET(E13,0,$Q$3-1)) -> 1161813.2
A14: 5-1004 | C14: Cost of other sold | D14: 74475.206 | E14: 14119.821 | F14: 31288.489 | G14: -139435.4 | H14: -16440.744 | Q14: =SUM(E14:OFFSET(E14,0,$Q$3-1)) -> -110467.84 | S14: =AVERAGE(E14:OFFSET(E14,0,$Q$3-1)) -> -27616.96
A15: 5-1005 | C15: Cost of trading | D15: 38733.077 | E15: 40113.887 | F15: 75994.187 | G15: 46740.305 | H15: 86147.695 | Q15: =SUM(E15:OFFSET(E15,0,$Q$3-1)) -> 248996.07 | S15: =AVERAGE(E15:OFFSET(E15,0,$Q$3-1)) -> 62249.019
C16: Total Cost of Goods Sold | D16: =+D10 -> 3299928.3 | E16: =+E10 -> 2633553.7 | F16: =+F10 -> 2581808.6 | G16: =+G10 -> 3130898.3 | H16: =+H10 -> 2825043.3 | Q16: =+Q10 -> 11171304 | S16: =AVERAGE(E16:OFFSET(E16,0,$Q$3-1)) -> 2792826
C17: CLEAR STOCK | D17: 227313.96 | E17: 204746.19 | F17: =2472326397.42279/26000 -> 95089.477 | G17: 112368.48 | Q17: =SUM(E17:OFFSET(E17,0,$Q$3-1)) -> 412204.15 | S17: =AVERAGE(E17:OFFSET(E17,0,$Q$3-1)) -> 137401.38
C18: Gross Profit without clear stock | D18: =D5-D10 -> 717588.32 | E18: =E5-E10 -> 1012627.4 | F18: =F5-F10 -> 562022.74 | G18: =G5-G10 -> 965612.18 | H18: =H5-H10 -> 469562.89 | I18: =I5-I10 -> 0 | J18: =J5-J10 -> 0 | K18: =K5-K10 -> 0 | ... Q18: =Q5-Q10 -> 3009825.2 | R18: =+Q18/Q5 -> 0.21224158 | S18: =AVERAGE(E18:OFFSET(E18,0,$Q$3-1)) -> 752456.3
C19: Gross margin | D19: =+D18/D5 -> 0.1786149 | E19: =+E18/E5 -> 0.27772273 | F19: =+F18/F5 -> 0.17877 | G19: =+G18/G5 -> 0.23571579 | H19: =+H18/H5 -> 0.14252474 | Q19: =+Q18/Q5 -> 0.21224158
C20: Gross Profit clear stock | D20: =+D9-D16-D17 -> 490274.36 | E20: =+E9-E16-E17 -> 807881.18 | F20: =+F9-F16-F17 -> 466933.26 | G20: =+G9-G16-G17 -> 853243.7 | H20: =+H9-H16-H17 -> 469562.89 | Q20: =+Q9-Q16-Q17 -> 2597621 | R20: =+Q20/Q5 -> 0.18317449 | S20: =AVERAGE(E20:OFFSET(E20,0,$Q$3-1)) -> 649405.26
C21: Gross margin | D21: =+D20/D5 -> 0.12203418 | E21: =+E20/E5 -> 0.22156913 | F21: =+F20/F5 -> 0.14852363 | G21: =+G20/G5 -> 0.20828549 | H21: =+H20/H5 -> 0.14252474 | Q21: =+Q20/Q5 -> 0.18317449
A22: 6-0000 | C22: Expenses(SA&GA) | D22: Dec.25 | E22: Jan.26 | F22: Feb.26 | G22: Mar.26 | H22: Apr.26 | I22: May.26 | J22: Jun.26 | K22: Jul.26 | L22: Aug.26 | M22: Sep.26 | N22: Oct.26 | O22: Nov.26 | P22: Dec.26 | Q22: Total | R22: % | S22: Average
A23: 6-0101 | C23: Salary (Included PIT,SHUI) | D23: 132527.42 | E23: 111161.2 | F23: 112429.82 | G23: 112019.33 | H23: 111093.04 | Q23: =SUM(E23:OFFSET(E23,0,$Q$3-1)) -> 446703.39 | R23: =+Q23/($Q$46+$Q$62) -> 0.26919538 | S23: =AVERAGE(E23:OFFSET(E23,0,$Q$3-1)) -> 111675.85
A24: 6-0102 | C24: Meal + other Welfare | D24: 21448.983 | E24: 7760.4779 | F24: 9958.0508 | G24: 8847.4437 | H24: 13127.86 | Q24: =SUM(E24:OFFSET(E24,0,$Q$3-1)) -> 39693.833 | R24: =+Q24/($Q$46+$Q$62) -> 0.023920563 | S24: =AVERAGE(E24:OFFSET(E24,0,$Q$3-1)) -> 9923.4581
A25: 6-0103 | C25: Travel -business trips | D25: 1642.5093 | E25: 3053.386 | F25: 9733.6693 | G25: -3304.3547 | H25: 760.47231 | Q25: =SUM(E25:OFFSET(E25,0,$Q$3-1)) -> 10243.173 | R25: =+Q25/($Q$46+$Q$62) -> 0.0061728093 | S25: =AVERAGE(E25:OFFSET(E25,0,$Q$3-1)) -> 2560.7932
A26: 6-0104 | C26: Logistics | D26: 51957.065 | E26: 59898.606 | F26: 35460.457 | G26: 43152.636 | H26: 68193.467 | Q26: =SUM(E26:OFFSET(E26,0,$Q$3-1)) -> 206705.17 | R26: =+Q26/($Q$46+$Q$62) -> 0.12456605 | S26: =AVERAGE(E26:OFFSET(E26,0,$Q$3-1)) -> 51676.292
A27: 6-0105 | C27: Communication | D27: 519.93512 | E27: 504.55728 | F27: 468.64223 | G27: 552.98808 | H27: 513.33262 | Q27: =SUM(E27:OFFSET(E27,0,$Q$3-1)) -> 2039.5202 | R27: =+Q27/($Q$46+$Q$62) -> 0.0012290693 | S27: =AVERAGE(E27:OFFSET(E27,0,$Q$3-1)) -> 509.88005
A28: 6-0106 | C28: Electricity | D28: 5811.083 | E28: 2273.363 | F28: 3631.2689 | G28: 3247.2722 | H28: 4612.383 | Q28: =SUM(E28:OFFSET(E28,0,$Q$3-1)) -> 13764.287 | R28: =+Q28/($Q$46+$Q$62) -> 0.0082947267 | S28: =AVERAGE(E28:OFFSET(E28,0,$Q$3-1)) -> 3441.0718
A29: 6-0108 | C29: Commission fee (M&C SG,KR,CH,JP) | D29: 30004.385 | E29: 10398.846 | F29: 0 | G29: 10140 | H29: 10318.788 | Q29: =SUM(E29:OFFSET(E29,0,$Q$3-1)) -> 30857.635 | R29: =+Q29/($Q$46+$Q$62) -> 0.018595634 | S29: =AVERAGE(E29:OFFSET(E29,0,$Q$3-1)) -> 7714.4087
A30: 6-0109 | C30: Consulting | D30: 3917.9305 | E30: 5199.2402 | F30: 2290.5983 | G30: 7317.3775 | H30: 4768.2416 | Q30: =SUM(E30:OFFSET(E30,0,$Q$3-1)) -> 19575.458 | R30: =+Q30/($Q$46+$Q$62) -> 0.011796693 | S30: =AVERAGE(E30:OFFSET(E30,0,$Q$3-1)) -> 4893.8644
A31: 6-0110 | C31: cars relative | D31: 9646.4987 | E31: 6865.1066 | F31: 8327.2716 | G31: 8229.7944 | H31: 8579.3791 | Q31: =SUM(E31:OFFSET(E31,0,$Q$3-1)) -> 32001.552 | R31: =+Q31/($Q$46+$Q$62) -> 0.019284989 | S31: =AVERAGE(E31:OFFSET(E31,0,$Q$3-1)) -> 8000.3879
A32: 6-0111 | C32: Rental others(house, land..) | D32: 6084.5 | E32: 4902.4552 | F32: 4071.9849 | G32: 4346.3261 | H32: 4928.6418 | Q32: =SUM(E32:OFFSET(E32,0,$Q$3-1)) -> 18249.408 | R32: =+Q32/($Q$46+$Q$62) -> 0.01099758 | S32: =AVERAGE(E32:OFFSET(E32,0,$Q$3-1)) -> 4562.352
A33: 6-0112 | C33: Rental - oversea -warehouse | D33: 39635.471 | E33: 43561.063 | F33: 40420.792 | G33: 41677.704 | H33: 56755.041 | Q33: =SUM(E33:OFFSET(E33,0,$Q$3-1)) -> 182414.6 | R33: =+Q33/($Q$46+$Q$62) -> 0.10992791 | S33: =AVERAGE(E33:OFFSET(E33,0,$Q$3-1)) -> 45603.65
A34: 6-0113 | C34: Sorting | D34: 41246.382 | E34: 54131.265 | F34: 65976.92 | G34: 66618.489 | H34: 48253.842 | Q34: =SUM(E34:OFFSET(E34,0,$Q$3-1)) -> 234980.52 | R34: =+Q34/($Q$46+$Q$62) -> 0.14160553 | S34: =AVERAGE(E34:OFFSET(E34,0,$Q$3-1)) -> 58745.129
... A45: 6-0126 | C45: Others (Garden,EHS,Unreasonable...) | D45: 19508.392 | E45: 3174.5671 | F45: 12165.537 | G45: 16816.728 | H45: 12507.059 | Q45: =SUM(E45:OFFSET(E45,0,$Q$3-1)) -> 44663.891 | R45: =+Q45/($Q$46+$Q$62) -> 0.026915653 | S45: =AVERAGE(E45:OFFSET(E45,0,$Q$3-1)) -> 11165.973
C46: Total Expenses Without R&D | D46: 407120.99 | E46: =SUM(E23:E45) -> 348666.18 | F46: =SUM(F23:F45) -> 334109.77 | G46: =SUM(G23:G45) -> 351521.91 | H46: =SUM(H23:H45) -> 366191.26 | I46: =SUM(I23:I45) -> 0 | J46: =SUM(J23:J45) -> 0 | K46: =SUM(K23:K45) -> 0 | L46: =SUM(L23:L45) -> 0 | ... Q46: =SUM(Q23:Q45) -> 1400489.1 | R46: =+Q46/($Q$46+$Q$62) -> 0.84397211 | S46: =AVERAGE(E46:OFFSET(E46,0,$Q$3-1)) -> 350122.28
C47: Salary (Included PIT,SHUI) | D47: 55502.412 | E47: 50620.956 | F47: 47781.144 | G47: 46669.745 | H47: 45478.654 | Q47: =SUM(E47:OFFSET(E47,0,$Q$3-1)) -> 190550.5 | R47: =+Q47/($Q$46+$Q$62) -> 0.11483082 | S47: =AVERAGE(E47:OFFSET(E47,0,$Q$3-1)) -> 47637.625
C48: Meal + other Welfare | D48: 4909.5409 | E48: 1372.1695 | F48: 1085.2895 | G48: 1644.478 | H48: 1487.7466 | Q48: =SUM(E48:OFFSET(E48,0,$Q$3-1)) -> 5589.6837 | R48: =+Q48/($Q$46+$Q$62) -> 0.0033684925 | S48: =AVERAGE(E48:OFFSET(E48,0,$Q$3-1)) -> 1397.4209
C49: Travel -business trips | D49: 0 | E49: 0 | F49: 999.92385 | G49: 0 | H49: 0 | Q49: =SUM(E49:OFFSET(E49,0,$Q$3-1)) -> 999.92385 | R49: =+Q49/($Q$46+$Q$62) -> 0.00060258079 | S49: =AVERAGE(E49:OFFSET(E49,0,$Q$3-1)) -> 249.98096
C50: Logistics | D50: 619.91923 | E50: 556.65 | F50: 0 | G50: 1119.5784 | H50: 0 | Q50: =SUM(E50:OFFSET(E50,0,$Q$3-1)) -> 1676.2284 | R50: =+Q50/($Q$46+$Q$62) -> 0.00101014 | S50: =AVERAGE(E50:OFFSET(E50,0,$Q$3-1)) -> 419.0571
C51: Communication | D51: 36.861539 | E51: 27.611538 | F51: 26.795462 | G51: 46.867154 | H51: 23.850615 | Q51: =SUM(E51:OFFSET(E51,0,$Q$3-1)) -> 125.12477 | R51: =+Q51/($Q$46+$Q$62) -> 7.5403525e-05 | S51: =AVERAGE(E51:OFFSET(E51,0,$Q$3-1)) -> 31.281192
C52: Consulting | D52: 95.538462 | E52: 0 | F52: 0 | G52: 157.84615 | H52: 0 | Q52: =SUM(E52:OFFSET(E52,0,$Q$3-1)) -> 157.84615 | R52: =+Q52/($Q$46+$Q$62) -> 9.5122304e-05 | S52: =AVERAGE(E52:OFFSET(E52,0,$Q$3-1)) -> 39.461538
C53: cars relative | D53: 2526.1408 | E53: 1607.5751 | F53: 1893.0303 | G53: 2044.1031 | H53: 2670.4421 | Q53: =SUM(E53:OFFSET(E53,0,$Q$3-1)) -> 8215.1506 | R53: =+Q53/($Q$46+$Q$62) -> 0.004950669 | S53: =AVERAGE(E53:OFFSET(E53,0,$Q$3-1)) -> 2053.7877
C54: Sample | D54: 5315.1891 | E54: 7112.7629 | F54: 1154.0732 | G54: 2141.5214 | H54: 2848.2685 | Q54: =SUM(E54:OFFSET(E54,0,$Q$3-1)) -> 13256.626 | R54: =+Q54/($Q$46+$Q$62) -> 0.0079887966 | S54: =AVERAGE(E54:OFFSET(E54,0,$Q$3-1)) -> 3314.1565
C55: Depreciation | D55: 0 | E55: 0 | F55: 0 | G55: 4507.1128 | H55: 4507.1128 | Q55: =SUM(E55:OFFSET(E55,0,$Q$3-1)) -> 9014.2256 | R55: =+Q55/($Q$46+$Q$62) -> 0.0054322129 | S55: =AVERAGE(E55:OFFSET(E55,0,$Q$3-1)) -> 2253.5564
C56: Amortization | D56: 483.50962 | E56: 483.50962 | F56: 483.50962 | G56: 483.50962 | H56: 483.50962 | Q56: =SUM(E56:OFFSET(E56,0,$Q$3-1)) -> 1934.0385 | R56: =+Q56/($Q$46+$Q$62) -> 0.0011655032 | S56: =AVERAGE(E56:OFFSET(E56,0,$Q$3-1)) -> 483.50962
C57: Entertainment | D57: 0 | E57: 0 | F57: 55.153846 | G57: 306.1 | H57: 1020.6415 | Q57: =SUM(E57:OFFSET(E57,0,$Q$3-1)) -> 1381.8954 | R57: =+Q57/($Q$46+$Q$62) -> 0.00083276703 | S57: =AVERAGE(E57:OFFSET(E57,0,$Q$3-1)) -> 345.47385
C58: Tuition fee | D58: 2339.1542 | E58: 2339.1542 | F58: 2339.1542 | G58: 2339.1542 | H58: 2339.1542 | Q58: =SUM(E58:OFFSET(E58,0,$Q$3-1)) -> 9356.6166 | R58: =+Q58/($Q$46+$Q$62) -> 0.0056385468 | S58: =AVERAGE(E58:OFFSET(E58,0,$Q$3-1)) -> 2339.1542
... C61: Others (Garden,EHS,Unreasonable...) | D61: 3899.7318 | E61: 3231.1438 | F61: 338.40915 | G61: 1415.3232 | H61: 123.52919 | Q61: =SUM(E61:OFFSET(E61,0,$Q$3-1)) -> 5108.4053 | R61: =+Q61/($Q$46+$Q$62) -> 0.0030784613 | S61: =AVERAGE(E61:OFFSET(E61,0,$Q$3-1)) -> 1277.1013
C62: Total Expenses R&D | D62: 78091.098 | E62: =SUM(E47:E61) -> 70161.86 | F62: =SUM(F47:F61) -> 59271.189 | G62: =SUM(G47:G61) -> 65128.591 | H62: =SUM(H47:H61) -> 64351.366 | I62: =SUM(I47:I61) -> 0 | J62: =SUM(J47:J61) -> 0 | K62: =SUM(K47:K61) -> 0 | L62: =SUM(L47:L61) -> 0 | ... P62: =SUM(P47:P61) -> 0 | Q62: =SUM(E62:OFFSET(E62,0,$Q$3-1)) -> 258913.01 | R62: =+Q62/($Q$46+$Q$62) -> 0.15602789 | S62: =AVERAGE(E62:OFFSET(E62,0,$Q$3-1)) -> 64728.251
C63: TOTAL SA&GA | D63: =+D46+D62 -> 485212.09 | E63: =+E46+E62 -> 418828.04 | F63: =+F46+F62 -> 393380.96 | G63: =+G46+G62 -> 416650.51 | H63: =+H46+H62 -> 430542.63 | I63: =+I46+I62 -> 0 | J63: =+J46+J62 -> 0 | K63: =+K46+K62 -> 0 | ... Q63: =+Q46+Q62 -> 1659402.1 | R63: =+Q63/($Q$46+$Q$62) -> 1 | S63: =AVERAGE(E63:OFFSET(E63,0,$Q$3-1)) -> 414850.53
C64: Operating Profit | D64: =D20-D46-D62 -> 5062.2745 | E64: =E20-E46-E62 -> 389053.15 | F64: =F20-F46-F62 -> 73552.302 | G64: =G20-G46-G62 -> 436593.2 | H64: =H20-H46-H62 -> 39020.266 | I64: =I20-I46-I62 -> 0 | J64: =J20-J46-J62 -> 0 | K64: =K20-K46-K62 -> 0 | ... Q64: =Q20-Q46-Q62 -> 938218.91 | R64: =+Q64/Q9 -> 0.066159677 | S64: =AVERAGE(E64:OFFSET(E64,0,$Q$3-1)) -> 234554.73
A65: 8-0000 | C65: Other Income
A66: 8-1001 | C66: Interest Income: Bank | D66: 6038.5492 | E66: 1632.3728 | F66: 1468.2573 | G66: 2371.1437 | H66: 18888.977 | Q66: =SUM(E66:OFFSET(E66,0,$Q$3-1)) -> 24360.751 | S66: =AVERAGE(E66:OFFSET(E66,0,$Q$3-1)) -> 6090.1878
A67: 8-1002 | C67: Exchange Gain | D67: 49719.831 | E67: 36320.948 | F67: 38167.874 | G67: 49578.102 | H67: 20513.597 | Q67: =SUM(E67:OFFSET(E67,0,$Q$3-1)) -> 144580.52 | S67: =AVERAGE(E67:OFFSET(E67,0,$Q$3-1)) -> 36145.13
A68: 8-1003 | C68: Sundry Income | D68: 745.99958 | E68: 689.15935 | F68: 698.80385 | G68: 1599.1762 | H68: 1239.3221 | Q68: =SUM(E68:OFFSET(E68,0,$Q$3-1)) -> 4226.4615 | S68: =AVERAGE(E68:OFFSET(E68,0,$Q$3-1)) -> 1056.6154
A69: 8-1004 | C69: Disposal assets-Gain | D69: 20743.531 | E69: 0 | F69: 0 | G69: 0 | H69: 0 | Q69: =SUM(E69:OFFSET(E69,0,$Q$3-1)) -> 0 | S69: =AVERAGE(E69:OFFSET(E69,0,$Q$3-1)) -> 0
C70: Total Other Income | D70: =SUM(D66:D69) -> 77247.911 | E70: =SUM(E66:E69) -> 38642.48 | F70: =SUM(F66:F69) -> 40334.935 | G70: =SUM(G66:G69) -> 53548.422 | H70: =SUM(H66:H69) -> 40641.896 | I70: =SUM(I66:I69) -> 0 | J70: =SUM(J66:J69) -> 0 | K70: =SUM(K66:K69) -> 0 | ... Q70: =SUM(Q66:Q69) -> 173167.73 | S70: =AVERAGE(E68:OFFSET(E68,0,$Q$3-1)) -> 1056.6154
A71: 9-0000 | C71: Other Expenses
A72: 9-0201 | C72: Bank Loan Interest | D72: 58596.576 | E72: 77067.748 | F72: 62672.23 | G72: 52505.798 | H72: 58302.95 | Q72: =SUM(E72:OFFSET(E72,0,$Q$3-1)) -> 250548.73 | S72: =AVERAGE(E72:OFFSET(E72,0,$Q$3-1)) -> 62637.181
A73: 9-0202 | C73: Personal interest | D73: 383.29615 | E73: 383.29615 | F73: 383.29615 | G73: 383.29615 | H73: 383.29615 | Q73: =SUM(E73:OFFSET(E73,0,$Q$3-1)) -> 1533.1846 | S73: =AVERAGE(E73:OFFSET(E73,0,$Q$3-1)) -> 383.29615
A74: 9-0203 | C74: Exchange (Gain)/Loss | D74: 34533.751 | E74: 56070.951 | F74: 50238.663 | G74: 27200.312 | H74: 6451.344 | Q74: =SUM(E74:OFFSET(E74,0,$Q$3-1)) -> 139961.27 | S74: =AVERAGE(E74:OFFSET(E74,0,$Q$3-1)) -> 34990.317
A75: 9-0204 | C75: Discount payment | D75: 0 | E75: 0 | F75: 0 | G75: 0 | H75: 0 | Q75: =SUM(E75:OFFSET(E75,0,$Q$3-1)) -> 0 | S75: =AVERAGE(E75:OFFSET(E75,0,$Q$3-1)) -> 0
A76: 9-0205 | C76: Other loss- Claim fee | D76: 0 | E76: 0 | F76: 0 | G76: 0 | H76: 0 | Q76: =SUM(E76:OFFSET(E76,0,$Q$3-1)) -> 0 | S76: =AVERAGE(E76:OFFSET(E76,0,$Q$3-1)) -> 0
A77: 9-0206 | C77: Sundry Expense | D77: 935.52805 | E77: 1274.7829 | F77: 593.04843 | G77: 1114.109 | H77: 4715.1883 | Q77: =SUM(E77:OFFSET(E77,0,$Q$3-1)) -> 7697.1287 | S77: =AVERAGE(E77:OFFSET(E77,0,$Q$3-1)) -> 1924.2822
A78: 9-0207 | C78: Disposal assets-Loss | D78: 2780.7692 | E78: 0 | F78: 0 | G78: =367374.744360769 -> 367374.74 | H78: 0 | Q78: =SUM(E78:OFFSET(E78,0,$Q$3-1)) -> 367374.74 | S78: =AVERAGE(E78:OFFSET(E78,0,$Q$3-1)) -> 91843.686
C79: Total Other Expenses | D79: =SUM(D72:D78) -> 97229.921 | E79: =SUM(E72:E78) -> 134796.78 | F79: =SUM(F72:F78) -> 113887.24 | G79: =SUM(G72:G78) -> 448578.26 | H79: =SUM(H72:H78) -> 69852.778 | I79: =SUM(I72:I78) -> 0 | J79: =SUM(J72:J78) -> 0 | K79: =SUM(K72:K78) -> 0 | ... P79: =SUM(P72:P78) -> 0 | Q79: =SUM(E79:OFFSET(E79,0,$Q$3-1)) -> 767115.05 | S79: =AVERAGE(E79:OFFSET(E79,0,$Q$3-1)) -> 191778.76
C80: CIT
C81: Net Profit/(Loss) without clear stock | D81: =+D64+D70-D79-D80+D17 -> 212394.22 | E81: =+E64+E70-E79-E80+E17 -> 497645.04 | F81: =+F64+F70-F79-F80+F17 -> 95089.477 | G81: =+G64+G70-G79-G80+G17+G78 -> 521306.58 | H81: =+H64+H70-H79-H80+H17 -> 9809.3846 | I81: =+I64+I70-I79-I80+I17 -> 0 | J81: =+J64+J70-J79-J80+J17 -> 0 | K81: =+K64+K70-K79-K80+K17 -> 0 | L81: =+L64+L70-L79-L80+L17 -> 0 | M81: =+M64+M70-M79-M80+M17 -> 0 | N81: =+N64+N70-N79-N80+N17 -> 0 | O81: =+O64+O70-O79-O80+O17 -> 0 | ... Q81: =+Q64+Q70-Q79-Q80+Q17 -> 756475.74 | R81: =+Q81/Q5 -> 0.05334383 | S81: =AVERAGE(E81:OFFSET(E81,0,$Q$3-1)) -> 280962.62
C82: Net Profit/(Loss) clear stock | D82: =+D64+D70-D79-D80 -> -14919.735 | E82: =+E64+E70-E79-E80 -> 292898.85 | F82: =+F64+F70-F79-F80 -> -3.9290171e-10 | G82: =+G64+G70-G79-G80 -> 41563.358 | H82: =+H64+H70-H79-H80 -> 9809.3846 | I82: =+I64+I70-I79-I80 -> 0 | J82: =+J64+J70-J79-J80 -> 0 | K82: =+K64+K70-K79-K80 -> 0 | ... Q82: =+Q64+Q70-Q79-Q80 -> 344271.59 | R82: =+Q82/Q5 -> 0.024276741 | S82: =AVERAGE(E82:OFFSET(E82,0,$Q$3-1)) -> 86067.898
C83: Gross profit Margin | D83: =+D20/D9 -> 0.12203418 | E83: =+E20/E9 -> 0.22156913 | F83: =+F20/F9 -> 0.14852363 | G83: =+G20/G9 -> 0.20828549 | H83: =+H20/H9 -> 0.14252474 | I83: =+I20/I9 -> #DIV/0! | J83: =+J20/J9 -> #DIV/0! | K83: =+K20/K9 -> #DIV/0! | ... P83: =+P20/P9 -> #DIV/0! | Q83: =Q20/Q9 -> 0.18317449
C84: COGSTS | D84: =+D10/D9 -> 0.8213851 | E84: =+E10/E9 -> 0.72227727 | F84: =+F10/F9 -> 0.82123 | G84: =+G10/G9 -> 0.76428421 | H84: =+H10/H9 -> 0.85747526 | I84: =+I10/I9 -> #DIV/0! | J84: =+J10/J9 -> #DIV/0! | K84: =+K10/K9 -> #DIV/0! | ... P84: =+P10/P9 -> #DIV/0! | Q84: =+Q16/Q9 -> 0.78775842
C85: Business management fee rate | D85: =D63/D9 -> 0.12077413 | E85: =E63/E9 -> 0.11486759 | F85: =F63/F9 -> 0.12512788 | G85: =G63/G9 -> 0.10170864 | H85: =H63/H9 -> 0.13068106 | I85: =I63/I9 -> #DIV/0! | J85: =J63/J9 -> #DIV/0! | K85: =K63/K9 -> #DIV/0! | ... P85: =P63/P9 -> #DIV/0! | Q85: =+Q20/Q10 -> 0.23252622
C86: Net Profit Margin | D86: =+D81/D9 -> 0.052867043 | E86: =+E81/E9 -> 0.13648391 | F86: =+F81/F9 -> 0.030246367 | G86: =+G81/G9 -> 0.12725626 | H86: =+H81/H9 -> 0.0029774073 | I86: =+I81/I9 -> #DIV/0! | J86: =+J81/J9 -> #DIV/0! | K86: =+K81/K9 -> #DIV/0! | ... Q86: =+Q81/Q9 -> 0.05334383
C87: Net Profit Margin Before Clear stock | D87: =+D82/D9 -> -0.0037136711 | E87: =+E82/E9 -> 0.080330309 | F87: =+F82/F9 -> -1.2497544e-16 | G87: =+G82/G9 -> 0.01014604 | H87: =+H82/H9 -> 0.0029774073 | I87: =+I82/I9 -> #DIV/0! | J87: =+J82/J9 -> #DIV/0! | K87: =+K82/K9 -> #DIV/0! | ... Q87: =+Q82/Q9 -> 0.024276741
C88: EBITDA | D88: =+D81+D80+D90+D92+D93 -> 596938.94 | E88: =+E82+E80+E90+E92+E93 -> 703640.85 | F88: =+F82+F80+F90+F92+F93 -> 400745.32 | G88: =+G82+G80+G90+G92+G93 -> 432934.11 | H88: =+H82+H80+H90+H92+H93 -> 407234.15 | I88: =+I82+I80+I90+I92+I93 -> 356497.25 | J88: =+J82+J80+J90+J92+J93 -> 370760.09 | K88: =+K82+K80+K90+K92+K93 -> 380870.62 | L88: =+L82+L80+L90+L92+L93 -> 381578.26 | ... O88: =+O82+O80+O90+O92+O93 -> 364984.14 | P88: =+P81+P80+P90+P92+P93 -> 384544.71 | Q88: =SUM(E88:OFFSET(E88,0,$Q$3-1)) -> 1944554.4
C90: Interest Expenses | D90: 58979.872 | E90: 77451.044 | F90: 63055.526 | G90: 52889.094 | H90: 58686.246 | I90: 66759.404 | J90: 67487.601 | K90: 61994.939 | L90: 63961.59 | M90: 60109.183 | N90: 60381.641 | O90: 60446.345 | P90: 58979.872 | Q90: =SUM(E90:OFFSET(E90,0,$Q$3-1)) -> 252081.91
C91: Taxes | D91: 0 | E91: 0 | F91: 0 | G91: 0 | H91: 0 | I91: 0 | J91: 0 | K91: 0 | L91: 0 | M91: 0 | N91: 0 | O91: 0 | P91: 0 | Q91: =SUM(E91:OFFSET(E91,0,$Q$3-1)) -> 0
C92: Depreciation | D92: 202202.87 | E92: 205800.61 | F92: 209386.77 | G92: 209759.11 | H92: 205689.61 | I92: 181536.51 | J92: 182418.17 | K92: 183799.14 | L92: 187387.46 | M92: 186374.02 | N92: 195101.3 | O92: 196275.81 | P92: 202202.87 | Q92: =SUM(E92:OFFSET(E92,0,$Q$3-1)) -> 830636.09
C93: Amortization | D93: 123361.97 | E93: 127490.34 | F93: 128303.03 | G93: 128722.55 | H93: 133048.9 | I93: 108201.33 | J93: 120854.32 | K93: 135076.54 | L93: 130229.21 | M93: 140237.83 | N93: 125776.19 | O93: 108261.99 | P93: 123361.97 | Q93: =SUM(E93:OFFSET(E93,0,$Q$3-1)) -> 517564.82
D96: 264242.51

Sheet Sch 2 - Manufacturing State
B1: Sch2.Manufacturing Statement
K2: 25500
B3: Category | C3: Dec.2025 | D3: Jan.26 | F3: Feb.26 | H3: Mar.26 | J3: Apr.26
B4: 1. Material Cost | C4: 1149307 | E4: =D5+D6-D8-D7 -> 1168999.4 | G4: =F5+F6-F8-F7 -> 703067.01 | I4: =H5+H6-H8-H7 -> 1269497.5 | K4: =J5+J6-J8-J7 -> 891773.11
B5: 1. Beginning Balance | C5: 1030861 | D5: 856754.83 | F5: =D8 -> 772365.72 | H5: =F8 -> 638942.02 | J5: =H8 -> 602966.12
B6: 2. Input Materials | C6: 1085840.3 | D6: 1247024.2 | F6: 672651.56 | H6: 1375706.6 | J6: 1112834.9
B7: 3. Other Accounts | C7: 12121.9 | D7: =144827.980140759+17586 -> 162413.98 | F7: =7919.25513165968+95089 -> 103008.26 | H7: 142185 | J7: 13495.692 | N7: ■ 월별 인건비·인원·OT 추이
B8: 4. Ending Balance | C8: 856754.83 | D8: 772365.72 | F8: 638942.02 | H8: 602966.12 | J8: 810532.18 | N8: 항목 | O8: 단위 | P8: Jan.26 | Q8: Feb.26 | R8: Mar.26 | S8: Apr.26 | T8: 1Q평균 | U8: Apr vs 1Q
B9: 2. Labor Cost | E9: =D10 -> 433923.41 | G9: =F10 -> 488222.36 | I9: 547646.11 | K9: =J10 -> 598756.38 | N9: 인건비 | O9: USD | P9: 433923 | Q9: 488222 | R9: 547646 | S9: 598756 | T9: =AVERAGE(P9:R9) -> 489930.33 | U9: =IFERROR((S9-T9)/T9,0) -> 0.22212478
B10: Salary (Included PIT,SHUI) | C10: 707689.55 | D10: 433923.41 | F10: 488222.36 | H10: 547646.11 | J10: 598756.38 | N10: 총 OT시간 | O10: 시간 | P10: 84286 | Q10: 59208 | R10: 62988 | S10: 81166 | T10: =AVERAGE(P10:R10) -> 68827.333 | U10: =IFERROR((S10-T10)/T10,0) -> 0.17926986
B11: 3. Expenses | E11: =SUM(D12:D32) -> 1073405.7 | G11: =SUM(F12:F32) -> 1041810.5 | I11: =SUM(H12:H32) -> 1116032.5 | K11: =SUM(J12:J32) -> 1180722 | N11: 총 인원수 | O11: 명 | P11: 867 | Q11: 858 | R11: 827 | S11: 801 | T11: =AVERAGE(P11:R11) -> 850.66667 | U11: =IFERROR((S11-T11)/T11,0) -> -0.05838558
B12: Meal | C12: 40725.695 | D12: 30875.727 | F12: 26018.554 | H12: 39132.475 | J12: 36421.748 | N12: 인당 평균 OT시간 | O12: 시간/명 | P12: =P10/P11 -> 97.215686 | Q12: =Q10/Q11 -> 69.006993 | R12: =R10/R11 -> 76.16445 | S12: =S10/S11 -> 101.33084 | T12: =AVERAGE(P12:R12) -> 80.79571 | U12: =IFERROR((S12-T12)/T12,0) -> 0.2541611
B13: Electricity | C13: 419174.62 | D13: 165249.43 | F13: 261565.85 | H13: 233883.33 | J13: 332468.07
B14: Water | C14: 1916.4866 | D14: 2014.1002 | F14: 1722.0365 | H14: 1220.7059 | J14: 2420.7852
B15: Gas | C15: 1243.2014 | D15: 1433.0995 | F15: 1079.4899 | H15: 1615.8567 | J15: 1882.0412
B16: Repair Expense | C16: 20311.871 | D16: 9777.1292 | F16: 5936.5594 | H16: 25174.583 | J16: 21625.904
B17: Transportation | C17: 8829.0432 | D17: 9193.138 | F17: 4507.1177 | H17: 6140.4254 | J17: 7120.412
B18: Travel(Business) | C18: 525.15269 | D18: 0 | F18: 3165.6298 | H18: 0 | J18: 858.98831
B19: Rent Expense (SG MCT, Outside WH, etc) | C19: 41890.523 | D19: 39464.832 | F19: 39304 | H19: 40245.248 | J19: 41604.532
B20: Tax (FCT machines and RM) | C20: 4185.0893 | D20: 3673.9295 | F20: 1429.8447 | H20: 6763.4757 | J20: 5937.7376
B21: Depreciation | C21: 189836.69 | D21: 194564.23 | F21: 197097.28 | H21: 196701.99 | J21: 192632.5
B22: Amortization | C22: 121129.46 | D22: 120468.21 | F22: 124800.87 | H22: 127080.79 | J22: 130447.54
B23: Amotization (Mold) | C23: 68404.037 | D23: 66169.142 | F23: 67646.068 | H23: 68804.584 | J23: 69983.352
B24: Outsourcing (Ano, Paint, Chromate ,CNC) | C24: 87754.566 | D24: 98953.735 | F24: 72915.855 | H24: 68269.669 | J24: 51752.566
... B32: Others (Garden and cleaning,EHS,comsumption,Unreasonable...) | C32: 40330.683 | D32: 21950.47 | F32: 20733.982 | H32: 19562.117 | J32: 24714.681
B33: 4. Total Production Cost | C33: 3177993.8 | E33: =E4+E9+E11 -> 2676328.5 | G33: =G4+G9+G11 -> 2233099.9 | I33: =I4+I9+I11 -> 2933176.2 | K33: =K4+K9+K11 -> 2671251.5
B34: 5. Beginning Balance(WIP) | C34: 515178.85 | E34: 400127 | G34: =E36 -> 419869.6 | I34: =G36 -> 439834.96 | K34: =I36 -> 240830.66
B35: 6. Total | C35: 3693172.7 | E35: =E33+E34 -> 3076455.5 | G35: =G33+G34 -> 2652969.5 | I35: =I33+I34 -> 3373011.1 | K35: =K33+K34 -> 2912082.1
B36: 7. Ending Balance(WIP) | C36: 400127 | E36: 419869.6 | G36: 439834.96 | I36: 240830.66 | K36: 194873.58
B37: 8. Other Accounts | C37: 28799.842 | E37: -155823.36 | G37: 2360.8871 | I37: 275644 | K37: 40
B38: 9. Manufacturing Cost | C38: =C35-C36-C37 -> 3264245.8 | E38: =E35-E36-E37 -> 2812409.3 | G38: =G35-G36-G37 -> 2210773.6 | I38: =I35-I36-I37 -> 2856536.5 | K38: =K35-K36-K37 -> 2717168.6

Sheet NG by Customers
B1: NG FG Detail by months | U1: Exr: 26000
B2: Customers | C2: Jan.26 | E2: Feb.26 | G2: Mar.26 | I2: Apr.26 | K2: May.26 | M2: Jun.26 | O2: Jul.26 | Q2: Aug.26 | S2: Sep.26 | U2: Oct.26 | W2: Nov.26 | Y2: Dec.26 | AA2: YTD26
C3: Qty Jan.26 | D3: Amt Jan.26 | E3: Qty Feb.26 | F3: Amt Feb.26 | G3: Qty Mar.26 | H3: Amt Mar.26 | I3: Qty Apr.26 | J3: Amt Apr.26 | K3: Qty Mat.26 | L3: Amt May.26 | M3: Qty Jun.26 | N3: Amt Jul.26 | O3: Qty Jul.26 | P3: Amt Jul.26 | Q3: Qty Aug.26 | R3: Amt Aug.26 | S3: Qty Sep.26 | T3: Amt Sep.26 | U3: Qty Oct.26 | V3: Amt Oct.26 | W3: Qty Nov.26 | X3: Amt Nov.26 | Y3: Qty Dec.26 | Z3: Amt Dec.26 | AA3: Qty total | AB3: Amt Total | AC3: Sale | AD3: Rate
B4: LG | C4: =SUMIF('NG by model'!$A:$A,B4,'NG by model'!D:D) -> 82154 | D4: =SUMIF('NG by model'!$A:$A,B4,'NG by model'!E:E) -> 83789.62 | E4: =SUMIF('NG by model'!$A:$A,B4,'NG by model'!F:F) -> 15974 | F4: =SUMIF('NG by model'!$A:$A,B4,'NG by model'!G:G) -> 11734.884 | G4: =SUMIF('NG by model'!$A:$A,B4,'NG by model'!H:H) -> 109353 | H4: =SUMIF('NG by model'!$A:$A,B4,'NG by model'!I:I) -> 138744.48 | I4: =SUMIF('NG by model'!$A:$A,B4,'NG by model'!J:J) -> 74013 | J4: =SUMIF('NG by model'!$A:$A,B4,'NG by model'!K:K) -> 114274.94 | AA4: =C4+E4+G4+I4+K4+M4+O4+Q4+S4+U4+W4 -> 281494 | AB4: =D4+F4+H4+J4+L4+N4+P4+R4+T4+V4+X4 -> 348543.92 | AC4: =SUMIF('Sch 1 - Sales'!R:R,B4,'Sch 1 - Sales'!P:P) -> 0 | AD4: =AB4/$AB$9 -> 0.39690465
B5: Samsung | C5: 3919 | D5: =SUMIF('NG by model'!$A:$A,B5,'NG by model'!E:E) -> 47060.262 | E5: =SUMIF('NG by model'!$A:$A,B5,'NG by model'!F:F) -> 24530 | F5: =SUMIF('NG by model'!$A:$A,B5,'NG by model'!G:G) -> 18277.96 | G5: =SUMIF('NG by model'!$A:$A,B5,'NG by model'!H:H) -> 100143 | H5: =SUMIF('NG by model'!$A:$A,B5,'NG by model'!I:I) -> 62822.712 | I5: =SUMIF('NG by model'!$A:$A,B5,'NG by model'!J:J) -> 103193 | J5: =SUMIF('NG by model'!$A:$A,B5,'NG by model'!K:K) -> 62099.278 | AA5: =C5+E5+G5+I5+K5+M5+O5+Q5+S5+U5+W5 -> 231785 | AB5: =D5+F5+H5+J5+L5+N5+P5+R5+T5+V5+X5 -> 190260.21 | AC5: =SUMIF('Sch 1 - Sales'!R:R,B5,'Sch 1 - Sales'!P:P) -> 0 | AD5: =AB5/$AB$9 -> 0.21665895
B6: Mando | C6: 19807 | D6: =SUMIF('NG by model'!$A:$A,B6,'NG by model'!E:E) -> 60051.501 | E6: =SUMIF('NG by model'!$A:$A,B6,'NG by model'!F:F) -> 11056 | F6: =SUMIF('NG by model'!$A:$A,B6,'NG by model'!G:G) -> 12286.579 | G6: =SUMIF('NG by model'!$A:$A,B6,'NG by model'!H:H) -> 55934 | H6: =SUMIF('NG by model'!$A:$A,B6,'NG by model'!I:I) -> 94008.948 | I6: =SUMIF('NG by model'!$A:$A,B6,'NG by model'!J:J) -> 41752 | J6: =SUMIF('NG by model'!$A:$A,B6,'NG by model'!K:K) -> 62956.794 | AA6: =C6+E6+G6+I6+K6+M6+O6+Q6+S6+U6+W6 -> 128549 | AB6: =D6+F6+H6+J6+L6+N6+P6+R6+T6+V6+X6 -> 229303.82 | AC6: =SUMIF('Sch 1 - Sales'!R:R,B6,'Sch 1 - Sales'!P:P) -> 2680709 | AD6: =AB6/$AB$9 -> 0.26111989
B7: ZF | C7: 58068 | D7: =SUMIF('NG by model'!$A:$A,B7,'NG by model'!E:E) -> 26455.294 | E7: =SUMIF('NG by model'!$A:$A,B7,'NG by model'!F:F) -> 16611 | F7: =SUMIF('NG by model'!$A:$A,B7,'NG by model'!G:G) -> 11075.958 | G7: =SUMIF('NG by model'!$A:$A,B7,'NG by model'!H:H) -> 65767 | H7: =SUMIF('NG by model'!$A:$A,B7,'NG by model'!I:I) -> 28491.299 | I7: =SUMIF('NG by model'!$A:$A,B7,'NG by model'!J:J) -> 46003 | J7: =SUMIF('NG by model'!$A:$A,B7,'NG by model'!K:K) -> 25824.411 | AA7: =C7+E7+G7+I7+K7+M7+O7+Q7+S7+U7+W7 -> 186449 | AB7: =D7+F7+H7+J7+L7+N7+P7+R7+T7+V7+X7 -> 91846.962 | AC7: =SUMIF('Sch 1 - Sales'!R:R,B7,'Sch 1 - Sales'!P:P) -> 2385496.5 | AD7: =AB7/$AB$9 -> 0.1045908
B8: Qualcom | C8: 672 | D8: =SUMIF('NG by model'!$A:$A,B8,'NG by model'!E:E) -> 7382.5641 | E8: =SUMIF('NG by model'!$A:$A,B8,'NG by model'!F:F) -> 1668 | F8: =SUMIF('NG by model'!$A:$A,B8,'NG by model'!G:G) -> 3585.0749 | G8: =SUMIF('NG by model'!$A:$A,B8,'NG by model'!H:H) -> 2222 | H8: =SUMIF('NG by model'!$A:$A,B8,'NG by model'!I:I) -> 5019.2724 | I8: =SUMIF('NG by model'!$A:$A,B8,'NG by model'!J:J) -> 711 | J8: =SUMIF('NG by model'!$A:$A,B8,'NG by model'!K:K) -> 2213.48 | AA8: =C8+E8+G8+I8+K8+M8+O8+Q8+S8+U8+W8 -> 5273 | AB8: =D8+F8+H8+J8+L8+N8+P8+R8+T8+V8+X8 -> 18200.391 | AC8: =SUMIF('Sch 1 - Sales'!R:R,B8,'Sch 1 - Sales'!P:P) -> 0 | AD8: =AB8/$AB$9 -> 0.020725709
B9: Total | C9: =SUM(C4:C8) -> 164620 | D9: =SUM(D4:D8) -> 224739.24 | E9: =SUM(E4:E8) -> 69839 | F9: =SUM(F4:F8) -> 56960.455 | G9: =SUM(G4:G8) -> 333419 | H9: =SUM(H4:H8) -> 329086.71 | I9: =SUM(I4:I8) -> 265672 | J9: =SUM(J4:J8) -> 267368.91 | ... AD9: =SUM(AD4:AD8) -> 1
B10: Rate by months | D10: =+D9/$AB$9 -> 0.25592197 | F10: =+F9/$AB$9 -> 0.06486376 | H10: =+H9/$AB$9 -> 0.37474773 | J10: =+J9/$AB$9 -> 0.30446654 | L10: =+L9/$AB$9 -> 0 | N10: =+N9/$AB$9 -> 0 | P10: =+P9/$AB$9 -> 0 | R10: =+R9/$AB$9 -> 0 | T10: =+T9/$AB$9 -> 0 | V10: =+V9/$AB$9 -> 0 | X10: =+X9/$AB$9 -> 0 | Z10: =+Z9/$AB$9 -> 0
B12: Content | C12: Jan.26 | D12: Feb.26 | E12: Mar.26 | F12: Apr.26
B13: Qty NG | C13: =+C9 -> 164620 | D13: =+E9 -> 69839 | E13: =+G9 -> 333419 | F13: =+I9 -> 265672
B14: Amt NG | C14: =+D9 -> 224739.24 | D14: =+F9 -> 56960.455 | E14: =+H9 -> 329086.71 | F14: =+J9 -> 267368.91
B35: * NG by customers | J35: * Amt NG by months
B36: -From Jan to Jul LG had the highest cost of discarded goods with an amount of $446K with 35% | J36: -July is the month with the highest amount of NG incurred at $297k with 23%
B37: -LG also had the highest proportion of discarded goods value in July with an amount of $134k with 45% | J37: - This cost has been fully recorded in COGS and is the reason for the significant decrease in profit in July

Sheet NG by model
S1: 25500 | U1: 26000 | W1: 26000 | Y1: 26000 | AA1: 26000
D2: Jan.26 | F2: Feb.26 Before | H2: Mar.26 | J2: Apr.26 | L2: May.26 | N2: Jun.26 | P2: Jul.26 | R2: Aug.26 | T2: Sep.26 | V2: Oct.26 | X2: Nov.26 | Z2: Dec.26 | AB2: Total .2026Y
A3: Customer | B3: item code | C3: Name | D3: Qty NG | E3: Amt NG | F3: Qty NG | G3: Amt NG | H3: Qty NG | I3: Amt NG | J3: Qty NG | K3: Amt NG | L3: Qty NG | M3: Amt NG | N3: Qty NG | O3: Amt NG | P3: Qty NG | Q3: Amt NG | R3: Qty NG | S3: Amt NG | T3: Qty NG | U3: Amt NG | V3: Qty NG | W3: Amt NG | X3: Qty NG | Y3: Amt NG | Z3: Qty NG | AA3: Amt NG | AB3: Qty NG | AC3: TOT Amt NG
A4: Samsung | B4: 120438 | C4: PK SM-A176B | D4: 34558 | E4: 19659.483 | F4: 5420 | G4: 3772.4068 | H4: 62447 | I4: 36654.309 | J4: 90710 | K4: 55851.949 | AB4: =D4+F4+H4+J4+L4+N4+P4+R4+T4+V4+X4+Z4 -> 193135 | AC4: =E4+G4+I4+K4+M4+O4+Q4+S4+U4+W4+Y4+AA4 -> 115938.15
A5: LG | B5: 120157 | C5: PK LGIT Gen3 AL5 | D5: 18581 | E5: 29502.25 | F5: 1042 | G5: 1956.7246 | H5: 28792 | I5: 48686.602 | J5: 15198 | K5: 27650.593 | AB5: =D5+F5+H5+J5+L5+N5+P5+R5+T5+V5+X5+Z5 -> 63613 | AC5: =E5+G5+I5+K5+M5+O5+Q5+S5+U5+W5+Y5+AA5 -> 107796.17
A6: Mando | B6: 120368 | C6: PK Mando Brose IMEB2 Housing(2) | D6: 11549 | E6: 23987.888 | F6: 0 | G6: 0 | H6: 21999 | I6: 47619.547 | J6: 9324 | K6: 19845.452 | AB6: =D6+F6+H6+J6+L6+N6+P6+R6+T6+V6+X6+Z6 -> 42872 | AC6: =E6+G6+I6+K6+M6+O6+Q6+S6+U6+W6+Y6+AA6 -> 91452.888
A7: LG | B7: 120415 | C7: PK LGIT 3CAZ00041A CL4 Housing | D7: 4387 | E7: 9934.2606 | F7: 0 | G7: 0 | H7: 17963 | I7: 39851.716 | J7: 11063 | K7: 24576.381 | AB7: =D7+F7+H7+J7+L7+N7+P7+R7+T7+V7+X7+Z7 -> 33413 | AC7: =E7+G7+I7+K7+M7+O7+Q7+S7+U7+W7+Y7+AA7 -> 74362.358
A8: Mando | B8: 120309 | C8: PK Mando NX4 Motor Housing | D8: 4985 | E8: 12334.884 | F8: 995 | G8: 2797.0888 | H8: 7624 | I8: 18631.284 | J8: 6620 | K8: 15480.379 | AB8: =D8+F8+H8+J8+L8+N8+P8+R8+T8+V8+X8+Z8 -> 20224 | AC8: =E8+G8+I8+K8+M8+O8+Q8+S8+U8+W8+Y8+AA8 -> 49243.636
A9: Samsung | B9: 120443 | C9: PK SM-A376B | D9: 16887 | E9: 12918.38 | F9: 12609 | G9: 9671.9326 | H9: 33199 | I9: 23305.396 | J9: 623 | K9: 461.55821 | AB9: =D9+F9+H9+J9+L9+N9+P9+R9+T9+V9+X9+Z9 -> 63318 | AC9: =E9+G9+I9+K9+M9+O9+Q9+S9+U9+W9+Y9+AA9 -> 46357.267
A10: LG | B10: 120414 | C10: PK LGIT MQ4a PE Housing 3CAZ00039A | D10: 6964 | E10: 16121.582 | F10: 22 | G10: 51.830122 | H10: 2111 | I10: 4643.8279 | J10: 6541 | K10: 16237.682 | AB10: =D10+F10+H10+J10+L10+N10+P10+R10+T10+V10+X10+Z10 -> 15638 | AC10: =E10+G10+I10+K10+M10+O10+Q10+S10+U10+W10+Y10+AA10 -> 37054.922
A11: LG | B11: 120362 | C11: PK LGIT MPC5.5 Cover lens 3HDC00003A | D11: 27303 | E11: 9275.5485 | F11: 7778 | G11: 4122.2081 | H11: 33180 | I11: 10226.198 | J11: 14736 | K11: 8041.6119 | AB11: =D11+F11+H11+J11+L11+N11+P11+R11+T11+V11+X11+Z11 -> 82997 | AC11: =E11+G11+I11+K11+M11+O11+Q11+S11+U11+W11+Y11+AA11 -> 31665.567
A12: Mando | B12: 120338 | C12: PK Mando N3 Motor & Heatsink Cover | D12: 5558 | E12: 4673.1824 | F12: 4877 | G12: 4896.9924 | H12: 11555 | I12: 10326.477 | J12: 10012 | K12: 9703.557 | AB12: =D12+F12+H12+J12+L12+N12+P12+R12+T12+V12+X12+Z12 -> 32002 | AC12: =E12+G12+I12+K12+M12+O12+Q12+S12+U12+W12+Y12+AA12 -> 29600.209
A13: LG | B13: 120341 | C13: PK LGIT T6M6 Housing 3HUC00006A | D13: 0 | E13: 0 | F13: 0 | G13: 0 | H13: 6246 | I13: 22597.942 | J13: 2112 | K13: 7563.0367 | AB13: =D13+F13+H13+J13+L13+N13+P13+R13+T13+V13+X13+Z13 -> 8358 | AC13: =E13+G13+I13+K13+M13+O13+Q13+S13+U13+W13+Y13+AA13 -> 30160.979
A14: ZF | B14: 120187 | C14: PK TRW-Nissan/FCA/GMT 4.8 Lenmount(336416-13/A011F352) | D14: 25043 | E14: 7476.9543 | F14: 2372 | G14: 734.89166 | H14: 42962 | I14: 12981.727 | J14: 22267 | K14: 8063.4652 | AB14: =D14+F14+H14+J14+L14+N14+P14+R14+T14+V14+X14+Z14 -> 92644 | AC14: =E14+G14+I14+K14+M14+O14+Q14+S14+U14+W14+Y14+AA14 -> 29257.038
A15: Mando | B15: 120367 | C15: PK Mando MAS65C 4.5 Heat Sink(2) | D15: 11209 | E15: 7675.1247 | F15: 4724 | G15: 3233.6503 | H15: 7224 | I15: 5483.744 | J15: 9425 | K15: 7956.4575 | AB15: =D15+F15+H15+J15+L15+N15+P15+R15+T15+V15+X15+Z15 -> 32582 | AC15: =E15+G15+I15+K15+M15+O15+Q15+S15+U15+W15+Y15+AA15 -> 24348.977
... A41: Qualcom | B41: 101263 | C41: PK Qualcomm RIDE 5 50-74187-1 MIDFRAME ASSEMBLY, RIDE 5 | D41: 0 | E41: 0 | F41: 0 | G41: 0 | H41: 453 | I41: 875.91988 | J41: 74 | K41: 507.50615 | AB41: =D41+F41+H41+J41+L41+N41+P41+R41+T41+V41+X41+Z41 -> 527 | AC41: =E41+G41+I41+K41+M41+O41+Q41+S41+U41+W41+Y41+AA41 -> 1383.426
A42: Mando | B42: 120435 | C42: PK Mando Brose JG REPS Housing cover | J42: 1160 | K42: 1256.7475 | AB42: =D42+F42+H42+J42+L42+N42+P42+R42+T42+V42+X42+Z42 -> 1160 | AC42: =E42+G42+I42+K42+M42+O42+Q42+S42+U42+W42+Y42+AA42 -> 1256.7475
A43: Qualcom | B43: 101268 | C43: PK Qualcomm RIDE 5 50-74194-1 BOTTOM HOUSING, PAINTED, BASE UNIT, RIDE 5 | D43: 0 | E43: 0 | F43: 0 | G43: 0 | H43: 106 | I43: 1153.4014 | J43: 1 | K43: 0.081069772 | AB43: =D43+F43+H43+J43+L43+N43+P43+R43+T43+V43+X43+Z43 -> 107 | AC43: =E43+G43+I43+K43+M43+O43+Q43+S43+U43+W43+Y43+AA43 -> 1153.4825
A44: Qualcom | B44: 101175 | C44: PK Qualcomm AIR GEN 5 50-36917-3 CAMERA CARD, BOTTOM TRAY (2) | D44: 1067 | E44: 685.34859 | F44: 4 | G44: 2.7083703 | H44: 75 | I44: 193.44924 | J44: 76 | K44: 96.568121 | AB44: =D44+F44+H44+J44+L44+N44+P44+R44+T44+V44+X44+Z44 -> 1222 | AC44: =E44+G44+I44+K44+M44+O44+Q44+S44+U44+W44+Y44+AA44 -> 978.07432
A45: Qualcom | B45: 101176 | C45: PK Qualcomm AIR GEN 5 50-36917-4 PCIE CARD, BOTTOM TRAY (2) | D45: 295 | E45: 434.87731 | F45: 1 | G45: 0.12916043 | H45: 68 | I45: 408.943 | J45: 66 | K45: 96.937993 | AB45: =D45+F45+H45+J45+L45+N45+P45+R45+T45+V45+X45+Z45 -> 430 | AC45: =E45+G45+I45+K45+M45+O45+Q45+S45+U45+W45+Y45+AA45 -> 940.88746
A46: Qualcom | B46: 101280 | C46: PK Qualcomm RIDE 5 50-74195-3 FRONT COVER, PAINTED, BASE UNIT SX KARUSSELL | D46: 96 | E46: 125.90229 | F46: 0 | G46: 0 | H46: 63 | I46: 717.63241 | J46: 0 | K46: 0 | AB46: =D46+F46+H46+J46+L46+N46+P46+R46+T46+V46+X46+Z46 -> 159 | AC46: =E46+G46+I46+K46+M46+O46+Q46+S46+U46+W46+Y46+AA46 -> 843.5347
A47: Qualcom | B47: 101174 | C47: PK Qualcomm AIR GEN 5 50-36917-2 SOC CARD, BOTTOM TRAY (2) | D47: 769 | E47: 667.17339 | F47: 0 | G47: 0 | H47: 0 | I47: 0 | J47: 47 | K47: 72.793922 | AB47: =D47+F47+H47+J47+L47+N47+P47+R47+T47+V47+X47+Z47 -> 816 | AC47: =E47+G47+I47+K47+M47+O47+Q47+S47+U47+W47+Y47+AA47 -> 739.96731
A48: LG | B48: 120195 | C48: PK LGIT IKC Camera base 3CAC00180A | D48: 586 | E48: 581.11106 | F48: 195 | G48: 133.53389 | H48: 0 | I48: 0 | J48: 11 | K48: 22.837742 | AB48: =D48+F48+H48+J48+L48+N48+P48+R48+T48+V48+X48+Z48 -> 792 | AC48: =E48+G48+I48+K48+M48+O48+Q48+S48+U48+W48+Y48+AA48 -> 737.48269
A49: Qualcom | B49: 101149 | C49: PK Qualcomm MTP Camano 55-PR725-20 Assy Font Housing | D49: 144 | E49: 552.66544 | F49: 0 | G49: 0 | H49: 0 | I49: 0 | J49: 0 | K49: 0 | AB49: =D49+F49+H49+J49+L49+N49+P49+R49+T49+V49+X49+Z49 -> 144 | AC49: =E49+G49+I49+K49+M49+O49+Q49+S49+U49+W49+Y49+AA49 -> 552.66544
A50: Qualcom | B50: 101301 | C50: PK Qualcomm HAWI 50-84675-1 Antenna Carrier | D50: 9 | E50: 456.66559 | F50: 0 | G50: 0 | H50: 5 | I50: 0.6236708 | J50: 0 | K50: 0 | AB50: =D50+F50+H50+J50+L50+N50+P50+R50+T50+V50+X50+Z50 -> 14 | AC50: =E50+G50+I50+K50+M50+O50+Q50+S50+U50+W50+Y50+AA50 -> 457.28926
A51: Qualcom | B51: 101177 | C51: PK Qualcomm AIR GEN 5 50-36917-5 ETHERNET CARD, BOTTOM TRAY (2) | D51: 272 | E51: 349.20641 | F51: 36 | G51: 40.675282 | H51: 17 | I51: 30.382233 | J51: 0 | K51: 0 | AB51: =D51+F51+H51+J51+L51+N51+P51+R51+T51+V51+X51+Z51 -> 325 | AC51: =E51+G51+I51+K51+M51+O51+Q51+S51+U51+W51+Y51+AA51 -> 420.26392
A52: Qualcom | B52: 101325 | C52: PK Qualcomm AMBOSELI CA90-84713-3 HIELD, HEATSINK, RF CARD, PICTOR/ALIOTH | D52: 250 | E52: 340.1084 | F52: 0 | G52: 0 | H52: 0 | I52: 0 | J52: 0 | K52: 0 | AB52: =D52+F52+H52+J52+L52+N52+P52+R52+T52+V52+X52+Z52 -> 250 | AC52: =E52+G52+I52+K52+M52+O52+Q52+S52+U52+W52+Y52+AA52 -> 340.1084
A53: Qualcom | B53: 101267 | C53: PK Qualcomm RIDE 5 50-74192-1 PCIe Cover | D53: 23 | E53: 121.66689 | F53: 37 | G53: 85.992084 | H53: 1 | I53: 5.2899269 | J53: 40 | K53: 85.144427 | AB53: =D53+F53+H53+J53+L53+N53+P53+R53+T53+V53+X53+Z53 -> 101 | AC53: =E53+G53+I53+K53+M53+O53+Q53+S53+U53+W53+Y53+AA53 -> 298.09333
A54: Qualcom | B54: 101270 | C54: PK Qualcomm RIDE 5 50-74196-1 REAR COVER, PAINTED, BASE UNIT, RIDE 5 | D54: 0 | E54: 0 | F54: 0 | G54: 0 | H54: 0 | I54: 0 | J54: 31 | K54: 292.27564 | AB54: =D54+F54+H54+J54+L54+N54+P54+R54+T54+V54+X54+Z54 -> 31 | AC54: =E54+G54+I54+K54+M54+O54+Q54+S54+U54+W54+Y54+AA54 -> 292.27564
... A58: Qualcom | B58: 101264 | C58: PK Qualcomm RIDE 5 50-74188-1 LOWER FRAME, RIDE 5 | D58: 1 | E58: 0.19304865 | F58: 9 | G58: 28.198353 | H58: 118 | I58: 182.44873 | J58: 0 | K58: 0 | AB58: =D58+F58+H58+J58+L58+N58+P58+R58+T58+V58+X58+Z58 -> 128 | AC58: =E58+G58+I58+K58+M58+O58+Q58+S58+U58+W58+Y58+AA58 -> 210.84013
A59: Qualcom | B59: 101336 | C59: PK A Sensor bar 135-8837-003 ISW Antenna Enclosure, Front Sensors | H59: 46 | I59: 203.94351 | J59: 0 | K59: 0 | AB59: =D59+F59+H59+J59+L59+N59+P59+R59+T59+V59+X59+Z59 -> 46 | AC59: =E59+G59+I59+K59+M59+O59+Q59+S59+U59+W59+Y59+AA59 -> 203.94351
A60: Qualcom | B60: 101275 | C60: PK Qualcomm AIR GEN 5 CA90-79362-1 | D60: 0 | E60: 0 | F60: 0 | G60: 0 | H60: 0 | I60: 0 | J60: 94 | K60: 195.66855 | AB60: =D60+F60+H60+J60+L60+N60+P60+R60+T60+V60+X60+Z60 -> 94 | AC60: =E60+G60+I60+K60+M60+O60+Q60+S60+U60+W60+Y60+AA60 -> 195.66855
A61: Qualcom | B61: 101282 | C61: PK Qualcomm MTP MOLOKAI 29708-70 ASSY 5G-MIDFRAME, HEAT PIPE | D61: 0 | E61: 0 | F61: 10 | G61: 64.729638 | H61: 0 | I61: 0 | J61: 15 | K61: 97.407118 | AB61: =D61+F61+H61+J61+L61+N61+P61+R61+T61+V61+X61+Z61 -> 25 | AC61: =E61+G61+I61+K61+M61+O61+Q61+S61+U61+W61+Y61+AA61 -> 162.13676
A62: Qualcom | B62: 101348 | C62: PK Qualcomm MAILI 55-97051-1 ALTERED FRAME, CAMERA CARD COVER ASSY_PROCESS | J62: 50 | K62: 107.65844 | AB62: =D62+F62+H62+J62+L62+N62+P62+R62+T62+V62+X62+Z62 -> 50 | AC62: =E62+G62+I62+K62+M62+O62+Q62+S62+U62+W62+Y62+AA62 -> 107.65844
A63: Qualcom | B63: 101059 | C63: PK Qualcomm MTP Kuno 50-PR952-3, Ant Carrier, Antenna 8 And 9 | D63: 0 | E63: 0 | F63: 0 | G63: 0 | H63: 148 | I63: 107.00637 | J63: 0 | K63: 0 | AB63: =D63+F63+H63+J63+L63+N63+P63+R63+T63+V63+X63+Z63 -> 148 | AC63: =E63+G63+I63+K63+M63+O63+Q63+S63+U63+W63+Y63+AA63 -> 107.00637
A64: Qualcom | B64: 101330 | C64: PK Qualcomm HAWI 50-84675-2 Antenna Carrier | F64: 7 | G64: 11.692582 | H64: 47 | I64: 59.570154 | J64: 9 | K64: 18.691479 | AB64: =D64+F64+H64+J64+L64+N64+P64+R64+T64+V64+X64+Z64 -> 63 | AC64: =E64+G64+I64+K64+M64+O64+Q64+S64+U64+W64+Y64+AA64 -> 89.954216
A65: Qualcom | B65: 101051 | C65: PK Qualcomm MTP Pinnacles 55-29819-1 Front Housing | J65: 30 | K65: 85.922555 | AB65: =D65+F65+H65+J65+L65+N65+P65+R65+T65+V65+X65+Z65 -> 30 | AC65: =E65+G65+I65+K65+M65+O65+Q65+S65+U65+W65+Y65+AA65 -> 85.922555
A66: Qualcom | B66: 101049 | C66: PK Qualcomm IDP Cedros 55-PR954-70 Assy, Rear Housing | D66: 0 | E66: 0 | F66: 41 | G66: 4.5522635 | H66: 0 | I66: 0 | J66: 43 | K66: 79.150839 | AB66: =D66+F66+H66+J66+L66+N66+P66+R66+T66+V66+X66+Z66 -> 84 | AC66: =E66+G66+I66+K66+M66+O66+Q66+S66+U66+W66+Y66+AA66 -> 83.703102
A67: Qualcom | B67: 101141 | C67: PK Qualcomm MTP Camano 55-PR919-20 Display Carrier Frame Assy | D67: 15 | E67: 41.266263 | F67: 0 | G67: 0 | H67: 0 | I67: 0 | J67: 0 | K67: 0 | AB67: =D67+F67+H67+J67+L67+N67+P67+R67+T67+V67+X67+Z67 -> 15 | AC67: =E67+G67+I67+K67+M67+O67+Q67+S67+U67+W67+Y67+AA67 -> 41.266263
A68: LG | B68: 120165 | C68: PK PSA BMS Bottom Cover 3CAC00182A | D68: 0 | E68: 0 | F68: 0 | G68: 0 | H68: 18 | I68: 34.804384 | J68: 0 | K68: 0 | AB68: =D68+F68+H68+J68+L68+N68+P68+R68+T68+V68+X68+Z68 -> 18 | AC68: =E68+G68+I68+K68+M68+O68+Q68+S68+U68+W68+Y68+AA68 -> 34.804384
A69: Qualcom | B69: 101134 | C69: PK Qualcomm MTP CAMANO 55-PR954-90 Assy, Sub Assy Rear Housing | D69: 0 | E69: 0 | F69: 19 | G69: 10.425058 | H69: 0 | I69: 0 | J69: 19 | K69: 18.598761 | AB69: =D69+F69+H69+J69+L69+N69+P69+R69+T69+V69+X69+Z69 -> 38 | AC69: =E69+G69+I69+K69+M69+O69+Q69+S69+U69+W69+Y69+AA69 -> 29.023819
A70: LG | B70: 120158 | C70: PK LGIT Gen3 AL6 | D70: 0 | E70: 0 | F70: 0 | G70: 0 | H70: 11 | I70: 18.237812 | J70: 0 | K70: 0 | AB70: =D70+F70+H70+J70+L70+N70+P70+R70+T70+V70+X70+Z70 -> 11 | AC70: =E70+G70+I70+K70+M70+O70+Q70+S70+U70+W70+Y70+AA70 -> 18.237812
A71: LG | B71: 120301 | C71: PK LGIT BYD 3CAC00129A Housing | D71: 10 | E71: 16.79968 | F71: 0 | G71: 0 | H71: 0 | I71: 0 | J71: 0 | K71: 0 | AB71: =D71+F71+H71+J71+L71+N71+P71+R71+T71+V71+X71+Z71 -> 10 | AC71: =E71+G71+I71+K71+M71+O71+Q71+S71+U71+W71+Y71+AA71 -> 16.79968
A72: Qualcom | B72: 101345 | C72: PK Qualcomm IDP CEDROS_55-PR954-80_ASSY, SUB-ASSY, REAR HOUSING | J72: 6 | K72: 10.527792 | AB72: =D72+F72+H72+J72+L72+N72+P72+R72+T72+V72+X72+Z72 -> 6 | AC72: =E72+G72+I72+K72+M72+O72+Q72+S72+U72+W72+Y72+AA72 -> 10.527792
A73: Qualcom | B73: 101142 | C73: PK Qualcomm MTP Camano 55-PR919-30 Display Carrier Frame Assy | D73: 0 | E73: 0 | F73: 0 | G73: 0 | H73: 0 | I73: 0 | J73: 4 | K73: 9.4446696 | AB73: =D73+F73+H73+J73+L73+N73+P73+R73+T73+V73+X73+Z73 -> 4 | AC73: =E73+G73+I73+K73+M73+O73+Q73+S73+U73+W73+Y73+AA73 -> 9.4446696
A74: Qualcom | B74: 101314 | C74: PK Qualcomm HAWI 55-68130-10 Front Housing ASSY_PROCESS | D74: 0 | E74: 0 | F74: 0 | G74: 0 | H74: 5 | I74: 8.0021002 | J74: 0 | K74: 0 | AB74: =D74+F74+H74+J74+L74+N74+P74+R74+T74+V74+X74+Z74 -> 5 | AC74: =E74+G74+I74+K74+M74+O74+Q74+S74+U74+W74+Y74+AA74 -> 8.0021002
A75: LG | B75: 120400 | C75: PK LGIT BYD 3CAC00069A/3MAM00121A Cover | D75: 0 | E75: 0 | F75: 1 | G75: 1.4462853 | H75: 1 | I75: 1.4462853 | J75: 0 | K75: 0 | AB75: =D75+F75+H75+J75+L75+N75+P75+R75+T75+V75+X75+Z75 -> 2 | AC75: =E75+G75+I75+K75+M75+O75+Q75+S75+U75+W75+Y75+AA75 -> 2.8925707
A76: Qualcom | B76: 100961 | C76: PK Qualcomm IDP Fillmore 50-PR727-3 Battery Door | D76: 0 | E76: 0 | F76: 0 | G76: 0 | H76: 0 | I76: 0 | J76: 5 | K76: 2.3273785 | AB76: =D76+F76+H76+J76+L76+N76+P76+R76+T76+V76+X76+Z76 -> 5 | AC76: =E76+G76+I76+K76+M76+O76+Q76+S76+U76+W76+Y76+AA76 -> 2.3273785
A77: Qualcom | B77: 100855 | C77: PK Qualcomm MTP Lahaina 50-PP493-1 Speaker Box | D77: 0 | E77: 0 | F77: 0 | G77: 0 | H77: 2 | I77: 0.81975024 | J77: 0 | K77: 0 | AB77: =D77+F77+H77+J77+L77+N77+P77+R77+T77+V77+X77+Z77 -> 2 | AC77: =E77+G77+I77+K77+M77+O77+Q77+S77+U77+W77+Y77+AA77 -> 0.81975024
A78: Qualcom | B78: 101315 | C78: Qualcomm IDP KUNO, 50-PR952-7, ANT CARRIER, ANT8+ANT9, UWB_GNSS, WDP, SW6100, MEP | D78: 0 | E78: 0 | F78: 0 | G78: 0 | H78: 1 | I78: 0.09535244 | J78: 0 | K78: 0 | AB78: =D78+F78+H78+J78+L78+N78+P78+R78+T78+V78+X78+Z78 -> 1 | AC78: =E78+G78+I78+K78+M78+O78+Q78+S78+U78+W78+Y78+AA78 -> 0.09535244
A79: Qualcom | B79: 101315 | C79: Qualcomm IDP KUNO, 50-PR952-7, ANT CARRIER, ANT8+ANT9, UWB_GNSS, WDP, SW6100, MEP | H79: 1 | I79: 0.09535244 | J79: 0 | K79: 0 | AB79: =D79+F79+H79+J79+L79+N79+P79+R79+T79+V79+X79+Z79 -> 1 | AC79: =E79+G79+I79+K79+M79+O79+Q79+S79+U79+W79+Y79+AA79 -> 0.09535244
A80: Qualcom | B80: 101333 | C80: PK Qualcomm Hana 50-PB615-2 Battery Cover | F80: 1 | G80: 0.019463475 | H80: 0 | I80: 0 | J80: 0 | K80: 0 | AB80: =D80+F80+H80+J80+L80+N80+P80+R80+T80+V80+X80+Z80 -> 1 | AC80: =E80+G80+I80+K80+M80+O80+Q80+S80+U80+W80+Y80+AA80 -> 0.019463475
D81: 0 | E81: 0 | F81: 0 | G81: 0 | H81: 0 | I81: 0 | T81: 0 | U81: 0 | V81: 0 | W81: 0 | X81: 0 | Y81: 0 | Z81: 0 | AA81: 0 | AB81: =D81+F81+H81+J81+L81+N81+P81+R81+T81+V81+X81+Z81 -> 0 | AC81: =E81+G81+I81+K81+M81+O81+Q81+S81+U81+W81+Y81+AA81 -> 0
D82: =SUM(D4:D80) -> 261220 | E82: =SUM(E4:E80) -> 224739.24 | F82: =SUM(F4:F81) -> 69839 | G82: =SUM(G4:G81) -> 56960.455 | H82: =SUM(H4:H81) -> 333419 | I82: =SUM(I4:I81) -> 329086.71 | J82: =SUM(J4:J81) -> 265672 | K82: =SUM(K4:K81) -> 267368.91 | L82: =SUM(L4:L80) -> 0 | M82: =SUM(M4:M80) -> 0 | N82: =SUM(N4:N80) -> 0 | O82: =SUM(O4:O80) -> 0 | P82: =SUM(P4:P80) -> 0 | Q82: =SUM(Q4:Q80) -> 0 | R82: =SUM(R4:R80) -> 0 | S82: =SUM(S4:S80) -> 0 | T82: =SUM(T4:T81) -> 0 | U82: =SUM(U4:U81) -> 0 | V82: =SUM(V4:V81) -> 0 | W82: =SUM(W4:W81) -> 0 | X82: =SUM(X4:X81) -> 0 | Y82: =SUM(Y4:Y81) -> 0 | Z82: =SUM(Z4:Z81) -> 0 | AA82: =SUM(AA4:AA81) -> 0 | ... AC82: =SUM(AC4:AC81) -> 878155.31

Sheet 비용 증가 사유
B2: 1. 금형 실적 반영 지연 (약 +1.5만불)
B3: * A276 금형 코아 실적 5벌 - 5월 8일 입력
B4: * 4월 마감 시 인건비 및 경비 추가 반영 (약 + 1.5만불)
B5: * 5월 매출 반영필요
B6: * 기타 금형도 확인 진행중
B7: 미반영 매출 반영 | C7: 수량 | D7: 매출단가 | E7: 매출금액 | F7: 원가 | G7: 이익
B8: A276 Mold | C8: 5 | D8: =E8/C8 -> 10982.8 | E8: 54914 | F8: =6500*5 -> 32500 | G8: =E8-F8 -> 22414
B9: TRIMMING JIG(DEGATING) | C9: 5 | D9: =E9/C9 -> 2683.4 | E9: 13417 | F9: 10341 | G9: =E9-F9 -> 3076
B10: TRIMMING JIG_01 | C10: 5 | D10: =E10/C10 -> 2187.6 | E10: 10938 | F10: 9497 | G10: =E10-F10 -> 1441
B11: CNC JIG | C11: 5 | D11: =E11/C11 -> 341.4 | E11: 1707 | F11: 2400 | G11: =E11-F11 -> -693
B12: Total | E12: =SUM(E8:E11) -> 80976 | F12: =SUM(F8:F11) -> 54738 | G12: =E12-F12 -> 26238
B14: 2. 인건비 증가 (약 +5만불)
B15: * 생산직 1인당 평균 잔업시간: 76시간 → 106시간 (+39%)
B16: * 생산물량 회복 및 납기 대응 과정에서 OT 증가
B17: → 5월부터 라인별 OT 한도 설정 및 일일 모니터링 시행 예정
B18: 항목 | C18: 단위 | D18: Jan.26 | E18: Feb.26 | F18: Mar.26 | G18: Apr.26 | H18: 1Q평균 | I18: Apr vs 1Q
B19: 인건비 | C19: USD | D19: 433923 | E19: 488222 | F19: 547646 | G19: 598756 | H19: =AVERAGE(D19:F19) -> 489930.33 | I19: =IFERROR((G19-H19)/H19,0) -> 0.22212478
B20: 총 OT시간 | C20: 시간 | D20: 84286 | E20: 59208 | F20: 62988 | G20: 81166 | H20: =AVERAGE(D20:F20) -> 68827.333 | I20: =IFERROR((G20-H20)/H20,0) -> 0.17926986
B21: 총 인원수 | C21: 명 | D21: 867 | E21: 858 | F21: 827 | G21: 801 | H21: =AVERAGE(D21:F21) -> 850.66667 | I21: =IFERROR((G21-H21)/H21,0) -> -0.05838558
B22: 인당 평균 OT시간 | C22: 시간/명 | D22: =D20/D21 -> 97.215686 | E22: =E20/E21 -> 69.006993 | F22: =F20/F21 -> 76.16445 | G22: =G20/G21 -> 101.33084 | H22: =AVERAGE(D22:F22) -> 80.79571 | I22: =IFERROR((G22-H22)/H22,0) -> 0.2541611
B24: 3. 물류비 증가 (약 +1.2만불)
B25: * 항공 운송 신규 발생 (3월 대비 증가)
B26: * LG, MANDO향 긴급 샘플 대응 목적
B27: → 향후 사전 승인 및 해상운송 전환 검토 프로세스 운영
B29: 4. 전기비용 증가 (마감 구조 및 계절 요인 약 + 9.8만불)
B30: * 전기료 반영기간: 전월 18일 ~ 당월 17일
B31: * 3월: 설 휴무 포함 24일 가동
B32: * 4월: 27일 정상 가동 (기저효과 발생)
B33: * 우기 진입에 따른 냉방(칠러) 가동 증가
B34: → 전력 사용량 상승

Sheet 전기사용량
A3: NAME | B3: AREA USING | C3: 46071 | D3: 46072 | E3: 46073 | F3: 46074 | G3: 46075 | H3: 46076 | I3: 46077 | J3: 46078 | K3: 46079 | L3: 46080 | M3: 46081 | N3: 46082 | O3: 46083 | P3: 46084 | Q3: 46085 | R3: 46086 | S3: 46087 | T3: 46088 | U3: 46089 | V3: 46090 | W3: 46091 | X3: 46092 | Y3: 46093 | Z3: 46094 | AA3: 46095 | AB3: 46096 | AC3: 46097 | AD3: 46098 | AH3: Total kWh | AI3: AVG | AJ3: SUNDAY | AK3: NOMAL DAY | AL3: TOTAL DAY
A4: Trans 3750 KVA | B4: CNC 1,CNC2,CNC3,CNC4. Chromate, Barel,Casting(1 machine) Trimming, Chiller-AHU trimming, Exhaust fan casting, Pump for casting Chiller factory B, Chiller casting, AHU, Exhaust FAN CNC 3, Air compressor(5 machine) | C4: 4512 | D4: 4486 | E4: 4534 | F4: 7605 | G4: 16522 | H4: 37290 | I4: 46188 | J4: 45942 | K4: 46061 | L4: 45433 | M4: 46027 | N4: 47992 | O4: 48824 | P4: 45473 | Q4: 44058 | R4: 46462 | S4: 32888 | T4: 19016 | U4: 21193 | V4: 33448 | W4: 37400 | X4: 29027 | Y4: 33509 | Z4: 31253 | AA4: 33589 | AB4: 30372 | AC4: 37712 | AD4: 36163 | AH4: =SUM(C4:AG4) -> 912979 | AI4: =AVERAGE(C4:AD4) -> 32606.393 | AJ4: 4 | AK4: 24 | AL4: 28
A5: Trans 2500 KVA | B5: Casting(16 machine),Aluminum transport line,Office, Pump, Bavia area, Canteen. | C5: 5808.64 | D5: 5772.16 | E5: 5866.24 | F5: 6079.36 | G5: 13792 | H5: 26583.04 | I5: 33264.64 | J5: 35201.92 | K5: 35095.68 | L5: 36382.72 | M5: 34610.56 | N5: 34412.16 | O5: 34839.68 | P5: 34426.88 | Q5: 34826.88 | R5: 35559.04 | S5: 34291.2 | T5: 20854.4 | U5: 24300.8 | V5: 32414.72 | W5: 32712.96 | X5: 33655.68 | Y5: 34237.44 | Z5: 33031.04 | AA5: 33609.6 | AB5: 32992 | AC5: 33568 | AD5: 34349.44 | AH5: =SUM(C5:AG5) -> 792538.88 | AI5: =AVERAGE(C5:AD5) -> 28304.96
A6: Trans 1250A KVA | B6: Chiller CNC3(3 machine),Air compressor(7 machine),chiller casting(1 machine), CNC2(1V4,1V2) | C6: 2921.2 | D6: 3498.4 | E6: 3212.8 | F6: 3596 | G6: 5396 | H6: 15472.4 | I6: 17209.2 | J6: 17658.8 | K6: 17531.6 | L6: 17588.4 | M6: 18399.6 | N6: 19070.4 | O6: 19096 | P6: 18905.6 | Q6: 18106.8 | R6: 18467.6 | S6: 17179.6 | T6: 9530.4 | U6: 10716 | V6: 17004.8 | W6: 18047.2 | X6: 18153.6 | Y6: 18374.4 | Z6: 18839.6 | AA6: 18620.8 | AB6: 18939.2 | AC6: 18732.8 | AD6: 18493.6 | AH6: =SUM(C6:AG6) -> 418762.8 | AI6: =AVERAGE(C6:AD6) -> 14955.814
A7: Trans 1250B KVA | B7: Casting machine(9 machine) | C7: 4141.8 | D7: 4145.4 | E7: 4139.1 | F7: 4149 | G7: 5106.3 | H7: 8164.8 | I7: 10138.8 | J7: 10941 | K7: 11703.9 | L7: 11859.6 | M7: 11304.6 | N7: 11188.2 | O7: 12354.6 | P7: 14207.1 | Q7: 14114.1 | R7: 14684.1 | S7: 14218.2 | T7: 8079 | U7: 9233.4 | V7: 12861.9 | W7: 14221.8 | X7: 14445.6 | Y7: 14951.7 | Z7: 14931 | AA7: 15585 | AB7: 14420.4 | AC7: 15000 | AD7: 15710.4 | AH7: =SUM(C7:AG7) -> 316000.8 | AI7: =AVERAGE(C7:AD7) -> 11285.743
A8: Trans 1250C KVA | B8: Recycling line, blaster,jnjection, air compress(4 machine) | C8: 28.8 | D8: 29.1 | E8: 28.8 | F8: 2356.2 | G8: 4866.9 | H8: 10045.5 | I8: 11973.6 | J8: 12064.5 | K8: 12864.9 | L8: 13884.9 | M8: 12111.6 | N8: 13140 | O8: 12420.6 | P8: 12795.9 | Q8: 15486.3 | R8: 15313.8 | S8: 15728.4 | T8: 6771 | U8: 11886.9 | V8: 14265.3 | W8: 13344 | X8: 12883.5 | Y8: 13993.5 | Z8: 13925.1 | AA8: 14754.3 | AB8: 14872.2 | AC8: 13929.9 | AD8: 14422.2 | AH8: =SUM(C8:AG8) -> 310187.7 | AI8: =AVERAGE(C8:AD8) -> 11078.132
B9: TOTAL | C9: =+C8+C7+C6+C5+C4 -> 17412.44 | D9: =+D8+D7+D6+D5+D4 -> 17931.06 | E9: =+E8+E7+E6+E5+E4 -> 17780.94 | F9: =+F8+F7+F6+F5+F4 -> 23785.56 | G9: =+G8+G7+G6+G5+G4 -> 45683.2 | H9: =+H8+H7+H6+H5+H4 -> 97555.74 | I9: =+I8+I7+I6+I5+I4 -> 118774.24 | J9: =+J8+J7+J6+J5+J4 -> 121808.22 | ... AD9: =+AD8+AD7+AD6+AD5+AD4 -> 119138.64 | AH9: =SUM(C9:AG9) -> 2750469.2 | AI9: =AVERAGE(C9:AD9) -> 98231.042
A11: NAME | B11: AREA USING | C11: 46099 | D11: 46100 | E11: 46101 | F11: 46102 | G11: 46103 | H11: 46104 | I11: 46105 | J11: 46106 | K11: 46107 | L11: 46108 | M11: 46109 | N11: 46110 | O11: 46111 | P11: 46112 | Q11: 46113 | R11: 46114 | S11: 46115 | T11: 46116 | U11: 46117 | V11: 46118 | W11: 46119 | X11: 46120 | Y11: 46121 | Z11: 46122 | AA11: 46123 | AB11: 46124 | AC11: 46125 | AD11: 46126 | AE11: 46127 | AF11: 46128 | AG11: 46129 | AH11: Total kWh | AI11: AVG | AJ11: SUNDAY | AK11: NOMAL DAY | AL11: TOTAL DAY
A12: Trans 3750 KVA | B12: CNC 1,CNC2,CNC3,CNC4. Chromate, Barel,Casting(1 machine) Trimming, Chiller-AHU trimming, Exhaust fan casting, Pump for casting Chiller factory B, Chiller casting, AHU, Exhaust FAN CNC 3, Air compressor(5 machine) | C12: 41655 | D12: 34926 | E12: 42480 | F12: 38570 | G12: 30401 | H12: 34090 | I12: 48600 | J12: 35018 | K12: 49466 | L12: 49664 | M12: 49780 | N12: 38108 | O12: 44964 | P12: 45179 | Q12: 49281 | R12: 49904 | S12: 29801 | T12: 37929 | U12: 34057 | V12: 37941 | W12: 40080 | X12: 43413 | Y12: 35070 | Z12: 35285 | AA12: 42727 | AB12: 30476 | AC12: 49036 | AD12: 53033 | AE12: 53467 | AF12: 54713 | AG12: 54096 | AH12: =SUM(C12:AG12) -> 1313210 | AI12: =AVERAGE(C12:AG12) -> 42361.613 | AJ12: 4 | AK12: 27 | AL12: =AK12+AJ12 -> 31
A13: Trans 2500 KVA | B13: Casting(16 machine),Aluminum transport line,Office, Pump, Bavia area, Canteen. | C13: 34121.6 | D13: 32850.56 | E13: 31937.28 | F13: 33212.8 | G13: 27653.12 | H13: 30947.84 | I13: 33662.72 | J13: 29197.44 | K13: 30769.92 | L13: 30085.12 | M13: 28547.2 | N13: 24794.88 | O13: 26842.88 | P13: 30515.84 | Q13: 32053.12 | R13: 33488.64 | S13: 33992.96 | T13: 34040.96 | U13: 29708.16 | V13: 30560 | W13: 34757.12 | X13: 35697.28 | Y13: 35123.2 | Z13: 34624 | AA13: 34908.16 | AB13: 28360.32 | AC13: 32449.28 | AD13: 35422.08 | AE13: 36280.96 | AF13: 35756.8 | AG13: 34373.76 | AH13: =SUM(C13:AG13) -> 996736 | AI13: =AVERAGE(C13:AG13) -> 32152.774
A14: Trans 1250A KVA | B14: Chiller CNC3(3 machine),Air compressor(7 machine),chiller casting(1 machine), CNC2(1V4,1V2) | C14: 18620.4 | D14: 18096.8 | E14: 18053.2 | F14: 18235.2 | G14: 18172.4 | H14: 18115.6 | I14: 19440.4 | J14: 17694.4 | K14: 19514.4 | L14: 19337.2 | M14: 19330.4 | N14: 18349.6 | O14: 18929.2 | P14: 19828 | Q14: 18271.6 | R14: 18540 | S14: 19450.8 | T14: 19683.6 | U14: 19350.4 | V14: 19802 | W14: 20666 | X14: 20322 | Y14: 20207.6 | Z14: 20378 | AA14: 20635.2 | AB14: 20843.6 | AC14: 20685.2 | AD14: 20737.2 | AE14: 20618.4 | AF14: 20518.8 | AG14: 19399.2 | AH14: =SUM(C14:AG14) -> 601826.8 | AI14: =AVERAGE(C14:AG14) -> 19413.768
A15: Trans 1250B KVA | B15: Casting machine(9 machine) | C15: 14433.3 | D15: 14984.1 | E15: 16085.1 | F15: 14940 | G15: 13136.4 | H15: 13796.1 | I15: 13563 | J15: 11518.8 | K15: 12561 | L15: 13102.8 | M15: 13184.4 | N15: 11889.3 | O15: 12499.2 | P15: 13106.7 | Q15: 13194.3 | R15: 14191.2 | S15: 15311.1 | T15: 14716.8 | U15: 13587.6 | V15: 12745.5 | W15: 14009.7 | X15: 14559.6 | Y15: 14996.4 | Z15: 14428.5 | AA15: 15440.7 | AB15: 13972.5 | AC15: 14627.7 | AD15: 14846.7 | AE15: 14450.7 | AF15: 15163.8 | AG15: 15183.6 | AH15: =SUM(C15:AG15) -> 434226.6 | AI15: =AVERAGE(C15:AG15) -> 14007.31
A16: Trans 1250C KVA | B16: Recycling line, blaster,jnjection, air compress(4 machine) | C16: 14523 | D16: 12207.3 | E16: 2553 | F16: 15100 | G16: 15100 | H16: 11332 | I16: 15100 | J16: 15100 | K16: 15100 | L16: 15100 | M16: 15100 | N16: 11600 | O16: 15100 | P16: 15100 | Q16: 15100 | R16: 15100 | S16: 15100 | T16: 9540 | U16: 11241.9 | V16: 14922.3 | W16: 15411.6 | X16: 16134.3 | Y16: 15027.9 | Z16: 15678.9 | AA16: 15898.5 | AB16: 14739.6 | AC16: 14397.9 | AD16: 16099.8 | AE16: 15922.8 | AF16: 15828.9 | AG16: 15519.3 | AH16: =SUM(C16:AG16) -> 439779 | AI16: =AVERAGE(C16:AG16) -> 14186.419
B17: TOTAL | C17: =+C16+C15+C14+C13+C12 -> 123353.3 | D17: =+D16+D15+D14+D13+D12 -> 113064.76 | E17: =+E16+E15+E14+E13+E12 -> 111108.58 | F17: =+F16+F15+F14+F13+F12 -> 120058 | G17: =+G16+G15+G14+G13+G12 -> 104462.92 | H17: =+H16+H15+H14+H13+H12 -> 108281.54 | I17: =+I16+I15+I14+I13+I12 -> 130366.12 | J17: =+J16+J15+J14+J13+J12 -> 108528.64 | ... AG17: =+AG16+AG15+AG14+AG13+AG12 -> 138571.86 | AH17: =SUM(C17:AG17) -> 3785778.4 | AI17: =AVERAGE(C17:AG17) -> 122121.88
