Workbook

Sheet 1.Dashboard
B2: 베트남 부가세(VAT) 환급 분기 점검 워크북 — 2026년 2분기
B4: 분기말 기준일(T) : 2026-06-30 | 작성일 : 2026-04-24 | 대상 : 베트남 법인
B6: 사전 점검(T-15) | C6: 2026-06-15 | D6: 신고 마감(T+20) | E6: 2026-07-20 | F6: 환급 신청(01/ĐNHT) | G6: 2026-07-20
B9: 분기 진척도 요약
B10: 전체 항목 수 | C10: =COUNTA('2.Schedule'!H6:H12) -> 7 | D10: =COUNTIF('2.Schedule'!H6:H12,"완료") -> 0 | E10: =COUNTIF('2.Schedule'!H6:H12,"진행")+COUNTIF('2.Schedule'!H6:H12,"미진행") -> 7 | F10: =COUNTIF('2.Schedule'!H6:H12,"리스크") -> 0 | G10: =IFERROR(D10/C10,0) -> 0
B13: VAT 환급 요건 판정
B14: 누적 매입세액(VND) | C14: 0
B15: 누적 매출세액(VND) | C15: 0
B16: 초과 매입세액 (=환급 가능 잔액) | C16: =C14-C15 -> 0
B17: 환급 요건(3억 VND 이상) 충족여부 | C17: =IF(C16>=300000000,"충족 (환급 신청 가능)","미충족 (이월)") -> 미충족 (이월)
B19: 사용 안내
B20: 1) 파란색(0000FF)으로 표시된 셀은 입력값입니다. 매월 갱신하십시오.
B21: 2) 각 시트는 SKILL.md의 '사전 준비 체크리스트(①~④)' 와 1:1로 대응됩니다.
B22: 3) Schedule 탭의 상태(H열)를 갱신하면 Dashboard 진척도가 자동 반영됩니다.
B23: 4) 6개월 이상 미지급 채무(시트 5)는 환급 거부 사유가 되므로 공급상 확인서를 사전 징구하십시오.
B24: 5) 위험 공급사(시트 6)에 해당될 경우 환급 대상에서 제외하거나 즉시 소명자료를 준비하십시오.

Sheet 2.Schedule
B2: 분기별 환급 업무 프로세스 및 스케줄 (Q2 2026)
A5: No. | B5: 단계 | C5: 기준일자(Offset) | D5: 실제 일자 | E5: 주요 활동 | F5: 산출물 | G5: 담당 | H5: 상태 | I5: 비고
A6: 1 | B6: 사전 점검 | C6: T-15일 | D6: 2026-06-15 | E6: 공급업체 세무 상태 전수 조사 (폐업, 블랙리스트 여부) | F6: 공급사 적격성 검토표 | G6: 회계팀 | H6: 미진행
A7: 2 | B7: 자료 수집 | C7: T-5일 | D7: 2026-06-25 | E7: 당월 매입/매출 E-Invoice 및 은행 송금증 취합 완료 | F7: 인보이스 일람 | G7: 회계팀 | H7: 미진행 | I7: 2,000만 동 이상은 반드시 송금 영수증
A8: 3 | B8: 1차 대조 | C8: T+5일 | D8: 2026-07-05 | E8: 회계 시스템 데이터 vs 세금계산서 총액 일치 확인 | F8: 대조 조서 | G8: 재무팀 | H8: 미진행 | I8: HTKK 입력값과 GL 총계 비교
A9: 4 | B9: 서류 보완 | C9: T+10일 | D9: 2026-07-10 | E9: 누락 계약서, 장기 미지급금 공급상 확인서 징구 | F9: 확인서, 계약서 | G9: 구매/외주 | H9: 미진행 | I9: 6개월 이상 AP 우선
A10: 5 | B10: 신고서 작성 | C10: T+15일 | D10: 2026-07-15 | E10: HTKK 프로그램 입력 및 부가세 신고서(01/GTGT) 초안 작성 | F10: 01/GTGT 초안 | G10: 회계팀 | H10: 미진행
A11: 6 | B11: 최종 승인 | C11: T+18일 | D11: 2026-07-18 | E11: CFO/법인장 최종 검토 및 내부 승인 | F11: 결재 문서 | G11: 경영진 | H11: 미진행
A12: 7 | B12: 신고 및 환급 | C12: T+20일 | D12: 2026-07-20 | E12: 전자 신고 완료 및 환급 신청서(01/ĐNHT) 제출 | F12: 신고/접수증 | G12: 회계팀 | H12: 미진행 | I12: 마감 엄수

Sheet 3.Document_Checklist
B2: ① 환급 기초 자료 준비 — 문서 체크리스트
B4: No. | C4: 구분 | D4: 점검 항목 | E4: 근거 규정/주의사항 | F4: 담당 | G4: 상태 | H4: 비고
B5: 1 | C5: 세금계산서 | D5: 매입 E-Invoice 법인명 일치 | E5: 사업자등록증과 동일 | F5: 회계 | G5: 미확인
B6: 2 | C6: 세금계산서 | D6: 매입 E-Invoice 주소 일치 | E6: 사업자등록증과 동일 | F6: 회계 | G6: 미확인
B7: 3 | C7: 세금계산서 | D7: 매입 E-Invoice MST(세무번호) 일치 | E7: 사업자등록증과 동일 | F7: 회계 | G7: 미확인
B8: 4 | C8: 송금증빙 | D8: 2,000만 VND 이상 거래 — 법인계좌 송금영수증 | E8: Non-cash payment 의무 | F8: 재무 | G8: 미확인 | H8: 현금결제 시 매입세액 공제 불가
B9: 5 | C9: 수입서류 | D9: 수입신고필증(Customs Declaration) | E9: HS Code, 수량, 단가 일치 | F9: 수출입 | G9: 미확인
B10: 6 | C10: 수입서류 | D10: 수입 부가세 납부 영수증 | E10: 납부증빙 원본 보관 | F10: 수출입 | G10: 미확인
B11: 7 | C11: 수입서류 | D11: 운송 서류 일체 (B/L, AWB, Packing List) | E11: 원본 매칭 | F11: 수출입 | G11: 미확인
B12: 8 | C12: 계약서 | D12: 매입 계약서 서명/날인 완비 | E12: 대표자 또는 대리인 서명 | F12: 구매 | G12: 미확인
B13: 9 | C13: 검증 | D13: VAT 매입대장 vs 회계장부 일치 | E13: HTKK 입력값 대조 | F13: 회계 | G13: 미확인
B14: 10 | C14: 검증 | D14: VAT 매출대장 vs 회계장부 일치 | E14: HTKK 입력값 대조 | F14: 회계 | G14: 미확인
C16: 총 점검 항목 | D16: =COUNTA(B5:B14) -> 10
C17: 확인 완료 | D17: =COUNTIF(G5:G14,"확인완료") -> 0
C18: 불일치 (즉시 보완) | D18: =COUNTIF(G5:G14,"불일치") -> 0
C19: 확인율 | D19: =IFERROR(D17/D16,0) -> 0

Sheet 4.Supplier_Verification
B2: ③ 공급업체 적격성 조회 (세무 블랙리스트 / 폐업 여부 전수조사)
B4: 조회처: 베트남 국세청 (gdt.gov.vn) 및 사업자정보 공시 시스템
B6: No. | C6: 공급사명 | D6: MST(세무번호) | E6: 업종 | F6: 당기 매입금액(VND) | G6: 해당 매입세액(VND) | H6: 폐업여부 | I6: 블랙리스트 여부 | J6: FCT 적용 | K6: 조회일 | L6: 상태/조치
B7: 1 | G7: =IF(F7="",0,F7*0.1) -> 0 | L7: =IF(OR(H7="Y",I7="Y"),"환급 제외/소명필요",IF(J7="Y","FCT 납부확인 필요","정상")) -> 정상
B8: 2 | G8: =IF(F8="",0,F8*0.1) -> 0 | L8: =IF(OR(H8="Y",I8="Y"),"환급 제외/소명필요",IF(J8="Y","FCT 납부확인 필요","정상")) -> 정상
B9: 3 | G9: =IF(F9="",0,F9*0.1) -> 0 | L9: =IF(OR(H9="Y",I9="Y"),"환급 제외/소명필요",IF(J9="Y","FCT 납부확인 필요","정상")) -> 정상
B10: 4 | G10: =IF(F10="",0,F10*0.1) -> 0 | L10: =IF(OR(H10="Y",I10="Y"),"환급 제외/소명필요",IF(J10="Y","FCT 납부확인 필요","정상")) -> 정상
B11: 5 | G11: =IF(F11="",0,F11*0.1) -> 0 | L11: =IF(OR(H11="Y",I11="Y"),"환급 제외/소명필요",IF(J11="Y","FCT 납부확인 필요","정상")) -> 정상
B12: 6 | G12: =IF(F12="",0,F12*0.1) -> 0 | L12: =IF(OR(H12="Y",I12="Y"),"환급 제외/소명필요",IF(J12="Y","FCT 납부확인 필요","정상")) -> 정상
B13: 7 | G13: =IF(F13="",0,F13*0.1) -> 0 | L13: =IF(OR(H13="Y",I13="Y"),"환급 제외/소명필요",IF(J13="Y","FCT 납부확인 필요","정상")) -> 정상
B14: 8 | G14: =IF(F14="",0,F14*0.1) -> 0 | L14: =IF(OR(H14="Y",I14="Y"),"환급 제외/소명필요",IF(J14="Y","FCT 납부확인 필요","정상")) -> 정상
B15: 9 | G15: =IF(F15="",0,F15*0.1) -> 0 | L15: =IF(OR(H15="Y",I15="Y"),"환급 제외/소명필요",IF(J15="Y","FCT 납부확인 필요","정상")) -> 정상
B16: 10 | G16: =IF(F16="",0,F16*0.1) -> 0 | L16: =IF(OR(H16="Y",I16="Y"),"환급 제외/소명필요",IF(J16="Y","FCT 납부확인 필요","정상")) -> 정상
B17: 11 | G17: =IF(F17="",0,F17*0.1) -> 0 | L17: =IF(OR(H17="Y",I17="Y"),"환급 제외/소명필요",IF(J17="Y","FCT 납부확인 필요","정상")) -> 정상
B18: 12 | G18: =IF(F18="",0,F18*0.1) -> 0 | L18: =IF(OR(H18="Y",I18="Y"),"환급 제외/소명필요",IF(J18="Y","FCT 납부확인 필요","정상")) -> 정상
... B21: 15 | G21: =IF(F21="",0,F21*0.1) -> 0 | L21: =IF(OR(H21="Y",I21="Y"),"환급 제외/소명필요",IF(J21="Y","FCT 납부확인 필요","정상")) -> 정상
B22: 합계 | F22: =SUM(F7:F21) -> 0 | G22: =SUM(G7:G21) -> 0

Sheet 5.AP_Aging
B2: ④ 장기 미지급금 관리 — 매입채무 연령 분석 (Aging Report)
B4: 기준일 | C4: 2026-06-30
B6: No. | C6: 공급사 | D6: 인보이스 번호 | E6: 발행일 | F6: 결제기한 | G6: 미지급액(VND) | H6: 경과일수 | I6: 연령구분 | J6: 공급상 확인서 | K6: 송금예정일
B7: 1 | H7: =IF(F7="","",$C$4-F7) | I7: =IF(H7="","",IF(H7<0,"기한전",IF(H7<=90,"0~3개월",IF(H7<=180,"3~6개월","6개월 초과"))))
B8: 2 | H8: =IF(F8="","",$C$4-F8) | I8: =IF(H8="","",IF(H8<0,"기한전",IF(H8<=90,"0~3개월",IF(H8<=180,"3~6개월","6개월 초과"))))
B9: 3 | H9: =IF(F9="","",$C$4-F9) | I9: =IF(H9="","",IF(H9<0,"기한전",IF(H9<=90,"0~3개월",IF(H9<=180,"3~6개월","6개월 초과"))))
B10: 4 | H10: =IF(F10="","",$C$4-F10) | I10: =IF(H10="","",IF(H10<0,"기한전",IF(H10<=90,"0~3개월",IF(H10<=180,"3~6개월","6개월 초과"))))
B11: 5 | H11: =IF(F11="","",$C$4-F11) | I11: =IF(H11="","",IF(H11<0,"기한전",IF(H11<=90,"0~3개월",IF(H11<=180,"3~6개월","6개월 초과"))))
B12: 6 | H12: =IF(F12="","",$C$4-F12) | I12: =IF(H12="","",IF(H12<0,"기한전",IF(H12<=90,"0~3개월",IF(H12<=180,"3~6개월","6개월 초과"))))
B13: 7 | H13: =IF(F13="","",$C$4-F13) | I13: =IF(H13="","",IF(H13<0,"기한전",IF(H13<=90,"0~3개월",IF(H13<=180,"3~6개월","6개월 초과"))))
B14: 8 | H14: =IF(F14="","",$C$4-F14) | I14: =IF(H14="","",IF(H14<0,"기한전",IF(H14<=90,"0~3개월",IF(H14<=180,"3~6개월","6개월 초과"))))
B15: 9 | H15: =IF(F15="","",$C$4-F15) | I15: =IF(H15="","",IF(H15<0,"기한전",IF(H15<=90,"0~3개월",IF(H15<=180,"3~6개월","6개월 초과"))))
B16: 10 | H16: =IF(F16="","",$C$4-F16) | I16: =IF(H16="","",IF(H16<0,"기한전",IF(H16<=90,"0~3개월",IF(H16<=180,"3~6개월","6개월 초과"))))
B17: 11 | H17: =IF(F17="","",$C$4-F17) | I17: =IF(H17="","",IF(H17<0,"기한전",IF(H17<=90,"0~3개월",IF(H17<=180,"3~6개월","6개월 초과"))))
B18: 12 | H18: =IF(F18="","",$C$4-F18) | I18: =IF(H18="","",IF(H18<0,"기한전",IF(H18<=90,"0~3개월",IF(H18<=180,"3~6개월","6개월 초과"))))
... B21: 15 | H21: =IF(F21="","",$C$4-F21) | I21: =IF(H21="","",IF(H21<0,"기한전",IF(H21<=90,"0~3개월",IF(H21<=180,"3~6개월","6개월 초과"))))
B22: 합계 | G22: =SUM(G7:G21) -> 0
B24: 연령 구간별 요약
B25: 기한전 | C25: =SUMIF(I7:I21,"기한전",G7:G21) -> 0
B26: 0~3개월 | C26: =SUMIF(I7:I21,"0~3개월",G7:G21) -> 0
B27: 3~6개월 | C27: =SUMIF(I7:I21,"3~6개월",G7:G21) -> 0
B28: 6개월 초과 ★ | C28: =SUMIF(I7:I21,"6개월 초과",G7:G21) -> 0
B29: 확인서 미징구(6개월 초과) | C29: =SUMIFS(G7:G21,I7:I21,"6개월 초과",J7:J21,"미징구") -> 0

Sheet 6.Risk_Filtering
B2: ③ 세무 리스크 필터링 — 위험 기업 / FCT 미납 점검
B4: 본 시트는 Supplier_Verification 시트와 연동되어 환급 제외/소명 대상 매입세액을 자동 집계합니다.
B6: 구분 | C6: 건수 | D6: 관련 매입세액(VND) | E6: 조치 사항
B7: 위험 공급사 (폐업/블랙리스트) | C7: =COUNTIFS('4.Supplier_Verification'!H7:H21,"Y")+COUNTIFS('4.Supplier_Verification'!I7:I21,"Y") -> 0 | D7: =SUMIF('4.Supplier_Verification'!H7:H21,"Y",'4.Supplier_Verification'!G7:G21)+SUMIF('4.Supplier_Verification'!I7:I21,"Y",'4.Supplier_Verification'!G7:G21)-SUMIFS('4.Supplier_Verification'!G7:G21,'4.Supplier_Verification'!H7:H21,"Y",'4.Supplier_Verification'!I7:I21,"Y") -> 0 | E7: 환급 대상 제외 또는 소명자료 제출
B8: FCT 적용 거래 | C8: =COUNTIF('4.Supplier_Verification'!J7:J21,"Y") -> 0 | D8: =SUMIF('4.Supplier_Verification'!J7:J21,"Y",'4.Supplier_Verification'!G7:G21) -> 0 | E8: FCT 신고/납부 완료 후에만 매입세액 공제 가능
B9: 장기 미지급(6개월 초과) | C9: =COUNTIF('5.AP_Aging'!I7:I21,"6개월 초과") -> 0 | D9: =SUMIF('5.AP_Aging'!I7:I21,"6개월 초과",'5.AP_Aging'!G7:G21)*0.1 -> 0 | E9: 공급상 확인서(Confirmation Letter) 즉시 징구
B10: 합계 (잠정 위험 매입세액) | C10: =SUM(C7:C9) -> 0 | D10: =SUM(D7:D9) -> 0 | E10: Dashboard의 '환급 가능 잔액'에서 차감 검토

Sheet 7.Audit_Readiness
B2: ④ 추가 권고 — 환급 신청 후 세무서 현장 실사 대비
B4: No. | C4: 점검 영역 | D4: 점검 항목 | E4: 장부 일치 여부 | F4: 원본 보관 여부 | G4: 비고/조치
B5: 1 | C5: 재고 | D5: 원자재 재고 실사 결과 vs 장부 | E5: 미확인 | F5: 미확인 | G5: 분기말 현장 실사 병행
B6: 2 | C6: 재고 | D6: 제공품/완성품 수량 일치 | E6: 미확인 | F6: 미확인
B7: 3 | C7: 설비 | D7: 생산 설비 리스트 vs 고정자산대장 | E7: 미확인 | F7: 미확인
B8: 4 | C8: 인력 | D8: 공장 인력 명단 vs 노무 신고 | E8: 미확인 | F8: 미확인
B9: 5 | C9: 증빙 | D9: E-Invoice 원본(또는 PDF) 보관 | E9: 미확인 | F9: 미확인 | G9: 바인더 정리
B10: 6 | C10: 증빙 | D10: 수입신고필증 원본 | E10: 미확인 | F10: 미확인
B11: 7 | C11: 증빙 | D11: 송금 영수증 원본 | E11: 미확인 | F11: 미확인
B12: 8 | C12: 증빙 | D12: 매입 계약서 원본 | E12: 미확인 | F12: 미확인
B13: 9 | C13: 보관 | D13: 문서 5년 보관 (Decree 123/2020/ND-CP) | E13: 미확인 | F13: 미확인
B14: 10 | C14: 기타 | D14: 공장 출입대장, CCTV 등 활동 증빙 | E14: 미확인 | F14: 미확인 | G14: 현장 실사 시 자주 요구됨
