Workbook
Name __DemandLoad: TRUE
Name __IntlFixup: TRUE
Name _1a1_: {"'Sheet1'!$L$16"}
Name _1a1_: {"'Sheet1'!$L$16"}
Name _1a1_: {"'Sheet1'!$L$16"}
Name _1a1_: {"'Sheet1'!$L$16"}
Name _1a1_: {"'Sheet1'!$L$16"}
Name _1a1_: {"'Sheet1'!$L$16"}
Name _Order1: 255
Name _Order2: 255
Name _PA3: {"'Sheet1'!$L$16"}
Name _PA3: {"'Sheet1'!$L$16"}
Name _PA3: {"'Sheet1'!$L$16"}
Name _PA3: {"'Sheet1'!$L$16"}
Name _PA3: {"'Sheet1'!$L$16"}
Name _PA3: {"'Sheet1'!$L$16"}
Name _Regression_Int: 1
Name AS2DocOpenMode: "AS2DocumentEdit"
Name AS2ReportLS: 1
Name AS2SyncStepLS: 0
Name AS2VersionLS: 300
Name BG_Del: 15
Name BG_Ins: 4
Name BG_Mod: 6
Name CTCT1: {"'Sheet1'!$L$16"}
Name CTCT1: {"'Sheet1'!$L$16"}
Name CTCT1: {"'Sheet1'!$L$16"}
Name CTCT1: {"'Sheet1'!$L$16"}
Name CTCT1: {"'Sheet1'!$L$16"}
Name CTCT1: {"'Sheet1'!$L$16"}
Name HTML_CodePage: 950
Name HTML_Control: {"'Sheet1'!$L$16"}
Name HTML_Control: {"'Sheet1'!$L$16"}
Name HTML_Control: {"'Sheet1'!$L$16"}
Name HTML_Control: {"'Sheet1'!$L$16"}
Name HTML_Control: {"'Sheet1'!$L$16"}
Name HTML_Control: {"'Sheet1'!$L$16"}
Name HTML_Description: ""
Name HTML_Email: ""
Name HTML_Header: "Sheet1"
Name HTML_LastUpdate: "2000/9/14"
Name HTML_LineAfter: FALSE
Name HTML_LineBefore: FALSE
Name HTML_Name: "J.C.WONG"
Name HTML_OBDlg2: TRUE
Name HTML_OBDlg4: TRUE
Name HTML_OS: 0
Name HTML_PathFile: "C:\2689\Q\國內\00q3961台化龍德PTA3建造\MyHTML.htm"
Name HTML_Title: "00Q3961-SUM"
Name huy: {"'Sheet1'!$L$16"}
Name huy: {"'Sheet1'!$L$16"}
Name huy: {"'Sheet1'!$L$16"}
Name huy: {"'Sheet1'!$L$16"}
Name huy: {"'Sheet1'!$L$16"}
Name huy: {"'Sheet1'!$L$16"}
Name JYFUJ: BLCH
Name JYFUJ: BLCH
Name JYFUJ: BLCH
Name JYFUJ: BLCH
Name KUGHIKJ: BLCH

Sheet Cover
A3: 2026 Business Plan M&C Electronics

Sheet Index
A2: <Index>
E6: 1. Assumption
E7: - 영업, 개발, 생산, 품질, 관리, 재무
E9: 2. Sales Plan (S Plan)
E10: - 매출 수량 및 금액
E12: 3. Production Plan (P Plan)
E13: - 생산 수량 및 필요 설비 수
E15: 4. Labor Plan (L Plan)
E16: - 인원 계획
E18: 5. Material Plan (M Plan)
E19: - 원부자재 계획
E21: 6. Outsourcing (O Plan)
E22: - 외주 비용(아노다이징,분체도장)
... E40: - 대출 현황

Sheet 1. Assumption
A1: Basic Assumption
A4: ☆ M&C 베트남 법인 사업계획 보고
A6: 1) 개발영업 - 매출
B7: No. | C7: 고객사 | D7: 내용 | E7: 매출액 | F7: 비고/특이사항
B8: 1 | C8: 삼성 Bracket | D8: 26.10월부터 15대 가동 - 월 최대 2,300,000대 수준으로 변경 | E8: ='2. S Plan'!X109+'2. S Plan'!X110+'2. S Plan'!X111+'2. S Plan'!X112+'2. S Plan'!X113+'2. S Plan'!X114+'2. S Plan'!X115 -> 12243940 | F8: - AI디바이스 교체에 따른 연간 출하량 지속 증가
B9: 2 | C9: 삼성 CNC | D9: 26.8월 LGIT 종료 설비 50대 + 26.10월 만도 종료 설비 25대 투입 반영 | E9: ='2. S Plan'!X117 -> 6451579.4
B10: 3 | C10: Qualcomm | E10: ='2. S Plan'!X119+'2. S Plan'!X120+'2. S Plan'!X121+'2. S Plan'!X122+'2. S Plan'!X123+'2. S Plan'!X124 -> 693554.69
B11: 4 | C11: LGIT | D11: 협의 수량으로 조정 | E11: ='2. S Plan'!X127+'2. S Plan'!X128+'2. S Plan'!X129+'2. S Plan'!X130+'2. S Plan'!X131+'2. S Plan'!X132+'2. S Plan'!X134+'2. S Plan'!X136+'2. S Plan'!X137+'2. S Plan'!X139+'2. S Plan'!X140+'2. S Plan'!X141+'2. S Plan'!X142+'2. S Plan'!X143+'2. S Plan'!X145+'2. S Plan'!X147+'2. S Plan'!X148+'2. S Plan'!X150+'2. S Plan'!X151+'2. S Plan'!X153+'2. S Plan'!X154+'2. S Plan'!X155+'2. S Plan'!X156+'2. S Plan'!X159+'2. S Plan'!X160+'2. S Plan'!X161+'2. S Plan'!X162 -> 5008883.3 | F11: CL4 & MQ4 기존 납품처 YT -> MX 변경 예정 구체적인 일정 및 단가 변경은 고객사와 협의 후 사업계획 내 반영 예정
B12: 5 | C12: Mando | D12: 3/16 거래 종료 통보 예정. 추후 최종 공급 수량 협의 필요 | E12: ='2. S Plan'!X165+'2. S Plan'!X166+'2. S Plan'!X167+'2. S Plan'!X169+'2. S Plan'!X168+'2. S Plan'!X170+'2. S Plan'!X172+'2. S Plan'!X173+'2. S Plan'!X174+'2. S Plan'!X175+'2. S Plan'!X176+'2. S Plan'!X178+'2. S Plan'!X180 -> 6540485.5
B13: 6 | C13: ZF | D13: 2026 Forecast 반영 | E13: ='2. S Plan'!X183+'2. S Plan'!X184+'2. S Plan'!X185+'2. S Plan'!X187+'2. S Plan'!X188+'2. S Plan'!X189+'2. S Plan'!X191+'2. S Plan'!X192+'2. S Plan'!X193+'2. S Plan'!X194+'2. S Plan'!X195+'2. S Plan'!X196 -> 8333548.6
B14: 7 | C14: A | D14: 2026년 테스트용 시제품 수요 예상 (월 200개, 2026.7~ 반영) | E14: ='2. S Plan'!X200+'2. S Plan'!X201+'2. S Plan'!#REF!+'2. S Plan'!#REF!+'2. S Plan'!#REF!+'2. S Plan'!#REF!+'2. S Plan'!X199 -> #REF! | F14: 2026년 3월까지 시제품 평가 완료. 하반기 저율초도생산(LRIP)으로 전환 예상 Qualcomm과 같이 VN 20%, SG 80%
B15: 8 | C15: 기타 | D15: - 스크랩 및 금형비 반영 | E15: ='2. S Plan'!X204+'2. S Plan'!X205 -> 2283491.7
B16: 합계 | E16: =SUM(E8:E15) -> #REF!
E17: TRUE
A18: 2) 개발영업 - 제품 개발
B19: No. | C19: 고객사 | D19: 내용 | F19: 비고/특이사항
B20: 1 | C20: 삼성 | D20: 자동화 설비 연계, 제품 개발 및 생산성 확보 효율화 / Bracket 금형 추가 배정 영업 지속
B21: 2 | C21: Qualcomm | D21: 기존 제품 양산 안정화 및 신규 프로젝트 수주 활동 지속
B22: 3 | C22: ZF | D22: ADAS 외 제품군 견적 및 수주 활동 지속
B23: 4 | C23: LGIT | D23: 사업 철수 진행
B24: 5 | C24: Mando
B25: 6 | C25: A | D25: Audit 준비 및 DFM, 긴급 물량 지속 대응/협업 진행

Sheet 1-1.Assumption
A1: Basic Assumption (Expense)
A3: 3) 관리
A4: No. | B4: 주제 | C4: 항목 | D4: 내용 | E4: 추정 이유(계산) (개선방안) | F4: 비고/특이사항
A5: 1 | B5: COGS (COGM) | C5: 원재료 | D5: (ADC12 $2.65, S36 $3.30, S3Y $3.37) / Kg | E5: 25년 (1~8월) 평균가 | F5: 5.M Plan 참조
C6: 인건비 | D6: 2025년 대비 Worker 7%, 관리자 5%, 주재원 3% 인상 적용 | F6: 4.L Plan 참조
D7: 2026년 주재원 충원 미반영 | F7: 4.L Plan 참조
C8: 관리비(3대보험&복지) | D8: 베트남 기준 (사회,고용,건강보험,노동조합)가입, 복지(식대) | E8: 개인별 급여 월 23.5%보험가입비*총 인원+식대
C9: 관리비(유틸리티) | D9: 생산일수 기반으로 현재 단가 적용 | E9: 2023~2025년도 평균 4.5%인상 기준으로 2026년도 베트남 전기료 인상 4.5% 반영
C10: 관리비(유틸리티) | D10: 폐수처리 비용 (생활 폐수,오염 절삭유,크로메이트 처리 폐수 ) | E10: 캐스팅 장비수+CNC생산일수(평균)*25년 (1~8월) 평균 폐수처리 단가계산로 반영
C11: 관리비(유틸리티) | D11: 수도,하수 비용 | E11: 월 계산=3개월 평균 가격 (월 인원수+캐스팅 가동수+크로메이트처리(시간당) 기준)
C12: 관리비(아웃소싱) | D12: Samsung Bracket 월 50만개 이상시 외주 사상 진행, ZF 아노다이징, 퀄컴 레이저 및 A사 외주 비용 반영 | F12: 6.O Plan 참조
C13: 관리비(Oil & 소모품) | D13: 매출액 대비 5.5%기준 적용 | E13: 2025년 영업매출 대비 평균 % 반영
C14: 관리비(Tool 소모품) | D14: 매출액 대비 1.2%기준 적용 | E14: 2024년 1.7% 대비 2025년 1~8월 평균 1.2%로, 0.5% 감소하여 2026년 1.2% 반영
C15: 관리비(납품차량렌트) | D15: 영업 납품용 차량 (화물 탑차 5ton 2대 임대 비용)
C16: 감가상각 | D16: 고정자산(장비&설비) 회계처리 비용 | E16: 2025년 8월 기준기준 실제 비용 적용 | F16: 8.I Plan 참조
C17: 기타 비용 | D17: 각종 납품용 박스 및 파렛트 년평균 매출 %기준 대비 추정
A18: 2 | B18: SG&A | C18: 컨설팅 서비스 비용 | D18: 서비스 비용(한국 $5만, 중국$3만)
C19: 출장비 | D19: 매출액의 0.2%로 적용 | E19: 2025년도 월 평균 반영 및 A사 (미국) 출장 비용 분기별 1만불 추가 적용
C20: 차량(출퇴근)임대 | D20: 카니발 7인승 5대, 15인승 1대 ,지게차 2대 운영비용 | E20: 추가 없음
C21: 학자금 지원 | D21: 주재원 자녀 복리 학비 지원 (1명당Net $6,500$ 총$45,500 월 평균 반영) | E21: 주재원 자녀 총 7명 지원
C22: 감가상각 | D22: 2026년 8월 기준, 신규 투자 설비 반영
C23: 기타비용 (사내 경비,청소) | D23: 경비 & 청소 용역, 정원 관리 비용 | E23: 2025년 비용 평균 적용 (예비비 포함)
C24: 근무일수 | D24: 2026년도 총 302일 (주일 53일,국경절&행사 10일) | F24: 4.L.Plan 참조
A25: 4 | B25: 투자계획 | C25: 주요구입장비 | D25: 사업계획에 투자 반영 | E25: 2025년 8월 기준 업데이트, 'I plan 참조 | F25: 8.I-Plan 참조
A26: 5 | B26: 환율 적용 | C26: SGD | D26: 외화(달러)현재 적용 환율 | E26: 2026년 시장 예상(단 환율 변동이 클 경우 조정 필요, update 25.08 UOB 및 Traders Union 참조) | F26: 1.29
C27: KRW | F27: 1450
C28: CNY | F28: 6.9
C29: VND | F29: 26400

Sheet 1. Master Plan
A1: Business Relocation Master Plan
A2: No | B2: Vendor | C2: Present | D2: Future 2027 | E2: 46023 | F2: 46054 | G2: 46082 | H2: 46113 | I2: 46143 | J2: 46174 | K2: 46204 | L2: 46235 | M2: 46266 | N2: 46296 | O2: 46327 | P2: 46357 | Q2: 46388 | R2: 46419 | S2: 46447 | T2: 46478 | U2: 46508 | V2: 46539 | W2: 비고 | Z2: Sales Down | AA2: -1200
A3: 1 | B3: Samsung Bracket | C3: 12500000 | D3: 25000000 | L3: 15 | M3: 15 | N3: 15 | O3: 15 | P3: 15 | Q3: 17 | R3: =Q3 -> 17 | S3: =R3 -> 17 | T3: =S3 -> 17 | U3: =T3 -> 17 | V3: =U3 -> 17 | W3: 15대 X 7K X 25 DAYS = 2.65M/M | Z3: Material AL | AA3: 550
A4: 2 | B4: Samsung CNC | C4: 6300000 | D4: 8000000 | J4: 319 | K4: =J4 -> 319 | L4: =K4 -> 319 | M4: =L4+31 -> 350 | N4: =M4 -> 350 | O4: =N4 -> 350 | P4: =O4 -> 350 | Q4: =P4+50 -> 400 | R4: =Q4 -> 400 | S4: =R4 -> 400 | T4: =S4 -> 400 | U4: =T4 -> 400 | V4: =U4 -> 400 | W4: 삼성 CNC생산 투입 400대 (삼성 283+당사 127대) | Z4: Labor | AA4: 100
A5: 3 | B5: Samsung CNC 설비 추가 | K5: 50 | L5: =K5 -> 50 | M5: =L5 -> 50 | N5: =M5 -> 50 | O5: =N5 -> 50 | P5: =O5 -> 50 | Q5: =P5 -> 50 | R5: =Q5 -> 50 | S5: =R5 -> 50 | ... V5: =U5 -> 50 | W5: 삼성 CNC 설비 추가 50대 임대 | Z5: Consummerable & Mold Fee | AA5: 200
A6: 4 | B6: ZF | C6: 9000000 | D6: 9000000 | L6: 5 | M6: 5 | N6: 5 | O6: 5 | P6: 5 | Q6: 5 | R6: 5 | S6: 5 | T6: 5 | U6: 5 | V6: 5 | Z6: Logsitics/Warehoues/QC Exp. | AA6: 150
A7: 5 | B7: Qualcomm | C7: 6000000 | D7: 5500000 | L7: 0 | M7: 0 | N7: 0 | O7: 0 | P7: 0 | Z7: 감가상각 및 기타 | AA7: 200
A8: 6 | B8: A | D8: 2500000 | L8: 0 | M8: 0 | N8: 0 | O8: 0 | P8: 0 | Z8: Cost Reduction | AA8: =SUM(AA3:AA7) -> 1200
A9: 7 | B9: LGIT | C9: 6500000 | D9: 0 | E9: 통지 | F9: 1차회의 | G9: 2차회의 | H9: 6 | I9: 6 | J9: 5 | K9: 5 | L9: 4 | M9: 3 | N9: 2 | O9: 2 | P9: 2 | W9: 최종 만도/LG재고생산 4-5대 배치 2027 상반기까지 지원 | Z9: Sales up
A10: 8 | B10: Mando | C10: 6800000 | D10: 1500000 | G10: 통지 | H10: 1차회의 | I10: 2차회의 | J10: 6 | K10: 6 | L10: 4 | M10: 4 | N10: 3 | O10: 3 | P10: 3 | Q10: 3 | R10: 3 | S10: 3 | T10: 3 | U10: 3 | V10: 3 | W10: 외주에 400톤 2대 설치하여 종료제품 SPOT생산 지원 | Z10: Samsung Bracket | AA10: 850
A11: 9 | B11: Total | C11: =SUM(C3:C10) -> 47100000 | D11: =SUM(D3:D10) -> 51500000 | L11: =SUM(L3,L6,L9:L10) -> 28 | M11: =SUM(M3,M6,M9:M10) -> 27 | N11: =SUM(N3,N6,N9:N10) -> 25 | O11: =SUM(O3,O6,O9:O10) -> 25 | P11: =SUM(P3,P6,P9:P10) -> 25 | Q11: =SUM(Q3,Q6,Q9:Q10) -> 25 | R11: =SUM(R3,R6,R9:R10) -> 25 | S11: =SUM(S3,S6,S9:S10) -> 25 | ... V11: =SUM(V3,V6,V9:V10) -> 25 | Z11: Samsung CNC | AA11: 150
A13: No | B13: Project 명칭 | C13: 단가 | D13: 소요예산 | E13: 46023 | F13: 46054 | G13: 46082 | H13: 46113 | I13: 46143 | J13: 46174 | K13: 46204 | L13: 46235 | M13: 46266 | N13: 46296 | O13: 46327 | P13: 46357 | Q13: 46388 | R13: 46419 | S13: 46447 | T13: 46478 | U13: 46508 | V13: 46539 | W13: 비고
A14: 1 | B14: 캐스팅 125톤 외주 임대 개시 | C14: 0 | D14: =C14 -> 0 | G14: 외부설치 | H14: 2 | I14: 2 | J14: 2 | K14: 2 | L14: 2 | M14: 2 | N14: 2 | O14: 2 | P14: 2 | Q14: 2 | R14: 2 | S14: 2 | T14: 2 | U14: 2 | V14: 2
A15: 2 | B15: 삼성 CNC 화장실 공사 완료 | C15: 0 | D15: =C15 -> 0 | G15: 설치
A16: 3 | B16: CNC ZF BT30생산 BT40 이전 생산 | C16: 0 | D16: =C16 -> 0 | H16: 설치 | W16: ZF 물량 BT40으로 이전하고 BT30 12대 삼성 CNC 라인 이동 배치
A17: 4 | B17: CNC화장실 CNC12대 이동 | C17: 10000 | D17: =C17 -> 10000 | H17: 설치 | W17: 283+24+12대 총 319대 생산 및 일요일 잔업 최소화
A18: 5 | B18: 삼성 CNC Block 자동화 CNC라인 구축 (6개라인 개조) | C18: 20000 | D18: =C18*6 -> 120000 | M18: 설계 | N18: 설계 | O18: 발주 | P18: 발주 | Q18: 설치 | W18: 최소 4개라인에서 최대 6개라인 개선 변경 후 삼성 Block생산
A19: 6 | B19: 삼성 CNC 설비 추가 임대 50대 진행 (삼성지속확인) | C19: 2000 | D19: =C19*50 -> 100000 | K19: 임대확정 | L19: 공간확보 | W19: 삼성 CNC가공 확인/ GEN3쪽 CNC라인 공간 확보 및 선반 배치 확인
A20: 7 | B20: 삼성 CNC세척라인 이동 및 개조 | C20: 10000 | D20: =C20 -> 10000 | O20: 설치 | W20: 기존 하우징 세척 라인 이용
A21: 8 | B21: 삼성 CNC Block 사상 및 검사 자동화 라인 | C21: 100000 | D21: =C21 -> 100000 | J21: 설계 | K21: 설계 | L21: 발주 | O21: 설치 | W21: Almus Burr 제거라인 확인 및 공간확보 혹은 당사 외주 발주
A22: 9 | B22: 삼성 CNC라인 공조설치 | C22: 100000 | D22: =C22*2 -> 200000 | G22: 설계 | H22: 발주 | I22: 설치 | W22: 5월15일 이전까지 삼성 CNC라인 공조 설치 및 배풍 개선
A23: 10 | B23: 캐스팅 라인 덮개 26대 공사 완료 및 배풍 시설 개선 | C23: 7000 | D23: =C23*26 -> 182000 | G23: 발주 | H23: 완료
A24: 11 | B24: 캐스팅 라인 집진 장비 테스트 및 문 추가 설치(통풍) | C24: 5000 | D24: =C24*26 -> 130000 | G24: TEST | H24: 발주 | K24: 도착 | Z24: =15*7*25 -> 2625
A25: 12 | B25: 캐스팅 설비 350톤 4대 도착 및 생산 | C25: 136000 | D25: =C25*4 -> 544000 | F25: 발주 | J25: 도착 | K25: 26 | L25: 26 | M25: 26 | N25: 26 | O25: 26 | P25: 26 | Q25: 26 | R25: 26 | S25: 26 | T25: 26 | U25: 26 | V25: 26 | W25: 2026년 7월부터 350톤 24대, 125톤 2대 체제 운영
A26: 13 | B26: 캐스팅 설비 400톤 2대 외주 임대 개시 | C26: 0 | D26: =C26 -> 0 | J26: 외부설치 | K26: 2 | L26: =K26 -> 2 | M26: =L26 -> 2 | N26: =M26 -> 2 | O26: =N26 -> 2 | P26: =O26 -> 2 | Q26: =P26 -> 2 | R26: =Q26 -> 2 | S26: =R26 -> 2 | ... V26: =U26 -> 2
A27: 14 | B27: 금형라인 CNC로 임시 생산 이동 및 생산 | C27: 20000 | D27: =C27 -> 20000 | I27: 이전 | J27: 생산 | K27: 생산 | W27: 현재 설비 전부 이동 (가공기 6대/방전기2대/와이어 1대)
A28: 15 | B28: 금형라인 사무실 및 유지보수 임시 이동 운영 | C28: 20000 | D28: =C28 -> 20000 | I28: 이전 | J28: 임시운영 | K28: 임시운영 | L28: 임시운영 | M28: 복귀
A29: 16 | B29: 금형가공 라인 공사 진행 (현 가공+사무실+공구창고) | C29: 200000 | D29: =C29 -> 200000
A30: 17 | B30: 금형유지보수 라인 공사 진행 | C30: 100000 | D30: =C30 -> 100000
A31: 18 | B31: 금형설비 발주 (방전기 4대, 가공기 2대, 와이어 1대) | C31: ='8. I Plan'!G8+'8. I Plan'!G9+'8. I Plan'!G10+'8. I Plan'!G11 -> 1206042 | D31: =C31 -> 1206042 | I31: 발주 | L31: 도착 | M31: 도착 | W31: 가공 6-8대, 방전 6대, 와이어 2대, 일반 방전 2-4대
A32: 19 | B32: 금형 자동화 라인 | C32: ='8. I Plan'!E49 -> 402923.08 | D32: =C32 -> 402923.08 | J32: 발주 | L32: 도착 | M32: 도착 | W32: CMM2대 자동화 및 AMR 도입 로봇형 자동화 라인
A33: 20 | B33: 금형 자동화 라인 CMM측정설비 도입 (신규 1대) | C33: 100000 | D33: =C33 -> 100000 | L33: 발주 | N33: 도착 | W33: CMM1대는 기존 설비 이동, CMM 1대는 추가 구매 진행
A34: 21 | B34: QC측정 자동화 라인 (CMM 3대 자동측정 라인) | C34: 70000 | D34: =C34 -> 70000 | K34: 발주 | N34: 도착
A35: 22 | B35: CL4 & IMEB CNC라인 이동 | C35: 10000 | D35: =C35 -> 10000 | N35: 라인이동
A36: 23 | B36: Braket 자동화 검사 5대운영 | C36: 30000 | D36: =C36 -> 30000 | G36: 발주 | H36: 도착 | I36: 5 | J36: 5 | K36: 5 | L36: 5 | M36: 5 | N36: 5 | O36: 5 | P36: 5 | Q36: 5 | R36: 5 | S36: 5 | T36: 5 | U36: 5 | V36: 5
A37: 24 | B37: Bracket Hot Press 자동화 4개라인 운영 | C37: 19818 | D37: =C37 -> 19818 | G37: 발주 | H37: 도착 | I37: 4 | J37: 4 | K37: 4 | L37: 4 | M37: 4 | N37: 4 | O37: 4 | P37: 4 | Q37: 4 | R37: 4 | S37: 4 | T37: 4 | U37: 4 | V37: 4
A38: 25 | B38: Bracket 자동화 Index 6개 라인 운영 | C38: 31700 | D38: =C38 -> 31700 | G38: 발주 | H38: 도착 | I38: 6 | J38: 6 | K38: 6 | L38: 6 | M38: 6 | N38: 6 | O38: 6 | P38: 6 | Q38: 6 | R38: 6 | S38: 6 | T38: 6 | U38: 6 | V38: 6
A39: 26 | B39: Bracket 자동화 사상 6개라인 운영 | C39: 46500 | D39: =C39*3 -> 139500 | G39: 발주 | H39: 도착 | I39: 6 | J39: 6 | K39: 6 | L39: 6 | M39: 6 | N39: 6 | O39: 6 | P39: 6 | Q39: 6 | R39: 6 | S39: 6 | T39: 6 | U39: 6 | V39: 6
A40: 27 | B40: Bracket 자동화 로봇 사상 라인 16개 라인 운영 | C40: 20000 | D40: =C40*4 -> 80000 | G40: 설계 | H40: 발주 | I40: 도착 | J40: 16 | K40: 16 | L40: 16 | M40: 16 | N40: 16 | O40: 16 | P40: 16 | Q40: 16 | R40: 16 | S40: 16 | T40: 16 | U40: 16 | V40: 16
A41: 28 | B41: Bracket 자동화 바렐 라인 라인 운영 | C41: 30000 | D41: =C41 -> 30000 | H41: 소싱 | I41: 발주 | K41: 도착
A42: 29 | B42: Bracket 화성라인 개선 진행 | C42: 30000 | D42: =C42 -> 30000 | H42: 설계 | I42: 발주 | K42: 도착
A43: 30 | B43: Braket 자동화 검사 5대 이동 설치 (자동화 투입개선) | C43: 5000 | D43: =C43*5 -> 25000 | Q43: 이동설치 | W43: 현재 OQC 구역으로 5대 이동 설치/ 투입 자동화 추가 개선
A44: 31 | B44: Bracket 자동화 라인 완성 | C44: 50000 | D44: =C44 -> 50000 | N44: 이동설치 | W44: 열정형4대/자동사상6대/로봇사상16대/자동인덱스6대 300만개 캐파
B45: 캐스팅 총 운영 가능 Capa | D45: =SUM(D14:D44) -> 3960983.1 | E45: 26 | F45: 26 | G45: 26 | H45: 28 | I45: 28 | J45: 28 | K45: =SUM(K14:K26) -> 30 | L45: =SUM(L14:L26) -> 30 | M45: =SUM(M14:M26) -> 30 | N45: =SUM(N14:N26) -> 30 | O45: =SUM(O14:O26) -> 30 | P45: =SUM(P14:P26) -> 30 | Q45: =SUM(Q14:Q26) -> 30 | R45: =SUM(R14:R26) -> 30 | ... V45: =SUM(V14:V26) -> 30 | W45: 내부: 250톤 24대, 125톤 2대, 외부 400톤 2대, 125톤 2대 총 30대

Sheet 2. S Plan
A1: 2. Sales Plan
X2: Rev 26
A3: 1) Sales Quantity | X3: 2026.06.06
A4: No. | B4: Industry | C4: Customer | D4: Categories | E4: No | F4: Model | G4: U/P | H4: Q1 | I4: Q2 | J4: Q3 | K4: Q4 | L4: Jan.26 | M4: Feb.26 | N4: Mar.26 | O4: Apr.26 | P4: May.26 | Q4: Jun.26 | R4: Jul.26 | S4: Aug.26 | T4: Sep.26 | U4: Oct.26 | V4: Nov.26 | W4: Dec.26 | X4: 2026 Total | AB4: Customer | AC4: Categories
A5: 1 | B5: Mobile | C5: Samsung | D5: Mobile | F5: =B.BasicInfomation!B10 -> Galaxy Tap | G5: 1.8 | H5: 0.86499679 | I5: 0.74 | J5: 0.7252 | K5: 0.710696 | L5: 0 | M5: 0 | N5: 0 | O5: 0 | P5: 0 | Q5: 0 | R5: 0 | V5: 10000 | W5: 50000 | X5: =SUM(L5:W5) -> 60000 | AB5: Samsung | AC5: Mobile
E6: 1 | F6: A15/17 | G6: 0.618 | H6: 0.68186719 | I6: 0.6625162 | J6: 0.66529412 | K6: 0.65198824 | L6: 1134160 | M6: 804560 | N6: 887570 | O6: 972545 | P6: 970800 | Q6: 1160000 | R6: 1200000 | S6: 1200000 | T6: 800000 | U6: 750000 | V6: 750000 | W6: 750000 | X6: =SUM(L6:W6) -> 11379635 | AB6: =AB5 -> Samsung | AC6: =AC5 -> Mobile
E7: 2 | F7: A36 | G7: 0.70957692 | H7: 0.76 | I7: 0.75126469 | J7: 0.72713725 | K7: 0.71259451 | L7: 46320 | M7: 0 | N7: 60960 | O7: 80640 | P7: 20160 | Q7: 15000 | R7: 0 | S7: 0 | T7: 0 | U7: 0 | V7: 0 | W7: 0 | X7: =SUM(L7:W7) -> 223080 | AB7: =AB6 -> Samsung | AC7: =AC6 -> Mobile
E8: 3 | F8: A26 | G8: 0.68169231 | H8: 0.80160892 | I8: 0.75653268 | J8: 0.7292549 | K8: 0.7146698 | L8: 209040 | M8: 55293 | N8: 0 | O8: 9876 | P8: 83280 | R8: 0 | S8: 0 | T8: 0 | U8: 0 | V8: 0 | W8: 0 | X8: =SUM(L8:W8) -> 357489 | AB8: =AB7 -> Samsung | AC8: =AC7 -> Mobile
E9: 4 | F9: A27 | G9: 0.71 | H9: 1.0308227 | I9: 0.95888659 | J9: 0.99600625 | K9: 1.0132913 | L9: 0 | M9: 0 | N9: 0 | O9: 0 | P9: 101760 | Q9: 790000 | R9: 1000000 | S9: 1000000 | T9: 700000 | U9: 500000 | V9: 500000 | W9: 400000 | X9: =SUM(L9:W9) -> 4991760 | AB9: =AB8 -> Samsung | AC9: =AC8 -> Mobile
E10: 5 | F10: A37 | G10: 0.752 | L10: 69200 | M10: 411900 | N10: 222600 | O10: 0 | P10: 48600 | Q10: 64000 | R10: 100000 | S10: 100000 | T10: 100000 | U10: 100000 | V10: 0 | W10: 0 | X10: =SUM(L10:W10) -> 1216300 | AB10: =AB9 -> Samsung | AC10: =AC9 -> Mobile
E11: 6 | F11: A18 | G11: 0.6 | L11: 0 | M11: 0 | N11: 0 | O11: 0 | P11: 0 | Q11: 0 | R11: 0 | S11: 0 | U11: 50000 | V11: 400000 | W11: 400000 | X11: =SUM(L11:W11) -> 850000 | AB11: =AB10 -> Samsung | AC11: =AC10 -> Mobile
E12: Braket Sub Toal | L12: =SUM(L5:L11) -> 1458720 | M12: =SUM(M5:M11) -> 1271753 | N12: =SUM(N5:N11) -> 1171130 | O12: =SUM(O5:O11) -> 1063061 | P12: =SUM(P5:P11) -> 1224600 | Q12: =SUM(Q5:Q11) -> 2029000 | R12: =SUM(R5:R11) -> 2300000 | S12: =SUM(S5:S11) -> 2300000 | ... W12: =SUM(W5:W11) -> 1600000 | X12: =SUM(L12:W12) -> 19078264
F13: CNC | G13: 1.14 | H13: 1.0308227 | I13: 0.91672214 | J13: 0.85039625 | K13: 0.8294203 | L13: 481641 | M13: 309968 | N13: 520149 | O13: 384822 | P13: 393686 | Q13: 450000 | R13: 480000 | S13: 566500 | T13: 550000 | U13: 561000 | V13: 517000 | W13: 495000 | X13: =SUM(L13:W13) -> 5709766 | AB13: =AB11 -> Samsung | AC13: =AC11 -> Mobile
C14: Samsung Sub Total | L14: =SUM(L12:L13) -> 1940361 | M14: =SUM(M12:M13) -> 1581721 | N14: =SUM(N12:N13) -> 1691279 | O14: =SUM(O12:O13) -> 1447883 | P14: =SUM(P12:P13) -> 1618286 | Q14: =SUM(Q12:Q13) -> 2479000 | R14: =SUM(R12:R13) -> 2780000 | S14: =SUM(S12:S13) -> 2866500 | ... X14: =SUM(X12:X13) -> 24788030 | Y14: =X14=SUM(L14:W14) -> TRUE
C15: Qualcomm | D15: Mobile | E15: 7 | F15: MTP+IDP+ADP | G15: 1.85 | L15: 18000 | M15: 6109.2 | N15: 17266.409 | O15: 16000 | P15: 14559.846 | Q15: 18266.409 | R15: 18266.409 | S15: 18266.409 | T15: 18266.409 | U15: 18266.409 | V15: 13633.205 | W15: 13633.205 | X15: =SUM(L15:W15) -> 190533.91 | Z15: =G15/4*10 -> 4.625 | AB15: Qualcomm | AC15: Mobile
E16: 8 | F16: Ride5 | G16: 71.43 | L16: 200 | M16: 200 | N16: 0 | O16: 141.99916 | P16: 200 | Q16: 200 | R16: 250 | S16: 250 | T16: 250 | U16: 200 | V16: 100 | W16: 100 | X16: =SUM(L16:W16) -> 2091.9992 | Z16: =G16/4*10 -> 178.575 | AB16: =AB15 -> Qualcomm | AC16: =AC15 -> Mobile
F17: Glymur | G17: 4.9 | L17: 0 | M17: 0 | N17: 0 | O17: 0 | P17: 0 | Q17: 0 | R17: 0 | S17: 0 | T17: 0 | U17: 0 | V17: 0 | W17: 0 | X17: =SUM(L17:W17) -> 0 | Z17: =G17/4*10 -> 12.25 | AB17: =AB16 -> Qualcomm | AC17: =AC16 -> Mobile
E18: 9 | F18: MTP Hawi | G18: 8.23 | L18: 1000 | M18: 812.06756 | N18: 1000 | O18: 1000 | P18: 1000 | Q18: 1000 | R18: 1000 | S18: 1000 | T18: 1000 | U18: 1000 | V18: 1000 | W18: 1000 | X18: =SUM(L18:W18) -> 11812.068 | Z18: =G18/4*10 -> 20.575 | AB18: =AB17 -> Qualcomm | AC18: =AC17 -> Mobile
E19: 10 | F19: QMP Amboseli | G19: 8.23 | L19: 500 | M19: 500 | N19: 531.22722 | O19: 0 | P19: 500 | Q19: 0 | R19: 500 | S19: 0 | T19: 500 | U19: 0 | V19: 500 | W19: 0 | X19: =SUM(L19:W19) -> 3531.2272 | Z19: =G19/4*10 -> 20.575 | AB19: =AB18 -> Qualcomm | AC19: =AC18 -> Mobile
F20: LDS Antenna | G20: 2.68 | L20: 3604.4776 | M20: 2000 | N20: 2000 | O20: 4500 | P20: 2500 | Q20: 1200 | R20: 2500 | S20: 1200 | T20: 1200 | U20: 1200 | V20: 1200 | W20: 1200 | X20: =SUM(L20:W20) -> 24304.478 | Z20: =G20/4*10 -> 6.7 | AB20: =AB19 -> Qualcomm | AC20: =AC19 -> Mobile
E21: Qualcomm Sub Total | L21: =SUM(L15:L20) -> 23304.478 | M21: =SUM(M15:M20) -> 9621.2676 | N21: =SUM(N15:N20) -> 20797.636 | O21: =SUM(O15:O20) -> 21641.999 | P21: =SUM(P15:P20) -> 18759.846 | Q21: =SUM(Q15:Q20) -> 20666.409 | R21: =SUM(R15:R20) -> 22516.409 | S21: =SUM(S15:S20) -> 20716.409 | ... W21: =SUM(W15:W20) -> 15933.205 | X21: =SUM(L21:W21) -> 232273.68 | Y21: =X21=SUM(L21:W21) -> TRUE
C22: Mobile Sub-Total | L22: =SUM(L21+L14) -> 1963665.5 | M22: =SUM(M21+M14) -> 1591342.3 | N22: =SUM(N21+N14) -> 1712076.6 | O22: =SUM(O21+O14) -> 1469525 | P22: =SUM(P21+P14) -> 1637045.8 | Q22: =SUM(Q21+Q14) -> 2499666.4 | R22: =SUM(R21+R14) -> 2802516.4 | S22: =SUM(S21+S14) -> 2887216.4 | ... W22: =SUM(W21+W14) -> 2110933.2 | X22: =SUM(L22:W22) -> 25020304 | Y22: =X22=SUM(L22:W22) -> TRUE
A23: 2 | B23: Automotive | C23: LGIT | D23: Motor HSG | E23: 11 | F23: GEN3 AL5 Housing (YT) | G23: 2.2135429 | L23: 38642.124 | M23: 37783.41 | N23: 54957.688 | O23: 54473.685 | P23: 47343.108 | Q23: 69934.438 | R23: 56323.823 | S23: 53208.763 | T23: 0 | U23: 0 | V23: 0 | W23: 0 | X23: =SUM(L23:W23) -> 412667.04 | AB23: LGIT | AC23: Motor HSG
E24: 12 | F24: GEN3 AL6 Housing (YT) | G24: 2.2725264 | L24: 0 | M24: 0 | N24: 3436.9501 | O24: 5550.8265 | P24: 520.07316 | Q24: 0 | R24: 0 | S24: 0 | T24: 0 | U24: 0 | V24: 0 | W24: 0 | X24: =SUM(L24:W24) -> 9507.8498 | AB24: =AB23 -> LGIT | AC24: =AC23 -> Motor HSG
F25: GEN3 AL5 Housing (MX) | G25: 2.0915656 | L25: 0 | M25: 0 | N25: 0 | O25: 0 | P25: 0 | Q25: 0 | R25: 0 | S25: 0 | T25: 0 | U25: 0 | V25: 0 | W25: 0 | X25: =SUM(L25:W25) -> 0 | AB25: =AB24 -> LGIT | AC25: =AC24 -> Motor HSG
F26: GEN3 AL6 Housing (MX) | G26: 2.2086071 | L26: 0 | M26: 0 | N26: 0 | O26: 0 | P26: 0 | Q26: 0 | R26: 0 | S26: 0 | T26: 0 | U26: 0 | V26: 0 | W26: 0 | X26: =SUM(L26:W26) -> 0 | AB26: =AB25 -> LGIT | AC26: =AC25 -> Motor HSG
F27: T6 Housing | G27: 4.226861 | L27: 0 | M27: 0 | N27: 24602.655 | O27: 12914.397 | P27: 0 | Q27: 0 | R27: 0 | S27: 0 | T27: 0 | U27: 0 | V27: 0 | W27: 0 | X27: =SUM(L27:W27) -> 37517.051 | AB27: =AB26 -> LGIT | AC27: =AC26 -> Motor HSG
E28: 13 | F28: CL4 Housing (YT) | G28: 3.3439707 | L28: 47052.918 | M28: 31690.774 | N28: 37461.345 | O28: 44492.256 | P28: 47519.124 | Q28: 28507.534 | R28: 0 | S28: 0 | T28: 0 | U28: 0 | V28: 0 | W28: 0 | X28: =SUM(L28:W28) -> 236723.95 | AB28: =AB27 -> LGIT | AC28: =AC27 -> Motor HSG
F29: CL4 Housing (MX) | G29: 3.32 | L29: 0 | M29: 19698.795 | N29: 0 | O29: 19698.795 | P29: 26807.229 | Q29: 23590.361 | R29: 19698.795 | S29: 0 | T29: 0 | X29: =SUM(L29:W29) -> 109493.98 | AB29: =AB28 -> LGIT | AC29: =AC28 -> Motor HSG
E30: 14 | F30: MQ4a PE Housing (YT) | G30: 3.3731399 | L30: 588.76894 | M30: 15896.761 | N30: 26916.553 | O30: 21502.775 | P30: 27132.204 | Q30: 10171.366 | R30: 16644.053 | S30: 30004.673 | T30: 10286.95 | U30: 0 | V30: 0 | W30: 0 | X30: =SUM(L30:W30) -> 159144.1 | AB30: =AB29 -> LGIT | AC30: =AC29 -> Motor HSG
F31: MQ4a PE Housing (MX) | G31: 3.26 | L31: 0 | M31: 19693.252 | N31: 0 | O31: 19693.252 | P31: 24763.804 | Q31: 21533.742 | R31: 19693.252 | S31: 0 | T31: 0 | X31: =SUM(L31:W31) -> 105377.3 | AB31: =AB30 -> LGIT | AC31: =AC30 -> Motor HSG
F32: BYD Housing | G32: 2.2574248 | L32: 0 | M32: 0 | N32: 0 | O32: 0 | P32: 0 | Q32: 0 | R32: 0 | S32: 0 | T32: 0 | U32: 0 | V32: 0 | W32: 0 | X32: =SUM(L32:W32) -> 0 | AB32: =AB31 -> LGIT | AC32: =AC31 -> Motor HSG
E33: 15 | F33: MX5 Housing | G33: 4.59 | L33: 0 | M33: 0 | N33: 0 | O33: 0 | P33: 0 | Q33: 0 | R33: 0 | S33: 0 | T33: 0 | U33: 0 | V33: 0 | W33: 0 | X33: =SUM(L33:W33) -> 0 | AB33: =AB32 -> LGIT | AC33: =AC32 -> Motor HSG
E34: Motor HSG Sub Total | L34: =SUM(L23:L31) -> 86283.811 | M34: =SUM(M23:M31) -> 124762.99 | N34: =SUM(N23:N31) -> 147375.19 | O34: =SUM(O23:O31) -> 178325.99 | P34: =SUM(P23:P31) -> 174085.54 | Q34: =SUM(Q23:Q31) -> 153737.44 | R34: =SUM(R23:R31) -> 112359.92 | S34: =SUM(S23:S31) -> 83213.436 | ... W34: =SUM(W23:W31) -> 0 | X34: =SUM(X23:X33) -> 1070431.3 | Y34: =X34=SUM(L34:W34) -> TRUE
D35: Motor CVR | F35: Gen2 Cover | G35: 2.1305741 | L35: 3579.0354 | M35: 0 | N35: 0 | O35: 0 | R35: 21960.081 | S35: 0 | T35: 0 | U35: 0 | V35: 0 | W35: 0 | X35: =SUM(L35:W35) -> 25539.117 | AB35: =AB33 -> LGIT | AC35: Motor CVR
F36: T6 Cover | G36: 1.2189326 | L36: 0 | M36: 0 | N36: 14112.348 | O36: 26901.406 | P36: 0 | Q36: 0 | R36: 0 | S36: 0 | T36: 0 | U36: 0 | V36: 0 | W36: 0 | X36: =SUM(L36:W36) -> 41013.754 | AB36: =AB35 -> LGIT | AC36: =AC35 -> Motor CVR
E37: 16 | F37: EK_Part Cover | G37: 1.7131494 | L37: 20264.152 | M37: 14474.394 | N37: 13026.955 | O37: 16520.147 | P37: 18736.264 | Q37: 16520.147 | R37: 16520.147 | S37: 13528.58 | X37: =SUM(L37:W37) -> 129590.78 | AB37: =AB36 -> LGIT | AC37: =AC36 -> Motor CVR
F38: 570W Cover | G38: 1.93 | L38: 0 | M38: 0 | N38: 0 | O38: 0 | P38: 0 | Q38: 0 | R38: 0 | S38: 0 | T38: 0 | U38: 0 | V38: 0 | W38: 0 | X38: =SUM(L38:W38) -> 0 | AB38: =AB37 -> LGIT | AC38: =AC37 -> Motor CVR
E39: 17 | F39: CL4 Cover (YT) | G39: 1.3549204 | L39: 7552.473 | M39: 18888.681 | N39: 19225.926 | O39: 7460.8071 | P39: 13586.038 | Q39: 12319.543 | R39: 0 | S39: 0 | T39: 0 | U39: 0 | V39: 0 | W39: 0 | X39: =SUM(L39:W39) -> 79033.467 | AB39: =AB38 -> LGIT | AC39: =AC38 -> Motor CVR
F40: CL4 Cover (MX) | G40: 1.34 | L40: 0 | M40: 19701.493 | N40: 0 | O40: 19701.493 | P40: 21720.896 | Q40: 25539.866 | R40: 30461.463 | S40: 0 | X40: =SUM(L40:W40) -> 117125.21 | AB40: =AB39 -> LGIT | AC40: =AC39 -> Motor CVR
E41: 18 | F41: MQ4a PE Cover (YT) | G41: 1.4397683 | L41: 2383.7168 | M41: 15977.57 | N41: 25564.112 | O41: 16562.664 | P41: 29524.75 | Q41: 29524.75 | R41: 29524.75 | S41: 16357.076 | T41: 0 | U41: 0 | V41: 0 | W41: 0 | X41: =SUM(L41:W41) -> 165419.39 | AB41: =AB40 -> LGIT | AC41: =AC40 -> Motor CVR
F42: MQ4a PE Cover (MX) | G42: 1.42 | L42: 0 | M42: 19718.31 | N42: 0 | O42: 19718.31 | P42: 26239.437 | Q42: 22816.901 | R42: 19718.31 | S42: 0 | X42: =SUM(L42:W42) -> 108211.27 | AB42: =AB41 -> LGIT | AC42: =AC41 -> Motor CVR
F43: BYD Cover | G43: 2.44736 | L43: 0 | M43: 0 | N43: 0 | O43: 0 | P43: 0 | Q43: 0 | R43: 0 | S43: 0 | T43: 0 | U43: 0 | V43: 0 | W43: 0 | X43: =SUM(L43:W43) -> 0 | AB43: =AB42 -> LGIT | AC43: =AC42 -> Motor CVR
E44: 19 | F44: MX5 Cover | G44: 1.22 | L44: 0 | M44: 0 | N44: 0 | O44: 0 | P44: 0 | Q44: 0 | R44: 0 | S44: 0 | T44: 0 | U44: 0 | V44: 0 | W44: 0 | X44: =SUM(L44:W44) -> 0 | AB44: =AB43 -> LGIT | AC44: =AC43 -> Motor CVR
E45: Motor CVR Sub Total | L45: =SUM(L35:L42) -> 33779.377 | M45: =SUM(M35:M42) -> 88760.448 | N45: =SUM(N35:N42) -> 71929.341 | O45: =SUM(O35:O42) -> 106864.83 | P45: =SUM(P35:P42) -> 109807.38 | Q45: =SUM(Q35:Q42) -> 106721.21 | R45: =SUM(R35:R42) -> 118184.75 | S45: =SUM(S35:S42) -> 29885.656 | ... W45: =SUM(W35:W42) -> 0 | X45: =SUM(X35:X44) -> 665932.99 | Y45: =X45=SUM(L45:W45) -> TRUE
F46: FCM30-Upper Housing | G46: 1.12 | L46: 0 | M46: 0 | N46: 0 | O46: 0 | P46: 0 | Q46: 0 | R46: 0 | S46: 0 | T46: 0 | U46: 0 | V46: 0 | W46: 0 | X46: =SUM(L46:W46) -> 0 | AB46: =AB44 -> LGIT | AC46: CAM HSG
D47: CAM HSG | E47: 20 | F47: DCU15 Housing | G47: 0.6942093 | L47: 22840.405 | M47: 26812.649 | N47: 64548.97 | O47: 65000 | Q47: 23000 | R47: 23000 | S47: 23000 | T47: 22250 | U47: 22250 | V47: 22250 | W47: 22250 | X47: =SUM(L47:W47) -> 337202.02 | AB47: =AB46 -> LGIT | AC47: =AC46 -> CAM HSG
E48: CAM HSG Sub Total | L48: =SUM(L47) -> 22840.405 | M48: =SUM(M47) -> 26812.649 | N48: =SUM(N47) -> 64548.97 | O48: =SUM(O47) -> 65000 | P48: =SUM(P47) -> 0 | Q48: =SUM(Q47) -> 23000 | R48: =SUM(R47) -> 23000 | S48: =SUM(S47) -> 23000 | ... X48: =SUM(X47) -> 337202.02 | Y48: =X48=SUM(L48:W48) -> TRUE
D49: CAM CVR | E49: 21 | F49: DCU15 Cover | G49: 0.48871134 | L49: 22838.071 | M49: 26809.909 | N49: 64542.374 | O49: 65000 | Q49: 23000 | R49: 23000 | S49: 23000 | T49: 22250 | U49: 22250 | V49: 22250 | W49: 22250 | X49: =SUM(L49:W49) -> 337190.35 | AB49: =AB47 -> LGIT | AC49: CAM CVR
F50: FCM30-Lower Housing | G50: 0.53 | L50: 0 | M50: 0 | N50: 0 | O50: 0 | P50: 0 | Q50: 0 | R50: 0 | S50: 0 | T50: 0 | U50: 0 | V50: 0 | W50: 0 | X50: =SUM(L50:W50) -> 0 | AB50: =AB49 -> LGIT | AC50: =AC49 -> CAM CVR
F51: OMS Entry Vcsel Cover(250A) | G51: 0.69273636 | L51: 0 | M51: 0 | N51: 0 | O51: 0 | P51: 0 | Q51: 0 | R51: 0 | S51: 0 | T51: 0 | U51: 0 | V51: 0 | W51: 0 | X51: =SUM(L51:W51) -> 0 | AB51: =AB50 -> LGIT | AC51: =AC50 -> CAM CVR
F52: HKMC Ikc Camera Base | G52: 3.3562 | L52: 1656 | M52: 0 | N52: 171 | O52: 1109 | Q52: 1607 | R52: 0 | S52: 0 | T52: 0 | U52: 0 | V52: 0 | W52: 0 | X52: =SUM(L52:W52) -> 4543 | AB52: =AB51 -> LGIT | AC52: =AC51 -> CAM CVR
F53: MRA2 | G53: 1.53229 | P53: 4965 | Q53: 4579 | R53: 3150 | X53: =SUM(L53:W53) -> 12694
E54: CAM CVR Sub Total | L54: =SUM(L49:L52) -> 24494.071 | M54: =SUM(M49:M52) -> 26809.909 | N54: =SUM(N49:N52) -> 64713.374 | O54: =SUM(O49:O53) -> 66109 | P54: =SUM(P49:P53) -> 4965 | Q54: =SUM(Q49:Q53) -> 29186 | R54: =SUM(R49:R53) -> 26150 | S54: =SUM(S49:S53) -> 23000 | T54: =SUM(T49:T53) -> 22250 | U54: =SUM(U49:U53) -> 22250 | V54: =SUM(V49:V53) -> 22250 | ... X54: =SUM(X49:X53) -> 354427.35 | Y54: =X54=SUM(L54:W54) -> TRUE
F55: OMS Entry Lens Holder (203A) | G55: 0.53564 | L55: 0 | M55: 0 | N55: 0 | O55: 0 | P55: 0 | Q55: 0 | R55: 0 | S55: 0 | T55: 0 | U55: 0 | V55: 0 | W55: 0 | X55: =SUM(L55:W55) -> 0 | AB55: =AB52 -> LGIT | AC55: CAM L.Mount
F56: OMS Front Lens Holder (207A) | G56: 0.72166 | L56: 0 | M56: 0 | N56: 0 | O56: 0 | P56: 64800 | Q56: 82850 | R56: 82850 | S56: 82850 | T56: 82850 | U56: 82850 | V56: 82850 | W56: 82850 | X56: =SUM(L56:W56) -> 644750 | AB56: =AB55 -> LGIT | AC56: =AC55 -> CAM L.Mount
D57: CAM L.Mount | E57: 22 | F57: MPC5.5 Cover Lens | G57: 0.881 | L57: 145774.23 | M57: 80811.176 | N57: 145774.23 | O57: 119959.14 | P57: 64777.934 | Q57: 82821.788 | R57: 82821.788 | S57: 82821.788 | T57: 82821.788 | U57: 82821.788 | V57: 82821.788 | W57: 82821.788 | X57: =SUM(L57:W57) -> 1136849.2 | AB57: =AB56 -> LGIT | AC57: =AC56 -> CAM L.Mount
F58: FCM30 Lens Holder | G58: 0.67 | L58: 0 | M58: 0 | N58: 0 | O58: 0 | P58: 0 | Q58: 0 | R58: 0 | S58: 0 | T58: 0 | U58: 0 | V58: 0 | W58: 0 | X58: =SUM(L58:W58) -> 0 | AB58: =AB57 -> LGIT | AC58: =AC57 -> CAM L.Mount
E59: CAM L.Mount Sub Total | L59: =SUM(L57) -> 145774.23 | M59: =SUM(M57) -> 80811.176 | N59: =SUM(N57) -> 145774.23 | O59: =SUM(O57) -> 119959.14 | P59: =SUM(P57) -> 64777.934 | Q59: =SUM(Q57) -> 82821.788 | R59: =SUM(R57) -> 82821.788 | S59: =SUM(S57) -> 82821.788 | ... W59: =SUM(W57) -> 82821.788 | X59: =SUM(X57:X58) -> 1136849.2 | Y59: =X59=SUM(L59:W59) -> TRUE
D60: LGIT Sub total | L60: =SUM(L59+L54+L48+L45+L34) -> 313171.89 | M60: =SUM(M59+M54+M48+M45+M34) -> 347957.17 | N60: =SUM(N59+N54+N48+N45+N34) -> 494341.1 | O60: =SUM(O59+O54+O48+O45+O34) -> 536258.95 | P60: =SUM(P59+P54+P48+P45+P34) -> 353635.86 | Q60: =SUM(Q59+Q54+Q48+Q45+Q34) -> 395466.44 | R60: =SUM(R59+R54+R48+R45+R34) -> 362516.46 | S60: =SUM(S59+S54+S48+S45+S34) -> 241920.88 | ... X60: =SUM(X59+X54+X48+X45+X34) -> 3564842.9
C61: Mando | D61: Motor HSG | E61: 23 | F61: NX4 HSG | G61: 3.82 | L61: 30138.691 | M61: 55488.953 | N61: 53003.56 | O61: 42198.953 | T61: 49000 | U61: 49000 | V61: 37000 | W61: 37000 | X61: =SUM(L61:W61) -> 352830.16 | AB61: Mando | AC61: Motor HSG
E62: 24 | F62: IMEB2 Housing | G62: 2.66 | L62: 42516.812 | M62: 28167.699 | N62: 45496.421 | O62: 40302.677 | P62: 42472.421 | Q62: 44064 | R62: 44000 | S62: 42000 | T62: 48000 | U62: 40000 | V62: 41500 | W62: 41500 | X62: =SUM(L62:W62) -> 500020.03 | AB62: =AB61 -> Mando | AC62: =AC61 -> Motor HSG
E63: 25 | F63: J100 Housing | G63: 3.78 | L63: 5040 | M63: 5287 | N63: 0 | O63: 10466.667 | P63: 6250 | Q63: 6500 | R63: 6500 | S63: 6500 | T63: 6500 | U63: 8550 | V63: 5700 | W63: 5700 | X63: =SUM(L63:W63) -> 72993.667 | AB63: =AB62 -> Mando | AC63: =AC62 -> Motor HSG
F64: BENZ R-EPS HSG (Anodizing) | G64: 5.28 | L64: 0 | M64: 0 | N64: 0 | O64: 0 | P64: 0 | Q64: 0 | R64: 0 | S64: 0 | T64: 0 | U64: 0 | V64: 0 | W64: 0 | X64: =SUM(L64:W64) -> 0 | AB64: =AB63 -> Mando | AC64: =AC63 -> Motor HSG
F65: NE2 R-EPS HSG | G65: 4 | L65: 0 | M65: 0 | N65: 0 | O65: 0 | P65: 0 | Q65: 0 | R65: 0 | S65: 0 | T65: 0 | U65: 0 | V65: 0 | W65: 0 | X65: =SUM(L65:W65) -> 0 | AB65: =AB64 -> Mando | AC65: =AC64 -> Motor HSG
F66: M184 R-EPS HSG | G66: 5.94 | L66: 0 | M66: 0 | N66: 0 | O66: 0 | P66: 0 | Q66: 0 | R66: 0 | S66: 0 | T66: 0 | U66: 0 | V66: 0 | W66: 0 | X66: =SUM(L66:W66) -> 0 | AB66: =AB65 -> Mando | AC66: =AC65 -> Motor HSG
E67: Motor HSG Sub Total | L67: =SUM(L61:L63) -> 77695.503 | M67: =SUM(M61:M63) -> 88943.652 | N67: =SUM(N61:N63) -> 98499.981 | O67: =SUM(O61:O63) -> 92968.296 | P67: =SUM(P61:P63) -> 48722.421 | Q67: =SUM(Q61:Q63) -> 50564 | R67: =SUM(R61:R63) -> 50500 | S67: =SUM(S61:S63) -> 48500 | ... X67: =SUM(X61:X63) -> 925843.85
D68: Motor CVR | E68: 26 | F68: NX4 Cover | G68: 1.41 | L68: 74396.496 | M68: 111262.98 | N68: 120727.6 | O68: 56404.965 | P68: 29167.66 | Q68: 30668.936 | R68: 32170.213 | S68: 16085.106 | T68: 16085.106 | U68: 16085.106 | V68: 16085.106 | W68: 16085.106 | X68: =SUM(L68:W68) -> 535224.38 | AB68: =AB66 -> Mando | AC68: Motor CVR
E69: 27 | F69: Tey Gen4 Cover | G69: 1.74 | L69: 91965.517 | M69: 78122.759 | N69: 93413.793 | O69: 77009.609 | P69: 84248.276 | Q69: 93792.874 | R69: 81586.207 | S69: 79643.678 | T69: 81586.207 | U69: 79643.678 | V69: 79643.678 | W69: 79643.678 | X69: =SUM(L69:W69) -> 1000300 | AB69: =AB68 -> Mando | AC69: =AC68 -> Motor CVR
E70: 28 | F70: CEER RWA CVR-만도향 | G70: 2.97 | L70: 0 | M70: 0 | N70: 0 | O70: 0 | P70: 0 | Q70: 0 | R70: 0 | S70: 0 | T70: 0 | U70: 0 | V70: 0 | W70: 0 | X70: =SUM(L70:W70) -> 0 | AB70: =AB69 -> Mando | AC70: =AC69 -> Motor CVR
E71: 29 | F71: CEER RWS CVR-만도향 | G71: 2.86 | L71: 0 | M71: 0 | N71: 0 | O71: 0 | P71: 0 | Q71: 0 | R71: 0 | S71: 0 | T71: 0 | U71: 0 | W71: 3333 | X71: =SUM(L71:W71) -> 3333 | AB71: =AB70 -> Mando | AC71: =AC70 -> Motor CVR
E72: 30 | F72: JG R-EPS CVR-만도향 | G72: 2.69 | L72: 0 | M72: 0 | N72: 0 | O72: 3862.0818 | Q72: 2351.3011 | R72: 2821.5613 | S72: 1881.0409 | T72: 1881.0409 | U72: 1692.9368 | V72: 1128.6245 | W72: 0 | X72: =SUM(L72:W72) -> 15618.587 | AB72: =AB71 -> Mando | AC72: =AC71 -> Motor CVR
F73: US Cover | G73: 2.63 | X73: =SUM(L73:W73) -> 0
E74: 31 | F74: JG RWS CVR-만도향 | G74: 2.86 | L74: 0 | M74: 0 | N74: 0 | O74: 269.05594 | P74: 0 | Q74: 0 | S74: 0 | T74: 0 | U74: 0 | V74: 0 | W74: 0 | X74: =SUM(L74:W74) -> 269.05594 | AB74: =AB72 -> Mando | AC74: =AC72 -> Motor CVR
E75: Motor CVR Sub Total | L75: =SUM(L68:L74) -> 166362.01 | M75: =SUM(M68:M74) -> 189385.74 | N75: =SUM(N68:N74) -> 214141.4 | O75: =SUM(O68:O74) -> 137545.71 | P75: =SUM(P68:P74) -> 113415.94 | Q75: =SUM(Q68:Q74) -> 126813.11 | R75: =SUM(R68:R74) -> 116577.98 | S75: =SUM(S68:S74) -> 97609.825 | ... X75: =SUM(X68:X74) -> 1554745
D76: Heatsink | E76: 32 | F76: MAS65 Heatsink Cover | G76: 1.1526911 | L76: 95545.943 | M76: 64304.617 | N76: 64304.617 | O76: 96456.925 | P76: 64304.617 | Q76: 92820.652 | R76: 95978.468 | S76: 64304.617 | T76: 64304.617 | U76: 64304.617 | V76: 64304.617 | W76: 64304.617 | X76: =SUM(L76:W76) -> 895238.92 | AB76: =AB74 -> Mando | AC76: Heatsink
E77: Heatsink Sub Total | L77: =SUM(L76) -> 95545.943 | M77: =SUM(M76) -> 64304.617 | N77: =SUM(N76) -> 64304.617 | O77: =SUM(O76) -> 96456.925 | P77: =SUM(P76) -> 64304.617 | Q77: =SUM(Q76) -> 92820.652 | R77: =SUM(R76) -> 95978.468 | S77: =SUM(S76) -> 64304.617 | ... W77: =SUM(W76) -> 64304.617 | X77: =SUM(L77:W77) -> 895238.92
D78: Mando Sub total | L78: =SUM(L75+L67+L77) -> 339603.46 | M78: =SUM(M75+M67+M77) -> 342634.01 | N78: =SUM(N75+N67+N77) -> 376945.99 | O78: =SUM(O75+O67+O77) -> 326970.93 | P78: =SUM(P75+P67+P77) -> 226442.97 | Q78: =SUM(Q75+Q67+Q77) -> 270197.76 | R78: =SUM(R75+R67+R77) -> 263056.45 | S78: =SUM(S75+S67+S77) -> 210414.44 | ... W78: =SUM(W75+W67+W77) -> 247566.4 | X78: =SUM(X77+X75+X67) -> 3375827.8 | Y78: =X78=SUM(L78:W78) -> TRUE
C79: ZF TRW | D79: Motor HSG | E79: 33 | F79: FCA Housing | G79: 1.2501192 | L79: 51756.898 | M79: 51756.898 | N79: 53673.82 | O79: 71765.515 | P79: 122392.08 | Q79: 59715.489 | R79: 46148.928 | S79: 46148.928 | T79: 46148.928 | U79: 46148.928 | V79: 46148.928 | W79: 46148.928 | X79: =SUM(L79:W79) -> 687954.26 | AB79: ZF TRW | AC79: Motor HSG
E80: 34 | F80: GM EU2L Housing | G80: 1.3520535 | L80: 49889.092 | M80: 43791.058 | N80: 55383.36 | O80: 7847.3758 | P80: 78172.7 | Q80: 31246.494 | R80: 52028.956 | S80: 36405.709 | T80: 35208.771 | U80: 35208.771 | V80: 35208.771 | W80: 36405.709 | X80: =SUM(L80:W80) -> 496796.77 | AB80: =AB79 -> ZF TRW | AC80: =AC79 -> Motor HSG
E81: 35 | F81: GM ACP Housing | G81: 1.7954715 | L81: 116257.05 | M81: 0 | N81: 151469.97 | O81: 18369.932 | P81: 36377.915 | Q81: 46812.411 | R81: 99935.192 | S81: 79135.152 | T81: 118105.73 | U81: 118105.73 | V81: 111554.83 | W81: 116953.41 | X81: =SUM(L81:W81) -> 1013077.3 | AB81: =AB80 -> ZF TRW | AC81: =AC80 -> Motor HSG
E82: Motor HSG sub Total | L82: =SUM(L79:L81) -> 217903.04 | M82: =SUM(M79:M81) -> 95547.956 | N82: =SUM(N79:N81) -> 260527.15 | O82: =SUM(O79:O81) -> 97982.823 | P82: =SUM(P79:P81) -> 236942.69 | Q82: =SUM(Q79:Q81) -> 137774.39 | R82: =SUM(R79:R81) -> 198113.08 | S82: =SUM(S79:S81) -> 161689.79 | ... X82: =SUM(X79:X81) -> 2197828.4
D83: Motor CVR | E83: 36 | F83: FCA Cover | G83: 1.1179262 | L83: 51791.726 | M83: 51791.726 | N83: 51791.726 | O83: 45660.675 | P83: 97757.02 | Q83: 59142.997 | R83: 45706.499 | S83: 45706.499 | T83: 45706.499 | U83: 45706.499 | V83: 45706.499 | W83: 45706.499 | X83: =SUM(L83:W83) -> 632174.86 | AB83: =AB81 -> ZF TRW | AC83: Motor CVR
E84: 37 | F84: GM EU2L Cover | G84: 1.1947816 | L84: 48660.2 | M84: 42775.266 | N84: 54544.299 | O84: 7881.2603 | P84: 76421.187 | Q84: 55257.88 | R84: 60484.847 | S84: 60484.847 | T84: 59272.19 | U84: 59272.19 | V84: 59272.19 | W84: 60484.847 | X84: =SUM(L84:W84) -> 644811.2 | AB84: =AB83 -> ZF TRW | AC84: =AC83 -> Motor CVR
E85: 38 | F85: GM ACP Cover | G85: 1.2052491 | L85: 115318.31 | M85: 0 | N85: 149757.17 | O85: 19667.782 | P85: 36296.196 | Q85: 47626.733 | R85: 100200.33 | S85: 79753.9 | T85: 117588.78 | U85: 117588.78 | V85: 111149.25 | W85: 116929.24 | X85: =SUM(L85:W85) -> 1011876.5 | AB85: =AB84 -> ZF TRW | AC85: =AC84 -> Motor CVR
E86: Motor CVR sub Total | L86: =SUM(L83:L85) -> 215770.24 | M86: =SUM(M83:M85) -> 94566.993 | N86: =SUM(N83:N85) -> 256093.2 | O86: =SUM(O83:O85) -> 73209.717 | P86: =SUM(P83:P85) -> 210474.4 | Q86: =SUM(Q83:Q85) -> 162027.61 | R86: =SUM(R83:R85) -> 206391.68 | S86: =SUM(S83:S85) -> 185945.24 | ... X86: =SUM(X83:X85) -> 2288862.5
D87: CAM L.Mount | E87: 39 | F87: Lens Mount | G87: 0.57168921 | L87: 146877.59 | M87: 170837.55 | N87: 178300.28 | O87: 143647.24 | P87: 271009 | Q87: 141587.97 | R87: 221410.19 | S87: 226455.2 | T87: 223399.15 | U87: 218354.14 | V87: 210226.36 | W87: 210226.36 | X87: =SUM(L87:W87) -> 2362331 | AB87: =AB85 -> ZF TRW | AC87: CAM L.Mount
D88: Heatsink | E88: 40 | F88: IPM 1.0 Housing | G88: 3.6863181 | L88: 10396.982 | M88: 9819.3723 | N88: 10974.593 | O88: 15924.59 | P88: 14155.191 | Q88: 17104.189 | R88: 14302.641 | S88: 14302.641 | T88: 14302.641 | U88: 14302.641 | V88: 14302.641 | W88: 14302.641 | X88: =SUM(L88:W88) -> 164190.76 | AB88: =AB87 -> ZF TRW | AC88: Heatsink
E89: 41 | F89: IPM 2.0 Base Housing | G89: 5.1493138 | L89: 3898.2831 | M89: 1436.2096 | N89: 4308.6287 | O89: 4578.7079 | P89: 6576.7881 | Q89: 5115.2796 | R89: 7307.5423 | S89: 5846.0339 | T89: 5846.0339 | U89: 5846.0339 | V89: 4384.5254 | W89: 4384.5254 | X89: =SUM(L89:W89) -> 59528.592 | AB89: =AB88 -> ZF TRW | AC89: =AC88 -> Heatsink
F90: IPM 2.0 Advanced HSG | G90: 5.25 | L90: 0 | M90: 0 | N90: 0 | O90: 0 | P90: 0 | Q90: 0 | R90: 0 | S90: 0 | T90: 0 | U90: 0 | V90: 0 | W90: 0 | X90: =SUM(L90:W90) -> 0 | AB90: =AB89 -> ZF TRW | AC90: =AC89 -> Heatsink
F91: IPM 2.0 HSG Base+ | G91: 4.79 | L91: 0 | M91: 0 | N91: 0 | O91: 0 | P91: 0 | Q91: 0 | R91: 0 | S91: 0 | T91: 0 | U91: 0 | V91: 0 | W91: 0 | X91: =SUM(L91:W91) -> 0 | AB91: =AB90 -> ZF TRW | AC91: =AC90 -> Heatsink
F92: IPM 2.0 HSG Premium | G92: 5.02 | L92: 0 | M92: 0 | N92: 0 | O92: 0 | P92: 0 | Q92: 0 | R92: 0 | S92: 0 | T92: 0 | U92: 0 | V92: 0 | W92: 0 | X92: =SUM(L92:W92) -> 0 | AB92: =AB91 -> ZF TRW | AC92: =AC91 -> Heatsink
E93: CAM L.Mount Sub Total | L93: =SUM(L87:L89) -> 161172.86 | M93: =SUM(M87:M89) -> 182093.13 | N93: =SUM(N87:N89) -> 193583.5 | O93: =SUM(O87:O89) -> 164150.54 | P93: =SUM(P87:P89) -> 291740.97 | Q93: =SUM(Q87:Q89) -> 163807.44 | R93: =SUM(R87:R89) -> 243020.37 | S93: =SUM(S87:S89) -> 246603.88 | ... X93: =SUM(X87:X89) -> 2586050.4
D94: ZF Sub total | L94: =SUM(L93+L86+L82) -> 594846.14 | M94: =SUM(M93+M86+M82) -> 372208.08 | N94: =SUM(N93+N86+N82) -> 710203.85 | O94: =SUM(O93+O86+O82) -> 335343.08 | P94: =SUM(P93+P86+P82) -> 739158.07 | Q94: =SUM(Q93+Q86+Q82) -> 463609.44 | R94: =SUM(R93+R86+R82) -> 647525.13 | S94: =SUM(S93+S86+S82) -> 594238.91 | ... X94: =SUM(X93+X86+X82) -> 7072741.3 | Y94: =X94-SUM(L94:W94) -> 0
C95: A | F95: Glass Frame (ZF60A-T5) | G95: 213.8 | L95: 0 | M95: 7.2684752 | N95: 0 | O95: 90.503274 | P95: 15 | S95: 77.17493 | T95: 115.76239 | U95: 77.17493 | V95: 77.17493 | W95: 77.17493 | X95: =SUM(L95:W95) -> 537.23386 | AB95: A | AC95: Cover
F96: Body Compute enclosure (AL6061-T6) | G96: 213.8 | L96: 0 | M96: 7.7315248 | N96: 67.291862 | O96: 0 | P96: 0 | Q96: 0 | R96: 0 | S96: 0 | T96: 0 | U96: 0 | V96: 0 | W96: 0 | X96: =SUM(L96:W96) -> 75.023386 | AB96: =#REF! -> #REF! | AC96: =#REF! -> #REF!
F97: Others Part | G97: 76 | M97: 66.61039 | N97: 2525.6623 | O97: 2449.5758 | P97: 2180 | Q97: 10.942105 | S97: 75 | T97: 75 | U97: 75 | V97: 75 | W97: 75 | X97: =SUM(L97:W97) -> 7607.7906 | AB97: A | AC97: Cover
X98: =SUM(L98:W98) -> 0 | AB98: A | AC98: Cover
X99: =SUM(L99:W99) -> 0 | AB99: A | AC99: Cover
X100: =SUM(L100:W100) -> 0 | AB100: A | AC100: Cover
...

Sheet 요약
A1: Basic Assumption (Expense)
A3: 5) 관리
A4: No. | B4: 담당부서 | C4: 주제 | D4: Category | E4: Content | F4: Remarks
A5: 1 | B5: EM | C5: S Plan | D5: 매출 계획 재 확인 | E5: - 각 고객사 2025년 SOP 최신 데이터 입수 후 반영 - T6 멕시코향 기존 3분기 시작 → 2분기 시작으로 변경 CL4 '24년 수량 수준 반영 (기존 월 4.8만개 → 6만개) IMEB2 고객사로부터 증량 수량 수취 (기존 월 2.9만개 → 4.2만개) 삼성 A26, A36 수주 건 (월 30만개(2벌) 기준)
D6: 개발 중 제품 | E6: - 고객사 및 품명 : LGIT eK Cover - 양산 기간 : 25년 하반기 ~ 2031년 - 총 매출 : $1,748,858
A7: 2 | B7: Production Plan | C7: P Plan | D7: 125Ton 부족 | E7: 125ton 부족으로 예상되어 현재 양산중인 125Ton 제품 350Ton으로 변경 필요
D8: MCT 부족 | E8: 4월 T6 Mexico 향 신규 물량 수주로 기존 6월 추가 5대 구매 계획 4월로 변경 필요
A9: 3 | B9: Production Plan, EM | C9: P Plan-2 | D9: 예상 금형 제작 벌 수 | E9: - 사내 제작 : $835,807 (79set) - 외주 제작 : $492,370 (20set - 한국) + $53,500 (5set - 베트남) - 합계 : $1,328,177 (104set)
A10: 4 | B10: Production, Production Plan, Quality, Finance | C10: L Plan | D10: 고객사별 인원 | E10: - 삼성 제품 생산을 위한 직접 인력: 103명 - LG/Mando/Hyosung 제품 생산을 위한 직접 인력: 303명 - ZF 제품 생산을 위한 직접 인력: 180명 | F10: 586명
D11: 오피스 인원 | E11: 2024년 90명, 2025년 70명으로 축소
D12: CNC 자동화 | E12: - CNC 선반 + MCT 자동화 도입 (1X3)+(1X2) - CNC 자동화(1X6) - 다관절 로봇타입 - 세척 및 검사 결합라인 등을 통한 인력절감
D13: 사상 자동화 | E13: - 하우징/ 플레이트 사상 자동화 도입으로 인원절감 추진 - 카메라류/브라캣 류 사상 자동화 도입 - 브라캣류 열정형 자동화 진행
D14: 비용 절감 (품질팀) | E14: - 검사 인원 축소 (152명 → 87명, 43% 인원절감) - 외관 한도 완화 : AUTO 제품 4% 폐기 비용 절감
A15: 5 | B15: Production Plan | C15: M Plan | D15: 내부 리사이클 진행 | E15: - 내부 리사이클 진행 예정으로, 리사이클링 비용 삭제 - 신재 52% 재생 48% 유지하되, 신재 사용 절감 방안 지속 강구
A16: 6 | B16: Production Plan | C16: O Plan | D16: 외주 진행 | E16: - 아노다이징 및 퀄컴 외주 외 100% 내부 진행
A17: 7 | B17: Finance | C17: E Plan
A22: 8 | B22: Automation | C22: I Plan
A27: 9 | B27: Finance | C27: C Plan

Sheet SOP 2024
A1: Customer | B1: Model | C1: PART NO. | D1: 2024-Q1 Unit Price | E1: 2024-Q2 Unit Price | F1: 2024-Q3 Unit Price | G1: 2024-Q4 Unit Price | H1: 2025 Unit Price | I1: 2026 Unit Price | J1: 2027 Unit Price | K1: 2028 Unit Price | M1: 2024 Quantity | Z1: 2024 Amount (USD) | AM1: 2025 Quantity | AZ1: 2025 Amount (USD) | BM1: 2026 Quantity | BZ1: 2026 Amount (USD) | CM1: 2027 Quantity | CZ1: 2027 Amount (USD) | DM1: 2028 Quantity | DZ1: 2028 Amount (USD)
M2: Jan | N2: Feb | O2: Mar | P2: Apr | Q2: May | R2: Jun | S2: Jul | T2: Aug | U2: Sep | V2: Oct | W2: Nov | X2: Dec | Y2: Total 2024 | Z2: 45293 | AA2: 45324 | AB2: 45353 | AC2: 45384 | AD2: 45414 | AE2: 45445 | AF2: 45475 | AG2: 45506 | AH2: 45537 | AI2: 45567 | AJ2: 45598 | AK2: 45628 | AL2: Total 2024 | AM2: Jan | AN2: Feb | AO2: Mar | AP2: Apr | AQ2: May | AR2: Jun | AS2: Jul | AT2: Aug | AU2: Sep | AV2: Oct | AW2: Nov | AX2: Dec | AY2: Total 2025 | AZ2: Jan | BA2: Feb | BB2: Mar | BC2: Apr | BD2: May | BE2: Jun | BF2: Jul | BG2: Aug | BH2: Sep | BI2: Oct | BJ2: Nov | BK2: Dec | BL2: Total 2025 | BM2: Jan | BN2: Feb | BO2: Mar | BP2: Apr | BQ2: May | BR2: Jun | BS2: Jul | BT2: Aug | BU2: Sep | BV2: Oct | BW2: Nov | BX2: Dec | BY2: Total 2026 | BZ2: Jan | CA2: Feb | CB2: Mar | CC2: Apr | CD2: May | CE2: Jun | CF2: Jul | CG2: Aug | CH2: Sep | CI2: Oct | CJ2: Nov | CK2: Dec | CL2: Total 2026 | CM2: Jan | CN2: Feb | CO2: Mar | CP2: Apr | CQ2: May | CR2: Jun | CS2: Jul | CT2: Aug | CU2: Sep | CV2: Oct | CW2: Nov | CX2: Dec | CY2: Total 2027 | CZ2: Jan | DA2: Feb | DB2: Mar | DC2: Apr | DD2: May | DE2: Jun | DF2: Jul | DG2: Aug | DH2: Sep | DI2: Oct | DJ2: Nov | DK2: Dec | DL2: Total 2027 | DM2: Jan | DN2: Feb | DO2: Mar | DP2: Apr | DQ2: May | DR2: Jun | DS2: Jul | DT2: Aug | DU2: Sep | DV2: Oct | DW2: Nov | DX2: Dec | DY2: Total 2028 | DZ2: Jan | EA2: Feb | EB2: Mar | EC2: Apr | ED2: May | EE2: Jun | EF2: Jul | EG2: Aug | EH2: Sep | EI2: Oct | EJ2: Nov | EK2: Dec | EL2: Total 2028
A3: Hosiden | B3: HEG Stand Cover | D3: 3.99 | E3: 3.578 | F3: 3.578 | G3: 3.578 | H3: =G3 -> 3.578 | I3: 3.79 | J3: 3.79 | K3: 3.79 | M3: 105000 | N3: 75000 | O3: 90000 | P3: 150000 | Q3: 200000 | R3: 250000 | S3: 250000 | T3: 230000 | U3: 130000 | V3: 130000 | W3: 130000 | X3: 130000 | Y3: =SUM(M3:X3) -> 1870000 | Z3: =M3*$D3 -> 418950 | AA3: =N3*$D3 -> 299250 | AB3: =O3*3.578 -> 322020 | AC3: =P3*3.578 -> 536700 | AD3: =17534800000/25000 -> 701392 | AE3: =R3*3.507 -> 876750 | AF3: =S3*3.778 -> 944500 | AG3: =T3*3.778 -> 868940 | AH3: =U3*3.778 -> 491140 | AI3: =V3*3.778 -> 491140 | AJ3: =W3*3.778 -> 491140 | AK3: =X3*3.778 -> 491140 | AL3: =SUM(Z3:AK3) -> 6933062 | AM3: 25000 | AN3: 25000 | AO3: 25000 | AP3: 25000 | AQ3: 25000 | AR3: 25000 | AS3: 25000 | AT3: 25000 | AU3: 25000 | AV3: 25000 | AW3: 25000 | AX3: 25000 | AY3: =SUM(AM3:AX3) -> 300000 | AZ3: =AM3*$H3 -> 89450 | BA3: =AN3*$H3 -> 89450 | BB3: =AO3*$H3 -> 89450 | BC3: =AP3*$H3 -> 89450 | BD3: =AQ3*$H3 -> 89450 | BE3: =AR3*$H3 -> 89450 | BF3: =AS3*$H3 -> 89450 | BG3: =AT3*$H3 -> 89450 | ... BK3: =AX3*$H3 -> 89450 | BL3: =SUM(AZ3:BK3) -> 1073400 | BY3: =SUM(BM3:BX3) -> 0 | BZ3: =BM3*$I3 -> 0 | CA3: =BN3*$I3 -> 0 | CB3: =BO3*$I3 -> 0 | CC3: =BP3*$I3 -> 0 | CD3: =BQ3*$I3 -> 0 | CE3: =BR3*$I3 -> 0 | CF3: =BS3*$I3 -> 0 | CG3: =BT3*$I3 -> 0 | ... CK3: =BX3*$I3 -> 0 | CL3: =SUM(BZ3:CK3) -> 0 | CY3: =SUM(CM3:CX3) -> 0 | CZ3: =CM3*$J3 -> 0 | DA3: =CN3*$J3 -> 0 | DB3: =CO3*$J3 -> 0 | DC3: =CP3*$J3 -> 0 | DD3: =CQ3*$J3 -> 0 | DE3: =CR3*$J3 -> 0 | DF3: =CS3*$J3 -> 0 | DG3: =CT3*$J3 -> 0 | ... DK3: =CX3*$J3 -> 0 | DL3: =SUM(CZ3:DK3) -> 0 | DY3: =SUM(DM3:DX3) -> 0 | DZ3: =DM3*$K3 -> 0 | EA3: =DN3*$K3 -> 0 | EB3: =DO3*$K3 -> 0 | EC3: =DP3*$K3 -> 0 | ED3: =DQ3*$K3 -> 0 | EE3: =DR3*$K3 -> 0 | EF3: =DS3*$K3 -> 0 | EG3: =DT3*$K3 -> 0 | ... EK3: =DX3*$K3 -> 0 | EL3: =SUM(DZ3:EK3) -> 0
A4: Hosiden | B4: Mold/Credit note | Y4: =SUM(M4:X4) -> 0 | Z4: =-(70333362+68963060+425415309+11353023+19844715)/24000 -> -24829.561 | AA4: =-(286963809+114084036+35604541)/24000 -> -18193.849 | AB4: 0 | AC4: =-(642) -> -642 | AD4: =-5692 -> -5692 | AE4: =-(15101) -> -15101 | AF4: =-(4506+8946) -> -13452 | AH4: =U4*$F4 -> 0 | AI4: =V4*$G4 -> 0 | AJ4: =W4*$G4 -> 0 | AK4: =X4*$G4 -> 0 | AL4: =SUM(Z4:AK4) -> -77910.411 | AY4: =SUM(AM4:AX4) -> 0 | AZ4: =AM4*$H4 -> 0 | BA4: =AN4*$H4 -> 0 | BB4: =AO4*$H4 -> 0 | BC4: =AP4*$H4 -> 0 | BD4: =AQ4*$H4 -> 0 | BE4: =AR4*$H4 -> 0 | BF4: =AS4*$H4 -> 0 | BG4: =AT4*$H4 -> 0 | ... BK4: =AX4*$H4 -> 0 | BL4: =SUM(AZ4:BK4) -> 0 | BY4: =SUM(BM4:BX4) -> 0 | BZ4: =BM4*$I4 -> 0 | CA4: =BN4*$I4 -> 0 | CB4: =BO4*$I4 -> 0 | CC4: =BP4*$I4 -> 0 | CD4: =BQ4*$I4 -> 0 | CE4: =BR4*$I4 -> 0 | CF4: =BS4*$I4 -> 0 | CG4: =BT4*$I4 -> 0 | ... CK4: =BX4*$I4 -> 0 | CL4: =SUM(BZ4:CK4) -> 0 | CY4: =SUM(CM4:CX4) -> 0 | CZ4: =CM4*$J4 -> 0 | DA4: =CN4*$J4 -> 0 | DB4: =CO4*$J4 -> 0 | DC4: =CP4*$J4 -> 0 | DD4: =CQ4*$J4 -> 0 | DE4: =CR4*$J4 -> 0 | DF4: =CS4*$J4 -> 0 | DG4: =CT4*$J4 -> 0 | ... DK4: =CX4*$J4 -> 0 | DL4: =SUM(CZ4:DK4) -> 0 | DY4: =SUM(DM4:DX4) -> 0 | DZ4: =DM4*$K4 -> 0 | EA4: =DN4*$K4 -> 0 | EB4: =DO4*$K4 -> 0 | EC4: =DP4*$K4 -> 0 | ED4: =DQ4*$K4 -> 0 | EE4: =DR4*$K4 -> 0 | EF4: =DS4*$K4 -> 0 | EG4: =DT4*$K4 -> 0 | ... EK4: =DX4*$K4 -> 0 | EL4: =SUM(DZ4:EK4) -> 0
A5: Hosiden Total | M5: =SUM(M3:M4) -> 105000 | N5: =SUM(N3:N4) -> 75000 | O5: =SUM(O3:O4) -> 90000 | P5: =SUM(P3:P4) -> 150000 | Q5: =SUM(Q3:Q4) -> 200000 | R5: =SUM(R3:R4) -> 250000 | S5: =SUM(S3:S4) -> 250000 | T5: =SUM(T3:T4) -> 230000 | ... EL5: =SUM(EL3:EL4) -> 0
A6: Samsung BRK | B6: A245 Mobase | C6: GH61-17884A | D6: 0.7448 | E6: 0.729904 | F6: 0.71530592 | G6: 0.71530592 | H6: =G6 -> 0.71530592 | M6: 71200 | Y6: =SUM(M6:X6) -> 71200 | Z6: =M6*$D6 -> 53029.76 | AA6: =N6*$D6 -> 0 | AB6: =O6*$E6 -> 0 | AC6: =P6*$E6 -> 0 | AD6: =Q6*$E6 -> 0 | AE6: =R6*$F6 -> 0 | AF6: =S6*$F6 -> 0 | AG6: =T6*$F6 -> 0 | AH6: =U6*$G6 -> 0 | AI6: =V6*$G6 -> 0 | AJ6: =W6*$G6 -> 0 | AK6: =X6*$G6 -> 0 | AL6: =SUM(Z6:AK6) -> 53029.76 | AY6: =SUM(AM6:AX6) -> 0 | AZ6: =AM6*$H6 -> 0 | BA6: =AN6*$H6 -> 0 | BB6: =AO6*$H6 -> 0 | BC6: =AP6*$H6 -> 0 | BD6: =AQ6*$H6 -> 0 | BE6: =AR6*$H6 -> 0 | BF6: =AS6*$H6 -> 0 | BG6: =AT6*$H6 -> 0 | ... BK6: =AX6*$H6 -> 0 | BL6: =SUM(AZ6:BK6) -> 0 | BY6: =SUM(BM6:BX6) -> 0 | BZ6: =BM6*$I6 -> 0 | CA6: =BN6*$I6 -> 0 | CB6: =BO6*$I6 -> 0 | CC6: =BP6*$I6 -> 0 | CD6: =BQ6*$I6 -> 0 | CE6: =BR6*$I6 -> 0 | CF6: =BS6*$I6 -> 0 | CG6: =BT6*$I6 -> 0 | ... CK6: =BX6*$I6 -> 0 | CL6: =SUM(BZ6:CK6) -> 0 | CY6: =SUM(CM6:CX6) -> 0 | CZ6: =CM6*$J6 -> 0 | DA6: =CN6*$J6 -> 0 | DB6: =CO6*$J6 -> 0 | DC6: =CP6*$J6 -> 0 | DD6: =CQ6*$J6 -> 0 | DE6: =CR6*$J6 -> 0 | DF6: =CS6*$J6 -> 0 | DG6: =CT6*$J6 -> 0 | ... DK6: =CX6*$J6 -> 0 | DL6: =SUM(CZ6:DK6) -> 0 | DY6: =SUM(DM6:DX6) -> 0 | DZ6: =DM6*$K6 -> 0 | EA6: =DN6*$K6 -> 0 | EB6: =DO6*$K6 -> 0 | EC6: =DP6*$K6 -> 0 | ED6: =DQ6*$K6 -> 0 | EE6: =DR6*$K6 -> 0 | EF6: =DS6*$K6 -> 0 | EG6: =DT6*$K6 -> 0 | ... EK6: =DX6*$K6 -> 0 | EL6: =SUM(DZ6:EK6) -> 0
A7: Samsung BRK | B7: A245 Elentec | C7: GH61-17884A | D7: 0.76350167 | E7: 0.73669388 | F7: 0.733267 | G7: 0.733267 | H7: =G7 -> 0.733267 | M7: 86400 | N7: 66800 | O7: 73800 | Y7: =SUM(M7:X7) -> 227000 | Z7: =M7*$D7 -> 65966.544 | AA7: =N7*$D7 -> 51001.911 | AB7: =O7*$E7 -> 54368.008 | AC7: =P7*$E7 -> 0 | AD7: =Q7*$E7 -> 0 | AE7: =R7*$F7 -> 0 | AF7: =S7*$F7 -> 0 | AG7: =T7*$F7 -> 0 | AH7: =U7*$G7 -> 0 | AI7: =V7*$G7 -> 0 | AJ7: =W7*$G7 -> 0 | AK7: =X7*$G7 -> 0 | AL7: =SUM(Z7:AK7) -> 171336.46 | AY7: =SUM(AM7:AX7) -> 0 | AZ7: =AM7*$H7 -> 0 | BA7: =AN7*$H7 -> 0 | BB7: =AO7*$H7 -> 0 | BC7: =AP7*$H7 -> 0 | BD7: =AQ7*$H7 -> 0 | BE7: =AR7*$H7 -> 0 | BF7: =AS7*$H7 -> 0 | BG7: =AT7*$H7 -> 0 | ... BK7: =AX7*$H7 -> 0 | BL7: =SUM(AZ7:BK7) -> 0 | BY7: =SUM(BM7:BX7) -> 0 | BZ7: =BM7*$I7 -> 0 | CA7: =BN7*$I7 -> 0 | CB7: =BO7*$I7 -> 0 | CC7: =BP7*$I7 -> 0 | CD7: =BQ7*$I7 -> 0 | CE7: =BR7*$I7 -> 0 | CF7: =BS7*$I7 -> 0 | CG7: =BT7*$I7 -> 0 | ... CK7: =BX7*$I7 -> 0 | CL7: =SUM(BZ7:CK7) -> 0 | CY7: =SUM(CM7:CX7) -> 0 | CZ7: =CM7*$J7 -> 0 | DA7: =CL4*$J7 -> 0 | DB7: =CO7*$J7 -> 0 | DC7: =CP7*$J7 -> 0 | DD7: =CQ7*$J7 -> 0 | DE7: =CR7*$J7 -> 0 | DF7: =CS7*$J7 -> 0 | DG7: =CT7*$J7 -> 0 | DH7: =CU7*$J7 -> 0 | DI7: =CV7*$J7 -> 0 | ... DK7: =CX7*$J7 -> 0 | DL7: =SUM(CZ7:DK7) -> 0 | DY7: =SUM(DM7:DX7) -> 0 | DZ7: =DM7*$K7 -> 0 | EA7: =DN7*$K7 -> 0 | EB7: =DO7*$K7 -> 0 | EC7: =DP7*$K7 -> 0 | ED7: =DQ7*$K7 -> 0 | EE7: =DR7*$K7 -> 0 | EF7: =DS7*$K7 -> 0 | EG7: =DT7*$K7 -> 0 | ... EK7: =DX7*$K7 -> 0 | EL7: =SUM(DZ7:EK7) -> 0
A8: Samsung BRK | B8: A346 Mobase | C8: GH61-17770A | D8: 0.77273 | E8: =D8*0.98 -> 0.7572754 | F8: =E8*0.98 -> 0.74212989 | G8: =F8 -> 0.74212989 | H8: =G8 -> 0.74212989 | Y8: =SUM(M8:X8) -> 0 | Z8: =M8*$D8 -> 0 | AA8: =N8*$D8 -> 0 | AB8: =O8*$E8 -> 0 | AC8: =P8*$E8 -> 0 | AD8: =Q8*$E8 -> 0 | AE8: =R8*$F8 -> 0 | AF8: =S8*$F8 -> 0 | AG8: =T8*$F8 -> 0 | AH8: =U8*$G8 -> 0 | AI8: =V8*$G8 -> 0 | AJ8: =W8*$G8 -> 0 | AK8: =X8*$G8 -> 0 | AL8: =SUM(Z8:AK8) -> 0 | AY8: =SUM(AM8:AX8) -> 0 | AZ8: =AM8*$H8 -> 0 | BA8: =AN8*$H8 -> 0 | BB8: =AO8*$H8 -> 0 | BC8: =AP8*$H8 -> 0 | BD8: =AQ8*$H8 -> 0 | BE8: =AR8*$H8 -> 0 | BF8: =AS8*$H8 -> 0 | BG8: =AT8*$H8 -> 0 | ... BK8: =AX8*$H8 -> 0 | BL8: =SUM(AZ8:BK8) -> 0 | BY8: =SUM(BM8:BX8) -> 0 | BZ8: =BM8*$I8 -> 0 | CA8: =BN8*$I8 -> 0 | CB8: =BO8*$I8 -> 0 | CC8: =BP8*$I8 -> 0 | CD8: =BQ8*$I8 -> 0 | CE8: =BR8*$I8 -> 0 | CF8: =BS8*$I8 -> 0 | CG8: =BT8*$I8 -> 0 | ... CK8: =BX8*$I8 -> 0 | CL8: =SUM(BZ8:CK8) -> 0 | CY8: =SUM(CM8:CX8) -> 0 | CZ8: =CM8*$J8 -> 0 | DA8: =CN8*$J8 -> 0 | DB8: =CO8*$J8 -> 0 | DC8: =CP8*$J8 -> 0 | DD8: =CQ8*$J8 -> 0 | DE8: =CR8*$J8 -> 0 | DF8: =CS8*$J8 -> 0 | DG8: =CT8*$J8 -> 0 | ... DK8: =CX8*$J8 -> 0 | DL8: =SUM(CZ8:DK8) -> 0 | DY8: =SUM(DM8:DX8) -> 0 | DZ8: =DM8*$K8 -> 0 | EA8: =DN8*$K8 -> 0 | EB8: =DO8*$K8 -> 0 | EC8: =DP8*$K8 -> 0 | ED8: =DQ8*$K8 -> 0 | EE8: =DR8*$K8 -> 0 | EF8: =DS8*$K8 -> 0 | EG8: =DT8*$K8 -> 0 | ... EK8: =DX8*$K8 -> 0 | EL8: =SUM(DZ8:EK8) -> 0
A9: Samsung BRK | B9: A546 Elentec | C9: GH61-17786A | D9: 0.77791583 | E9: =D9*0.98 -> 0.76235752 | F9: =E9*0.98 -> 0.74711037 | G9: =F9 -> 0.74711037 | H9: =G9 -> 0.74711037 | M9: 0 | Y9: =SUM(M9:X9) -> 0 | Z9: =M9*$D9 -> 0 | AA9: =N9*$D9 -> 0 | AB9: =O9*$E9 -> 0 | AC9: =P9*$E9 -> 0 | AD9: =Q9*$E9 -> 0 | AE9: =R9*$F9 -> 0 | AF9: =S9*$F9 -> 0 | AG9: =T9*$F9 -> 0 | AH9: =U9*$G9 -> 0 | AI9: =V9*$G9 -> 0 | AJ9: =W9*$G9 -> 0 | AK9: =X9*$G9 -> 0 | AL9: =SUM(Z9:AK9) -> 0 | AY9: =SUM(AM9:AX9) -> 0 | AZ9: =AM9*$H9 -> 0 | BA9: =AN9*$H9 -> 0 | BB9: =AO9*$H9 -> 0 | BC9: =AP9*$H9 -> 0 | BD9: =AQ9*$H9 -> 0 | BE9: =AR9*$H9 -> 0 | BF9: =AS9*$H9 -> 0 | BG9: =AT9*$H9 -> 0 | ... BK9: =AX9*$H9 -> 0 | BL9: =SUM(AZ9:BK9) -> 0 | BY9: =SUM(BM9:BX9) -> 0 | BZ9: =BM9*$I9 -> 0 | CA9: =BN9*$I9 -> 0 | CB9: =BO9*$I9 -> 0 | CC9: =BP9*$I9 -> 0 | CD9: =BQ9*$I9 -> 0 | CE9: =BR9*$I9 -> 0 | CF9: =BS9*$I9 -> 0 | CG9: =BT9*$I9 -> 0 | ... CK9: =BX9*$I9 -> 0 | CL9: =SUM(BZ9:CK9) -> 0 | CY9: =SUM(CM9:CX9) -> 0 | CZ9: =CM9*$J9 -> 0 | DA9: =CN9*$J9 -> 0 | DB9: =CO9*$J9 -> 0 | DC9: =CP9*$J9 -> 0 | DD9: =CQ9*$J9 -> 0 | DE9: =CR9*$J9 -> 0 | DF9: =CS9*$J9 -> 0 | DG9: =CT9*$J9 -> 0 | ... DK9: =CX9*$J9 -> 0 | DL9: =SUM(CZ9:DK9) -> 0 | DY9: =SUM(DM9:DX9) -> 0 | DZ9: =DM9*$K9 -> 0 | EA9: =DN9*$K9 -> 0 | EB9: =DO9*$K9 -> 0 | EC9: =DP9*$K9 -> 0 | ED9: =DQ9*$K9 -> 0 | EE9: =DR9*$K9 -> 0 | EF9: =DS9*$K9 -> 0 | EG9: =DT9*$K9 -> 0 | ... EK9: =DX9*$K9 -> 0 | EL9: =SUM(DZ9:EK9) -> 0
A10: Samsung BRK | B10: A15 | C10: GH61-18886A | D10: 0.7817 | E10: 0.75428571 | F10: 0.718 | G10: =F10*0.98 -> 0.70364 | H10: =G10 -> 0.70364 | M10: 821300 | N10: 610000 | O10: 785200 | P10: 800400 | Q10: 753500 | R10: 767650 | S10: 800000 | T10: 800000 | U10: 800000 | V10: 600000 | W10: 400000 | X10: 300000 | Y10: =SUM(M10:X10) -> 8238050 | Z10: 642010.21 | AA10: 476837 | AB10: 592265.14 | AC10: 603730.29 | AD10: =556987.2+528 -> 557515.2 | AE10: =R10*$F10+400-30-17385 -> 534157.7 | AF10: =S10*$F10 -> 574400 | AG10: =T10*$F10 -> 574400 | AH10: =U10*$G10 -> 562912 | AI10: =V10*$G10 -> 422184 | AJ10: =W10*$G10 -> 281456 | AK10: =X10*$H10 -> 211092 | AL10: =SUM(Z10:AK10) -> 6032959.5 | AM10: 100000 | AN10: 50000 | AY10: =SUM(AM10:AX10) -> 150000 | AZ10: =AM10*$H10 -> 70364 | BA10: =AN10*$H10 -> 35182 | BB10: =AO10*$H10 -> 0 | BC10: =AP10*$H10 -> 0 | BD10: =AQ10*$H10 -> 0 | BE10: =AR10*$H10 -> 0 | BF10: =AS10*$H10 -> 0 | BG10: =AT10*$H10 -> 0 | ... BK10: =AX10*$H10 -> 0 | BL10: =SUM(AZ10:BK10) -> 105546 | BY10: =SUM(BM10:BX10) -> 0 | BZ10: =BM10*$I10 -> 0 | CA10: =BN10*$I10 -> 0 | CB10: =BO10*$I10 -> 0 | CC10: =BP10*$I10 -> 0 | CD10: =BQ10*$I10 -> 0 | CE10: =BR10*$I10 -> 0 | CF10: =BS10*$I10 -> 0 | CG10: =BT10*$I10 -> 0 | ... CK10: =BX10*$I10 -> 0 | CL10: =SUM(BZ10:CK10) -> 0 | CY10: =SUM(CM10:CX10) -> 0 | CZ10: =CM10*$J10 -> 0 | DA10: =CN10*$J10 -> 0 | DB10: =CO10*$J10 -> 0 | DC10: =CP10*$J10 -> 0 | DD10: =CQ10*$J10 -> 0 | DE10: =CR10*$J10 -> 0 | DF10: =CS10*$J10 -> 0 | DG10: =CT10*$J10 -> 0 | ... DK10: =CX10*$J10 -> 0 | DL10: =SUM(CZ10:DK10) -> 0 | DY10: =SUM(DM10:DX10) -> 0 | DZ10: =DM10*$K10 -> 0 | EA10: =DN10*$K10 -> 0 | EB10: =DO10*$K10 -> 0 | EC10: =DP10*$K10 -> 0 | ED10: =DQ10*$K10 -> 0 | EE10: =DR10*$K10 -> 0 | EF10: =DS10*$K10 -> 0 | EG10: =DT10*$K10 -> 0 | ... EK10: =DX10*$K10 -> 0 | EL10: =SUM(DZ10:EK10) -> 0
A11: Samsung BRK | B11: A35 | C11: GH61-18868A | D11: 0.83 | E11: 0.81330612 | F11: =E11*0.97 -> 0.78890694 | G11: =F11*0.97 -> 0.76523973 | H11: =G11 -> 0.76523973 | M11: 92149 | N11: 312000 | O11: 453100 | P11: 116300 | Y11: =SUM(M11:X11) -> 973549 | Z11: =M11*$D11+2000-400 -> 78083.67 | AA11: =N11*$D11 -> 258960 | AB11: =O11*$E11 -> 368509 | AC11: =P11*$E11 -> 94587.502 | AD11: =Q11*$E11 -> 0 | AE11: =R11*$F11 -> 0 | AF11: =S11*$F11 -> 0 | AG11: =T11*$F11 -> 0 | AH11: =U11*$G11 -> 0 | AI11: =V11*$G11 -> 0 | AJ11: =W11*$G11 -> 0 | AK11: =X11*$G11 -> 0 | AL11: =SUM(Z11:AK11) -> 800140.18 | AY11: =SUM(AM11:AX11) -> 0 | AZ11: =AM11*$H11 -> 0 | BA11: =AN11*$H11 -> 0 | BB11: =AO11*$H11 -> 0 | BC11: =AP11*$H11 -> 0 | BD11: =AQ11*$H11 -> 0 | BE11: =AR11*$H11 -> 0 | BF11: =AS11*$H11 -> 0 | BG11: =AT11*$H11 -> 0 | ... BK11: =AX11*$H11 -> 0 | BL11: =SUM(AZ11:BK11) -> 0 | BY11: =SUM(BM11:BX11) -> 0 | BZ11: =BM11*$I11 -> 0 | CA11: =BN11*$I11 -> 0 | CB11: =BO11*$I11 -> 0 | CC11: =BP11*$I11 -> 0 | CD11: =BQ11*$I11 -> 0 | CE11: =BR11*$I11 -> 0 | CF11: =BS11*$I11 -> 0 | CG11: =BT11*$I11 -> 0 | ... CK11: =BX11*$I11 -> 0 | CL11: =SUM(BZ11:CK11) -> 0 | CY11: =SUM(CM11:CX11) -> 0 | CZ11: =CM11*$J11 -> 0 | DA11: =CN11*$J11 -> 0 | DB11: =CO11*$J11 -> 0 | DC11: =CP11*$J11 -> 0 | DD11: =CQ11*$J11 -> 0 | DE11: =CR11*$J11 -> 0 | DF11: =CS11*$J11 -> 0 | DG11: =CT11*$J11 -> 0 | ... DK11: =CX11*$J11 -> 0 | DL11: =SUM(CZ11:DK11) -> 0 | DY11: =SUM(DM11:DX11) -> 0 | DZ11: =DM11*$K11 -> 0 | EA11: =DN11*$K11 -> 0 | EB11: =DO11*$K11 -> 0 | EC11: =DP11*$K11 -> 0 | ED11: =DQ11*$K11 -> 0 | EE11: =DR11*$K11 -> 0 | EF11: =DS11*$K11 -> 0 | EG11: =DT11*$K11 -> 0 | ... EK11: =DX11*$K11 -> 0 | EL11: =SUM(DZ11:EK11) -> 0
A12: Samsung BRK | B12: New BRK 1 | E12: 0.69 | F12: 0.69 | G12: 0.69 | H12: =G12*0.98 -> 0.6762 | I12: =H12*0.98 -> 0.662676 | J12: =I12*0.98 -> 0.64942248 | K12: =J12*0.98 -> 0.63643403 | Y12: =SUM(M12:X12) -> 0 | Z12: =M12*$D12 -> 0 | AA12: =N12*$D12 -> 0 | AB12: =O12*$D12 -> 0 | AC12: =P12*$D12 -> 0 | AD12: =Q12*$D12 -> 0 | AE12: =R12*$D12 -> 0 | AF12: =S12*$D12 -> 0 | AG12: =T12*$D12 -> 0 | AH12: =U12*$G12 -> 0 | AI12: =V12*$G12 -> 0 | AJ12: =W12*$G12 -> 0 | AK12: =X12*$H12 -> 0 | AL12: =SUM(Z12:AK12) -> 0 | AY12: =SUM(AM12:AX12) -> 0 | AZ12: =AM12*$H12 -> 0 | BA12: =AN12*$H12 -> 0 | BB12: =AO12*$H12 -> 0 | BC12: =AP12*$H12 -> 0 | BD12: =AQ12*$H12 -> 0 | BE12: =AR12*$H12 -> 0 | BF12: =AS12*$H12 -> 0 | BG12: =AT12*$H12 -> 0 | ... BK12: =AX12*$H12 -> 0 | BL12: =SUM(AZ12:BK12) -> 0 | BM12: 500000 | BN12: 300000 | BO12: 300000 | BP12: 400000 | BQ12: =25000*24 -> 600000 | BR12: =25000*24 -> 600000 | BS12: =30000*26 -> 780000 | BT12: =30000*26 -> 780000 | BU12: =30000*26 -> 780000 | BV12: =30000*26 -> 780000 | BW12: =30000*26 -> 780000 | BX12: =30000*26 -> 780000 | BY12: =SUM(BM12:BX12) -> 7380000 | BZ12: =BM12*$I12 -> 331338 | CA12: =BN12*$I12 -> 198802.8 | CB12: =BO12*$I12 -> 198802.8 | CC12: =BP12*$I12 -> 265070.4 | CD12: =BQ12*$I12 -> 397605.6 | CE12: =BR12*$I12 -> 397605.6 | CF12: =BS12*$I12 -> 516887.28 | CG12: =BT12*$I12 -> 516887.28 | ... CK12: =BX12*$I12 -> 516887.28 | CL12: =SUM(BZ12:CK12) -> 4890548.9 | CM12: 500000 | CN12: 300000 | CO12: 300000 | CP12: 400000 | CQ12: =25000*24 -> 600000 | CR12: =25000*24 -> 600000 | CS12: =30000*26 -> 780000 | CT12: =30000*26 -> 780000 | CU12: =30000*26 -> 780000 | CV12: =30000*26 -> 780000 | CW12: =30000*26 -> 780000 | CX12: =30000*26 -> 780000 | CY12: =SUM(CM12:CX12) -> 7380000 | CZ12: =CM12*$J12 -> 324711.24 | DA12: =CN12*$J12 -> 194826.74 | DB12: =CO12*$J12 -> 194826.74 | DC12: =CP12*$J12 -> 259768.99 | DD12: =CQ12*$J12 -> 389653.49 | DE12: =CR12*$J12 -> 389653.49 | DF12: =CS12*$J12 -> 506549.53 | DG12: =CT12*$J12 -> 506549.53 | ... DK12: =CX12*$J12 -> 506549.53 | DL12: =SUM(CZ12:DK12) -> 4792737.9 | DM12: 500000 | DN12: 300000 | DO12: 300000 | DP12: 400000 | DQ12: =25000*24 -> 600000 | DR12: =25000*24 -> 600000 | DS12: =30000*26 -> 780000 | DT12: =30000*26 -> 780000 | DU12: =30000*26 -> 780000 | DV12: =30000*26 -> 780000 | DW12: =30000*26 -> 780000 | DX12: =30000*26 -> 780000 | DY12: =SUM(DM12:DX12) -> 7380000 | DZ12: =DM12*$K12 -> 318217.02 | EA12: =DN12*$K12 -> 190930.21 | EB12: =DO12*$K12 -> 190930.21 | EC12: =DP12*$K12 -> 254573.61 | ED12: =DQ12*$K12 -> 381860.42 | EE12: =DR12*$K12 -> 381860.42 | EF12: =DS12*$K12 -> 496418.54 | EG12: =DT12*$K12 -> 496418.54 | ... EK12: =DX12*$K12 -> 496418.54 | EL12: =SUM(DZ12:EK12) -> 4696883.1
A13: Samsung BRK | B13: New BRK 2 | F13: 0.8 | G13: 0.8 | H13: =G13*0.98 -> 0.784 | I13: =H13*0.98 -> 0.76832 | J13: =I13*0.98 -> 0.7529536 | K13: =J13*0.98 -> 0.73789453 | Y13: =SUM(M13:X13) -> 0 | Z13: =M13*$D13 -> 0 | AA13: =N13*$D13 -> 0 | AB13: =O13*$D13 -> 0 | AC13: =P13*$D13 -> 0 | AD13: =Q13*$D13 -> 0 | AE13: =R13*$D13 -> 0 | AF13: =S13*$D13 -> 0 | AG13: =T13*$D13 -> 0 | AH13: =U13*$G13 -> 0 | AI13: =V13*$G13 -> 0 | AJ13: =W13*$G13 -> 0 | AK13: =X13*$H13 -> 0 | AL13: =SUM(Z13:AK13) -> 0 | AY13: =SUM(AM13:AX13) -> 0 | AZ13: =AM13*$H13 -> 0 | BA13: =AN13*$H13 -> 0 | BB13: =AO13*$H13 -> 0 | BC13: =AP13*$H13 -> 0 | BD13: =AQ13*$H13 -> 0 | BE13: =AR13*$H13 -> 0 | BF13: =AS13*$H13 -> 0 | BG13: =AT13*$H13 -> 0 | ... BK13: =AX13*$H13 -> 0 | BL13: =SUM(AZ13:BK13) -> 0 | BM13: 300000 | BN13: 300000 | BO13: 400000 | BP13: 500000 | BQ13: 400000 | BR13: 500000 | BS13: 400000 | BT13: 200000 | BU13: 100000 | BV13: 50000 | BY13: =SUM(BM13:BX13) -> 3150000 | BZ13: =BM13*$I13 -> 230496 | CA13: =BN13*$I13 -> 230496 | CB13: =BO13*$I13 -> 307328 | CC13: =BP13*$I13 -> 384160 | CD13: =BQ13*$I13 -> 307328 | CE13: =BR13*$I13 -> 384160 | CF13: =BS13*$I13 -> 307328 | CG13: =BT13*$I13 -> 153664 | ... CK13: =BX13*$I13 -> 0 | CL13: =SUM(BZ13:CK13) -> 2420208 | CM13: 300000 | CN13: 300000 | CO13: 400000 | CP13: 500000 | CQ13: 400000 | CR13: 500000 | CS13: 400000 | CT13: 200000 | CU13: 100000 | CV13: 50000 | CY13: =SUM(CM13:CX13) -> 3150000 | CZ13: =CM13*$J13 -> 225886.08 | DA13: =CN13*$J13 -> 225886.08 | DB13: =CO13*$J13 -> 301181.44 | DC13: =CP13*$J13 -> 376476.8 | DD13: =CQ13*$J13 -> 301181.44 | DE13: =CR13*$J13 -> 376476.8 | DF13: =CS13*$J13 -> 301181.44 | DG13: =CT13*$J13 -> 150590.72 | ... DK13: =CX13*$J13 -> 0 | DL13: =SUM(CZ13:DK13) -> 2371803.8 | DM13: 300000 | DN13: 300000 | DO13: 400000 | DP13: 500000 | DQ13: 400000 | DR13: 500000 | DS13: 400000 | DT13: 200000 | DU13: 100000 | DV13: 50000 | DY13: =SUM(DM13:DX13) -> 3150000 | DZ13: =DM13*$K13 -> 221368.36 | EA13: =DN13*$K13 -> 221368.36 | EB13: =DO13*$K13 -> 295157.81 | EC13: =DP13*$K13 -> 368947.26 | ED13: =DQ13*$K13 -> 295157.81 | EE13: =DR13*$K13 -> 368947.26 | EF13: =DS13*$K13 -> 295157.81 | EG13: =DT13*$K13 -> 147578.91 | ... EK13: =DX13*$K13 -> 0 | EL13: =SUM(DZ13:EK13) -> 2324367.8
A14: Samsung BRK VN Total | M14: =SUM(M6:M13) -> 1071049 | N14: =SUM(N6:N13) -> 988800 | O14: =SUM(O6:O13) -> 1312100 | P14: =SUM(P6:P13) -> 916700 | Q14: =SUM(Q6:Q13) -> 753500 | R14: =SUM(R6:R13) -> 767650 | S14: =SUM(S6:S13) -> 800000 | T14: =SUM(T6:T13) -> 800000 | ... EL14: =SUM(EL6:EL13) -> 7021250.9
A15: Samsung CNC | B15: DM3 (S23) | C15: GH94-35427A | D15: 1.305 | E15: 1.305 | F15: 1.305 | G15: 1.34 | H15: 1.34 | I15: 1.34 | J15: 1.34 | K15: 1.34 | M15: 80500 | N15: 66800 | O15: 89800 | P15: 78900 | Q15: 44204 | R15: 20900 | S15: 115000 | T15: 80000 | U15: 70000 | V15: 80000 | W15: 80000 | X15: 60000 | Y15: =SUM(M15:X15) -> 866104 | Z15: 107870 | AA15: 89512 | AB15: 120332 | AC15: 104263.93 | AD15: 58349.28 | AE15: 27588 | AF15: =S15*$E15 -> 150075 | AG15: =T15*$E15 -> 104400 | AH15: =U15*$E15 -> 91350 | AI15: =V15*$E15 -> 104400 | AJ15: =W15*$E15 -> 104400 | AK15: =X15*$E15 -> 78300 | AL15: =SUM(Z15:AK15) -> 1140840.2 | AM15: 80500 | AN15: 66800 | AO15: 50000 | AP15: 40000 | AY15: =SUM(AM15:AX15) -> 237300 | AZ15: =AM15*$H15 -> 107870 | BA15: =AN15*$H15 -> 89512 | BB15: =AO15*$H15 -> 67000 | BC15: =AP15*$H15 -> 53600 | BD15: =AQ15*$H15 -> 0 | BE15: =AR15*$H15 -> 0 | BF15: =AS15*$H15 -> 0 | BG15: =AT15*$H15 -> 0 | ... BK15: =AX15*$H15 -> 0 | BL15: =SUM(AZ15:BK15) -> 317982 | BY15: =SUM(BM15:BX15) -> 0 | BZ15: =BM15*$I15 -> 0 | CA15: =BN15*$I15 -> 0 | CB15: =BO15*$I15 -> 0 | CC15: =BP15*$I15 -> 0 | CD15: =BQ15*$I15 -> 0 | CE15: =BR15*$I15 -> 0 | CF15: =BS15*$I15 -> 0 | CG15: =BT15*$I15 -> 0 | ... CK15: =BX15*$I15 -> 0 | CL15: =SUM(BZ15:CK15) -> 0 | CY15: =SUM(CM15:CX15) -> 0 | CZ15: =CM15*$J15 -> 0 | DA15: =CN15*$J15 -> 0 | DB15: =CO15*$J15 -> 0 | DC15: =CP15*$J15 -> 0 | DD15: =CQ15*$J15 -> 0 | DE15: =CR15*$J15 -> 0 | DF15: =CS15*$J15 -> 0 | DG15: =CT15*$J15 -> 0 | ... DK15: =CX15*$J15 -> 0 | DL15: =SUM(CZ15:DK15) -> 0 | DY15: =SUM(DM15:DX15) -> 0 | DZ15: =DM15*$K15 -> 0 | EA15: =DN15*$K15 -> 0 | EB15: =DO15*$K15 -> 0 | EC15: =DP15*$K15 -> 0 | ED15: =DQ15*$K15 -> 0 | EE15: =DR15*$K15 -> 0 | EF15: =DS15*$K15 -> 0 | EG15: =DT15*$K15 -> 0 | ... EK15: =DX15*$K15 -> 0 | EL15: =SUM(DZ15:EK15) -> 0
A16: Samsung CNC | B16: Q4 | C16: GH94-34528A | D16: 0.8 | E16: 0.8 | F16: 0.8 | G16: 0.79 | H16: 0.79 | I16: 0.79 | J16: 0.79 | K16: =J16*0.98 -> 0.7742 | M16: 157900 | N16: 93500 | O16: 129000 | P16: 94640 | Q16: 75282 | R16: 71000 | T16: 10000 | U16: 20000 | V16: 20000 | W16: 20000 | X16: 20000 | Y16: =SUM(M16:X16) -> 711322 | Z16: 126320 | AA16: 74800 | AB16: 103200 | AC16: 75712 | AD16: 61454.694 | AE16: 56800 | AF16: =S16*$E16 -> 0 | AG16: =T16*$E16 -> 8000 | AH16: =U16*$E16 -> 16000 | AI16: =V16*$E16 -> 16000 | AJ16: =W16*$E16 -> 16000 | AK16: =X16*$E16 -> 16000 | AL16: =SUM(Z16:AK16) -> 570286.69 | AM16: 157900 | AN16: 93500 | AO16: 150000 | AP16: 120000 | AQ16: 100000 | AR16: 110000 | AS16: 100000 | AT16: 100000 | AU16: 100000 | AV16: 100000 | AW16: 100000 | AX16: 100000 | AY16: =SUM(AM16:AX16) -> 1331400 | AZ16: =AM16*$H16 -> 124741 | BA16: =AN16*$H16 -> 73865 | BB16: =AO16*$H16 -> 118500 | BC16: =AP16*$H16 -> 94800 | BD16: =AQ16*$H16 -> 79000 | BE16: =AR16*$H16 -> 86900 | BF16: =AS16*$H16 -> 79000 | BG16: =AT16*$H16 -> 79000 | ... BK16: =AX16*$H16 -> 79000 | BL16: =SUM(AZ16:BK16) -> 1051806 | BY16: =SUM(BM16:BX16) -> 0 | BZ16: =BM16*$I16 -> 0 | CA16: =BN16*$I16 -> 0 | CB16: =BO16*$I16 -> 0 | CC16: =BP16*$I16 -> 0 | CD16: =BQ16*$I16 -> 0 | CE16: =BR16*$I16 -> 0 | CF16: =BS16*$I16 -> 0 | CG16: =BT16*$I16 -> 0 | ... CK16: =BX16*$I16 -> 0 | CL16: =SUM(BZ16:CK16) -> 0 | CY16: =SUM(CM16:CX16) -> 0 | CZ16: =CM16*$J16 -> 0 | DA16: =CN16*$J16 -> 0 | DB16: =CO16*$J16 -> 0 | DC16: =CP16*$J16 -> 0 | DD16: =CQ16*$J16 -> 0 | DE16: =CR16*$J16 -> 0 | DF16: =CS16*$J16 -> 0 | DG16: =CT16*$J16 -> 0 | ... DK16: =CX16*$J16 -> 0 | DL16: =SUM(CZ16:DK16) -> 0 | DY16: =SUM(DM16:DX16) -> 0 | DZ16: =DM16*$K16 -> 0 | EA16: =DN16*$K16 -> 0 | EB16: =DO16*$K16 -> 0 | EC16: =DP16*$K16 -> 0 | ED16: =DQ16*$K16 -> 0 | EE16: =DR16*$K16 -> 0 | EF16: =DS16*$K16 -> 0 | EG16: =DT16*$K16 -> 0 | ... EK16: =DX16*$K16 -> 0 | EL16: =SUM(DZ16:EK16) -> 0
A17: Samsung CNC | B17: Q5 | C17: GH94-35418A | D17: 0.92 | E17: 0.92 | F17: 0.92 | G17: 0.94293878 | H17: 0.94293878 | I17: 0.94293878 | J17: 0.94293878 | K17: =J17*0.98 -> 0.92408 | M17: 7000 | Q17: 37400 | R17: 4400 | S17: 1700 | Y17: =SUM(M17:X17) -> 50500 | Z17: 6300 | AA17: 0 | AB17: 0 | AC17: 0 | AD17: 35265.91 | AE17: 4048 | AF17: =S17*$E17 -> 1564 | AG17: =T17*$E17 -> 0 | AH17: =U17*$E17 -> 0 | AI17: =V17*$E17 -> 0 | AJ17: =W17*$E17 -> 0 | AK17: =X17*$E17 -> 0 | AL17: =SUM(Z17:AK17) -> 47177.91 | AM17: 7000 | AY17: =SUM(AM17:AX17) -> 7000 | AZ17: =AM17*$H17 -> 6600.5714 | BA17: =AN17*$H17 -> 0 | BB17: =AO17*$H17 -> 0 | BC17: =AP17*$H17 -> 0 | BD17: =AQ17*$H17 -> 0 | BE17: =AR17*$H17 -> 0 | BF17: =AS17*$H17 -> 0 | BG17: =AT17*$H17 -> 0 | ... BK17: =AX17*$H17 -> 0 | BL17: =SUM(AZ17:BK17) -> 6600.5714 | BY17: =SUM(BM17:BX17) -> 0 | BZ17: =BM17*$I17 -> 0 | CA17: =BN17*$I17 -> 0 | CB17: =BO17*$I17 -> 0 | CC17: =BP17*$I17 -> 0 | CD17: =BQ17*$I17 -> 0 | CE17: =BR17*$I17 -> 0 | CF17: =BS17*$I17 -> 0 | CG17: =BT17*$I17 -> 0 | ... CK17: =BX17*$I17 -> 0 | CL17: =SUM(BZ17:CK17) -> 0 | CY17: =SUM(CM17:CX17) -> 0 | CZ17: =CM17*$J17 -> 0 | DA17: =CN17*$J17 -> 0 | DB17: =CO17*$J17 -> 0 | DC17: =CP17*$J17 -> 0 | DD17: =CQ17*$J17 -> 0 | DE17: =CR17*$J17 -> 0 | DF17: =CS17*$J17 -> 0 | DG17: =CT17*$J17 -> 0 | ... DK17: =CX17*$J17 -> 0 | DL17: =SUM(CZ17:DK17) -> 0 | DY17: =SUM(DM17:DX17) -> 0 | DZ17: =DM17*$K17 -> 0 | EA17: =DN17*$K17 -> 0 | EB17: =DO17*$K17 -> 0 | EC17: =DP17*$K17 -> 0 | ED17: =DQ17*$K17 -> 0 | EE17: =DR17*$K17 -> 0 | EF17: =DS17*$K17 -> 0 | EG17: =DT17*$K17 -> 0 | ... EK17: =DX17*$K17 -> 0 | EL17: =SUM(DZ17:EK17) -> 0
A18: Samsung CNC | B18: HX1 | C18: GH94-26469A | D18: 1.1 | E18: 1.1 | F18: 1.1 | G18: 1.1 | H18: 1.1 | I18: 1.1 | J18: 1.1 | K18: =J18*0.98 -> 1.078 | M18: 17353 | Y18: =SUM(M18:X18) -> 17353 | Z18: 19088.3 | AA18: 0 | AB18: 0 | AC18: 0 | AD18: 0 | AE18: 0 | AF18: =S18*$E18 -> 0 | AG18: =T18*$E18 -> 0 | AH18: =U18*$E18 -> 0 | AI18: =V18*$E18 -> 0 | AJ18: =W18*$E18 -> 0 | AK18: =X18*$E18 -> 0 | AL18: =SUM(Z18:AK18) -> 19088.3 | AM18: 17353 | AY18: =SUM(AM18:AX18) -> 17353 | AZ18: =AM18*$H18 -> 19088.3 | BA18: =AN18*$H18 -> 0 | BB18: =AO18*$H18 -> 0 | BC18: =AP18*$H18 -> 0 | BD18: =AQ18*$H18 -> 0 | BE18: =AR18*$H18 -> 0 | BF18: =AS18*$H18 -> 0 | BG18: =AT18*$H18 -> 0 | ... BK18: =AX18*$H18 -> 0 | BL18: =SUM(AZ18:BK18) -> 19088.3 | BY18: =SUM(BM18:BX18) -> 0 | BZ18: =BM18*$I18 -> 0 | CA18: =BN18*$I18 -> 0 | CB18: =BO18*$I18 -> 0 | CC18: =BP18*$I18 -> 0 | CD18: =BQ18*$I18 -> 0 | CE18: =BR18*$I18 -> 0 | CF18: =BS18*$I18 -> 0 | CG18: =BT18*$I18 -> 0 | ... CK18: =BX18*$I18 -> 0 | CL18: =SUM(BZ18:CK18) -> 0 | CY18: =SUM(CM18:CX18) -> 0 | CZ18: =CM18*$J18 -> 0 | DA18: =CN18*$J18 -> 0 | DB18: =CO18*$J18 -> 0 | DC18: =CP18*$J18 -> 0 | DD18: =CQ18*$J18 -> 0 | DE18: =CR18*$J18 -> 0 | DF18: =CS18*$J18 -> 0 | DG18: =CT18*$J18 -> 0 | ... DK18: =CX18*$J18 -> 0 | DL18: =SUM(CZ18:DK18) -> 0 | DY18: =SUM(DM18:DX18) -> 0 | DZ18: =DM18*$K18 -> 0 | EA18: =DN18*$K18 -> 0 | EB18: =DO18*$K18 -> 0 | EC18: =DP18*$K18 -> 0 | ED18: =DQ18*$K18 -> 0 | EE18: =DR18*$K18 -> 0 | EF18: =DS18*$K18 -> 0 | EG18: =DT18*$K18 -> 0 | ... EK18: =DX18*$K18 -> 0 | EL18: =SUM(DZ18:EK18) -> 0
A19: Samsung CNC | B19: B0 | C19: GH94-32719A | D19: 1.19 | E19: 1.19 | F19: 1.19 | G19: 1.203 | H19: 1.203 | I19: 1.203 | J19: 1.203 | K19: =J19*0.98 -> 1.17894 | M19: 59600 | N19: 34200 | O19: 56805 | P19: 37207 | Q19: 28440 | R19: 72400 | S19: 100000 | T19: 75000 | U19: 75000 | V19: 80000 | W19: 80000 | X19: 80000 | Y19: =SUM(M19:X19) -> 778652 | Z19: 73308 | AA19: 42066 | AB19: 69870.15 | AC19: 44980.985 | AD19: 35172.735 | AE19: 87604 | AF19: =S19*$E19 -> 119000 | AG19: =T19*$E19 -> 89250 | AH19: =U19*$E19 -> 89250 | AI19: =V19*$E19 -> 95200 | AJ19: =W19*$E19 -> 95200 | AK19: =X19*$E19 -> 95200 | AL19: =SUM(Z19:AK19) -> 936101.87 | AM19: 59600 | AN19: 34200 | AO19: 40000 | AP19: 70000 | AQ19: 100000 | AR19: 120000 | AS19: 120000 | AT19: 120000 | AU19: 100000 | AV19: 100000 | AW19: 100000 | AX19: 100000 | AY19: =SUM(AM19:AX19) -> 1063800 | AZ19: =AM19*$H19 -> 71698.8 | BA19: =AN19*$H19 -> 41142.6 | BB19: =AO19*$H19 -> 48120 | BC19: =AP19*$H19 -> 84210 | BD19: =AQ19*$H19 -> 120300 | BE19: =AR19*$H19 -> 144360 | BF19: =AS19*$H19 -> 144360 | BG19: =AT19*$H19 -> 144360 | ... BK19: =AX19*$H19 -> 120300 | BL19: =SUM(AZ19:BK19) -> 1279751.4 | BM19: 150000 | BN19: 100000 | BO19: 150000 | BP19: 150000 | BQ19: 150000 | BR19: 150000 | BS19: 150000 | BT19: 150000 | BU19: 150000 | BV19: 150000 | BW19: 150000 | BX19: 150000 | BY19: =SUM(BM19:BX19) -> 1750000 | BZ19: =BM19*$I19 -> 180450 | CA19: =BN19*$I19 -> 120300 | CB19: =BO19*$I19 -> 180450 | CC19: =BP19*$I19 -> 180450 | CD19: =BQ19*$I19 -> 180450 | CE19: =BR19*$I19 -> 180450 | CF19: =BS19*$I19 -> 180450 | CG19: =BT19*$I19 -> 180450 | ... CK19: =BX19*$I19 -> 180450 | CL19: =SUM(BZ19:CK19) -> 2105250 | CM19: 150000 | CN19: 100000 | CO19: 150000 | CP19: 150000 | CQ19: 150000 | CR19: 150000 | CS19: 150000 | CT19: 150000 | CU19: 150000 | CV19: 150000 | CW19: 150000 | CX19: 150000 | CY19: =SUM(CM19:CX19) -> 1750000 | CZ19: =CM19*$J19 -> 180450 | DA19: =CN19*$J19 -> 120300 | DB19: =CO19*$J19 -> 180450 | DC19: =CP19*$J19 -> 180450 | DD19: =CQ19*$J19 -> 180450 | DE19: =CR19*$J19 -> 180450 | DF19: =CS19*$J19 -> 180450 | DG19: =CT19*$J19 -> 180450 | ... DK19: =CX19*$J19 -> 180450 | DL19: =SUM(CZ19:DK19) -> 2105250 | DM19: 150000 | DN19: 100000 | DO19: 150000 | DP19: 150000 | DQ19: 150000 | DR19: 150000 | DS19: 150000 | DT19: 150000 | DU19: 150000 | DV19: 150000 | DW19: 150000 | DX19: 150000 | DY19: =SUM(DM19:DX19) -> 1750000 | DZ19: =DM19*$K19 -> 176841 | EA19: =DN19*$K19 -> 117894 | EB19: =DO19*$K19 -> 176841 | EC19: =DP19*$K19 -> 176841 | ED19: =DQ19*$K19 -> 176841 | EE19: =DR19*$K19 -> 176841 | EF19: =DS19*$K19 -> 176841 | EG19: =DT19*$K19 -> 176841 | ... EK19: =DX19*$K19 -> 176841 | EL19: =SUM(DZ19:EK19) -> 2063145
A20: Samsung CNC | B20: E1 | C20: GH94-38080A | D20: 1.18 | E20: 1.18 | F20: 1.18 | G20: 1.2040816 | H20: 1.2040816 | I20: 1.2040816 | J20: 1.2040816 | K20: =J20*0.98 -> 1.18 | M20: 156400 | N20: 129500 | O20: 181500 | P20: 127500 | Q20: 111260 | R20: 13000 | S20: 80000 | T20: 80000 | U20: 75000 | V20: 80000 | W20: 80000 | X20: 80000 | Y20: =SUM(M20:X20) -> 1194160 | Z20: 189244 | AA20: 156695 | AB20: 223604 | AC20: 151136.53 | AD20: 133966.12 | AE20: 15340 | AF20: =S20*$E20 -> 94400 | AG20: =T20*$E20 -> 94400 | AH20: =U20*$E20 -> 88500 | AI20: =V20*$E20 -> 94400 | AJ20: =W20*$E20 -> 94400 | AK20: =X20*$E20 -> 94400 | AL20: =SUM(Z20:AK20) -> 1430485.7 | AM20: 156400 | AN20: 129500 | AO20: 200000 | AP20: 180000 | AQ20: 180000 | AR20: 220000 | AS20: 220000 | AT20: 220000 | AU20: 200000 | AV20: 200000 | AW20: 200000 | AX20: 200000 | AY20: =SUM(AM20:AX20) -> 2305900 | AZ20: =AM20*$H20 -> 188318.37 | BA20: =AN20*$H20 -> 155928.57 | BB20: =AO20*$H20 -> 240816.33 | BC20: =AP20*$H20 -> 216734.69 | BD20: =AQ20*$H20 -> 216734.69 | BE20: =AR20*$H20 -> 264897.96 | BF20: =AS20*$H20 -> 264897.96 | BG20: =AT20*$H20 -> 264897.96 | ... BK20: =AX20*$H20 -> 240816.33 | BL20: =SUM(AZ20:BK20) -> 2776491.8 | BM20: 250000 | BN20: 129500 | BO20: 250000 | BP20: 250000 | BQ20: 250000 | BR20: 250000 | BS20: 250000 | BT20: 250000 | BU20: 250000 | BV20: 250000 | BW20: 250000 | BX20: 250000 | BY20: =SUM(BM20:BX20) -> 2879500 | BZ20: =BM20*$I20 -> 301020.41 | CA20: =BN20*$I20 -> 155928.57 | CB20: =BO20*$I20 -> 301020.41 | CC20: =BP20*$I20 -> 301020.41 | CD20: =BQ20*$I20 -> 301020.41 | CE20: =BR20*$I20 -> 301020.41 | CF20: =BS20*$I20 -> 301020.41 | CG20: =BT20*$I20 -> 301020.41 | ... CK20: =BX20*$I20 -> 301020.41 | CL20: =SUM(BZ20:CK20) -> 3467153.1 | CM20: 250000 | CN20: 129500 | CO20: 250000 | CP20: 250000 | CQ20: 250000 | CR20: 250000 | CS20: 250000 | CT20: 250000 | CU20: 250000 | CV20: 250000 | CW20: 250000 | CX20: 250000 | CY20: =SUM(CM20:CX20) -> 2879500 | CZ20: =CM20*$J20 -> 301020.41 | DA20: =CN20*$J20 -> 155928.57 | DB20: =CO20*$J20 -> 301020.41 | DC20: =CP20*$J20 -> 301020.41 | DD20: =CQ20*$J20 -> 301020.41 | DE20: =CR20*$J20 -> 301020.41 | DF20: =CS20*$J20 -> 301020.41 | DG20: =CT20*$J20 -> 301020.41 | ... DK20: =CX20*$J20 -> 301020.41 | DL20: =SUM(CZ20:DK20) -> 3467153.1 | DM20: 250000 | DN20: 129500 | DO20: 250000 | DP20: 250000 | DQ20: 250000 | DR20: 250000 | DS20: 250000 | DT20: 250000 | DU20: 250000 | DV20: 250000 | DW20: 250000 | DX20: 250000 | DY20: =SUM(DM20:DX20) -> 2879500 | DZ20: =DM20*$K20 -> 295000 | EA20: =DN20*$K20 -> 152810 | EB20: =DO20*$K20 -> 295000 | EC20: =DP20*$K20 -> 295000 | ED20: =DQ20*$K20 -> 295000 | EE20: =DR20*$K20 -> 295000 | EF20: =DS20*$K20 -> 295000 | EG20: =DT20*$K20 -> 295000 | ... EK20: =DX20*$K20 -> 295000 | EL20: =SUM(DZ20:EK20) -> 3397810
A21: Samsung CNC | B21: B6 | C21: GH94-39228A | D21: 0.63 | E21: 0.63 | F21: 0.63 | G21: 0.6 | H21: 0.6 | I21: 0.6 | J21: 0.6 | K21: =J21*0.98 -> 0.588 | Q21: 29000 | R21: 185544 | S21: 75000 | T21: 80000 | U21: 110000 | V21: 140000 | W21: 150000 | X21: 150000 | Y21: =SUM(M21:X21) -> 919544 | AD21: 11278.857 | AE21: 113181.84 | AF21: =S21*$E21 -> 47250 | AG21: =T21*$E21 -> 50400 | AH21: =U21*$E21 -> 69300 | AI21: =V21*$E21 -> 88200 | AJ21: =W21*$E21 -> 94500 | AK21: =X21*$E21 -> 94500 | AL21: =SUM(Z21:AK21) -> 568610.7 | AY21: =SUM(AM21:AX21) -> 0 | BL21: =SUM(AZ21:BK21) -> 0 | BY21: =SUM(BM21:BX21) -> 0 | CL21: =SUM(BZ21:CK21) -> 0 | CY21: =SUM(CM21:CX21) -> 0 | DL21: =SUM(CZ21:DK21) -> 0 | DY21: =SUM(DM21:DX21) -> 0 | EL21: =SUM(DZ21:EK21) -> 0
A22: Samsung CNC | B22: Q6 Sub | C22: GH94-39352A | D22: 0.7 | E22: 0.7 | F22: 0.7 | G22: 0.74 | H22: 0.74 | I22: 0.74 | J22: 0.74 | K22: 0.69477551 | Q22: 3000 | R22: =65398+13676 -> 79074 | S22: 42000 | T22: 35000 | U22: 80000 | V22: 160000 | W22: 160000 | X22: 160000 | Y22: =SUM(M22:X22) -> 719074 | AD22: 3904.3265 | AE22: 53770.32 | AF22: =S22*$E22 -> 29400 | AG22: =T22*$E22 -> 24500 | AH22: =U22*$E22 -> 56000 | AI22: =V22*$E22 -> 112000 | AJ22: =W22*$E22 -> 112000 | AK22: =X22*$E22 -> 112000 | AL22: =SUM(Z22:AK22) -> 503574.65 | AY22: =SUM(AM22:AX22) -> 0 | BL22: =SUM(AZ22:BK22) -> 0 | BY22: =SUM(BM22:BX22) -> 0 | CL22: =SUM(BZ22:CK22) -> 0 | CY22: =SUM(CM22:CX22) -> 0 | DL22: =SUM(CZ22:DK22) -> 0 | DY22: =SUM(DM22:DX22) -> 0 | EL22: =SUM(DZ22:EK22) -> 0
A23: Samsung CNC | B23: Beyond2 | C23: GH94-21815A | D23: 1.3 | E23: 1.3469388 | F23: 1.3 | G23: 1.3 | H23: 1.3 | I23: 1.3 | J23: 1.3 | K23: 1.3 | O23: 4750 | P23: 17548 | Y23: =SUM(M23:X23) -> 22298 | Z23: =M23*$D23 -> 0 | AA23: =N23*$D23 -> 0 | AB23: =O23*$D23 -> 6175 | AC23: =P23*$E23+2000+8000-300 -> 33336.082 | AD23: =Q23*$E23 -> 0 | AE23: =R23*$E23 -> 0 | AF23: =S23*$E23 -> 0 | AG23: =T23*$E23 -> 0 | AH23: =U23*$E23 -> 0 | AI23: =V23*$E23 -> 0 | AJ23: =W23*$E23 -> 0 | AK23: =X23*$E23 -> 0 | AL23: =SUM(Z23:AK23) -> 39511.082 | AY23: =SUM(AM23:AX23) -> 0 | BL23: =SUM(AZ23:BK23) -> 0 | BY23: =SUM(BM23:BX23) -> 0 | CL23: =SUM(BZ23:CK23) -> 0 | CY23: =SUM(CM23:CX23) -> 0 | DL23: =SUM(CZ23:DK23) -> 0 | DY23: =SUM(DM23:DX23) -> 0 | EL23: =SUM(DZ23:EK23) -> 0
A24: Samsung CNC Total | M24: =SUM(M15:M23) -> 478753 | N24: =SUM(N15:N23) -> 324000 | O24: =SUM(O15:O23) -> 461855 | P24: =SUM(P15:P23) -> 355795 | Q24: =SUM(Q15:Q23) -> 328586 | R24: =SUM(R15:R23) -> 446318 | S24: =SUM(S15:S23) -> 413700 | T24: =SUM(T15:T23) -> 360000 | ... AD24: =SUM(AD15:AD23) -> 339391.92 | AE24: =SUM(AE15:AE23)-300+16000+700 -> 374732.16 | AF24: =SUM(AF15:AF23) -> 441689 | AG24: =SUM(AG15:AG23) -> 370950 | AH24: =SUM(AH15:AH23) -> 410400 | AI24: =SUM(AI15:AI23) -> 510200 | AJ24: =SUM(AJ15:AJ23) -> 516500 | AK24: =SUM(AK15:AK23) -> 490400 | AL24: =SUM(AL15:AL23) -> 5255677.1 | AM24: =SUM(AM15:AM23) -> 478753 | ... EL24: =SUM(EL15:EL23) -> 5460955
A25: Qualcomm | B25: MTP Pinnacles | C25: MTP/IDP | D25: 5 | E25: 5 | F25: 5 | G25: 5 | H25: 5 | I25: 5 | J25: 5 | K25: 5 | M25: 18000 | N25: 15000 | O25: 25500 | P25: 5819 | Q25: 40476 | R25: 6750 | S25: 10050 | T25: 17000 | U25: 20000 | V25: 13000 | W25: 30000 | X25: 20000 | Y25: =SUM(M25:X25) -> 221595 | Z25: 9324 | AA25: 20895 | AB25: 33589.5 | AC25: 43319.29 | AD25: 141093.85 | AE25: 28959.2 | AF25: 7037.45 | AG25: =+T25*$G$25 -> 85000 | AH25: =+U25*$G$25 -> 100000 | AI25: =+V25*$G$25 -> 65000 | AJ25: =+W25*$G$25 -> 150000 | AK25: =+X25*$G$25 -> 100000 | AL25: =SUM(Z25:AK25) -> 784218.29 | AM25: 16000 | AN25: =N25*90% -> 13500 | AO25: 20000 | AP25: 12000 | AQ25: =Q25*90% -> 36428.4 | AR25: =R25*90% -> 6075 | AS25: =S25*90% -> 9045 | AT25: =T25*90% -> 15300 | AU25: 14000 | AV25: 10000 | AW25: 12000 | AX25: =X25*90% -> 18000 | AY25: =SUM(AM25:AX25) -> 182348.4 | AZ25: =AM25*$H25 -> 80000 | BA25: =AN25*$H25 -> 67500 | BB25: =AO25*$H25 -> 100000 | BC25: =AP25*$H25 -> 60000 | BD25: =AQ25*$H25 -> 182142 | BE25: =AR25*$H25 -> 30375 | BF25: =AS25*$H25 -> 45225 | BG25: =AT25*$H25 -> 76500 | ... BK25: =AX25*$H25 -> 90000 | BL25: =SUM(AZ25:BK25) -> 911742 | BM25: 25000 | BN25: 15000 | BO25: =AO25*90% -> 18000 | BP25: 12000 | BQ25: 9000 | BR25: 9000 | BS25: 10000 | BT25: 14000 | BU25: 14000 | BV25: 10000 | BW25: 20000 | BX25: 10000 | BY25: =SUM(BM25:BX25) -> 166000 | BZ25: =+BM25*$G$25 -> 125000 | CA25: =+BN25*$G$25 -> 75000 | CB25: =+BO25*$G$25 -> 90000 | CC25: =+BP25*$G$25 -> 60000 | CD25: =+BQ25*$G$25 -> 45000 | CE25: =+BR25*$G$25 -> 45000 | CF25: =+BS25*$G$25 -> 50000 | CG25: =+BT25*$G$25 -> 70000 | ... CK25: =+BX25*$G$25 -> 50000 | CL25: =SUM(BZ25:CK25) -> 830000 | CM25: 18000 | CN25: =BN25*90% -> 13500 | CO25: =BO25*90% -> 16200 | CP25: 12000 | CQ25: =BQ25*90% -> 8100 | CR25: 12000 | CS25: 12000 | CT25: 15000 | CU25: 14000 | CV25: 15000 | CW25: 12000 | CX25: =BX25*90% -> 9000 | CY25: =SUM(CM25:CX25) -> 156800 | CZ25: =+CM25*$G$25 -> 90000 | DA25: =+CN25*$G$25 -> 67500 | DB25: =+CO25*$G$25 -> 81000 | DC25: =+CP25*$G$25 -> 60000 | DD25: =+CQ25*$G$25 -> 40500 | DE25: =+CR25*$G$25 -> 60000 | DF25: =+CS25*$G$25 -> 60000 | DG25: =+CT25*$G$25 -> 75000 | ... DK25: =+CX25*$G$25 -> 45000 | DL25: =SUM(CZ25:DK25) -> 784000 | DM25: 16000 | DN25: =CN25*90% -> 12150 | DO25: =CO25*90% -> 14580 | DP25: 12000 | DQ25: =CQ25*90% -> 7290 | DR25: =CR25*90% -> 10800 | DS25: =CS25*90% -> 10800 | DT25: =CT25*90% -> 13500 | DU25: 14000 | DV25: 10000 | DW25: 12000 | DX25: =CX25*90% -> 8100 | DY25: =SUM(DM25:DX25) -> 141220 | DZ25: 71809 | EA25: 100856 | EB25: =+DO25*$G$25 -> 72900 | EC25: =+DP25*$G$25 -> 60000 | ED25: =+DQ25*$G$25 -> 36450 | EE25: =+DR25*$G$25 -> 54000 | EF25: =+DS25*$G$25 -> 54000 | EG25: =+DT25*$G$25 -> 67500 | EH25: =+DU25*$G$25 -> 70000 | EI25: =+DV25*$G$25 -> 50000 | ... EK25: =+DX25*$G$25 -> 40500 | EL25: =SUM(DZ25:EK25) -> 738015
A26: Qualcomm | B26: MTP Pakala | C26: MTP/IDP | D26: 5 | E26: 5 | F26: 5 | G26: 5 | H26: 5 | I26: 5 | J26: 5 | K26: 5 | M26: 4030 | N26: 17154 | O26: 16482 | P26: 3700 | Q26: 3100 | R26: 2459 | S26: =2460+3164 -> 5624 | T26: 25000 | U26: 30000 | V26: 29000 | W26: 26500 | X26: 20000 | Y26: =SUM(M26:X26) -> 183049 | Z26: =37810.08-12651 -> 25159.08 | AA26: =35512.008+29047-6856 -> 57703.008 | AB26: 70867.096 | AC26: 30306.5 | AD26: =33535.6+2322 -> 35857.6 | AE26: 43003.97 | AF26: 64432.62 | AG26: =+T26*$G$25-39000 -> 86000 | AH26: =+U26*$G$25 -> 150000 | AI26: =+V26*$G$25 -> 145000 | AJ26: =+W26*$G$25 -> 132500 | AK26: =+X26*$G$25 -> 100000 | AL26: =SUM(Z26:AK26) -> 940829.87 | AM26: 15000 | AN26: =N26*90% -> 15438.6 | AO26: 15000 | AP26: 12000 | AQ26: =Q26*90% -> 2790 | AR26: =R26*90% -> 2213.1 | AS26: =S26*90% -> 5061.6 | AT26: 25000 | AU26: 30000 | AV26: 20000 | AW26: 20000 | AX26: =X26*90% -> 18000 | AY26: =SUM(AM26:AX26) -> 180503.3 | AZ26: =AM26*$H26 -> 75000 | BA26: =AN26*$H26 -> 77193 | BB26: =AO26*$H26 -> 75000 | BC26: =AP26*$H26 -> 60000 | BD26: =AQ26*$H26 -> 13950 | BE26: =AR26*$H26 -> 11065.5 | BF26: =AS26*$H26 -> 25308 | BG26: =AT26*$H26 -> 125000 | ... BK26: =AX26*$H26 -> 90000 | BL26: =SUM(AZ26:BK26) -> 902516.5 | BM26: 15000 | BN26: 15000 | BO26: 15000 | BP26: =AP26*90% -> 10800 | BQ26: 16000 | BR26: 16000 | BS26: 16000 | BT26: 25000 | BU26: 30000 | BV26: 20000 | BW26: 20000 | BX26: 15000 | BY26: =SUM(BM26:BX26) -> 213800 | BZ26: =+BM26*$G$25 -> 75000 | CA26: =+BN26*$G$25 -> 75000 | CB26: =+BO26*$G$25 -> 75000 | CC26: =+BP26*$G$25 -> 54000 | CD26: =+BQ26*$G$25 -> 80000 | CE26: =+BR26*$G$25 -> 80000 | CF26: =+BS26*$G$25 -> 80000 | CG26: =+BT26*$G$25 -> 125000 | ... CK26: =+BX26*$G$25 -> 75000 | CL26: =SUM(BZ26:CK26) -> 1069000 | CM26: 15000 | CN26: =BN26*90% -> 13500 | CO26: 20000 | CP26: 15000 | CQ26: =BQ26*90% -> 14400 | CR26: =BR26*90% -> 14400 | CS26: =BS26*90% -> 14400 | CT26: 25000 | CU26: 30000 | CV26: 22000 | CW26: 20000 | CX26: =BX26*90% -> 13500 | CY26: =SUM(CM26:CX26) -> 217200 | CZ26: =+CM26*$G$25 -> 75000 | DA26: =+CN26*$G$25 -> 67500 | DB26: =+CO26*$G$25 -> 100000 | DC26: =+CP26*$G$25 -> 75000 | DD26: =+CQ26*$G$25 -> 72000 | DE26: =+CR26*$G$25 -> 72000 | DF26: =+CS26*$G$25 -> 72000 | DG26: =+CT26*$G$25 -> 125000 | ... DK26: =+CX26*$G$25 -> 67500 | DL26: =SUM(CZ26:DK26) -> 1086000 | DM26: 3000 | DN26: =CN26*90% -> 12150 | DO26: =CO26*90% -> 18000 | DP26: =CP26*90% -> 13500 | DQ26: =CQ26*90% -> 12960 | DR26: =CR26*90% -> 12960 | DS26: =CS26*90% -> 12960 | DT26: 25000 | DU26: 30000 | DV26: 20000 | DW26: 20000 | DX26: =CX26*90% -> 12150 | DY26: =SUM(DM26:DX26) -> 192680 | DZ26: 71809 | EA26: 100856 | EB26: =+DO26*$G$25 -> 90000 | EC26: =+DP26*$G$25 -> 67500 | ED26: =+DQ26*$G$25 -> 64800 | EE26: =+DR26*$G$25 -> 64800 | EF26: =+DS26*$G$25 -> 64800 | EG26: =+DT26*$G$25 -> 125000 | EH26: =+DU26*$G$25 -> 150000 | EI26: =+DV26*$G$25 -> 100000 | ... EK26: =+DX26*$G$25 -> 60750 | EL26: =SUM(DZ26:EK26) -> 1060315
A27: Qualcomm | B27: LDS Antenna | C27: LDS | D27: 9.38 | E27: 9.38 | F27: 9.38 | G27: 9.38 | H27: 9.38 | I27: 9.38 | J27: 9.38 | K27: 9.38 | M27: 3980 | N27: 6109 | O27: 10411 | P27: 2302 | Q27: 5570 | R27: 1728 | S27: =850+500 -> 1350 | T27: 2000 | U27: 5000 | V27: 7000 | W27: 9000 | X27: 2000 | Y27: =SUM(M27:X27) -> 56450 | Z27: 37326 | AA27: 22258 | AB27: 83632.507 | AC27: 14608.99 | AD27: 57085.126 | AE27: 15921 | AF27: 17686.2 | AG27: =+T27*$G$25 -> 10000 | AH27: =+U27*$G$25 -> 25000 | AI27: =+V27*$G$25 -> 35000 | AJ27: =+W27*$G$25 -> 45000 | AK27: =+X27*$G$25 -> 10000 | AL27: =SUM(Z27:AK27) -> 373517.82 | AM27: 10000 | AN27: 5500 | AO27: 5600 | AP27: 4500 | AQ27: 1500 | AR27: 1500 | AS27: 2000 | AT27: 2500 | AU27: =U27*90% -> 4500 | AV27: 6000 | AW27: =W27*90% -> 8100 | AX27: 4000 | AY27: =SUM(AM27:AX27) -> 55700 | AZ27: =AM27*$H27 -> 93800 | BA27: =AN27*$H27 -> 51590 | BB27: =AO27*$H27 -> 52528 | BC27: =AP27*$H27 -> 42210 | BD27: =AQ27*$H27 -> 14070 | BE27: =AR27*$H27 -> 14070 | BF27: =AS27*$H27 -> 18760 | BG27: =AT27*$H27 -> 23450 | ... BK27: =AX27*$H27 -> 37520 | BL27: =SUM(AZ27:BK27) -> 522466 | BM27: 3500 | BN27: 5500 | BO27: 5600 | BP27: 4500 | BQ27: 1500 | BR27: 1500 | BS27: 2000 | BT27: 2500 | BU27: =AU27*90% -> 4050 | BV27: 6000 | BW27: =AW27*90% -> 7290 | BX27: 4000 | BY27: =SUM(BM27:BX27) -> 47940 | BZ27: =+BM27*$G$25 -> 17500 | CA27: =+BN27*$G$25 -> 27500 | CB27: =+BO27*$G$25 -> 28000 | CC27: =+BP27*$G$25 -> 22500 | CD27: =+BQ27*$G$25 -> 7500 | CE27: =+BR27*$G$25 -> 7500 | CF27: =+BS27*$G$25 -> 10000 | CG27: =+BT27*$G$25 -> 12500 | ... CK27: =+BX27*$G$25 -> 20000 | CL27: =SUM(BZ27:CK27) -> 239700 | CM27: 5000 | CN27: 5500 | CO27: 5600 | CP27: 4500 | CQ27: 1500 | CR27: 1500 | CS27: 2000 | CT27: 2500 | CU27: =BU27*90% -> 3645 | CV27: 6000 | CW27: =BW27*90% -> 6561 | CX27: 4000 | CY27: =SUM(CM27:CX27) -> 48306 | CZ27: =+CM27*$G$25 -> 25000 | DA27: =+CN27*$G$25 -> 27500 | DB27: =+CO27*$G$25 -> 28000 | DC27: =+CP27*$G$25 -> 22500 | DD27: =+CQ27*$G$25 -> 7500 | DE27: =+CR27*$G$25 -> 7500 | DF27: =+CS27*$G$25 -> 10000 | DG27: =+CT27*$G$25 -> 12500 | ... DK27: =+CX27*$G$25 -> 20000 | DL27: =SUM(CZ27:DK27) -> 241530 | DM27: 3500 | DN27: 5500 | DO27: 5600 | DP27: 4500 | DQ27: 1500 | DR27: 1500 | DS27: 2000 | DT27: 2500 | DU27: =CU27*90% -> 3280.5 | DV27: 6000 | DW27: =CW27*90% -> 5904.9 | DX27: 4000 | DY27: =SUM(DM27:DX27) -> 45785.4 | DZ27: 71809 | EA27: 100856 | EB27: =+DO27*$G$25 -> 28000 | EC27: =+DP27*$G$25 -> 22500 | ED27: =+DQ27*$G$25 -> 7500 | EE27: =+DR27*$G$25 -> 7500 | EF27: =+DS27*$G$25 -> 10000 | EG27: =+DT27*$G$25 -> 12500 | EH27: =+DU27*$G$25 -> 16402.5 | EI27: =+DV27*$G$25 -> 30000 | ... EK27: =+DX27*$G$25 -> 20000 | EL27: =SUM(DZ27:EK27) -> 356592
A28: Qualcomm | B28: Tooling | C28: Tooling USA | D28: 10000 | E28: 10000 | F28: 10000 | G28: 10000 | H28: 10000 | I28: 10000 | J28: 10000 | K28: 10000 | P28: 18 | Q28: 4 | R28: 5 | T28: 7 | V28: 5 | X28: 5 | Y28: =SUM(M28:X28) -> 44 | Z28: 0 | AB28: =O28*$D$25 -> 0 | AC28: 14233.85 | AD28: =8841.91-1403.36 -> 7438.55 | AE28: 10497.5 | AG28: 39000 | AH28: =U28*$D$28 -> 0 | AI28: =V28*$D$28 -> 50000 | AJ28: =W28*$D$28 -> 0 | AK28: =X28*$D$28 -> 50000 | AL28: =SUM(Z28:AK28) -> 171169.9 | AM28: =M28*90% -> 0 | AN28: =N28*90% -> 0 | AO28: =O28*90% -> 0 | AP28: =P28*90% -> 16.2 | AQ28: 4 | AR28: =R28*90% -> 4.5 | AS28: 4 | AT28: =T28*90% -> 6.3 | AU28: =U28*90% -> 0 | AV28: 4 | AW28: =W28*90% -> 0 | AX28: 4 | AY28: =SUM(AM28:AX28) -> 43 | AZ28: =AM28*$H28 -> 0 | BA28: =AN28*$H28 -> 0 | BB28: =AO28*$H28 -> 0 | BC28: =AP28*$H28 -> 162000 | BD28: =AQ28*$H28 -> 40000 | BE28: =AR28*$H28 -> 45000 | BF28: =AS28*$H28 -> 40000 | BG28: =AT28*$H28 -> 63000 | ... BK28: =AX28*$H28 -> 40000 | BL28: =SUM(AZ28:BK28) -> 430000 | BM28: =AM28*90% -> 0 | BN28: =AN28*90% -> 0 | BO28: =AO28*90% -> 0 | BP28: =AP28*90% -> 14.58 | BQ28: 4 | BR28: =AR28*90% -> 4.05 | BS28: 4 | BT28: =AT28*90% -> 5.67 | BU28: =AU28*90% -> 0 | BV28: 4 | BW28: =AW28*90% -> 0 | BX28: 4 | BY28: =SUM(BM28:BX28) -> 40.3 | BZ28: 0 | CB28: =BO28*$D$25 -> 0 | CC28: =BP28*$D$25 -> 72.9 | CD28: =BQ28*$D$28 -> 40000 | CE28: =BR28*$D$28 -> 40500 | CF28: =BS28*$D$28 -> 40000 | CG28: =BT28*$D$28 -> 56700 | CH28: =BU28*$D$28 -> 0 | CI28: =BV28*$D$28 -> 40000 | CJ28: =BW28*$D$28 -> 0 | CK28: =BX28*$D$28 -> 40000 | CL28: =SUM(BZ28:CK28) -> 257272.9 | CM28: =BM28*90% -> 0 | CN28: =BN28*90% -> 0 | CO28: =BO28*90% -> 0 | CP28: =BP28*90% -> 13.122 | CQ28: 4 | CR28: =BR28*90% -> 3.645 | CS28: 4 | CT28: =BT28*90% -> 5.103 | CU28: =BU28*90% -> 0 | CV28: 4 | CW28: =BW28*90% -> 0 | CX28: 4 | CY28: =SUM(CM28:CX28) -> 37.87 | CZ28: 0 | DB28: =CO28*$D$25 -> 0 | DC28: =CP28*$D$25 -> 65.61 | DD28: =CQ28*$D$28 -> 40000 | DE28: =CR28*$D$28 -> 36450 | DF28: =CS28*$D$28 -> 40000 | DG28: =CT28*$D$28 -> 51030 | DH28: =CU28*$D$28 -> 0 | DI28: =CV28*$D$28 -> 40000 | DJ28: =CW28*$D$28 -> 0 | DK28: =CX28*$D$28 -> 40000 | DL28: =SUM(CZ28:DK28) -> 247545.61 | DM28: =CM28*90% -> 0 | DN28: =CN28*90% -> 0 | DO28: =CO28*90% -> 0 | DP28: =CP28*90% -> 11.8098 | DQ28: 4 | DR28: =CR28*90% -> 3.2805 | DS28: 4 | DT28: =CT28*90% -> 4.5927 | DU28: =CU28*90% -> 0 | DV28: 4 | DW28: =CW28*90% -> 0 | DX28: 4 | DY28: =SUM(DM28:DX28) -> 35.683 | DZ28: 0 | EB28: =DO28*$D$25 -> 0 | EC28: =DP28*$D$25 -> 59.049 | ED28: =DQ28*$D$28 -> 40000 | EE28: =DR28*$D$28 -> 32805 | EF28: =DS28*$D$28 -> 40000 | EG28: =DT28*$D$28 -> 45927 | EH28: =DU28*$D$28 -> 0 | EI28: =DV28*$D$28 -> 40000 | EJ28: =DW28*$D$28 -> 0 | EK28: =DX28*$D$28 -> 40000 | EL28: =SUM(DZ28:EK28) -> 238791.05
A29: Qualcomm Total | M29: =SUM(M25:M28) -> 26010 | N29: =SUM(N25:N28) -> 38263 | O29: =SUM(O25:O28) -> 52393 | P29: =SUM(P25:P28) -> 11839 | Q29: =SUM(Q25:Q28) -> 49150 | R29: =SUM(R25:R28) -> 10942 | S29: =SUM(S25:S28) -> 17024 | T29: =SUM(T25:T28) -> 44007 | ... EL29: =SUM(EL25:EL28) -> 2393713
A30: LG Innotek | B30: (GEN3/AL5) - YT | C30: 3CAC00159A | D30: 2.18 | E30: 2.192524 | F30: 2.2047277 | G30: 2.24 | H30: =G30 -> 2.24 | I30: =H30 -> 2.24 | J30: =I30 -> 2.24 | K30: =J30 -> 2.24 | M30: 30240 | N30: 31968 | O30: 44664 | Q30: 22140 | R30: 36288 | S30: 12612 | T30: 15000 | U30: 20000 | V30: 25000 | W30: 25000 | X30: 25000 | Y30: =SUM(M30:X30) -> 287912 | Z30: 65923.2 | AA30: 69690.24 | AB30: 97367.52 | AC30: =P30*$E30 -> 0 | AD30: =48265.2 -> 48265.2 | AE30: 79447.92 | AF30: =S30*2.19 -> 27620.28 | AG30: =T30*$F30 -> 33070.915 | AH30: =U30*$F30 -> 44094.554 | AI30: =V30*$G30 -> 56000 | AJ30: =W30*$G30 -> 56000 | AK30: =X30*$G30 -> 56000 | AL30: =SUM(Z30:AK30) -> 633479.83 | AM30: =291388/12 -> 24282.333 | AN30: =291388/12 -> 24282.333 | AO30: =291388/12 -> 24282.333 | AP30: =291388/12 -> 24282.333 | AQ30: =291388/12 -> 24282.333 | AR30: =291388/12 -> 24282.333 | AS30: =291388/12 -> 24282.333 | AT30: =291388/12 -> 24282.333 | ... AX30: =291388/12 -> 24282.333 | AY30: =SUM(AM30:AX30) -> 291388 | AZ30: =AM30*$H30 -> 54392.427 | BA30: =AN30*$H30 -> 54392.427 | BB30: =AO30*$H30 -> 54392.427 | BC30: =AP30*$H30 -> 54392.427 | BD30: =AQ30*$H30 -> 54392.427 | BE30: =AR30*$H30 -> 54392.427 | BF30: =AS30*$H30 -> 54392.427 | BG30: =AT30*$H30 -> 54392.427 | ... BK30: =AX30*$H30 -> 54392.427 | BL30: =SUM(AZ30:BK30) -> 652709.12 | BY30: =SUM(BM30:BX30) -> 0 | BZ30: =BM30*$I30 -> 0 | CA30: =BN30*$I30 -> 0 | CB30: =BO30*$I30 -> 0 | CC30: =BP30*$I30 -> 0 | CD30: =BQ30*$I30 -> 0 | CE30: =BR30*$I30 -> 0 | CF30: =BS30*$I30 -> 0 | CG30: =BT30*$I30 -> 0 | ... CK30: =BX30*$I30 -> 0 | CL30: =SUM(BZ30:CK30) -> 0 | CY30: =SUM(CM30:CX30) -> 0 | CZ30: =CM30*$J30 -> 0 | DA30: =CN30*$J30 -> 0 | DB30: =CO30*$J30 -> 0 | DC30: =CP30*$J30 -> 0 | DD30: =CQ30*$J30 -> 0 | DE30: =CR30*$J30 -> 0 | DF30: =CS30*$J30 -> 0 | DG30: =CT30*$J30 -> 0 | ... DK30: =CX30*$J30 -> 0 | DL30: =SUM(CZ30:DK30) -> 0 | DY30: =SUM(DM30:DX30) -> 0 | DZ30: =DM30*$K30 -> 0 | EA30: =DN30*$K30 -> 0 | EB30: =DO30*$K30 -> 0 | EC30: =DP30*$K30 -> 0 | ED30: =DQ30*$K30 -> 0 | EE30: =DR30*$K30 -> 0 | EF30: =DS30*$K30 -> 0 | EG30: =DT30*$K30 -> 0 | ... EK30: =DX30*$K30 -> 0 | EL30: =SUM(DZ30:EK30) -> 0
A31: LG Innotek | B31: (GEN3/AL6) - YT | C31: 3CAC00160A | D31: 2.22 | E31: 2.0829704 | F31: 2.2452525 | G31: 2.28 | H31: =G31 -> 2.28 | I31: =H31 -> 2.28 | J31: =I31 -> 2.28 | K31: =J31 -> 2.28 | M31: 1512 | N31: 1728 | O31: 1728 | P31: 1728 | Q31: 0 | R31: 0 | S31: 0 | T31: 0 | U31: 0 | V31: 2000 | W31: 2000 | X31: 2000 | Y31: =SUM(M31:X31) -> 12696 | Z31: 3356.64 | AA31: 3629 | AB31: 3836.16 | AC31: 3836.16 | AD31: 0 | AE31: 0 | AF31: =S31*$F31 -> 0 | AG31: =T31*$F31 -> 0 | AH31: =U31*$F31 -> 0 | AI31: =V31*$G31 -> 4560 | AJ31: =W31*$G31 -> 4560 | AK31: =X31*$G31 -> 4560 | AL31: =SUM(Z31:AK31) -> 28337.96 | AM31: =41547/12 -> 3462.25 | AN31: =41547/12 -> 3462.25 | AO31: =41547/12 -> 3462.25 | AP31: =41547/12 -> 3462.25 | AQ31: =41547/12 -> 3462.25 | AR31: =41547/12 -> 3462.25 | AS31: =41547/12 -> 3462.25 | AT31: =41547/12 -> 3462.25 | ... AX31: =41547/12 -> 3462.25 | AY31: =SUM(AM31:AX31) -> 41547 | AZ31: =AM31*$H31 -> 7893.93 | BA31: =AN31*$H31 -> 7893.93 | BB31: =AO31*$H31 -> 7893.93 | BC31: =AP31*$H31 -> 7893.93 | BD31: =AQ31*$H31 -> 7893.93 | BE31: =AR31*$H31 -> 7893.93 | BF31: =AS31*$H31 -> 7893.93 | BG31: =AT31*$H31 -> 7893.93 | ... BK31: =AX31*$H31 -> 7893.93 | BL31: =SUM(AZ31:BK31) -> 94727.16 | BY31: =SUM(BM31:BX31) -> 0 | BZ31: =BM31*$I31 -> 0 | CA31: =BN31*$I31 -> 0 | CB31: =BO31*$I31 -> 0 | CC31: =BP31*$I31 -> 0 | CD31: =BQ31*$I31 -> 0 | CE31: =BR31*$I31 -> 0 | CF31: =BS31*$I31 -> 0 | CG31: =BT31*$I31 -> 0 | ... CK31: =BX31*$I31 -> 0 | CL31: =SUM(BZ31:CK31) -> 0 | CY31: =SUM(CM31:CX31) -> 0 | CZ31: =CM31*$J31 -> 0 | DA31: =CN31*$J31 -> 0 | DB31: =CO31*$J31 -> 0 | DC31: =CP31*$J31 -> 0 | DD31: =CQ31*$J31 -> 0 | DE31: =CR31*$J31 -> 0 | DF31: =CS31*$J31 -> 0 | DG31: =CT31*$J31 -> 0 | ... DK31: =CX31*$J31 -> 0 | DL31: =SUM(CZ31:DK31) -> 0 | DY31: =SUM(DM31:DX31) -> 0 | DZ31: =DM31*$K31 -> 0 | EA31: =DN31*$K31 -> 0 | EB31: =DO31*$K31 -> 0 | EC31: =DP31*$K31 -> 0 | ED31: =DQ31*$K31 -> 0 | EE31: =DR31*$K31 -> 0 | EF31: =DS31*$K31 -> 0 | EG31: =DT31*$K31 -> 0 | ... EK31: =DX31*$K31 -> 0 | EL31: =SUM(DZ31:EK31) -> 0
A32: LG Innotek | B32: (GEN3/AL5) - MX | C32: 3CAC00159A_MX | D32: 2.04 | E32: 2.052524 | F32: 2.0647277 | G32: 2.1 | H32: =G32 -> 2.1 | I32: =H32 -> 2.1 | J32: =I32 -> 2.1 | K32: =J32 -> 2.1 | M32: 50976 | N32: 55296 | O32: 62708 | P32: 60736 | Q32: =79508-250 -> 79258 | R32: 57664 | S32: =8640+8640 -> 17280 | V32: 12960 | W32: 12960 | X32: 12960 | Y32: =SUM(M32:X32) -> 422798 | Z32: 106600.32 | AA32: 114612.91 | AB32: 134262.48 | AC32: 123901.44 | AD32: =166766.32-2625 -> 164141.32 | AE32: 117824.64 | AF32: =17280*2.05 -> 35424 | AG32: =T32*$F32 -> 0 | AH32: =U32*$F32 -> 0 | AI32: =V32*$G32 -> 27216 | AJ32: =W32*$G32 -> 27216 | AK32: =X32*$G32 -> 27216 | AL32: =SUM(Z32:AK32) -> 878415.11 | AM32: =317402/12 -> 26450.167 | AN32: =317402/12 -> 26450.167 | AO32: =317402/12 -> 26450.167 | AP32: =317402/12 -> 26450.167 | AQ32: =317402/12 -> 26450.167 | AR32: =317402/12 -> 26450.167 | AS32: =317402/12 -> 26450.167 | AT32: =317402/12 -> 26450.167 | ... AX32: =317402/12 -> 26450.167 | AY32: =SUM(AM32:AX32) -> 317402 | AZ32: =AM32*$H32 -> 55545.35 | BA32: =AN32*$H32 -> 55545.35 | BB32: =AO32*$H32 -> 55545.35 | BC32: =AP32*$H32 -> 55545.35 | BD32: =AQ32*$H32 -> 55545.35 | BE32: =AR32*$H32 -> 55545.35 | BF32: =AS32*$H32 -> 55545.35 | BG32: =AT32*$H32 -> 55545.35 | ... BK32: =AX32*$H32 -> 55545.35 | BL32: =SUM(AZ32:BK32) -> 666544.2 | BY32: =SUM(BM32:BX32) -> 0 | BZ32: =BM32*$I32 -> 0 | CA32: =BN32*$I32 -> 0 | CB32: =BO32*$I32 -> 0 | CC32: =BP32*$I32 -> 0 | CD32: =BQ32*$I32 -> 0 | CE32: =BR32*$I32 -> 0 | CF32: =BS32*$I32 -> 0 | CG32: =BT32*$I32 -> 0 | ... CK32: =BX32*$I32 -> 0 | CL32: =SUM(BZ32:CK32) -> 0 | CY32: =SUM(CM32:CX32) -> 0 | CZ32: =CM32*$J32 -> 0 | DA32: =CN32*$J32 -> 0 | DB32: =CO32*$J32 -> 0 | DC32: =CP32*$J32 -> 0 | DD32: =CQ32*$J32 -> 0 | DE32: =CR32*$J32 -> 0 | DF32: =CS32*$J32 -> 0 | DG32: =CT32*$J32 -> 0 | ... DK32: =CX32*$J32 -> 0 | DL32: =SUM(CZ32:DK32) -> 0 | DY32: =SUM(DM32:DX32) -> 0 | DZ32: =DM32*$K32 -> 0 | EA32: =DN32*$K32 -> 0 | EB32: =DO32*$K32 -> 0 | EC32: =DP32*$K32 -> 0 | ED32: =DQ32*$K32 -> 0 | EE32: =DR32*$K32 -> 0 | EF32: =DS32*$K32 -> 0 | EG32: =DT32*$K32 -> 0 | ... EK32: =DX32*$K32 -> 0 | EL32: =SUM(DZ32:EK32) -> 0
A33: LG Innotek | B33: (GEN3/AL6) - MX | C33: 3CAC00160A_MX | D33: 2.07 | E33: 2.0829704 | F33: 2.0952525 | G33: 2.13 | H33: =G33 -> 2.13 | I33: =H33 -> 2.13 | J33: =I33 -> 2.13 | K33: =J33 -> 2.13 | M33: 2592 | N33: 6912 | O33: 8928 | P33: 0 | S33: 8640 | V33: 14688 | W33: 11232 | X33: 10000 | Y33: =SUM(M33:X33) -> 62992 | Z33: 42347.52 | AA33: 14584.32 | AB33: 18838.08 | AC33: =P33*$E33 -> 0 | AD33: =Q33*$E33 -> 0 | AF33: =8640*2.1 -> 18144 | AG33: =T33*$F33 -> 0 | AH33: =U33*$F33 -> 0 | AI33: =V33*$G33 -> 31285.44 | AJ33: =W33*$G33 -> 23924.16 | AK33: =X33*$G33 -> 21300 | AL33: =SUM(Z33:AK33) -> 170423.52 | AM33: =111436/12 -> 9286.3333 | AN33: =111436/12 -> 9286.3333 | AO33: =111436/12 -> 9286.3333 | AP33: =111436/12 -> 9286.3333 | AQ33: =111436/12 -> 9286.3333 | AR33: =111436/12 -> 9286.3333 | AS33: =111436/12 -> 9286.3333 | AT33: =111436/12 -> 9286.3333 | ... AX33: =111436/12 -> 9286.3333 | AY33: =SUM(AM33:AX33) -> 111436 | AZ33: =AM33*$H33 -> 19779.89 | BA33: =AN33*$H33 -> 19779.89 | BB33: =AO33*$H33 -> 19779.89 | BC33: =AP33*$H33 -> 19779.89 | BD33: =AQ33*$H33 -> 19779.89 | BE33: =AR33*$H33 -> 19779.89 | BF33: =AS33*$H33 -> 19779.89 | BG33: =AT33*$H33 -> 19779.89 | ... BK33: =AX33*$H33 -> 19779.89 | BL33: =SUM(AZ33:BK33) -> 237358.68 | BY33: =SUM(BM33:BX33) -> 0 | BZ33: =BM33*$I33 -> 0 | CA33: =BN33*$I33 -> 0 | CB33: =BO33*$I33 -> 0 | CC33: =BP33*$I33 -> 0 | CD33: =BQ33*$I33 -> 0 | CE33: =BR33*$I33 -> 0 | CF33: =BS33*$I33 -> 0 | CG33: =BT33*$I33 -> 0 | ... CK33: =BX33*$I33 -> 0 | CL33: =SUM(BZ33:CK33) -> 0 | CY33: =SUM(CM33:CX33) -> 0 | CZ33: =CM33*$J33 -> 0 | DA33: =CN33*$J33 -> 0 | DB33: =CO33*$J33 -> 0 | DC33: =CP33*$J33 -> 0 | DD33: =CQ33*$J33 -> 0 | DE33: =CR33*$J33 -> 0 | DF33: =CS33*$J33 -> 0 | DG33: =CT33*$J33 -> 0 | ... DK33: =CX33*$J33 -> 0 | DL33: =SUM(CZ33:DK33) -> 0 | DY33: =SUM(DM33:DX33) -> 0 | DZ33: =DM33*$K33 -> 0 | EA33: =DN33*$K33 -> 0 | EB33: =DO33*$K33 -> 0 | EC33: =DP33*$K33 -> 0 | ED33: =DQ33*$K33 -> 0 | EE33: =DR33*$K33 -> 0 | EF33: =DS33*$K33 -> 0 | EG33: =DT33*$K33 -> 0 | ... EK33: =DX33*$K33 -> 0 | EL33: =SUM(DZ33:EK33) -> 0
A34: LG Innotek | B34: (GEN3/AL5) - YT (추가물량) | C34: 3CAC00159A | H34: 2.44 | I34: =H34 -> 2.44 | J34: =I34 -> 2.44 | K34: =J34 -> 2.44 | Y34: =SUM(M34:X34) -> 0 | Z34: =M34*$D34 -> 0 | AA34: =N34*$D34 -> 0 | AB34: 0 | AC34: =P34*$E34 -> 0 | AD34: =Q34*$E34 -> 0 | AE34: 0 | AF34: =S34*$F34 -> 0 | AG34: =T34*$F34 -> 0 | AH34: =U34*$F34 -> 0 | AI34: =V34*$G34 -> 0 | AJ34: =W34*$G34 -> 0 | AK34: =X34*$G34 -> 0 | AL34: =SUM(Z34:AK34) -> 0 | AY34: =SUM(AM34:AX34) -> 0 | AZ34: =AM34*$H34 -> 0 | BA34: =AN34*$H34 -> 0 | BB34: =AO34*$H34 -> 0 | BC34: =AP34*$H34 -> 0 | BD34: =AQ34*$H34 -> 0 | BE34: =AR34*$H34 -> 0 | BF34: =AS34*$H34 -> 0 | BG34: =AT34*$H34 -> 0 | ... BK34: =AX34*$H34 -> 0 | BL34: =SUM(AZ34:BK34) -> 0 | BM34: =522815/12 -> 43567.917 | BN34: =522815/12 -> 43567.917 | BO34: =522815/12 -> 43567.917 | BP34: =522815/12 -> 43567.917 | BQ34: =522815/12 -> 43567.917 | BR34: =522815/12 -> 43567.917 | BS34: =522815/12 -> 43567.917 | BT34: =522815/12 -> 43567.917 | ... BX34: =522815/12 -> 43567.917 | BY34: =SUM(BM34:BX34) -> 522815 | BZ34: =BM34*$I34 -> 106305.72 | CA34: =BN34*$I34 -> 106305.72 | CB34: =BO34*$I34 -> 106305.72 | CC34: =BP34*$I34 -> 106305.72 | CD34: =BQ34*$I34 -> 106305.72 | CE34: =BR34*$I34 -> 106305.72 | CF34: =BS34*$I34 -> 106305.72 | CG34: =BT34*$I34 -> 106305.72 | ... CK34: =BX34*$I34 -> 106305.72 | CL34: =SUM(BZ34:CK34) -> 1275668.6 | CM34: =351187/12 -> 29265.583 | CN34: =351187/12 -> 29265.583 | CO34: =351187/12 -> 29265.583 | CP34: =351187/12 -> 29265.583 | CQ34: =351187/12 -> 29265.583 | CR34: =351187/12 -> 29265.583 | CS34: =351187/12 -> 29265.583 | CT34: =351187/12 -> 29265.583 | ... CX34: =351187/12 -> 29265.583 | CY34: =SUM(CM34:CX34) -> 351187 | CZ34: =CM34*$J34 -> 71408.023 | DA34: =CN34*$J34 -> 71408.023 | DB34: =CO34*$J34 -> 71408.023 | DC34: =CP34*$J34 -> 71408.023 | DD34: =CQ34*$J34 -> 71408.023 | DE34: =CR34*$J34 -> 71408.023 | DF34: =CS34*$J34 -> 71408.023 | DG34: =CT34*$J34 -> 71408.023 | ... DK34: =CX34*$J34 -> 71408.023 | DL34: =SUM(CZ34:DK34) -> 856896.28 | DM34: =330065/12 -> 27505.417 | DN34: =330065/12 -> 27505.417 | DO34: =330065/12 -> 27505.417 | DP34: =330065/12 -> 27505.417 | DQ34: =330065/12 -> 27505.417 | DR34: =330065/12 -> 27505.417 | DS34: =330065/12 -> 27505.417 | DT34: =330065/12 -> 27505.417 | ... DX34: =330065/12 -> 27505.417 | DY34: =SUM(DM34:DX34) -> 330065 | DZ34: =DM34*$K34 -> 67113.217 | EA34: =DN34*$K34 -> 67113.217 | EB34: =DO34*$K34 -> 67113.217 | EC34: =DP34*$K34 -> 67113.217 | ED34: =DQ34*$K34 -> 67113.217 | EE34: =DR34*$K34 -> 67113.217 | EF34: =DS34*$K34 -> 67113.217 | EG34: =DT34*$K34 -> 67113.217 | ... EK34: =DX34*$K34 -> 67113.217 | EL34: =SUM(DZ34:EK34) -> 805358.6
A35: LG Innotek | B35: (GEN3/AL6) - YT (추가물량) | C35: 3CAC00160A | H35: 2.66 | I35: =H35 -> 2.66 | J35: =I35 -> 2.66 | K35: =J35 -> 2.66 | Y35: =SUM(M35:X35) -> 0 | Z35: =M35*$D35 -> 0 | AA35: =N35*$D35 -> 0 | AB35: 0 | AC35: =P35*$E35 -> 0 | AD35: =Q35*$E35 -> 0 | AE35: 0 | AF35: =S35*$F35 -> 0 | AG35: =T35*$F35 -> 0 | AH35: =U35*$F35 -> 0 | AI35: =V35*$G35 -> 0 | AJ35: =W35*$G35 -> 0 | AK35: =X35*$G35 -> 0 | AL35: =SUM(Z35:AK35) -> 0 | AY35: =SUM(AM35:AX35) -> 0 | AZ35: =AM35*$H35 -> 0 | BA35: =AN35*$H35 -> 0 | BB35: =AO35*$H35 -> 0 | BC35: =AP35*$H35 -> 0 | BD35: =AQ35*$H35 -> 0 | BE35: =AR35*$H35 -> 0 | BF35: =AS35*$H35 -> 0 | BG35: =AT35*$H35 -> 0 | ... BK35: =AX35*$H35 -> 0 | BL35: =SUM(AZ35:BK35) -> 0 | BM35: =(109566+50161)/12 -> 13310.583 | BN35: =(109566+50161)/12 -> 13310.583 | BO35: =(109566+50161)/12 -> 13310.583 | BP35: =(109566+50161)/12 -> 13310.583 | BQ35: =(109566+50161)/12 -> 13310.583 | BR35: =(109566+50161)/12 -> 13310.583 | BS35: =(109566+50161)/12 -> 13310.583 | BT35: =(109566+50161)/12 -> 13310.583 | ... BX35: =(109566+50161)/12 -> 13310.583 | BY35: =SUM(BM35:BX35) -> 159727 | BZ35: =BM35*$I35 -> 35406.152 | CA35: =BN35*$I35 -> 35406.152 | CB35: =BO35*$I35 -> 35406.152 | CC35: =BP35*$I35 -> 35406.152 | CD35: =BQ35*$I35 -> 35406.152 | CE35: =BR35*$I35 -> 35406.152 | CF35: =BS35*$I35 -> 35406.152 | CG35: =BT35*$I35 -> 35406.152 | ... CK35: =BX35*$I35 -> 35406.152 | CL35: =SUM(BZ35:CK35) -> 424873.82 | CM35: =(80983+60194)/12 -> 11764.75 | CN35: =(80983+60194)/12 -> 11764.75 | CO35: =(80983+60194)/12 -> 11764.75 | CP35: =(80983+60194)/12 -> 11764.75 | CQ35: =(80983+60194)/12 -> 11764.75 | CR35: =(80983+60194)/12 -> 11764.75 | CS35: =(80983+60194)/12 -> 11764.75 | CT35: =(80983+60194)/12 -> 11764.75 | ... CX35: =(80983+60194)/12 -> 11764.75 | CY35: =SUM(CM35:CX35) -> 141177 | CZ35: =CM35*$J35 -> 31294.235 | DA35: =CN35*$J35 -> 31294.235 | DB35: =CO35*$J35 -> 31294.235 | DC35: =CP35*$J35 -> 31294.235 | DD35: =CQ35*$J35 -> 31294.235 | DE35: =CR35*$J35 -> 31294.235 | DF35: =CS35*$J35 -> 31294.235 | DG35: =CT35*$J35 -> 31294.235 | ... DK35: =CX35*$J35 -> 31294.235 | DL35: =SUM(CZ35:DK35) -> 375530.82 | DM35: =(854+60194)/12 -> 5087.3333 | DN35: =(854+60194)/12 -> 5087.3333 | DO35: =(854+60194)/12 -> 5087.3333 | DP35: =(854+60194)/12 -> 5087.3333 | DQ35: =(854+60194)/12 -> 5087.3333 | DR35: =(854+60194)/12 -> 5087.3333 | DS35: =(854+60194)/12 -> 5087.3333 | DT35: =(854+60194)/12 -> 5087.3333 | ... DX35: =(854+60194)/12 -> 5087.3333 | DY35: =SUM(DM35:DX35) -> 61048 | DZ35: =DM35*$K35 -> 13532.307 | EA35: =DN35*$K35 -> 13532.307 | EB35: =DO35*$K35 -> 13532.307 | EC35: =DP35*$K35 -> 13532.307 | ED35: =DQ35*$K35 -> 13532.307 | EE35: =DR35*$K35 -> 13532.307 | EF35: =DS35*$K35 -> 13532.307 | EG35: =DT35*$K35 -> 13532.307 | ... EK35: =DX35*$K35 -> 13532.307 | EL35: =SUM(DZ35:EK35) -> 162387.68
A36: LG Innotek | B36: (GEN3/AL5) - MX (추가물량) | C36: 3CAC00159A_MX | H36: =H34-0.14 -> 2.3 | I36: =H36 -> 2.3 | J36: =I36 -> 2.3 | K36: =J36 -> 2.3 | Y36: =SUM(M36:X36) -> 0 | Z36: =M36*$D36 -> 0 | AA36: =N36*$D36 -> 0 | AB36: 0 | AC36: =P36*$E36 -> 0 | AD36: =Q36*$E36 -> 0 | AE36: 0 | AF36: =S36*$F36 -> 0 | AG36: =T36*$F36 -> 0 | AH36: =U36*$F36 -> 0 | AI36: =V36*$G36 -> 0 | AJ36: =W36*$G36 -> 0 | AK36: =X36*$G36 -> 0 | AL36: =SUM(Z36:AK36) -> 0 | AY36: =SUM(AM36:AX36) -> 0 | AZ36: =AM36*$H36 -> 0 | BA36: =AN36*$H36 -> 0 | BB36: =AO36*$H36 -> 0 | BC36: =AP36*$H36 -> 0 | BD36: =AQ36*$H36 -> 0 | BE36: =AR36*$H36 -> 0 | BF36: =AS36*$H36 -> 0 | BG36: =AT36*$H36 -> 0 | ... BK36: =AX36*$H36 -> 0 | BL36: =SUM(AZ36:BK36) -> 0 | BY36: =SUM(BM36:BX36) -> 0 | BZ36: =BM36*$I36 -> 0 | CA36: =BN36*$I36 -> 0 | CB36: =BO36*$I36 -> 0 | CC36: =BP36*$I36 -> 0 | CD36: =BQ36*$I36 -> 0 | CE36: =BR36*$I36 -> 0 | CF36: =BS36*$I36 -> 0 | CG36: =BT36*$I36 -> 0 | ... CK36: =BX36*$I36 -> 0 | CL36: =SUM(BZ36:CK36) -> 0 | CY36: =SUM(CM36:CX36) -> 0 | CZ36: =CM36*$J36 -> 0 | DA36: =CN36*$J36 -> 0 | DB36: =CO36*$J36 -> 0 | DC36: =CP36*$J36 -> 0 | DD36: =CQ36*$J36 -> 0 | DE36: =CR36*$J36 -> 0 | DF36: =CS36*$J36 -> 0 | DG36: =CT36*$J36 -> 0 | ... DK36: =CX36*$J36 -> 0 | DL36: =SUM(CZ36:DK36) -> 0 | DY36: =SUM(DM36:DX36) -> 0 | DZ36: =DM36*$K36 -> 0 | EA36: =DN36*$K36 -> 0 | EB36: =DO36*$K36 -> 0 | EC36: =DP36*$K36 -> 0 | ED36: =DQ36*$K36 -> 0 | EE36: =DR36*$K36 -> 0 | EF36: =DS36*$K36 -> 0 | EG36: =DT36*$K36 -> 0 | ... EK36: =DX36*$K36 -> 0 | EL36: =SUM(DZ36:EK36) -> 0
A37: LG Innotek | B37: (GEN3/AL6) - MX (추가물량) | C37: 3CAC00160A_MX | H37: =H35-0.14 -> 2.52 | I37: =H37 -> 2.52 | J37: =I37 -> 2.52 | K37: =J37 -> 2.52 | Y37: =SUM(M37:X37) -> 0 | Z37: =M37*$D37 -> 0 | AA37: =N37*$D37 -> 0 | AB37: 0 | AC37: =P37*$E37 -> 0 | AD37: =Q37*$E37 -> 0 | AE37: 0 | AF37: =S37*$F37 -> 0 | AG37: =T37*$F37 -> 0 | AH37: =U37*$F37 -> 0 | AI37: =V37*$G37 -> 0 | AJ37: =W37*$G37 -> 0 | AK37: =X37*$G37 -> 0 | AL37: =SUM(Z37:AK37) -> 0 | AY37: =SUM(AM37:AX37) -> 0 | AZ37: =AM37*$H37 -> 0 | BA37: =AN37*$H37 -> 0 | BB37: =AO37*$H37 -> 0 | BC37: =AP37*$H37 -> 0 | BD37: =AQ37*$H37 -> 0 | BE37: =AR37*$H37 -> 0 | BF37: =AS37*$H37 -> 0 | BG37: =AT37*$H37 -> 0 | ... BK37: =AX37*$H37 -> 0 | BL37: =SUM(AZ37:BK37) -> 0 | BY37: =SUM(BM37:BX37) -> 0 | BZ37: =BM37*$I37 -> 0 | CA37: =BN37*$I37 -> 0 | CB37: =BO37*$I37 -> 0 | CC37: =BP37*$I37 -> 0 | CD37: =BQ37*$I37 -> 0 | CE37: =BR37*$I37 -> 0 | CF37: =BS37*$I37 -> 0 | CG37: =BT37*$I37 -> 0 | ... CK37: =BX37*$I37 -> 0 | CL37: =SUM(BZ37:CK37) -> 0 | CY37: =SUM(CM37:CX37) -> 0 | CZ37: =CM37*$J37 -> 0 | DA37: =CN37*$J37 -> 0 | DB37: =CO37*$J37 -> 0 | DC37: =CP37*$J37 -> 0 | DD37: =CQ37*$J37 -> 0 | DE37: =CR37*$J37 -> 0 | DF37: =CS37*$J37 -> 0 | DG37: =CT37*$J37 -> 0 | ... DK37: =CX37*$J37 -> 0 | DL37: =SUM(CZ37:DK37) -> 0 | DY37: =SUM(DM37:DX37) -> 0 | DZ37: =DM37*$K37 -> 0 | EA37: =DN37*$K37 -> 0 | EB37: =DO37*$K37 -> 0 | EC37: =DP37*$K37 -> 0 | ED37: =DQ37*$K37 -> 0 | EE37: =DR37*$K37 -> 0 | EF37: =DS37*$K37 -> 0 | EG37: =DT37*$K37 -> 0 | ... EK37: =DX37*$K37 -> 0 | EL37: =SUM(DZ37:EK37) -> 0
A38: LG Innotek | B38: (GEN2)EPS Motor Cover | C38: 3MAM00269A | D38: 2.1 | E38: 2.1077661 | F38: 2.1191326 | G38: 2.17 | H38: =G38 -> 2.17 | I38: =H38 -> 2.17 | J38: =I38 -> 2.17 | K38: =J38 -> 2.17 | M38: 22840 | N38: 14080 | O38: 21840 | P38: 23620 | Q38: 21180 | R38: 6713 | S38: 15120 | T38: 13927 | U38: 0 | V38: 10000 | Y38: =SUM(M38:X38) -> 149320 | Z38: 47964 | AA38: 29568 | AB38: 45864 | AC38: 49602 | AD38: 44478 | AE38: 14164.43 | AF38: =S38*2.11 -> 31903.2 | AG38: =T38*$F38 -> 29513.16 | AH38: =U38*$F38 -> 0 | AI38: =V38*$G38 -> 21700 | AJ38: =W38*$G38 -> 0 | AK38: =X38*$G38 -> 0 | AL38: =SUM(Z38:AK38) -> 314756.79 | AY38: =SUM(AM38:AX38) -> 0 | AZ38: =AM38*$H38 -> 0 | BA38: =AN38*$H38 -> 0 | BB38: =AO38*$H38 -> 0 | BC38: =AP38*$H38 -> 0 | BD38: =AQ38*$H38 -> 0 | BE38: =AR38*$H38 -> 0 | BF38: =AS38*$H38 -> 0 | BG38: =AT38*$H38 -> 0 | ... BK38: =AX38*$H38 -> 0 | BL38: =SUM(AZ38:BK38) -> 0 | BY38: =SUM(BM38:BX38) -> 0 | BZ38: =BM38*$I38 -> 0 | CA38: =BN38*$I38 -> 0 | CB38: =BO38*$I38 -> 0 | CC38: =BP38*$I38 -> 0 | CD38: =BQ38*$I38 -> 0 | CE38: =BR38*$I38 -> 0 | CF38: =BS38*$I38 -> 0 | CG38: =BT38*$I38 -> 0 | ... CK38: =BX38*$I38 -> 0 | CL38: =SUM(BZ38:CK38) -> 0 | CY38: =SUM(CM38:CX38) -> 0 | CZ38: =CM38*$J38 -> 0 | DA38: =CN38*$J38 -> 0 | DB38: =CO38*$J38 -> 0 | DC38: =CP38*$J38 -> 0 | DD38: =CQ38*$J38 -> 0 | DE38: =CR38*$J38 -> 0 | DF38: =CS38*$J38 -> 0 | DG38: =CT38*$J38 -> 0 | ... DK38: =CX38*$J38 -> 0 | DL38: =SUM(CZ38:DK38) -> 0 | DY38: =SUM(DM38:DX38) -> 0 | DZ38: =DM38*$K38 -> 0 | EA38: =DN38*$K38 -> 0 | EB38: =DO38*$K38 -> 0 | EC38: =DP38*$K38 -> 0 | ED38: =DQ38*$K38 -> 0 | EE38: =DR38*$K38 -> 0 | EF38: =DS38*$K38 -> 0 | EG38: =DT38*$K38 -> 0 | ... EK38: =DX38*$K38 -> 0 | EL38: =SUM(DZ38:EK38) -> 0
A39: LG Innotek | B39: Yubei 570W EPS Bracket | C39: 3MAM00541A | D39: 1.93 | E39: 1.9369627 | F39: 1.9481879 | G39: 1.96 | H39: =G39 -> 1.96 | I39: =H39 -> 1.96 | J39: =I39 -> 1.96 | K39: =J39 -> 1.96 | M39: 8000 | N39: 20600 | O39: 11400 | P39: =18920+1960 -> 20880 | Q39: 31120 | Y39: =SUM(M39:X39) -> 92000 | Z39: 15440 | AA39: 39758 | AB39: 22002 | AC39: 40298.4 | AD39: 60061.6 | AF39: =S39*$F39 -> 0 | AG39: =T39*$F39 -> 0 | AH39: =U39*$F39 -> 0 | AI39: =V39*$G39 -> 0 | AJ39: =W39*$G39 -> 0 | AK39: =X39*$G39 -> 0 | AL39: =SUM(Z39:AK39) -> 177560 | AY39: =SUM(AM39:AX39) -> 0 | AZ39: =AM39*$H39 -> 0 | BA39: =AN39*$H39 -> 0 | BB39: =AO39*$H39 -> 0 | BC39: =AP39*$H39 -> 0 | BD39: =AQ39*$H39 -> 0 | BE39: =AR39*$H39 -> 0 | BF39: =AS39*$H39 -> 0 | BG39: =AT39*$H39 -> 0 | ... BK39: =AX39*$H39 -> 0 | BL39: =SUM(AZ39:BK39) -> 0 | BY39: =SUM(BM39:BX39) -> 0 | BZ39: =BM39*$I39 -> 0 | CA39: =BN39*$I39 -> 0 | CB39: =BO39*$I39 -> 0 | CC39: =BP39*$I39 -> 0 | CD39: =BQ39*$I39 -> 0 | CE39: =BR39*$I39 -> 0 | CF39: =BS39*$I39 -> 0 | CG39: =BT39*$I39 -> 0 | ... CK39: =BX39*$I39 -> 0 | CL39: =SUM(BZ39:CK39) -> 0 | CY39: =SUM(CM39:CX39) -> 0 | CZ39: =CM39*$J39 -> 0 | DA39: =CN39*$J39 -> 0 | DB39: =CO39*$J39 -> 0 | DC39: =CP39*$J39 -> 0 | DD39: =CQ39*$J39 -> 0 | DE39: =CR39*$J39 -> 0 | DF39: =CS39*$J39 -> 0 | DG39: =CT39*$J39 -> 0 | ... DK39: =CX39*$J39 -> 0 | DL39: =SUM(CZ39:DK39) -> 0 | DY39: =SUM(DM39:DX39) -> 0 | DZ39: =DM39*$K39 -> 0 | EA39: =DN39*$K39 -> 0 | EB39: =DO39*$K39 -> 0 | EC39: =DP39*$K39 -> 0 | ED39: =DQ39*$K39 -> 0 | EE39: =DR39*$K39 -> 0 | EF39: =DS39*$K39 -> 0 | EG39: =DT39*$K39 -> 0 | ... EK39: =DX39*$K39 -> 0 | EL39: =SUM(DZ39:EK39) -> 0
A40: LG Innotek | B40: T6 Housing M6 | C40: 3HUC00006A | D40: 4.22 | E40: 4.2391922 | F40: 4.2625691 | G40: 4.38 | H40: =G40 -> 4.38 | I40: =H40 -> 4.38 | J40: =I40 -> 4.38 | K40: =J40 -> 4.38 | M40: 27216 | N40: 27632 | O40: 34776 | P40: =26200+6600 -> 32800 | Q40: 13284 | R40: 23148 | S40: 22177 | T40: 25000 | U40: 25000 | V40: 25000 | W40: 25000 | X40: 25000 | Y40: =SUM(M40:X40) -> 306033 | Z40: 116484.48 | AA40: 118265 | AB40: 146754.72 | AC40: =138416 -> 138416 | AD40: 57324.48 | AE40: 97830.72 | AF40: =S40*$F40 -> 94530.996 | AG40: =T40*$F40 -> 106564.23 | AH40: =U40*$F40 -> 106564.23 | AI40: =V40*$G40 -> 109500 | AJ40: =W40*$G40 -> 109500 | AK40: =X40*$G40 -> 109500 | AL40: =SUM(Z40:AK40) -> 1311234.9 | AM40: =322100/12 -> 26841.667 | AN40: =322100/12 -> 26841.667 | AO40: =322100/12 -> 26841.667 | AP40: =322100/12 -> 26841.667 | AQ40: =322100/12 -> 26841.667 | AR40: =322100/12 -> 26841.667 | AS40: =322100/12 -> 26841.667 | AT40: =322100/12 -> 26841.667 | ... AX40: =322100/12 -> 26841.667 | AY40: =SUM(AM40:AX40) -> 322100 | AZ40: =AM40*$H40 -> 117566.5 | BA40: =AN40*$H40 -> 117566.5 | BB40: =AO40*$H40 -> 117566.5 | BC40: =AP40*$H40 -> 117566.5 | BD40: =AQ40*$H40 -> 117566.5 | BE40: =AR40*$H40 -> 117566.5 | BF40: =AS40*$H40 -> 117566.5 | BG40: =AT40*$H40 -> 117566.5 | ... BK40: =AX40*$H40 -> 117566.5 | BL40: =SUM(AZ40:BK40) -> 1410798 | BM40: =322100/12 -> 26841.667 | BN40: =322100/12 -> 26841.667 | BO40: =322100/12 -> 26841.667 | BP40: =322100/12 -> 26841.667 | BQ40: =322100/12 -> 26841.667 | BR40: =322100/12 -> 26841.667 | BS40: =322100/12 -> 26841.667 | BT40: =322100/12 -> 26841.667 | ... BX40: =322100/12 -> 26841.667 | BY40: =SUM(BM40:BX40) -> 322100 | BZ40: =BM40*$I40 -> 117566.5 | CA40: =BN40*$I40 -> 117566.5 | CB40: =BO40*$I40 -> 117566.5 | CC40: =BP40*$I40 -> 117566.5 | CD40: =BQ40*$I40 -> 117566.5 | CE40: =BR40*$I40 -> 117566.5 | CF40: =BS40*$I40 -> 117566.5 | CG40: =BT40*$I40 -> 117566.5 | ... CK40: =BX40*$I40 -> 117566.5 | CL40: =SUM(BZ40:CK40) -> 1410798 | CM40: =300000/12 -> 25000 | CN40: =300000/12 -> 25000 | CO40: =300000/12 -> 25000 | CP40: =300000/12 -> 25000 | CQ40: =300000/12 -> 25000 | CR40: =300000/12 -> 25000 | CS40: =300000/12 -> 25000 | CT40: =300000/12 -> 25000 | ... CX40: =300000/12 -> 25000 | CY40: =SUM(CM40:CX40) -> 300000 | CZ40: =CM40*$J40 -> 109500 | DA40: =CN40*$J40 -> 109500 | DB40: =CO40*$J40 -> 109500 | DC40: =CP40*$J40 -> 109500 | DD40: =CQ40*$J40 -> 109500 | DE40: =CR40*$J40 -> 109500 | DF40: =CS40*$J40 -> 109500 | DG40: =CT40*$J40 -> 109500 | ... DK40: =CX40*$J40 -> 109500 | DL40: =SUM(CZ40:DK40) -> 1314000 | DM40: =300000/12 -> 25000 | DN40: =300000/12 -> 25000 | DO40: =300000/12 -> 25000 | DP40: =300000/12 -> 25000 | DQ40: =300000/12 -> 25000 | DR40: =300000/12 -> 25000 | DS40: =300000/12 -> 25000 | DT40: =300000/12 -> 25000 | ... DX40: =300000/12 -> 25000 | DY40: =SUM(DM40:DX40) -> 300000 | DZ40: =DM40*$K40 -> 109500 | EA40: =DN40*$K40 -> 109500 | EB40: =DO40*$K40 -> 109500 | EC40: =DP40*$K40 -> 109500 | ED40: =DQ40*$K40 -> 109500 | EE40: =DR40*$K40 -> 109500 | EF40: =DS40*$K40 -> 109500 | EG40: =DT40*$K40 -> 109500 | ... EK40: =DX40*$K40 -> 109500 | EL40: =SUM(DZ40:EK40) -> 1314000
A41: LG Innotek | B41: T6 Housing M8 | C41: 3HUC00007A | D41: 4.23 | E41: 4.2491922 | F41: 4.2725691 | G41: 4.4 | H41: =G41 -> 4.4 | I41: =H41 -> 4.4 | J41: =I41 -> 4.4 | K41: =J41 -> 4.4 | M41: 1841 | N41: 0 | O41: 300 | P41: 6300 | Q41: 6600 | R41: 6600 | S41: 6230 | T41: 6600 | U41: 6600 | V41: 5000 | W41: 5000 | X41: 5000 | Y41: =SUM(M41:X41) -> 56071 | Z41: 7916.3 | AA41: 0 | AB41: 1269 | AC41: 26649 | AD41: 27918 | AE41: 27918 | AF41: =S41*$F41 -> 26618.106 | AG41: =T41*$F41 -> 28198.956 | AH41: =U41*$F41 -> 28198.956 | AI41: =V41*$G41 -> 22000 | AJ41: =W41*$G41 -> 22000 | AK41: =X41*$G41 -> 22000 | AL41: =SUM(Z41:AK41) -> 240686.32 | AM41: =6095/12 -> 507.91667 | AN41: =6095/12 -> 507.91667 | AO41: =6095/12 -> 507.91667 | AP41: =6095/12 -> 507.91667 | AQ41: =6095/12 -> 507.91667 | AR41: =6095/12 -> 507.91667 | AS41: =6095/12 -> 507.91667 | AT41: =6095/12 -> 507.91667 | ... AX41: =6095/12 -> 507.91667 | AY41: =SUM(AM41:AX41) -> 6095 | AZ41: =AM41*$H41 -> 2234.8333 | BA41: =AN41*$H41 -> 2234.8333 | BB41: =AO41*$H41 -> 2234.8333 | BC41: =AP41*$H41 -> 2234.8333 | BD41: =AQ41*$H41 -> 2234.8333 | BE41: =AR41*$H41 -> 2234.8333 | BF41: =AS41*$H41 -> 2234.8333 | BG41: =AT41*$H41 -> 2234.8333 | ... BK41: =AX41*$H41 -> 2234.8333 | BL41: =SUM(AZ41:BK41) -> 26818 | BM41: =6095/12 -> 507.91667 | BN41: =6095/12 -> 507.91667 | BO41: =6095/12 -> 507.91667 | BP41: =6095/12 -> 507.91667 | BQ41: =6095/12 -> 507.91667 | BR41: =6095/12 -> 507.91667 | BS41: =6095/12 -> 507.91667 | BT41: =6095/12 -> 507.91667 | ... BX41: =6095/12 -> 507.91667 | BY41: =SUM(BM41:BX41) -> 6095 | BZ41: =BM41*$I41 -> 2234.8333 | CA41: =BN41*$I41 -> 2234.8333 | CB41: =BO41*$I41 -> 2234.8333 | CC41: =BP41*$I41 -> 2234.8333 | CD41: =BQ41*$I41 -> 2234.8333 | CE41: =BR41*$I41 -> 2234.8333 | CF41: =BS41*$I41 -> 2234.8333 | CG41: =BT41*$I41 -> 2234.8333 | ... CK41: =BX41*$I41 -> 2234.8333 | CL41: =SUM(BZ41:CK41) -> 26818 | CM41: =30000/12 -> 2500 | CN41: =30000/12 -> 2500 | CO41: =30000/12 -> 2500 | CP41: =30000/12 -> 2500 | CQ41: =30000/12 -> 2500 | CR41: =30000/12 -> 2500 | CS41: =30000/12 -> 2500 | CT41: =30000/12 -> 2500 | ... CX41: =30000/12 -> 2500 | CY41: =SUM(CM41:CX41) -> 30000 | CZ41: =CM41*$J41 -> 11000 | DA41: =CN41*$J41 -> 11000 | DB41: =CO41*$J41 -> 11000 | DC41: =CP41*$J41 -> 11000 | DD41: =CQ41*$J41 -> 11000 | DE41: =CR41*$J41 -> 11000 | DF41: =CS41*$J41 -> 11000 | DG41: =CT41*$J41 -> 11000 | ... DK41: =CX41*$J41 -> 11000 | DL41: =SUM(CZ41:DK41) -> 132000 | DM41: =30000/12 -> 2500 | DN41: =30000/12 -> 2500 | DO41: =30000/12 -> 2500 | DP41: =30000/12 -> 2500 | DQ41: =30000/12 -> 2500 | DR41: =30000/12 -> 2500 | DS41: =30000/12 -> 2500 | DT41: =30000/12 -> 2500 | ... DX41: =30000/12 -> 2500 | DY41: =SUM(DM41:DX41) -> 30000 | DZ41: =DM41*$K41 -> 11000 | EA41: =DN41*$K41 -> 11000 | EB41: =DO41*$K41 -> 11000 | EC41: =DP41*$K41 -> 11000 | ED41: =DQ41*$K41 -> 11000 | EE41: =DR41*$K41 -> 11000 | EF41: =DS41*$K41 -> 11000 | EG41: =DT41*$K41 -> 11000 | ... EK41: =DX41*$K41 -> 11000 | EL41: =SUM(DZ41:EK41) -> 132000
A42: LG Innotek | B42: T6 Bearing Plate | C42: 3CVC00004A | D42: 1.22 | E42: 1.2246865 | F42: 1.2255111 | G42: 1.27 | H42: =G42 -> 1.27 | I42: =H42 -> 1.27 | J42: =I42 -> 1.27 | K42: =J42 -> 1.27 | M42: 42900 | N42: 33550 | O42: 23100 | P42: =26400+6600 -> 33000 | Q42: 19800 | R42: 49800 | S42: 29400 | T42: 30000 | U42: 30000 | V42: 30000 | W42: 30000 | X42: 30000 | Y42: =SUM(M42:X42) -> 381550 | Z42: 53064 | AA42: 40260 | AB42: 28182 | AC42: 40260 | AD42: =24156 -> 24156 | AE42: 60756 | AF42: =S42*$F42 -> 36030.025 | AG42: =T42*$F42 -> 36765.332 | AH42: =U42*$F42 -> 36765.332 | AI42: =V42*$G42 -> 38100 | AJ42: =W42*$G42 -> 38100 | AK42: =X42*$G42 -> 38100 | AL42: =SUM(Z42:AK42) -> 470538.69 | AM42: =262556/12 -> 21879.667 | AN42: =262556/12 -> 21879.667 | AO42: =262556/12 -> 21879.667 | AP42: =262556/12 -> 21879.667 | AQ42: =262556/12 -> 21879.667 | AR42: =262556/12 -> 21879.667 | AS42: =262556/12 -> 21879.667 | AT42: =262556/12 -> 21879.667 | ... AX42: =262556/12 -> 21879.667 | AY42: =SUM(AM42:AX42) -> 262556 | AZ42: =AM42*$H42 -> 27787.177 | BA42: =AN42*$H42 -> 27787.177 | BB42: =AO42*$H42 -> 27787.177 | BC42: =AP42*$H42 -> 27787.177 | BD42: =AQ42*$H42 -> 27787.177 | BE42: =AR42*$H42 -> 27787.177 | BF42: =AS42*$H42 -> 27787.177 | BG42: =AT42*$H42 -> 27787.177 | ... BK42: =AX42*$H42 -> 27787.177 | BL42: =SUM(AZ42:BK42) -> 333446.12 | BM42: =262556/12 -> 21879.667 | BN42: =262556/12 -> 21879.667 | BO42: =262556/12 -> 21879.667 | BP42: =262556/12 -> 21879.667 | BQ42: =262556/12 -> 21879.667 | BR42: =262556/12 -> 21879.667 | BS42: =262556/12 -> 21879.667 | BT42: =262556/12 -> 21879.667 | ... BX42: =262556/12 -> 21879.667 | BY42: =SUM(BM42:BX42) -> 262556 | BZ42: =BM42*$I42 -> 27787.177 | CA42: =BN42*$I42 -> 27787.177 | CB42: =BO42*$I42 -> 27787.177 | CC42: =BP42*$I42 -> 27787.177 | CD42: =BQ42*$I42 -> 27787.177 | CE42: =BR42*$I42 -> 27787.177 | CF42: =BS42*$I42 -> 27787.177 | CG42: =BT42*$I42 -> 27787.177 | ... CK42: =BX42*$I42 -> 27787.177 | CL42: =SUM(BZ42:CK42) -> 333446.12 | CM42: =260000/12 -> 21666.667 | CN42: =260000/12 -> 21666.667 | CO42: =260000/12 -> 21666.667 | CP42: =260000/12 -> 21666.667 | CQ42: =260000/12 -> 21666.667 | CR42: =260000/12 -> 21666.667 | CS42: =260000/12 -> 21666.667 | CT42: =260000/12 -> 21666.667 | ... CX42: =260000/12 -> 21666.667 | CY42: =SUM(CM42:CX42) -> 260000 | CZ42: =CM42*$J42 -> 27516.667 | DA42: =CN42*$J42 -> 27516.667 | DB42: =CO42*$J42 -> 27516.667 | DC42: =CP42*$J42 -> 27516.667 | DD42: =CQ42*$J42 -> 27516.667 | DE42: =CR42*$J42 -> 27516.667 | DF42: =CS42*$J42 -> 27516.667 | DG42: =CT42*$J42 -> 27516.667 | ... DK42: =CX42*$J42 -> 27516.667 | DL42: =SUM(CZ42:DK42) -> 330200 | DM42: =260000/12 -> 21666.667 | DN42: =260000/12 -> 21666.667 | DO42: =260000/12 -> 21666.667 | DP42: =260000/12 -> 21666.667 | DQ42: =260000/12 -> 21666.667 | DR42: =260000/12 -> 21666.667 | DS42: =260000/12 -> 21666.667 | DT42: =260000/12 -> 21666.667 | ... DX42: =260000/12 -> 21666.667 | DY42: =SUM(DM42:DX42) -> 260000 | DZ42: =DM42*$K42 -> 27516.667 | EA42: =DN42*$K42 -> 27516.667 | EB42: =DO42*$K42 -> 27516.667 | EC42: =DP42*$K42 -> 27516.667 | ED42: =DQ42*$K42 -> 27516.667 | EE42: =DR42*$K42 -> 27516.667 | EF42: =DS42*$K42 -> 27516.667 | EG42: =DT42*$K42 -> 27516.667 | ... EK42: =DX42*$K42 -> 27516.667 | EL42: =SUM(DZ42:EK42) -> 330200
A43: LG Innotek | B43: T6 Housing M6 - Mexico | G43: 4.774 | H43: 4.46 | I43: 4.46 | J43: 4.46 | K43: 4.46 | Y43: =SUM(M43:X43) -> 0 | AD43: 0 | AI43: =V43*$G43 -> 0 | AJ43: =W43*$G43 -> 0 | AK43: =X43*$G43 -> 0 | AL43: =SUM(Z43:AK43) -> 0 | AS43: =317888/12 -> 26490.667 | AT43: =317888/12 -> 26490.667 | AU43: =317888/12 -> 26490.667 | AV43: =317888/12 -> 26490.667 | AW43: =317888/12 -> 26490.667 | AX43: =317888/12 -> 26490.667 | AY43: =SUM(AM43:AX43) -> 158944 | AZ43: =AM43*$H43 -> 0 | BA43: =AN43*$H43 -> 0 | BB43: =AO43*$H43 -> 0 | BC43: =AP43*$H43 -> 0 | BD43: =AQ43*$H43 -> 0 | BE43: =AR43*$H43 -> 0 | BF43: =AS43*$H43 -> 118148.37 | BG43: =AT43*$H43 -> 118148.37 | ... BK43: =AX43*$H43 -> 118148.37 | BL43: =SUM(AZ43:BK43) -> 708890.24 | BM43: =317888/12 -> 26490.667 | BN43: =317888/12 -> 26490.667 | BO43: =317888/12 -> 26490.667 | BP43: =317888/12 -> 26490.667 | BQ43: =317888/12 -> 26490.667 | BR43: =317888/12 -> 26490.667 | BS43: =317888/12 -> 26490.667 | BT43: =317888/12 -> 26490.667 | ... BX43: =317888/12 -> 26490.667 | BY43: =SUM(BM43:BX43) -> 317888 | BZ43: =BM43*$I43 -> 118148.37 | CA43: =BN43*$I43 -> 118148.37 | CB43: =BO43*$I43 -> 118148.37 | CC43: =BP43*$I43 -> 118148.37 | CD43: =BQ43*$I43 -> 118148.37 | CE43: =BR43*$I43 -> 118148.37 | CF43: =BS43*$I43 -> 118148.37 | CG43: =BT43*$I43 -> 118148.37 | ... CK43: =BX43*$I43 -> 118148.37 | CL43: =SUM(BZ43:CK43) -> 1417780.5 | CM43: =317888/12 -> 26490.667 | CN43: =317888/12 -> 26490.667 | CO43: =317888/12 -> 26490.667 | CP43: =317888/12 -> 26490.667 | CQ43: =317888/12 -> 26490.667 | CR43: =317888/12 -> 26490.667 | CS43: =317888/12 -> 26490.667 | CT43: =317888/12 -> 26490.667 | ... CX43: =317888/12 -> 26490.667 | CY43: =SUM(CM43:CX43) -> 317888 | CZ43: =CM43*$J43 -> 118148.37 | DA43: =CN43*$J43 -> 118148.37 | DB43: =CO43*$J43 -> 118148.37 | DC43: =CP43*$J43 -> 118148.37 | DD43: =CQ43*$J43 -> 118148.37 | DE43: =CR43*$J43 -> 118148.37 | DF43: =CS43*$J43 -> 118148.37 | DG43: =CT43*$J43 -> 118148.37 | ... DK43: =CX43*$J43 -> 118148.37 | DL43: =SUM(CZ43:DK43) -> 1417780.5 | DM43: =317888/12 -> 26490.667 | DN43: =317888/12 -> 26490.667 | DO43: =317888/12 -> 26490.667 | DP43: =317888/12 -> 26490.667 | DQ43: =317888/12 -> 26490.667 | DR43: =317888/12 -> 26490.667 | DS43: =317888/12 -> 26490.667 | DT43: =317888/12 -> 26490.667 | ... DX43: =317888/12 -> 26490.667 | DY43: =SUM(DM43:DX43) -> 317888 | DZ43: =DM43*$K43 -> 118148.37 | EA43: =DN43*$K43 -> 118148.37 | EB43: =DO43*$K43 -> 118148.37 | EC43: =DP43*$K43 -> 118148.37 | ED43: =DQ43*$K43 -> 118148.37 | EE43: =DR43*$K43 -> 118148.37 | EF43: =DS43*$K43 -> 118148.37 | EG43: =DT43*$K43 -> 118148.37 | ... EK43: =DX43*$K43 -> 118148.37 | EL43: =SUM(DZ43:EK43) -> 1417780.5
A44: LG Innotek | B44: T6 Housing M8 - Mexico | H44: 4.55 | I44: 4.55 | J44: 4.55 | K44: 4.55 | Y44: =SUM(M44:X44) -> 0 | AD44: 0 | AI44: =V44*$G44 -> 0 | AJ44: =W44*$G44 -> 0 | AK44: =X44*$G44 -> 0 | AL44: =SUM(Z44:AK44) -> 0 | AS44: =78975/12 -> 6581.25 | AT44: =78975/12 -> 6581.25 | AU44: =78975/12 -> 6581.25 | AV44: =78975/12 -> 6581.25 | AW44: =78975/12 -> 6581.25 | AX44: =78975/12 -> 6581.25 | AY44: =SUM(AM44:AX44) -> 39487.5 | AZ44: =AM44*$H44 -> 0 | BA44: =AN44*$H44 -> 0 | BB44: =AO44*$H44 -> 0 | BC44: =AP44*$H44 -> 0 | BD44: =AQ44*$H44 -> 0 | BE44: =AR44*$H44 -> 0 | BF44: =AS44*$H44 -> 29944.688 | BG44: =AT44*$H44 -> 29944.688 | ... BK44: =AX44*$H44 -> 29944.688 | BL44: =SUM(AZ44:BK44) -> 179668.12 | BM44: =78975/12 -> 6581.25 | BN44: =78975/12 -> 6581.25 | BO44: =78975/12 -> 6581.25 | BP44: =78975/12 -> 6581.25 | BQ44: =78975/12 -> 6581.25 | BR44: =78975/12 -> 6581.25 | BS44: =78975/12 -> 6581.25 | BT44: =78975/12 -> 6581.25 | ... BX44: =78975/12 -> 6581.25 | BY44: =SUM(BM44:BX44) -> 78975 | BZ44: =BM44*$I44 -> 29944.688 | CA44: =BN44*$I44 -> 29944.688 | CB44: =BO44*$I44 -> 29944.688 | CC44: =BP44*$I44 -> 29944.688 | CD44: =BQ44*$I44 -> 29944.688 | CE44: =BR44*$I44 -> 29944.688 | CF44: =BS44*$I44 -> 29944.688 | CG44: =BT44*$I44 -> 29944.688 | ... CK44: =BX44*$I44 -> 29944.688 | CL44: =SUM(BZ44:CK44) -> 359336.25 | CM44: =78975/12 -> 6581.25 | CN44: =78975/12 -> 6581.25 | CO44: =78975/12 -> 6581.25 | CP44: =78975/12 -> 6581.25 | CQ44: =78975/12 -> 6581.25 | CR44: =78975/12 -> 6581.25 | CS44: =78975/12 -> 6581.25 | CT44: =78975/12 -> 6581.25 | ... CX44: =78975/12 -> 6581.25 | CY44: =SUM(CM44:CX44) -> 78975 | CZ44: =CM44*$J44 -> 29944.688 | DA44: =CN44*$J44 -> 29944.688 | DB44: =CO44*$J44 -> 29944.688 | DC44: =CP44*$J44 -> 29944.688 | DD44: =CQ44*$J44 -> 29944.688 | DE44: =CR44*$J44 -> 29944.688 | DF44: =CS44*$J44 -> 29944.688 | DG44: =CT44*$J44 -> 29944.688 | ... DK44: =CX44*$J44 -> 29944.688 | DL44: =SUM(CZ44:DK44) -> 359336.25 | DM44: =78975/12 -> 6581.25 | DN44: =78975/12 -> 6581.25 | DO44: =78975/12 -> 6581.25 | DP44: =78975/12 -> 6581.25 | DQ44: =78975/12 -> 6581.25 | DR44: =78975/12 -> 6581.25 | DS44: =78975/12 -> 6581.25 | DT44: =78975/12 -> 6581.25 | ... DX44: =78975/12 -> 6581.25 | DY44: =SUM(DM44:DX44) -> 78975 | DZ44: =DM44*$K44 -> 29944.688 | EA44: =DN44*$K44 -> 29944.688 | EB44: =DO44*$K44 -> 29944.688 | EC44: =DP44*$K44 -> 29944.688 | ED44: =DQ44*$K44 -> 29944.688 | EE44: =DR44*$K44 -> 29944.688 | EF44: =DS44*$K44 -> 29944.688 | EG44: =DT44*$K44 -> 29944.688 | ... EK44: =DX44*$K44 -> 29944.688 | EL44: =SUM(DZ44:EK44) -> 359336.25
A45: LG Innotek | B45: BEV Housing | G45: 4.774 | H45: 5.4 | I45: 5.4 | J45: 5.4 | K45: 5.4 | Y45: =SUM(M45:X45) -> 0 | AD45: 0 | AI45: =V45*$G45 -> 0 | AJ45: =W45*$G45 -> 0 | AK45: =X45*$G45 -> 0 | AL45: =SUM(Z45:AK45) -> 0 | AS45: =272340/12 -> 22695 | AT45: =272340/12 -> 22695 | AU45: =272340/12 -> 22695 | AV45: =272340/12 -> 22695 | AW45: =272340/12 -> 22695 | AX45: =272340/12 -> 22695 | AY45: =SUM(AM45:AX45) -> 136170 | AZ45: =AM45*$H45 -> 0 | BA45: =AN45*$H45 -> 0 | BB45: =AO45*$H45 -> 0 | BC45: =AP45*$H45 -> 0 | BD45: =AQ45*$H45 -> 0 | BE45: =AR45*$H45 -> 0 | BF45: =AS45*$H45 -> 122553 | BG45: =AT45*$H45 -> 122553 | ... BK45: =AX45*$H45 -> 122553 | BL45: =SUM(AZ45:BK45) -> 735318 | BM45: =146985/12 -> 12248.75 | BN45: =146985/12 -> 12248.75 | BO45: =146985/12 -> 12248.75 | BP45: =146985/12 -> 12248.75 | BQ45: =146985/12 -> 12248.75 | BR45: =146985/12 -> 12248.75 | BS45: =146985/12 -> 12248.75 | BT45: =146985/12 -> 12248.75 | ... BX45: =146985/12 -> 12248.75 | BY45: =SUM(BM45:BX45) -> 146985 | BZ45: =BM45*$I45 -> 66143.25 | CA45: =BN45*$I45 -> 66143.25 | CB45: =BO45*$I45 -> 66143.25 | CC45: =BP45*$I45 -> 66143.25 | CD45: =BQ45*$I45 -> 66143.25 | CE45: =BR45*$I45 -> 66143.25 | CF45: =BS45*$I45 -> 66143.25 | CG45: =BT45*$I45 -> 66143.25 | ... CK45: =BX45*$I45 -> 66143.25 | CL45: =SUM(BZ45:CK45) -> 793719 | CM45: =121914/12 -> 10159.5 | CN45: =121914/12 -> 10159.5 | CO45: =121914/12 -> 10159.5 | CP45: =121914/12 -> 10159.5 | CQ45: =121914/12 -> 10159.5 | CR45: =121914/12 -> 10159.5 | CS45: =121914/12 -> 10159.5 | CT45: =121914/12 -> 10159.5 | ... CX45: =121914/12 -> 10159.5 | CY45: =SUM(CM45:CX45) -> 121914 | CZ45: =CM45*$J45 -> 54861.3 | DA45: =CN45*$J45 -> 54861.3 | DB45: =CO45*$J45 -> 54861.3 | DC45: =CP45*$J45 -> 54861.3 | DD45: =CQ45*$J45 -> 54861.3 | DE45: =CR45*$J45 -> 54861.3 | DF45: =CS45*$J45 -> 54861.3 | DG45: =CT45*$J45 -> 54861.3 | ... DK45: =CX45*$J45 -> 54861.3 | DL45: =SUM(CZ45:DK45) -> 658335.6 | DM45: =113299/12 -> 9441.5833 | DN45: =113299/12 -> 9441.5833 | DO45: =113299/12 -> 9441.5833 | DP45: =113299/12 -> 9441.5833 | DQ45: =113299/12 -> 9441.5833 | DR45: =113299/12 -> 9441.5833 | DS45: =113299/12 -> 9441.5833 | DT45: =113299/12 -> 9441.5833 | ... DX45: =113299/12 -> 9441.5833 | DY45: =SUM(DM45:DX45) -> 113299 | DZ45: =DM45*$K45 -> 50984.55 | EA45: =DN45*$K45 -> 50984.55 | EB45: =DO45*$K45 -> 50984.55 | EC45: =DP45*$K45 -> 50984.55 | ED45: =DQ45*$K45 -> 50984.55 | EE45: =DR45*$K45 -> 50984.55 | EF45: =DS45*$K45 -> 50984.55 | EG45: =DT45*$K45 -> 50984.55 | ... EK45: =DX45*$K45 -> 50984.55 | EL45: =SUM(DZ45:EK45) -> 611814.6
A46: LG Innotek | B46: T6 BP - Mexico | G46: 1.38325 | H46: 1.29 | I46: 1.38325 | J46: 1.38325 | K46: 1.38325 | Y46: =SUM(M46:X46) -> 0 | AD46: 0 | AI46: =V46*$G46 -> 0 | AJ46: =W46*$G46 -> 0 | AK46: =X46*$G46 -> 0 | AL46: =SUM(Z46:AK46) -> 0 | AS46: =669203/12 -> 55766.917 | AT46: =669203/12 -> 55766.917 | AU46: =669203/12 -> 55766.917 | AV46: =669203/12 -> 55766.917 | AW46: =669203/12 -> 55766.917 | AX46: =669203/12 -> 55766.917 | AY46: =SUM(AM46:AX46) -> 334601.5 | AZ46: =AM46*$H46 -> 0 | BA46: =AN46*$H46 -> 0 | BB46: =AO46*$H46 -> 0 | BC46: =AP46*$H46 -> 0 | BD46: =AQ46*$H46 -> 0 | BE46: =AR46*$H46 -> 0 | BF46: =AS46*$H46 -> 71939.322 | BG46: =AT46*$H46 -> 71939.322 | ... BK46: =AX46*$H46 -> 71939.322 | BL46: =SUM(AZ46:BK46) -> 431635.93 | BM46: =543848/12 -> 45320.667 | BN46: =543848/12 -> 45320.667 | BO46: =543848/12 -> 45320.667 | BP46: =543848/12 -> 45320.667 | BQ46: =543848/12 -> 45320.667 | BR46: =543848/12 -> 45320.667 | BS46: =543848/12 -> 45320.667 | BT46: =543848/12 -> 45320.667 | ... BX46: =543848/12 -> 45320.667 | BY46: =SUM(BM46:BX46) -> 543848 | BZ46: =BM46*$I46 -> 62689.812 | CA46: =BN46*$I46 -> 62689.812 | CB46: =BO46*$I46 -> 62689.812 | CC46: =BP46*$I46 -> 62689.812 | CD46: =BQ46*$I46 -> 62689.812 | CE46: =BR46*$I46 -> 62689.812 | CF46: =BS46*$I46 -> 62689.812 | CG46: =BT46*$I46 -> 62689.812 | ... CK46: =BX46*$I46 -> 62689.812 | CL46: =SUM(BZ46:CK46) -> 752277.75 | CM46: =518777/12 -> 43231.417 | CN46: =518777/12 -> 43231.417 | CO46: =518777/12 -> 43231.417 | CP46: =518777/12 -> 43231.417 | CQ46: =518777/12 -> 43231.417 | CR46: =518777/12 -> 43231.417 | CS46: =518777/12 -> 43231.417 | CT46: =518777/12 -> 43231.417 | ... CX46: =518777/12 -> 43231.417 | CY46: =SUM(CM46:CX46) -> 518777 | CZ46: =CM46*$J46 -> 59799.857 | DA46: =CN46*$J46 -> 59799.857 | DB46: =CO46*$J46 -> 59799.857 | DC46: =CP46*$J46 -> 59799.857 | DD46: =CQ46*$J46 -> 59799.857 | DE46: =CR46*$J46 -> 59799.857 | DF46: =CS46*$J46 -> 59799.857 | DG46: =CT46*$J46 -> 59799.857 | ... DK46: =CX46*$J46 -> 59799.857 | DL46: =SUM(CZ46:DK46) -> 717598.29 | DM46: =510162/12 -> 42513.5 | DN46: =510162/12 -> 42513.5 | DO46: =510162/12 -> 42513.5 | DP46: =510162/12 -> 42513.5 | DQ46: =510162/12 -> 42513.5 | DR46: =510162/12 -> 42513.5 | DS46: =510162/12 -> 42513.5 | DT46: =510162/12 -> 42513.5 | ... DX46: =510162/12 -> 42513.5 | DY46: =SUM(DM46:DX46) -> 510162 | DZ46: =DM46*$K46 -> 58806.799 | EA46: =DN46*$K46 -> 58806.799 | EB46: =DO46*$K46 -> 58806.799 | EC46: =DP46*$K46 -> 58806.799 | ED46: =DQ46*$K46 -> 58806.799 | EE46: =DR46*$K46 -> 58806.799 | EF46: =DS46*$K46 -> 58806.799 | EG46: =DT46*$K46 -> 58806.799 | ... EK46: =DX46*$K46 -> 58806.799 | EL46: =SUM(DZ46:EK46) -> 705681.59
A47: LG Innotek | B47: T3 BP | G47: 1.38325 | H47: 1.68 | I47: 1.38325 | J47: 1.38325 | K47: 1.38325 | Y47: =SUM(M47:X47) -> 0 | AD47: 0 | AI47: =V47*$G47 -> 0 | AJ47: =W47*$G47 -> 0 | AK47: =X47*$G47 -> 0 | AL47: =SUM(Z47:AK47) -> 0 | AS47: =755105/12 -> 62925.417 | AT47: =755105/12 -> 62925.417 | AU47: =755105/12 -> 62925.417 | AV47: =755105/12 -> 62925.417 | AW47: =755105/12 -> 62925.417 | AX47: =755105/12 -> 62925.417 | AY47: =SUM(AM47:AX47) -> 377552.5 | AZ47: =AM47*$H47 -> 0 | BA47: =AN47*$H47 -> 0 | BB47: =AO47*$H47 -> 0 | BC47: =AP47*$H47 -> 0 | BD47: =AQ47*$H47 -> 0 | BE47: =AR47*$H47 -> 0 | BF47: =AS47*$H47 -> 105714.7 | BG47: =AT47*$H47 -> 105714.7 | ... BK47: =AX47*$H47 -> 105714.7 | BL47: =SUM(AZ47:BK47) -> 634288.2 | BM47: =418486/12 -> 34873.833 | BN47: =418486/12 -> 34873.833 | BO47: =418486/12 -> 34873.833 | BP47: =418486/12 -> 34873.833 | BQ47: =418486/12 -> 34873.833 | BR47: =418486/12 -> 34873.833 | BS47: =418486/12 -> 34873.833 | BT47: =418486/12 -> 34873.833 | ... BX47: =418486/12 -> 34873.833 | BY47: =SUM(BM47:BX47) -> 418486 | BZ47: =BM47*$I47 -> 48239.23 | CA47: =BN47*$I47 -> 48239.23 | CB47: =BO47*$I47 -> 48239.23 | CC47: =BP47*$I47 -> 48239.23 | CD47: =BQ47*$I47 -> 48239.23 | CE47: =BR47*$I47 -> 48239.23 | CF47: =BS47*$I47 -> 48239.23 | CG47: =BT47*$I47 -> 48239.23 | ... CK47: =BX47*$I47 -> 48239.23 | CL47: =SUM(BZ47:CK47) -> 578870.76 | CM47: =136314/12 -> 11359.5 | CN47: =136314/12 -> 11359.5 | CO47: =136314/12 -> 11359.5 | CP47: =136314/12 -> 11359.5 | CQ47: =136314/12 -> 11359.5 | CR47: =136314/12 -> 11359.5 | CS47: =136314/12 -> 11359.5 | CT47: =136314/12 -> 11359.5 | ... CX47: =136314/12 -> 11359.5 | CY47: =SUM(CM47:CX47) -> 136314 | CZ47: =CM47*$J47 -> 15713.028 | DA47: =CN47*$J47 -> 15713.028 | DB47: =CO47*$J47 -> 15713.028 | DC47: =CP47*$J47 -> 15713.028 | DD47: =CQ47*$J47 -> 15713.028 | DE47: =CR47*$J47 -> 15713.028 | DF47: =CS47*$J47 -> 15713.028 | DG47: =CT47*$J47 -> 15713.028 | ... DK47: =CX47*$J47 -> 15713.028 | DL47: =SUM(CZ47:DK47) -> 188556.34 | DM47: =136314/12 -> 11359.5 | DN47: =136314/12 -> 11359.5 | DO47: =136314/12 -> 11359.5 | DP47: =136314/12 -> 11359.5 | DQ47: =136314/12 -> 11359.5 | DR47: =136314/12 -> 11359.5 | DS47: =136314/12 -> 11359.5 | DT47: =136314/12 -> 11359.5 | ... DX47: =136314/12 -> 11359.5 | DY47: =SUM(DM47:DX47) -> 136314 | DZ47: =DM47*$K47 -> 15713.028 | EA47: =DN47*$K47 -> 15713.028 | EB47: =DO47*$K47 -> 15713.028 | EC47: =DP47*$K47 -> 15713.028 | ED47: =DQ47*$K47 -> 15713.028 | EE47: =DR47*$K47 -> 15713.028 | EF47: =DS47*$K47 -> 15713.028 | EG47: =DT47*$K47 -> 15713.028 | ... EK47: =DX47*$K47 -> 15713.028 | EL47: =SUM(DZ47:EK47) -> 188556.34
A48: LG Innotek | B48: CL4 Housing | C48: 3CAZ00041A | D48: 3.44 | E48: 3.428969 | F48: 3.4500748 | G48: 3.45 | H48: =G48 -> 3.45 | I48: =H48 -> 3.45 | J48: =I48 -> 3.45 | K48: =J48 -> 3.45 | M48: 14947 | N48: 28890 | O48: 56160 | P48: 52596 | Q48: 80652 | R48: 68340 | S48: =67229-2000 -> 65229 | T48: 79000 | U48: 79000 | V48: 79000 | W48: 79000 | X48: 79000 | Y48: =SUM(M48:X48) -> 761814 | Z48: 51417.68 | AA48: 99381.6 | AB48: 193190.4 | AC48: 180930.24 | AD48: =275868.66+1025 -> 276893.66 | AE48: 234406.2 | AF48: =S48*$F48 -> 225044.93 | AG48: =T48*$F48 -> 272555.91 | AH48: =U48*$F48 -> 272555.91 | AI48: =V48*$G48 -> 272550 | AJ48: =W48*$G48 -> 272550 | AK48: =X48*$G48 -> 272550 | AL48: =SUM(Z48:AK48) -> 2624026.5 | AM48: =579320/12 -> 48276.667 | AN48: =579320/12 -> 48276.667 | AO48: =579320/12 -> 48276.667 | AP48: =579320/12 -> 48276.667 | AQ48: =579320/12 -> 48276.667 | AR48: =579320/12 -> 48276.667 | AS48: =579320/12 -> 48276.667 | AT48: =579320/12 -> 48276.667 | ... AX48: =579320/12 -> 48276.667 | AY48: =SUM(AM48:AX48) -> 579320 | AZ48: =AM48*$H48 -> 166554.5 | BA48: =AN48*$H48 -> 166554.5 | BB48: =AO48*$H48 -> 166554.5 | BC48: =AP48*$H48 -> 166554.5 | BD48: =AQ48*$H48 -> 166554.5 | BE48: =AR48*$H48 -> 166554.5 | BF48: =AS48*$H48 -> 166554.5 | BG48: =AT48*$H48 -> 166554.5 | ... BK48: =AX48*$H48 -> 166554.5 | BL48: =SUM(AZ48:BK48) -> 1998654 | BM48: =424400/12 -> 35366.667 | BN48: =424400/12 -> 35366.667 | BO48: =424400/12 -> 35366.667 | BP48: =424400/12 -> 35366.667 | BQ48: =424400/12 -> 35366.667 | BR48: =424400/12 -> 35366.667 | BS48: =424400/12 -> 35366.667 | BT48: =424400/12 -> 35366.667 | ... BX48: =424400/12 -> 35366.667 | BY48: =SUM(BM48:BX48) -> 424400 | BZ48: =BM48*$I48 -> 122015 | CA48: =BN48*$I48 -> 122015 | CB48: =BO48*$I48 -> 122015 | CC48: =BP48*$I48 -> 122015 | CD48: =BQ48*$I48 -> 122015 | CE48: =BR48*$I48 -> 122015 | CF48: =BS48*$I48 -> 122015 | CG48: =BT48*$I48 -> 122015 | ... CK48: =BX48*$I48 -> 122015 | CL48: =SUM(BZ48:CK48) -> 1464180 | CM48: =271610/12 -> 22634.167 | CN48: =271610/12 -> 22634.167 | CO48: =271610/12 -> 22634.167 | CP48: =271610/12 -> 22634.167 | CQ48: =271610/12 -> 22634.167 | CR48: =271610/12 -> 22634.167 | CS48: =271610/12 -> 22634.167 | CT48: =271610/12 -> 22634.167 | ... CX48: =271610/12 -> 22634.167 | CY48: =SUM(CM48:CX48) -> 271610 | CZ48: =CM48*$J48 -> 78087.875 | DA48: =CN48*$J48 -> 78087.875 | DB48: =CO48*$J48 -> 78087.875 | DC48: =CP48*$J48 -> 78087.875 | DD48: =CQ48*$J48 -> 78087.875 | DE48: =CR48*$J48 -> 78087.875 | DF48: =CS48*$J48 -> 78087.875 | DG48: =CT48*$J48 -> 78087.875 | ... DK48: =CX48*$J48 -> 78087.875 | DL48: =SUM(CZ48:DK48) -> 937054.5 | DM48: =215320/12 -> 17943.333 | DN48: =215320/12 -> 17943.333 | DO48: =215320/12 -> 17943.333 | DP48: =215320/12 -> 17943.333 | DQ48: =215320/12 -> 17943.333 | DR48: =215320/12 -> 17943.333 | DS48: =215320/12 -> 17943.333 | DT48: =215320/12 -> 17943.333 | ... DX48: =215320/12 -> 17943.333 | DY48: =SUM(DM48:DX48) -> 215320 | DZ48: =DM48*$K48 -> 61904.5 | EA48: =DN48*$K48 -> 61904.5 | EB48: =DO48*$K48 -> 61904.5 | EC48: =DP48*$K48 -> 61904.5 | ED48: =DQ48*$K48 -> 61904.5 | EE48: =DR48*$K48 -> 61904.5 | EF48: =DS48*$K48 -> 61904.5 | EG48: =DT48*$K48 -> 61904.5 | ... EK48: =DX48*$K48 -> 61904.5 | EL48: =SUM(DZ48:EK48) -> 742854
A49: LG Innotek | B49: CL4 Cover | C49: 3CAZ00042A | D49: 1.35 | E49: 1.3760478 | F49: 1.3763462 | G49: 1.35 | H49: =G49 -> 1.35 | I49: =H49 -> 1.35 | J49: =I49 -> 1.35 | K49: =J49 -> 1.35 | M49: 12626 | N49: 300 | O49: 22920 | P49: 0 | Q49: 23520 | R49: 23520 | S49: 23520 | T49: 16000 | U49: 16000 | V49: 16000 | W49: 15000 | X49: 14000 | Y49: =SUM(M49:X49) -> 183406 | Z49: 17045.1 | AA49: 405 | AB49: =+O49*D49 -> 30942 | AC49: =P49*$E49 -> 0 | AD49: 31516.8 | AE49: 32213.4 | AF49: =S49*1.37 -> 32222.4 | AG49: =T49*$F49 -> 22021.539 | AH49: =U49*$F49 -> 22021.539 | AI49: =V49*$G49 -> 21600 | AJ49: =W49*$G49 -> 20250 | AK49: =X49*$G49 -> 18900 | AL49: =SUM(Z49:AK49) -> 249137.78 | AM49: =190000/12 -> 15833.333 | AN49: =190000/12 -> 15833.333 | AO49: =190000/12 -> 15833.333 | AP49: =190000/12 -> 15833.333 | AQ49: =190000/12 -> 15833.333 | AR49: =190000/12 -> 15833.333 | AS49: =190000/12 -> 15833.333 | AT49: =190000/12 -> 15833.333 | ... AX49: =190000/12 -> 15833.333 | AY49: =SUM(AM49:AX49) -> 190000 | AZ49: =AM49*$H49 -> 21375 | BA49: =AN49*$H49 -> 21375 | BB49: =AO49*$H49 -> 21375 | BC49: =AP49*$H49 -> 21375 | BD49: =AQ49*$H49 -> 21375 | BE49: =AR49*$H49 -> 21375 | BF49: =AS49*$H49 -> 21375 | BG49: =AT49*$H49 -> 21375 | ... BK49: =AX49*$H49 -> 21375 | BL49: =SUM(AZ49:BK49) -> 256500 | BM49: =190000/12 -> 15833.333 | BN49: =190000/12 -> 15833.333 | BO49: =190000/12 -> 15833.333 | BP49: =190000/12 -> 15833.333 | BQ49: =190000/12 -> 15833.333 | BR49: =190000/12 -> 15833.333 | BS49: =190000/12 -> 15833.333 | BT49: =190000/12 -> 15833.333 | ... BX49: =190000/12 -> 15833.333 | BY49: =SUM(BM49:BX49) -> 190000 | BZ49: =BM49*$I49 -> 21375 | CA49: =BN49*$I49 -> 21375 | CB49: =BO49*$I49 -> 21375 | CC49: =BP49*$I49 -> 21375 | CD49: =BQ49*$I49 -> 21375 | CE49: =BR49*$I49 -> 21375 | CF49: =BS49*$I49 -> 21375 | CG49: =BT49*$I49 -> 21375 | ... CK49: =BX49*$I49 -> 21375 | CL49: =SUM(BZ49:CK49) -> 256500 | CM49: =190000/12 -> 15833.333 | CN49: =190000/12 -> 15833.333 | CO49: =190000/12 -> 15833.333 | CP49: =190000/12 -> 15833.333 | CQ49: =190000/12 -> 15833.333 | CR49: =190000/12 -> 15833.333 | CS49: =190000/12 -> 15833.333 | CT49: =190000/12 -> 15833.333 | ... CX49: =190000/12 -> 15833.333 | CY49: =SUM(CM49:CX49) -> 190000 | CZ49: =CM49*$J49 -> 21375 | DA49: =CN49*$J49 -> 21375 | DB49: =CO49*$J49 -> 21375 | DC49: =CP49*$J49 -> 21375 | DD49: =CQ49*$J49 -> 21375 | DE49: =CR49*$J49 -> 21375 | DF49: =CS49*$J49 -> 21375 | DG49: =CT49*$J49 -> 21375 | ... DK49: =CX49*$J49 -> 21375 | DL49: =SUM(CZ49:DK49) -> 256500 | DM49: =190000/12 -> 15833.333 | DN49: =190000/12 -> 15833.333 | DO49: =190000/12 -> 15833.333 | DP49: =190000/12 -> 15833.333 | DQ49: =190000/12 -> 15833.333 | DR49: =190000/12 -> 15833.333 | DS49: =190000/12 -> 15833.333 | DT49: =190000/12 -> 15833.333 | ... DX49: =190000/12 -> 15833.333 | DY49: =SUM(DM49:DX49) -> 190000 | DZ49: =DM49*$K49 -> 21375 | EA49: =DN49*$K49 -> 21375 | EB49: =DO49*$K49 -> 21375 | EC49: =DP49*$K49 -> 21375 | ED49: =DQ49*$K49 -> 21375 | EE49: =DR49*$K49 -> 21375 | EF49: =DS49*$K49 -> 21375 | EG49: =DT49*$K49 -> 21375 | ... EK49: =DX49*$K49 -> 21375 | EL49: =SUM(DZ49:EK49) -> 256500
A50: LG Innotek | B50: MQ4a PE Housing | C50: 3CAZ00039A | D50: 3.49 | E50: 3.378969 | F50: 3.4006831 | G50: 3.5 | H50: =G50 -> 3.5 | I50: =H50 -> 3.5 | J50: =I50 -> 3.5 | K50: =J50 -> 3.5 | M50: 24820 | N50: 23760 | O50: 23760 | P50: 30002 | Q50: 23556 | R50: 35213 | S50: =27634-1000 -> 26634 | T50: 40000 | U50: 40000 | V50: 40000 | W50: 40000 | X50: 40000 | Y50: =SUM(M50:X50) -> 387745 | Z50: 86621.8 | AA50: 82922.4 | AB50: 82922.4 | AC50: 104706.98 | AD50: 80578.18 | AE50: 120428.46 | AF50: =S50*$F50 -> 90573.793 | AG50: =T50*$F50 -> 136027.32 | AH50: =U50*$F50 -> 136027.32 | AI50: =V50*$G50 -> 140000 | AJ50: =W50*$G50 -> 140000 | AK50: =X50*$G50 -> 140000 | AL50: =SUM(Z50:AK50) -> 1340808.7 | AM50: =230000/12 -> 19166.667 | AN50: =230000/12 -> 19166.667 | AO50: =230000/12 -> 19166.667 | AP50: =230000/12 -> 19166.667 | AQ50: =230000/12 -> 19166.667 | AR50: =230000/12 -> 19166.667 | AS50: =230000/12 -> 19166.667 | AT50: =230000/12 -> 19166.667 | ... AX50: =230000/12 -> 19166.667 | AY50: =SUM(AM50:AX50) -> 230000 | AZ50: =AM50*$H50 -> 67083.333 | BA50: =AN50*$H50 -> 67083.333 | BB50: =AO50*$H50 -> 67083.333 | BC50: =AP50*$H50 -> 67083.333 | BD50: =AQ50*$H50 -> 67083.333 | BE50: =AR50*$H50 -> 67083.333 | BF50: =AS50*$H50 -> 67083.333 | BG50: =AT50*$H50 -> 67083.333 | ... BK50: =AX50*$H50 -> 67083.333 | BL50: =SUM(AZ50:BK50) -> 805000 | BM50: =330000/12 -> 27500 | BN50: =330000/12 -> 27500 | BO50: =330000/12 -> 27500 | BP50: =330000/12 -> 27500 | BQ50: =330000/12 -> 27500 | BR50: =330000/12 -> 27500 | BS50: =330000/12 -> 27500 | BT50: =330000/12 -> 27500 | ... BX50: =330000/12 -> 27500 | BY50: =SUM(BM50:BX50) -> 330000 | BZ50: =BM50*$I50 -> 96250 | CA50: =BN50*$I50 -> 96250 | CB50: =BO50*$I50 -> 96250 | CC50: =BP50*$I50 -> 96250 | CD50: =BQ50*$I50 -> 96250 | CE50: =BR50*$I50 -> 96250 | CF50: =BS50*$I50 -> 96250 | CG50: =BT50*$I50 -> 96250 | ... CK50: =BX50*$I50 -> 96250 | CL50: =SUM(BZ50:CK50) -> 1155000 | CM50: =330000/12 -> 27500 | CN50: =330000/12 -> 27500 | CO50: =330000/12 -> 27500 | CP50: =330000/12 -> 27500 | CQ50: =330000/12 -> 27500 | CR50: =330000/12 -> 27500 | CS50: =330000/12 -> 27500 | CT50: =330000/12 -> 27500 | ... CX50: =330000/12 -> 27500 | CY50: =SUM(CM50:CX50) -> 330000 | CZ50: =CM50*$J50 -> 96250 | DA50: =CN50*$J50 -> 96250 | DB50: =CO50*$J50 -> 96250 | DC50: =CP50*$J50 -> 96250 | DD50: =CQ50*$J50 -> 96250 | DE50: =CR50*$J50 -> 96250 | DF50: =CS50*$J50 -> 96250 | DG50: =CT50*$J50 -> 96250 | ... DK50: =CX50*$J50 -> 96250 | DL50: =SUM(CZ50:DK50) -> 1155000 | DM50: =330000/12 -> 27500 | DN50: =330000/12 -> 27500 | DO50: =330000/12 -> 27500 | DP50: =330000/12 -> 27500 | DQ50: =330000/12 -> 27500 | DR50: =330000/12 -> 27500 | DS50: =330000/12 -> 27500 | DT50: =330000/12 -> 27500 | ... DX50: =330000/12 -> 27500 | DY50: =SUM(DM50:DX50) -> 330000 | DZ50: =DM50*$K50 -> 96250 | EA50: =DN50*$K50 -> 96250 | EB50: =DO50*$K50 -> 96250 | EC50: =DP50*$K50 -> 96250 | ED50: =DQ50*$K50 -> 96250 | EE50: =DR50*$K50 -> 96250 | EF50: =DS50*$K50 -> 96250 | EG50: =DT50*$K50 -> 96250 | ... EK50: =DX50*$K50 -> 96250 | EL50: =SUM(DZ50:EK50) -> 1155000
A51: LG Innotek | B51: MQ4a PE Cover | C51: 3CAZ00038A | D51: 1.43 | E51: 1.4460478 | F51: 1.4468563 | G51: 1.43 | H51: =G51 -> 1.43 | I51: =H51 -> 1.43 | J51: =I51 -> 1.43 | K51: =J51 -> 1.43 | M51: 27300 | N51: 22800 | O51: 30240 | P51: 35000 | Q51: 34860 | R51: 40180 | S51: 35011 | T51: 40000 | U51: 40000 | V51: 40000 | W51: 40000 | X51: 40000 | Y51: =SUM(M51:X51) -> 425391 | Z51: 39039 | AA51: 32604 | AB51: 43243.2 | AC51: 50050 | AD51: 49753.8 | AE51: 57403.2 | AF51: =S51*$F51 -> 50655.887 | AG51: =T51*$F51 -> 57874.254 | AH51: =U51*$F51 -> 57874.254 | AI51: =V51*$G51 -> 57200 | AJ51: =W51*$G51 -> 57200 | AK51: =X51*$G51 -> 57200 | AL51: =SUM(Z51:AK51) -> 610097.59 | AM51: =230000/12 -> 19166.667 | AN51: =230000/12 -> 19166.667 | AO51: =230000/12 -> 19166.667 | AP51: =230000/12 -> 19166.667 | AQ51: =230000/12 -> 19166.667 | AR51: =230000/12 -> 19166.667 | AS51: =230000/12 -> 19166.667 | AT51: =230000/12 -> 19166.667 | ... AX51: =230000/12 -> 19166.667 | AY51: =SUM(AM51:AX51) -> 230000 | AZ51: =AM51*$H51 -> 27408.333 | BA51: =AN51*$H51 -> 27408.333 | BB51: =AO51*$H51 -> 27408.333 | BC51: =AP51*$H51 -> 27408.333 | BD51: =AQ51*$H51 -> 27408.333 | BE51: =AR51*$H51 -> 27408.333 | BF51: =AS51*$H51 -> 27408.333 | BG51: =AT51*$H51 -> 27408.333 | ... BK51: =AX51*$H51 -> 27408.333 | BL51: =SUM(AZ51:BK51) -> 328900 | BM51: =330000/12 -> 27500 | BN51: =330000/12 -> 27500 | BO51: =330000/12 -> 27500 | BP51: =330000/12 -> 27500 | BQ51: =330000/12 -> 27500 | BR51: =330000/12 -> 27500 | BS51: =330000/12 -> 27500 | BT51: =330000/12 -> 27500 | ... BX51: =330000/12 -> 27500 | BY51: =SUM(BM51:BX51) -> 330000 | BZ51: =BM51*$I51 -> 39325 | CA51: =BN51*$I51 -> 39325 | CB51: =BO51*$I51 -> 39325 | CC51: =BP51*$I51 -> 39325 | CD51: =BQ51*$I51 -> 39325 | CE51: =BR51*$I51 -> 39325 | CF51: =BS51*$I51 -> 39325 | CG51: =BT51*$I51 -> 39325 | ... CK51: =BX51*$I51 -> 39325 | CL51: =SUM(BZ51:CK51) -> 471900 | CM51: =330000/12 -> 27500 | CN51: =330000/12 -> 27500 | CO51: =330000/12 -> 27500 | CP51: =330000/12 -> 27500 | CQ51: =330000/12 -> 27500 | CR51: =330000/12 -> 27500 | CS51: =330000/12 -> 27500 | CT51: =330000/12 -> 27500 | ... CX51: =330000/12 -> 27500 | CY51: =SUM(CM51:CX51) -> 330000 | CZ51: =CM51*$J51 -> 39325 | DA51: =CN51*$J51 -> 39325 | DB51: =CO51*$J51 -> 39325 | DC51: =CP51*$J51 -> 39325 | DD51: =CQ51*$J51 -> 39325 | DE51: =CR51*$J51 -> 39325 | DF51: =CS51*$J51 -> 39325 | DG51: =CT51*$J51 -> 39325 | ... DK51: =CX51*$J51 -> 39325 | DL51: =SUM(CZ51:DK51) -> 471900 | DM51: =330000/12 -> 27500 | DN51: =330000/12 -> 27500 | DO51: =330000/12 -> 27500 | DP51: =330000/12 -> 27500 | DQ51: =330000/12 -> 27500 | DR51: =330000/12 -> 27500 | DS51: =330000/12 -> 27500 | DT51: =330000/12 -> 27500 | ... DX51: =330000/12 -> 27500 | DY51: =SUM(DM51:DX51) -> 330000 | DZ51: =DM51*$K51 -> 39325 | EA51: =DN51*$K51 -> 39325 | EB51: =DO51*$K51 -> 39325 | EC51: =DP51*$K51 -> 39325 | ED51: =DQ51*$K51 -> 39325 | EE51: =DR51*$K51 -> 39325 | EF51: =DS51*$K51 -> 39325 | EG51: =DT51*$K51 -> 39325 | ... EK51: =DX51*$K51 -> 39325 | EL51: =SUM(DZ51:EK51) -> 471900
A52: LG Innotek | B52: BYD Housing | C52: 3CAC00129A | E52: 2.2303236 | F52: 2.2421401 | G52: 2.22 | H52: 2.22 | I52: 2.22 | J52: 2.22 | K52: 2.22 | M52: 0 | N52: 0 | O52: 0 | P52: 6204 | Q52: 3456 | R52: 864 | S52: 4210 | Y52: =SUM(M52:X52) -> 14734 | Z52: 0 | AA52: 0 | AB52: 0 | AC52: 13772.88 | AD52: 7672.32 | AE52: 2020.03 | AF52: =S52*$F52 -> 9439.4098 | AG52: =T52*$F52 -> 0 | AH52: =U52*$F52 -> 0 | AI52: =V52*$G52 -> 0 | AJ52: =W52*$G52 -> 0 | AK52: =X52*$G52 -> 0 | AL52: =SUM(Z52:AK52) -> 32904.64 | AY52: =SUM(AM52:AX52) -> 0 | AZ52: =AM52*$H52 -> 0 | BA52: =AN52*$H52 -> 0 | BB52: =AO52*$H52 -> 0 | BC52: =AP52*$H52 -> 0 | BD52: =AQ52*$H52 -> 0 | BE52: =AR52*$H52 -> 0 | BF52: =AS52*$H52 -> 0 | BG52: =AT52*$H52 -> 0 | ... BK52: =AX52*$H52 -> 0 | BL52: =SUM(AZ52:BK52) -> 0 | BY52: =SUM(BM52:BX52) -> 0 | BZ52: =BM52*$I52 -> 0 | CA52: =BN52*$I52 -> 0 | CB52: =BO52*$I52 -> 0 | CC52: =BP52*$I52 -> 0 | CD52: =BQ52*$I52 -> 0 | CE52: =BR52*$I52 -> 0 | CF52: =BS52*$I52 -> 0 | CG52: =BT52*$I52 -> 0 | ... CK52: =BX52*$I52 -> 0 | CL52: =SUM(BZ52:CK52) -> 0 | CY52: =SUM(CM52:CX52) -> 0 | CZ52: =CM52*$J52 -> 0 | DA52: =CN52*$J52 -> 0 | DB52: =CO52*$J52 -> 0 | DC52: =CP52*$J52 -> 0 | DD52: =CQ52*$J52 -> 0 | DE52: =CR52*$J52 -> 0 | DF52: =CS52*$J52 -> 0 | DG52: =CT52*$J52 -> 0 | ... DK52: =CX52*$J52 -> 0 | DL52: =SUM(CZ52:DK52) -> 0 | DY52: =SUM(DM52:DX52) -> 0 | DZ52: =DM52*$K52 -> 0 | EA52: =DN52*$K52 -> 0 | EB52: =DO52*$K52 -> 0 | EC52: =DP52*$K52 -> 0 | ED52: =DQ52*$K52 -> 0 | EE52: =DR52*$K52 -> 0 | EF52: =DS52*$K52 -> 0 | EG52: =DT52*$K52 -> 0 | ... EK52: =DX52*$K52 -> 0 | EL52: =SUM(DZ52:EK52) -> 0
A53: LG Innotek | B53: BYD Bracket(cover) | C53: 3MAM00121A | E53: 2.409239 | F53: 2.4208647 | G53: 2.4 | H53: 2.4 | I53: 2.4 | J53: 2.4 | K53: 2.4 | M53: 0 | N53: 0 | O53: 0 | P53: 6680 | Q53: 3840 | R53: 3880 | S53: 1920 | Y53: =SUM(M53:X53) -> 16320 | Z53: 0 | AA53: 0 | AB53: 0 | AC53: =P53*2.4 -> 16032 | AD53: 9216 | AE53: 9350.5 | AF53: =S53*$F53 -> 4648.0602 | AG53: =T53*$F53 -> 0 | AH53: =U53*$F53 -> 0 | AI53: =V53*$G53 -> 0 | AJ53: =W53*$G53 -> 0 | AK53: =X53*$G53 -> 0 | AL53: =SUM(Z53:AK53) -> 39246.56 | AY53: =SUM(AM53:AX53) -> 0 | AZ53: =AM53*$H53 -> 0 | BA53: =AN53*$H53 -> 0 | BB53: =AO53*$H53 -> 0 | BC53: =AP53*$H53 -> 0 | BD53: =AQ53*$H53 -> 0 | BE53: =AR53*$H53 -> 0 | BF53: =AS53*$H53 -> 0 | BG53: =AT53*$H53 -> 0 | ... BK53: =AX53*$H53 -> 0 | BL53: =SUM(AZ53:BK53) -> 0 | BY53: =SUM(BM53:BX53) -> 0 | BZ53: =BM53*$I53 -> 0 | CA53: =BN53*$I53 -> 0 | CB53: =BO53*$I53 -> 0 | CC53: =BP53*$I53 -> 0 | CD53: =BQ53*$I53 -> 0 | CE53: =BR53*$I53 -> 0 | CF53: =BS53*$I53 -> 0 | CG53: =BT53*$I53 -> 0 | ... CK53: =BX53*$I53 -> 0 | CL53: =SUM(BZ53:CK53) -> 0 | CY53: =SUM(CM53:CX53) -> 0 | CZ53: =CM53*$J53 -> 0 | DA53: =CN53*$J53 -> 0 | DB53: =CO53*$J53 -> 0 | DC53: =CP53*$J53 -> 0 | DD53: =CQ53*$J53 -> 0 | DE53: =CR53*$J53 -> 0 | DF53: =CS53*$J53 -> 0 | DG53: =CT53*$J53 -> 0 | ... DK53: =CX53*$J53 -> 0 | DL53: =SUM(CZ53:DK53) -> 0 | DY53: =SUM(DM53:DX53) -> 0 | DZ53: =DM53*$K53 -> 0 | EA53: =DN53*$K53 -> 0 | EB53: =DO53*$K53 -> 0 | EC53: =DP53*$K53 -> 0 | ED53: =DQ53*$K53 -> 0 | EE53: =DR53*$K53 -> 0 | EF53: =DS53*$K53 -> 0 | EG53: =DT53*$K53 -> 0 | ... EK53: =DX53*$K53 -> 0 | EL53: =SUM(DZ53:EK53) -> 0
A54: LG Innotek | B54: BYD HX Housing | C54: 3HUO00001A | D54: 4.29 | E54: 4.21 | F54: 4.0632423 | G54: 4.21 | H54: =G54 -> 4.21 | I54: =H54 -> 4.21 | J54: =I54 -> 4.21 | K54: =J54 -> 4.21 | M54: 5005 | N54: 1405 | Q54: 1860 | R54: 0 | S54: 0 | T54: 0 | U54: 0 | V54: 0 | W54: 0 | X54: 0 | Y54: =SUM(M54:X54) -> 8270 | Z54: 21471.45 | AA54: 6429.98 | AB54: 0 | AC54: =P54*$E54 -> 0 | AD54: 7588.8 | AE54: 0 | AF54: =S54*$F54 -> 0 | AG54: =T54*$F54 -> 0 | AH54: =U54*$F54 -> 0 | AI54: =V54*$G54 -> 0 | AJ54: =W54*$G54 -> 0 | AK54: =X54*$G54 -> 0 | AL54: =SUM(Z54:AK54) -> 35490.23 | AY54: =SUM(AM54:AX54) -> 0 | AZ54: =AM54*$H54 -> 0 | BA54: =AN54*$H54 -> 0 | BB54: =AO54*$H54 -> 0 | BC54: =AP54*$H54 -> 0 | BD54: =AQ54*$H54 -> 0 | BE54: =AR54*$H54 -> 0 | BF54: =AS54*$H54 -> 0 | BG54: =AT54*$H54 -> 0 | ... BK54: =AX54*$H54 -> 0 | BL54: =SUM(AZ54:BK54) -> 0 | BY54: =SUM(BM54:BX54) -> 0 | BZ54: =BM54*$I54 -> 0 | CA54: =BN54*$I54 -> 0 | CB54: =BO54*$I54 -> 0 | CC54: =BP54*$I54 -> 0 | CD54: =BQ54*$I54 -> 0 | CE54: =BR54*$I54 -> 0 | CF54: =BS54*$I54 -> 0 | CG54: =BT54*$I54 -> 0 | ... CK54: =BX54*$I54 -> 0 | CL54: =SUM(BZ54:CK54) -> 0 | CY54: =SUM(CM54:CX54) -> 0 | CZ54: =CM54*$J54 -> 0 | DA54: =CN54*$J54 -> 0 | DB54: =CO54*$J54 -> 0 | DC54: =CP54*$J54 -> 0 | DD54: =CQ54*$J54 -> 0 | DE54: =CR54*$J54 -> 0 | DF54: =CS54*$J54 -> 0 | DG54: =CT54*$J54 -> 0 | ... DK54: =CX54*$J54 -> 0 | DL54: =SUM(CZ54:DK54) -> 0 | DY54: =SUM(DM54:DX54) -> 0 | DZ54: =DM54*$K54 -> 0 | EA54: =DN54*$K54 -> 0 | EB54: =DO54*$K54 -> 0 | EC54: =DP54*$K54 -> 0 | ED54: =DQ54*$K54 -> 0 | EE54: =DR54*$K54 -> 0 | EF54: =DS54*$K54 -> 0 | EG54: =DT54*$K54 -> 0 | ... EK54: =DX54*$K54 -> 0 | EL54: =SUM(DZ54:EK54) -> 0
A55: LG Innotek | B55: New LGIT R-EPS Housing 1 | H55: =4.5 -> 4.5 | I55: =H55 -> 4.5 | J55: =I55 -> 4.5 | K55: =J55 -> 4.5 | Y55: =SUM(M55:X55) -> 0 | AB55: 0 | AC55: =P55*$E55 -> 0 | AD55: =Q55*$E55 -> 0 | AE55: =R55*$E55 -> 0 | AF55: =S55*$F55 -> 0 | AG55: =T55*$F55 -> 0 | AH55: =U55*$F55 -> 0 | AI55: =V55*$G55 -> 0 | AJ55: =W55*$G55 -> 0 | AK55: =X55*$G55 -> 0 | AL55: =SUM(Z55:AK55) -> 0 | AS55: 3000 | AT55: 5000 | AU55: 10000 | AV55: 10000 | AW55: 10000 | AX55: 10000 | AY55: =SUM(AM55:AX55) -> 48000 | AZ55: =AM55*$H55 -> 0 | BA55: =AN55*$H55 -> 0 | BB55: =AO55*$H55 -> 0 | BC55: =AP55*$H55 -> 0 | BD55: =AQ55*$H55 -> 0 | BE55: =AR55*$H55 -> 0 | BF55: =AS55*$H55 -> 13500 | BG55: =AT55*$H55 -> 22500 | ... BK55: =AX55*$H55 -> 45000 | BL55: =SUM(AZ55:BK55) -> 216000 | BM55: =200000/12 -> 16666.667 | BN55: =200000/12 -> 16666.667 | BO55: =200000/12 -> 16666.667 | BP55: =200000/12 -> 16666.667 | BQ55: =200000/12 -> 16666.667 | BR55: =200000/12 -> 16666.667 | BS55: =200000/12 -> 16666.667 | BT55: =200000/12 -> 16666.667 | ... BX55: =200000/12 -> 16666.667 | BY55: =SUM(BM55:BX55) -> 200000 | BZ55: =BM55*$I55 -> 75000 | CA55: =BN55*$I55 -> 75000 | CB55: =BO55*$I55 -> 75000 | CC55: =BP55*$I55 -> 75000 | CD55: =BQ55*$I55 -> 75000 | CE55: =BR55*$I55 -> 75000 | CF55: =BS55*$I55 -> 75000 | CG55: =BT55*$I55 -> 75000 | ... CK55: =BX55*$I55 -> 75000 | CL55: =SUM(BZ55:CK55) -> 900000 | CM55: =200000/12 -> 16666.667 | CN55: =200000/12 -> 16666.667 | CO55: =200000/12 -> 16666.667 | CP55: =200000/12 -> 16666.667 | CQ55: =200000/12 -> 16666.667 | CR55: =200000/12 -> 16666.667 | CS55: =200000/12 -> 16666.667 | CT55: =200000/12 -> 16666.667 | ... CX55: =200000/12 -> 16666.667 | CY55: =SUM(CM55:CX55) -> 200000 | CZ55: =CM55*$J55 -> 75000 | DA55: =CN55*$J55 -> 75000 | DB55: =CO55*$J55 -> 75000 | DC55: =CP55*$J55 -> 75000 | DD55: =CQ55*$J55 -> 75000 | DE55: =CR55*$J55 -> 75000 | DF55: =CS55*$J55 -> 75000 | DG55: =CT55*$J55 -> 75000 | ... DK55: =CX55*$J55 -> 75000 | DL55: =SUM(CZ55:DK55) -> 900000 | DM55: =250000/12 -> 20833.333 | DN55: =250000/12 -> 20833.333 | DO55: =250000/12 -> 20833.333 | DP55: =250000/12 -> 20833.333 | DQ55: =250000/12 -> 20833.333 | DR55: =250000/12 -> 20833.333 | DS55: =250000/12 -> 20833.333 | DT55: =250000/12 -> 20833.333 | ... DX55: =250000/12 -> 20833.333 | DY55: =SUM(DM55:DX55) -> 250000 | DZ55: =DM55*$K55 -> 93750 | EA55: =DN55*$K55 -> 93750 | EB55: =DO55*$K55 -> 93750 | EC55: =DP55*$K55 -> 93750 | ED55: =DQ55*$K55 -> 93750 | EE55: =DR55*$K55 -> 93750 | EF55: =DS55*$K55 -> 93750 | EG55: =DT55*$K55 -> 93750 | ... EK55: =DX55*$K55 -> 93750 | EL55: =SUM(DZ55:EK55) -> 1125000
A56: LG Innotek | B56: New LGIT R-EPS Cover 1 | H56: 1.65 | I56: =H56 -> 1.65 | J56: =I56 -> 1.65 | K56: =J56 -> 1.65 | Y56: =SUM(M56:X56) -> 0 | AB56: 0 | AC56: =P56*$E56 -> 0 | AD56: =Q56*$E56 -> 0 | AE56: =R56*$E56 -> 0 | AF56: =S56*$F56 -> 0 | AG56: =T56*$F56 -> 0 | AH56: =U56*$F56 -> 0 | AI56: =V56*$G56 -> 0 | AJ56: =W56*$G56 -> 0 | AK56: =X56*$G56 -> 0 | AL56: =SUM(Z56:AK56) -> 0 | AS56: 3000 | AT56: 5000 | AU56: 10000 | AV56: 10000 | AW56: 10000 | AX56: 10000 | AY56: =SUM(AM56:AX56) -> 48000 | AZ56: =AM56*$H56 -> 0 | BA56: =AN56*$H56 -> 0 | BB56: =AO56*$H56 -> 0 | BC56: =AP56*$H56 -> 0 | BD56: =AQ56*$H56 -> 0 | BE56: =AR56*$H56 -> 0 | BF56: =AS56*$H56 -> 4950 | BG56: =AT56*$H56 -> 8250 | ... BK56: =AX56*$H56 -> 16500 | BL56: =SUM(AZ56:BK56) -> 79200 | BM56: =200000/12 -> 16666.667 | BN56: =200000/12 -> 16666.667 | BO56: =200000/12 -> 16666.667 | BP56: =200000/12 -> 16666.667 | BQ56: =200000/12 -> 16666.667 | BR56: =200000/12 -> 16666.667 | BS56: =200000/12 -> 16666.667 | BT56: =200000/12 -> 16666.667 | ... BX56: =200000/12 -> 16666.667 | BY56: =SUM(BM56:BX56) -> 200000 | BZ56: =BM56*$I56 -> 27500 | CA56: =BN56*$I56 -> 27500 | CB56: =BO56*$I56 -> 27500 | CC56: =BP56*$I56 -> 27500 | CD56: =BQ56*$I56 -> 27500 | CE56: =BR56*$I56 -> 27500 | CF56: =BS56*$I56 -> 27500 | CG56: =BT56*$I56 -> 27500 | ... CK56: =BX56*$I56 -> 27500 | CL56: =SUM(BZ56:CK56) -> 330000 | CM56: =200000/12 -> 16666.667 | CN56: =200000/12 -> 16666.667 | CO56: =200000/12 -> 16666.667 | CP56: =200000/12 -> 16666.667 | CQ56: =200000/12 -> 16666.667 | CR56: =200000/12 -> 16666.667 | CS56: =200000/12 -> 16666.667 | CT56: =200000/12 -> 16666.667 | ... CX56: =200000/12 -> 16666.667 | CY56: =SUM(CM56:CX56) -> 200000 | CZ56: =CM56*$J56 -> 27500 | DA56: =CN56*$J56 -> 27500 | DB56: =CO56*$J56 -> 27500 | DC56: =CP56*$J56 -> 27500 | DD56: =CQ56*$J56 -> 27500 | DE56: =CR56*$J56 -> 27500 | DF56: =CS56*$J56 -> 27500 | DG56: =CT56*$J56 -> 27500 | ... DK56: =CX56*$J56 -> 27500 | DL56: =SUM(CZ56:DK56) -> 330000 | DM56: =250000/12 -> 20833.333 | DN56: =250000/12 -> 20833.333 | DO56: =250000/12 -> 20833.333 | DP56: =250000/12 -> 20833.333 | DQ56: =250000/12 -> 20833.333 | DR56: =250000/12 -> 20833.333 | DS56: =250000/12 -> 20833.333 | DT56: =250000/12 -> 20833.333 | ... DX56: =250000/12 -> 20833.333 | DY56: =SUM(DM56:DX56) -> 250000 | DZ56: =DM56*$K56 -> 34375 | EA56: =DN56*$K56 -> 34375 | EB56: =DO56*$K56 -> 34375 | EC56: =DP56*$K56 -> 34375 | ED56: =DQ56*$K56 -> 34375 | EE56: =DR56*$K56 -> 34375 | EF56: =DS56*$K56 -> 34375 | EG56: =DT56*$K56 -> 34375 | ... EK56: =DX56*$K56 -> 34375 | EL56: =SUM(DZ56:EK56) -> 412500
A57: LG Innotek | B57: New LGIT R-EPS Housing 2 | H57: 4.5 | I57: =H57 -> 4.5 | J57: =I57 -> 4.5 | K57: =J57 -> 4.5 | Y57: =SUM(M57:X57) -> 0 | AB57: 0 | AC57: =P57*$E57 -> 0 | AD57: =Q57*$E57 -> 0 | AE57: =R57*$E57 -> 0 | AF57: =S57*$F57 -> 0 | AG57: =T57*$F57 -> 0 | AH57: =U57*$F57 -> 0 | AI57: =V57*$G57 -> 0 | AJ57: =W57*$G57 -> 0 | AK57: =X57*$G57 -> 0 | AL57: =SUM(Z57:AK57) -> 0 | AU57: 3000 | AV57: 5000 | AW57: 10000 | AX57: 10000 | AY57: =SUM(AM57:AX57) -> 28000 | AZ57: =AM57*$H57 -> 0 | BA57: =AN57*$H57 -> 0 | BB57: =AO57*$H57 -> 0 | BC57: =AP57*$H57 -> 0 | BD57: =AQ57*$H57 -> 0 | BE57: =AR57*$H57 -> 0 | BF57: =AS57*$H57 -> 0 | BG57: =AT57*$H57 -> 0 | ... BK57: =AX57*$H57 -> 45000 | BL57: =SUM(AZ57:BK57) -> 126000 | BM57: =250000/12 -> 20833.333 | BN57: =250000/12 -> 20833.333 | BO57: =250000/12 -> 20833.333 | BP57: =250000/12 -> 20833.333 | BQ57: =250000/12 -> 20833.333 | BR57: =250000/12 -> 20833.333 | BS57: =250000/12 -> 20833.333 | BT57: =250000/12 -> 20833.333 | ... BX57: =250000/12 -> 20833.333 | BY57: =SUM(BM57:BX57) -> 250000 | BZ57: =BM57*$I57 -> 93750 | CA57: =BN57*$I57 -> 93750 | CB57: =BO57*$I57 -> 93750 | CC57: =BP57*$I57 -> 93750 | CD57: =BQ57*$I57 -> 93750 | CE57: =BR57*$I57 -> 93750 | CF57: =BS57*$I57 -> 93750 | CG57: =BT57*$I57 -> 93750 | ... CK57: =BX57*$I57 -> 93750 | CL57: =SUM(BZ57:CK57) -> 1125000 | CM57: =250000/12 -> 20833.333 | CN57: =250000/12 -> 20833.333 | CO57: =250000/12 -> 20833.333 | CP57: =250000/12 -> 20833.333 | CQ57: =250000/12 -> 20833.333 | CR57: =250000/12 -> 20833.333 | CS57: =250000/12 -> 20833.333 | CT57: =250000/12 -> 20833.333 | ... CX57: =250000/12 -> 20833.333 | CY57: =SUM(CM57:CX57) -> 250000 | CZ57: =CM57*$J57 -> 93750 | DA57: =CN57*$J57 -> 93750 | DB57: =CO57*$J57 -> 93750 | DC57: =CP57*$J57 -> 93750 | DD57: =CQ57*$J57 -> 93750 | DE57: =CR57*$J57 -> 93750 | DF57: =CS57*$J57 -> 93750 | DG57: =CT57*$J57 -> 93750 | ... DK57: =CX57*$J57 -> 93750 | DL57: =SUM(CZ57:DK57) -> 1125000 | DM57: =300000/12 -> 25000 | DN57: =300000/12 -> 25000 | DO57: =300000/12 -> 25000 | DP57: =300000/12 -> 25000 | DQ57: =300000/12 -> 25000 | DR57: =300000/12 -> 25000 | DS57: =300000/12 -> 25000 | DT57: =300000/12 -> 25000 | ... DX57: =300000/12 -> 25000 | DY57: =SUM(DM57:DX57) -> 300000 | DZ57: =DM57*$K57 -> 112500 | EA57: =DN57*$K57 -> 112500 | EB57: =DO57*$K57 -> 112500 | EC57: =DP57*$K57 -> 112500 | ED57: =DQ57*$K57 -> 112500 | EE57: =DR57*$K57 -> 112500 | EF57: =DS57*$K57 -> 112500 | EG57: =DT57*$K57 -> 112500 | ... EK57: =DX57*$K57 -> 112500 | EL57: =SUM(DZ57:EK57) -> 1350000
A58: LG Innotek | B58: New LGIT R-EPS Cover 2 | H58: 1.65 | I58: =H58 -> 1.65 | J58: =I58 -> 1.65 | K58: =J58 -> 1.65 | Y58: =SUM(M58:X58) -> 0 | AB58: 0 | AC58: =P58*$E58 -> 0 | AD58: =Q58*$E58 -> 0 | AE58: =R58*$E58 -> 0 | AF58: =S58*$F58 -> 0 | AG58: =T58*$F58 -> 0 | AH58: =U58*$F58 -> 0 | AI58: =V58*$G58 -> 0 | AJ58: =W58*$G58 -> 0 | AK58: =X58*$G58 -> 0 | AL58: =SUM(Z58:AK58) -> 0 | AU58: 3000 | AV58: 5000 | AW58: 10000 | AX58: 10000 | AY58: =SUM(AM58:AX58) -> 28000 | AZ58: =AM58*$H58 -> 0 | BA58: =AN58*$H58 -> 0 | BB58: =AO58*$H58 -> 0 | BC58: =AP58*$H58 -> 0 | BD58: =AQ58*$H58 -> 0 | BE58: =AR58*$H58 -> 0 | BF58: =AS58*$H58 -> 0 | BG58: =AT58*$H58 -> 0 | ... BK58: =AX58*$H58 -> 16500 | BL58: =SUM(AZ58:BK58) -> 46200 | BM58: =250000/12 -> 20833.333 | BN58: =250000/12 -> 20833.333 | BO58: =250000/12 -> 20833.333 | BP58: =250000/12 -> 20833.333 | BQ58: =250000/12 -> 20833.333 | BR58: =250000/12 -> 20833.333 | BS58: =250000/12 -> 20833.333 | BT58: =250000/12 -> 20833.333 | ... BX58: =250000/12 -> 20833.333 | BY58: =SUM(BM58:BX58) -> 250000 | BZ58: =BM58*$I58 -> 34375 | CA58: =BN58*$I58 -> 34375 | CB58: =BO58*$I58 -> 34375 | CC58: =BP58*$I58 -> 34375 | CD58: =BQ58*$I58 -> 34375 | CE58: =BR58*$I58 -> 34375 | CF58: =BS58*$I58 -> 34375 | CG58: =BT58*$I58 -> 34375 | ... CK58: =BX58*$I58 -> 34375 | CL58: =SUM(BZ58:CK58) -> 412500 | CM58: =250000/12 -> 20833.333 | CN58: =250000/12 -> 20833.333 | CO58: =250000/12 -> 20833.333 | CP58: =250000/12 -> 20833.333 | CQ58: =250000/12 -> 20833.333 | CR58: =250000/12 -> 20833.333 | CS58: =250000/12 -> 20833.333 | CT58: =250000/12 -> 20833.333 | ... CX58: =250000/12 -> 20833.333 | CY58: =SUM(CM58:CX58) -> 250000 | CZ58: =CM58*$J58 -> 34375 | DA58: =CN58*$J58 -> 34375 | DB58: =CO58*$J58 -> 34375 | DC58: =CP58*$J58 -> 34375 | DD58: =CQ58*$J58 -> 34375 | DE58: =CR58*$J58 -> 34375 | DF58: =CS58*$J58 -> 34375 | DG58: =CT58*$J58 -> 34375 | ... DK58: =CX58*$J58 -> 34375 | DL58: =SUM(CZ58:DK58) -> 412500 | DM58: =300000/12 -> 25000 | DN58: =300000/12 -> 25000 | DO58: =300000/12 -> 25000 | DP58: =300000/12 -> 25000 | DQ58: =300000/12 -> 25000 | DR58: =300000/12 -> 25000 | DS58: =300000/12 -> 25000 | DT58: =300000/12 -> 25000 | ... DX58: =300000/12 -> 25000 | DY58: =SUM(DM58:DX58) -> 300000 | DZ58: =DM58*$K58 -> 41250 | EA58: =DN58*$K58 -> 41250 | EB58: =DO58*$K58 -> 41250 | EC58: =DP58*$K58 -> 41250 | ED58: =DQ58*$K58 -> 41250 | EE58: =DR58*$K58 -> 41250 | EF58: =DS58*$K58 -> 41250 | EG58: =DT58*$K58 -> 41250 | ... EK58: =DX58*$K58 -> 41250 | EL58: =SUM(DZ58:EK58) -> 495000
A59: LG Innotek | B59: New LGIT C-EPS Housing 1 | H59: 4 | I59: =H59 -> 4 | J59: =I59 -> 4 | K59: =J59 -> 4 | Y59: =SUM(M59:X59) -> 0 | AB59: 0 | AC59: =P59*$E59 -> 0 | AD59: =Q59*$E59 -> 0 | AE59: =R59*$E59 -> 0 | AF59: =S59*$F59 -> 0 | AG59: =T59*$F59 -> 0 | AH59: =U59*$F59 -> 0 | AI59: =V59*$G59 -> 0 | AJ59: =W59*$G59 -> 0 | AK59: =X59*$G59 -> 0 | AL59: =SUM(Z59:AK59) -> 0 | AW59: 5000 | AX59: 10000 | AY59: =SUM(AM59:AX59) -> 15000 | AZ59: =AM59*$H59 -> 0 | BA59: =AN59*$H59 -> 0 | BB59: =AO59*$H59 -> 0 | BC59: =AP59*$H59 -> 0 | BD59: =AQ59*$H59 -> 0 | BE59: =AR59*$H59 -> 0 | BF59: =AS59*$H59 -> 0 | BG59: =AT59*$H59 -> 0 | ... BK59: =AX59*$H59 -> 40000 | BL59: =SUM(AZ59:BK59) -> 60000 | BS59: 3000 | BT59: 5000 | BU59: 10000 | BV59: 10000 | BW59: 10000 | BX59: 10000 | BY59: =SUM(BM59:BX59) -> 48000 | BZ59: =BM59*$I59 -> 0 | CA59: =BN59*$I59 -> 0 | CB59: =BO59*$I59 -> 0 | CC59: =BP59*$I59 -> 0 | CD59: =BQ59*$I59 -> 0 | CE59: =BR59*$I59 -> 0 | CF59: =BS59*$I59 -> 12000 | CG59: =BT59*$I59 -> 20000 | ... CK59: =BX59*$I59 -> 40000 | CL59: =SUM(BZ59:CK59) -> 192000 | CM59: =300000/12 -> 25000 | CN59: =300000/12 -> 25000 | CO59: =300000/12 -> 25000 | CP59: =300000/12 -> 25000 | CQ59: =300000/12 -> 25000 | CR59: =300000/12 -> 25000 | CS59: =300000/12 -> 25000 | CT59: =300000/12 -> 25000 | ... CX59: =300000/12 -> 25000 | CY59: =SUM(CM59:CX59) -> 300000 | CZ59: =CM59*$J59 -> 100000 | DA59: =CN59*$J59 -> 100000 | DB59: =CO59*$J59 -> 100000 | DC59: =CP59*$J59 -> 100000 | DD59: =CQ59*$J59 -> 100000 | DE59: =CR59*$J59 -> 100000 | DF59: =CS59*$J59 -> 100000 | DG59: =CT59*$J59 -> 100000 | ... DK59: =CX59*$J59 -> 100000 | DL59: =SUM(CZ59:DK59) -> 1200000 | DM59: =600000/12 -> 50000 | DN59: =600000/12 -> 50000 | DO59: =600000/12 -> 50000 | DP59: =600000/12 -> 50000 | DQ59: =600000/12 -> 50000 | DR59: =600000/12 -> 50000 | DS59: =600000/12 -> 50000 | DT59: =600000/12 -> 50000 | ... DX59: =600000/12 -> 50000 | DY59: =SUM(DM59:DX59) -> 600000 | DZ59: =DM59*$K59 -> 200000 | EA59: =DN59*$K59 -> 200000 | EB59: =DO59*$K59 -> 200000 | EC59: =DP59*$K59 -> 200000 | ED59: =DQ59*$K59 -> 200000 | EE59: =DR59*$K59 -> 200000 | EF59: =DS59*$K59 -> 200000 | EG59: =DT59*$K59 -> 200000 | ... EK59: =DX59*$K59 -> 200000 | EL59: =SUM(DZ59:EK59) -> 2400000
A60: LG Innotek | B60: New LGIT C-EPS Cover 1 | H60: 1.3 | I60: =H60 -> 1.3 | J60: =I60 -> 1.3 | K60: =J60 -> 1.3 | Y60: =SUM(M60:X60) -> 0 | Z60: =M60*$E60 -> 0 | AA60: =N60*$E60 -> 0 | AB60: 0 | AC60: =P60*$F60 -> 0 | AD60: =Q60*$E60 -> 0 | AE60: =R60*$F60 -> 0 | AF60: =S60*$G60 -> 0 | AG60: =T60*$G60 -> 0 | AH60: =U60*$G60 -> 0 | AI60: =V60*$H60 -> 0 | AJ60: =W60*$H60 -> 0 | AK60: =X60*$H60 -> 0 | AL60: =SUM(Z60:AK60) -> 0 | AW60: 5000 | AX60: 10000 | AY60: =SUM(AM60:AX60) -> 15000 | AZ60: =AM60*$I60 -> 0 | BA60: =AN60*$I60 -> 0 | BB60: =AO60*$I60 -> 0 | BC60: =AP60*$I60 -> 0 | BD60: =AQ60*$I60 -> 0 | BE60: =AR60*$I60 -> 0 | BF60: =AS60*$I60 -> 0 | BG60: =AT60*$I60 -> 0 | ... BK60: =AX60*$I60 -> 13000 | BL60: =SUM(AZ60:BK60) -> 19500 | BS60: 3000 | BT60: 5000 | BU60: 10000 | BV60: 10000 | BW60: 10000 | BX60: 10000 | BY60: =SUM(BM60:BX60) -> 48000 | BZ60: =BM60*$J60 -> 0 | CA60: =BN60*$J60 -> 0 | CB60: =BO60*$J60 -> 0 | CC60: =BP60*$J60 -> 0 | CD60: =BQ60*$J60 -> 0 | CE60: =BR60*$J60 -> 0 | CF60: =BS60*$J60 -> 3900 | CG60: =BT60*$J60 -> 6500 | ... CK60: =BX60*$J60 -> 13000 | CL60: =SUM(BZ60:CK60) -> 62400 | CM60: =300000/12 -> 25000 | CN60: =300000/12 -> 25000 | CO60: =300000/12 -> 25000 | CP60: =300000/12 -> 25000 | CQ60: =300000/12 -> 25000 | CR60: =300000/12 -> 25000 | CS60: =300000/12 -> 25000 | CT60: =300000/12 -> 25000 | ... CX60: =300000/12 -> 25000 | CY60: =SUM(CM60:CX60) -> 300000 | CZ60: =CM60*$J60 -> 32500 | DA60: =CN60*$J60 -> 32500 | DB60: =CO60*$J60 -> 32500 | DC60: =CP60*$J60 -> 32500 | DD60: =CQ60*$J60 -> 32500 | DE60: =CR60*$J60 -> 32500 | DF60: =CS60*$J60 -> 32500 | DG60: =CT60*$J60 -> 32500 | ... DK60: =CX60*$J60 -> 32500 | DL60: =SUM(CZ60:DK60) -> 390000 | DM60: =600000/12 -> 50000 | DN60: =600000/12 -> 50000 | DO60: =600000/12 -> 50000 | DP60: =600000/12 -> 50000 | DQ60: =600000/12 -> 50000 | DR60: =600000/12 -> 50000 | DS60: =600000/12 -> 50000 | DT60: =600000/12 -> 50000 | ... DX60: =600000/12 -> 50000 | DY60: =SUM(DM60:DX60) -> 600000 | DZ60: =DM60*$K60 -> 65000 | EA60: =DN60*$K60 -> 65000 | EB60: =DO60*$K60 -> 65000 | EC60: =DP60*$K60 -> 65000 | ED60: =DQ60*$K60 -> 65000 | EE60: =DR60*$K60 -> 65000 | EF60: =DS60*$K60 -> 65000 | EG60: =DT60*$K60 -> 65000 | ... EK60: =DX60*$K60 -> 65000 | EL60: =SUM(DZ60:EK60) -> 780000
A61: LG Innotek | B61: BMS Top Case | C61: 3CAC00181A | D61: 2.5909 | E61: 2.5909 | F61: 2.5909 | G61: 2.5909 | H61: =G61 -> 2.5909 | I61: =H61 -> 2.5909 | J61: =I61 -> 2.5909 | K61: =J61 -> 2.5909 | P61: 11520 | X61: 0 | Y61: =SUM(M61:X61) -> 11520 | Z61: 0 | AA61: 0 | AB61: 0 | AC61: 27142 | AD61: =Q61*$E61 -> 0 | AE61: =R61*$E61 -> 0 | AF61: =S61*$F61 -> 0 | AG61: =T61*$F61 -> 0 | AH61: =U61*$F61 -> 0 | AI61: =V61*$G61 -> 0 | AJ61: =W61*$G61 -> 0 | AK61: =X61*$G61 -> 0 | AL61: =SUM(Z61:AK61) -> 27142 | AM61: =35000/12 -> 2916.6667 | AN61: =35000/12 -> 2916.6667 | AO61: =35000/12 -> 2916.6667 | AP61: =35000/12 -> 2916.6667 | AQ61: =35000/12 -> 2916.6667 | AR61: =35000/12 -> 2916.6667 | AS61: =35000/12 -> 2916.6667 | AT61: =35000/12 -> 2916.6667 | ... AX61: =35000/12 -> 2916.6667 | AY61: =SUM(AM61:AX61) -> 35000 | AZ61: =AM61*$H61 -> 7556.7917 | BA61: =AN61*$H61 -> 7556.7917 | BB61: =AO61*$H61 -> 7556.7917 | BC61: =AP61*$H61 -> 7556.7917 | BD61: =AQ61*$H61 -> 7556.7917 | BE61: =AR61*$H61 -> 7556.7917 | BF61: =AS61*$H61 -> 7556.7917 | BG61: =AT61*$H61 -> 7556.7917 | ... BK61: =AX61*$H61 -> 7556.7917 | BL61: =SUM(AZ61:BK61) -> 90681.5 | BM61: =35000/12 -> 2916.6667 | BN61: =35000/12 -> 2916.6667 | BO61: =35000/12 -> 2916.6667 | BP61: =35000/12 -> 2916.6667 | BQ61: =35000/12 -> 2916.6667 | BR61: =35000/12 -> 2916.6667 | BS61: =35000/12 -> 2916.6667 | BT61: =35000/12 -> 2916.6667 | ... BX61: =35000/12 -> 2916.6667 | BY61: =SUM(BM61:BX61) -> 35000 | BZ61: =BM61*$I61 -> 7556.7917 | CA61: =BN61*$I61 -> 7556.7917 | CB61: =BO61*$I61 -> 7556.7917 | CC61: =BP61*$I61 -> 7556.7917 | CD61: =BQ61*$I61 -> 7556.7917 | CE61: =BR61*$I61 -> 7556.7917 | CF61: =BS61*$I61 -> 7556.7917 | CG61: =BT61*$I61 -> 7556.7917 | ... CK61: =BX61*$I61 -> 7556.7917 | CL61: =SUM(BZ61:CK61) -> 90681.5 | CM61: =35000/12 -> 2916.6667 | CN61: =35000/12 -> 2916.6667 | CO61: =35000/12 -> 2916.6667 | CP61: =35000/12 -> 2916.6667 | CQ61: =35000/12 -> 2916.6667 | CR61: =35000/12 -> 2916.6667 | CS61: =35000/12 -> 2916.6667 | CT61: =35000/12 -> 2916.6667 | ... CX61: =35000/12 -> 2916.6667 | CY61: =SUM(CM61:CX61) -> 35000 | CZ61: =CM61*$J61 -> 7556.7917 | DA61: =CN61*$J61 -> 7556.7917 | DB61: =CO61*$J61 -> 7556.7917 | DC61: =CP61*$J61 -> 7556.7917 | DD61: =CQ61*$J61 -> 7556.7917 | DE61: =CR61*$J61 -> 7556.7917 | DF61: =CS61*$J61 -> 7556.7917 | DG61: =CT61*$J61 -> 7556.7917 | ... DK61: =CX61*$J61 -> 7556.7917 | DL61: =SUM(CZ61:DK61) -> 90681.5 | DM61: =35000/12 -> 2916.6667 | DN61: =35000/12 -> 2916.6667 | DO61: =35000/12 -> 2916.6667 | DP61: =35000/12 -> 2916.6667 | DQ61: =35000/12 -> 2916.6667 | DR61: =35000/12 -> 2916.6667 | DS61: =35000/12 -> 2916.6667 | DT61: =35000/12 -> 2916.6667 | ... DX61: =35000/12 -> 2916.6667 | DY61: =SUM(DM61:DX61) -> 35000 | DZ61: =DM61*$K61 -> 7556.7917 | EA61: =DN61*$K61 -> 7556.7917 | EB61: =DO61*$K61 -> 7556.7917 | EC61: =DP61*$K61 -> 7556.7917 | ED61: =DQ61*$K61 -> 7556.7917 | EE61: =DR61*$K61 -> 7556.7917 | EF61: =DS61*$K61 -> 7556.7917 | EG61: =DT61*$K61 -> 7556.7917 | ... EK61: =DX61*$K61 -> 7556.7917 | EL61: =SUM(DZ61:EK61) -> 90681.5
A62: LG Innotek | B62: BMS Bottom Case | C62: 3CAC00182A | D62: 2.0857 | E62: 2.0857 | F62: 2.0857 | G62: 2.0857 | H62: =G62 -> 2.0857 | I62: =H62 -> 2.0857 | J62: =I62 -> 2.0857 | K62: =J62 -> 2.0857 | O62: 1000 | P62: 9800 | X62: 0 | Y62: =SUM(M62:X62) -> 10800 | Z62: 0 | AA62: 0 | AB62: 1866.4 | AC62: 18291 | AD62: =Q62*$E62 -> 0 | AE62: =R62*$E62 -> 0 | AF62: =S62*$F62 -> 0 | AG62: =T62*$F62 -> 0 | AH62: =U62*$F62 -> 0 | AI62: =V62*$G62 -> 0 | AJ62: =W62*$G62 -> 0 | AK62: =X62*$G62 -> 0 | AL62: =SUM(Z62:AK62) -> 20157.4 | AM62: =35000/12 -> 2916.6667 | AN62: =35000/12 -> 2916.6667 | AO62: =35000/12 -> 2916.6667 | AP62: =35000/12 -> 2916.6667 | AQ62: =35000/12 -> 2916.6667 | AR62: =35000/12 -> 2916.6667 | AS62: =35000/12 -> 2916.6667 | AT62: =35000/12 -> 2916.6667 | ... AX62: =35000/12 -> 2916.6667 | AY62: =SUM(AM62:AX62) -> 35000 | AZ62: =AM62*$H62 -> 6083.2917 | BA62: =AN62*$H62 -> 6083.2917 | BB62: =AO62*$H62 -> 6083.2917 | BC62: =AP62*$H62 -> 6083.2917 | BD62: =AQ62*$H62 -> 6083.2917 | BE62: =AR62*$H62 -> 6083.2917 | BF62: =AS62*$H62 -> 6083.2917 | BG62: =AT62*$H62 -> 6083.2917 | ... BK62: =AX62*$H62 -> 6083.2917 | BL62: =SUM(AZ62:BK62) -> 72999.5 | BM62: =35000/12 -> 2916.6667 | BN62: =35000/12 -> 2916.6667 | BO62: =35000/12 -> 2916.6667 | BP62: =35000/12 -> 2916.6667 | BQ62: =35000/12 -> 2916.6667 | BR62: =35000/12 -> 2916.6667 | BS62: =35000/12 -> 2916.6667 | BT62: =35000/12 -> 2916.6667 | ... BX62: =35000/12 -> 2916.6667 | BY62: =SUM(BM62:BX62) -> 35000 | BZ62: =BM62*$I62 -> 6083.2917 | CA62: =BN62*$I62 -> 6083.2917 | CB62: =BO62*$I62 -> 6083.2917 | CC62: =BP62*$I62 -> 6083.2917 | CD62: =BQ62*$I62 -> 6083.2917 | CE62: =BR62*$I62 -> 6083.2917 | CF62: =BS62*$I62 -> 6083.2917 | CG62: =BT62*$I62 -> 6083.2917 | ... CK62: =BX62*$I62 -> 6083.2917 | CL62: =SUM(BZ62:CK62) -> 72999.5 | CM62: =35000/12 -> 2916.6667 | CN62: =35000/12 -> 2916.6667 | CO62: =35000/12 -> 2916.6667 | CP62: =35000/12 -> 2916.6667 | CQ62: =35000/12 -> 2916.6667 | CR62: =35000/12 -> 2916.6667 | CS62: =35000/12 -> 2916.6667 | CT62: =35000/12 -> 2916.6667 | ... CX62: =35000/12 -> 2916.6667 | CY62: =SUM(CM62:CX62) -> 35000 | CZ62: =CM62*$J62 -> 6083.2917 | DA62: =CN62*$J62 -> 6083.2917 | DB62: =CO62*$J62 -> 6083.2917 | DC62: =CP62*$J62 -> 6083.2917 | DD62: =CQ62*$J62 -> 6083.2917 | DE62: =CR62*$J62 -> 6083.2917 | DF62: =CS62*$J62 -> 6083.2917 | DG62: =CT62*$J62 -> 6083.2917 | ... DK62: =CX62*$J62 -> 6083.2917 | DL62: =SUM(CZ62:DK62) -> 72999.5 | DM62: =35000/12 -> 2916.6667 | DN62: =35000/12 -> 2916.6667 | DO62: =35000/12 -> 2916.6667 | DP62: =35000/12 -> 2916.6667 | DQ62: =35000/12 -> 2916.6667 | DR62: =35000/12 -> 2916.6667 | DS62: =35000/12 -> 2916.6667 | DT62: =35000/12 -> 2916.6667 | ... DX62: =35000/12 -> 2916.6667 | DY62: =SUM(DM62:DX62) -> 35000 | DZ62: =DM62*$K62 -> 6083.2917 | EA62: =DN62*$K62 -> 6083.2917 | EB62: =DO62*$K62 -> 6083.2917 | EC62: =DP62*$K62 -> 6083.2917 | ED62: =DQ62*$K62 -> 6083.2917 | EE62: =DR62*$K62 -> 6083.2917 | EF62: =DS62*$K62 -> 6083.2917 | EG62: =DT62*$K62 -> 6083.2917 | ... EK62: =DX62*$K62 -> 6083.2917 | EL62: =SUM(DZ62:EK62) -> 72999.5
A63: LG Innotek | B63: BMS Top Case-PL | C63: 3CAC00181A-PL | D63: 2.4709 | E63: 2.4709 | F63: 2.166 | G63: 2.4709 | H63: =G63 -> 2.4709 | I63: =H63 -> 2.4709 | J63: =I63 -> 2.4709 | K63: =J63 -> 2.4709 | M63: 3600 | N63: 3600 | O63: 3600 | S63: 1350 | T63: 1500 | U63: 1500 | V63: 1500 | Y63: =SUM(M63:X63) -> 16650 | Z63: 8678.52 | AA63: 7797.6 | AB63: 7797.6 | AC63: =P63*$E63 -> 0 | AD63: =Q63*$E63 -> 0 | AE63: =R63*$E63 -> 0 | AF63: =S63*$F63 -> 2924.1 | AG63: =T63*$F63 -> 3249 | AH63: =U63*$F63 -> 3249 | AI63: =V63*$G63 -> 3706.35 | AJ63: =W63*$G63 -> 0 | AK63: =X63*$G63 -> 0 | AL63: =SUM(Z63:AK63) -> 37402.17 | AM63: =41000/12 -> 3416.6667 | AN63: =41000/12 -> 3416.6667 | AO63: =41000/12 -> 3416.6667 | AP63: =41000/12 -> 3416.6667 | AQ63: =41000/12 -> 3416.6667 | AR63: =41000/12 -> 3416.6667 | AS63: =41000/12 -> 3416.6667 | AT63: =41000/12 -> 3416.6667 | ... AX63: =41000/12 -> 3416.6667 | AY63: =SUM(AM63:AX63) -> 41000 | AZ63: =AM63*$H63 -> 8442.2417 | BA63: =AN63*$H63 -> 8442.2417 | BB63: =AO63*$H63 -> 8442.2417 | BC63: =AP63*$H63 -> 8442.2417 | BD63: =AQ63*$H63 -> 8442.2417 | BE63: =AR63*$H63 -> 8442.2417 | BF63: =AS63*$H63 -> 8442.2417 | BG63: =AT63*$H63 -> 8442.2417 | ... BK63: =AX63*$H63 -> 8442.2417 | BL63: =SUM(AZ63:BK63) -> 101306.9 | BM63: =41000/12 -> 3416.6667 | BN63: =41000/12 -> 3416.6667 | BO63: =41000/12 -> 3416.6667 | BP63: =41000/12 -> 3416.6667 | BQ63: =41000/12 -> 3416.6667 | BR63: =41000/12 -> 3416.6667 | BS63: =41000/12 -> 3416.6667 | BT63: =41000/12 -> 3416.6667 | ... BX63: =41000/12 -> 3416.6667 | BY63: =SUM(BM63:BX63) -> 41000 | BZ63: =BM63*$I63 -> 8442.2417 | CA63: =BN63*$I63 -> 8442.2417 | CB63: =BO63*$I63 -> 8442.2417 | CC63: =BP63*$I63 -> 8442.2417 | CD63: =BQ63*$I63 -> 8442.2417 | CE63: =BR63*$I63 -> 8442.2417 | CF63: =BS63*$I63 -> 8442.2417 | CG63: =BT63*$I63 -> 8442.2417 | ... CK63: =BX63*$I63 -> 8442.2417 | CL63: =SUM(BZ63:CK63) -> 101306.9 | CM63: =41000/12 -> 3416.6667 | CN63: =41000/12 -> 3416.6667 | CO63: =41000/12 -> 3416.6667 | CP63: =41000/12 -> 3416.6667 | CQ63: =41000/12 -> 3416.6667 | CR63: =41000/12 -> 3416.6667 | CS63: =41000/12 -> 3416.6667 | CT63: =41000/12 -> 3416.6667 | ... CX63: =41000/12 -> 3416.6667 | CY63: =SUM(CM63:CX63) -> 41000 | CZ63: =CM63*$J63 -> 8442.2417 | DA63: =CN63*$J63 -> 8442.2417 | DB63: =CO63*$J63 -> 8442.2417 | DC63: =CP63*$J63 -> 8442.2417 | DD63: =CQ63*$J63 -> 8442.2417 | DE63: =CR63*$J63 -> 8442.2417 | DF63: =CS63*$J63 -> 8442.2417 | DG63: =CT63*$J63 -> 8442.2417 | ... DK63: =CX63*$J63 -> 8442.2417 | DL63: =SUM(CZ63:DK63) -> 101306.9 | DM63: =41000/12 -> 3416.6667 | DN63: =41000/12 -> 3416.6667 | DO63: =41000/12 -> 3416.6667 | DP63: =41000/12 -> 3416.6667 | DQ63: =41000/12 -> 3416.6667 | DR63: =41000/12 -> 3416.6667 | DS63: =41000/12 -> 3416.6667 | DT63: =41000/12 -> 3416.6667 | ... DX63: =41000/12 -> 3416.6667 | DY63: =SUM(DM63:DX63) -> 41000 | DZ63: =DM63*$K63 -> 8442.2417 | EA63: =DN63*$K63 -> 8442.2417 | EB63: =DO63*$K63 -> 8442.2417 | EC63: =DP63*$K63 -> 8442.2417 | ED63: =DQ63*$K63 -> 8442.2417 | EE63: =DR63*$K63 -> 8442.2417 | EF63: =DS63*$K63 -> 8442.2417 | EG63: =DT63*$K63 -> 8442.2417 | ... EK63: =DX63*$K63 -> 8442.2417 | EL63: =SUM(DZ63:EK63) -> 101306.9
A64: LG Innotek | B64: BMS Bottom Case-PL | C64: 3CAC00182A-PL | D64: 1.9857 | E64: 1.9857 | F64: 1.7044 | G64: 1.9857 | H64: =G64 -> 1.9857 | I64: =H64 -> 1.9857 | J64: =I64 -> 1.9857 | K64: =J64 -> 1.9857 | M64: 3600 | N64: 3600 | O64: 3600 | S64: 2700 | T64: 1500 | U64: 1500 | V64: 1500 | Y64: =SUM(M64:X64) -> 18000 | Z64: 7016.76 | AA64: 6429.48 | AB64: 6135.84 | AC64: =P64*$E64 -> 0 | AD64: =Q64*$E64 -> 0 | AE64: =R64*$E64 -> 0 | AF64: =S64*$F64 -> 4601.88 | AG64: =T64*$F64 -> 2556.6 | AH64: =U64*$F64 -> 2556.6 | AI64: =V64*$G64 -> 2978.55 | AJ64: =W64*$G64 -> 0 | AK64: =X64*$G64 -> 0 | AL64: =SUM(Z64:AK64) -> 32275.71 | AM64: =41000/12 -> 3416.6667 | AN64: =41000/12 -> 3416.6667 | AO64: =41000/12 -> 3416.6667 | AP64: =41000/12 -> 3416.6667 | AQ64: =41000/12 -> 3416.6667 | AR64: =41000/12 -> 3416.6667 | AS64: =41000/12 -> 3416.6667 | AT64: =41000/12 -> 3416.6667 | ... AX64: =41000/12 -> 3416.6667 | AY64: =SUM(AM64:AX64) -> 41000 | AZ64: =AM64*$H64 -> 6784.475 | BA64: =AN64*$H64 -> 6784.475 | BB64: =AO64*$H64 -> 6784.475 | BC64: =AP64*$H64 -> 6784.475 | BD64: =AQ64*$H64 -> 6784.475 | BE64: =AR64*$H64 -> 6784.475 | BF64: =AS64*$H64 -> 6784.475 | BG64: =AT64*$H64 -> 6784.475 | ... BK64: =AX64*$H64 -> 6784.475 | BL64: =SUM(AZ64:BK64) -> 81413.7 | BM64: =41000/12 -> 3416.6667 | BN64: =41000/12 -> 3416.6667 | BO64: =41000/12 -> 3416.6667 | BP64: =41000/12 -> 3416.6667 | BQ64: =41000/12 -> 3416.6667 | BR64: =41000/12 -> 3416.6667 | BS64: =41000/12 -> 3416.6667 | BT64: =41000/12 -> 3416.6667 | ... BX64: =41000/12 -> 3416.6667 | BY64: =SUM(BM64:BX64) -> 41000 | BZ64: =BM64*$I64 -> 6784.475 | CA64: =BN64*$I64 -> 6784.475 | CB64: =BO64*$I64 -> 6784.475 | CC64: =BP64*$I64 -> 6784.475 | CD64: =BQ64*$I64 -> 6784.475 | CE64: =BR64*$I64 -> 6784.475 | CF64: =BS64*$I64 -> 6784.475 | CG64: =BT64*$I64 -> 6784.475 | ... CK64: =BX64*$I64 -> 6784.475 | CL64: =SUM(BZ64:CK64) -> 81413.7 | CM64: =41000/12 -> 3416.6667 | CN64: =41000/12 -> 3416.6667 | CO64: =41000/12 -> 3416.6667 | CP64: =41000/12 -> 3416.6667 | CQ64: =41000/12 -> 3416.6667 | CR64: =41000/12 -> 3416.6667 | CS64: =41000/12 -> 3416.6667 | CT64: =41000/12 -> 3416.6667 | ... CX64: =41000/12 -> 3416.6667 | CY64: =SUM(CM64:CX64) -> 41000 | CZ64: =CM64*$J64 -> 6784.475 | DA64: =CN64*$J64 -> 6784.475 | DB64: =CO64*$J64 -> 6784.475 | DC64: =CP64*$J64 -> 6784.475 | DD64: =CQ64*$J64 -> 6784.475 | DE64: =CR64*$J64 -> 6784.475 | DF64: =CS64*$J64 -> 6784.475 | DG64: =CT64*$J64 -> 6784.475 | ... DK64: =CX64*$J64 -> 6784.475 | DL64: =SUM(CZ64:DK64) -> 81413.7 | DM64: =41000/12 -> 3416.6667 | DN64: =41000/12 -> 3416.6667 | DO64: =41000/12 -> 3416.6667 | DP64: =41000/12 -> 3416.6667 | DQ64: =41000/12 -> 3416.6667 | DR64: =41000/12 -> 3416.6667 | DS64: =41000/12 -> 3416.6667 | DT64: =41000/12 -> 3416.6667 | ... DX64: =41000/12 -> 3416.6667 | DY64: =SUM(DM64:DX64) -> 41000 | DZ64: =DM64*$K64 -> 6784.475 | EA64: =DN64*$K64 -> 6784.475 | EB64: =DO64*$K64 -> 6784.475 | EC64: =DP64*$K64 -> 6784.475 | ED64: =DQ64*$K64 -> 6784.475 | EE64: =DR64*$K64 -> 6784.475 | EF64: =DS64*$K64 -> 6784.475 | EG64: =DT64*$K64 -> 6784.475 | ... EK64: =DX64*$K64 -> 6784.475 | EL64: =SUM(DZ64:EK64) -> 81413.7
A65: LG Innotek | B65: DCU15 Housing-KR | C65: 3CAC00306A | D65: 0.71 | E65: 0.71 | F65: 0.71 | G65: 0.71 | H65: =G65 -> 0.71 | I65: =H65 -> 0.71 | J65: =I65 -> 0.71 | K65: =J65 -> 0.71 | M65: 23000 | N65: 24000 | O65: 30000 | P65: 32000 | Q65: 33000 | R65: 20000 | T65: 30000 | U65: 20000 | V65: 12000 | W65: 12000 | X65: 12000 | Y65: =SUM(M65:X65) -> 248000 | Z65: 16330 | AA65: 17040 | AB65: 21300 | AC65: =P65*$E65 -> 22720 | AD65: =Q65*$E65 -> 23430 | AE65: =R65*$E65 -> 14200 | AF65: =S65*$F65 -> 0 | AG65: =T65*$F65 -> 21300 | AH65: =U65*$F65 -> 14200 | AI65: =V65*$G65 -> 8520 | AJ65: =W65*$G65 -> 8520 | AK65: =X65*$G65 -> 8520 | AL65: =SUM(Z65:AK65) -> 176080 | AM65: =84042/12 -> 7003.5 | AN65: =84042/12 -> 7003.5 | AO65: =84042/12 -> 7003.5 | AP65: =84042/12 -> 7003.5 | AQ65: =84042/12 -> 7003.5 | AR65: =84042/12 -> 7003.5 | AS65: =84042/12 -> 7003.5 | AT65: =84042/12 -> 7003.5 | ... AX65: =84042/12 -> 7003.5 | AY65: =SUM(AM65:AX65) -> 84042 | AZ65: =AM65*$H65 -> 4972.485 | BA65: =AN65*$H65 -> 4972.485 | BB65: =AO65*$H65 -> 4972.485 | BC65: =AP65*$H65 -> 4972.485 | BD65: =AQ65*$H65 -> 4972.485 | BE65: =AR65*$H65 -> 4972.485 | BF65: =AS65*$H65 -> 4972.485 | BG65: =AT65*$H65 -> 4972.485 | ... BK65: =AX65*$H65 -> 4972.485 | BL65: =SUM(AZ65:BK65) -> 59669.82 | BM65: =89978/12 -> 7498.1667 | BN65: =89978/12 -> 7498.1667 | BO65: =89978/12 -> 7498.1667 | BP65: =89978/12 -> 7498.1667 | BQ65: =89978/12 -> 7498.1667 | BR65: =89978/12 -> 7498.1667 | BS65: =89978/12 -> 7498.1667 | BT65: =89978/12 -> 7498.1667 | ... BX65: =89978/12 -> 7498.1667 | BY65: =SUM(BM65:BX65) -> 89978 | BZ65: =BM65*$I65 -> 5323.6983 | CA65: =BN65*$I65 -> 5323.6983 | CB65: =BO65*$I65 -> 5323.6983 | CC65: =BP65*$I65 -> 5323.6983 | CD65: =BQ65*$I65 -> 5323.6983 | CE65: =BR65*$I65 -> 5323.6983 | CF65: =BS65*$I65 -> 5323.6983 | CG65: =BT65*$I65 -> 5323.6983 | ... CK65: =BX65*$I65 -> 5323.6983 | CL65: =SUM(BZ65:CK65) -> 63884.38 | CM65: =89978/12 -> 7498.1667 | CN65: =89978/12 -> 7498.1667 | CO65: =89978/12 -> 7498.1667 | CP65: =89978/12 -> 7498.1667 | CQ65: =89978/12 -> 7498.1667 | CR65: =89978/12 -> 7498.1667 | CS65: =89978/12 -> 7498.1667 | CT65: =89978/12 -> 7498.1667 | ... CX65: =89978/12 -> 7498.1667 | CY65: =SUM(CM65:CX65) -> 89978 | CZ65: =CM65*$J65 -> 5323.6983 | DA65: =CN65*$J65 -> 5323.6983 | DB65: =CO65*$J65 -> 5323.6983 | DC65: =CP65*$J65 -> 5323.6983 | DD65: =CQ65*$J65 -> 5323.6983 | DE65: =CR65*$J65 -> 5323.6983 | DF65: =CS65*$J65 -> 5323.6983 | DG65: =CT65*$J65 -> 5323.6983 | ... DK65: =CX65*$J65 -> 5323.6983 | DL65: =SUM(CZ65:DK65) -> 63884.38 | DM65: =90720/12 -> 7560 | DN65: =90720/12 -> 7560 | DO65: =90720/12 -> 7560 | DP65: =90720/12 -> 7560 | DQ65: =90720/12 -> 7560 | DR65: =90720/12 -> 7560 | DS65: =90720/12 -> 7560 | DT65: =90720/12 -> 7560 | ... DX65: =90720/12 -> 7560 | DY65: =SUM(DM65:DX65) -> 90720 | DZ65: =DM65*$K65 -> 5367.6 | EA65: =DN65*$K65 -> 5367.6 | EB65: =DO65*$K65 -> 5367.6 | EC65: =DP65*$K65 -> 5367.6 | ED65: =DQ65*$K65 -> 5367.6 | EE65: =DR65*$K65 -> 5367.6 | EF65: =DS65*$K65 -> 5367.6 | EG65: =DT65*$K65 -> 5367.6 | ... EK65: =DX65*$K65 -> 5367.6 | EL65: =SUM(DZ65:EK65) -> 64411.2
A66: LG Innotek | B66: DCU15 Cover-KR | C66: 3CAC00307A | D66: 0.5 | E66: 0.5 | F66: 0.5 | G66: 0.5 | H66: =G66 -> 0.5 | I66: =H66 -> 0.5 | J66: =I66 -> 0.5 | K66: =J66 -> 0.5 | M66: 23000 | N66: 24000 | O66: 30000 | P66: 32000 | Q66: 33000 | R66: 20000 | T66: 30000 | U66: 20000 | V66: 12000 | W66: 12000 | X66: 12000 | Y66: =SUM(M66:X66) -> 248000 | Z66: 11500 | AA66: 12000 | AB66: 15000 | AC66: =P66*$E66 -> 16000 | AD66: =Q66*$E66 -> 16500 | AE66: =R66*$E66 -> 10000 | AF66: =S66*$F66 -> 0 | AG66: =T66*$F66 -> 15000 | AH66: =U66*$F66 -> 10000 | AI66: =V66*$G66 -> 6000 | AJ66: =W66*$G66 -> 6000 | AK66: =X66*$G66 -> 6000 | AL66: =SUM(Z66:AK66) -> 124000 | AM66: =84042/12 -> 7003.5 | AN66: =84042/12 -> 7003.5 | AO66: =84042/12 -> 7003.5 | AP66: =84042/12 -> 7003.5 | AQ66: =84042/12 -> 7003.5 | AR66: =84042/12 -> 7003.5 | AS66: =84042/12 -> 7003.5 | AT66: =84042/12 -> 7003.5 | ... AX66: =84042/12 -> 7003.5 | AY66: =SUM(AM66:AX66) -> 84042 | AZ66: =AM66*$H66 -> 3501.75 | BA66: =AN66*$H66 -> 3501.75 | BB66: =AO66*$H66 -> 3501.75 | BC66: =AP66*$H66 -> 3501.75 | BD66: =AQ66*$H66 -> 3501.75 | BE66: =AR66*$H66 -> 3501.75 | BF66: =AS66*$H66 -> 3501.75 | BG66: =AT66*$H66 -> 3501.75 | ... BK66: =AX66*$H66 -> 3501.75 | BL66: =SUM(AZ66:BK66) -> 42021 | BM66: =89978/12 -> 7498.1667 | BN66: =89978/12 -> 7498.1667 | BO66: =89978/12 -> 7498.1667 | BP66: =89978/12 -> 7498.1667 | BQ66: =89978/12 -> 7498.1667 | BR66: =89978/12 -> 7498.1667 | BS66: =89978/12 -> 7498.1667 | BT66: =89978/12 -> 7498.1667 | ... BX66: =89978/12 -> 7498.1667 | BY66: =SUM(BM66:BX66) -> 89978 | BZ66: =BM66*$I66 -> 3749.0833 | CA66: =BN66*$I66 -> 3749.0833 | CB66: =BO66*$I66 -> 3749.0833 | CC66: =BP66*$I66 -> 3749.0833 | CD66: =BQ66*$I66 -> 3749.0833 | CE66: =BR66*$I66 -> 3749.0833 | CF66: =BS66*$I66 -> 3749.0833 | CG66: =BT66*$I66 -> 3749.0833 | ... CK66: =BX66*$I66 -> 3749.0833 | CL66: =SUM(BZ66:CK66) -> 44989 | CM66: =89978/12 -> 7498.1667 | CN66: =89978/12 -> 7498.1667 | CO66: =89978/12 -> 7498.1667 | CP66: =89978/12 -> 7498.1667 | CQ66: =89978/12 -> 7498.1667 | CR66: =89978/12 -> 7498.1667 | CS66: =89978/12 -> 7498.1667 | CT66: =89978/12 -> 7498.1667 | ... CX66: =89978/12 -> 7498.1667 | CY66: =SUM(CM66:CX66) -> 89978 | CZ66: =CM66*$J66 -> 3749.0833 | DA66: =CN66*$J66 -> 3749.0833 | DB66: =CO66*$J66 -> 3749.0833 | DC66: =CP66*$J66 -> 3749.0833 | DD66: =CQ66*$J66 -> 3749.0833 | DE66: =CR66*$J66 -> 3749.0833 | DF66: =CS66*$J66 -> 3749.0833 | DG66: =CT66*$J66 -> 3749.0833 | ... DK66: =CX66*$J66 -> 3749.0833 | DL66: =SUM(CZ66:DK66) -> 44989 | DM66: =90720/12 -> 7560 | DN66: =90720/12 -> 7560 | DO66: =90720/12 -> 7560 | DP66: =90720/12 -> 7560 | DQ66: =90720/12 -> 7560 | DR66: =90720/12 -> 7560 | DS66: =90720/12 -> 7560 | DT66: =90720/12 -> 7560 | ... DX66: =90720/12 -> 7560 | DY66: =SUM(DM66:DX66) -> 90720 | DZ66: =DM66*$K66 -> 3780 | EA66: =DN66*$K66 -> 3780 | EB66: =DO66*$K66 -> 3780 | EC66: =DP66*$K66 -> 3780 | ED66: =DQ66*$K66 -> 3780 | EE66: =DR66*$K66 -> 3780 | EF66: =DS66*$K66 -> 3780 | EG66: =DT66*$K66 -> 3780 | ... EK66: =DX66*$K66 -> 3780 | EL66: =SUM(DZ66:EK66) -> 45360
A67: LG Innotek | B67: OMS Entry Vcsel Cover | C67: 3CAC00250A | D67: 0.7155 | E67: 0.7155 | F67: 0.7155 | G67: 0.7155 | H67: 0.7155 | I67: 0.7155 | J67: 0.7155 | K67: 0.7155 | M67: 6300 | N67: 18900 | O67: 12600 | P67: 12600 | R67: 12600 | S67: 12600 | T67: 12000 | U67: 12000 | V67: 12000 | W67: 12000 | X67: 12000 | Y67: =SUM(M67:X67) -> 135600 | Z67: 4507.65 | AA67: 13522.95 | AB67: 9015.3 | AC67: 9015 | AE67: =R67*$E67 -> 9015.3 | AF67: =S67*$F67 -> 9015.3 | AG67: =T67*$F67 -> 8586 | AH67: =U67*$F67 -> 8586 | AI67: =V67*$G67 -> 8586 | AJ67: =W67*$G67 -> 8586 | AK67: =X67*$G67 -> 8586 | AL67: =SUM(Z67:AK67) -> 97021.5 | AM67: 10000 | AN67: 10000 | AO67: 10000 | AP67: 10000 | AQ67: 10000 | AR67: 10000 | AS67: 10000 | AT67: 10000 | AU67: 10000 | AV67: 10000 | AW67: 10000 | AX67: 10000 | AY67: =SUM(AM67:AX67) -> 120000 | AZ67: =AM67*$H67 -> 7155 | BA67: =AN67*$H67 -> 7155 | BB67: =AO67*$H67 -> 7155 | BC67: =AP67*$H67 -> 7155 | BD67: =AQ67*$H67 -> 7155 | BE67: =AR67*$H67 -> 7155 | BF67: =AS67*$H67 -> 7155 | BG67: =AT67*$H67 -> 7155 | ... BK67: =AX67*$H67 -> 7155 | BL67: =SUM(AZ67:BK67) -> 85860 | BM67: 10000 | BN67: 10000 | BO67: 10000 | BP67: 10000 | BQ67: 10000 | BR67: 10000 | BS67: 10000 | BT67: 10000 | BU67: 10000 | BV67: 10000 | BW67: 10000 | BX67: 10000 | BY67: =SUM(BM67:BX67) -> 120000 | BZ67: =BM67*$I67 -> 7155 | CA67: =BN67*$I67 -> 7155 | CB67: =BO67*$I67 -> 7155 | CC67: =BP67*$I67 -> 7155 | CD67: =BQ67*$I67 -> 7155 | CE67: =BR67*$I67 -> 7155 | CF67: =BS67*$I67 -> 7155 | CG67: =BT67*$I67 -> 7155 | ... CK67: =BX67*$I67 -> 7155 | CL67: =SUM(BZ67:CK67) -> 85860 | CM67: 5000 | CN67: 5000 | CO67: 5000 | CP67: 5000 | CQ67: 5000 | CR67: 5000 | CS67: 5000 | CT67: 5000 | CU67: 5000 | CV67: 5000 | CW67: 5000 | CX67: 5000 | CY67: =SUM(CM67:CX67) -> 60000 | CZ67: =CM67*$J67 -> 3577.5 | DA67: =CN67*$J67 -> 3577.5 | DB67: =CO67*$J67 -> 3577.5 | DC67: =CP67*$J67 -> 3577.5 | DD67: =CQ67*$J67 -> 3577.5 | DE67: =CR67*$J67 -> 3577.5 | DF67: =CS67*$J67 -> 3577.5 | DG67: =CT67*$J67 -> 3577.5 | ... DK67: =CX67*$J67 -> 3577.5 | DL67: =SUM(CZ67:DK67) -> 42930 | DM67: 5000 | DN67: 5000 | DO67: 5000 | DP67: 5000 | DQ67: 5000 | DR67: 5000 | DS67: 5000 | DT67: 5000 | DU67: 5000 | DV67: 5000 | DW67: 5000 | DX67: 5000 | DY67: =SUM(DM67:DX67) -> 60000 | DZ67: =DM67*$K67 -> 3577.5 | EA67: =DN67*$K67 -> 3577.5 | EB67: =DO67*$K67 -> 3577.5 | EC67: =DP67*$K67 -> 3577.5 | ED67: =DQ67*$K67 -> 3577.5 | EE67: =DR67*$K67 -> 3577.5 | EF67: =DS67*$K67 -> 3577.5 | EG67: =DT67*$K67 -> 3577.5 | ... EK67: =DX67*$K67 -> 3577.5 | EL67: =SUM(DZ67:EK67) -> 42930
A68: LG Innotek | B68: OMS Entry Lens Holder | C68: 3CAC00203A | D68: 0.55547 | E68: 0.55547 | F68: 0.55547 | G68: 0.55547 | H68: 0.55547 | I68: 0.55547 | J68: 0.55547 | K68: 0.55547 | M68: 13920 | N68: 8000 | O68: 10920 | P68: 12000 | Q68: 10840 | R68: 13920 | S68: 13920 | T68: 12000 | U68: 12000 | V68: 12000 | W68: 12000 | X68: 12000 | Y68: =SUM(M68:X68) -> 143520 | Z68: 7732.1424 | AA68: 4443.76 | AB68: 6065.7324 | AC68: 6660 | AD68: 6021.2948 | AE68: =R68*$E68 -> 7732.1424 | AF68: =S68*$F68 -> 7732.1424 | AG68: =T68*$F68 -> 6665.64 | AH68: =U68*$F68 -> 6665.64 | AI68: =V68*$G68 -> 6665.64 | AJ68: =W68*$G68 -> 6665.64 | AK68: =X68*$G68 -> 6665.64 | AL68: =SUM(Z68:AK68) -> 79715.414 | AM68: 10000 | AN68: 10000 | AO68: 10000 | AP68: 10000 | AQ68: 10000 | AR68: 10000 | AS68: 10000 | AT68: 10000 | AU68: 10000 | AV68: 10000 | AW68: 10000 | AX68: 10000 | AY68: =SUM(AM68:AX68) -> 120000 | AZ68: =AM68*$H68 -> 5554.7 | BA68: =AN68*$H68 -> 5554.7 | BB68: =AO68*$H68 -> 5554.7 | BC68: =AP68*$H68 -> 5554.7 | BD68: =AQ68*$H68 -> 5554.7 | BE68: =AR68*$H68 -> 5554.7 | BF68: =AS68*$H68 -> 5554.7 | BG68: =AT68*$H68 -> 5554.7 | ... BK68: =AX68*$H68 -> 5554.7 | BL68: =SUM(AZ68:BK68) -> 66656.4 | BM68: 10000 | BN68: 10000 | BO68: 10000 | BP68: 10000 | BQ68: 10000 | BR68: 10000 | BS68: 10000 | BT68: 10000 | BU68: 10000 | BV68: 10000 | BW68: 10000 | BX68: 10000 | BY68: =SUM(BM68:BX68) -> 120000 | BZ68: =BM68*$I68 -> 5554.7 | CA68: =BN68*$I68 -> 5554.7 | CB68: =BO68*$I68 -> 5554.7 | CC68: =BP68*$I68 -> 5554.7 | CD68: =BQ68*$I68 -> 5554.7 | CE68: =BR68*$I68 -> 5554.7 | CF68: =BS68*$I68 -> 5554.7 | CG68: =BT68*$I68 -> 5554.7 | ... CK68: =BX68*$I68 -> 5554.7 | CL68: =SUM(BZ68:CK68) -> 66656.4 | CM68: 5000 | CN68: 5000 | CO68: 5000 | CP68: 5000 | CQ68: 5000 | CR68: 5000 | CS68: 5000 | CT68: 5000 | CU68: 5000 | CV68: 5000 | CW68: 5000 | CX68: 5000 | CY68: =SUM(CM68:CX68) -> 60000 | CZ68: =CM68*$J68 -> 2777.35 | DA68: =CN68*$J68 -> 2777.35 | DB68: =CO68*$J68 -> 2777.35 | DC68: =CP68*$J68 -> 2777.35 | DD68: =CQ68*$J68 -> 2777.35 | DE68: =CR68*$J68 -> 2777.35 | DF68: =CS68*$J68 -> 2777.35 | DG68: =CT68*$J68 -> 2777.35 | ... DK68: =CX68*$J68 -> 2777.35 | DL68: =SUM(CZ68:DK68) -> 33328.2 | DM68: 5000 | DN68: 5000 | DO68: 5000 | DP68: 5000 | DQ68: 5000 | DR68: 5000 | DS68: 5000 | DT68: 5000 | DU68: 5000 | DV68: 5000 | DW68: 5000 | DX68: 5000 | DY68: =SUM(DM68:DX68) -> 60000 | DZ68: =DM68*$K68 -> 2777.35 | EA68: =DN68*$K68 -> 2777.35 | EB68: =DO68*$K68 -> 2777.35 | EC68: =DP68*$K68 -> 2777.35 | ED68: =DQ68*$K68 -> 2777.35 | EE68: =DR68*$K68 -> 2777.35 | EF68: =DS68*$K68 -> 2777.35 | EG68: =DT68*$K68 -> 2777.35 | ... EK68: =DX68*$K68 -> 2777.35 | EL68: =SUM(DZ68:EK68) -> 33328.2
A69: LG Innotek | B69: OMS Front Lens Holder | C69: 3CAC00207A | D69: 0.7777 | E69: 0.7777 | F69: 0.7777 | G69: 0.7777 | H69: =G69 -> 0.7777 | I69: =H69 -> 0.7777 | J69: =I69 -> 0.7777 | K69: =J69 -> 0.7777 | S69: 8000 | V69: 12000 | W69: 12000 | X69: 12000 | Y69: =SUM(M69:X69) -> 44000 | Z69: 0 | AA69: 0 | AB69: 0 | AC69: =P69*$E69 -> 0 | AD69: =Q69*$E69 -> 0 | AE69: =R69*$E69 -> 0 | AF69: =S69*$F69 -> 6221.6 | AG69: =T69*$F69 -> 0 | AH69: =U69*$F69 -> 0 | AI69: =V69*$G69 -> 9332.4 | AJ69: =W69*$G69 -> 9332.4 | AK69: =X69*$G69 -> 9332.4 | AL69: =SUM(Z69:AK69) -> 34218.8 | AM69: 10000 | AN69: 10000 | AO69: 10000 | AP69: 10000 | AQ69: 10000 | AR69: 10000 | AS69: 10000 | AT69: 10000 | AU69: 10000 | AV69: 10000 | AW69: 10000 | AX69: 10000 | AY69: =SUM(AM69:AX69) -> 120000 | AZ69: =AM69*$H69 -> 7777 | BA69: =AN69*$H69 -> 7777 | BB69: =AO69*$H69 -> 7777 | BC69: =AP69*$H69 -> 7777 | BD69: =AQ69*$H69 -> 7777 | BE69: =AR69*$H69 -> 7777 | BF69: =AS69*$H69 -> 7777 | BG69: =AT69*$H69 -> 7777 | ... BK69: =AX69*$H69 -> 7777 | BL69: =SUM(AZ69:BK69) -> 93324 | BM69: 10000 | BN69: 10000 | BO69: 10000 | BP69: 10000 | BQ69: 10000 | BR69: 10000 | BS69: 10000 | BT69: 10000 | BU69: 10000 | BV69: 10000 | BW69: 10000 | BX69: 10000 | BY69: =SUM(BM69:BX69) -> 120000 | BZ69: =BM69*$I69 -> 7777 | CA69: =BN69*$I69 -> 7777 | CB69: =BO69*$I69 -> 7777 | CC69: =BP69*$I69 -> 7777 | CD69: =BQ69*$I69 -> 7777 | CE69: =BR69*$I69 -> 7777 | CF69: =BS69*$I69 -> 7777 | CG69: =BT69*$I69 -> 7777 | ... CK69: =BX69*$I69 -> 7777 | CL69: =SUM(BZ69:CK69) -> 93324 | CM69: 5000 | CN69: 5000 | CO69: 5000 | CP69: 5000 | CQ69: 5000 | CR69: 5000 | CS69: 5000 | CT69: 5000 | CU69: 5000 | CV69: 5000 | CW69: 5000 | CX69: 5000 | CY69: =SUM(CM69:CX69) -> 60000 | CZ69: =CM69*$J69 -> 3888.5 | DA69: =CN69*$J69 -> 3888.5 | DB69: =CO69*$J69 -> 3888.5 | DC69: =CP69*$J69 -> 3888.5 | DD69: =CQ69*$J69 -> 3888.5 | DE69: =CR69*$J69 -> 3888.5 | DF69: =CS69*$J69 -> 3888.5 | DG69: =CT69*$J69 -> 3888.5 | ... DK69: =CX69*$J69 -> 3888.5 | DL69: =SUM(CZ69:DK69) -> 46662 | DM69: 5000 | DN69: 5000 | DO69: 5000 | DP69: 5000 | DQ69: 5000 | DR69: 5000 | DS69: 5000 | DT69: 5000 | DU69: 5000 | DV69: 5000 | DW69: 5000 | DX69: 5000 | DY69: =SUM(DM69:DX69) -> 60000 | DZ69: =DM69*$K69 -> 3888.5 | EA69: =DN69*$K69 -> 3888.5 | EB69: =DO69*$K69 -> 3888.5 | EC69: =DP69*$K69 -> 3888.5 | ED69: =DQ69*$K69 -> 3888.5 | EE69: =DR69*$K69 -> 3888.5 | EF69: =DS69*$K69 -> 3888.5 | EG69: =DT69*$K69 -> 3888.5 | ... EK69: =DX69*$K69 -> 3888.5 | EL69: =SUM(DZ69:EK69) -> 46662
A70: LG Innotek | B70: HKMC Ikc Camera Base | C70: 3CAC00180A | D70: 3.3562 | E70: 3.3562 | F70: 3.3562 | G70: 3.3562 | H70: =G70 -> 3.3562 | I70: =H70 -> 3.3562 | J70: =I70 -> 3.3562 | K70: =J70 -> 3.3562 | Y70: =SUM(M70:X70) -> 0 | Z70: 0 | AA70: 0 | AB70: 0 | AC70: =P70*$E70 -> 0 | AD70: =Q70*$E70 -> 0 | AE70: =R70*$E70 -> 0 | AF70: =S70*$F70 -> 0 | AG70: =T70*$F70 -> 0 | AH70: =U70*$F70 -> 0 | AI70: =V70*$G70 -> 0 | AJ70: =W70*$G70 -> 0 | AK70: =X70*$G70 -> 0 | AL70: =SUM(Z70:AK70) -> 0 | AY70: =SUM(AM70:AX70) -> 0 | AZ70: =AM70*$H70 -> 0 | BA70: =AN70*$H70 -> 0 | BB70: =AO70*$H70 -> 0 | BC70: =AP70*$H70 -> 0 | BD70: =AQ70*$H70 -> 0 | BE70: =AR70*$H70 -> 0 | BF70: =AS70*$H70 -> 0 | BG70: =AT70*$H70 -> 0 | ... BK70: =AX70*$H70 -> 0 | BL70: =SUM(AZ70:BK70) -> 0 | BY70: =SUM(BM70:BX70) -> 0 | BZ70: =BM70*$I70 -> 0 | CA70: =BN70*$I70 -> 0 | CB70: =BO70*$I70 -> 0 | CC70: =BP70*$I70 -> 0 | CD70: =BQ70*$I70 -> 0 | CE70: =BR70*$I70 -> 0 | CF70: =BS70*$I70 -> 0 | CG70: =BT70*$I70 -> 0 | ... CK70: =BX70*$I70 -> 0 | CL70: =SUM(BZ70:CK70) -> 0 | CY70: =SUM(CM70:CX70) -> 0 | CZ70: =CM70*$J70 -> 0 | DA70: =CN70*$J70 -> 0 | DB70: =CO70*$J70 -> 0 | DC70: =CP70*$J70 -> 0 | DD70: =CQ70*$J70 -> 0 | DE70: =CR70*$J70 -> 0 | DF70: =CS70*$J70 -> 0 | DG70: =CT70*$J70 -> 0 | ... DK70: =CX70*$J70 -> 0 | DL70: =SUM(CZ70:DK70) -> 0 | DY70: =SUM(DM70:DX70) -> 0 | DZ70: =DM70*$K70 -> 0 | EA70: =DN70*$K70 -> 0 | EB70: =DO70*$K70 -> 0 | EC70: =DP70*$K70 -> 0 | ED70: =DQ70*$K70 -> 0 | EE70: =DR70*$K70 -> 0 | EF70: =DS70*$K70 -> 0 | EG70: =DT70*$K70 -> 0 | ... EK70: =DX70*$K70 -> 0 | EL70: =SUM(DZ70:EK70) -> 0
A71: LG Innotek | B71: MRA2 | C71: 3CAC00196A | D71: 1.57497 | E71: 1.6641 | F71: 1.6641 | G71: 1.6641 | H71: =G71 -> 1.6641 | I71: =H71 -> 1.6641 | J71: =I71 -> 1.6641 | K71: =J71 -> 1.6641 | M71: 3748 | Y71: =SUM(M71:X71) -> 3748 | Z71: 5902.9876 | AA71: 0 | AB71: 0 | AC71: =P71*$E71 -> 0 | AD71: =Q71*$E71 -> 0 | AE71: =R71*$E71 -> 0 | AF71: =S71*$F71 -> 0 | AG71: =T71*$F71 -> 0 | AH71: =U71*$F71 -> 0 | AI71: =V71*$G71 -> 0 | AJ71: =W71*$G71 -> 0 | AK71: =X71*$G71 -> 0 | AL71: =SUM(Z71:AK71) -> 5902.9876 | AY71: =SUM(AM71:AX71) -> 0 | AZ71: =AM71*$H71 -> 0 | BA71: =AN71*$H71 -> 0 | BB71: =AO71*$H71 -> 0 | BC71: =AP71*$H71 -> 0 | BD71: =AQ71*$H71 -> 0 | BE71: =AR71*$H71 -> 0 | BF71: =AS71*$H71 -> 0 | BG71: =AT71*$H71 -> 0 | ... BK71: =AX71*$H71 -> 0 | BL71: =SUM(AZ71:BK71) -> 0 | BY71: =SUM(BM71:BX71) -> 0 | BZ71: =BM71*$I71 -> 0 | CA71: =BN71*$I71 -> 0 | CB71: =BO71*$I71 -> 0 | CC71: =BP71*$I71 -> 0 | CD71: =BQ71*$I71 -> 0 | CE71: =BR71*$I71 -> 0 | CF71: =BS71*$I71 -> 0 | CG71: =BT71*$I71 -> 0 | ... CK71: =BX71*$I71 -> 0 | CL71: =SUM(BZ71:CK71) -> 0 | CY71: =SUM(CM71:CX71) -> 0 | CZ71: =CM71*$J71 -> 0 | DA71: =CN71*$J71 -> 0 | DB71: =CO71*$J71 -> 0 | DC71: =CP71*$J71 -> 0 | DD71: =CQ71*$J71 -> 0 | DE71: =CR71*$J71 -> 0 | DF71: =CS71*$J71 -> 0 | DG71: =CT71*$J71 -> 0 | ... DK71: =CX71*$J71 -> 0 | DL71: =SUM(CZ71:DK71) -> 0 | DY71: =SUM(DM71:DX71) -> 0 | DZ71: =DM71*$K71 -> 0 | EA71: =DN71*$K71 -> 0 | EB71: =DO71*$K71 -> 0 | EC71: =DP71*$K71 -> 0 | ED71: =DQ71*$K71 -> 0 | EE71: =DR71*$K71 -> 0 | EF71: =DS71*$K71 -> 0 | EG71: =DT71*$K71 -> 0 | ... EK71: =DX71*$K71 -> 0 | EL71: =SUM(DZ71:EK71) -> 0
A72: LG Innotek | B72: MPC5.5 Cover Lens | C72: 3HDC00003A | D72: 0.97 | E72: 0.97 | F72: 0.97 | G72: 0.97 | H72: =G72 -> 0.97 | I72: =H72 -> 0.97 | J72: =I72 -> 0.97 | K72: =J72 -> 0.97 | M72: 87400 | N72: 60900 | O72: 146438 | P72: 150000 | Q72: 160000 | R72: 78283 | S72: 130000 | T72: 145000 | U72: 160000 | V72: 160000 | W72: 160000 | X72: 150000 | Y72: =SUM(M72:X72) -> 1588021 | Z72: 84778 | AA72: 59073 | AB72: 142044.86 | AC72: 145500 | AD72: =Q72*$E72 -> 155200 | AE72: =R72*$E72 -> 75934.51 | AF72: =S72*$F72 -> 126100 | AG72: =T72*$F72 -> 140650 | AH72: =U72*$F72 -> 155200 | AI72: =V72*$G72 -> 155200 | AJ72: =W72*$G72 -> 155200 | AK72: =X72*$G72 -> 145500 | AL72: =SUM(Z72:AK72) -> 1540380.4 | AM72: 100000 | AN72: 100000 | AO72: 100000 | AP72: 100000 | AQ72: 100000 | AR72: 100000 | AS72: 100000 | AT72: 100000 | AU72: 100000 | AV72: 100000 | AW72: 100000 | AX72: 100000 | AY72: =SUM(AM72:AX72) -> 1200000 | AZ72: =AM72*$H72 -> 97000 | BA72: =AN72*$H72 -> 97000 | BB72: =AO72*$H72 -> 97000 | BC72: =AP72*$H72 -> 97000 | BD72: =AQ72*$H72 -> 97000 | BE72: =AR72*$H72 -> 97000 | BF72: =AS72*$H72 -> 97000 | BG72: =AT72*$H72 -> 97000 | ... BK72: =AX72*$H72 -> 97000 | BL72: =SUM(AZ72:BK72) -> 1164000 | BM72: 100000 | BN72: 100000 | BO72: 100000 | BP72: 100000 | BQ72: 100000 | BR72: 100000 | BS72: 100000 | BT72: 100000 | BU72: 100000 | BV72: 100000 | BW72: 100000 | BX72: 100000 | BY72: =SUM(BM72:BX72) -> 1200000 | BZ72: =BM72*$I72 -> 97000 | CA72: =BN72*$I72 -> 97000 | CB72: =BO72*$I72 -> 97000 | CC72: =BP72*$I72 -> 97000 | CD72: =BQ72*$I72 -> 97000 | CE72: =BR72*$I72 -> 97000 | CF72: =BS72*$I72 -> 97000 | CG72: =BT72*$I72 -> 97000 | ... CK72: =BX72*$I72 -> 97000 | CL72: =SUM(BZ72:CK72) -> 1164000 | CM72: =1000000/12 -> 83333.333 | CN72: =1000000/12 -> 83333.333 | CO72: =1000000/12 -> 83333.333 | CP72: =1000000/12 -> 83333.333 | CQ72: =1000000/12 -> 83333.333 | CR72: =1000000/12 -> 83333.333 | CS72: =1000000/12 -> 83333.333 | CT72: =1000000/12 -> 83333.333 | ... CX72: =1000000/12 -> 83333.333 | CY72: =SUM(CM72:CX72) -> 1000000 | CZ72: =CM72*$J72 -> 80833.333 | DA72: =CN72*$J72 -> 80833.333 | DB72: =CO72*$J72 -> 80833.333 | DC72: =CP72*$J72 -> 80833.333 | DD72: =CQ72*$J72 -> 80833.333 | DE72: =CR72*$J72 -> 80833.333 | DF72: =CS72*$J72 -> 80833.333 | DG72: =CT72*$J72 -> 80833.333 | ... DK72: =CX72*$J72 -> 80833.333 | DL72: =SUM(CZ72:DK72) -> 970000 | DM72: =1000000/12 -> 83333.333 | DN72: =1000000/12 -> 83333.333 | DO72: =1000000/12 -> 83333.333 | DP72: =1000000/12 -> 83333.333 | DQ72: =1000000/12 -> 83333.333 | DR72: =1000000/12 -> 83333.333 | DS72: =1000000/12 -> 83333.333 | DT72: =1000000/12 -> 83333.333 | ... DX72: =1000000/12 -> 83333.333 | DY72: =SUM(DM72:DX72) -> 1000000 | DZ72: =DM72*$K72 -> 80833.333 | EA72: =DN72*$K72 -> 80833.333 | EB72: =DO72*$K72 -> 80833.333 | EC72: =DP72*$K72 -> 80833.333 | ED72: =DQ72*$K72 -> 80833.333 | EE72: =DR72*$K72 -> 80833.333 | EF72: =DS72*$K72 -> 80833.333 | EG72: =DT72*$K72 -> 80833.333 | ... EK72: =DX72*$K72 -> 80833.333 | EL72: =SUM(DZ72:EK72) -> 970000
