Workbook

Sheet Summary.
A1: Status 2025 | B1: SLMV
C3: Values
A4: Kind | B4: Note | C4: Qty Blance | D4: Amount Balance ( VND)
A5: FG | B5: Keep provision | C5: 172145 | D5: 2.7610329e+09
B6: No provision | C6: 12913 | D6: 8.1430181e+08
B7: Reverse provison | C7: 127669 | D7: 2.0073344e+09
A8: FG Total | C8: 312727 | D8: 5.5826691e+09
A9: RM | B9: Keep provision | C9: 2983098 | D9: 3309687928
B10: Make provision 2025 | C10: 80760 | D10: 2686138185
B11: No provision | C11: 1100223 | D11: 1.7597279e+09
B12: Reverse provison | C12: 399001 | D12: 1454433383
A13: RM Total | C13: 4563082 | D13: 9.2099874e+09
A14: Trading | B14: No provision | C14: 6 | D14: 1.10835e+09
A15: Trading Total | C15: 6 | D15: 1.10835e+09
A16: WIP | B16: Keep provision | C16: 1121441.1 | D16: 6.9010404e+09
B17: Reverse provison | C17: 13108 | D17: 4.9041556e+08
A18: WIP Total | C18: 1134549.1 | D18: 7.391456e+09
A19: Grand Total | C19: 6010364.2 | D19: 2.3292462e+10

Sheet MC propose
C1: Openning 2025 | E1: Movement 2025 | H1: Ending 2025
A3: Sum of 12.end amnt=2+8-10 | B3: Column Labels
A4: Row Labels | B4: Provision 2020 | C4: (blank) | D4: Grand Total
A5: FG | B5: 1.2153954e+08 | D5: 1.2153954e+08
A6: RM | B6: 5.8074429e+09 | C6: 1.38677e+09 | D6: 7.1942129e+09
A7: Suplies | B7: 73161632 | D7: 73161632
A8: WIP | B8: 4.5364014e+08 | D8: 4.5364014e+08
A9: Grand Total | B9: 6.4557842e+09 | C9: 1.38677e+09 | D9: 7.8425542e+09
B10: Total | C10: -8866172212
B11: NRV | C11: 2410388030
A12: No | B12: Type | C12: VND | D12: USD | E12: Clear at 31.Dec.2025 | F12: Reverse Provision 2024 | G12: Add at 31.Dec.2025 | H12: VND | I12: USD
A13: I | B13: Provison Stock | C13: =SUM(C14:C17) -> 1.7286985e+10 | D13: =+C13/25000 -> 691479.4 | E13: =SUM(E14:E18) -> 82219484 | F13: =SUM(F14:F18) -> 4.0048158e+09 | G13: =SUM(G14:G17) -> 0 | H13: =SUM(H14:H17) -> 1.324011e+10 | I13: =SUM(I14:I17) -> 551671.24
A14: 1 | B14: FG | C14: 4.7709049e+09 | D14: =+C14/26000 -> 183496.34 | F14: =SUMIFS('SLMV end2025'!K:K,'SLMV end2025'!M:M,"Reverse provison",'SLMV end2025'!A:A,B14) -> 2.0073344e+09 | G14: =SUMIFS('SLMV end2025'!F:F,'SLMV end2025'!M:M,"Make provision 2025",'SLMV end2025'!A:A,B14) -> 0 | H14: =+C14-E14-F14+G14 -> 2.7635705e+09 | I14: =H14/24000 -> 115148.77
A15: 2 | B15: RM | C15: 4.8851483e+09 | D15: =+C15/26000 -> 187890.32 | E15: 15809484 | F15: =SUMIFS('SLMV end2025'!K:K,'SLMV end2025'!M:M,"Reverse provison",'SLMV end2025'!A:A,B15) -> 1.5070659e+09 | G15: =SUMIFS('SLMV end2025'!F:F,'SLMV end2025'!M:M,"Make provision 2025",'SLMV end2025'!A:A,B15) -> 0 | H15: =+C15-E15-F15+G15 -> 3.3622729e+09 | I15: =H15/24000 -> 140094.7
A16: 3 | B16: Supply | C16: 26250000 | D16: =+C16/26000 -> 1009.6154 | E16: 26250000 | F16: =SUMIFS('SLMV end2025'!K:K,'SLMV end2025'!M:M,"Reverse provison",'SLMV end2025'!A:A,B16) -> 0 | G16: =SUMIFS('SLMV end2025'!F:F,'SLMV end2025'!M:M,"Make provision 2025",'SLMV end2025'!A:A,B16) -> 0 | H16: =+C16-E16-F16+G16 -> 0 | I16: =H16/24000 -> 0
A17: 4 | B17: WIP | C17: 7.6046819e+09 | D17: =+C17/26000 -> 292487.76 | F17: =SUMIFS('SLMV end2025'!K:K,'SLMV end2025'!M:M,"Reverse provison",'SLMV end2025'!A:A,B17) -> 4.9041556e+08 | G17: =SUMIFS('SLMV end2025'!F:F,'SLMV end2025'!M:M,"Make provision 2025",'SLMV end2025'!A:A,B17) -> 0 | H17: =+C17-E17-F17+G17 -> 7.1142663e+09 | I17: =H17/24000 -> 296427.76
A18: 5 | B18: Trading | C18: 40160000 | D18: =+C18/26000 -> 1544.6154 | E18: 40160000 | F18: =SUMIFS('SLMV end2025'!K:K,'SLMV end2025'!M:M,"Reverse provison",'SLMV end2025'!A:A,B18) -> 0 | G18: =SUMIFS('SLMV end2025'!F:F,'SLMV end2025'!M:M,"Make provision 2025",'SLMV end2025'!A:A,B18) -> 0 | H18: =+C18-E18-F18+G18 -> 0
A19: II | B19: NRV | G19: ='SLMV end2025'!S3*0 -> 0 | H19: =+C19-E19+G19 -> 0 | I19: =H19/25000 -> 0
A20: (I) +(II) | B20: Total VND | C20: =+C13+C19 -> 1.7286985e+10 | D20: =+C20/25000 -> 691479.4 | E20: =+E13+E19 -> 82219484 | F20: =+F13+F19 -> 4.0048158e+09 | G20: =+G13+G19 -> 0 | H20: =+H13+H19 -> 1.324011e+10 | I20: =+I13+I19 -> 551671.24
F21: =+F20/26000 -> 154031.38

Sheet SLMV end2025
F1: Exr | G1: 26000 | I1: PROVISION 2024
C2: INVENTORY BALANCE END-2025 | E2: ENDING 2025 | J2: =SUBTOTAL(9,J5:J3685) -> 4861326.7 | K2: =SUBTOTAL(9,K5:K3685) -> 1.6983711e+10 | O2: NRV
A3: Kind | B3: item code | C3: Name | D3: Classify | E3: Qty Blance | F3: Amount Balance ( VND) | G3: Amount Balance ( USD) | H3: Unit price | I3: Technical Justification | J3: Qty provision | K3: Amt provision | L3: Status 2025 | M3: Note | N3: AUDITED | O3: Unit Selling 2025 | P3: 0.069360811 | Q3: Diff unit amt (Sale vs cost) | R3: =SUBTOTAL(9,R4:R3689) -> -3.1135471e+08 | S3: =SUM(S4:S3685) -> 3.1135471e+08
L4: xx
A5: RM | B5: 760011 | C5: Nhôm hợp kim dạng thanh S36 | D5: Alumium | E5: 19237.399 | F5: 5.4981198e+08 | G5: =+F5/$G$1 -> 21146.615 | H5: =IFERROR(F5/E5,0) -> 28580.37 | J5: 0 | K5: 0 | L5: OK | N5: N | T5: 25415 | U5: =+E5-T5 -> -6177.6009
A6: RM | B6: 760309 | C6: Aluminum Ingots ADC3 , Hợp kim nhôm ADC3 | D6: Alumium | E6: 2657.3005 | F6: 2.0903568e+08 | G6: =+F6/$G$1 -> 8039.834 | H6: =IFERROR(F6/E6,0) -> 78664.677 | I6: 0 | J6: 0 | K6: 0 | L6: OK | N6: N | T6: 2144.1705 | U6: =+E6-T6 -> 513.13
A7: RM | B7: 762249 | C7: Aluminum S3Y/Nhôm hợp kim dạng thanh S3Y | D7: Alumium | E7: 16146.277 | F7: 5.2496466e+08 | G7: =+F7/$G$1 -> 20190.949 | H7: =IFERROR(F7/E7,0) -> 32513.046 | J7: 0 | K7: 0 | L7: OK | N7: N | T7: 28122.491 | U7: =+E7-T7 -> -11976.213
A8: RM | B8: 762750 | C8: Aluminum A380/Nhôm A380 | D8: Alumium | E8: 272 | F8: 8031878.2 | G8: =+F8/$G$1 -> 308.91839 | H8: =IFERROR(F8/E8,0) -> 29528.964 | J8: 0 | K8: 0 | L8: SLMV | N8: Y | T8: 272 | U8: =+E8-T8 -> 0
A9: RM | B9: 762800 | C9: A413 Aluminium alloy for Handle Bar product-Nguyên liệu A413 sản xuất Handle bar | D9: Alumium | E9: 9910 | F9: 352468421 | G9: =+F9/$G$1 -> 13556.478 | H9: =IFERROR(F9/E9,0) -> 35566.945 | I9: Raw Material relating to Aluminium, which is the core material of the company. No movement is due to company has been actively using another size. Item able to recycle and re-produce to new size. | J9: 0 | K9: 0 | L9: SLMV | N9: Y | T9: 0 | U9: =+E9-T9 -> 9910
A10: RM | B10: 762802 | C10: Aluminium ALDCS 12 Fe 0.9%-Nhôm thỏi ALDC12 thành phần Fe 0.9% | D10: Alumium | E10: 32883.937 | F10: 1.0227306e+09 | G10: =+F10/$G$1 -> 39335.791 | H10: =IFERROR(F10/E10,0) -> 31101.22 | J10: 0 | K10: 0 | L10: OK | N10: N | T10: 40543.033 | U10: =+E10-T10 -> -7659.0961
A11: RM | B11: 763915 | C11: Aluminium plate for bracket(0102-002945)-B6/ Phôi nhôm (0102-002945)-B6 | D11: AL-SEVT | E11: 4292 | F11: 0 | G11: =+F11/$G$1 -> 0 | H11: =IFERROR(F11/E11,0) -> 0 | I11: 0 | J11: 0 | K11: 0 | L11: OK | N11: N | T11: 0 | U11: =+E11-T11 -> 4292
A12: RM | B12: 762897 | C12: Bracket Q4/Vỏ (khung đỡ) điện thoại di động bằng kim loại/Q4 | D12: AL-SEVT | E12: 97 | F12: 0 | G12: =+F12/$G$1 -> 0 | H12: =IFERROR(F12/E12,0) -> 0 | I12: 0 | J12: 0 | K12: 0 | L12: OK | N12: N | T12: 0 | U12: =+E12-T12 -> 97
A13: RM | B13: 740202 | C13: Hexagonal bolt/chìm lục giác kt M8*60 | D13: Mold Jig Material | E13: 110 | F13: 256410 | G13: =+F13/$G$1 -> 9.8619231 | H13: =IFERROR(F13/E13,0) -> 2331 | J13: 0 | K13: 0 | L13: OK | N13: N | T13: 100 | U13: =+E13-T13 -> 10
A14: RM | B14: 740215 | C14: Hexagonal bolt/ Chìm lục giác M10*60(1) | D14: Mold Jig Material | E14: 30 | F14: 107520 | G14: =+F14/$G$1 -> 4.1353846 | H14: =IFERROR(F14/E14,0) -> 3584 | J14: 0 | K14: 0 | L14: OK | N14: N | T14: 6 | U14: =+E14-T14 -> 24
A15: RM | B15: 741351 | C15: Master box label/Giấy in tem cuộn. Size: 30*13mm (2 tem) | D15: Etc | E15: 15 | F15: 1687500 | G15: =+F15/$G$1 -> 64.903846 | H15: =IFERROR(F15/E15,0) -> 112500 | I15: Currenly no customer using these RM. Hence, full provision to be made | J15: 15 | K15: 1687500 | L15: SLMV | M15: Reverse provison | N15: Y | T15: 15 | U15: =+E15-T15 -> 0
A16: RM | B16: 741352 | C16: Master box label/ Giấy in tem cuộn. Size: 100*150mm | D16: Etc | E16: 5 | F16: 900000 | G16: =+F16/$G$1 -> 34.615385 | H16: =IFERROR(F16/E16,0) -> 180000 | J16: 0 | K16: 0 | L16: OK | N16: N | T16: 5 | U16: =+E16-T16 -> 0
A17: RM | B17: 741689 | C17: Inner label/ Giấy in tem cuộn. Size: 13*32mm (khổ cuộn 75mm) | D17: Etc | E17: 5 | F17: 1100000 | G17: =+F17/$G$1 -> 42.307692 | H17: =IFERROR(F17/E17,0) -> 220000 | I17: These raw materials are in good condition and can be used for other customer, no expiry date on these raw materials. Hence, no provison | J17: 0 | K17: 0 | L17: OK | N17: N | T17: 5 | U17: =+E17-T17 -> 0
A18: RM | B18: 742008 | C18: Master box label/Giấy in tem cuộn. Size: 30*13mm (3 tem) | D18: Cosmetic | E18: 7 | F18: 787500 | G18: =+F18/$G$1 -> 30.288462 | H18: =IFERROR(F18/E18,0) -> 112500 | I18: BU Discontinued - [1] | J18: 7 | K18: 787500 | L18: SLMV | M18: Keep provision | N18: Y | T18: 7 | U18: =+E18-T18 -> 0
A19: RM | B19: 742255 | C19: PE bag/ Túi chống tĩnh điện màu xanh dương 21cm*25cm*0.04mm (dùng cho model hàng GEN2/1v5 pre/Al5) | D19: Etc | E19: 275.02306 | F19: 12405820 | G19: =+F19/$G$1 -> 477.14694 | H19: =IFERROR(F19/E19,0) -> 45108.292 | J19: 0 | K19: 0 | L19: OK | N19: N | T19: 219.02306 | U19: =+E19-T19 -> 56
A20: RM | B20: 742313 | C20: Vacuum poly bag 350*490*0.1/Túi chân không | D20: Etc | E20: 1350.0237 | F20: 3915068.7 | G20: =+F20/$G$1 -> 150.57956 | H20: =IFERROR(F20/E20,0) -> 2900 | J20: 0 | K20: 0 | L20: OK | N20: N | T20: 800.02367 | U20: =+E20-T20 -> 550
A21: RM | B21: 742342 | C21: Zipper bag/Túi zipper KT: 180*250*0.05mm | D21: Etc | E21: 500 | F21: 300000 | G21: =+F21/$G$1 -> 11.538462 | H21: =IFERROR(F21/E21,0) -> 600 | I21: Currenly no customer using these RM. Hence, full provision to be made | J21: 2100 | K21: 1260000 | L21: OK | M21: Reverse provison | N21: N | T21: 500 | U21: =+E21-T21 -> 0
A22: RM | B22: 742343 | C22: Tem QR/Sticker for QR printing, kt: 10*10mm | D22: Etc | E22: 1372800 | F22: 27456000 | G22: =+F22/$G$1 -> 1056 | H22: =IFERROR(F22/E22,0) -> 20 | J22: 0 | K22: 0 | L22: OK | N22: N | T22: 370000 | U22: =+E22-T22 -> 1002800
A23: RM | B23: 742369 | C23: PE bag/ Túi chống tĩnh điện màu trắng 680mm*600mm*0.04mm | D23: Etc | E23: 60.243324 | F23: 2289246.3 | G23: =+F23/$G$1 -> 88.047936 | H23: =IFERROR(F23/E23,0) -> 38000 | J23: 0 | K23: 0 | L23: OK | N23: N | T23: 28.243324 | U23: =+E23-T23 -> 32
A24: RM | B24: 742370 | C24: PE bag/Túi chống tĩnh điện màu xanh lá 21cm*25cm*0.04mm(570W/AL6) | D24: Etc | E24: 35.038255 | F24: 1582433.8 | G24: =+F24/$G$1 -> 60.86284 | H24: =IFERROR(F24/E24,0) -> 45163.032 | J24: 0 | K24: 0 | L24: OK | N24: N | T24: 75.038255 | U24: =+E24-T24 -> -40
A25: RM | B25: 742371 | C25: PE bag/Túi chống tĩnh điện màu vàng 21cm*25cm*0.04mm( 1v5 base/BYD housing/Nu) | D25: Etc | E25: 74.532165 | F25: 3359138 | G25: =+F25/$G$1 -> 129.19761 | H25: =IFERROR(F25/E25,0) -> 45069.642 | J25: 0 | K25: 0 | L25: OK | N25: N | T25: 92.532165 | U25: =+E25-T25 -> -18
A26: RM | B26: 742399 | C26: PE bag/ Túi chống tĩnh điện màu xanh dương 210mm*350mm*0.04mm (dùng cho model hàng 1V5 Housing 1826) | D26: Etc | E26: 149.91644 | F26: 6757585.2 | G26: =+F26/$G$1 -> 259.90712 | H26: =IFERROR(F26/E26,0) -> 45075.679 | J26: 0 | K26: 0 | L26: OK | N26: N | T26: 177.91644 | U26: =+E26-T26 -> -28
A27: RM | B27: 752055 | C27: Hair/ tóc thật | D27: Cosmetic | E27: 10 | F27: 26661450 | G27: =+F27/$G$1 -> 1025.4404 | H27: =IFERROR(F27/E27,0) -> 2666145 | I27: BU Discontinued - [1] | J27: 10 | K27: 26661450 | L27: SLMV | M27: Keep provision | N27: Y | T27: 10 | U27: =+E27-T27 -> 0
A28: RM | B28: 754012 | C28: Miếng dán móng tay 412-24 (từ 0-3) | D28: Cosmetic | E28: 400 | F28: 173600 | G28: =+F28/$G$1 -> 6.6769231 | H28: =IFERROR(F28/E28,0) -> 434 | I28: BU Discontinued - [1] | J28: 400 | K28: 173600 | L28: SLMV | M28: Keep provision | N28: Y | T28: 400 | U28: =+E28-T28 -> 0
A29: RM | B29: 754576 | C29: Silical gel 50 gr/hạt hút ẩm | D29: Etc | E29: 150.15499 | F29: 6886708.5 | G29: =+F29/$G$1 -> 264.8734 | H29: =IFERROR(F29/E29,0) -> 45864 | J29: 0 | K29: 0 | L29: OK | N29: N | T29: 535.15499 | U29: =+E29-T29 -> -385
A30: RM | B30: 754654 | C30: Mold Pin-EJECTOR PIN _x000D_/Chốt hãm bằng thép SKD61 của khuôn đúc d2*L100*H4*D4/ 밀핀" EPN2-100 | D30: Mold Jig Material | E30: 99 | F30: 2772000 | G30: =+F30/$G$1 -> 106.61538 | H30: =IFERROR(F30/E30,0) -> 28000 | J30: 0 | K30: 0 | L30: OK | N30: N | T30: 87 | U30: =+E30-T30 -> 12
A31: RM | B31: 760018 | C31: Carton box. 5 Plate: 1 surface Yellow, 1 surface raw. Thùng carton 5 lớp,mặt ngoài vàng, mặt trong thô MC-YLR01 | D31: Etc | E31: 345.90514 | F31: 5090015.5 | G31: =+F31/$G$1 -> 195.76983 | H31: =IFERROR(F31/E31,0) -> 14715.062 | J31: 0 | K31: 0 | L31: OK | N31: N | T31: 251.72836 | U31: =+E31-T31 -> 94.176775
A32: RM | B32: 760119 | C32: Clear Sticker-Stick paper box, dim: 16mm_x000D_ /Miếng dán ở giữa vị trí trên cùng và dưới cùng hộp đựng lông mi giả | D32: Cosmetic | E32: 45000 | F32: 3573812 | G32: =+F32/$G$1 -> 137.45431 | H32: =IFERROR(F32/E32,0) -> 79.418044 | I32: BU Discontinued - [1] | J32: 45000 | K32: 3573812 | L32: SLMV | M32: Keep provision | N32: Y | T32: 45000 | U32: =+E32-T32 -> 0
A33: RM | B33: 760120 | C33: Inner box. Size: 97*77*83mm . Color : white/Hộp Inner box đựng ngoài hộp lông mi giả, màu trắng | D33: Cosmetic | E33: 4700 | F33: 10180752 | G33: =+F33/$G$1 -> 391.56738 | H33: =IFERROR(F33/E33,0) -> 2166.1174 | I33: BU Discontinued - [1] | J33: 4700 | K33: 10180752 | L33: SLMV | M33: Keep provision | N33: Y | T33: 4700 | U33: =+E33-T33 -> 0
A34: RM | B34: 760233 | C34: PET13 Tray. Color: White 0.4T. Model MC-PET13-1Pair_x000D_ /Khay đựng lông mi giả - PET13-1 đôi . Size 95*55*15 | D34: Cosmetic | E34: 2594 | F34: 941172 | G34: =+F34/$G$1 -> 36.198923 | H34: =IFERROR(F34/E34,0) -> 362.82652 | I34: BU Discontinued - [1] | J34: 2594 | K34: 941172 | L34: SLMV | M34: Keep provision | N34: Y | T34: 2594 | U34: =+E34-T34 -> 0
A35: RM | B35: 760235 | C35: PET15 Tray. Color: White. Model MC-PET15-4pairs_x000D_ /Khay đựng lông mi giả - PET15-4 đôi. Size: 95*96*15 | D35: Cosmetic | E35: 16 | F35: 11200 | G35: =+F35/$G$1 -> 0.43076923 | H35: =IFERROR(F35/E35,0) -> 700 | I35: BU Discontinued - [1] | J35: 16 | K35: 11200 | L35: SLMV | M35: Keep provision | N35: Y | T35: 16 | U35: =+E35-T35 -> 0
A36: RM | B36: 760246 | C36: EYELENE box. Color: Pink. 1 pair /Hộp EYELENE, 30-88133-E01, 1 đôi | D36: Cosmetic | E36: 904 | F36: 1075285 | G36: =+F36/$G$1 -> 41.357115 | H36: =IFERROR(F36/E36,0) -> 1189.4746 | I36: BU Discontinued - [1] | J36: 904 | K36: 1075285 | L36: SLMV | M36: Keep provision | N36: Y | T36: 904 | U36: =+E36-T36 -> 0
A37: RM | B37: 760300 | C37: Tray PP 0.4T Black_x000D_ /(Khay 932-63) Khay nhựa PP-04 Đen , 10 ô | D37: Etc | E37: 200 | F37: 360000 | G37: =+F37/$G$1 -> 13.846154 | H37: =IFERROR(F37/E37,0) -> 1800 | I37: Currenly no customer using these RM. Hence, full provision to be made | J37: 200 | K37: 360000 | L37: SLMV | M37: Reverse provison | N37: Y | T37: 200 | U37: =+E37-T37 -> 0
A38: RM | B38: 760318 | C38: Bar code 01-91295-002. Size: 20*34mm_x000D_ /Tem mã vạch 079181912952. Loại mã Code UPCA-12 | D38: Etc | E38: 900 | F38: 150442 | G38: =+F38/$G$1 -> 5.7862308 | H38: =IFERROR(F38/E38,0) -> 167.15778 | I38: Currenly no customer using these RM. Hence, full provision to be made | J38: 900 | K38: 150442 | L38: SLMV | M38: Reverse provison | N38: Y | T38: 900 | U38: =+E38-T38 -> 0
A39: RM | B39: 760319 | C39: Bar code 01-91297-002. Size: 20*34mm_x000D_ /Tem mã vạch 079181912976. Loại mã Code UPCA-12 | D39: Etc | E39: 1500 | F39: 55500 | G39: =+F39/$G$1 -> 2.1346154 | H39: =IFERROR(F39/E39,0) -> 37 | I39: Currenly no customer using these RM. Hence, full provision to be made | J39: 1500 | K39: 55500 | L39: SLMV | M39: Reverse provison | N39: Y | T39: 1500 | U39: =+E39-T39 -> 0
A40: RM | B40: 760367 | C40: Item label, Black ink_x000D_ / Tem số 88132 mực đen . Size : 17*8mm | D40: Cosmetic | E40: 9702 | F40: 1293276 | G40: =+F40/$G$1 -> 49.741385 | H40: =IFERROR(F40/E40,0) -> 133.29994 | I40: BU Discontinued - [1] | J40: 9702 | K40: 1293276 | L40: SLMV | M40: Keep provision | N40: Y | T40: 9702 | U40: =+E40-T40 -> 0
A41: RM | B41: 760369 | C41: Item label, Black ink_x000D_ / Tem số 88133 mực đen . Size : 17*8mm | D41: Cosmetic | E41: 10168 | F41: 1016800 | G41: =+F41/$G$1 -> 39.107692 | H41: =IFERROR(F41/E41,0) -> 100 | I41: BU Discontinued - [1] | J41: 10168 | K41: 1016800 | L41: SLMV | M41: Keep provision | N41: Y | T41: 10168 | U41: =+E41-T41 -> 0
A42: RM | B42: 760376 | C42: Bar code 01-88150-U02. Size: 18*32mm_x000D_ / Tem mã vạch 079181881500 Loại mã Code UPCA-12 | D42: Etc | E42: 2200 | F42: 81400 | G42: =+F42/$G$1 -> 3.1307692 | H42: =IFERROR(F42/E42,0) -> 37 | I42: Currenly no customer using these RM. Hence, full provision to be made | J42: 2200 | K42: 81400 | L42: SLMV | M42: Reverse provison | N42: Y | T42: 2200 | U42: =+E42-T42 -> 0
A43: RM | B43: 760464 | C43: Eyelash box. Color: Pink/ Hộp hồng 1 pair 30-88130-FE4 | D43: Cosmetic | E43: 1101 | F43: 2300297 | G43: =+F43/$G$1 -> 88.472962 | H43: =IFERROR(F43/E43,0) -> 2089.2797 | I43: BU Discontinued - [1] | J43: 1101 | K43: 2300297 | L43: SLMV | M43: Keep provision | N43: Y | T43: 1101 | U43: =+E43-T43 -> 0
... A46: RM | B46: 760469 | C46: Item label for Revlon box, Black ink /Tem số 88136 mực đen . Size : 17*8mm | D46: Cosmetic | E46: 7506 | F46: 735817 | G46: =+F46/$G$1 -> 28.300654 | H46: =IFERROR(F46/E46,0) -> 98.030509 | I46: BU Discontinued - [1] | J46: 7506 | K46: 735817 | L46: SLMV | M46: Keep provision | N46: Y | T46: 7506 | U46: =+E46-T46 -> 0
A47: RM | B47: 760482 | C47: Tray Bottom cover 2P+Clamp Support, 9 holes/ Khay nhựa PET trong suốt, 9 hố MC-PS02. | D47: Etc | E47: 171.03954 | F47: 487222.63 | G47: =+F47/$G$1 -> 18.739332 | H47: =IFERROR(F47/E47,0) -> 2848.5964 | J47: 0 | K47: 0 | L47: OK | N47: N | T47: 163.04104 | U47: =+E47-T47 -> 7.9985
A48: RM | B48: 760488 | C48: UP_P45_FEEDER 61A-01434 for WHB Dipole | D48: Etc | E48: 171270 | F48: 679406726 | G48: =+F48/$G$1 -> 26131.028 | H48: =IFERROR(F48/E48,0) -> 3966.8753 | I48: Currenly no customer using these RM. Hence, full provision to be made | J48: 171270 | K48: 679406726 | L48: SLMV | M48: Reverse provison | N48: Y | T48: 171270 | U48: =+E48-T48 -> 0
A49: RM | B49: 760489 | C49: DOWN_M45_FEEDER 61A-01435 for WHB Dipole | D49: Etc | E49: 119648 | F49: 487688779 | G49: =+F49/$G$1 -> 18757.261 | H49: =IFERROR(F49/E49,0) -> 4076.0295 | I49: Currenly no customer using these RM. Hence, full provision to be made | J49: 119648 | K49: 487688779 | L49: SLMV | M49: Reverse provison | N49: Y | T49: 119648 | U49: =+E49-T49 -> 0
A50: RM | B50: 760505 | C50: Devide Pad: 3 plates, 2 Yellow surface. Model: MC-YL10 | D50: Etc | E50: 330 | F50: 190901 | G50: =+F50/$G$1 -> 7.3423462 | H50: =IFERROR(F50/E50,0) -> 578.48788 | I50: Item unable to re-use as damage during a flood in Year 2024 | J50: 330 | K50: 190901 | L50: SLMV | M50: Reverse provison | N50: Y | T50: 330 | U50: =+E50-T50 -> 0
A51: RM | B51: 760506 | C51: THINNER T-900 | D51: Chemical | E51: 45 | F51: 5433030 | G51: =+F51/$G$1 -> 208.96269 | H51: =IFERROR(F51/E51,0) -> 120734 | I51: Currenly no customer using these RM. Hence, full provision to be made | J51: 45 | K51: 5433030 | L51: SLMV | M51: Reverse provison | N51: Y | T51: 45 | U51: =+E51-T51 -> 0
A52: RM | B52: 760508 | C52: UV SF-001 | D52: Cosmetic | E52: 45 | F52: 13385970 | G52: =+F52/$G$1 -> 514.845 | H52: =IFERROR(F52/E52,0) -> 297466 | I52: BU Discontinued - [1] | J52: 45 | K52: 13385970 | L52: SLMV | M52: Keep provision | N52: Y | T52: 45 | U52: =+E52-T52 -> 0
A53: RM | B53: 760509 | C53: UV 747 | D53: Cosmetic | E53: 45 | F53: 11458170 | G53: =+F53/$G$1 -> 440.69885 | H53: =IFERROR(F53/E53,0) -> 254626 | I53: BU Discontinued - [1] | J53: 45 | K53: 11458170 | L53: SLMV | M53: Keep provision | N53: Y | T53: 45 | U53: =+E53-T53 -> 0
A54: RM | B54: 760511 | C54: PET13-1 Tray. Color: White 0.4T. Model MC-PET13-1 Pair_x000D_ /Khay đựng lông mi giả - PET13 -1 (1 đôi). Size 95*55*15 | D54: Cosmetic | E54: 500 | F54: 170000 | G54: =+F54/$G$1 -> 6.5384615 | H54: =IFERROR(F54/E54,0) -> 340 | I54: BU Discontinued - [1] | J54: 500 | K54: 170000 | L54: SLMV | M54: Keep provision | N54: Y | T54: 500 | U54: =+E54-T54 -> 0
A55: RM | B55: 760518 | C55: Tray nail FP 1296 | D55: Cosmetic | E55: 15629 | F55: 18442220 | G55: =+F55/$G$1 -> 709.31615 | H55: =IFERROR(F55/E55,0) -> 1180 | I55: BU Discontinued - [1] | J55: 15629 | K55: 18442220 | L55: SLMV | M55: Keep provision | N55: Y | T55: 15629 | U55: =+E55-T55 -> 0
A56: RM | B56: 760521 | C56: Tray nail FP2280 | D56: Cosmetic | E56: 57105 | F56: 94223250 | G56: =+F56/$G$1 -> 3623.9712 | H56: =IFERROR(F56/E56,0) -> 1650 | I56: BU Discontinued - [1] | J56: 57105 | K56: 94223250 | L56: SLMV | M56: Keep provision | N56: Y | T56: 57105 | U56: =+E56-T56 -> 0
A57: RM | B57: 760522 | C57: Tray nail FP 301-P | D57: Cosmetic | E57: 500 | F57: 600000 | G57: =+F57/$G$1 -> 23.076923 | H57: =IFERROR(F57/E57,0) -> 1200 | I57: BU Discontinued - [1] | J57: 500 | K57: 600000 | L57: SLMV | M57: Keep provision | N57: Y | T57: 500 | U57: =+E57-T57 -> 0
A58: RM | B58: 760523 | C58: Tray nail FP 411-p | D58: Cosmetic | E58: 3000 | F58: 3600000 | G58: =+F58/$G$1 -> 138.46154 | H58: =IFERROR(F58/E58,0) -> 1200 | I58: BU Discontinued - [1] | J58: 3000 | K58: 3600000 | L58: SLMV | M58: Keep provision | N58: Y | T58: 3000 | U58: =+E58-T58 -> 0
A59: RM | B59: 760525 | C59: Tray nail FP UTETSO-P | D59: Cosmetic | E59: 600 | F59: 1116000 | G59: =+F59/$G$1 -> 42.923077 | H59: =IFERROR(F59/E59,0) -> 1860 | I59: BU Discontinued - [1] | J59: 600 | K59: 1116000 | L59: SLMV | M59: Keep provision | N59: Y | T59: 600 | U59: =+E59-T59 -> 0
... A86: RM | B86: 760622 | C86: Paper display for Nail AII/Hộp giấy trưng bày sản phẩm display | D86: Cosmetic | E86: 150 | F86: 602100 | G86: =+F86/$G$1 -> 23.157692 | H86: =IFERROR(F86/E86,0) -> 4014 | I86: BU Discontinued - [1] | J86: 150 | K86: 602100 | L86: SLMV | M86: Keep provision | N86: Y | T86: 150 | U86: =+E86-T86 -> 0
A87: RM | B87: 760625 | C87: Tray for bracket PET 08 (for Note 8)_x000D_/Khay nhựa bracket 410*350*20 mm (cho Note 8) | D87: Etc | E87: 3500 | F87: 10482500 | G87: =+F87/$G$1 -> 403.17308 | H87: =IFERROR(F87/E87,0) -> 2995 | J87: 0 | K87: 0 | L87: OK | N87: N | T87: 0 | U87: =+E87-T87 -> 3500
A88: RM | B88: 760634 | C88: Tray PET 23 clear , Khay PET 23, màu trong, size 415*360*27.5 mm (0.5T) Tray PET 23 | D88: Etc | E88: 494 | F88: 702952.29 | G88: =+F88/$G$1 -> 27.036627 | H88: =IFERROR(F88/E88,0) -> 1422.9804 | J88: 0 | K88: 0 | L88: OK | N88: N | T88: 385.0013 | U88: =+E88-T88 -> 108.9987
A89: RM | B89: 760636 | C89: Tray NRK 20ea , color: black/Khay nhựa (NRK20ea) màu đen | D89: Etc | E89: 150 | F89: 360000 | G89: =+F89/$G$1 -> 13.846154 | H89: =IFERROR(F89/E89,0) -> 2400 | I89: Currenly no customer using these RM. Hence, full provision to be made | J89: 150 | K89: 360000 | L89: SLMV | M89: Reverse provison | N89: Y | T89: 150 | U89: =+E89-T89 -> 0
A90: RM | B90: 760645 | C90: PCB nail led lamp/bản mạch điện tử đèn led móng tay | D90: Cosmetic | E90: 40610 | F90: 2682886035 | G90: =+F90/$G$1 -> 103187.92 | H90: =IFERROR(F90/E90,0) -> 66064.665 | I90: These raw materials are in good condition and can be used for other customer, no expiry date on these raw materials. Hence, no provison | J90: 0 | K90: 0 | L90: SLMV | M90: No provision | N90: Y | O90: =+F90/26000 -> 103187.92 | T90: 3187.1748 | U90: =+E90-T90 -> 37422.825
A91: RM | B91: 760653 | C91: Insert M1.6- Ø3*5mm( Qualcomm MTP SDX24/55-PB922 Front housing) | D91: Etc | E91: 500 | F91: 160000 | G91: =+F91/$G$1 -> 6.1538462 | H91: =IFERROR(F91/E91,0) -> 320 | I91: Currenly no customer using these RM. Hence, full provision to be made | J91: 500 | K91: 160000 | L91: SLMV | M91: Reverse provison | N91: Y | T91: 500 | U91: =+E91-T91 -> 0
A92: RM | B92: 760654 | C92: Insert M1.6- Ø3*4mm( Qualcomm MTP SDX24/55-PB922 Front housing) | D92: Etc | E92: 250 | F92: 75000 | G92: =+F92/$G$1 -> 2.8846154 | H92: =IFERROR(F92/E92,0) -> 300 | I92: Currenly no customer using these RM. Hence, full provision to be made | J92: 250 | K92: 75000 | L92: SLMV | M92: Reverse provison | N92: Y | T92: 250 | U92: =+E92-T92 -> 0
A93: RM | B93: 760656 | C93: Ant Right 1( 50-PA571) (Qualcomm Ant Carrier Right)/linh kiện qualcomm | D93: Etc | E93: 609 | F93: 10188879 | G93: =+F93/$G$1 -> 391.87994 | H93: =IFERROR(F93/E93,0) -> 16730.507 | I93: These raw materials are in good condition and can be used for other customer, no expiry date on these raw materials. Hence, no provison | J93: 0 | K93: 0 | L93: OK | N93: N | T93: 0 | U93: =+E93-T93 -> 609
A94: RM | B94: 760657 | C94: Ant Right 2( 50-PA572) (Qualcomm Ant Carrier Right)/linh kiện qualcomm | D94: Etc | E94: 757 | F94: 12665759 | G94: =+F94/$G$1 -> 487.14457 | H94: =IFERROR(F94/E94,0) -> 16731.518 | I94: These raw materials are in good condition and can be used for other customer, no expiry date on these raw materials. Hence, no provison | J94: 0 | K94: 0 | L94: OK | N94: N | T94: 0 | U94: =+E94-T94 -> 757
A95: RM | B95: 760671 | C95: (Production) SHIELD, RF TO MAIN, PROJECT 50-PB736-P1 Qualcomm shield can | D95: Etc | E95: 96 | F95: 1481856 | G95: =+F95/$G$1 -> 56.994462 | H95: =IFERROR(F95/E95,0) -> 15436 | I95: Currenly no customer using these RM. Hence, full provision to be made | J95: 96 | K95: 1481856 | L95: SLMV | M95: Reverse provison | N95: Y | T95: 96 | U95: =+E95-T95 -> 0
A96: RM | B96: 760679 | C96: Glossy ink YD-1001 for nail/Mực bóng YD-1001 | D96: Cosmetic | E96: 5 | F96: 5238965 | G96: =+F96/$G$1 -> 201.49865 | H96: =IFERROR(F96/E96,0) -> 1047793 | I96: BU Discontinued - [1] | J96: 5 | K96: 5238965 | L96: SLMV | M96: Keep provision | N96: Y | T96: 5 | U96: =+E96-T96 -> 0
A97: RM | B97: 760725 | C97: Sơn UV phủ bóng móng tay UVILON #ART 1007(MC1) CLEAR | D97: Cosmetic | E97: 75 | F97: 19720498 | G97: =+F97/$G$1 -> 758.48069 | H97: =IFERROR(F97/E97,0) -> 262939.97 | I97: BU Discontinued - [1] | J97: 75 | K97: 19720498 | L97: SLMV | M97: Keep provision | N97: Y | T97: 75 | U97: =+E97-T97 -> 0
A98: RM | B98: 760726 | C98: Paint_x000D_/Sơn UV phủ bóng móng tay UVILON #ART 1009(MC4) CLEAR | D98: Cosmetic | E98: 135 | F98: 28762296 | G98: =+F98/$G$1 -> 1106.2422 | H98: =IFERROR(F98/E98,0) -> 213054.04 | I98: BU Discontinued - [1] | J98: 135 | K98: 28762296 | L98: SLMV | M98: Keep provision | N98: Y | T98: 135 | U98: =+E98-T98 -> 0
A99: RM | B99: 760728 | C99: Ink black 3C for nail/ Mực đen 3C | D99: Cosmetic | E99: 2 | F99: 2900000 | G99: =+F99/$G$1 -> 111.53846 | H99: =IFERROR(F99/E99,0) -> 1450000 | I99: BU Discontinued - [1] | J99: 2 | K99: 2900000 | L99: SLMV | M99: Keep provision | N99: Y | T99: 2 | U99: =+E99-T99 -> 0
A100: RM | B100: 760731 | C100: Color powder BK117/Bột màu BK117 | D100: Cosmetic | E100: 10 | F100: 15500000 | G100: =+F100/$G$1 -> 596.15385 | H100: =IFERROR(F100/E100,0) -> 1550000 | I100: BU Discontinued - [1] | J100: 10 | K100: 15500000 | L100: SLMV | M100: Keep provision | N100: Y | T100: 10 | U100: =+E100-T100 -> 0
A101: RM | B101: 760747 | C101: pink glue 70-02202-000 (EC 200p- with label) | D101: Etc | E101: 75609 | F101: 3.8540728e+08 | G101: =+F101/$G$1 -> 14823.357 | H101: =IFERROR(F101/E101,0) -> 5097.3731 | I101: These raw materials are in good condition and can be used for other customer, no expiry date on these raw materials. Hence, no provison | J101: 0 | K101: 0 | L101: OK | N101: N | T101: 75609 | U101: =+E101-T101 -> 0
A102: RM | B102: 760752 | C102: Tray FP1296/tray móng tay | D102: Cosmetic | E102: 13370 | F102: 16249692 | G102: =+F102/$G$1 -> 624.98815 | H102: =IFERROR(F102/E102,0) -> 1215.3846 | I102: BU Discontinued - [1] | J102: 13370 | K102: 16249692 | L102: SLMV | M102: Keep provision | N102: Y | T102: 13370 | U102: =+E102-T102 -> 0
A103: RM | B103: 760766 | C103: Lot No. sticker 9*23 mm/Nhãn dán ghi lot xuất hàng 9*23 mm mực trắng | D103: Cosmetic | E103: 24375 | F103: 1755928 | G103: =+F103/$G$1 -> 67.535692 | H103: =IFERROR(F103/E103,0) -> 72.038072 | I103: BU Discontinued - [1] | J103: 24375 | K103: 1755928 | L103: SLMV | M103: Keep provision | N103: Y | T103: 24375 | U103: =+E103-T103 -> 0
A104: RM | B104: 760789 | C104: Glitter HW-1001/Nhũ HW-1001 1/256 | D104: Cosmetic | E104: 10 | F104: 5320000 | G104: =+F104/$G$1 -> 204.61538 | H104: =IFERROR(F104/E104,0) -> 532000 | I104: BU Discontinued - [1] | J104: 10 | K104: 5320000 | L104: SLMV | M104: Keep provision | N104: Y | T104: 10 | U104: =+E104-T104 -> 0
A105: RM | B105: 760820 | C105: Devide pad YL 12/Tấm đệm YL 12, 3 lớp, 2 mặt vàng kích thước 580*340 mm | D105: Etc | E105: 300 | F105: 518100 | G105: =+F105/$G$1 -> 19.926923 | H105: =IFERROR(F105/E105,0) -> 1727 | I105: Currenly no customer using these RM. Hence, full provision to be made | J105: 300 | K105: 518100 | L105: SLMV | M105: Reverse provison | N105: Y | T105: 300 | U105: =+E105-T105 -> 0
A106: RM | B106: 760827 | C106: 6 pcs: white diamond -4/Đá trắng gắn móng tay giả | D106: Cosmetic | E106: 95040 | F106: 1571460 | G106: =+F106/$G$1 -> 60.440769 | H106: =IFERROR(F106/E106,0) -> 16.534722 | I106: BU Discontinued - [1] | J106: 95040 | K106: 1571460 | L106: SLMV | M106: Keep provision | N106: Y | T106: 95040 | U106: =+E106-T106 -> 0
A107: RM | B107: 760829 | C107: White diamond -SS3/Đá trắng gắn móng tay giả SS3 | D107: Cosmetic | E107: 608876 | F107: 11718427 | G107: =+F107/$G$1 -> 450.70873 | H107: =IFERROR(F107/E107,0) -> 19.245999 | I107: BU Discontinued - [1] | J107: 608876 | K107: 11718427 | L107: SLMV | M107: Keep provision | N107: Y | T107: 608876 | U107: =+E107-T107 -> 0
A108: RM | B108: 760831 | C108: AB-3 diamond/Đá AB-3 găn móng tay giả | D108: Cosmetic | E108: 173 | F108: 980676 | G108: =+F108/$G$1 -> 37.718308 | H108: =IFERROR(F108/E108,0) -> 5668.6474 | I108: BU Discontinued - [1] | J108: 173 | K108: 980676 | L108: SLMV | M108: Keep provision | N108: Y | T108: 173 | U108: =+E108-T108 -> 0
A109: RM | B109: 760833 | C109: white diamond ss4/Đá trắng ss4 gắn móng tay giả | D109: Cosmetic | E109: 7141 | F109: 5558452 | G109: =+F109/$G$1 -> 213.78662 | H109: =IFERROR(F109/E109,0) -> 778.38566 | I109: BU Discontinued - [1] | J109: 7141 | K109: 5558452 | L109: SLMV | M109: Keep provision | N109: Y | T109: 7141 | U109: =+E109-T109 -> 0
A110: RM | B110: 760834 | C110: Stone AB ss4/Đá AB ss4 | D110: Cosmetic | E110: 74883 | F110: 1723355 | G110: =+F110/$G$1 -> 66.282885 | H110: =IFERROR(F110/E110,0) -> 23.013968 | I110: BU Discontinued - [1] | J110: 74883 | K110: 1723355 | L110: SLMV | M110: Keep provision | N110: Y | T110: 74883 | U110: =+E110-T110 -> 0
A111: RM | B111: 760835 | C111: Champange stone ss3/đá màu vàng đồng ss3 | D111: Cosmetic | E111: 10197 | F111: 11920483 | G111: =+F111/$G$1 -> 458.48012 | H111: =IFERROR(F111/E111,0) -> 1169.0186 | I111: BU Discontinued - [1] | J111: 10197 | K111: 11920483 | L111: SLMV | M111: Keep provision | N111: Y | T111: 10197 | U111: =+E111-T111 -> 0
A112: RM | B112: 760838 | C112: white diamond 001AB-SS6/Đá gắn móng tay | D112: Cosmetic | E112: 11 | F112: 371092 | G112: =+F112/$G$1 -> 14.272769 | H112: =IFERROR(F112/E112,0) -> 33735.636 | I112: BU Discontinued - [1] | J112: 11 | K112: 371092 | L112: SLMV | M112: Keep provision | N112: Y | T112: 11 | U112: =+E112-T112 -> 0
A113: RM | B113: 760843 | C113: AB-SS8/Đá 7 màu SS8 cho móng tay giả | D113: Cosmetic | E113: 42 | F113: 1176000 | G113: =+F113/$G$1 -> 45.230769 | H113: =IFERROR(F113/E113,0) -> 28000 | I113: BU Discontinued - [1] | J113: 42 | K113: 1176000 | L113: SLMV | M113: Keep provision | N113: Y | T113: 42 | U113: =+E113-T113 -> 0
... A125: RM | B125: 760994 | C125: Bột màu HW-1001A 1/128 | D125: Cosmetic | E125: 5 | F125: 2517500 | G125: =+F125/$G$1 -> 96.826923 | H125: =IFERROR(F125/E125,0) -> 503500 | I125: BU Discontinued - [1] | J125: 5 | K125: 2517500 | L125: SLMV | M125: Keep provision | N125: Y | T125: 5 | U125: =+E125-T125 -> 0
A126: RM | B126: 760997 | C126: EC 300 2g glue | D126: Etc | E126: 20578 | F126: 65747502 | G126: =+F126/$G$1 -> 2528.7501 | H126: =IFERROR(F126/E126,0) -> 3195.0385 | I126: These raw materials are in good condition and can be used for other customer, no expiry date on these raw materials. Hence, no provison | J126: 0 | K126: 0 | L126: OK | N126: N | T126: 20578 | U126: =+E126-T126 -> 0
A127: RM | B127: 760999 | C127: ''Master lable 05011522136004'Master box label size 100*77mm | D127: Etc | E127: 30 | F127: 7050 | G127: =+F127/$G$1 -> 0.27115385 | H127: =IFERROR(F127/E127,0) -> 235 | I127: Currenly no customer using these RM. Hence, full provision to be made | J127: 30 | K127: 7050 | L127: SLMV | M127: Reverse provison | N127: Y | T127: 30 | U127: =+E127-T127 -> 0
A128: RM | B128: 761001 | C128: 'Master lable ''05011522136035 Barcode l size '55*32mm . Code ITF14 size 100*77mm/Tem dán | D128: Etc | E128: 140 | F128: 62825 | G128: =+F128/$G$1 -> 2.4163462 | H128: =IFERROR(F128/E128,0) -> 448.75 | I128: Currenly no customer using these RM. Hence, full provision to be made | J128: 140 | K128: 62825 | L128: SLMV | M128: Reverse provison | N128: Y | T128: 140 | U128: =+E128-T128 -> 0
A129: RM | B129: 761008 | C129: InnerLable ''05011522135960 Barcode l size '55*32mm . Code ITF14 size 100*77mm | D129: Etc | E129: 530 | F129: 124550 | G129: =+F129/$G$1 -> 4.7903846 | H129: =IFERROR(F129/E129,0) -> 235 | I129: Currenly no customer using these RM. Hence, full provision to be made | J129: 530 | K129: 124550 | L129: SLMV | M129: Reverse provison | N129: Y | T129: 530 | U129: =+E129-T129 -> 0
A130: RM | B130: 761009 | C130: 'Master lable ''05011522135977 Barcode l size '55*32mm . Code ITF14 size 100*77m | D130: Etc | E130: 50 | F130: 11750 | G130: =+F130/$G$1 -> 0.45192308 | H130: =IFERROR(F130/E130,0) -> 235 | I130: Currenly no customer using these RM. Hence, full provision to be made | J130: 50 | K130: 11750 | L130: SLMV | M130: Reverse provison | N130: Y | T130: 50 | U130: =+E130-T130 -> 0
A131: RM | B131: 761023 | C131: Item box label UCPA: '078462630264 Size 30*12 mm | D131: Etc | E131: 1000 | F131: 55000 | G131: =+F131/$G$1 -> 2.1153846 | H131: =IFERROR(F131/E131,0) -> 55 | I131: Currenly no customer using these RM. Hence, full provision to be made | J131: 1000 | K131: 55000 | L131: SLMV | M131: Reverse provison | N131: Y | T131: 1000 | U131: =+E131-T131 -> 0
A132: RM | B132: 761034 | C132: Hộp giấy 4013535-Instanails-Wild weekend | D132: Cosmetic | E132: 3350 | F132: 14741598 | G132: =+F132/$G$1 -> 566.98454 | H132: =IFERROR(F132/E132,0) -> 4400.477 | I132: BU Discontinued - [1] | J132: 3350 | K132: 14741598 | L132: SLMV | M132: Keep provision | N132: Y | T132: 3350 | U132: =+E132-T132 -> 0
A133: RM | B133: 761059 | C133: Paint_x000D_ /EMS Gray (M&C) paint | D133: Etc | E133: 45 | F133: 15096465 | G133: =+F133/$G$1 -> 580.63327 | H133: =IFERROR(F133/E133,0) -> 335477 | I133: These raw materials are in good condition and can be used for other customer, no expiry date on these raw materials. Hence, no provison | J133: 0 | K133: 0 | L133: SLMV | M133: No provision | N133: Y | T133: 0 | U133: =+E133-T133 -> 45
A134: RM | B134: 761081 | C134: color powder/bột màu hw-3403 1/128 | D134: Cosmetic | E134: 4 | F134: 1806000 | G134: =+F134/$G$1 -> 69.461538 | H134: =IFERROR(F134/E134,0) -> 451500 | I134: BU Discontinued - [1] | J134: 4 | K134: 1806000 | L134: SLMV | M134: Keep provision | N134: Y | T134: 4 | U134: =+E134-T134 -> 0
A135: RM | B135: 761096 | C135: Vách ngăn, 3 lớp,YL17 kích thước 378*125 | D135: Etc | E135: 250 | F135: 177250 | G135: =+F135/$G$1 -> 6.8173077 | H135: =IFERROR(F135/E135,0) -> 709 | I135: BU Discontinued - [1] | J135: 650 | K135: 460850 | L135: OK | M135: Reverse provison | N135: N | T135: 250 | U135: =+E135-T135 -> 0
A136: RM | B136: 761103 | C136: Tray nail/Tray móng tay giả FP72137 | D136: Cosmetic | E136: 32976 | F136: 59890480 | G136: =+F136/$G$1 -> 2303.48 | H136: =IFERROR(F136/E136,0) -> 1816.1839 | I136: BU Discontinued - [1] | J136: 32976 | K136: 59890480 | L136: SLMV | M136: Keep provision | N136: Y | T136: 32976 | U136: =+E136-T136 -> 0
A137: RM | B137: 761105 | C137: Alcohol Prep pad for muse&co | D137: Cosmetic | E137: 28800 | F137: 7253054 | G137: =+F137/$G$1 -> 278.96362 | H137: =IFERROR(F137/E137,0) -> 251.84215 | I137: BU Discontinued - [1] | J137: 28800 | K137: 7253054 | L137: SLMV | M137: Keep provision | N137: Y | T137: 28800 | U137: =+E137-T137 -> 0
A138: RM | B138: 761111 | C138: Paper box /Hộp giấy móng tay 30-02294-FA1 | D138: Cosmetic | E138: 3304 | F138: 4427101 | G138: =+F138/$G$1 -> 170.27312 | H138: =IFERROR(F138/E138,0) -> 1339.9216 | I138: BU Discontinued - [1] | J138: 3304 | K138: 4427101 | L138: SLMV | M138: Keep provision | N138: Y | T138: 3304 | U138: =+E138-T138 -> 0
... A143: RM | B143: 761133 | C143: Back label 70269 FB1/Nhãn sau 70269 FB1 | D143: Etc | E143: 5950 | F143: 1295218 | G143: =+F143/$G$1 -> 49.816077 | H143: =IFERROR(F143/E143,0) -> 217.6837 | I143: Currenly no customer using these RM. Hence, full provision to be made | J143: 5950 | K143: 1295218 | L143: SLMV | M143: Reverse provison | N143: Y | T143: 5950 | U143: =+E143-T143 -> 0
...

Sheet Sheet1
G1: Status 2025 | H1: SLMV
A3: Row Labels | B3: Sum of Qty Blance | C3: Sum of Amount Balance ( VND) | E3: 2024 Make provision | G3: Row Labels | H3: Sum of Qty Blance | I3: Sum of Amount Balance ( VND)
A4: FG | B4: 1469823 | C4: 4.0354451e+10 | E4: =SUMIF('SLM 2024 updated Dec.25'!A:A,A4,'SLM 2024 updated Dec.25'!L:L) -> 4.7709049e+09 | G4: FG | H4: 312727 | I4: 5.5826691e+09
A5: RM | B5: 8953586.2 | C5: 2.2272429e+10 | E5: =SUMIF('SLM 2024 updated Dec.25'!A:A,A5,'SLM 2024 updated Dec.25'!L:L) -> 4.8851483e+09 | G5: RM | H5: 4573264 | I5: 9.5704877e+09
A6: Supply | B6: 431983.5 | C6: 2.1009464e+10 | E6: =SUMIF('SLM 2024 updated Dec.25'!A:A,A6,'SLM 2024 updated Dec.25'!L:L) -> 26250000 | G6: Supply | H6: 8336 | I6: 1.2212376e+09
A7: Trading | B7: 1084 | C7: 4.8099794e+09 | E7: =SUMIF('SLM 2024 updated Dec.25'!A:A,A7,'SLM 2024 updated Dec.25'!L:L) -> 40160000 | G7: Trading | H7: 6 | I7: 1.10835e+09
A8: WIP | B8: 1339044.1 | C8: 1.0403302e+10 | E8: =SUMIF('SLM 2024 updated Dec.25'!A:A,A8,'SLM 2024 updated Dec.25'!L:L) -> 7.6046819e+09 | G8: WIP | H8: 1134549.1 | I8: 7.391456e+09
A9: (blank) | E9: =SUM(E3:E8) -> 1.7327145e+10 | G9: Grand Total | H9: 6028882.2 | I9: 2.48742e+10
A10: Grand Total | B10: 12195521 | C10: 9.8849625e+10

Sheet SLM 2024 updated Dec.25
C1: Slow-Moving List ASSESSMENT (Audit's file) | K1: Provision Dec.2024 | O1: SLMV at Ending 31.12.24 (Accounting book) | S1: Remaining Ending
A2: Kind | B2: item code | C2: Name | D2: Qty Slm | E2: Amount Slm | F2: Price | G2: xxx | H2: Condition | I2: Technical Justification | J2: Disposition Plan | K2: Qty Provision | L2: Amt provision | M2: % | N2: XX | O2: Qty | P2: Amt VND | Q2: Qty | R2: Amt VND | S2: Qty | T2: Amt VND | U2: Note
E3: =SUM(E4:E3436) -> 9.4908928e+10 | L3: =SUM(L4:L3436) -> 1.7327145e+10 | O3: =SUM(O4:O3436) -> 15557575 | P3: =SUM(P4:P3436) -> 1.1454977e+11 | Q3: =SUM(Q4:Q3436) -> 7827112.2 | R3: =SUM(R4:R3436) -> 8.5190233e+10 | S3: =SUM(S4:S3436) -> 2810813 | T3: =SUM(T4:T3436) -> 1.2032731e+10
A4: FG | B4: 100876 | C4: PK Qualcomm IDP CEDROS 50-PT525-2 Ant Carrier, Antenna 5 And 6 | D4: 26 | E4: 58655288 | F4: =+E4/D4 -> 2255972.6 | H4: Good | I4: No provision to be made, as item will be recycle to New Ingot in Year 2025 | J4: Recycle | K4: 0 | L4: 0 | M4: =+L4/E4 -> 0 | O4: 26 | P4: 58655288 | Q4: 26 | R4: 58655288 | S4: =O4-K4-Q4 -> 0 | T4: =P4-L4-R4 -> 0 | U4: Produce again 2025
A5: FG | B5: 100913 | C5: PK Qualcom QRD Fillmore MCVC21-003 Front Housing | D5: 120 | E5: 84446843 | F5: =+E5/D5 -> 703723.69 | H5: Good | I5: No provision to be made, as item will be recycle to New Ingot in Year 2025 | J5: Recycle | K5: 0 | L5: 0 | M5: =+L5/E5 -> 0 | O5: 153 | P5: 1.0766972e+08 | Q5: 153 | R5: 1.0766972e+08 | S5: =O5-K5-Q5 -> 0 | T5: =P5-L5-R5 -> 0 | U5: Clearing ok
A6: FG | B6: 100723 | C6: PK Qualcomm Front housing CNC JIG STEP 2 | D6: 1 | E6: 603989.42 | F6: =+E6/D6 -> 603989.42 | H6: Good | I6: No provision to be made, amount can be recover - [2] | J6: N.A | K6: 0 | L6: 0 | M6: =+L6/E6 -> 0 | O6: 1 | P6: 603989.42 | Q6: 1 | R6: 603989.42 | S6: =O6-K6-Q6 -> 0 | T6: =P6-L6-R6 -> 0 | U6: Clearing ok
A7: FG | B7: 100725 | C7: PK Qualcomm Front housing CNC JIG STEP 4 | D7: 2 | E7: 1207978.8 | F7: =+E7/D7 -> 603989.42 | H7: Good | I7: No provision to be made, amount can be recover - [2] | J7: N.A | K7: 0 | L7: 0 | M7: =+L7/E7 -> 0 | O7: 2 | P7: 1207978.8 | Q7: 2 | R7: 1207978.8 | S7: =O7-K7-Q7 -> 0 | T7: =P7-L7-R7 -> 0 | U7: Clearing ok
A8: FG | B8: 100472 | C8: PK Viettel VPH-411S-1 Inner base Frame( Sanding& Anodizing) | D8: 16 | E8: 9069087.9 | F8: =+E8/D8 -> 566818 | H8: Good | I8: No provision to be made, as item will be recycle to New Ingot in Year 2025 | J8: Recycle | K8: 0 | L8: 0 | M8: =+L8/E8 -> 0 | O8: 16 | P8: 9069087.9 | Q8: 16 | R8: 9069087.9 | S8: =O8-K8-Q8 -> 0 | T8: =P8-L8-R8 -> 0 | U8: Clearing ok
A9: FG | B9: 100477 | C9: PK Viettel VPH-411S-6 Back cover( Sanding& Anodizing) | D9: 23 | E9: 11410849 | F9: =+E9/D9 -> 496123.87 | H9: Good | I9: No provision to be made, as item will be recycle to New Ingot in Year 2025 | J9: Recycle | K9: 0 | L9: 0 | M9: =+L9/E9 -> 0 | O9: 23 | P9: 11410849 | Q9: 23 | R9: 11410849 | S9: =O9-K9-Q9 -> 0 | T9: =P9-L9-R9 -> 0 | U9: Clearing ok
A10: FG | B10: 100476 | C10: PK Viettel VPH-411S-5 Back base (Sanding) | D10: 106 | E10: 52500352 | F10: =+E10/D10 -> 495286.34 | H10: Good | I10: No provision to be made, as item will be recycle to New Ingot in Year 2025 | J10: Recycle | K10: 0 | L10: 0 | M10: =+L10/E10 -> 0 | O10: 106 | P10: 52500352 | Q10: 106 | R10: 52500352 | S10: =O10-K10-Q10 -> 0 | T10: =P10-L10-R10 -> 0 | U10: Clearing ok
A11: FG | B11: 100428 | C11: PK CP15 DCT002 (Logo DW ) | D11: 72 | E11: 30046293 | F11: =+E11/D11 -> 417309.62 | H11: Good | I11: BU Discontinued - [1] | J11: Full Provision | K11: =D11 -> 72 | L11: =E11 -> 30046293 | M11: =+L11/E11 -> 1 | O11: 72 | P11: 30046293 | Q11: 0 | R11: 0 | S11: =O11-K11-Q11 -> 0 | T11: =P11-L11-R11 -> 0 | U11: Make provision 2024
A12: FG | B12: 100416 | C12: ACE Tech 83A-00167 | D12: 359 | E12: 1.3713226e+08 | F12: =+E12/D12 -> 381984.01 | H12: Good | I12: No provision to be made, as item will be recycle to New Ingot in Year 2025 | J12: Recycle | K12: 0 | L12: 0 | M12: =+L12/E12 -> 0 | O12: 359 | P12: 1.3713226e+08 | Q12: 359 | R12: 1.3713226e+08 | S12: =O12-K12-Q12 -> 0 | T12: =P12-L12-R12 -> 0 | U12: Clearing ok
A13: FG | B13: 100474 | C13: PK Viettel VPH-411S-3 Right cover (Sanding) | D13: 97 | E13: 32672242 | F13: =+E13/D13 -> 336827.23 | H13: Good | I13: No provision to be made, as item will be recycle to New Ingot in Year 2025 | J13: Recycle | K13: 0 | L13: 0 | M13: =+L13/E13 -> 0 | O13: 97 | P13: 32672242 | Q13: 97 | R13: 32672242 | S13: =O13-K13-Q13 -> 0 | T13: =P13-L13-R13 -> 0 | U13: Clearing ok
A14: FG | B14: 100475 | C14: PK Viettel VPH-411S-4 Left Cover (Sanding) | D14: 97 | E14: 32672242 | F14: =+E14/D14 -> 336827.23 | H14: Good | I14: No provision to be made, as item will be recycle to New Ingot in Year 2025 | J14: Recycle | K14: 0 | L14: 0 | M14: =+L14/E14 -> 0 | O14: 97 | P14: 32672242 | Q14: 97 | R14: 32672242 | S14: =O14-K14-Q14 -> 0 | T14: =P14-L14-R14 -> 0 | U14: Clearing ok
A15: FG | B15: 100646 | C15: PK Qualcomm CPE Huracan 50-PM307-1 Stand | D15: 6 | E15: 1882766 | F15: =+E15/D15 -> 313794.33 | H15: Good | I15: No provision to be made, as item will be recycle to New Ingot in Year 2025 | J15: Recycle | M15: =+L15/E15 -> 0 | O15: 6 | P15: 1882766 | Q15: 6 | R15: 1882766 | S15: =O15-K15-Q15 -> 0 | T15: =P15-L15-R15 -> 0 | U15: Clearing ok
A16: FG | B16: 150581 | C16: PK NF0019AF(36 Nails) | D16: 220 | E16: 51958758 | F16: =+E16/D16 -> 236176.17 | H16: Good | I16: BU Discontinued - [1] | J16: Full Provision | K16: 220 | L16: 51958758 | M16: =+L16/E16 -> 1 | O16: 220 | P16: 51958758 | Q16: 0 | R16: 0 | S16: =O16-K16-Q16 -> 0 | T16: =P16-L16-R16 -> 0 | U16: Make provision 2024
A17: FG | B17: 100413 | C17: ACE Tech 83A-00220 | D17: 48 | E17: 11046054 | F17: =+E17/D17 -> 230126.14 | H17: Good | I17: No provision to be made, as item will be recycle to New Ingot in Year 2025 | J17: Recycle | K17: 0 | L17: 0 | M17: =+L17/E17 -> 0 | O17: 48 | P17: 11046054 | Q17: 48 | R17: 11046054 | S17: =O17-K17-Q17 -> 0 | T17: =P17-L17-R17 -> 0 | U17: Clearing ok
A18: FG | B18: 100551 | C18: PK ACE Tech 83A-00185 ( not Base) | D18: 178 | E18: 37894005 | F18: =+E18/D18 -> 212887.67 | H18: Good | I18: No provision to be made, as item will be recycle to New Ingot in Year 2025 | J18: Recycle | K18: 0 | L18: 0 | M18: =+L18/E18 -> 0 | O18: 178 | P18: 37894005 | Q18: 178 | R18: 37894005 | S18: =O18-K18-Q18 -> 0 | T18: =P18-L18-R18 -> 0 | U18: Clearing ok
A19: FG | B19: 100306 | C19: HM003 | D19: 78 | E19: 15542026 | F19: =+E19/D19 -> 199256.74 | H19: Good | I19: No provision to be made, as item will be recycle to New Ingot in Year 2025 | J19: Recycle | K19: 0 | L19: 0 | M19: =+L19/E19 -> 0 | O19: 78 | P19: 15542026 | Q19: 78 | R19: 15542026 | S19: =O19-K19-Q19 -> 0 | T19: =P19-L19-R19 -> 0 | U19: Clearing ok
A20: FG | B20: 100480 | C20: PK Viettel VPH-411S-9 Bottom Front deco (Sanding) | D20: 88 | E20: 16109462 | F20: =+E20/D20 -> 183062.07 | H20: Good | I20: No provision to be made, as item will be recycle to New Ingot in Year 2025 | J20: Recycle | K20: 0 | L20: 0 | M20: =+L20/E20 -> 0 | O20: 88 | P20: 16109462 | Q20: 88 | R20: 16109462 | S20: =O20-K20-Q20 -> 0 | T20: =P20-L20-R20 -> 0 | U20: Clearing ok
A21: FG | B21: 100789 | C21: PK Vinsmart V650 Front Frame Assy | D21: 81 | E21: 13645344 | F21: =+E21/D21 -> 168461.04 | H21: Good | I21: No provision to be made, as item will be recycle to New Ingot in Year 2025 | J21: Recycle | M21: =+L21/E21 -> 0 | O21: 81 | P21: 13645344 | Q21: 81 | R21: 13645344 | S21: =O21-K21-Q21 -> 0 | T21: =P21-L21-R21 -> 0 | U21: Clearing ok
A22: FG | B22: 101220 | C22: PK Qualcomm MTP KAANAPALI 50-58183-2 FRAME, WLAN AREA, MULTIPURPOSE | D22: 4.2472055 | E22: 703523.43 | F22: =+E22/D22 -> 165643.84 | H22: Good | I22: No provision to be made, as item will be recycle to New Ingot in Year 2025 | J22: Recycle | M22: =+L22/E22 -> 0 | O22: 144 | P22: 23852713 | Q22: 144 | R22: 23852713 | S22: =O22-K22-Q22 -> 0 | T22: =P22-L22-R22 -> 0 | U22: Produce again 2025
A23: FG | B23: 100473 | C23: PK Viettel VPH-411S-2 Back deco (Sanding) | D23: 90 | E23: 14898140 | F23: =+E23/D23 -> 165534.89 | H23: Good | I23: No provision to be made, as item will be recycle to New Ingot in Year 2025 | J23: Recycle | K23: 0 | L23: 0 | M23: =+L23/E23 -> 0 | O23: 90 | P23: 14898140 | Q23: 90 | R23: 14898140 | S23: =O23-K23-Q23 -> 0 | T23: =P23-L23-R23 -> 0 | U23: Clearing ok
A24: FG | B24: 101135 | C24: PK Qualcomm MTP Pinnacles 50-28768-2 Frame Wlan Area, Multipurpose | D24: 156 | E24: 25658410 | F24: =+E24/D24 -> 164476.99 | H24: Good | I24: No provision to be made, as item will be recycle to New Ingot in Year 2025 | J24: Recycle | K24: 0 | L24: 0 | M24: =+L24/E24 -> 0 | O24: 156 | P24: 25658410 | Q24: 0 | R24: 0 | S24: =O24-K24-Q24 -> 156 | T24: =P24-L24-R24 -> 25658410 | U24: Will sale again
A25: FG | B25: 101168 | C25: PK Qualcomm MTP PAKALA 55-58184-1 CARRIER FRAME, ASSY | D25: 51 | E25: 8223562.6 | F25: =+E25/D25 -> 161246.33 | H25: Good | I25: No provision to be made, as item will be recycle to New Ingot in Year 2025 | J25: Recycle | K25: 0 | L25: 0 | M25: =+L25/E25 -> 0 | O25: 51 | P25: 8223562.6 | Q25: 0 | R25: 0 | S25: =O25-K25-Q25 -> 51 | T25: =P25-L25-R25 -> 8223562.6 | U25: Will sale again
A26: FG | B26: 100300 | C26: AS DCT048 | D26: 85 | E26: 13370582 | F26: =+E26/D26 -> 157300.96 | H26: Good | I26: No provision to be made, as item will be recycle to New Ingot in Year 2025 | J26: Recycle | K26: 0 | L26: 0 | M26: =+L26/E26 -> 0 | O26: 85 | P26: 13370582 | Q26: 85 | R26: 13370582 | S26: =O26-K26-Q26 -> 0 | T26: =P26-L26-R26 -> 0 | U26: Clearing ok
A27: FG | B27: 100558 | C27: PK Qualcomm IDP Moorea 55-PF951-4 Front housing | D27: 60 | E27: 9325947.1 | F27: =+E27/D27 -> 155432.45 | H27: Good | I27: No provision to be made, as item will be recycle to New Ingot in Year 2025 | J27: Recycle | K27: 0 | L27: 0 | M27: =+L27/E27 -> 0 | O27: 60 | P27: 9325947.1 | Q27: 60 | R27: 9325947.1 | S27: =O27-K27-Q27 -> 0 | T27: =P27-L27-R27 -> 0 | U27: Clearing ok
A28: FG | B28: 150564 | C28: PK ZN0022 | D28: 636 | E28: 92683686 | F28: =+E28/D28 -> 145729.07 | H28: Good | I28: BU Discontinued - [1] | J28: Full Provision | K28: =+D28 -> 636 | L28: =+E28 -> 92683686 | M28: =+L28/E28 -> 1 | O28: 636 | P28: 92683686 | Q28: 0 | R28: 0 | S28: =O28-K28-Q28 -> 0 | T28: =P28-L28-R28 -> 0 | U28: Make provision 2024
A29: FG | B29: 101051 | C29: PK Qualcomm MTP Pinnacles 55-29819-1 Front Housing | D29: 160 | E29: 22938399 | F29: =+E29/D29 -> 143364.99 | H29: Good | I29: No provision to be made, as item will be recycle to New Ingot in Year 2025 | J29: Recycle | K29: 0 | L29: 0 | M29: =+L29/E29 -> 0 | O29: 160 | P29: 22938399 | Q29: 160 | R29: 22938399 | S29: =O29-K29-Q29 -> 0 | T29: =P29-L29-R29 -> 0 | U29: Clearing ok
A30: FG | B30: 100641 | C30: PK Qualcomm Kona 55-PG165-4 Ant Carrier 1 | D30: 365 | E30: 51357507 | F30: =+E30/D30 -> 140705.5 | H30: Good | I30: No provision to be made, as item will be recycle to New Ingot in Year 2025 | J30: Recycle | K30: 0 | L30: 0 | M30: =+L30/E30 -> 0 | O30: 365 | P30: 51357507 | Q30: 365 | R30: 51357507 | S30: =O30-K30-Q30 -> 0 | T30: =P30-L30-R30 -> 0 | U30: Clearing ok
A31: FG | B31: 101093 | C31: PK Qualcomm CPE Pinnacles 50-38556-1 LDS, Antenna, Left | D31: 15 | E31: 2064524.3 | F31: =+E31/D31 -> 137634.95 | H31: Good | I31: No provision to be made, as item will be recycle to New Ingot in Year 2025 | J31: Recycle | K31: 0 | L31: 0 | M31: =+L31/E31 -> 0 | O31: 15 | P31: 2064524.3 | Q31: 15 | R31: 2064524.3 | S31: =O31-K31-Q31 -> 0 | T31: =P31-L31-R31 -> 0 | U31: Sale again 2025
A32: FG | B32: 100479 | C32: PK Viettel VPH-411S-8 Top Front deco 2 (Sanding) | D32: 77 | E32: 10295810 | F32: =+E32/D32 -> 133711.82 | H32: Good | I32: No provision to be made, as item will be recycle to New Ingot in Year 2025 | J32: Recycle | K32: 0 | L32: 0 | M32: =+L32/E32 -> 0 | O32: 77 | P32: 10295810 | Q32: 77 | R32: 10295810 | S32: =O32-K32-Q32 -> 0 | T32: =P32-L32-R32 -> 0 | U32: Clearing ok
A33: FG | B33: 150565 | C33: PK ZN0023 | D33: 100 | E33: 13167147 | F33: =+E33/D33 -> 131671.47 | H33: Good | I33: BU Discontinued - [1] | J33: Full Provision | K33: =+D33 -> 100 | L33: =+E33 -> 13167147 | M33: =+L33/E33 -> 1 | O33: 100 | P33: 13167147 | Q33: 0 | R33: 0 | S33: =O33-K33-Q33 -> 0 | T33: =P33-L33-R33 -> 0 | U33: Make provision 2024
A34: FG | B34: 120196 | C34: PK ZF IPM Housing A010R190 | D34: 897 | E34: 1.1766951e+08 | F34: =+E34/D34 -> 131181.17 | H34: Good | I34: No provision to be made, as item will be recycle to New Ingot in Year 2025 | J34: Recycle | K34: 0 | L34: 0 | M34: =+L34/E34 -> 0 | O34: 897 | P34: 1.1766951e+08 | Q34: 897 | R34: 1.1766951e+08 | S34: =O34-K34-Q34 -> 0 | T34: =P34-L34-R34 -> 0 | U34: Clearing ok
A35: FG | B35: 100831 | C35: PK Qualcomm MTP Olympic Waipio 55-PV454-11 Sub Assy Front Bottom | D35: 10 | E35: 1310782.8 | F35: =+E35/D35 -> 131078.28 | H35: Good | I35: No provision to be made, as item will be recycle to New Ingot in Year 2025 | J35: Recycle | M35: =+L35/E35 -> 0 | O35: 275 | P35: 36046528 | Q35: 275 | R35: 36046528 | S35: =O35-K35-Q35 -> 0 | T35: =P35-L35-R35 -> 0 | U35: Clearing ok
A36: FG | B36: 101185 | C36: PK Qualcomm MTP PAKALA 55-58184-20 CARRIER FRAME, ASSY | D36: 21 | E36: 2740084.2 | F36: =+E36/D36 -> 130480.2 | H36: Good | I36: No provision to be made, as item will be recycle to New Ingot in Year 2025 | J36: Recycle | K36: 0 | L36: 0 | M36: =+L36/E36 -> 0 | O36: 21 | P36: 2740084.2 | Q36: 0 | R36: 0 | S36: =O36-K36-Q36 -> 21 | T36: =P36-L36-R36 -> 2740084.2 | U36: Will sale again
A37: FG | B37: 120430 | C37: PK LGIT MRA2 Camera Base 3CAC00196A( Casting MC) (2) | D37: 8345 | E37: 1.0720066e+09 | F37: =+E37/D37 -> 128460.94 | H37: Good | I37: No provision to be made, as item will be recycle to New Ingot in Year 2025 | J37: Recycle | K37: 0 | L37: 0 | M37: =+L37/E37 -> 0 | O37: 8345 | P37: 1.0720066e+09 | Q37: 5476 | R37: 7.0345211e+08 | S37: =O37-K37-Q37 -> 2869 | T37: =P37-L37-R37 -> 3.6855444e+08 | U37: Sale again 2025
A38: FG | B38: 120303 | C38: PK LGIT MRA2 Camera Base 3CAC00196A( Casting MC) | D38: 52 | E38: 6506626.2 | F38: =+E38/D38 -> 125127.43 | H38: Good | I38: No provision to be made, as item will be recycle to New Ingot in Year 2025 | J38: Recycle | K38: 0 | L38: 0 | M38: =+L38/E38 -> 0 | O38: 3062 | P38: 3.8314018e+08 | Q38: 3062 | R38: 3.8314018e+08 | S38: =O38-K38-Q38 -> 0 | T38: =P38-L38-R38 -> 0 | U38: Sale again 2025
A39: FG | B39: 150552 | C39: PK ZN0006 | D39: 200 | E39: 24351591 | F39: =+E39/D39 -> 121757.95 | H39: Good | I39: BU Discontinued - [1] | J39: Full Provision | K39: =+D39 -> 200 | L39: =+E39 -> 24351591 | M39: =+L39/E39 -> 1 | O39: 200 | P39: 24351591 | Q39: 0 | R39: 0 | S39: =O39-K39-Q39 -> 0 | T39: =P39-L39-R39 -> 0 | U39: Make provision 2024
A40: FG | B40: 100716 | C40: PK Qualcomm MTP Bittra 55-PM920-10 Front housing | D40: 108 | E40: 13066087 | F40: =+E40/D40 -> 120982.29 | H40: Good | I40: No provision to be made, as item will be recycle to New Ingot in Year 2025 | J40: Recycle | K40: 0 | L40: 0 | M40: =+L40/E40 -> 0 | O40: 849 | P40: 1.0271396e+08 | Q40: 849 | R40: 1.0271396e+08 | S40: =O40-K40-Q40 -> 0 | T40: =P40-L40-R40 -> 0 | U40: Sale again 2025
A41: FG | B41: 150551 | C41: PK ZN0005 | D41: 200 | E41: 24153504 | F41: =+E41/D41 -> 120767.52 | H41: Good | I41: BU Discontinued - [1] | J41: Full Provision | K41: =+D41 -> 200 | L41: =+E41 -> 24153504 | M41: =+L41/E41 -> 1 | O41: 200 | P41: 24153504 | Q41: 0 | R41: 0 | S41: =O41-K41-Q41 -> 0 | T41: =P41-L41-R41 -> 0 | U41: Make provision 2024
A42: FG | B42: 101141 | C42: PK Qualcomm MTP Camano 55-PR919-20 Display Carrier Frame Assy | D42: 43 | E42: 5159913.2 | F42: =+E42/D42 -> 119997.98 | H42: Good | I42: No provision to be made, as item will be recycle to New Ingot in Year 2025 | J42: Recycle | K42: 0 | L42: 0 | M42: =+L42/E42 -> 0 | O42: 43 | P42: 5159913.2 | Q42: 43 | R42: 5159913.2 | S42: =O42-K42-Q42 -> 0 | T42: =P42-L42-R42 -> 0 | U42: Produce again 2025
A43: FG | B43: 100858 | C43: PK Qualcomm CPE Olympic 50-PV355-1 Cover, Front. V1 | D43: 20 | E43: 2395462 | F43: =+E43/D43 -> 119773.1 | H43: Good | I43: No provision to be made, as item will be recycle to New Ingot in Year 2025 | J43: Recycle | M43: =+L43/E43 -> 0 | O43: 20 | P43: 2395462 | Q43: 20 | R43: 2395462 | S43: =O43-K43-Q43 -> 0 | T43: =P43-L43-R43 -> 0 | U43: Clearing ok
A44: FG | B44: 120307 | C44: PK LGIT 1V5 1452 3CAC00308A Base Housing | D44: 428 | E44: 50823919 | F44: =+E44/D44 -> 118747.47 | H44: Good | I44: No provision to be made, as item will be recycle to New Ingot in Year 2025 | J44: Recycle | K44: 0 | L44: 0 | M44: =+L44/E44 -> 0 | O44: 428 | P44: 50823919 | Q44: 428 | R44: 50823919 | S44: =O44-K44-Q44 -> 0 | T44: =P44-L44-R44 -> 0 | U44: Clearing ok
A45: FG | B45: 101190 | C45: PK Qualcomm MTP IDPS MILOS 55-PM920-100 FRONT HOUSING | D45: 96 | E45: 11264352 | F45: =+E45/D45 -> 117337 | H45: Good | I45: No provision to be made, as item will be recycle to New Ingot in Year 2025 | J45: Recycle | K45: 0 | L45: 0 | M45: =+L45/E45 -> 0 | O45: 96 | P45: 11264352 | Q45: 96 | R45: 11264352 | S45: =O45-K45-Q45 -> 0 | T45: =P45-L45-R45 -> 0 | U45: Produce again 2025
A46: FG | B46: 150543 | C46: PK CP0134AF -6 PACKS | D46: 200 | E46: 22968160 | F46: =+E46/D46 -> 114840.8 | H46: Good | I46: BU Discontinued - [1] | J46: Full Provision | K46: =D46 -> 200 | L46: =E46 -> 22968160 | M46: =+L46/E46 -> 1 | O46: 200 | P46: 22968160 | Q46: 0 | R46: 0 | S46: =O46-K46-Q46 -> 0 | T46: =P46-L46-R46 -> 0 | U46: Make provision 2024
A47: FG | B47: 150544 | C47: PK CP0135AF -6 PACKS | D47: 200 | E47: 22827711 | F47: =+E47/D47 -> 114138.56 | H47: Good | I47: BU Discontinued - [1] | J47: Full Provision | K47: =D47 -> 200 | L47: =E47 -> 22827711 | M47: =+L47/E47 -> 1 | O47: 200 | P47: 22827711 | Q47: 0 | R47: 0 | S47: =O47-K47-Q47 -> 0 | T47: =P47-L47-R47 -> 0 | U47: Make provision 2024
A48: FG | B48: 101100 | C48: PK Qualcomm IPD Cedros 50-PR954-80 Assy, Sub Assy Rear Housing | D48: 29 | E48: 3291145.7 | F48: =+E48/D48 -> 113487.78 | H48: Good | I48: No provision to be made, as item will be recycle to New Ingot in Year 2025 | J48: Recycle | M48: =+L48/E48 -> 0 | O48: 29 | P48: 3291145.7 | Q48: 29 | R48: 3291145.7 | S48: =O48-K48-Q48 -> 0 | T48: =P48-L48-R48 -> 0 | U48: Clearing ok
A49: FG | B49: 120366 | C49: PK Hosiden HEG Cover HGU0810-27PW(2) | D49: 951 | E49: 1.0680823e+08 | F49: =+E49/D49 -> 112311.49 | H49: Good | I49: No provision to be made, as item will be recycle to New Ingot in Year 2025 | J49: Recycle | K49: 0 | L49: 0 | M49: =+L49/E49 -> 0 | O49: 951 | P49: 1.0680823e+08 | Q49: 951 | R49: 1.0680823e+08 | S49: =O49-K49-Q49 -> 0 | T49: =P49-L49-R49 -> 0 | U49: Clearing ok
A50: FG | B50: 100838 | C50: PK Qualcomm CPE Olympic 50-17810-1 Cover Radome, Spherical V1 | D50: 90 | E50: 10017155 | F50: =+E50/D50 -> 111301.72 | H50: Good | I50: No provision to be made, as item will be recycle to New Ingot in Year 2025 | J50: Recycle | M50: =+L50/E50 -> 0 | O50: 90 | P50: 10017155 | Q50: 90 | R50: 10017155 | S50: =O50-K50-Q50 -> 0 | T50: =P50-L50-R50 -> 0 | U50: Clearing ok
A51: FG | B51: 100974 | C51: PK Qualcom MTP Waipo 55-33711-1 Front Carrier 6.8 Display | D51: 168 | E51: 18308287 | F51: =+E51/D51 -> 108977.9 | H51: Good | I51: No provision to be made, as item will be recycle to New Ingot in Year 2025 | J51: Recycle | K51: 0 | L51: 0 | M51: =+L51/E51 -> 0 | O51: 229 | P51: 24955939 | Q51: 229 | R51: 24955939 | S51: =O51-K51-Q51 -> 0 | T51: =P51-L51-R51 -> 0 | U51: Clearing ok
A52: FG | B52: 120365 | C52: PK Hosiden HEG Upper Housing HGU0810-26PW(2) | D52: 3884 | E52: 4.0982855e+08 | F52: =+E52/D52 -> 105517.14 | H52: Good | I52: No provision to be made, as item will be recycle to New Ingot in Year 2025 | J52: Recycle | K52: 0 | L52: 0 | M52: =+L52/E52 -> 0 | O52: 145207 | P52: 1.5321827e+10 | Q52: 145207 | R52: 1.5321827e+10 | S52: =O52-K52-Q52 -> 0 | T52: =P52-L52-R52 -> 0 | U52: Clearing ok
A53: FG | B53: 120208 | C53: PK Hanwha FC15-002206B- Cover Bottom | D53: 766 | E53: 79685902 | F53: =+E53/D53 -> 104028.59 | H53: Obsolete | I53: Item Unable to do in-house recycle due to special painting on product, Item will be included in Scrap Sales Plan in Year 2025 | J53: Full Provision | K53: 766 | L53: 79685902 | M53: =+L53/E53 -> 1 | O53: 766 | P53: 79685902 | Q53: 0 | R53: 0 | S53: =O53-K53-Q53 -> 0 | T53: =P53-L53-R53 -> 0 | U53: Make provision 2024
A54: FG | B54: 100599 | C54: PK Qualcomm 55-PG160-3 | D54: 23 | E54: 2363434.7 | F54: =+E54/D54 -> 102758.03 | H54: Good | I54: No provision to be made, as item will be recycle to New Ingot in Year 2025 | J54: Recycle | M54: =+L54/E54 -> 0 | O54: 23 | P54: 2363434.7 | Q54: 23 | R54: 2363434.7 | S54: =O54-K54-Q54 -> 0 | T54: =P54-L54-R54 -> 0 | U54: Clearing ok
A55: FG | B55: 101059 | C55: PK Qualcomm MTP Kuno 50-PR952-3, Ant Carrier, Antenna 8 And 9 | D55: 148 | E55: 14991247 | F55: =+E55/D55 -> 101292.21 | H55: Good | I55: No provision to be made, as item will be recycle to New Ingot in Year 2025 | J55: Recycle | K55: 0 | L55: 0 | M55: =+L55/E55 -> 0 | O55: 148 | P55: 14991247 | Q55: 148 | R55: 14991247 | S55: =O55-K55-Q55 -> 0 | T55: =P55-L55-R55 -> 0 | U55: Produce again 2025
A56: FG | B56: 150550 | C56: PK ZN0004 | D56: 300 | E56: 30149107 | F56: =+E56/D56 -> 100497.02 | H56: Good | I56: BU Discontinued - [1] | J56: Full Provision | K56: =+D56 -> 300 | L56: =+E56 -> 30149107 | M56: =+L56/E56 -> 1 | O56: 300 | P56: 30149107 | Q56: 0 | R56: 0 | S56: =O56-K56-Q56 -> 0 | T56: =P56-L56-R56 -> 0 | U56: Make provision 2024
A57: FG | B57: 100305 | C57: PK HM72 | D57: 394 | E57: 37581692 | F57: =+E57/D57 -> 95385.004 | H57: Good | I57: No provision to be made, as item will be recycle to New Ingot in Year 2025 | J57: Recycle | K57: 0 | L57: 0 | M57: =+L57/E57 -> 0 | O57: 394 | P57: 37581692 | Q57: 394 | R57: 37581692 | S57: =O57-K57-Q57 -> 0 | T57: =P57-L57-R57 -> 0 | U57: Clearing ok
A58: FG | B58: 101112 | C58: PK Qualcomm MTP Pinnacles 55-28899-2 Carrier Frame Assy | D58: 9 | E58: 856428.77 | F58: =+E58/D58 -> 95158.753 | H58: Good | I58: No provision to be made, as item will be recycle to New Ingot in Year 2025 | J58: Recycle | M58: =+L58/E58 -> 0 | O58: 9 | P58: 856428.77 | Q58: 9 | R58: 856428.77 | S58: =O58-K58-Q58 -> 0 | T58: =P58-L58-R58 -> 0 | U58: Sale again 2025
A59: FG | B59: 120300 | C59: PK LGIT 1V5 1826 3CAC00309A Housing | D59: 720 | E59: 65070885 | F59: =+E59/D59 -> 90376.229 | H59: Good | I59: No provision to be made, as item will be recycle to New Ingot in Year 2025 | J59: Recycle | K59: 0 | L59: 0 | M59: =+L59/E59 -> 0 | O59: 928 | P59: 83869140 | Q59: 928 | R59: 83869140 | S59: =O59-K59-Q59 -> 0 | T59: =P59-L59-R59 -> 0 | U59: Clearing ok
A60: FG | B60: 101131 | C60: PK Qualcomm CPE Pinnacles 55-36814-2 Grounding Frame | D60: 277 | E60: 24415877 | F60: =+E60/D60 -> 88143.959 | H60: Good | I60: No provision to be made, as item will be recycle to New Ingot in Year 2025 | J60: Recycle | K60: 0 | L60: 0 | M60: =+L60/E60 -> 0 | O60: 277 | P60: 24415877 | Q60: 277 | R60: 24415877 | S60: =O60-K60-Q60 -> 0 | T60: =P60-L60-R60 -> 0 | U60: Produce again 2025
A61: FG | B61: 101142 | C61: PK Qualcomm MTP Camano 55-PR919-30 Display Carrier Frame Assy | D61: 53 | E61: 4639796.8 | F61: =+E61/D61 -> 87543.337 | H61: Good | I61: No provision to be made, as item will be recycle to New Ingot in Year 2025 | J61: Recycle | K61: 0 | L61: 0 | M61: =+L61/E61 -> 0 | O61: 53 | P61: 4639796.8 | Q61: 53 | R61: 4639796.8 | S61: =O61-K61-Q61 -> 0 | T61: =P61-L61-R61 -> 0 | U61: Produce again 2025
A62: FG | B62: 100955 | C62: PK Qualcomm MTP Kailua 55-PV452-5 Mid Frame Heatsink | D62: 145 | E62: 12429630 | F62: =+E62/D62 -> 85721.588 | H62: Good | I62: No provision to be made, as item will be recycle to New Ingot in Year 2025 | J62: Recycle | M62: =+L62/E62 -> 0 | O62: 145 | P62: 12429630 | Q62: 145 | R62: 12429630 | S62: =O62-K62-Q62 -> 0 | T62: =P62-L62-R62 -> 0 | U62: Sale again 2025
A63: FG | B63: 101167 | C63: PK Qualcomm MTP PAKALA 55-58484-1 FRONT HOUSING | D63: 190 | E63: 16020514 | F63: =+E63/D63 -> 84318.493 | H63: Good | I63: No provision to be made, as item will be recycle to New Ingot in Year 2025 | J63: Recycle | K63: 0 | L63: 0 | M63: =+L63/E63 -> 0 | O63: 190 | P63: 16020514 | Q63: 0 | R63: 0 | S63: =O63-K63-Q63 -> 190 | T63: =P63-L63-R63 -> 16020514 | U63: Will sale again
A64: FG | B64: 101163 | C64: PK Qualcomm QCP Hamoa 55-34673-3 Housing, Front Assy | D64: 10 | E64: 841727.52 | F64: =+E64/D64 -> 84172.752 | H64: Good | I64: No provision to be made, as item will be recycle to New Ingot in Year 2025 | J64: Recycle | M64: =+L64/E64 -> 0 | O64: 10 | P64: 841727.52 | Q64: 0 | R64: 0 | S64: =O64-K64-Q64 -> 10 | T64: =P64-L64-R64 -> 841727.52 | U64: Will sale again
A65: FG | B65: 100260 | C65: AS CP15 DCT038 | D65: 253 | E65: 21150581 | F65: =+E65/D65 -> 83599.133 | H65: Good | I65: BU Discontinued - [1] | J65: Full Provision | K65: =D65 -> 253 | L65: =E65 -> 21150581 | M65: =+L65/E65 -> 1 | O65: 253 | P65: 21150581 | Q65: 0 | R65: 0 | S65: =O65-K65-Q65 -> 0 | T65: =P65-L65-R65 -> 0 | U65: Make provision 2024
A66: FG | B66: 150563 | C66: PK ZN0021 | D66: 380 | E66: 30527348 | F66: =+E66/D66 -> 80335.126 | H66: Good | I66: BU Discontinued - [1] | J66: Full Provision | K66: =+D66 -> 380 | L66: =+E66 -> 30527348 | M66: =+L66/E66 -> 1 | O66: 380 | P66: 30527348 | Q66: 0 | R66: 0 | S66: =O66-K66-Q66 -> 0 | T66: =P66-L66-R66 -> 0 | U66: Make provision 2024
A67: FG | B67: 100580 | C67: PK Qualcomm MTP Kona 55-PG165-1 Ant Carrier 1 | D67: 110 | E67: 8708460.4 | F67: =+E67/D67 -> 79167.822 | H67: Good | I67: No provision to be made, as item will be recycle to New Ingot in Year 2025 | J67: Recycle | K67: 0 | L67: 0 | M67: =+L67/E67 -> 0 | O67: 110 | P67: 8708460.4 | Q67: 110 | R67: 8708460.4 | S67: =O67-K67-Q67 -> 0 | T67: =P67-L67-R67 -> 0 | U67: Clearing ok
A68: FG | B68: 100304 | C68: PK GM-D1004 | D68: 573 | E68: 44929400 | F68: =+E68/D68 -> 78410.821 | H68: Good | I68: No provision to be made, as item will be recycle to New Ingot in Year 2025 | J68: Recycle | K68: 0 | L68: 0 | M68: =+L68/E68 -> 0 | O68: 573 | P68: 44929400 | Q68: 573 | R68: 44929400 | S68: =O68-K68-Q68 -> 0 | T68: =P68-L68-R68 -> 0 | U68: Clearing ok
A69: FG | B69: 120006 | C69: PK 925#29 | D69: 270 | E69: 20760672 | F69: =+E69/D69 -> 76891.379 | H69: Good | I69: No provision to be made, as item will be recycle to New Ingot in Year 2025 | J69: Recycle | K69: 0 | L69: 0 | M69: =+L69/E69 -> 0 | O69: 270 | P69: 20760672 | Q69: 270 | R69: 20760672 | S69: =O69-K69-Q69 -> 0 | T69: =P69-L69-R69 -> 0 | U69: Clearing ok
A70: FG | B70: 100336 | C70: AS CP15DCT073-A( prinlogo) | D70: 137 | E70: 10290623 | F70: =+E70/D70 -> 75114.039 | H70: Good | I70: BU Discontinued - [1] | J70: Full Provision | K70: =D70 -> 137 | L70: =E70 -> 10290623 | M70: =+L70/E70 -> 1 | O70: 137 | P70: 10290623 | Q70: 0 | R70: 0 | S70: =O70-K70-Q70 -> 0 | T70: =P70-L70-R70 -> 0 | U70: Make provision 2024
A71: FG | B71: 120008 | C71: PK 900#86(F) | D71: 6628 | E71: 4.9688347e+08 | F71: =+E71/D71 -> 74967.331 | H71: Good | I71: No provision to be made, as item will be recycle to New Ingot in Year 2025 | J71: Recycle | K71: 0 | L71: 0 | M71: =+L71/E71 -> 0 | O71: 6628 | P71: 4.9688347e+08 | Q71: 6628 | R71: 4.9688347e+08 | S71: =O71-K71-Q71 -> 0 | T71: =P71-L71-R71 -> 0 | U71: Clearing ok
A72: FG | B72: 101054 | C72: PK Qualcomm MTP Pinnacles 50-28768-1 Frame Wlan Area, Multipurpose | D72: 59 | E72: 4395348.4 | F72: =+E72/D72 -> 74497.43 | H72: Good | I72: No provision to be made, as item will be recycle to New Ingot in Year 2025 | J72: Recycle | M72: =+L72/E72 -> 0 | O72: 59 | P72: 4395348.4 | Q72: 59 | R72: 4395348.4 | S72: =O72-K72-Q72 -> 0 | T72: =P72-L72-R72 -> 0 | U72: Clearing ok
A73: FG | B73: 100321 | C73: AS DCT 020 | D73: 192 | E73: 14186539 | F73: =+E73/D73 -> 73888.225 | H73: Good | I73: No provision to be made, as item will be recycle to New Ingot in Year 2025 | J73: Recycle | K73: 0 | L73: 0 | M73: =+L73/E73 -> 0 | O73: 192 | P73: 14186539 | Q73: 192 | R73: 14186539 | S73: =O73-K73-Q73 -> 0 | T73: =P73-L73-R73 -> 0 | U73: Clearing ok
A74: FG | B74: 100291 | C74: AS DCT075 ( Logo) | D74: 1632 | E74: 1.1688431e+08 | F74: =+E74/D74 -> 71620.291 | H74: Good | I74: No provision to be made, as item will be recycle to New Ingot in Year 2025 | J74: Recycle | K74: 0 | L74: 0 | M74: =+L74/E74 -> 0 | O74: 1632 | P74: 1.1688431e+08 | Q74: 1632 | R74: 1.1688431e+08 | S74: =O74-K74-Q74 -> 0 | T74: =P74-L74-R74 -> 0 | U74: Clearing ok
A75: FG | B75: 120371 | C75: PK ZF IPM 2.0 Housing Advance A014A907/A014A881 | D75: 582 | E75: 41326000 | F75: =+E75/D75 -> 71006.872 | H75: Good | I75: No provision to be made, as item will be recycle to New Ingot in Year 2025 | J75: Recycle | K75: 0 | L75: 0 | M75: =+L75/E75 -> 0 | O75: 840 | P75: 59645773 | Q75: 0 | R75: 0 | S75: =O75-K75-Q75 -> 840 | T75: =P75-L75-R75 -> 59645773 | U75: Will sale again
A76: FG | B76: 100855 | C76: PK Qualcomm MTP Lahaina 50-PP493-1 Speaker Box | D76: 300 | E76: 20762761 | F76: =+E76/D76 -> 69209.204 | H76: Good | I76: No provision to be made, as item will be recycle to New Ingot in Year 2025 | J76: Recycle | M76: =+L76/E76 -> 0 | O76: 1711 | P76: 1.1841695e+08 | Q76: 1711 | R76: 1.1841695e+08 | S76: =O76-K76-Q76 -> 0 | T76: =P76-L76-R76 -> 0 | U76: Produce again 2025
A77: FG | B77: 150558 | C77: PK ZN0012 | D77: 1307 | E77: 88994293 | F77: =+E77/D77 -> 68090.507 | H77: Good | I77: BU Discontinued - [1] | J77: Full Provision | K77: =+D77 -> 1307 | L77: =+E77 -> 88994293 | M77: =+L77/E77 -> 1 | O77: 1307 | P77: 88994293 | Q77: 0 | R77: 0 | S77: =O77-K77-Q77 -> 0 | T77: =P77-L77-R77 -> 0 | U77: Make provision 2024
A78: FG | B78: 101191 | C78: PK Qualcomm MTP Sariska 55-29708-60 MIDFRAME, HEATSINK ASSY_PROCESS (NO HIEAT PIPE) | D78: 1790 | E78: 1.2142312e+08 | F78: =+E78/D78 -> 67834.144 | H78: Good | I78: No provision to be made, as item will be recycle to New Ingot in Year 2025 | J78: Recycle | M78: =+L78/E78 -> 0 | O78: 1790 | P78: 1.2142312e+08 | Q78: 2 | R78: 135668.29 | S78: =O78-K78-Q78 -> 1788 | T78: =P78-L78-R78 -> 1.2128745e+08 | U78: Will sale again
A79: FG | B79: 120224 | C79: PK Hanwha FC15-005434A- Cover Cabel Hole | D79: 384 | E79: 26000022 | F79: =+E79/D79 -> 67708.39 | H79: Obsolete | I79: Item Unable to do in-house recycle due to special painting on product, Item will be included in Scrap Sales Plan in Year 2025 | J79: Full Provision | K79: 384 | L79: 26000022 | M79: =+L79/E79 -> 1 | O79: 384 | P79: 26000022 | Q79: 0 | R79: 0 | S79: =O79-K79-Q79 -> 0 | T79: =P79-L79-R79 -> 0 | U79: Make provision 2024
A80: FG | B80: 101179 | C80: PK Qualcomm MTP PINNACLES CA90-28768-2 FRAME, WLAN AREA, MULTIPURPOSE | D80: 154 | E80: 10257440 | F80: =+E80/D80 -> 66606.756 | H80: Good | I80: No provision to be made, as item will be recycle to New Ingot in Year 2025 | J80: Recycle | K80: 0 | L80: 0 | M80: =+L80/E80 -> 0 | O80: 154 | P80: 10257440 | Q80: 0 | R80: 0 | S80: =O80-K80-Q80 -> 154 | T80: =P80-L80-R80 -> 10257440 | U80: Will sale again
A81: FG | B81: 100267 | C81: AS DCT068 | D81: 1316 | E81: 87430508 | F81: =+E81/D81 -> 66436.556 | H81: Good | I81: No provision to be made, as item will be recycle to New Ingot in Year 2025 | J81: Recycle | K81: 0 | L81: 0 | M81: =+L81/E81 -> 0 | O81: 1316 | P81: 87430508 | Q81: 1316 | R81: 87430508 | S81: =O81-K81-Q81 -> 0 | T81: =P81-L81-R81 -> 0 | U81: Clearing ok
A82: FG | B82: 120156 | C82: PK SM-A507F | D82: 3445 | E82: 2.2862887e+08 | F82: =+E82/D82 -> 66365.419 | H82: Good | I82: No provision to be made, as item will be recycle to New Ingot in Year 2025 | J82: Recycle | K82: 0 | L82: 0 | M82: =+L82/E82 -> 0 | O82: 3445 | P82: 2.2862887e+08 | Q82: 3445 | R82: 2.2862887e+08 | S82: =O82-K82-Q82 -> 0 | T82: =P82-L82-R82 -> 0 | U82: Clearing ok
A83: FG | B83: 100882 | C83: PK Qualcomm IPD Cedros 50-PR952-1 Ant Carrier8-9 | D83: 138 | E83: 9059960 | F83: =+E83/D83 -> 65651.884 | H83: Good | I83: No provision to be made, as item will be recycle to New Ingot in Year 2025 | J83: Recycle | K83: 0 | L83: 0 | M83: =+L83/E83 -> 0 | O83: 138 | P83: 9059960 | Q83: 138 | R83: 9059960 | S83: =O83-K83-Q83 -> 0 | T83: =P83-L83-R83 -> 0 | U83: Clearing ok
A84: FG | B84: 120002 | C84: PK 920#30 | D84: 90049 | E84: 5.7877014e+09 | F84: =+E84/D84 -> 64272.8 | H84: Good | I84: No provision to be made, as item will be recycle to New Ingot in Year 2025 | J84: Recycle | K84: 0 | L84: 0 | M84: =+L84/E84 -> 0 | O84: 90049 | P84: 5.7877014e+09 | Q84: 90049 | R84: 5.7877014e+09 | S84: =O84-K84-Q84 -> 0 | T84: =P84-L84-R84 -> 0 | U84: Clearing ok
A85: FG | B85: 101090 | C85: PK Qualcomm CPE Pinnacles 50-40109-1 Omni Antenna, Carrier | D85: 80 | E85: 4960244.3 | F85: =+E85/D85 -> 62003.054 | H85: Good | I85: No provision to be made, as item will be recycle to New Ingot in Year 2025 | J85: Recycle | M85: =+L85/E85 -> 0 | O85: 80 | P85: 4960244.3 | Q85: 80 | R85: 4960244.3 | S85: =O85-K85-Q85 -> 0 | T85: =P85-L85-R85 -> 0 | U85: Clearing ok
A86: FG | B86: 100611 | C86: PK Qualcomm MTP Kona 55-PG162-2 Rear housing | D86: 70 | E86: 4338698.4 | F86: =+E86/D86 -> 61981.405 | H86: Good | I86: No provision to be made, as item will be recycle to New Ingot in Year 2025 | J86: Recycle | M86: =+L86/E86 -> 0 | O86: 70 | P86: 4338698.4 | Q86: 70 | R86: 4338698.4 | S86: =O86-K86-Q86 -> 0 | T86: =P86-L86-R86 -> 0 | U86: Clearing ok
A87: FG | B87: 101195 | C87: PK Qualcomm MTP IDPS MILOS CA90-58183-1 FRAME, WLAN AREA, MULTIPURPOSE (2) | D87: 154 | E87: 9382010.3 | F87: =+E87/D87 -> 60922.145 | H87: Good | I87: No provision to be made, as item will be recycle to New Ingot in Year 2025 | J87: Recycle | K87: 0 | L87: 0 | M87: =+L87/E87 -> 0 | O87: 154 | P87: 9382010.3 | Q87: 0 | R87: 0 | S87: =O87-K87-Q87 -> 154 | T87: =P87-L87-R87 -> 9382010.3 | U87: Will sale again
A88: FG | B88: 120203 | C88: PK Hanwha FC15-002791A- Cover Bottom | D88: 910 | E88: 54211405 | F88: =+E88/D88 -> 59572.973 | H88: Obsolete | I88: Item Unable to do in-house recycle due to special painting on product, Item will be included in Scrap Sales Plan in Year 2025 | J88: Full Provision | K88: 910 | L88: 54211405 | M88: =+L88/E88 -> 1 | O88: 910 | P88: 54211405 | Q88: 0 | R88: 0 | S88: =O88-K88-Q88 -> 0 | T88: =P88-L88-R88 -> 0 | U88: Make provision 2024
A89: FG | B89: 100452 | C89: PK Qualcomm front housing MTP SDX24 55-PB922 | D89: 832 | E89: 48471429 | F89: =+E89/D89 -> 58258.929 | H89: Good | I89: No provision to be made, as item will be recycle to New Ingot in Year 2025 | J89: Recycle | K89: 0 | L89: 0 | M89: =+L89/E89 -> 0 | O89: 2294 | P89: 1.3364598e+08 | Q89: 2294 | R89: 1.3364598e+08 | S89: =O89-K89-Q89 -> 0 | T89: =P89-L89-R89 -> 0 | U89: Clearing ok
A90: FG | B90: 100367 | C90: Qual comm QRD845- Simtray | D90: 262 | E90: 15191502 | F90: =+E90/D90 -> 57982.832 | H90: Good | I90: No provision to be made, as item will be recycle to New Ingot in Year 2025 | J90: Recycle | K90: 0 | L90: 0 | M90: =+L90/E90 -> 0 | O90: 262 | P90: 15191502 | Q90: 262 | R90: 15191502 | S90: =O90-K90-Q90 -> 0 | T90: =P90-L90-R90 -> 0 | U90: Clearing ok
A91: FG | B91: 150547 | C91: PK ZN0001 | D91: 500 | E91: 28927907 | F91: =+E91/D91 -> 57855.814 | H91: Good | I91: BU Discontinued - [1] | J91: Full Provision | K91: =+D91 -> 500 | L91: =+E91 -> 28927907 | M91: =+L91/E91 -> 1 | O91: 500 | P91: 28927907 | Q91: 0 | R91: 0 | S91: =O91-K91-Q91 -> 0 | T91: =P91-L91-R91 -> 0 | U91: Make provision 2024
A92: FG | B92: 100790 | C92: PK Qualcom MTP Makena 55-PV167-1 Frount Housing Assy | D92: 8 | E92: 456506.23 | F92: =+E92/D92 -> 57063.279 | H92: Damage | I92: Item Damage and unable to recycle | J92: Full Provision | K92: 8 | L92: 456506.23 | M92: =+L92/E92 -> 1 | O92: 8 | P92: 456506.23 | Q92: 0 | R92: 0 | S92: =O92-K92-Q92 -> 0 | T92: =P92-L92-R92 -> 0 | U92: Make provision 2024
A93: FG | B93: 100158 | C93: AS 530H#31-3 | D93: 571 | E93: 32541562 | F93: =+E93/D93 -> 56990.477 | H93: Good | I93: No provision to be made, as item will be recycle to New Ingot in Year 2025 | J93: Recycle | K93: 0 | L93: 0 | M93: =+L93/E93 -> 0 | O93: 571 | P93: 32541562 | Q93: 571 | R93: 32541562 | S93: =O93-K93-Q93 -> 0 | T93: =P93-L93-R93 -> 0 | U93: Clearing ok
A94: FG | B94: 101134 | C94: PK Qualcomm MTP CAMANO 55-PR954-90 Assy, Sub Assy Rear Housing | D94: 85 | E94: 4840303.1 | F94: =+E94/D94 -> 56944.742 | H94: Good | I94: No provision to be made, as item will be recycle to New Ingot in Year 2025 | J94: Recycle | K94: 0 | L94: 0 | M94: =+L94/E94 -> 0 | O94: 85 | P94: 4840303.1 | Q94: 85 | R94: 4840303.1 | S94: =O94-K94-Q94 -> 0 | T94: =P94-L94-R94 -> 0 | U94: Produce again 2025
A95: FG | B95: 120310 | C95: PK LGIT 1V5 3CAC00312A/3MAZ01180A Bearing Plate Premium(2) | D95: 15589 | E95: 8.8585609e+08 | F95: =+E95/D95 -> 56825.716 | H95: Good | I95: No provision to be made, as item will be recycle to New Ingot in Year 2025 | J95: Recycle | K95: 0 | L95: 0 | M95: =+L95/E95 -> 0 | O95: 15589 | P95: 8.8585609e+08 | Q95: 15589 | R95: 8.8585609e+08 | S95: =O95-K95-Q95 -> 0 | T95: =P95-L95-R95 -> 0 | U95: Clearing ok
A96: FG | B96: 120377 | C96: PK Mando SV2 Housing ME210SV500 | D96: 72 | E96: 4036484 | F96: =+E96/D96 -> 56062.278 | H96: Good | I96: No provision to be made, as item will be recycle to New Ingot in Year 2025 | J96: Recycle | K96: 0 | L96: 0 | M96: =+L96/E96 -> 0 | O96: 1240 | P96: 69517225 | Q96: 1240 | R96: 69517225 | S96: =O96-K96-Q96 -> 0 | T96: =P96-L96-R96 -> 0 | U96: Clearing ok
A97: FG | B97: 120211 | C97: PK Hanwha FC29-008329A- Case Bottom | D97: 14 | E97: 784809.46 | F97: =+E97/D97 -> 56057.819 | H97: Obsolete | I97: Item Unable to do in-house recycle due to special painting on product, Item will be included in Scrap Sales Plan in Year 2025 | J97: Full Provision | K97: 14 | L97: 784809.46 | M97: =+L97/E97 -> 1 | O97: 14 | P97: 784809.46 | Q97: 0 | R97: 0 | S97: =O97-K97-Q97 -> 0 | T97: =P97-L97-R97 -> 0 | U97: Make provision 2024
A98: FG | B98: 101194 | C98: PK Qualcomm MTP IDPS MILOS 55-PR954-100 FRONT HOUSING (2) | D98: 53 | E98: 2920094.5 | F98: =+E98/D98 -> 55096.123 | H98: Good | I98: No provision to be made, as item will be recycle to New Ingot in Year 2025 | J98: Recycle | K98: 0 | L98: 0 | M98: =+L98/E98 -> 0 | O98: 53 | P98: 2920094.5 | Q98: 53 | R98: 2920094.5 | S98: =O98-K98-Q98 -> 0 | T98: =P98-L98-R98 -> 0 | U98: Sale again 2025
A99: FG | B99: 120014 | C99: PK A5#15(B) | D99: 22346 | E99: 1.2038957e+09 | F99: =+E99/D99 -> 53875.222 | H99: Good | I99: No provision to be made, as item will be recycle to New Ingot in Year 2025 | J99: Recycle | K99: 0 | L99: 0 | M99: =+L99/E99 -> 0 | O99: 22346 | P99: 1.2038957e+09 | Q99: 22346 | R99: 1.2038957e+09 | S99: =O99-K99-Q99 -> 0 | T99: =P99-L99-R99 -> 0 | U99: Clearing ok
A100: FG | B100: 120210 | C100: PK Hanwha FC29-003420A- Cap Bolt | D100: 1380 | E100: 72916735 | F100: =+E100/D100 -> 52838.214 | H100: Obsolete | I100: Item Unable to do in-house recycle due to special painting on product, Item will be included in Scrap Sales Plan in Year 2025 | J100: Full Provision | K100: 1380 | L100: 72916735 | M100: =+L100/E100 -> 1 | O100: 1380 | P100: 72916735 | Q100: 0 | R100: 0 | S100: =O100-K100-Q100 -> 0 | T100: =P100-L100-R100 -> 0 | U100: Make provision 2024
...
